Workbook
Name AnnualManagementFee: 'Operating Expense Budget'!$B$15
Name AssumedOperatingExpenseRatio: 'Operating Expense Budget'!$B$5
Name CalculatedOperatingExpenseRatio: 'Operating Expense Budget'!$B$6
Name ClassACapital: Assumptions!$B$39
Name ClassAPreferredReturn: Assumptions!$B$40
Name ClassAResidualShare: Assumptions!$B$44
Name ClassBCapital: Assumptions!$B$41
Name ClassBResidualShare: Assumptions!$B$45
Name ClassBReturnPriority: Assumptions!$B$42
Name CoLivingSuiteRent: Assumptions!$B$11
Name CoLivingSuiteRentHigh: Assumptions!$G$10
Name CoLivingSuiteRentLow: Assumptions!$E$10
Name CoLivingSuiteRentMedium: Assumptions!$F$10
Name CoLivingSuites: Assumptions!$B$10
Name ExistingDebtServiceAnnual: Assumptions!$B$28
Name ExistingFirstMortgage: Assumptions!$B$20
Name ExistingFirstMortgageAnnualPayment: Assumptions!$B$26
Name ExistingFirstMortgageMonthlyPI: Assumptions!$B$25
Name ExistingFirstMortgagePrincipal: Assumptions!$B$20
Name ExistingFirstMortgageRate: Assumptions!$B$21
Name ExitCapRate: Assumptions!$B$35
Name LeaseUpOccupancy: Assumptions!$B$14
Name ManagementFeeRate: 'Operating Expense Budget'!$D$15
Name NOIGrowth: Assumptions!$B$16
Name OperatingExpenseRatio: Assumptions!$B$15
Name OtherMonthlyIncome: Assumptions!$B$12
Name PermanentLoanAmortizationYears: Assumptions!$B$34
Name PermanentLoanAmount: Assumptions!$B$30
Name PermanentLoanRate: Assumptions!$B$33
Name PremiumSuiteRent: Assumptions!$B$9
Name PremiumSuiteRentHigh: Assumptions!$G$9
Name PremiumSuiteRentLow: Assumptions!$E$9
Name PremiumSuiteRentMedium: Assumptions!$F$9
Name PremiumSuites: Assumptions!$B$8
Name PrivateDebtAnnualInterestPayment: Assumptions!$B$27
Name PrivateDebtInterestRate: Assumptions!$B$23
Name PrivateDebtPrincipal: Assumptions!$B$22
Name ProjectDebtPayoffAtRefi: Assumptions!$B$24
Name RefinanceLoanAmortizationYears: Assumptions!$B$34
Name RefinanceLoanAmount: Assumptions!$B$30
Name RefinanceLoanRate: Assumptions!$B$33
Name RefinanceLoanToValueCap: Assumptions!$B$29
Name RefinanceProceedsAfterDebtAndClassA: Assumptions!$B$32
Name RefinanceProceedsAfterExistingDebt: Assumptions!$B$31
Name RentScenarioAverageMonthlyGross: Assumptions!$H$11
Name RentScenarioHighEffectiveYear: Assumptions!$G$12
Name RentScenarioHighMonthlyGross: Assumptions!$G$11
Name RentScenarioLowEffectiveYear: Assumptions!$E$12
Name RentScenarioLowMonthlyGross: Assumptions!$E$11
Name RentScenarioMediumEffectiveYear: Assumptions!$F$12
Name RentScenarioMediumMonthlyGross: Assumptions!$F$11
Name SaleExitYear: Assumptions!$B$5
Name SelectedCostCase: 'Cost Analysis'!$E$8
Name SelectedCostCaseId: 'Cost Analysis'!$D$11
Name SelectedOperatingExpenseRatio: 'Operating Expense Budget'!$B$7
Name SelectedProjectCost: 'Cost Analysis'!$G$10
Name SelectedProjectCostHigh: 'Cost Analysis'!$C$10
Name SelectedProjectCostLow: 'Cost Analysis'!$B$10
Name SelectedScenario: 'Cost Analysis'!$C$6
Name SelectedScenarioId: 'Cost Analysis'!$D$12

Sheet Assumptions
A1: 3325 Banks Rd - Investor Return Model | C1: Editable inputs are in column B. Outputs update through formulas.
A3: Project Timing
A4: Stabilization / Refinance Year | B4: 2 | C4: Year when refinance proceeds are modeled
A5: Sale / Exit Year | B5: 10 | C5: Model uses annual periods 0 through this year
A7: Rental Program | D7: Rent Scenario Schedule
A8: First Floor Premium Suites | B8: 4 | C8: Private bed/bath/kitchenette suites | D8: Rent Input | E8: Low | F8: Medium | G8: High | H8: Average | I8: Current Use | J8: Notes
A9: Monthly Rent per Premium Suite | B9: 1600 | C9: Mid/base reference; Annual Model uses scenario schedule at right | D9: Premium Suite Rent | E9: 1350 | F9: 1600 | G9: 1750 | H9: =AVERAGE(E9:G9) -> 1566.6667 | I9: Rent levels increase left to right
A10: Second Floor Co-Living Suites | B10: 4 | C10: Private bed/bath with shared amenities | D10: Co-Living Suite Rent | E10: 850 | F10: 1100 | G10: 1250 | H10: =AVERAGE(E10:G10) -> 1066.6667 | I10: Rent levels increase left to right
A11: Monthly Rent per Co-Living Suite | B11: 1100 | C11: Mid/base reference; Annual Model uses scenario schedule at right | D11: Monthly Gross Rent | E11: =PremiumSuites*E9+CoLivingSuites*E10+OtherMonthlyIncome -> 8800 | F11: =PremiumSuites*F9+CoLivingSuites*F10+OtherMonthlyIncome -> 10800 | G11: =PremiumSuites*G9+CoLivingSuites*G10+OtherMonthlyIncome -> 12000 | H11: =AVERAGE(E11:G11) -> 10533.333 | I11: Average feeds stabilized monthly rent
A12: Other Monthly Income | B12: 0 | C12: Parking, utility fees, laundry, etc. | D12: Effective Year | E12: 1 | F12: 2 | G12: 3 | I12: Annual Model timing | J12: Low ends after Year 1 under current schedule
A13: Stabilized Occupancy | B13: 0.93 | C13: Before operating expense load
A14: Year 1 Lease-Up Occupancy | B14: 0.5 | C14: First partial operating year
A15: Selected Operating Expense Ratio | B15: =SelectedOperatingExpenseRatio -> 0.4 | C15: From Operating Expense Budget tab; toggle between assumed ratio and calculated budget ratio
A16: NOI Growth | B16: 0.03 | C16: Annual growth after stabilization
A17: Stabilized Monthly Gross Rent | B17: =RentScenarioAverageMonthlyGross -> 10533.333 | C17: Average of low, medium, and high rent scenarios
A19: Debt / Refinance / Exit
A20: Existing First Mortgage Principal | B20: 119000 | C20: Existing first mortgage principal to be paid from refinance proceeds
A21: Existing First Mortgage Rate | B21: 0.0325 | C21: Interest rate on existing first mortgage
A22: Private Debt Principal | B22: 75000 | C22: Private debt principal; interest-only before payoff
A23: Private Debt Interest Rate | B23: 0.1 | C23: Interest-only private debt rate
A24: Total Existing Debt Payoff | B24: =_xlfn.SINGLE(ExistingFirstMortgagePrincipal)+PrivateDebtPrincipal -> 194000 | C24: Existing first mortgage principal plus private debt principal
A25: First Mortgage Monthly P&I Excl. Escrow | B25: 526 | C25: Actual monthly principal and interest payment; excludes escrow, taxes, and insurance
A26: First Mortgage Annual P&I Excl. Escrow | B26: =_xlfn.SINGLE(ExistingFirstMortgageMonthlyPI)*12 -> 6312 | C26: Annual principal and interest payment; excludes escrow, taxes, and insurance
A27: Private Debt Annual Interest Payment | B27: =PrivateDebtPrincipal*PrivateDebtInterestRate -> 7500 | C27: Interest-only payment on private debt
A28: Total Existing Annual Debt Service | B28: =ExistingFirstMortgageAnnualPayment+PrivateDebtAnnualInterestPayment -> 13812 | C28: Existing debt service before refinance; taxes and insurance remain in operating expenses
A29: Refinance Loan-to-Value Cap | B29: 0.7 | C29: Maximum refinance loan as % of stabilized value
A30: Refinance Loan Amount | B30: =MIN((StabilizedMonthlyGrossRent*12*StabilizedOccupancy*(1-OperatingExpenseRatio)*(1+NOIGrowth)/ExitCapRate)*RefinanceLoanToValueCap,TotalExistingDebt+ClassACapital+ClassBCapital) -> 726471.36 | C30: Only new loan; takeout/refinance proceeds, not development or construction debt
A31: Refi Proceeds After Existing Debt | B31: =MAX(0,RefinanceLoanAmount-TotalExistingDebt) -> 532471.36 | C31: Available to Class A first through waterfall
A32: Refi Remaining After Debt + Class A | B32: =MAX(0,RefinanceLoanAmount-TotalExistingDebt-ClassACapital) -> 232471.36 | C32: Indicative amount available to Class B before waterfall details
A33: Refinance Loan Interest Rate | B33: 0.065 | C33: Annual fixed rate on stabilization refinance loan
A34: Refinance Loan Amortization Years | B34: 30 | C34: Used for annual debt service after stabilization refinance
A35: Exit Cap Rate | B35: 0.07 | C35: Sale value = following year NOI / cap rate
A36: Selling Costs | B36: 0.02 | C36: Percent deducted from gross sale value
A38: Capital Stack / Waterfall
A39: Class A Capital | B39: 300000 | C39: Preferred capital raise
A40: Class A Preferred Return | B40: 0.08 | C40: Cumulative annual preferred return
A41: Class B Capital | B41: =MAX(0,SelectedProjectCost-ClassACapital) -> 597500 | C41: Subordinate beneficiary capital; dependent upon selected project cost in Cost Analysis
A42: Class B Capital Return Priority | B42: 1 | C42: 1 = return Class B capital before residual split
A43: Sponsor Residual Share | B43: 0.4 | C43: Editable sponsor share of residual after capital return priorities
A44: Class A Residual Share | B44: =(1-SponsorResidualShare)*(ClassACapital/(ClassACapital+ClassBCapital)) -> 0.2005571 | C44: Class A share of non-sponsor residual, proportional to Class A capital
A45: Class B Residual Share | B45: =(1-SponsorResidualShare)*(ClassBCapital/(ClassACapital+ClassBCapital)) -> 0.3994429 | C45: Class B share of non-sponsor residual, proportional to Class B capital
A46: Sponsor Property Payment / Basis | B46: 150000 | C46: Payment to Sponsor for property; also used as Sponsor basis for return analysis
A47: Model Note | B47: This is a planning model, not tax, legal, securities, or investment advice.

Sheet Annual Model
A1: Annual Project Model
A3: Year | B3: Phase | C3: Gross Potential Rent | D3: Effective Gross Income | E3: Operating Expenses | F3: NOI | G3: Debt Service | H3: Current Year Cash Before Refi/Sale | I3: Net Refi/Sale Proceeds | J3: Cash Available Before Distributions | K3: Waterfall Distributions | L3: Ending Cash Balance | M3: Loan Balance | N3: Property Value / Refi Value
A4: 0 | B4: Capitalization / Entitlement | C4: =IF(AnnualModelTable[[#This Row],[Year]]=0,0,IF(AnnualModelTable[[#This Row],[Year]]>=RentScenarioHighEffectiveYear,RentScenarioHighMonthlyGross*12,IF(AnnualModelTable[[#This Row],[Year]]>=RentScenarioMediumEffectiveYear,RentScenarioMediumMonthlyGross*12,IF(AnnualModelTable[[#This Row],[Year]]>=RentScenarioLowEffectiveYear,RentScenarioLowMonthlyGross*12,0)))) -> 0 | D4: =IF(A4=0,0,C4*IF(A4=1,LeaseUpOccupancy,StabilizedOccupancy)) -> 0 | E4: =D4*OperatingExpenseRatio -> 0 | F4: =D4-E4 -> 0 | G4: =IF(AND(AnnualModelTable[[#This Row],[Year]]>=1,AnnualModelTable[[#This Row],[Year]]<StabilizationRefiYear),ExistingDebtServiceAnnual,IF(AND(AnnualModelTable[[#This Row],[Year]]>=StabilizationRefiYear,AnnualModelTable[[#This Row],[Year]]<=SaleExitYear),-PMT(RefinanceLoanRate/12,RefinanceLoanAmortizationYears*12,RefinanceLoanAmount)*12,0)) -> 0 | H4: =AnnualModelTable[[#This Row],[NOI]]-AnnualModelTable[[#This Row],[Debt Service]] -> 0 | I4: =SponsorPropertyPayment -> 150000 | J4: =IF(AnnualModelTable[[#This Row],[Year]]=0,0,IFERROR(INDEX(AnnualModelTable[Ending Cash Balance],MATCH(AnnualModelTable[[#This Row],[Year]]-1,AnnualModelTable[Year],0)),0))+AnnualModelTable[[#This Row],[Current Year Cash Before Refi/Sale]]+AnnualModelTable[[#This Row],[Net Refi/Sale Proceeds]] -> 150000 | K4: =SUM(INDEX(WaterfallTable[A Total Dist],MATCH(AnnualModelTable[[#This Row],[Year]],WaterfallTable[Year],0)),INDEX(WaterfallTable[B Total Dist],MATCH(AnnualModelTable[[#This Row],[Year]],WaterfallTable[Year],0)),INDEX(WaterfallTable[Total Dist],MATCH(AnnualModelTable[[#This Row],[Year]],WaterfallTable[Year],0))) -> 150000 | L4: =MAX(0,AnnualModelTable[[#This Row],[Cash Available Before Distributions]]-AnnualModelTable[[#This Row],[Waterfall Distributions]]) -> 0 | M4: =IF(AnnualModelTable[[#This Row],[Year]]<StabilizationRefiYear,0,IF(AnnualModelTable[[#This Row],[Year]]=SaleExitYear,0,-FV(RefinanceLoanRate/12,(AnnualModelTable[[#This Row],[Year]]-StabilizationRefiYear)*12,PMT(RefinanceLoanRate/12,RefinanceLoanAmortizationYears*12,RefinanceLoanAmount),RefinanceLoanAmount))) -> 0 | N4: =IF(AnnualModelTable[[#This Row],[Year]]<StabilizationRefiYear,0,AnnualModelTable[[#This Row],[NOI]]*(1+NOIGrowth)/ExitCapRate) -> 0
A5: 1 | B5: Lease-Up | C5: =IF(AnnualModelTable[[#This Row],[Year]]=0,0,IF(AnnualModelTable[[#This Row],[Year]]>=RentScenarioHighEffectiveYear,RentScenarioHighMonthlyGross*12,IF(AnnualModelTable[[#This Row],[Year]]>=RentScenarioMediumEffectiveYear,RentScenarioMediumMonthlyGross*12,IF(AnnualModelTable[[#This Row],[Year]]>=RentScenarioLowEffectiveYear,RentScenarioLowMonthlyGross*12,0)))) -> 105600 | D5: =IF(A5=0,0,C5*IF(A5=1,LeaseUpOccupancy,StabilizedOccupancy)) -> 52800 | E5: =D5*OperatingExpenseRatio -> 21120 | F5: =D5-E5 -> 31680 | G5: =IF(AND(AnnualModelTable[[#This Row],[Year]]>=1,AnnualModelTable[[#This Row],[Year]]<StabilizationRefiYear),ExistingDebtServiceAnnual,IF(AND(AnnualModelTable[[#This Row],[Year]]>=StabilizationRefiYear,AnnualModelTable[[#This Row],[Year]]<=SaleExitYear),-PMT(RefinanceLoanRate/12,RefinanceLoanAmortizationYears*12,RefinanceLoanAmount)*12,0)) -> 13812 | H5: =AnnualModelTable[[#This Row],[NOI]]-AnnualModelTable[[#This Row],[Debt Service]] -> 17868 | I5: =IF(AnnualModelTable[[#This Row],[Year]]=StabilizationRefiYear,MAX(0,RefinanceLoanAmount-TotalExistingDebt),IF(AnnualModelTable[[#This Row],[Year]]=SaleExitYear,MAX(0,AnnualModelTable[[#This Row],[Property Value / Refi Value]]*(1-SellingCosts)-AnnualModelTable[[#This Row],[Loan Balance]]),0)) -> 0 | J5: =IF(AnnualModelTable[[#This Row],[Year]]=0,0,IFERROR(INDEX(AnnualModelTable[Ending Cash Balance],MATCH(AnnualModelTable[[#This Row],[Year]]-1,AnnualModelTable[Year],0)),0))+AnnualModelTable[[#This Row],[Current Year Cash Before Refi/Sale]]+AnnualModelTable[[#This Row],[Net Refi/Sale Proceeds]] -> 17868 | K5: =SUM(INDEX(WaterfallTable[A Total Dist],MATCH(AnnualModelTable[[#This Row],[Year]],WaterfallTable[Year],0)),INDEX(WaterfallTable[B Total Dist],MATCH(AnnualModelTable[[#This Row],[Year]],WaterfallTable[Year],0)),INDEX(WaterfallTable[Total Dist],MATCH(AnnualModelTable[[#This Row],[Year]],WaterfallTable[Year],0))) -> 17868 | L5: =MAX(0,AnnualModelTable[[#This Row],[Cash Available Before Distributions]]-AnnualModelTable[[#This Row],[Waterfall Distributions]]) -> 0 | M5: =IF(AnnualModelTable[[#This Row],[Year]]<StabilizationRefiYear,0,IF(AnnualModelTable[[#This Row],[Year]]=SaleExitYear,0,-FV(RefinanceLoanRate/12,(AnnualModelTable[[#This Row],[Year]]-StabilizationRefiYear)*12,PMT(RefinanceLoanRate/12,RefinanceLoanAmortizationYears*12,RefinanceLoanAmount),RefinanceLoanAmount))) -> 0 | N5: =IF(AnnualModelTable[[#This Row],[Year]]<StabilizationRefiYear,0,AnnualModelTable[[#This Row],[NOI]]*(1+NOIGrowth)/ExitCapRate) -> 0
A6: 2 | B6: Stabilization / Refi | C6: =IF(AnnualModelTable[[#This Row],[Year]]=0,0,IF(AnnualModelTable[[#This Row],[Year]]>=RentScenarioHighEffectiveYear,RentScenarioHighMonthlyGross*12,IF(AnnualModelTable[[#This Row],[Year]]>=RentScenarioMediumEffectiveYear,RentScenarioMediumMonthlyGross*12,IF(AnnualModelTable[[#This Row],[Year]]>=RentScenarioLowEffectiveYear,RentScenarioLowMonthlyGross*12,0)))) -> 129600 | D6: =IF(A6=0,0,C6*IF(A6=1,LeaseUpOccupancy,StabilizedOccupancy)) -> 120528 | E6: =D6*OperatingExpenseRatio -> 48211.2 | F6: =D6-E6 -> 72316.8 | G6: =IF(AND(AnnualModelTable[[#This Row],[Year]]>=1,AnnualModelTable[[#This Row],[Year]]<StabilizationRefiYear),ExistingDebtServiceAnnual,IF(AND(AnnualModelTable[[#This Row],[Year]]>=StabilizationRefiYear,AnnualModelTable[[#This Row],[Year]]<=SaleExitYear),-PMT(RefinanceLoanRate/12,RefinanceLoanAmortizationYears*12,RefinanceLoanAmount)*12,0)) -> 55101.518 | H6: =AnnualModelTable[[#This Row],[NOI]]-AnnualModelTable[[#This Row],[Debt Service]] -> 17215.282 | I6: =IF(AnnualModelTable[[#This Row],[Year]]=StabilizationRefiYear,MAX(0,RefinanceLoanAmount-TotalExistingDebt),IF(AnnualModelTable[[#This Row],[Year]]=SaleExitYear,MAX(0,AnnualModelTable[[#This Row],[Property Value / Refi Value]]*(1-SellingCosts)-AnnualModelTable[[#This Row],[Loan Balance]]),0)) -> 532471.36 | J6: =IF(AnnualModelTable[[#This Row],[Year]]=0,0,IFERROR(INDEX(AnnualModelTable[Ending Cash Balance],MATCH(AnnualModelTable[[#This Row],[Year]]-1,AnnualModelTable[Year],0)),0))+AnnualModelTable[[#This Row],[Current Year Cash Before Refi/Sale]]+AnnualModelTable[[#This Row],[Net Refi/Sale Proceeds]] -> 549686.64 | K6: =SUM(INDEX(WaterfallTable[A Total Dist],MATCH(AnnualModelTable[[#This Row],[Year]],WaterfallTable[Year],0)),INDEX(WaterfallTable[B Total Dist],MATCH(AnnualModelTable[[#This Row],[Year]],WaterfallTable[Year],0)),INDEX(WaterfallTable[Total Dist],MATCH(AnnualModelTable[[#This Row],[Year]],WaterfallTable[Year],0))) -> 549686.64 | L6: =MAX(0,AnnualModelTable[[#This Row],[Cash Available Before Distributions]]-AnnualModelTable[[#This Row],[Waterfall Distributions]]) -> 0 | M6: =IF(AnnualModelTable[[#This Row],[Year]]<StabilizationRefiYear,0,IF(AnnualModelTable[[#This Row],[Year]]=SaleExitYear,0,-FV(RefinanceLoanRate/12,(AnnualModelTable[[#This Row],[Year]]-StabilizationRefiYear)*12,PMT(RefinanceLoanRate/12,RefinanceLoanAmortizationYears*12,RefinanceLoanAmount),RefinanceLoanAmount))) -> 726471.36 | N6: =IF(AnnualModelTable[[#This Row],[Year]]<StabilizationRefiYear,0,AnnualModelTable[[#This Row],[NOI]]*(1+NOIGrowth)/ExitCapRate) -> 1064090.1
A7: 3 | B7: Operations | C7: =IF(AnnualModelTable[[#This Row],[Year]]=0,0,IF(AnnualModelTable[[#This Row],[Year]]>=RentScenarioHighEffectiveYear,RentScenarioHighMonthlyGross*12,IF(AnnualModelTable[[#This Row],[Year]]>=RentScenarioMediumEffectiveYear,RentScenarioMediumMonthlyGross*12,IF(AnnualModelTable[[#This Row],[Year]]>=RentScenarioLowEffectiveYear,RentScenarioLowMonthlyGross*12,0)))) -> 144000 | D7: =IF(A7=0,0,C7*IF(A7=1,LeaseUpOccupancy,StabilizedOccupancy)) -> 133920 | E7: =D7*OperatingExpenseRatio -> 53568 | F7: =D7-E7 -> 80352 | G7: =IF(AND(AnnualModelTable[[#This Row],[Year]]>=1,AnnualModelTable[[#This Row],[Year]]<StabilizationRefiYear),ExistingDebtServiceAnnual,IF(AND(AnnualModelTable[[#This Row],[Year]]>=StabilizationRefiYear,AnnualModelTable[[#This Row],[Year]]<=SaleExitYear),-PMT(RefinanceLoanRate/12,RefinanceLoanAmortizationYears*12,RefinanceLoanAmount)*12,0)) -> 55101.518 | H7: =AnnualModelTable[[#This Row],[NOI]]-AnnualModelTable[[#This Row],[Debt Service]] -> 25250.482 | I7: =IF(AnnualModelTable[[#This Row],[Year]]=StabilizationRefiYear,MAX(0,RefinanceLoanAmount-TotalExistingDebt),IF(AnnualModelTable[[#This Row],[Year]]=SaleExitYear,MAX(0,AnnualModelTable[[#This Row],[Property Value / Refi Value]]*(1-SellingCosts)-AnnualModelTable[[#This Row],[Loan Balance]]),0)) -> 0 | J7: =IF(AnnualModelTable[[#This Row],[Year]]=0,0,IFERROR(INDEX(AnnualModelTable[Ending Cash Balance],MATCH(AnnualModelTable[[#This Row],[Year]]-1,AnnualModelTable[Year],0)),0))+AnnualModelTable[[#This Row],[Current Year Cash Before Refi/Sale]]+AnnualModelTable[[#This Row],[Net Refi/Sale Proceeds]] -> 25250.482 | K7: =SUM(INDEX(WaterfallTable[A Total Dist],MATCH(AnnualModelTable[[#This Row],[Year]],WaterfallTable[Year],0)),INDEX(WaterfallTable[B Total Dist],MATCH(AnnualModelTable[[#This Row],[Year]],WaterfallTable[Year],0)),INDEX(WaterfallTable[Total Dist],MATCH(AnnualModelTable[[#This Row],[Year]],WaterfallTable[Year],0))) -> 25250.482 | L7: =MAX(0,AnnualModelTable[[#This Row],[Cash Available Before Distributions]]-AnnualModelTable[[#This Row],[Waterfall Distributions]]) -> 0 | M7: =IF(AnnualModelTable[[#This Row],[Year]]<StabilizationRefiYear,0,IF(AnnualModelTable[[#This Row],[Year]]=SaleExitYear,0,-FV(RefinanceLoanRate/12,(AnnualModelTable[[#This Row],[Year]]-StabilizationRefiYear)*12,PMT(RefinanceLoanRate/12,RefinanceLoanAmortizationYears*12,RefinanceLoanAmount),RefinanceLoanAmount))) -> 718351.4 | N7: =IF(AnnualModelTable[[#This Row],[Year]]<StabilizationRefiYear,0,AnnualModelTable[[#This Row],[NOI]]*(1+NOIGrowth)/ExitCapRate) -> 1182322.3
A8: 4 | B8: Operations | C8: =IF(AnnualModelTable[[#This Row],[Year]]=0,0,IF(AnnualModelTable[[#This Row],[Year]]>=RentScenarioHighEffectiveYear,RentScenarioHighMonthlyGross*12,IF(AnnualModelTable[[#This Row],[Year]]>=RentScenarioMediumEffectiveYear,RentScenarioMediumMonthlyGross*12,IF(AnnualModelTable[[#This Row],[Year]]>=RentScenarioLowEffectiveYear,RentScenarioLowMonthlyGross*12,0)))) -> 144000 | D8: =IF(A8=0,0,C8*IF(A8=1,LeaseUpOccupancy,StabilizedOccupancy)) -> 133920 | E8: =D8*OperatingExpenseRatio -> 53568 | F8: =D8-E8 -> 80352 | G8: =IF(AND(AnnualModelTable[[#This Row],[Year]]>=1,AnnualModelTable[[#This Row],[Year]]<StabilizationRefiYear),ExistingDebtServiceAnnual,IF(AND(AnnualModelTable[[#This Row],[Year]]>=StabilizationRefiYear,AnnualModelTable[[#This Row],[Year]]<=SaleExitYear),-PMT(RefinanceLoanRate/12,RefinanceLoanAmortizationYears*12,RefinanceLoanAmount)*12,0)) -> 55101.518 | H8: =AnnualModelTable[[#This Row],[NOI]]-AnnualModelTable[[#This Row],[Debt Service]] -> 25250.482 | I8: =IF(AnnualModelTable[[#This Row],[Year]]=StabilizationRefiYear,MAX(0,RefinanceLoanAmount-TotalExistingDebt),IF(AnnualModelTable[[#This Row],[Year]]=SaleExitYear,MAX(0,AnnualModelTable[[#This Row],[Property Value / Refi Value]]*(1-SellingCosts)-AnnualModelTable[[#This Row],[Loan Balance]]),0)) -> 0 | J8: =IF(AnnualModelTable[[#This Row],[Year]]=0,0,IFERROR(INDEX(AnnualModelTable[Ending Cash Balance],MATCH(AnnualModelTable[[#This Row],[Year]]-1,AnnualModelTable[Year],0)),0))+AnnualModelTable[[#This Row],[Current Year Cash Before Refi/Sale]]+AnnualModelTable[[#This Row],[Net Refi/Sale Proceeds]] -> 25250.482 | K8: =SUM(INDEX(WaterfallTable[A Total Dist],MATCH(AnnualModelTable[[#This Row],[Year]],WaterfallTable[Year],0)),INDEX(WaterfallTable[B Total Dist],MATCH(AnnualModelTable[[#This Row],[Year]],WaterfallTable[Year],0)),INDEX(WaterfallTable[Total Dist],MATCH(AnnualModelTable[[#This Row],[Year]],WaterfallTable[Year],0))) -> 25250.482 | L8: =MAX(0,AnnualModelTable[[#This Row],[Cash Available Before Distributions]]-AnnualModelTable[[#This Row],[Waterfall Distributions]]) -> 0 | M8: =IF(AnnualModelTable[[#This Row],[Year]]<StabilizationRefiYear,0,IF(AnnualModelTable[[#This Row],[Year]]=SaleExitYear,0,-FV(RefinanceLoanRate/12,(AnnualModelTable[[#This Row],[Year]]-StabilizationRefiYear)*12,PMT(RefinanceLoanRate/12,RefinanceLoanAmortizationYears*12,RefinanceLoanAmount),RefinanceLoanAmount))) -> 709687.64 | N8: =IF(AnnualModelTable[[#This Row],[Year]]<StabilizationRefiYear,0,AnnualModelTable[[#This Row],[NOI]]*(1+NOIGrowth)/ExitCapRate) -> 1182322.3
A9: 5 | B9: Operations | C9: =IF(AnnualModelTable[[#This Row],[Year]]=0,0,IF(AnnualModelTable[[#This Row],[Year]]>=RentScenarioHighEffectiveYear,RentScenarioHighMonthlyGross*12,IF(AnnualModelTable[[#This Row],[Year]]>=RentScenarioMediumEffectiveYear,RentScenarioMediumMonthlyGross*12,IF(AnnualModelTable[[#This Row],[Year]]>=RentScenarioLowEffectiveYear,RentScenarioLowMonthlyGross*12,0)))) -> 144000 | D9: =IF(A9=0,0,C9*IF(A9=1,LeaseUpOccupancy,StabilizedOccupancy)) -> 133920 | E9: =D9*OperatingExpenseRatio -> 53568 | F9: =D9-E9 -> 80352 | G9: =IF(AND(AnnualModelTable[[#This Row],[Year]]>=1,AnnualModelTable[[#This Row],[Year]]<StabilizationRefiYear),ExistingDebtServiceAnnual,IF(AND(AnnualModelTable[[#This Row],[Year]]>=StabilizationRefiYear,AnnualModelTable[[#This Row],[Year]]<=SaleExitYear),-PMT(RefinanceLoanRate/12,RefinanceLoanAmortizationYears*12,RefinanceLoanAmount)*12,0)) -> 55101.518 | H9: =AnnualModelTable[[#This Row],[NOI]]-AnnualModelTable[[#This Row],[Debt Service]] -> 25250.482 | I9: =IF(AnnualModelTable[[#This Row],[Year]]=StabilizationRefiYear,MAX(0,RefinanceLoanAmount-TotalExistingDebt),IF(AnnualModelTable[[#This Row],[Year]]=SaleExitYear,MAX(0,AnnualModelTable[[#This Row],[Property Value / Refi Value]]*(1-SellingCosts)-AnnualModelTable[[#This Row],[Loan Balance]]),0)) -> 0 | J9: =IF(AnnualModelTable[[#This Row],[Year]]=0,0,IFERROR(INDEX(AnnualModelTable[Ending Cash Balance],MATCH(AnnualModelTable[[#This Row],[Year]]-1,AnnualModelTable[Year],0)),0))+AnnualModelTable[[#This Row],[Current Year Cash Before Refi/Sale]]+AnnualModelTable[[#This Row],[Net Refi/Sale Proceeds]] -> 25250.482 | K9: =SUM(INDEX(WaterfallTable[A Total Dist],MATCH(AnnualModelTable[[#This Row],[Year]],WaterfallTable[Year],0)),INDEX(WaterfallTable[B Total Dist],MATCH(AnnualModelTable[[#This Row],[Year]],WaterfallTable[Year],0)),INDEX(WaterfallTable[Total Dist],MATCH(AnnualModelTable[[#This Row],[Year]],WaterfallTable[Year],0))) -> 25250.482 | L9: =MAX(0,AnnualModelTable[[#This Row],[Cash Available Before Distributions]]-AnnualModelTable[[#This Row],[Waterfall Distributions]]) -> 0 | M9: =IF(AnnualModelTable[[#This Row],[Year]]<StabilizationRefiYear,0,IF(AnnualModelTable[[#This Row],[Year]]=SaleExitYear,0,-FV(RefinanceLoanRate/12,(AnnualModelTable[[#This Row],[Year]]-StabilizationRefiYear)*12,PMT(RefinanceLoanRate/12,RefinanceLoanAmortizationYears*12,RefinanceLoanAmount),RefinanceLoanAmount))) -> 700443.65 | N9: =IF(AnnualModelTable[[#This Row],[Year]]<StabilizationRefiYear,0,AnnualModelTable[[#This Row],[NOI]]*(1+NOIGrowth)/ExitCapRate) -> 1182322.3
A10: 6 | B10: Operations | C10: =IF(AnnualModelTable[[#This Row],[Year]]=0,0,IF(AnnualModelTable[[#This Row],[Year]]>=RentScenarioHighEffectiveYear,RentScenarioHighMonthlyGross*12,IF(AnnualModelTable[[#This Row],[Year]]>=RentScenarioMediumEffectiveYear,RentScenarioMediumMonthlyGross*12,IF(AnnualModelTable[[#This Row],[Year]]>=RentScenarioLowEffectiveYear,RentScenarioLowMonthlyGross*12,0)))) -> 144000 | D10: =IF(A10=0,0,C10*IF(A10=1,LeaseUpOccupancy,StabilizedOccupancy)) -> 133920 | E10: =D10*OperatingExpenseRatio -> 53568 | F10: =D10-E10 -> 80352 | G10: =IF(AND(AnnualModelTable[[#This Row],[Year]]>=1,AnnualModelTable[[#This Row],[Year]]<StabilizationRefiYear),ExistingDebtServiceAnnual,IF(AND(AnnualModelTable[[#This Row],[Year]]>=StabilizationRefiYear,AnnualModelTable[[#This Row],[Year]]<=SaleExitYear),-PMT(RefinanceLoanRate/12,RefinanceLoanAmortizationYears*12,RefinanceLoanAmount)*12,0)) -> 55101.518 | H10: =AnnualModelTable[[#This Row],[NOI]]-AnnualModelTable[[#This Row],[Debt Service]] -> 25250.482 | I10: =IF(AnnualModelTable[[#This Row],[Year]]=StabilizationRefiYear,MAX(0,RefinanceLoanAmount-TotalExistingDebt),IF(AnnualModelTable[[#This Row],[Year]]=SaleExitYear,MAX(0,AnnualModelTable[[#This Row],[Property Value / Refi Value]]*(1-SellingCosts)-AnnualModelTable[[#This Row],[Loan Balance]]),0)) -> 0 | J10: =IF(AnnualModelTable[[#This Row],[Year]]=0,0,IFERROR(INDEX(AnnualModelTable[Ending Cash Balance],MATCH(AnnualModelTable[[#This Row],[Year]]-1,AnnualModelTable[Year],0)),0))+AnnualModelTable[[#This Row],[Current Year Cash Before Refi/Sale]]+AnnualModelTable[[#This Row],[Net Refi/Sale Proceeds]] -> 25250.482 | K10: =SUM(INDEX(WaterfallTable[A Total Dist],MATCH(AnnualModelTable[[#This Row],[Year]],WaterfallTable[Year],0)),INDEX(WaterfallTable[B Total Dist],MATCH(AnnualModelTable[[#This Row],[Year]],WaterfallTable[Year],0)),INDEX(WaterfallTable[Total Dist],MATCH(AnnualModelTable[[#This Row],[Year]],WaterfallTable[Year],0))) -> 25250.482 | L10: =MAX(0,AnnualModelTable[[#This Row],[Cash Available Before Distributions]]-AnnualModelTable[[#This Row],[Waterfall Distributions]]) -> 0 | M10: =IF(AnnualModelTable[[#This Row],[Year]]<StabilizationRefiYear,0,IF(AnnualModelTable[[#This Row],[Year]]=SaleExitYear,0,-FV(RefinanceLoanRate/12,(AnnualModelTable[[#This Row],[Year]]-StabilizationRefiYear)*12,PMT(RefinanceLoanRate/12,RefinanceLoanAmortizationYears*12,RefinanceLoanAmount),RefinanceLoanAmount))) -> 690580.57 | N10: =IF(AnnualModelTable[[#This Row],[Year]]<StabilizationRefiYear,0,AnnualModelTable[[#This Row],[NOI]]*(1+NOIGrowth)/ExitCapRate) -> 1182322.3
A11: 7 | B11: Operations | C11: =IF(AnnualModelTable[[#This Row],[Year]]=0,0,IF(AnnualModelTable[[#This Row],[Year]]>=RentScenarioHighEffectiveYear,RentScenarioHighMonthlyGross*12,IF(AnnualModelTable[[#This Row],[Year]]>=RentScenarioMediumEffectiveYear,RentScenarioMediumMonthlyGross*12,IF(AnnualModelTable[[#This Row],[Year]]>=RentScenarioLowEffectiveYear,RentScenarioLowMonthlyGross*12,0)))) -> 144000 | D11: =IF(A11=0,0,C11*IF(A11=1,LeaseUpOccupancy,StabilizedOccupancy)) -> 133920 | E11: =D11*OperatingExpenseRatio -> 53568 | F11: =D11-E11 -> 80352 | G11: =IF(AND(AnnualModelTable[[#This Row],[Year]]>=1,AnnualModelTable[[#This Row],[Year]]<StabilizationRefiYear),ExistingDebtServiceAnnual,IF(AND(AnnualModelTable[[#This Row],[Year]]>=StabilizationRefiYear,AnnualModelTable[[#This Row],[Year]]<=SaleExitYear),-PMT(RefinanceLoanRate/12,RefinanceLoanAmortizationYears*12,RefinanceLoanAmount)*12,0)) -> 55101.518 | H11: =AnnualModelTable[[#This Row],[NOI]]-AnnualModelTable[[#This Row],[Debt Service]] -> 25250.482 | I11: =IF(AnnualModelTable[[#This Row],[Year]]=StabilizationRefiYear,MAX(0,RefinanceLoanAmount-TotalExistingDebt),IF(AnnualModelTable[[#This Row],[Year]]=SaleExitYear,MAX(0,AnnualModelTable[[#This Row],[Property Value / Refi Value]]*(1-SellingCosts)-AnnualModelTable[[#This Row],[Loan Balance]]),0)) -> 0 | J11: =IF(AnnualModelTable[[#This Row],[Year]]=0,0,IFERROR(INDEX(AnnualModelTable[Ending Cash Balance],MATCH(AnnualModelTable[[#This Row],[Year]]-1,AnnualModelTable[Year],0)),0))+AnnualModelTable[[#This Row],[Current Year Cash Before Refi/Sale]]+AnnualModelTable[[#This Row],[Net Refi/Sale Proceeds]] -> 25250.482 | K11: =SUM(INDEX(WaterfallTable[A Total Dist],MATCH(AnnualModelTable[[#This Row],[Year]],WaterfallTable[Year],0)),INDEX(WaterfallTable[B Total Dist],MATCH(AnnualModelTable[[#This Row],[Year]],WaterfallTable[Year],0)),INDEX(WaterfallTable[Total Dist],MATCH(AnnualModelTable[[#This Row],[Year]],WaterfallTable[Year],0))) -> 25250.482 | L11: =MAX(0,AnnualModelTable[[#This Row],[Cash Available Before Distributions]]-AnnualModelTable[[#This Row],[Waterfall Distributions]]) -> 0 | M11: =IF(AnnualModelTable[[#This Row],[Year]]<StabilizationRefiYear,0,IF(AnnualModelTable[[#This Row],[Year]]=SaleExitYear,0,-FV(RefinanceLoanRate/12,(AnnualModelTable[[#This Row],[Year]]-StabilizationRefiYear)*12,PMT(RefinanceLoanRate/12,RefinanceLoanAmortizationYears*12,RefinanceLoanAmount),RefinanceLoanAmount))) -> 680056.94 | N11: =IF(AnnualModelTable[[#This Row],[Year]]<StabilizationRefiYear,0,AnnualModelTable[[#This Row],[NOI]]*(1+NOIGrowth)/ExitCapRate) -> 1182322.3
A12: 8 | B12: Operations | C12: =IF(AnnualModelTable[[#This Row],[Year]]=0,0,IF(AnnualModelTable[[#This Row],[Year]]>=RentScenarioHighEffectiveYear,RentScenarioHighMonthlyGross*12,IF(AnnualModelTable[[#This Row],[Year]]>=RentScenarioMediumEffectiveYear,RentScenarioMediumMonthlyGross*12,IF(AnnualModelTable[[#This Row],[Year]]>=RentScenarioLowEffectiveYear,RentScenarioLowMonthlyGross*12,0)))) -> 144000 | D12: =IF(A12=0,0,C12*IF(A12=1,LeaseUpOccupancy,StabilizedOccupancy)) -> 133920 | E12: =D12*OperatingExpenseRatio -> 53568 | F12: =D12-E12 -> 80352 | G12: =IF(AND(AnnualModelTable[[#This Row],[Year]]>=1,AnnualModelTable[[#This Row],[Year]]<StabilizationRefiYear),ExistingDebtServiceAnnual,IF(AND(AnnualModelTable[[#This Row],[Year]]>=StabilizationRefiYear,AnnualModelTable[[#This Row],[Year]]<=SaleExitYear),-PMT(RefinanceLoanRate/12,RefinanceLoanAmortizationYears*12,RefinanceLoanAmount)*12,0)) -> 55101.518 | H12: =AnnualModelTable[[#This Row],[NOI]]-AnnualModelTable[[#This Row],[Debt Service]] -> 25250.482 | I12: =IF(AnnualModelTable[[#This Row],[Year]]=StabilizationRefiYear,MAX(0,RefinanceLoanAmount-TotalExistingDebt),IF(AnnualModelTable[[#This Row],[Year]]=SaleExitYear,MAX(0,AnnualModelTable[[#This Row],[Property Value / Refi Value]]*(1-SellingCosts)-AnnualModelTable[[#This Row],[Loan Balance]]),0)) -> 0 | J12: =IF(AnnualModelTable[[#This Row],[Year]]=0,0,IFERROR(INDEX(AnnualModelTable[Ending Cash Balance],MATCH(AnnualModelTable[[#This Row],[Year]]-1,AnnualModelTable[Year],0)),0))+AnnualModelTable[[#This Row],[Current Year Cash Before Refi/Sale]]+AnnualModelTable[[#This Row],[Net Refi/Sale Proceeds]] -> 25250.482 | K12: =SUM(INDEX(WaterfallTable[A Total Dist],MATCH(AnnualModelTable[[#This Row],[Year]],WaterfallTable[Year],0)),INDEX(WaterfallTable[B Total Dist],MATCH(AnnualModelTable[[#This Row],[Year]],WaterfallTable[Year],0)),INDEX(WaterfallTable[Total Dist],MATCH(AnnualModelTable[[#This Row],[Year]],WaterfallTable[Year],0))) -> 25250.482 | L12: =MAX(0,AnnualModelTable[[#This Row],[Cash Available Before Distributions]]-AnnualModelTable[[#This Row],[Waterfall Distributions]]) -> 0 | M12: =IF(AnnualModelTable[[#This Row],[Year]]<StabilizationRefiYear,0,IF(AnnualModelTable[[#This Row],[Year]]=SaleExitYear,0,-FV(RefinanceLoanRate/12,(AnnualModelTable[[#This Row],[Year]]-StabilizationRefiYear)*12,PMT(RefinanceLoanRate/12,RefinanceLoanAmortizationYears*12,RefinanceLoanAmount),RefinanceLoanAmount))) -> 668828.53 | N12: =IF(AnnualModelTable[[#This Row],[Year]]<StabilizationRefiYear,0,AnnualModelTable[[#This Row],[NOI]]*(1+NOIGrowth)/ExitCapRate) -> 1182322.3
A13: 9 | B13: Operations | C13: =IF(AnnualModelTable[[#This Row],[Year]]=0,0,IF(AnnualModelTable[[#This Row],[Year]]>=RentScenarioHighEffectiveYear,RentScenarioHighMonthlyGross*12,IF(AnnualModelTable[[#This Row],[Year]]>=RentScenarioMediumEffectiveYear,RentScenarioMediumMonthlyGross*12,IF(AnnualModelTable[[#This Row],[Year]]>=RentScenarioLowEffectiveYear,RentScenarioLowMonthlyGross*12,0)))) -> 144000 | D13: =IF(A13=0,0,C13*IF(A13=1,LeaseUpOccupancy,StabilizedOccupancy)) -> 133920 | E13: =D13*OperatingExpenseRatio -> 53568 | F13: =D13-E13 -> 80352 | G13: =IF(AND(AnnualModelTable[[#This Row],[Year]]>=1,AnnualModelTable[[#This Row],[Year]]<StabilizationRefiYear),ExistingDebtServiceAnnual,IF(AND(AnnualModelTable[[#This Row],[Year]]>=StabilizationRefiYear,AnnualModelTable[[#This Row],[Year]]<=SaleExitYear),-PMT(RefinanceLoanRate/12,RefinanceLoanAmortizationYears*12,RefinanceLoanAmount)*12,0)) -> 55101.518 | H13: =AnnualModelTable[[#This Row],[NOI]]-AnnualModelTable[[#This Row],[Debt Service]] -> 25250.482 | I13: =IF(AnnualModelTable[[#This Row],[Year]]=StabilizationRefiYear,MAX(0,RefinanceLoanAmount-TotalExistingDebt),IF(AnnualModelTable[[#This Row],[Year]]=SaleExitYear,MAX(0,AnnualModelTable[[#This Row],[Property Value / Refi Value]]*(1-SellingCosts)-AnnualModelTable[[#This Row],[Loan Balance]]),0)) -> 0 | J13: =IF(AnnualModelTable[[#This Row],[Year]]=0,0,IFERROR(INDEX(AnnualModelTable[Ending Cash Balance],MATCH(AnnualModelTable[[#This Row],[Year]]-1,AnnualModelTable[Year],0)),0))+AnnualModelTable[[#This Row],[Current Year Cash Before Refi/Sale]]+AnnualModelTable[[#This Row],[Net Refi/Sale Proceeds]] -> 25250.482 | K13: =SUM(INDEX(WaterfallTable[A Total Dist],MATCH(AnnualModelTable[[#This Row],[Year]],WaterfallTable[Year],0)),INDEX(WaterfallTable[B Total Dist],MATCH(AnnualModelTable[[#This Row],[Year]],WaterfallTable[Year],0)),INDEX(WaterfallTable[Total Dist],MATCH(AnnualModelTable[[#This Row],[Year]],WaterfallTable[Year],0))) -> 25250.482 | L13: =MAX(0,AnnualModelTable[[#This Row],[Cash Available Before Distributions]]-AnnualModelTable[[#This Row],[Waterfall Distributions]]) -> 0 | M13: =IF(AnnualModelTable[[#This Row],[Year]]<StabilizationRefiYear,0,IF(AnnualModelTable[[#This Row],[Year]]=SaleExitYear,0,-FV(RefinanceLoanRate/12,(AnnualModelTable[[#This Row],[Year]]-StabilizationRefiYear)*12,PMT(RefinanceLoanRate/12,RefinanceLoanAmortizationYears*12,RefinanceLoanAmount),RefinanceLoanAmount))) -> 656848.12 | N13: =IF(AnnualModelTable[[#This Row],[Year]]<StabilizationRefiYear,0,AnnualModelTable[[#This Row],[NOI]]*(1+NOIGrowth)/ExitCapRate) -> 1182322.3
A14: 10 | B14: Exit | C14: =IF(AnnualModelTable[[#This Row],[Year]]=0,0,IF(AnnualModelTable[[#This Row],[Year]]>=RentScenarioHighEffectiveYear,RentScenarioHighMonthlyGross*12,IF(AnnualModelTable[[#This Row],[Year]]>=RentScenarioMediumEffectiveYear,RentScenarioMediumMonthlyGross*12,IF(AnnualModelTable[[#This Row],[Year]]>=RentScenarioLowEffectiveYear,RentScenarioLowMonthlyGross*12,0)))) -> 144000 | D14: =IF(A14=0,0,C14*IF(A14=1,LeaseUpOccupancy,StabilizedOccupancy)) -> 133920 | E14: =D14*OperatingExpenseRatio -> 53568 | F14: =D14-E14 -> 80352 | G14: =IF(AND(AnnualModelTable[[#This Row],[Year]]>=1,AnnualModelTable[[#This Row],[Year]]<StabilizationRefiYear),ExistingDebtServiceAnnual,IF(AND(AnnualModelTable[[#This Row],[Year]]>=StabilizationRefiYear,AnnualModelTable[[#This Row],[Year]]<=SaleExitYear),-PMT(RefinanceLoanRate/12,RefinanceLoanAmortizationYears*12,RefinanceLoanAmount)*12,0)) -> 55101.518 | H14: =AnnualModelTable[[#This Row],[NOI]]-AnnualModelTable[[#This Row],[Debt Service]] -> 25250.482 | I14: =IF(AnnualModelTable[[#This Row],[Year]]=StabilizationRefiYear,MAX(0,RefinanceLoanAmount-TotalExistingDebt),IF(AnnualModelTable[[#This Row],[Year]]=SaleExitYear,MAX(0,AnnualModelTable[[#This Row],[Property Value / Refi Value]]*(1-SellingCosts)-AnnualModelTable[[#This Row],[Loan Balance]]),0)) -> 1158675.8 | J14: =IF(AnnualModelTable[[#This Row],[Year]]=0,0,IFERROR(INDEX(AnnualModelTable[Ending Cash Balance],MATCH(AnnualModelTable[[#This Row],[Year]]-1,AnnualModelTable[Year],0)),0))+AnnualModelTable[[#This Row],[Current Year Cash Before Refi/Sale]]+AnnualModelTable[[#This Row],[Net Refi/Sale Proceeds]] -> 1183926.3 | K14: =SUM(INDEX(WaterfallTable[A Total Dist],MATCH(AnnualModelTable[[#This Row],[Year]],WaterfallTable[Year],0)),INDEX(WaterfallTable[B Total Dist],MATCH(AnnualModelTable[[#This Row],[Year]],WaterfallTable[Year],0)),INDEX(WaterfallTable[Total Dist],MATCH(AnnualModelTable[[#This Row],[Year]],WaterfallTable[Year],0))) -> 1183926.3 | L14: =MAX(0,AnnualModelTable[[#This Row],[Cash Available Before Distributions]]-AnnualModelTable[[#This Row],[Waterfall Distributions]]) -> 0 | M14: =IF(AnnualModelTable[[#This Row],[Year]]<StabilizationRefiYear,0,IF(AnnualModelTable[[#This Row],[Year]]=SaleExitYear,0,-FV(RefinanceLoanRate/12,(AnnualModelTable[[#This Row],[Year]]-StabilizationRefiYear)*12,PMT(RefinanceLoanRate/12,RefinanceLoanAmortizationYears*12,RefinanceLoanAmount),RefinanceLoanAmount))) -> 0 | N14: =IF(AnnualModelTable[[#This Row],[Year]]<StabilizationRefiYear,0,AnnualModelTable[[#This Row],[NOI]]*(1+NOIGrowth)/ExitCapRate) -> 1182322.3

Sheet Waterfall
A1: Annual Waterfall
C2: Class A | L2: Class B | Q2: Sponsor
A3: Year | B3: Cash Available | C3: Beg Pref Accrued | D3: Pref Accrued | E3: Pref Paid | F3: Capital | G3: A Capital Returned | H3: A End Accrued Pref | I3: A End Capital | J3: A Residual | K3: A Total Dist | L3: B Capital | M3: B Capital Returned | N3: B End Capital | O3: B Residual | P3: B Total Dist | Q3: Property Payment | R3: Residual | S3: Total Dist
A4: 0 | B4: =INDEX(AnnualModelTable[Cash Available Before Distributions],MATCH(WaterfallTable[[#This Row],[Year]],AnnualModelTable[Year],0)) -> 150000 | C4: =IF(WaterfallTable[[#This Row],[Year]]=0,0,INDEX(WaterfallTable[A End Accrued Pref],MATCH(WaterfallTable[[#This Row],[Year]]-1,WaterfallTable[Year],0))) -> 0 | D4: =WaterfallTable[[#This Row],[Capital]]*ClassAPreferredReturn -> 24000 | E4: =IF(WaterfallTable[[#This Row],[Year]]=0,0,MIN(WaterfallTable[[#This Row],[Cash Available]],WaterfallTable[[#This Row],[Beg Pref Accrued]]+WaterfallTable[[#This Row],[Pref Accrued]])) -> 0 | F4: =IF(WaterfallTable[[#This Row],[Year]]=0,ClassACapital,INDEX(WaterfallTable[A End Capital],MATCH(WaterfallTable[[#This Row],[Year]]-1,WaterfallTable[Year],0))) -> 300000 | G4: =IF(WaterfallTable[[#This Row],[Year]]=0,0,MIN(MAX(0,WaterfallTable[[#This Row],[Cash Available]]-WaterfallTable[[#This Row],[Pref Paid]]),WaterfallTable[[#This Row],[Capital]])) -> 0 | H4: =WaterfallTable[[#This Row],[Beg Pref Accrued]]+WaterfallTable[[#This Row],[Pref Accrued]]-WaterfallTable[[#This Row],[Pref Paid]] -> 24000 | I4: =WaterfallTable[[#This Row],[Capital]]-WaterfallTable[[#This Row],[A Capital Returned]] -> 300000 | J4: =IF(WaterfallTable[[#This Row],[Year]]=0,0,MAX(0,WaterfallTable[[#This Row],[Cash Available]]-WaterfallTable[[#This Row],[Pref Paid]]-WaterfallTable[[#This Row],[A Capital Returned]]-WaterfallTable[[#This Row],[B Capital Returned]])*ClassAResidualShare) -> 0 | K4: =WaterfallTable[[#This Row],[Pref Paid]]+WaterfallTable[[#This Row],[A Capital Returned]]+WaterfallTable[[#This Row],[A Residual]] -> 0 | L4: =IF(WaterfallTable[[#This Row],[Year]]=0,ClassBCapital,INDEX(WaterfallTable[B End Capital],MATCH(WaterfallTable[[#This Row],[Year]]-1,WaterfallTable[Year],0))) -> 597500 | M4: =IF(WaterfallTable[[#This Row],[Year]]=0,0,IF(ClassBReturnPriority=1,MIN(MAX(0,WaterfallTable[[#This Row],[Cash Available]]-WaterfallTable[[#This Row],[Pref Paid]]-WaterfallTable[[#This Row],[A Capital Returned]]),WaterfallTable[[#This Row],[B Capital]]),0)) -> 0 | N4: =WaterfallTable[[#This Row],[B Capital]]-WaterfallTable[[#This Row],[B Capital Returned]] -> 597500 | O4: =IF(WaterfallTable[[#This Row],[Year]]=0,0,MAX(0,WaterfallTable[[#This Row],[Cash Available]]-WaterfallTable[[#This Row],[Pref Paid]]-WaterfallTable[[#This Row],[A Capital Returned]]-WaterfallTable[[#This Row],[B Capital Returned]])*ClassBResidualShare) -> 0 | P4: =WaterfallTable[[#This Row],[B Capital Returned]]+WaterfallTable[[#This Row],[B Residual]] -> 0 | Q4: =IF(WaterfallTable[[#This Row],[Year]]=0,SponsorPropertyPayment,0) -> 150000 | R4: =IF(WaterfallTable[[#This Row],[Year]]=0,0,MAX(0,WaterfallTable[[#This Row],[Cash Available]]-WaterfallTable[[#This Row],[Pref Paid]]-WaterfallTable[[#This Row],[A Capital Returned]]-WaterfallTable[[#This Row],[B Capital Returned]])*SponsorResidualShare) -> 0 | S4: =WaterfallTable[[#This Row],[Property Payment]]+WaterfallTable[[#This Row],[Residual]] -> 150000
A5: 1 | B5: =INDEX(AnnualModelTable[Cash Available Before Distributions],MATCH(WaterfallTable[[#This Row],[Year]],AnnualModelTable[Year],0)) -> 17868 | C5: =IF(WaterfallTable[[#This Row],[Year]]=0,0,INDEX(WaterfallTable[A End Accrued Pref],MATCH(WaterfallTable[[#This Row],[Year]]-1,WaterfallTable[Year],0))) -> 24000 | D5: =WaterfallTable[[#This Row],[Capital]]*ClassAPreferredReturn -> 24000 | E5: =IF(WaterfallTable[[#This Row],[Year]]=0,0,MIN(WaterfallTable[[#This Row],[Cash Available]],WaterfallTable[[#This Row],[Beg Pref Accrued]]+WaterfallTable[[#This Row],[Pref Accrued]])) -> 17868 | F5: =IF(WaterfallTable[[#This Row],[Year]]=0,ClassACapital,INDEX(WaterfallTable[A End Capital],MATCH(WaterfallTable[[#This Row],[Year]]-1,WaterfallTable[Year],0))) -> 300000 | G5: =IF(WaterfallTable[[#This Row],[Year]]=0,0,MIN(MAX(0,WaterfallTable[[#This Row],[Cash Available]]-WaterfallTable[[#This Row],[Pref Paid]]),WaterfallTable[[#This Row],[Capital]])) -> 0 | H5: =WaterfallTable[[#This Row],[Beg Pref Accrued]]+WaterfallTable[[#This Row],[Pref Accrued]]-WaterfallTable[[#This Row],[Pref Paid]] -> 30132 | I5: =WaterfallTable[[#This Row],[Capital]]-WaterfallTable[[#This Row],[A Capital Returned]] -> 300000 | J5: =IF(WaterfallTable[[#This Row],[Year]]=0,0,MAX(0,WaterfallTable[[#This Row],[Cash Available]]-WaterfallTable[[#This Row],[Pref Paid]]-WaterfallTable[[#This Row],[A Capital Returned]]-WaterfallTable[[#This Row],[B Capital Returned]])*ClassAResidualShare) -> 0 | K5: =WaterfallTable[[#This Row],[Pref Paid]]+WaterfallTable[[#This Row],[A Capital Returned]]+WaterfallTable[[#This Row],[A Residual]] -> 17868 | L5: =IF(WaterfallTable[[#This Row],[Year]]=0,ClassBCapital,INDEX(WaterfallTable[B End Capital],MATCH(WaterfallTable[[#This Row],[Year]]-1,WaterfallTable[Year],0))) -> 597500 | M5: =IF(WaterfallTable[[#This Row],[Year]]=0,0,IF(ClassBReturnPriority=1,MIN(MAX(0,WaterfallTable[[#This Row],[Cash Available]]-WaterfallTable[[#This Row],[Pref Paid]]-WaterfallTable[[#This Row],[A Capital Returned]]),WaterfallTable[[#This Row],[B Capital]]),0)) -> 0 | N5: =WaterfallTable[[#This Row],[B Capital]]-WaterfallTable[[#This Row],[B Capital Returned]] -> 597500 | O5: =IF(WaterfallTable[[#This Row],[Year]]=0,0,MAX(0,WaterfallTable[[#This Row],[Cash Available]]-WaterfallTable[[#This Row],[Pref Paid]]-WaterfallTable[[#This Row],[A Capital Returned]]-WaterfallTable[[#This Row],[B Capital Returned]])*ClassBResidualShare) -> 0 | P5: =WaterfallTable[[#This Row],[B Capital Returned]]+WaterfallTable[[#This Row],[B Residual]] -> 0 | Q5: =IF(WaterfallTable[[#This Row],[Year]]=0,SponsorPropertyPayment,0) -> 0 | R5: =IF(WaterfallTable[[#This Row],[Year]]=0,0,MAX(0,WaterfallTable[[#This Row],[Cash Available]]-WaterfallTable[[#This Row],[Pref Paid]]-WaterfallTable[[#This Row],[A Capital Returned]]-WaterfallTable[[#This Row],[B Capital Returned]])*SponsorResidualShare) -> 0 | S5: =WaterfallTable[[#This Row],[Property Payment]]+WaterfallTable[[#This Row],[Residual]] -> 0
A6: 2 | B6: =INDEX(AnnualModelTable[Cash Available Before Distributions],MATCH(WaterfallTable[[#This Row],[Year]],AnnualModelTable[Year],0)) -> 549686.64 | C6: =IF(WaterfallTable[[#This Row],[Year]]=0,0,INDEX(WaterfallTable[A End Accrued Pref],MATCH(WaterfallTable[[#This Row],[Year]]-1,WaterfallTable[Year],0))) -> 30132 | D6: =WaterfallTable[[#This Row],[Capital]]*ClassAPreferredReturn -> 24000 | E6: =IF(WaterfallTable[[#This Row],[Year]]=0,0,MIN(WaterfallTable[[#This Row],[Cash Available]],WaterfallTable[[#This Row],[Beg Pref Accrued]]+WaterfallTable[[#This Row],[Pref Accrued]])) -> 54132 | F6: =IF(WaterfallTable[[#This Row],[Year]]=0,ClassACapital,INDEX(WaterfallTable[A End Capital],MATCH(WaterfallTable[[#This Row],[Year]]-1,WaterfallTable[Year],0))) -> 300000 | G6: =IF(WaterfallTable[[#This Row],[Year]]=0,0,MIN(MAX(0,WaterfallTable[[#This Row],[Cash Available]]-WaterfallTable[[#This Row],[Pref Paid]]),WaterfallTable[[#This Row],[Capital]])) -> 300000 | H6: =WaterfallTable[[#This Row],[Beg Pref Accrued]]+WaterfallTable[[#This Row],[Pref Accrued]]-WaterfallTable[[#This Row],[Pref Paid]] -> 0 | I6: =WaterfallTable[[#This Row],[Capital]]-WaterfallTable[[#This Row],[A Capital Returned]] -> 0 | J6: =IF(WaterfallTable[[#This Row],[Year]]=0,0,MAX(0,WaterfallTable[[#This Row],[Cash Available]]-WaterfallTable[[#This Row],[Pref Paid]]-WaterfallTable[[#This Row],[A Capital Returned]]-WaterfallTable[[#This Row],[B Capital Returned]])*ClassAResidualShare) -> 0 | K6: =WaterfallTable[[#This Row],[Pref Paid]]+WaterfallTable[[#This Row],[A Capital Returned]]+WaterfallTable[[#This Row],[A Residual]] -> 354132 | L6: =IF(WaterfallTable[[#This Row],[Year]]=0,ClassBCapital,INDEX(WaterfallTable[B End Capital],MATCH(WaterfallTable[[#This Row],[Year]]-1,WaterfallTable[Year],0))) -> 597500 | M6: =IF(WaterfallTable[[#This Row],[Year]]=0,0,IF(ClassBReturnPriority=1,MIN(MAX(0,WaterfallTable[[#This Row],[Cash Available]]-WaterfallTable[[#This Row],[Pref Paid]]-WaterfallTable[[#This Row],[A Capital Returned]]),WaterfallTable[[#This Row],[B Capital]]),0)) -> 195554.64 | N6: =WaterfallTable[[#This Row],[B Capital]]-WaterfallTable[[#This Row],[B Capital Returned]] -> 401945.36 | O6: =IF(WaterfallTable[[#This Row],[Year]]=0,0,MAX(0,WaterfallTable[[#This Row],[Cash Available]]-WaterfallTable[[#This Row],[Pref Paid]]-WaterfallTable[[#This Row],[A Capital Returned]]-WaterfallTable[[#This Row],[B Capital Returned]])*ClassBResidualShare) -> 0 | P6: =WaterfallTable[[#This Row],[B Capital Returned]]+WaterfallTable[[#This Row],[B Residual]] -> 195554.64 | Q6: =IF(WaterfallTable[[#This Row],[Year]]=0,SponsorPropertyPayment,0) -> 0 | R6: =IF(WaterfallTable[[#This Row],[Year]]=0,0,MAX(0,WaterfallTable[[#This Row],[Cash Available]]-WaterfallTable[[#This Row],[Pref Paid]]-WaterfallTable[[#This Row],[A Capital Returned]]-WaterfallTable[[#This Row],[B Capital Returned]])*SponsorResidualShare) -> 0 | S6: =WaterfallTable[[#This Row],[Property Payment]]+WaterfallTable[[#This Row],[Residual]] -> 0
A7: 3 | B7: =INDEX(AnnualModelTable[Cash Available Before Distributions],MATCH(WaterfallTable[[#This Row],[Year]],AnnualModelTable[Year],0)) -> 25250.482 | C7: =IF(WaterfallTable[[#This Row],[Year]]=0,0,INDEX(WaterfallTable[A End Accrued Pref],MATCH(WaterfallTable[[#This Row],[Year]]-1,WaterfallTable[Year],0))) -> 0 | D7: =WaterfallTable[[#This Row],[Capital]]*ClassAPreferredReturn -> 0 | E7: =IF(WaterfallTable[[#This Row],[Year]]=0,0,MIN(WaterfallTable[[#This Row],[Cash Available]],WaterfallTable[[#This Row],[Beg Pref Accrued]]+WaterfallTable[[#This Row],[Pref Accrued]])) -> 0 | F7: =IF(WaterfallTable[[#This Row],[Year]]=0,ClassACapital,INDEX(WaterfallTable[A End Capital],MATCH(WaterfallTable[[#This Row],[Year]]-1,WaterfallTable[Year],0))) -> 0 | G7: =IF(WaterfallTable[[#This Row],[Year]]=0,0,MIN(MAX(0,WaterfallTable[[#This Row],[Cash Available]]-WaterfallTable[[#This Row],[Pref Paid]]),WaterfallTable[[#This Row],[Capital]])) -> 0 | H7: =WaterfallTable[[#This Row],[Beg Pref Accrued]]+WaterfallTable[[#This Row],[Pref Accrued]]-WaterfallTable[[#This Row],[Pref Paid]] -> 0 | I7: =WaterfallTable[[#This Row],[Capital]]-WaterfallTable[[#This Row],[A Capital Returned]] -> 0 | J7: =IF(WaterfallTable[[#This Row],[Year]]=0,0,MAX(0,WaterfallTable[[#This Row],[Cash Available]]-WaterfallTable[[#This Row],[Pref Paid]]-WaterfallTable[[#This Row],[A Capital Returned]]-WaterfallTable[[#This Row],[B Capital Returned]])*ClassAResidualShare) -> 0 | K7: =WaterfallTable[[#This Row],[Pref Paid]]+WaterfallTable[[#This Row],[A Capital Returned]]+WaterfallTable[[#This Row],[A Residual]] -> 0 | L7: =IF(WaterfallTable[[#This Row],[Year]]=0,ClassBCapital,INDEX(WaterfallTable[B End Capital],MATCH(WaterfallTable[[#This Row],[Year]]-1,WaterfallTable[Year],0))) -> 401945.36 | M7: =IF(WaterfallTable[[#This Row],[Year]]=0,0,IF(ClassBReturnPriority=1,MIN(MAX(0,WaterfallTable[[#This Row],[Cash Available]]-WaterfallTable[[#This Row],[Pref Paid]]-WaterfallTable[[#This Row],[A Capital Returned]]),WaterfallTable[[#This Row],[B Capital]]),0)) -> 25250.482 | N7: =WaterfallTable[[#This Row],[B Capital]]-WaterfallTable[[#This Row],[B Capital Returned]] -> 376694.88 | O7: =IF(WaterfallTable[[#This Row],[Year]]=0,0,MAX(0,WaterfallTable[[#This Row],[Cash Available]]-WaterfallTable[[#This Row],[Pref Paid]]-WaterfallTable[[#This Row],[A Capital Returned]]-WaterfallTable[[#This Row],[B Capital Returned]])*ClassBResidualShare) -> 0 | P7: =WaterfallTable[[#This Row],[B Capital Returned]]+WaterfallTable[[#This Row],[B Residual]] -> 25250.482 | Q7: =IF(WaterfallTable[[#This Row],[Year]]=0,SponsorPropertyPayment,0) -> 0 | R7: =IF(WaterfallTable[[#This Row],[Year]]=0,0,MAX(0,WaterfallTable[[#This Row],[Cash Available]]-WaterfallTable[[#This Row],[Pref Paid]]-WaterfallTable[[#This Row],[A Capital Returned]]-WaterfallTable[[#This Row],[B Capital Returned]])*SponsorResidualShare) -> 0 | S7: =WaterfallTable[[#This Row],[Property Payment]]+WaterfallTable[[#This Row],[Residual]] -> 0
A8: 4 | B8: =INDEX(AnnualModelTable[Cash Available Before Distributions],MATCH(WaterfallTable[[#This Row],[Year]],AnnualModelTable[Year],0)) -> 25250.482 | C8: =IF(WaterfallTable[[#This Row],[Year]]=0,0,INDEX(WaterfallTable[A End Accrued Pref],MATCH(WaterfallTable[[#This Row],[Year]]-1,WaterfallTable[Year],0))) -> 0 | D8: =WaterfallTable[[#This Row],[Capital]]*ClassAPreferredReturn -> 0 | E8: =IF(WaterfallTable[[#This Row],[Year]]=0,0,MIN(WaterfallTable[[#This Row],[Cash Available]],WaterfallTable[[#This Row],[Beg Pref Accrued]]+WaterfallTable[[#This Row],[Pref Accrued]])) -> 0 | F8: =IF(WaterfallTable[[#This Row],[Year]]=0,ClassACapital,INDEX(WaterfallTable[A End Capital],MATCH(WaterfallTable[[#This Row],[Year]]-1,WaterfallTable[Year],0))) -> 0 | G8: =IF(WaterfallTable[[#This Row],[Year]]=0,0,MIN(MAX(0,WaterfallTable[[#This Row],[Cash Available]]-WaterfallTable[[#This Row],[Pref Paid]]),WaterfallTable[[#This Row],[Capital]])) -> 0 | H8: =WaterfallTable[[#This Row],[Beg Pref Accrued]]+WaterfallTable[[#This Row],[Pref Accrued]]-WaterfallTable[[#This Row],[Pref Paid]] -> 0 | I8: =WaterfallTable[[#This Row],[Capital]]-WaterfallTable[[#This Row],[A Capital Returned]] -> 0 | J8: =IF(WaterfallTable[[#This Row],[Year]]=0,0,MAX(0,WaterfallTable[[#This Row],[Cash Available]]-WaterfallTable[[#This Row],[Pref Paid]]-WaterfallTable[[#This Row],[A Capital Returned]]-WaterfallTable[[#This Row],[B Capital Returned]])*ClassAResidualShare) -> 0 | K8: =WaterfallTable[[#This Row],[Pref Paid]]+WaterfallTable[[#This Row],[A Capital Returned]]+WaterfallTable[[#This Row],[A Residual]] -> 0 | L8: =IF(WaterfallTable[[#This Row],[Year]]=0,ClassBCapital,INDEX(WaterfallTable[B End Capital],MATCH(WaterfallTable[[#This Row],[Year]]-1,WaterfallTable[Year],0))) -> 376694.88 | M8: =IF(WaterfallTable[[#This Row],[Year]]=0,0,IF(ClassBReturnPriority=1,MIN(MAX(0,WaterfallTable[[#This Row],[Cash Available]]-WaterfallTable[[#This Row],[Pref Paid]]-WaterfallTable[[#This Row],[A Capital Returned]]),WaterfallTable[[#This Row],[B Capital]]),0)) -> 25250.482 | N8: =WaterfallTable[[#This Row],[B Capital]]-WaterfallTable[[#This Row],[B Capital Returned]] -> 351444.39 | O8: =IF(WaterfallTable[[#This Row],[Year]]=0,0,MAX(0,WaterfallTable[[#This Row],[Cash Available]]-WaterfallTable[[#This Row],[Pref Paid]]-WaterfallTable[[#This Row],[A Capital Returned]]-WaterfallTable[[#This Row],[B Capital Returned]])*ClassBResidualShare) -> 0 | P8: =WaterfallTable[[#This Row],[B Capital Returned]]+WaterfallTable[[#This Row],[B Residual]] -> 25250.482 | Q8: =IF(WaterfallTable[[#This Row],[Year]]=0,SponsorPropertyPayment,0) -> 0 | R8: =IF(WaterfallTable[[#This Row],[Year]]=0,0,MAX(0,WaterfallTable[[#This Row],[Cash Available]]-WaterfallTable[[#This Row],[Pref Paid]]-WaterfallTable[[#This Row],[A Capital Returned]]-WaterfallTable[[#This Row],[B Capital Returned]])*SponsorResidualShare) -> 0 | S8: =WaterfallTable[[#This Row],[Property Payment]]+WaterfallTable[[#This Row],[Residual]] -> 0
A9: 5 | B9: =INDEX(AnnualModelTable[Cash Available Before Distributions],MATCH(WaterfallTable[[#This Row],[Year]],AnnualModelTable[Year],0)) -> 25250.482 | C9: =IF(WaterfallTable[[#This Row],[Year]]=0,0,INDEX(WaterfallTable[A End Accrued Pref],MATCH(WaterfallTable[[#This Row],[Year]]-1,WaterfallTable[Year],0))) -> 0 | D9: =WaterfallTable[[#This Row],[Capital]]*ClassAPreferredReturn -> 0 | E9: =IF(WaterfallTable[[#This Row],[Year]]=0,0,MIN(WaterfallTable[[#This Row],[Cash Available]],WaterfallTable[[#This Row],[Beg Pref Accrued]]+WaterfallTable[[#This Row],[Pref Accrued]])) -> 0 | F9: =IF(WaterfallTable[[#This Row],[Year]]=0,ClassACapital,INDEX(WaterfallTable[A End Capital],MATCH(WaterfallTable[[#This Row],[Year]]-1,WaterfallTable[Year],0))) -> 0 | G9: =IF(WaterfallTable[[#This Row],[Year]]=0,0,MIN(MAX(0,WaterfallTable[[#This Row],[Cash Available]]-WaterfallTable[[#This Row],[Pref Paid]]),WaterfallTable[[#This Row],[Capital]])) -> 0 | H9: =WaterfallTable[[#This Row],[Beg Pref Accrued]]+WaterfallTable[[#This Row],[Pref Accrued]]-WaterfallTable[[#This Row],[Pref Paid]] -> 0 | I9: =WaterfallTable[[#This Row],[Capital]]-WaterfallTable[[#This Row],[A Capital Returned]] -> 0 | J9: =IF(WaterfallTable[[#This Row],[Year]]=0,0,MAX(0,WaterfallTable[[#This Row],[Cash Available]]-WaterfallTable[[#This Row],[Pref Paid]]-WaterfallTable[[#This Row],[A Capital Returned]]-WaterfallTable[[#This Row],[B Capital Returned]])*ClassAResidualShare) -> 0 | K9: =WaterfallTable[[#This Row],[Pref Paid]]+WaterfallTable[[#This Row],[A Capital Returned]]+WaterfallTable[[#This Row],[A Residual]] -> 0 | L9: =IF(WaterfallTable[[#This Row],[Year]]=0,ClassBCapital,INDEX(WaterfallTable[B End Capital],MATCH(WaterfallTable[[#This Row],[Year]]-1,WaterfallTable[Year],0))) -> 351444.39 | M9: =IF(WaterfallTable[[#This Row],[Year]]=0,0,IF(ClassBReturnPriority=1,MIN(MAX(0,WaterfallTable[[#This Row],[Cash Available]]-WaterfallTable[[#This Row],[Pref Paid]]-WaterfallTable[[#This Row],[A Capital Returned]]),WaterfallTable[[#This Row],[B Capital]]),0)) -> 25250.482 | N9: =WaterfallTable[[#This Row],[B Capital]]-WaterfallTable[[#This Row],[B Capital Returned]] -> 326193.91 | O9: =IF(WaterfallTable[[#This Row],[Year]]=0,0,MAX(0,WaterfallTable[[#This Row],[Cash Available]]-WaterfallTable[[#This Row],[Pref Paid]]-WaterfallTable[[#This Row],[A Capital Returned]]-WaterfallTable[[#This Row],[B Capital Returned]])*ClassBResidualShare) -> 0 | P9: =WaterfallTable[[#This Row],[B Capital Returned]]+WaterfallTable[[#This Row],[B Residual]] -> 25250.482 | Q9: =IF(WaterfallTable[[#This Row],[Year]]=0,SponsorPropertyPayment,0) -> 0 | R9: =IF(WaterfallTable[[#This Row],[Year]]=0,0,MAX(0,WaterfallTable[[#This Row],[Cash Available]]-WaterfallTable[[#This Row],[Pref Paid]]-WaterfallTable[[#This Row],[A Capital Returned]]-WaterfallTable[[#This Row],[B Capital Returned]])*SponsorResidualShare) -> 0 | S9: =WaterfallTable[[#This Row],[Property Payment]]+WaterfallTable[[#This Row],[Residual]] -> 0
A10: 6 | B10: =INDEX(AnnualModelTable[Cash Available Before Distributions],MATCH(WaterfallTable[[#This Row],[Year]],AnnualModelTable[Year],0)) -> 25250.482 | C10: =IF(WaterfallTable[[#This Row],[Year]]=0,0,INDEX(WaterfallTable[A End Accrued Pref],MATCH(WaterfallTable[[#This Row],[Year]]-1,WaterfallTable[Year],0))) -> 0 | D10: =WaterfallTable[[#This Row],[Capital]]*ClassAPreferredReturn -> 0 | E10: =IF(WaterfallTable[[#This Row],[Year]]=0,0,MIN(WaterfallTable[[#This Row],[Cash Available]],WaterfallTable[[#This Row],[Beg Pref Accrued]]+WaterfallTable[[#This Row],[Pref Accrued]])) -> 0 | F10: =IF(WaterfallTable[[#This Row],[Year]]=0,ClassACapital,INDEX(WaterfallTable[A End Capital],MATCH(WaterfallTable[[#This Row],[Year]]-1,WaterfallTable[Year],0))) -> 0 | G10: =IF(WaterfallTable[[#This Row],[Year]]=0,0,MIN(MAX(0,WaterfallTable[[#This Row],[Cash Available]]-WaterfallTable[[#This Row],[Pref Paid]]),WaterfallTable[[#This Row],[Capital]])) -> 0 | H10: =WaterfallTable[[#This Row],[Beg Pref Accrued]]+WaterfallTable[[#This Row],[Pref Accrued]]-WaterfallTable[[#This Row],[Pref Paid]] -> 0 | I10: =WaterfallTable[[#This Row],[Capital]]-WaterfallTable[[#This Row],[A Capital Returned]] -> 0 | J10: =IF(WaterfallTable[[#This Row],[Year]]=0,0,MAX(0,WaterfallTable[[#This Row],[Cash Available]]-WaterfallTable[[#This Row],[Pref Paid]]-WaterfallTable[[#This Row],[A Capital Returned]]-WaterfallTable[[#This Row],[B Capital Returned]])*ClassAResidualShare) -> 0 | K10: =WaterfallTable[[#This Row],[Pref Paid]]+WaterfallTable[[#This Row],[A Capital Returned]]+WaterfallTable[[#This Row],[A Residual]] -> 0 | L10: =IF(WaterfallTable[[#This Row],[Year]]=0,ClassBCapital,INDEX(WaterfallTable[B End Capital],MATCH(WaterfallTable[[#This Row],[Year]]-1,WaterfallTable[Year],0))) -> 326193.91 | M10: =IF(WaterfallTable[[#This Row],[Year]]=0,0,IF(ClassBReturnPriority=1,MIN(MAX(0,WaterfallTable[[#This Row],[Cash Available]]-WaterfallTable[[#This Row],[Pref Paid]]-WaterfallTable[[#This Row],[A Capital Returned]]),WaterfallTable[[#This Row],[B Capital]]),0)) -> 25250.482 | N10: =WaterfallTable[[#This Row],[B Capital]]-WaterfallTable[[#This Row],[B Capital Returned]] -> 300943.43 | O10: =IF(WaterfallTable[[#This Row],[Year]]=0,0,MAX(0,WaterfallTable[[#This Row],[Cash Available]]-WaterfallTable[[#This Row],[Pref Paid]]-WaterfallTable[[#This Row],[A Capital Returned]]-WaterfallTable[[#This Row],[B Capital Returned]])*ClassBResidualShare) -> 0 | P10: =WaterfallTable[[#This Row],[B Capital Returned]]+WaterfallTable[[#This Row],[B Residual]] -> 25250.482 | Q10: =IF(WaterfallTable[[#This Row],[Year]]=0,SponsorPropertyPayment,0) -> 0 | R10: =IF(WaterfallTable[[#This Row],[Year]]=0,0,MAX(0,WaterfallTable[[#This Row],[Cash Available]]-WaterfallTable[[#This Row],[Pref Paid]]-WaterfallTable[[#This Row],[A Capital Returned]]-WaterfallTable[[#This Row],[B Capital Returned]])*SponsorResidualShare) -> 0 | S10: =WaterfallTable[[#This Row],[Property Payment]]+WaterfallTable[[#This Row],[Residual]] -> 0
A11: 7 | B11: =INDEX(AnnualModelTable[Cash Available Before Distributions],MATCH(WaterfallTable[[#This Row],[Year]],AnnualModelTable[Year],0)) -> 25250.482 | C11: =IF(WaterfallTable[[#This Row],[Year]]=0,0,INDEX(WaterfallTable[A End Accrued Pref],MATCH(WaterfallTable[[#This Row],[Year]]-1,WaterfallTable[Year],0))) -> 0 | D11: =WaterfallTable[[#This Row],[Capital]]*ClassAPreferredReturn -> 0 | E11: =IF(WaterfallTable[[#This Row],[Year]]=0,0,MIN(WaterfallTable[[#This Row],[Cash Available]],WaterfallTable[[#This Row],[Beg Pref Accrued]]+WaterfallTable[[#This Row],[Pref Accrued]])) -> 0 | F11: =IF(WaterfallTable[[#This Row],[Year]]=0,ClassACapital,INDEX(WaterfallTable[A End Capital],MATCH(WaterfallTable[[#This Row],[Year]]-1,WaterfallTable[Year],0))) -> 0 | G11: =IF(WaterfallTable[[#This Row],[Year]]=0,0,MIN(MAX(0,WaterfallTable[[#This Row],[Cash Available]]-WaterfallTable[[#This Row],[Pref Paid]]),WaterfallTable[[#This Row],[Capital]])) -> 0 | H11: =WaterfallTable[[#This Row],[Beg Pref Accrued]]+WaterfallTable[[#This Row],[Pref Accrued]]-WaterfallTable[[#This Row],[Pref Paid]] -> 0 | I11: =WaterfallTable[[#This Row],[Capital]]-WaterfallTable[[#This Row],[A Capital Returned]] -> 0 | J11: =IF(WaterfallTable[[#This Row],[Year]]=0,0,MAX(0,WaterfallTable[[#This Row],[Cash Available]]-WaterfallTable[[#This Row],[Pref Paid]]-WaterfallTable[[#This Row],[A Capital Returned]]-WaterfallTable[[#This Row],[B Capital Returned]])*ClassAResidualShare) -> 0 | K11: =WaterfallTable[[#This Row],[Pref Paid]]+WaterfallTable[[#This Row],[A Capital Returned]]+WaterfallTable[[#This Row],[A Residual]] -> 0 | L11: =IF(WaterfallTable[[#This Row],[Year]]=0,ClassBCapital,INDEX(WaterfallTable[B End Capital],MATCH(WaterfallTable[[#This Row],[Year]]-1,WaterfallTable[Year],0))) -> 300943.43 | M11: =IF(WaterfallTable[[#This Row],[Year]]=0,0,IF(ClassBReturnPriority=1,MIN(MAX(0,WaterfallTable[[#This Row],[Cash Available]]-WaterfallTable[[#This Row],[Pref Paid]]-WaterfallTable[[#This Row],[A Capital Returned]]),WaterfallTable[[#This Row],[B Capital]]),0)) -> 25250.482 | N11: =WaterfallTable[[#This Row],[B Capital]]-WaterfallTable[[#This Row],[B Capital Returned]] -> 275692.95 | O11: =IF(WaterfallTable[[#This Row],[Year]]=0,0,MAX(0,WaterfallTable[[#This Row],[Cash Available]]-WaterfallTable[[#This Row],[Pref Paid]]-WaterfallTable[[#This Row],[A Capital Returned]]-WaterfallTable[[#This Row],[B Capital Returned]])*ClassBResidualShare) -> 0 | P11: =WaterfallTable[[#This Row],[B Capital Returned]]+WaterfallTable[[#This Row],[B Residual]] -> 25250.482 | Q11: =IF(WaterfallTable[[#This Row],[Year]]=0,SponsorPropertyPayment,0) -> 0 | R11: =IF(WaterfallTable[[#This Row],[Year]]=0,0,MAX(0,WaterfallTable[[#This Row],[Cash Available]]-WaterfallTable[[#This Row],[Pref Paid]]-WaterfallTable[[#This Row],[A Capital Returned]]-WaterfallTable[[#This Row],[B Capital Returned]])*SponsorResidualShare) -> 0 | S11: =WaterfallTable[[#This Row],[Property Payment]]+WaterfallTable[[#This Row],[Residual]] -> 0
A12: 8 | B12: =INDEX(AnnualModelTable[Cash Available Before Distributions],MATCH(WaterfallTable[[#This Row],[Year]],AnnualModelTable[Year],0)) -> 25250.482 | C12: =IF(WaterfallTable[[#This Row],[Year]]=0,0,INDEX(WaterfallTable[A End Accrued Pref],MATCH(WaterfallTable[[#This Row],[Year]]-1,WaterfallTable[Year],0))) -> 0 | D12: =WaterfallTable[[#This Row],[Capital]]*ClassAPreferredReturn -> 0 | E12: =IF(WaterfallTable[[#This Row],[Year]]=0,0,MIN(WaterfallTable[[#This Row],[Cash Available]],WaterfallTable[[#This Row],[Beg Pref Accrued]]+WaterfallTable[[#This Row],[Pref Accrued]])) -> 0 | F12: =IF(WaterfallTable[[#This Row],[Year]]=0,ClassACapital,INDEX(WaterfallTable[A End Capital],MATCH(WaterfallTable[[#This Row],[Year]]-1,WaterfallTable[Year],0))) -> 0 | G12: =IF(WaterfallTable[[#This Row],[Year]]=0,0,MIN(MAX(0,WaterfallTable[[#This Row],[Cash Available]]-WaterfallTable[[#This Row],[Pref Paid]]),WaterfallTable[[#This Row],[Capital]])) -> 0 | H12: =WaterfallTable[[#This Row],[Beg Pref Accrued]]+WaterfallTable[[#This Row],[Pref Accrued]]-WaterfallTable[[#This Row],[Pref Paid]] -> 0 | I12: =WaterfallTable[[#This Row],[Capital]]-WaterfallTable[[#This Row],[A Capital Returned]] -> 0 | J12: =IF(WaterfallTable[[#This Row],[Year]]=0,0,MAX(0,WaterfallTable[[#This Row],[Cash Available]]-WaterfallTable[[#This Row],[Pref Paid]]-WaterfallTable[[#This Row],[A Capital Returned]]-WaterfallTable[[#This Row],[B Capital Returned]])*ClassAResidualShare) -> 0 | K12: =WaterfallTable[[#This Row],[Pref Paid]]+WaterfallTable[[#This Row],[A Capital Returned]]+WaterfallTable[[#This Row],[A Residual]] -> 0 | L12: =IF(WaterfallTable[[#This Row],[Year]]=0,ClassBCapital,INDEX(WaterfallTable[B End Capital],MATCH(WaterfallTable[[#This Row],[Year]]-1,WaterfallTable[Year],0))) -> 275692.95 | M12: =IF(WaterfallTable[[#This Row],[Year]]=0,0,IF(ClassBReturnPriority=1,MIN(MAX(0,WaterfallTable[[#This Row],[Cash Available]]-WaterfallTable[[#This Row],[Pref Paid]]-WaterfallTable[[#This Row],[A Capital Returned]]),WaterfallTable[[#This Row],[B Capital]]),0)) -> 25250.482 | N12: =WaterfallTable[[#This Row],[B Capital]]-WaterfallTable[[#This Row],[B Capital Returned]] -> 250442.47 | O12: =IF(WaterfallTable[[#This Row],[Year]]=0,0,MAX(0,WaterfallTable[[#This Row],[Cash Available]]-WaterfallTable[[#This Row],[Pref Paid]]-WaterfallTable[[#This Row],[A Capital Returned]]-WaterfallTable[[#This Row],[B Capital Returned]])*ClassBResidualShare) -> 0 | P12: =WaterfallTable[[#This Row],[B Capital Returned]]+WaterfallTable[[#This Row],[B Residual]] -> 25250.482 | Q12: =IF(WaterfallTable[[#This Row],[Year]]=0,SponsorPropertyPayment,0) -> 0 | R12: =IF(WaterfallTable[[#This Row],[Year]]=0,0,MAX(0,WaterfallTable[[#This Row],[Cash Available]]-WaterfallTable[[#This Row],[Pref Paid]]-WaterfallTable[[#This Row],[A Capital Returned]]-WaterfallTable[[#This Row],[B Capital Returned]])*SponsorResidualShare) -> 0 | S12: =WaterfallTable[[#This Row],[Property Payment]]+WaterfallTable[[#This Row],[Residual]] -> 0
A13: 9 | B13: =INDEX(AnnualModelTable[Cash Available Before Distributions],MATCH(WaterfallTable[[#This Row],[Year]],AnnualModelTable[Year],0)) -> 25250.482 | C13: =IF(WaterfallTable[[#This Row],[Year]]=0,0,INDEX(WaterfallTable[A End Accrued Pref],MATCH(WaterfallTable[[#This Row],[Year]]-1,WaterfallTable[Year],0))) -> 0 | D13: =WaterfallTable[[#This Row],[Capital]]*ClassAPreferredReturn -> 0 | E13: =IF(WaterfallTable[[#This Row],[Year]]=0,0,MIN(WaterfallTable[[#This Row],[Cash Available]],WaterfallTable[[#This Row],[Beg Pref Accrued]]+WaterfallTable[[#This Row],[Pref Accrued]])) -> 0 | F13: =IF(WaterfallTable[[#This Row],[Year]]=0,ClassACapital,INDEX(WaterfallTable[A End Capital],MATCH(WaterfallTable[[#This Row],[Year]]-1,WaterfallTable[Year],0))) -> 0 | G13: =IF(WaterfallTable[[#This Row],[Year]]=0,0,MIN(MAX(0,WaterfallTable[[#This Row],[Cash Available]]-WaterfallTable[[#This Row],[Pref Paid]]),WaterfallTable[[#This Row],[Capital]])) -> 0 | H13: =WaterfallTable[[#This Row],[Beg Pref Accrued]]+WaterfallTable[[#This Row],[Pref Accrued]]-WaterfallTable[[#This Row],[Pref Paid]] -> 0 | I13: =WaterfallTable[[#This Row],[Capital]]-WaterfallTable[[#This Row],[A Capital Returned]] -> 0 | J13: =IF(WaterfallTable[[#This Row],[Year]]=0,0,MAX(0,WaterfallTable[[#This Row],[Cash Available]]-WaterfallTable[[#This Row],[Pref Paid]]-WaterfallTable[[#This Row],[A Capital Returned]]-WaterfallTable[[#This Row],[B Capital Returned]])*ClassAResidualShare) -> 0 | K13: =WaterfallTable[[#This Row],[Pref Paid]]+WaterfallTable[[#This Row],[A Capital Returned]]+WaterfallTable[[#This Row],[A Residual]] -> 0 | L13: =IF(WaterfallTable[[#This Row],[Year]]=0,ClassBCapital,INDEX(WaterfallTable[B End Capital],MATCH(WaterfallTable[[#This Row],[Year]]-1,WaterfallTable[Year],0))) -> 250442.47 | M13: =IF(WaterfallTable[[#This Row],[Year]]=0,0,IF(ClassBReturnPriority=1,MIN(MAX(0,WaterfallTable[[#This Row],[Cash Available]]-WaterfallTable[[#This Row],[Pref Paid]]-WaterfallTable[[#This Row],[A Capital Returned]]),WaterfallTable[[#This Row],[B Capital]]),0)) -> 25250.482 | N13: =WaterfallTable[[#This Row],[B Capital]]-WaterfallTable[[#This Row],[B Capital Returned]] -> 225191.98 | O13: =IF(WaterfallTable[[#This Row],[Year]]=0,0,MAX(0,WaterfallTable[[#This Row],[Cash Available]]-WaterfallTable[[#This Row],[Pref Paid]]-WaterfallTable[[#This Row],[A Capital Returned]]-WaterfallTable[[#This Row],[B Capital Returned]])*ClassBResidualShare) -> 0 | P13: =WaterfallTable[[#This Row],[B Capital Returned]]+WaterfallTable[[#This Row],[B Residual]] -> 25250.482 | Q13: =IF(WaterfallTable[[#This Row],[Year]]=0,SponsorPropertyPayment,0) -> 0 | R13: =IF(WaterfallTable[[#This Row],[Year]]=0,0,MAX(0,WaterfallTable[[#This Row],[Cash Available]]-WaterfallTable[[#This Row],[Pref Paid]]-WaterfallTable[[#This Row],[A Capital Returned]]-WaterfallTable[[#This Row],[B Capital Returned]])*SponsorResidualShare) -> 0 | S13: =WaterfallTable[[#This Row],[Property Payment]]+WaterfallTable[[#This Row],[Residual]] -> 0
A14: 10 | B14: =INDEX(AnnualModelTable[Cash Available Before Distributions],MATCH(WaterfallTable[[#This Row],[Year]],AnnualModelTable[Year],0)) -> 1183926.3 | C14: =IF(WaterfallTable[[#This Row],[Year]]=0,0,INDEX(WaterfallTable[A End Accrued Pref],MATCH(WaterfallTable[[#This Row],[Year]]-1,WaterfallTable[Year],0))) -> 0 | D14: =WaterfallTable[[#This Row],[Capital]]*ClassAPreferredReturn -> 0 | E14: =IF(WaterfallTable[[#This Row],[Year]]=0,0,MIN(WaterfallTable[[#This Row],[Cash Available]],WaterfallTable[[#This Row],[Beg Pref Accrued]]+WaterfallTable[[#This Row],[Pref Accrued]])) -> 0 | F14: =IF(WaterfallTable[[#This Row],[Year]]=0,ClassACapital,INDEX(WaterfallTable[A End Capital],MATCH(WaterfallTable[[#This Row],[Year]]-1,WaterfallTable[Year],0))) -> 0 | G14: =IF(WaterfallTable[[#This Row],[Year]]=0,0,MIN(MAX(0,WaterfallTable[[#This Row],[Cash Available]]-WaterfallTable[[#This Row],[Pref Paid]]),WaterfallTable[[#This Row],[Capital]])) -> 0 | H14: =WaterfallTable[[#This Row],[Beg Pref Accrued]]+WaterfallTable[[#This Row],[Pref Accrued]]-WaterfallTable[[#This Row],[Pref Paid]] -> 0 | I14: =WaterfallTable[[#This Row],[Capital]]-WaterfallTable[[#This Row],[A Capital Returned]] -> 0 | J14: =IF(WaterfallTable[[#This Row],[Year]]=0,0,MAX(0,WaterfallTable[[#This Row],[Cash Available]]-WaterfallTable[[#This Row],[Pref Paid]]-WaterfallTable[[#This Row],[A Capital Returned]]-WaterfallTable[[#This Row],[B Capital Returned]])*ClassAResidualShare) -> 192280.98 | K14: =WaterfallTable[[#This Row],[Pref Paid]]+WaterfallTable[[#This Row],[A Capital Returned]]+WaterfallTable[[#This Row],[A Residual]] -> 192280.98 | L14: =IF(WaterfallTable[[#This Row],[Year]]=0,ClassBCapital,INDEX(WaterfallTable[B End Capital],MATCH(WaterfallTable[[#This Row],[Year]]-1,WaterfallTable[Year],0))) -> 225191.98 | M14: =IF(WaterfallTable[[#This Row],[Year]]=0,0,IF(ClassBReturnPriority=1,MIN(MAX(0,WaterfallTable[[#This Row],[Cash Available]]-WaterfallTable[[#This Row],[Pref Paid]]-WaterfallTable[[#This Row],[A Capital Returned]]),WaterfallTable[[#This Row],[B Capital]]),0)) -> 225191.98 | N14: =WaterfallTable[[#This Row],[B Capital]]-WaterfallTable[[#This Row],[B Capital Returned]] -> 0 | O14: =IF(WaterfallTable[[#This Row],[Year]]=0,0,MAX(0,WaterfallTable[[#This Row],[Cash Available]]-WaterfallTable[[#This Row],[Pref Paid]]-WaterfallTable[[#This Row],[A Capital Returned]]-WaterfallTable[[#This Row],[B Capital Returned]])*ClassBResidualShare) -> 382959.62 | P14: =WaterfallTable[[#This Row],[B Capital Returned]]+WaterfallTable[[#This Row],[B Residual]] -> 608151.61 | Q14: =IF(WaterfallTable[[#This Row],[Year]]=0,SponsorPropertyPayment,0) -> 0 | R14: =IF(WaterfallTable[[#This Row],[Year]]=0,0,MAX(0,WaterfallTable[[#This Row],[Cash Available]]-WaterfallTable[[#This Row],[Pref Paid]]-WaterfallTable[[#This Row],[A Capital Returned]]-WaterfallTable[[#This Row],[B Capital Returned]])*SponsorResidualShare) -> 383493.74 | S14: =WaterfallTable[[#This Row],[Property Payment]]+WaterfallTable[[#This Row],[Residual]] -> 383493.74
A16: Returns Summary
A18: Participant | B18: Capital / Basis | C18: IRR | D18: Year 0 | E18: Year 1 | F18: Year 2 | G18: Year 3 | H18: Year 4 | I18: Year 5 | J18: Year 6 | K18: Year 7 | L18: Year 8 | M18: Year 9 | N18: Year 10 | O18: Total Profit | P18: Total Distributions | Q18: Equity Multiple | R18: ROI %
A19: Class A | B19: =ClassACapital -> 300000 | C19: =IFERROR(IRR(ReturnsTable[[#This Row],[Year 0]:[Year 10]]),0) -> 0.18840981 | D19: =-ReturnsTable[[#This Row],[Capital / Basis]] -> -300000 | E19: =INDEX(WaterfallTable[A Total Dist],MATCH(1,WaterfallTable[Year],0)) -> 17868 | F19: =INDEX(WaterfallTable[A Total Dist],MATCH(2,WaterfallTable[Year],0)) -> 354132 | G19: =INDEX(WaterfallTable[A Total Dist],MATCH(3,WaterfallTable[Year],0)) -> 0 | H19: =INDEX(WaterfallTable[A Total Dist],MATCH(4,WaterfallTable[Year],0)) -> 0 | I19: =INDEX(WaterfallTable[A Total Dist],MATCH(5,WaterfallTable[Year],0)) -> 0 | J19: =INDEX(WaterfallTable[A Total Dist],MATCH(6,WaterfallTable[Year],0)) -> 0 | K19: =INDEX(WaterfallTable[A Total Dist],MATCH(7,WaterfallTable[Year],0)) -> 0 | L19: =INDEX(WaterfallTable[A Total Dist],MATCH(8,WaterfallTable[Year],0)) -> 0 | M19: =INDEX(WaterfallTable[A Total Dist],MATCH(9,WaterfallTable[Year],0)) -> 0 | N19: =INDEX(WaterfallTable[A Total Dist],MATCH(10,WaterfallTable[Year],0)) -> 192280.98 | O19: =SUM(ReturnsTable[[#This Row],[Year 0]:[Year 10]]) -> 264280.98 | P19: =ReturnsTable[[#This Row],[Total Profit]]+ReturnsTable[[#This Row],[Capital / Basis]] -> 564280.98 | Q19: =IFERROR(ReturnsTable[[#This Row],[Total Distributions]]/ReturnsTable[[#This Row],[Capital / Basis]],0) -> 1.8809366 | R19: =IFERROR(ReturnsTable[[#This Row],[Total Profit]]/ReturnsTable[[#This Row],[Capital / Basis]],0) -> 0.8809366
A20: Class B | B20: =ClassBCapital -> 597500 | C20: =IFERROR(IRR(ReturnsTable[[#This Row],[Year 0]:[Year 10]]),0) -> 0.070343274 | D20: =-ReturnsTable[[#This Row],[Capital / Basis]] -> -597500 | E20: =INDEX(WaterfallTable[B Total Dist],MATCH(1,WaterfallTable[Year],0)) -> 0 | F20: =INDEX(WaterfallTable[B Total Dist],MATCH(2,WaterfallTable[Year],0)) -> 195554.64 | G20: =INDEX(WaterfallTable[B Total Dist],MATCH(3,WaterfallTable[Year],0)) -> 25250.482 | H20: =INDEX(WaterfallTable[B Total Dist],MATCH(4,WaterfallTable[Year],0)) -> 25250.482 | I20: =INDEX(WaterfallTable[B Total Dist],MATCH(5,WaterfallTable[Year],0)) -> 25250.482 | J20: =INDEX(WaterfallTable[B Total Dist],MATCH(6,WaterfallTable[Year],0)) -> 25250.482 | K20: =INDEX(WaterfallTable[B Total Dist],MATCH(7,WaterfallTable[Year],0)) -> 25250.482 | L20: =INDEX(WaterfallTable[B Total Dist],MATCH(8,WaterfallTable[Year],0)) -> 25250.482 | M20: =INDEX(WaterfallTable[B Total Dist],MATCH(9,WaterfallTable[Year],0)) -> 25250.482 | N20: =INDEX(WaterfallTable[B Total Dist],MATCH(10,WaterfallTable[Year],0)) -> 608151.61 | O20: =SUM(ReturnsTable[[#This Row],[Year 0]:[Year 10]]) -> 382959.62 | P20: =ReturnsTable[[#This Row],[Total Profit]]+ReturnsTable[[#This Row],[Capital / Basis]] -> 980459.62 | Q20: =IFERROR(ReturnsTable[[#This Row],[Total Distributions]]/ReturnsTable[[#This Row],[Capital / Basis]],0) -> 1.6409366 | R20: =IFERROR(ReturnsTable[[#This Row],[Total Profit]]/ReturnsTable[[#This Row],[Capital / Basis]],0) -> 0.6409366
A21: Sponsor | B21: =SponsorBasis -> 150000 | C21: =IFERROR(IRR(ReturnsTable[[#This Row],[Year 0]:[Year 10]]),0) -> 0 | D21: =INDEX(WaterfallTable[Total Dist],MATCH(0,WaterfallTable[Year],0)) -> 150000 | E21: =INDEX(WaterfallTable[Total Dist],MATCH(1,WaterfallTable[Year],0)) -> 0 | F21: =INDEX(WaterfallTable[Total Dist],MATCH(2,WaterfallTable[Year],0)) -> 0 | G21: =INDEX(WaterfallTable[Total Dist],MATCH(3,WaterfallTable[Year],0)) -> 0 | H21: =INDEX(WaterfallTable[Total Dist],MATCH(4,WaterfallTable[Year],0)) -> 0 | I21: =INDEX(WaterfallTable[Total Dist],MATCH(5,WaterfallTable[Year],0)) -> 0 | J21: =INDEX(WaterfallTable[Total Dist],MATCH(6,WaterfallTable[Year],0)) -> 0 | K21: =INDEX(WaterfallTable[Total Dist],MATCH(7,WaterfallTable[Year],0)) -> 0 | L21: =INDEX(WaterfallTable[Total Dist],MATCH(8,WaterfallTable[Year],0)) -> 0 | M21: =INDEX(WaterfallTable[Total Dist],MATCH(9,WaterfallTable[Year],0)) -> 0 | N21: =INDEX(WaterfallTable[Total Dist],MATCH(10,WaterfallTable[Year],0)) -> 383493.74 | O21: =SUM(ReturnsTable[[#This Row],[Year 0]:[Year 10]]) -> 533493.74 | P21: =ReturnsTable[[#This Row],[Total Profit]]+ReturnsTable[[#This Row],[Capital / Basis]] -> 683493.74 | Q21: =IFERROR(ReturnsTable[[#This Row],[Total Distributions]]/ReturnsTable[[#This Row],[Capital / Basis]],0) -> 4.5566249 | R21: =IFERROR(ReturnsTable[[#This Row],[Total Profit]]/ReturnsTable[[#This Row],[Capital / Basis]],0) -> 3.5566249
A22: Management | B22: =0 -> 0 | C22: =0 -> 0 | D22: =0 -> 0 | E22: =ManagementFeeRate*INDEX(AnnualModelTable[Effective Gross Income],MATCH(1,AnnualModelTable[Year],0)) -> 3168 | F22: =ManagementFeeRate*INDEX(AnnualModelTable[Effective Gross Income],MATCH(2,AnnualModelTable[Year],0)) -> 7231.68 | G22: =ManagementFeeRate*INDEX(AnnualModelTable[Effective Gross Income],MATCH(3,AnnualModelTable[Year],0)) -> 8035.2 | H22: =ManagementFeeRate*INDEX(AnnualModelTable[Effective Gross Income],MATCH(4,AnnualModelTable[Year],0)) -> 8035.2 | I22: =ManagementFeeRate*INDEX(AnnualModelTable[Effective Gross Income],MATCH(5,AnnualModelTable[Year],0)) -> 8035.2 | J22: =ManagementFeeRate*INDEX(AnnualModelTable[Effective Gross Income],MATCH(6,AnnualModelTable[Year],0)) -> 8035.2 | K22: =ManagementFeeRate*INDEX(AnnualModelTable[Effective Gross Income],MATCH(7,AnnualModelTable[Year],0)) -> 8035.2 | L22: =ManagementFeeRate*INDEX(AnnualModelTable[Effective Gross Income],MATCH(8,AnnualModelTable[Year],0)) -> 8035.2 | M22: =ManagementFeeRate*INDEX(AnnualModelTable[Effective Gross Income],MATCH(9,AnnualModelTable[Year],0)) -> 8035.2 | N22: =ManagementFeeRate*INDEX(AnnualModelTable[Effective Gross Income],MATCH(10,AnnualModelTable[Year],0)) -> 8035.2 | O22: =SUM(ReturnsTable[[#This Row],[Year 0]:[Year 10]]) -> 74681.28 | P22: =ReturnsTable[[#This Row],[Total Profit]] -> 74681.28 | Q22: =0 -> 0 | R22: =0 -> 0

Sheet Returns
A1: Legacy Returns sheet retained for reference. Primary ReturnsTable is now on the Waterfall tab.
A3: Participant | B3: Capital / Basis | C3: Total Distributions | D3: Net Profit | E3: Equity Multiple | F3: ROI % | G3: IRR | H3: Year 0 | I3: Year 1 | J3: Year 2 | K3: Year 3 | L3: Year 4 | M3: Year 5 | N3: Year 6 | O3: Year 7 | P3: Year 8 | Q3: Year 9 | R3: Year 10
A4: Class A | B4: =ClassACapital -> 300000 | C4: =SUM(Waterfall!$K$4:$K$14) -> 564280.98 | D4: =C4-B4 -> 264280.98 | E4: =IFERROR(C4/B4,0) -> 1.8809366 | F4: =IFERROR(D4/B4,0) -> 0.8809366 | G4: =IRR(H4:R4) -> 0.18840981 | H4: =-B4 -> -300000 | I4: =INDEX(Waterfall!$K$4:$K$14,MATCH(1,Waterfall!$A$4:$A$14,0)) -> 17868 | J4: =INDEX(Waterfall!$K$4:$K$14,MATCH(2,Waterfall!$A$4:$A$14,0)) -> 354132 | K4: =INDEX(Waterfall!$K$4:$K$14,MATCH(3,Waterfall!$A$4:$A$14,0)) -> 0 | L4: =INDEX(Waterfall!$K$4:$K$14,MATCH(4,Waterfall!$A$4:$A$14,0)) -> 0 | M4: =INDEX(Waterfall!$K$4:$K$14,MATCH(5,Waterfall!$A$4:$A$14,0)) -> 0 | N4: =INDEX(Waterfall!$K$4:$K$14,MATCH(6,Waterfall!$A$4:$A$14,0)) -> 0 | O4: =INDEX(Waterfall!$K$4:$K$14,MATCH(7,Waterfall!$A$4:$A$14,0)) -> 0 | P4: =INDEX(Waterfall!$K$4:$K$14,MATCH(8,Waterfall!$A$4:$A$14,0)) -> 0 | Q4: =INDEX(Waterfall!$K$4:$K$14,MATCH(9,Waterfall!$A$4:$A$14,0)) -> 0 | R4: =INDEX(Waterfall!$K$4:$K$14,MATCH(10,Waterfall!$A$4:$A$14,0)) -> 192280.98
A5: Class B | B5: =ClassBCapital -> 597500 | C5: =SUM(Waterfall!$P$4:$P$14) -> 980459.62 | D5: =C5-B5 -> 382959.62 | E5: =IFERROR(C5/B5,0) -> 1.6409366 | F5: =IFERROR(D5/B5,0) -> 0.6409366 | G5: =IFERROR(IRR(H5:R5),0) -> 0.070343274 | H5: =-B5 -> -597500 | I5: =INDEX(Waterfall!$P$4:$P$14,MATCH(1,Waterfall!$A$4:$A$14,0)) -> 0 | J5: =INDEX(Waterfall!$P$4:$P$14,MATCH(2,Waterfall!$A$4:$A$14,0)) -> 195554.64 | K5: =INDEX(Waterfall!$P$4:$P$14,MATCH(3,Waterfall!$A$4:$A$14,0)) -> 25250.482 | L5: =INDEX(Waterfall!$P$4:$P$14,MATCH(4,Waterfall!$A$4:$A$14,0)) -> 25250.482 | M5: =INDEX(Waterfall!$P$4:$P$14,MATCH(5,Waterfall!$A$4:$A$14,0)) -> 25250.482 | N5: =INDEX(Waterfall!$P$4:$P$14,MATCH(6,Waterfall!$A$4:$A$14,0)) -> 25250.482 | O5: =INDEX(Waterfall!$P$4:$P$14,MATCH(7,Waterfall!$A$4:$A$14,0)) -> 25250.482 | P5: =INDEX(Waterfall!$P$4:$P$14,MATCH(8,Waterfall!$A$4:$A$14,0)) -> 25250.482 | Q5: =INDEX(Waterfall!$P$4:$P$14,MATCH(9,Waterfall!$A$4:$A$14,0)) -> 25250.482 | R5: =INDEX(Waterfall!$P$4:$P$14,MATCH(10,Waterfall!$A$4:$A$14,0)) -> 608151.61
A6: Sponsor | B6: =SponsorBasis -> 150000 | C6: =SUM(Waterfall!$S$4:$S$14) -> 533493.74 | D6: =C6-B6 -> 383493.74 | E6: =IFERROR(C6/B6,0) -> 3.5566249 | F6: =IFERROR(D6/B6,0) -> 2.5566249 | G6: =IFERROR(IRR(H6:R6),0) -> 0.098415623 | H6: =-B6 -> -150000 | I6: =INDEX(Waterfall!$S$4:$S$14,MATCH(1,Waterfall!$A$4:$A$14,0)) -> 0 | J6: =INDEX(Waterfall!$S$4:$S$14,MATCH(2,Waterfall!$A$4:$A$14,0)) -> 0 | K6: =INDEX(Waterfall!$S$4:$S$14,MATCH(3,Waterfall!$A$4:$A$14,0)) -> 0 | L6: =INDEX(Waterfall!$S$4:$S$14,MATCH(4,Waterfall!$A$4:$A$14,0)) -> 0 | M6: =INDEX(Waterfall!$S$4:$S$14,MATCH(5,Waterfall!$A$4:$A$14,0)) -> 0 | N6: =INDEX(Waterfall!$S$4:$S$14,MATCH(6,Waterfall!$A$4:$A$14,0)) -> 0 | O6: =INDEX(Waterfall!$S$4:$S$14,MATCH(7,Waterfall!$A$4:$A$14,0)) -> 0 | P6: =INDEX(Waterfall!$S$4:$S$14,MATCH(8,Waterfall!$A$4:$A$14,0)) -> 0 | Q6: =INDEX(Waterfall!$S$4:$S$14,MATCH(9,Waterfall!$A$4:$A$14,0)) -> 0 | R6: =INDEX(Waterfall!$S$4:$S$14,MATCH(10,Waterfall!$A$4:$A$14,0)) -> 383493.74
A9: Important | B9: Class A preferred return is modeled as cumulative simple annual accrual on unrecovered Class A capital. After Class A and Class B capital are returned, Sponsor receives the editable Sponsor residual share. Class A and Class B split the remaining residual in proportion to their capital.

Sheet Notes
A1: Model Notes
A3: Purpose | B3: Calculates project-level cash available, then allocates distributions to Class A, Class B, and Sponsor through a simplified waterfall.
A4: Key editable cells | B4: Use the Assumptions tab, column B.
A5: Class A | B5: Modeled with 8% cumulative annual preferred return by default, then return of capital, then no residual share unless you revise the waterfall.
A6: Class B | B6: Modeled as subordinate capital that can receive capital back before residual distributions, plus residual participation.
A7: Sponsor | B7: Modeled using sponsor basis / deemed investment as the return denominator and sponsor residual share as the distribution source.
A8: Caution | B8: This workbook is for planning and discussion only. It is not legal, tax, securities, appraisal, or investment advice. Have counsel and CPA review before investor use.

Sheet Cost Analysis
A1: 3325 Banks Rd - Design, Development & Build Cost Analysis
A2: Status | B2: Planning estimate added 2026-05-11
A3: Source Markdown | B3: 04_Design_Development_and_Build_Cost_Analysis.md
B6: Select Scenario: | C6: Low
A7: Project Cost Case Summary | B7: Low | C7: High | E7: Case Selection | G7: =$C$6="Low" -> TRUE | H7: =$C$6="High" -> FALSE
A8: Sponsor-Controlled Case (from controlling bridge below) | B8: =B27 -> 897500 | C8: =C27 -> 1635000 | E8: Sponsor-Controlled | H8: =$E$8="Sponsor-Controlled" -> TRUE
A9: Outside-Market Benchmark (from outside-market subtotals below) | B9: =B41+B50+B59 -> 1880000 | C9: =C41+C50+C59 -> 4160000 | H9: =$E$8="Outside-Market Benchmark" -> FALSE
A10: Selected Total Project Cost | B10: =IF($C$6="Low",IF($E$8="Sponsor-Controlled",B8,B9),"") -> 897500 | C10: =IF($C$6="High",IF($E$8="Sponsor-Controlled",C8,C9),"") | G10: =IF($C$6="Low",B10,C10) -> 897500
A12: Selected Cost Metrics | B12: Low Case | C12: High Case
A14: Cost per SF at 5,000 SF | B14: =$G$10/5000 -> 179.5
A15: Cost per SF at 6,000 SF | B15: =$G$10/6000 -> 149.58333
A17: Controlling Sponsor-Controlled Line-Item Bridge | B17: Low | C17: High
A18: Sponsor property payment | B18: =SponsorPropertyPayment -> 150000 | C18: =SponsorPropertyPayment -> 150000
A19: Design, entitlement, permits, and professional services | B19: 75000 | C19: 175000
A20: Development, financing, carrying, and administration | B20: 40000 | C20: 100000
A21: Construction-period insurance | B21: 7500 | C21: 10000
A22: Post-frame building shell and interior buildout | B22: 390000 | C22: 610000
A23: Sitework, access, grading, drainage, and parking | B23: 55000 | C23: 110000
A24: Private utilities, well, wastewater, and related infrastructure | B24: 90000 | C24: 225000
A25: Furnishings, fixtures, equipment, and turnover | B25: 30000 | C25: 100000
A26: Contingency and owner reserve | B26: 60000 | C26: 155000
A27: Sponsor-Controlled Total Package | B27: =SUM(B18:B26) -> 897500 | C27: =SUM(C18:C26) -> 1635000
A28: Funding Gap Analysis | B28: Selected
A29: Estimated total project cost | B29: =SelectedProjectCost -> 897500
A30: Class A + Class B capitalization | B30: =ClassACapital+ClassBCapital -> 897500
A31: Potential unfunded development gap | B31: =MAX(0,B29-B30) -> 0
A33: Outside Market - Design & Entitlement Detail | B33: Low | C33: High
A34: Architecture and building design | B34: 35000 | C34: 90000
A35: Civil engineering and site planning | B35: 20000 | C35: 60000
A36: Septic, soil, and wastewater engineering | B36: 20000 | C36: 90000
A37: Survey, testing, environmental, and due diligence | B37: 10000 | C37: 30000
A38: Permitting, review, and municipal/county coordination | B38: 15000 | C38: 50000
A39: Legal, accounting, and trust structuring | B39: 15000 | C39: 40000
A40: Design/entitlement contingency | B40: 15000 | C40: 45000
A41: Design & entitlement total | B41: =SUM(B34:B40) -> 130000 | C41: =SUM(C34:C40) -> 405000
A43: Outside Market - Development & Pre-Construction Detail | B43: Low | C43: High
A44: Development management / sponsor fee | B44: 50000 | C44: 150000
A45: Financing, lender, appraisal, and closing costs | B45: 40000 | C45: 120000
A46: Insurance, taxes, utilities, and carrying costs | B46: 25000 | C46: 75000
A47: Accounting, administration, and reporting | B47: 10000 | C47: 30000
A48: Leasing, operations setup, and launch costs | B48: 20000 | C48: 60000
A49: Development contingency / liquidity reserve | B49: 40000 | C49: 125000
A50: Development & pre-construction total | B50: =SUM(B44:B49) -> 185000 | C50: =SUM(C44:C49) -> 560000
A52: Outside Market - Build & Delivery Detail | B52: Low | C52: High
A53: Building construction, 5,000-6,000 SF | B53: 1125000 | C53: 1950000
A54: Sitework, grading, access, parking, and drainage | B54: 125000 | C54: 350000
A55: Private utilities and well infrastructure | B55: 35000 | C55: 125000
A56: Engineered onsite wastewater system | B56: 75000 | C56: 300000
A57: Furnishings, fixtures, equipment, and turnover | B57: 60000 | C57: 180000
A58: Construction contingency | B58: 145000 | C58: 290000
A59: Build & delivery total | B59: =SUM(B53:B58) -> 1565000 | C59: =SUM(C53:C58) -> 3195000
A61: Sponsor-Controlled Cost Justification
A62: Cost-positioning note | B62: 700,000-1,300,000 is a target range, not a guaranteed budget. It depends on post-frame construction, sponsor-owned equipment, sponsor-controlled crew capacity, disciplined finish scope, and avoiding a high-cost engineered wastewater outcome.
A65: Conditions Required To Support Target Range
A66: Post-frame approach accepted through design and permitting | B66: Yes | C66: Confirmed cost saver
A67: Sponsor can self-perform or directly manage meaningful construction scope | B67: Yes | C67: Confirmed cost saver
A68: Equipment ownership reduces sitework and construction logistics cost | B68: Yes | C68: Confirmed cost saver
A69: Major subcontracted trades are competitively bid | B69: Yes | C69: Confirmed cost saver
A70: Wastewater solution does not require a high-end engineered system | B70: No | C70: Not confirmed; risk reserve retained
A71: Suite count and bathroom/kitchenette count do not expand | B71: Yes | C71: Confirmed scope control
A72: Finish package stays durable and efficient rather than luxury | B72: Yes | C72: Confirmed finish discipline
A73: Project carries a disciplined contingency | B73: Yes | C73: Confirmed reserve discipline
A75: Risks That Could Break Target Range
A76: Advanced/high-cost wastewater system requirement | B76: Yes | C76: Confirmed risk; wastewater allowance increased
A77: Expensive fire, code, or occupancy upgrades | B77: No
A78: Higher-than-expected mechanical/electrical/plumbing scope | B78: No
A79: Extensive parking, drainage, or access improvements | B79: No
A80: Sponsor crew advantage limited by labor availability | B80: No
A81: Finish level moves closer to conventional apartment construction | B81: Yes | C81: Confirmed risk; FF&E/contingency allowance increased

Sheet Operating Expense Budget
A1: 3325 Banks Rd - Operating Expense Budget
A3: Toggle / Selection
A4: Use Calculated Budget Ratio? | C4: FALSE = use assumed ratio; TRUE = use calculated budget ratio | I4: FALSE
A5: Assumed Operating Expense Ratio | B5: 0.4 | C5: Current planning assumption reflected in Assumptions tab when toggle is FALSE
A6: Calculated Operating Expense Ratio | B6: =IFERROR(B36/B10,0) -> 0.62987546 | C6: Total annual operating expense budget / effective gross income
A7: Selected Operating Expense Ratio | B7: =IF(I4,B6,B5) -> 0.4 | C7: Feeds Assumptions!B15
A9: Revenue Basis
A10: Stabilized Effective Gross Income | B10: =StabilizedMonthlyGrossRent*12*StabilizedOccupancy -> 117552 | C10: Annual stabilized EGI after occupancy
A12: Expense Category | B12: Annual Amount | C12: Basis / Notes
A13: Property taxes | B13: 7000 | C13: Placeholder; replace with assessed value/tax estimate
A14: Completed property insurance | B14: 4350 | C14: Post-completion hazard/liability coverage estimate; excludes construction-period insurance
A15: Property management / administration | B15: =D15*B10 -> 7053.12 | C15: 6% of stabilized effective gross income (EGI) | D15: 0.06
A16: Utilities - electric | B16: 15000 | C16: Owner-paid/common-area and vacancy exposure
A17: Utilities - water / well maintenance | B17: 500 | C17: Well testing, maintenance, treatment allowance
A18: Utilities - internet | B18: 2400 | C18: Shared/furnished rental expectation
A19: Trash / recycling | B19: 1800 | C19: Recurring service
A20: Repairs and maintenance | B20: 9000 | C20: Routine R&M reserve
A21: Turnover, cleaning, and supplies | B21: =200*8 -> 1600 | C21: Co-living/furnished turnover allowance
A22: Landscaping / grounds | B22: 3600 | C22: Mowing, upkeep, seasonal cleanup
A23: Pest control | B23: 1200 | C23: Recurring service
A24: Septic / wastewater maintenance | B24: 3000 | C24: Inspection, pump, service contracts
A25: CapEx / replacement reserve | B25: 4000 | C25: Furniture, fixtures, equipment, building reserves
A26: Marketing / leasing | B26: 0 | C26: Listings, tenant placement, materials
A27: Bookkeeping / accounting | B27: =120*12 -> 1440 | C27: Operating accounting/reporting
A28: Legal / compliance | C28: Lease forms, notices, compliance allowance
A29: Licenses, permits, inspections | B29: 1200 | C29: Recurring local/regulatory allowance
A30: Security / access control | C30: Locks, cameras, access systems, monitoring
A31: Common area furnishings replacement | B31: 2400 | C31: Shared space replacement reserve
A32: Laundry equipment maintenance | B32: 1200 | C32: Repair/replacement allowance
A33: Snow/ice/storm cleanup reserve | B33: 800 | C33: Weather/event allowance
A34: Bad debt / collections | B34: 2500 | C34: Collection loss allowance
A35: Miscellaneous / operating contingency | B35: 4000 | C35: Catch-all reserve
A36: Total Annual Operating Expense Budget | B36: =SUM(B13:B35) -> 74043.12 | C36: Calculated from line items
