Workbook
Name AnnualManagementFee: 'Operating Expense Budget'!$B$15
Name AssumedOperatingExpenseRatio: 'Operating Expense Budget'!$B$5
Name CalculatedOperatingExpenseRatio: 'Operating Expense Budget'!$B$6
Name ClassACapital: Assumptions!$B$39
Name ClassAPreferredReturn: Assumptions!$B$40
Name ClassAResidualShare: Assumptions!$B$44
Name ClassBCapital: Assumptions!$B$41
Name ClassBResidualShare: Assumptions!$B$45
Name ClassBReturnPriority: Assumptions!$B$42
Name CoLivingSuiteRent: Assumptions!$B$11
Name CoLivingSuiteRentHigh: Assumptions!$G$10
Name CoLivingSuiteRentLow: Assumptions!$E$10
Name CoLivingSuiteRentMedium: Assumptions!$F$10
Name CoLivingSuites: Assumptions!$B$10
Name ExistingDebtServiceAnnual: Assumptions!$B$28
Name ExistingFirstMortgage: Assumptions!$B$20
Name ExistingFirstMortgageAnnualPayment: Assumptions!$B$26
Name ExistingFirstMortgageMonthlyPI: Assumptions!$B$25
Name ExistingFirstMortgagePrincipal: Assumptions!$B$20
Name ExistingFirstMortgageRate: Assumptions!$B$21
Name ExitCapRate: Assumptions!$B$35
Name LeaseUpOccupancy: Assumptions!$B$14
Name ManagementFeeRate: 'Operating Expense Budget'!$D$15
Name NOIGrowth: Assumptions!$B$16
Name OperatingExpenseRatio: Assumptions!$B$15
Name OtherMonthlyIncome: Assumptions!$B$12
Name PermanentLoanAmortizationYears: Assumptions!$B$34
Name PermanentLoanAmount: Assumptions!$B$30
Name PermanentLoanRate: Assumptions!$B$33
Name PremiumSuiteRent: Assumptions!$B$9
Name PremiumSuiteRentHigh: Assumptions!$G$9
Name PremiumSuiteRentLow: Assumptions!$E$9
Name PremiumSuiteRentMedium: Assumptions!$F$9
Name PremiumSuites: Assumptions!$B$8
Name PrivateDebtAnnualInterestPayment: Assumptions!$B$27
Name PrivateDebtInterestRate: Assumptions!$B$23
Name PrivateDebtPrincipal: Assumptions!$B$22
Name ProjectDebtPayoffAtRefi: Assumptions!$B$24
Name RefinanceLoanAmortizationYears: Assumptions!$B$34
Name RefinanceLoanAmount: Assumptions!$B$30
Name RefinanceLoanRate: Assumptions!$B$33
Name RefinanceLoanToValueCap: Assumptions!$B$29
Name RefinanceProceedsAfterDebtAndClassA: Assumptions!$B$32
Name RefinanceProceedsAfterExistingDebt: Assumptions!$B$31
Name RentScenarioAverageMonthlyGross: Assumptions!$H$11
Name RentScenarioHighEffectiveYear: Assumptions!$G$12
Name RentScenarioHighMonthlyGross: Assumptions!$G$11
Name RentScenarioLowEffectiveYear: Assumptions!$E$12
Name RentScenarioLowMonthlyGross: Assumptions!$E$11
Name RentScenarioMediumEffectiveYear: Assumptions!$F$12
Name RentScenarioMediumMonthlyGross: Assumptions!$F$11
Name RepairsMaintenanceReserveTarget: 'Operating Expense Budget'!$B$20
Name SaleExitYear: Assumptions!$B$5
Name SelectedCostCase: 'Cost Analysis'!$E$8
Name SelectedCostCaseId: 'Cost Analysis'!$D$11
Name SelectedOperatingExpenseRatio: 'Operating Expense Budget'!$B$7
Name SelectedProjectCost: 'Cost Analysis'!$G$10
Name SelectedProjectCostHigh: 'Cost Analysis'!$C$10
Name SelectedProjectCostLow: 'Cost Analysis'!$B$10
Name SelectedScenario: 'Cost Analysis'!$C$6

Sheet Assumptions
A1: 3325 Banks Rd - Investor Return Model | C1: Editable inputs are in column B. Outputs update through formulas.
A3: Project Timing
A4: Stabilization / Refinance Year | B4: =MAX(1,MIN(10,SelectedWaterfallRefiOption)) -> 3 | C4: Model uses selected Waterfall refinance-year option button; helper cell Waterfall!R3; buttons shown for Years 1-10 only
A5: Sale / Exit Year | B5: =MAX(1,MIN(10,SelectedWaterfallExitOption)) -> 5 | C5: Model uses selected Waterfall exit-year option button; helper cell Waterfall!S3; buttons shown for Years 1-10 only
A7: Rental Program | D7: Rent Scenario Schedule
A8: First Floor Premium Suites | B8: 4 | C8: Private bed/bath/kitchenette suites | D8: Rent Input | E8: Low | F8: Medium | G8: High | H8: Average | I8: Current Use | J8: Notes
A9: Monthly Rent per Premium Suite | B9: 1600 | C9: Mid/base reference; Annual Model uses scenario schedule at right | D9: Premium Suite Rent | E9: 1350 | F9: 1600 | G9: 1750 | H9: =AVERAGE(E9:G9) -> 1566.6667 | I9: Rent levels increase left to right
A10: Second Floor Co-Living Suites | B10: 4 | C10: Private bed/bath with shared amenities | D10: Co-Living Suite Rent | E10: 850 | F10: 1100 | G10: 1250 | H10: =AVERAGE(E10:G10) -> 1066.6667 | I10: Rent levels increase left to right
A11: Monthly Rent per Co-Living Suite | B11: 1100 | C11: Mid/base reference; Annual Model uses scenario schedule at right | D11: Monthly Gross Rent | E11: =PremiumSuites*E9+CoLivingSuites*E10+OtherMonthlyIncome -> 8800 | F11: =PremiumSuites*F9+CoLivingSuites*F10+OtherMonthlyIncome -> 10800 | G11: =PremiumSuites*G9+CoLivingSuites*G10+OtherMonthlyIncome -> 12000 | H11: =AVERAGE(E11:G11) -> 10533.333 | I11: Average is reference only; model uses scenario schedule
A12: Other Monthly Income | B12: 0 | C12: Parking, utility fees, laundry, etc. | D12: Effective Year | E12: 1 | F12: 2 | G12: 3 | I12: Annual Model timing | J12: Low ends after Year 1 under current schedule
A13: Stabilized Occupancy | B13: 0.93 | C13: Before operating expense load
A14: Year 1 Lease-Up Occupancy | B14: 0.5 | C14: First partial operating year
A15: Selected Operating Expense Ratio | B15: =SelectedOperatingExpenseRatio -> 0.46912485 | C15: From Operating Expense Budget tab; toggle between assumed ratio and calculated budget ratio
A16: NOI Growth | B16: 0.03 | C16: Annual growth after stabilization
A17: Stabilized Monthly Gross Rent | B17: =IF(StabilizationRefiYear>=RentScenarioHighEffectiveYear,RentScenarioHighMonthlyGross,IF(StabilizationRefiYear>=RentScenarioMediumEffectiveYear,RentScenarioMediumMonthlyGross,IF(StabilizationRefiYear>=RentScenarioLowEffectiveYear,RentScenarioLowMonthlyGross,0))) -> 12000 | C17: Selected by Rent Scenario Schedule for the Stabilization / Refinance Year; average is reference only
A19: Debt / Refinance / Exit
A20: Existing First Mortgage Principal | B20: 119000 | C20: Existing first mortgage principal to be paid from refinance proceeds
A21: Existing First Mortgage Rate | B21: 0.0325 | C21: Interest rate on existing first mortgage
A22: Private Debt Principal | B22: 75000 | C22: Private debt principal; interest-only before payoff
A23: Private Debt Interest Rate | B23: 0.1 | C23: Interest-only private debt rate
A24: Total Existing Debt Payoff | B24: =_xlfn.SINGLE(ExistingFirstMortgagePrincipal)+PrivateDebtPrincipal -> 194000 | C24: Existing first mortgage principal plus private debt principal
A25: First Mortgage Monthly P&I Excl. Escrow | B25: 526 | C25: Actual monthly principal and interest payment; excludes escrow, taxes, and insurance
A26: First Mortgage Annual P&I Excl. Escrow | B26: =_xlfn.SINGLE(ExistingFirstMortgageMonthlyPI)*12 -> 6312 | C26: Annual principal and interest payment; excludes escrow, taxes, and insurance
A27: Private Debt Annual Interest Payment | B27: =PrivateDebtPrincipal*PrivateDebtInterestRate -> 7500 | C27: Interest-only payment on private debt
A28: Total Existing Annual Debt Service | B28: =ExistingFirstMortgageAnnualPayment+PrivateDebtAnnualInterestPayment -> 13812 | C28: Existing debt service before refinance; taxes and insurance remain in operating expenses
A29: Refinance Loan-to-Value Cap | B29: 0.7 | C29: Maximum refinance loan as % of stabilized value
A30: Refinance Loan Amount | B30: =MIN((StabilizedMonthlyGrossRent*12*StabilizedOccupancy*(1-OperatingExpenseRatio)*(1+NOIGrowth)/ExitCapRate)*RefinanceLoanToValueCap,TotalExistingDebt+ClassACapital+ClassBCapital) -> 732276.44 | C30: Only new loan; takeout/refinance proceeds, not development or construction debt
A31: Refi Proceeds After Existing Debt | B31: =MAX(0,RefinanceLoanAmount-TotalExistingDebt) -> 538276.44 | C31: Available to Class A first through waterfall
A32: Refi Remaining After Debt + Class A | B32: =MAX(0,RefinanceLoanAmount-TotalExistingDebt-ClassACapital) -> 238276.44 | C32: Indicative amount available to Class B before waterfall details
A33: Refinance Loan Interest Rate | B33: 0.065 | C33: Annual fixed rate on stabilization refinance loan
A34: Refinance Loan Amortization Years | B34: 30 | C34: Used for annual debt service after stabilization refinance
A35: Exit Cap Rate | B35: 0.07 | C35: Sale value = following year NOI / cap rate
A36: Selling Costs | B36: 0.02 | C36: Percent deducted from gross sale value
A38: Capital Stack / Waterfall
A39: Class A Capital | B39: 300000 | C39: Preferred capital raise
A40: Class A Preferred Return | B40: 0.08 | C40: Cumulative annual preferred return
A41: Class B Capital | B41: =MAX(0,SelectedProjectCost-ClassACapital) -> 597500 | C41: Subordinate beneficiary capital; dependent upon selected project cost in Cost Analysis
A42: Class B Capital Return Priority | B42: 1 | C42: 1 = return Class B capital before residual split
A43: Sponsor Residual Share | B43: 0.4 | C43: Editable sponsor share of residual after capital return priorities
A44: Class A Residual Share | B44: =(1-SponsorResidualShare)*(ClassACapital/(ClassACapital+ClassBCapital)) -> 0.2005571 | C44: Class A share of non-sponsor residual, proportional to Class A capital
A45: Class B Residual Share | B45: =(1-SponsorResidualShare)*(ClassBCapital/(ClassACapital+ClassBCapital)) -> 0.3994429 | C45: Class B share of non-sponsor residual, proportional to Class B capital
A46: Sponsor Property Payment / Basis | B46: 150000 | C46: Payment to Sponsor for property; also used as Sponsor basis for return analysis
A47: Sponsor Capital Investment | B47: 125000 | C47: Actual sponsor cash/cost invested; separate from property payment / basis
A48: Model Note | B48: This is a planning model, not tax, legal, securities, or investment advice.

Sheet Annual Model
A1: Annual Project Model
A3: Year | B3: Phase | C3: Gross Potential Rent | D3: Occupancy Effective Gross Income | E3: Operating Expenses | F3: NOI | G3: Debt Service | H3: Cash Before Refi/Sale | I3: Net Refi/Sale Proceeds | J3: Reserve Funding | K3: Reserve Balance | L3: Cash Available Before Distributions | M3: Waterfall Distributions | N3: Ending Cash Balance | O3: Loan Balance | P3: Property Value / Refi Value
A4: 0 | B4: Capitalization / Entitlement | C4: =IF(AnnualModelTable[[#This Row],[Year]]>SaleExitYear,0,IF(AnnualModelTable[[#This Row],[Year]]=0,0,IF(AnnualModelTable[[#This Row],[Year]]>=RentScenarioHighEffectiveYear,RentScenarioHighMonthlyGross*12,IF(AnnualModelTable[[#This Row],[Year]]>=RentScenarioMediumEffectiveYear,RentScenarioMediumMonthlyGross*12,IF(AnnualModelTable[[#This Row],[Year]]>=RentScenarioLowEffectiveYear,RentScenarioLowMonthlyGross*12,0))))) -> 0 | D4: =IF(AnnualModelTable[[#This Row],[Year]]>SaleExitYear,0,IF(AnnualModelTable[[#This Row],[Year]]=0,0,AnnualModelTable[[#This Row],[Gross Potential Rent]]*IF(AnnualModelTable[[#This Row],[Year]]=1,LeaseUpOccupancy,StabilizedOccupancy))) -> 0 | E4: =IF(AnnualModelTable[[#This Row],[Year]]>SaleExitYear,0,AnnualModelTable[[#This Row],[Occupancy Effective Gross Income]]*OperatingExpenseRatio) -> 0 | F4: =IF(AnnualModelTable[[#This Row],[Year]]>SaleExitYear,0,AnnualModelTable[[#This Row],[Occupancy Effective Gross Income]]-AnnualModelTable[[#This Row],[Operating Expenses]]) -> 0 | G4: =IF(AnnualModelTable[[#This Row],[Year]]>SaleExitYear,0,IF(AND(AnnualModelTable[[#This Row],[Year]]>=1,AnnualModelTable[[#This Row],[Year]]<StabilizationRefiYear),ExistingDebtServiceAnnual,IF(AND(AnnualModelTable[[#This Row],[Year]]>=StabilizationRefiYear,AnnualModelTable[[#This Row],[Year]]<=SaleExitYear),-PMT(RefinanceLoanRate/12,RefinanceLoanAmortizationYears*12,RefinanceLoanAmount)*12,0))) -> 0 | H4: =IF(AnnualModelTable[[#This Row],[Year]]>SaleExitYear,0,AnnualModelTable[[#This Row],[NOI]]-AnnualModelTable[[#This Row],[Debt Service]]) -> 0 | I4: =IF(AnnualModelTable[[#This Row],[Year]]>SaleExitYear,0,IF(AnnualModelTable[[#This Row],[Year]]=0,SponsorPropertyPayment,IF(AnnualModelTable[[#This Row],[Year]]=StabilizationRefiYear,MAX(0,RefinanceLoanAmount-TotalExistingDebt),IF(AnnualModelTable[[#This Row],[Year]]=SaleExitYear,MAX(0,AnnualModelTable[[#This Row],[Property Value / Refi Value]]*(1-SellingCosts)-AnnualModelTable[[#This Row],[Loan Balance]]),0)))) -> 150000 | J4: =IF(AnnualModelTable[[#This Row],[Year]]>SaleExitYear,0,IF(AnnualModelTable[[#This Row],[Year]]=0,0,MIN(MAX(0,RepairsMaintenanceReserveTarget-IFERROR(INDEX(AnnualModelTable[Reserve Balance],MATCH(AnnualModelTable[[#This Row],[Year]]-1,AnnualModelTable[Year],0)),0)),MAX(0,IFERROR(INDEX(AnnualModelTable[Ending Cash Balance],MATCH(AnnualModelTable[[#This Row],[Year]]-1,AnnualModelTable[Year],0)),0)+AnnualModelTable[[#This Row],[Cash Before Refi/Sale]]+AnnualModelTable[[#This Row],[Net Refi/Sale Proceeds]])))) -> 0 | K4: =IF(AnnualModelTable[[#This Row],[Year]]>SaleExitYear,0,IF(AnnualModelTable[[#This Row],[Year]]=0,0,IFERROR(INDEX(AnnualModelTable[Reserve Balance],MATCH(AnnualModelTable[[#This Row],[Year]]-1,AnnualModelTable[Year],0)),0)+AnnualModelTable[[#This Row],[Reserve Funding]])) -> 0 | L4: =IF(AnnualModelTable[[#This Row],[Year]]>SaleExitYear,0,IF(AnnualModelTable[[#This Row],[Year]]=0,0,IFERROR(INDEX(AnnualModelTable[Ending Cash Balance],MATCH(AnnualModelTable[[#This Row],[Year]]-1,AnnualModelTable[Year],0)),0))+AnnualModelTable[[#This Row],[Cash Before Refi/Sale]]+AnnualModelTable[[#This Row],[Net Refi/Sale Proceeds]]-AnnualModelTable[[#This Row],[Reserve Funding]]) -> 150000 | M4: =IF(AnnualModelTable[[#This Row],[Year]]>SaleExitYear,0,SUM(INDEX(WaterfallTable[Total Dist A],MATCH(AnnualModelTable[[#This Row],[Year]],WaterfallTable[Year],0)),INDEX(WaterfallTable[Total Dist B],MATCH(AnnualModelTable[[#This Row],[Year]],WaterfallTable[Year],0)),INDEX(WaterfallTable[Total Dist2],MATCH(AnnualModelTable[[#This Row],[Year]],WaterfallTable[Year],0)))) -> 150000 | N4: =IF(AnnualModelTable[[#This Row],[Year]]>SaleExitYear,0,MAX(0,AnnualModelTable[[#This Row],[Cash Available Before Distributions]]-AnnualModelTable[[#This Row],[Waterfall Distributions]])) -> 0 | O4: =IF(AnnualModelTable[[#This Row],[Year]]>SaleExitYear,0,IF(AnnualModelTable[[#This Row],[Year]]<StabilizationRefiYear,0,IF(AnnualModelTable[[#This Row],[Year]]=SaleExitYear,0,-FV(RefinanceLoanRate/12,(AnnualModelTable[[#This Row],[Year]]-StabilizationRefiYear)*12,PMT(RefinanceLoanRate/12,RefinanceLoanAmortizationYears*12,RefinanceLoanAmount),RefinanceLoanAmount)))) -> 0 | P4: =IF(AnnualModelTable[[#This Row],[Year]]>SaleExitYear,0,IF(AnnualModelTable[[#This Row],[Year]]<StabilizationRefiYear,0,AnnualModelTable[[#This Row],[NOI]]*(1+NOIGrowth)/ExitCapRate)) -> 0
A5: 1 | B5: Lease-Up | C5: =IF(AnnualModelTable[[#This Row],[Year]]>SaleExitYear,0,IF(AnnualModelTable[[#This Row],[Year]]=0,0,IF(AnnualModelTable[[#This Row],[Year]]>=RentScenarioHighEffectiveYear,RentScenarioHighMonthlyGross*12,IF(AnnualModelTable[[#This Row],[Year]]>=RentScenarioMediumEffectiveYear,RentScenarioMediumMonthlyGross*12,IF(AnnualModelTable[[#This Row],[Year]]>=RentScenarioLowEffectiveYear,RentScenarioLowMonthlyGross*12,0))))) -> 105600 | D5: =IF(AnnualModelTable[[#This Row],[Year]]>SaleExitYear,0,IF(AnnualModelTable[[#This Row],[Year]]=0,0,AnnualModelTable[[#This Row],[Gross Potential Rent]]*IF(AnnualModelTable[[#This Row],[Year]]=1,LeaseUpOccupancy,StabilizedOccupancy))) -> 52800 | E5: =IF(AnnualModelTable[[#This Row],[Year]]>SaleExitYear,0,AnnualModelTable[[#This Row],[Occupancy Effective Gross Income]]*OperatingExpenseRatio) -> 24769.792 | F5: =IF(AnnualModelTable[[#This Row],[Year]]>SaleExitYear,0,AnnualModelTable[[#This Row],[Occupancy Effective Gross Income]]-AnnualModelTable[[#This Row],[Operating Expenses]]) -> 28030.208 | G5: =IF(AnnualModelTable[[#This Row],[Year]]>SaleExitYear,0,IF(AND(AnnualModelTable[[#This Row],[Year]]>=1,AnnualModelTable[[#This Row],[Year]]<StabilizationRefiYear),ExistingDebtServiceAnnual,IF(AND(AnnualModelTable[[#This Row],[Year]]>=StabilizationRefiYear,AnnualModelTable[[#This Row],[Year]]<=SaleExitYear),-PMT(RefinanceLoanRate/12,RefinanceLoanAmortizationYears*12,RefinanceLoanAmount)*12,0))) -> 13812 | H5: =IF(AnnualModelTable[[#This Row],[Year]]>SaleExitYear,0,AnnualModelTable[[#This Row],[NOI]]-AnnualModelTable[[#This Row],[Debt Service]]) -> 14218.208 | I5: =IF(AnnualModelTable[[#This Row],[Year]]>SaleExitYear,0,IF(AnnualModelTable[[#This Row],[Year]]=0,SponsorPropertyPayment,IF(AnnualModelTable[[#This Row],[Year]]=StabilizationRefiYear,MAX(0,RefinanceLoanAmount-TotalExistingDebt),IF(AnnualModelTable[[#This Row],[Year]]=SaleExitYear,MAX(0,AnnualModelTable[[#This Row],[Property Value / Refi Value]]*(1-SellingCosts)-AnnualModelTable[[#This Row],[Loan Balance]]),0)))) -> 0 | J5: =IF(AnnualModelTable[[#This Row],[Year]]>SaleExitYear,0,IF(AnnualModelTable[[#This Row],[Year]]=0,0,MIN(MAX(0,RepairsMaintenanceReserveTarget-IFERROR(INDEX(AnnualModelTable[Reserve Balance],MATCH(AnnualModelTable[[#This Row],[Year]]-1,AnnualModelTable[Year],0)),0)),MAX(0,IFERROR(INDEX(AnnualModelTable[Ending Cash Balance],MATCH(AnnualModelTable[[#This Row],[Year]]-1,AnnualModelTable[Year],0)),0)+AnnualModelTable[[#This Row],[Cash Before Refi/Sale]]+AnnualModelTable[[#This Row],[Net Refi/Sale Proceeds]])))) -> 9000 | K5: =IF(AnnualModelTable[[#This Row],[Year]]>SaleExitYear,0,IF(AnnualModelTable[[#This Row],[Year]]=0,0,IFERROR(INDEX(AnnualModelTable[Reserve Balance],MATCH(AnnualModelTable[[#This Row],[Year]]-1,AnnualModelTable[Year],0)),0)+AnnualModelTable[[#This Row],[Reserve Funding]])) -> 9000 | L5: =IF(AnnualModelTable[[#This Row],[Year]]>SaleExitYear,0,IF(AnnualModelTable[[#This Row],[Year]]=0,0,IFERROR(INDEX(AnnualModelTable[Ending Cash Balance],MATCH(AnnualModelTable[[#This Row],[Year]]-1,AnnualModelTable[Year],0)),0))+AnnualModelTable[[#This Row],[Cash Before Refi/Sale]]+AnnualModelTable[[#This Row],[Net Refi/Sale Proceeds]]-AnnualModelTable[[#This Row],[Reserve Funding]]) -> 5218.2079 | M5: =IF(AnnualModelTable[[#This Row],[Year]]>SaleExitYear,0,SUM(INDEX(WaterfallTable[Total Dist A],MATCH(AnnualModelTable[[#This Row],[Year]],WaterfallTable[Year],0)),INDEX(WaterfallTable[Total Dist B],MATCH(AnnualModelTable[[#This Row],[Year]],WaterfallTable[Year],0)),INDEX(WaterfallTable[Total Dist2],MATCH(AnnualModelTable[[#This Row],[Year]],WaterfallTable[Year],0)))) -> 5218.2079 | N5: =IF(AnnualModelTable[[#This Row],[Year]]>SaleExitYear,0,MAX(0,AnnualModelTable[[#This Row],[Cash Available Before Distributions]]-AnnualModelTable[[#This Row],[Waterfall Distributions]])) -> 0 | O5: =IF(AnnualModelTable[[#This Row],[Year]]>SaleExitYear,0,IF(AnnualModelTable[[#This Row],[Year]]<StabilizationRefiYear,0,IF(AnnualModelTable[[#This Row],[Year]]=SaleExitYear,0,-FV(RefinanceLoanRate/12,(AnnualModelTable[[#This Row],[Year]]-StabilizationRefiYear)*12,PMT(RefinanceLoanRate/12,RefinanceLoanAmortizationYears*12,RefinanceLoanAmount),RefinanceLoanAmount)))) -> 0 | P5: =IF(AnnualModelTable[[#This Row],[Year]]>SaleExitYear,0,IF(AnnualModelTable[[#This Row],[Year]]<StabilizationRefiYear,0,AnnualModelTable[[#This Row],[NOI]]*(1+NOIGrowth)/ExitCapRate)) -> 0
A6: 2 | B6: Stabilization / Refi | C6: =IF(AnnualModelTable[[#This Row],[Year]]>SaleExitYear,0,IF(AnnualModelTable[[#This Row],[Year]]=0,0,IF(AnnualModelTable[[#This Row],[Year]]>=RentScenarioHighEffectiveYear,RentScenarioHighMonthlyGross*12,IF(AnnualModelTable[[#This Row],[Year]]>=RentScenarioMediumEffectiveYear,RentScenarioMediumMonthlyGross*12,IF(AnnualModelTable[[#This Row],[Year]]>=RentScenarioLowEffectiveYear,RentScenarioLowMonthlyGross*12,0))))) -> 129600 | D6: =IF(AnnualModelTable[[#This Row],[Year]]>SaleExitYear,0,IF(AnnualModelTable[[#This Row],[Year]]=0,0,AnnualModelTable[[#This Row],[Gross Potential Rent]]*IF(AnnualModelTable[[#This Row],[Year]]=1,LeaseUpOccupancy,StabilizedOccupancy))) -> 120528 | E6: =IF(AnnualModelTable[[#This Row],[Year]]>SaleExitYear,0,AnnualModelTable[[#This Row],[Occupancy Effective Gross Income]]*OperatingExpenseRatio) -> 56542.68 | F6: =IF(AnnualModelTable[[#This Row],[Year]]>SaleExitYear,0,AnnualModelTable[[#This Row],[Occupancy Effective Gross Income]]-AnnualModelTable[[#This Row],[Operating Expenses]]) -> 63985.32 | G6: =IF(AnnualModelTable[[#This Row],[Year]]>SaleExitYear,0,IF(AND(AnnualModelTable[[#This Row],[Year]]>=1,AnnualModelTable[[#This Row],[Year]]<StabilizationRefiYear),ExistingDebtServiceAnnual,IF(AND(AnnualModelTable[[#This Row],[Year]]>=StabilizationRefiYear,AnnualModelTable[[#This Row],[Year]]<=SaleExitYear),-PMT(RefinanceLoanRate/12,RefinanceLoanAmortizationYears*12,RefinanceLoanAmount)*12,0))) -> 13812 | H6: =IF(AnnualModelTable[[#This Row],[Year]]>SaleExitYear,0,AnnualModelTable[[#This Row],[NOI]]-AnnualModelTable[[#This Row],[Debt Service]]) -> 50173.32 | I6: =IF(AnnualModelTable[[#This Row],[Year]]>SaleExitYear,0,IF(AnnualModelTable[[#This Row],[Year]]=0,SponsorPropertyPayment,IF(AnnualModelTable[[#This Row],[Year]]=StabilizationRefiYear,MAX(0,RefinanceLoanAmount-TotalExistingDebt),IF(AnnualModelTable[[#This Row],[Year]]=SaleExitYear,MAX(0,AnnualModelTable[[#This Row],[Property Value / Refi Value]]*(1-SellingCosts)-AnnualModelTable[[#This Row],[Loan Balance]]),0)))) -> 0 | J6: =IF(AnnualModelTable[[#This Row],[Year]]>SaleExitYear,0,IF(AnnualModelTable[[#This Row],[Year]]=0,0,MIN(MAX(0,RepairsMaintenanceReserveTarget-IFERROR(INDEX(AnnualModelTable[Reserve Balance],MATCH(AnnualModelTable[[#This Row],[Year]]-1,AnnualModelTable[Year],0)),0)),MAX(0,IFERROR(INDEX(AnnualModelTable[Ending Cash Balance],MATCH(AnnualModelTable[[#This Row],[Year]]-1,AnnualModelTable[Year],0)),0)+AnnualModelTable[[#This Row],[Cash Before Refi/Sale]]+AnnualModelTable[[#This Row],[Net Refi/Sale Proceeds]])))) -> 0 | K6: =IF(AnnualModelTable[[#This Row],[Year]]>SaleExitYear,0,IF(AnnualModelTable[[#This Row],[Year]]=0,0,IFERROR(INDEX(AnnualModelTable[Reserve Balance],MATCH(AnnualModelTable[[#This Row],[Year]]-1,AnnualModelTable[Year],0)),0)+AnnualModelTable[[#This Row],[Reserve Funding]])) -> 9000 | L6: =IF(AnnualModelTable[[#This Row],[Year]]>SaleExitYear,0,IF(AnnualModelTable[[#This Row],[Year]]=0,0,IFERROR(INDEX(AnnualModelTable[Ending Cash Balance],MATCH(AnnualModelTable[[#This Row],[Year]]-1,AnnualModelTable[Year],0)),0))+AnnualModelTable[[#This Row],[Cash Before Refi/Sale]]+AnnualModelTable[[#This Row],[Net Refi/Sale Proceeds]]-AnnualModelTable[[#This Row],[Reserve Funding]]) -> 50173.32 | M6: =IF(AnnualModelTable[[#This Row],[Year]]>SaleExitYear,0,SUM(INDEX(WaterfallTable[Total Dist A],MATCH(AnnualModelTable[[#This Row],[Year]],WaterfallTable[Year],0)),INDEX(WaterfallTable[Total Dist B],MATCH(AnnualModelTable[[#This Row],[Year]],WaterfallTable[Year],0)),INDEX(WaterfallTable[Total Dist2],MATCH(AnnualModelTable[[#This Row],[Year]],WaterfallTable[Year],0)))) -> 50173.32 | N6: =IF(AnnualModelTable[[#This Row],[Year]]>SaleExitYear,0,MAX(0,AnnualModelTable[[#This Row],[Cash Available Before Distributions]]-AnnualModelTable[[#This Row],[Waterfall Distributions]])) -> 0 | O6: =IF(AnnualModelTable[[#This Row],[Year]]>SaleExitYear,0,IF(AnnualModelTable[[#This Row],[Year]]<StabilizationRefiYear,0,IF(AnnualModelTable[[#This Row],[Year]]=SaleExitYear,0,-FV(RefinanceLoanRate/12,(AnnualModelTable[[#This Row],[Year]]-StabilizationRefiYear)*12,PMT(RefinanceLoanRate/12,RefinanceLoanAmortizationYears*12,RefinanceLoanAmount),RefinanceLoanAmount)))) -> 0 | P6: =IF(AnnualModelTable[[#This Row],[Year]]>SaleExitYear,0,IF(AnnualModelTable[[#This Row],[Year]]<StabilizationRefiYear,0,AnnualModelTable[[#This Row],[NOI]]*(1+NOIGrowth)/ExitCapRate)) -> 0
A7: 3 | B7: Operations | C7: =IF(AnnualModelTable[[#This Row],[Year]]>SaleExitYear,0,IF(AnnualModelTable[[#This Row],[Year]]=0,0,IF(AnnualModelTable[[#This Row],[Year]]>=RentScenarioHighEffectiveYear,RentScenarioHighMonthlyGross*12,IF(AnnualModelTable[[#This Row],[Year]]>=RentScenarioMediumEffectiveYear,RentScenarioMediumMonthlyGross*12,IF(AnnualModelTable[[#This Row],[Year]]>=RentScenarioLowEffectiveYear,RentScenarioLowMonthlyGross*12,0))))) -> 144000 | D7: =IF(AnnualModelTable[[#This Row],[Year]]>SaleExitYear,0,IF(AnnualModelTable[[#This Row],[Year]]=0,0,AnnualModelTable[[#This Row],[Gross Potential Rent]]*IF(AnnualModelTable[[#This Row],[Year]]=1,LeaseUpOccupancy,StabilizedOccupancy))) -> 133920 | E7: =IF(AnnualModelTable[[#This Row],[Year]]>SaleExitYear,0,AnnualModelTable[[#This Row],[Occupancy Effective Gross Income]]*OperatingExpenseRatio) -> 62825.2 | F7: =IF(AnnualModelTable[[#This Row],[Year]]>SaleExitYear,0,AnnualModelTable[[#This Row],[Occupancy Effective Gross Income]]-AnnualModelTable[[#This Row],[Operating Expenses]]) -> 71094.8 | G7: =IF(AnnualModelTable[[#This Row],[Year]]>SaleExitYear,0,IF(AND(AnnualModelTable[[#This Row],[Year]]>=1,AnnualModelTable[[#This Row],[Year]]<StabilizationRefiYear),ExistingDebtServiceAnnual,IF(AND(AnnualModelTable[[#This Row],[Year]]>=StabilizationRefiYear,AnnualModelTable[[#This Row],[Year]]<=SaleExitYear),-PMT(RefinanceLoanRate/12,RefinanceLoanAmortizationYears*12,RefinanceLoanAmount)*12,0))) -> 55541.823 | H7: =IF(AnnualModelTable[[#This Row],[Year]]>SaleExitYear,0,AnnualModelTable[[#This Row],[NOI]]-AnnualModelTable[[#This Row],[Debt Service]]) -> 15552.977 | I7: =IF(AnnualModelTable[[#This Row],[Year]]>SaleExitYear,0,IF(AnnualModelTable[[#This Row],[Year]]=0,SponsorPropertyPayment,IF(AnnualModelTable[[#This Row],[Year]]=StabilizationRefiYear,MAX(0,RefinanceLoanAmount-TotalExistingDebt),IF(AnnualModelTable[[#This Row],[Year]]=SaleExitYear,MAX(0,AnnualModelTable[[#This Row],[Property Value / Refi Value]]*(1-SellingCosts)-AnnualModelTable[[#This Row],[Loan Balance]]),0)))) -> 538276.44 | J7: =IF(AnnualModelTable[[#This Row],[Year]]>SaleExitYear,0,IF(AnnualModelTable[[#This Row],[Year]]=0,0,MIN(MAX(0,RepairsMaintenanceReserveTarget-IFERROR(INDEX(AnnualModelTable[Reserve Balance],MATCH(AnnualModelTable[[#This Row],[Year]]-1,AnnualModelTable[Year],0)),0)),MAX(0,IFERROR(INDEX(AnnualModelTable[Ending Cash Balance],MATCH(AnnualModelTable[[#This Row],[Year]]-1,AnnualModelTable[Year],0)),0)+AnnualModelTable[[#This Row],[Cash Before Refi/Sale]]+AnnualModelTable[[#This Row],[Net Refi/Sale Proceeds]])))) -> 0 | K7: =IF(AnnualModelTable[[#This Row],[Year]]>SaleExitYear,0,IF(AnnualModelTable[[#This Row],[Year]]=0,0,IFERROR(INDEX(AnnualModelTable[Reserve Balance],MATCH(AnnualModelTable[[#This Row],[Year]]-1,AnnualModelTable[Year],0)),0)+AnnualModelTable[[#This Row],[Reserve Funding]])) -> 9000 | L7: =IF(AnnualModelTable[[#This Row],[Year]]>SaleExitYear,0,IF(AnnualModelTable[[#This Row],[Year]]=0,0,IFERROR(INDEX(AnnualModelTable[Ending Cash Balance],MATCH(AnnualModelTable[[#This Row],[Year]]-1,AnnualModelTable[Year],0)),0))+AnnualModelTable[[#This Row],[Cash Before Refi/Sale]]+AnnualModelTable[[#This Row],[Net Refi/Sale Proceeds]]-AnnualModelTable[[#This Row],[Reserve Funding]]) -> 553829.42 | M7: =IF(AnnualModelTable[[#This Row],[Year]]>SaleExitYear,0,SUM(INDEX(WaterfallTable[Total Dist A],MATCH(AnnualModelTable[[#This Row],[Year]],WaterfallTable[Year],0)),INDEX(WaterfallTable[Total Dist B],MATCH(AnnualModelTable[[#This Row],[Year]],WaterfallTable[Year],0)),INDEX(WaterfallTable[Total Dist2],MATCH(AnnualModelTable[[#This Row],[Year]],WaterfallTable[Year],0)))) -> 553829.42 | N7: =IF(AnnualModelTable[[#This Row],[Year]]>SaleExitYear,0,MAX(0,AnnualModelTable[[#This Row],[Cash Available Before Distributions]]-AnnualModelTable[[#This Row],[Waterfall Distributions]])) -> 0 | O7: =IF(AnnualModelTable[[#This Row],[Year]]>SaleExitYear,0,IF(AnnualModelTable[[#This Row],[Year]]<StabilizationRefiYear,0,IF(AnnualModelTable[[#This Row],[Year]]=SaleExitYear,0,-FV(RefinanceLoanRate/12,(AnnualModelTable[[#This Row],[Year]]-StabilizationRefiYear)*12,PMT(RefinanceLoanRate/12,RefinanceLoanAmortizationYears*12,RefinanceLoanAmount),RefinanceLoanAmount)))) -> 732276.44 | P7: =IF(AnnualModelTable[[#This Row],[Year]]>SaleExitYear,0,IF(AnnualModelTable[[#This Row],[Year]]<StabilizationRefiYear,0,AnnualModelTable[[#This Row],[NOI]]*(1+NOIGrowth)/ExitCapRate)) -> 1046109.2
A8: 4 | B8: Operations | C8: =IF(AnnualModelTable[[#This Row],[Year]]>SaleExitYear,0,IF(AnnualModelTable[[#This Row],[Year]]=0,0,IF(AnnualModelTable[[#This Row],[Year]]>=RentScenarioHighEffectiveYear,RentScenarioHighMonthlyGross*12,IF(AnnualModelTable[[#This Row],[Year]]>=RentScenarioMediumEffectiveYear,RentScenarioMediumMonthlyGross*12,IF(AnnualModelTable[[#This Row],[Year]]>=RentScenarioLowEffectiveYear,RentScenarioLowMonthlyGross*12,0))))) -> 144000 | D8: =IF(AnnualModelTable[[#This Row],[Year]]>SaleExitYear,0,IF(AnnualModelTable[[#This Row],[Year]]=0,0,AnnualModelTable[[#This Row],[Gross Potential Rent]]*IF(AnnualModelTable[[#This Row],[Year]]=1,LeaseUpOccupancy,StabilizedOccupancy))) -> 133920 | E8: =IF(AnnualModelTable[[#This Row],[Year]]>SaleExitYear,0,AnnualModelTable[[#This Row],[Occupancy Effective Gross Income]]*OperatingExpenseRatio) -> 62825.2 | F8: =IF(AnnualModelTable[[#This Row],[Year]]>SaleExitYear,0,AnnualModelTable[[#This Row],[Occupancy Effective Gross Income]]-AnnualModelTable[[#This Row],[Operating Expenses]]) -> 71094.8 | G8: =IF(AnnualModelTable[[#This Row],[Year]]>SaleExitYear,0,IF(AND(AnnualModelTable[[#This Row],[Year]]>=1,AnnualModelTable[[#This Row],[Year]]<StabilizationRefiYear),ExistingDebtServiceAnnual,IF(AND(AnnualModelTable[[#This Row],[Year]]>=StabilizationRefiYear,AnnualModelTable[[#This Row],[Year]]<=SaleExitYear),-PMT(RefinanceLoanRate/12,RefinanceLoanAmortizationYears*12,RefinanceLoanAmount)*12,0))) -> 55541.823 | H8: =IF(AnnualModelTable[[#This Row],[Year]]>SaleExitYear,0,AnnualModelTable[[#This Row],[NOI]]-AnnualModelTable[[#This Row],[Debt Service]]) -> 15552.977 | I8: =IF(AnnualModelTable[[#This Row],[Year]]>SaleExitYear,0,IF(AnnualModelTable[[#This Row],[Year]]=0,SponsorPropertyPayment,IF(AnnualModelTable[[#This Row],[Year]]=StabilizationRefiYear,MAX(0,RefinanceLoanAmount-TotalExistingDebt),IF(AnnualModelTable[[#This Row],[Year]]=SaleExitYear,MAX(0,AnnualModelTable[[#This Row],[Property Value / Refi Value]]*(1-SellingCosts)-AnnualModelTable[[#This Row],[Loan Balance]]),0)))) -> 0 | J8: =IF(AnnualModelTable[[#This Row],[Year]]>SaleExitYear,0,IF(AnnualModelTable[[#This Row],[Year]]=0,0,MIN(MAX(0,RepairsMaintenanceReserveTarget-IFERROR(INDEX(AnnualModelTable[Reserve Balance],MATCH(AnnualModelTable[[#This Row],[Year]]-1,AnnualModelTable[Year],0)),0)),MAX(0,IFERROR(INDEX(AnnualModelTable[Ending Cash Balance],MATCH(AnnualModelTable[[#This Row],[Year]]-1,AnnualModelTable[Year],0)),0)+AnnualModelTable[[#This Row],[Cash Before Refi/Sale]]+AnnualModelTable[[#This Row],[Net Refi/Sale Proceeds]])))) -> 0 | K8: =IF(AnnualModelTable[[#This Row],[Year]]>SaleExitYear,0,IF(AnnualModelTable[[#This Row],[Year]]=0,0,IFERROR(INDEX(AnnualModelTable[Reserve Balance],MATCH(AnnualModelTable[[#This Row],[Year]]-1,AnnualModelTable[Year],0)),0)+AnnualModelTable[[#This Row],[Reserve Funding]])) -> 9000 | L8: =IF(AnnualModelTable[[#This Row],[Year]]>SaleExitYear,0,IF(AnnualModelTable[[#This Row],[Year]]=0,0,IFERROR(INDEX(AnnualModelTable[Ending Cash Balance],MATCH(AnnualModelTable[[#This Row],[Year]]-1,AnnualModelTable[Year],0)),0))+AnnualModelTable[[#This Row],[Cash Before Refi/Sale]]+AnnualModelTable[[#This Row],[Net Refi/Sale Proceeds]]-AnnualModelTable[[#This Row],[Reserve Funding]]) -> 15552.977 | M8: =IF(AnnualModelTable[[#This Row],[Year]]>SaleExitYear,0,SUM(INDEX(WaterfallTable[Total Dist A],MATCH(AnnualModelTable[[#This Row],[Year]],WaterfallTable[Year],0)),INDEX(WaterfallTable[Total Dist B],MATCH(AnnualModelTable[[#This Row],[Year]],WaterfallTable[Year],0)),INDEX(WaterfallTable[Total Dist2],MATCH(AnnualModelTable[[#This Row],[Year]],WaterfallTable[Year],0)))) -> 15552.977 | N8: =IF(AnnualModelTable[[#This Row],[Year]]>SaleExitYear,0,MAX(0,AnnualModelTable[[#This Row],[Cash Available Before Distributions]]-AnnualModelTable[[#This Row],[Waterfall Distributions]])) -> 0 | O8: =IF(AnnualModelTable[[#This Row],[Year]]>SaleExitYear,0,IF(AnnualModelTable[[#This Row],[Year]]<StabilizationRefiYear,0,IF(AnnualModelTable[[#This Row],[Year]]=SaleExitYear,0,-FV(RefinanceLoanRate/12,(AnnualModelTable[[#This Row],[Year]]-StabilizationRefiYear)*12,PMT(RefinanceLoanRate/12,RefinanceLoanAmortizationYears*12,RefinanceLoanAmount),RefinanceLoanAmount)))) -> 724091.6 | P8: =IF(AnnualModelTable[[#This Row],[Year]]>SaleExitYear,0,IF(AnnualModelTable[[#This Row],[Year]]<StabilizationRefiYear,0,AnnualModelTable[[#This Row],[NOI]]*(1+NOIGrowth)/ExitCapRate)) -> 1046109.2
A9: 5 | B9: Operations | C9: =IF(AnnualModelTable[[#This Row],[Year]]>SaleExitYear,0,IF(AnnualModelTable[[#This Row],[Year]]=0,0,IF(AnnualModelTable[[#This Row],[Year]]>=RentScenarioHighEffectiveYear,RentScenarioHighMonthlyGross*12,IF(AnnualModelTable[[#This Row],[Year]]>=RentScenarioMediumEffectiveYear,RentScenarioMediumMonthlyGross*12,IF(AnnualModelTable[[#This Row],[Year]]>=RentScenarioLowEffectiveYear,RentScenarioLowMonthlyGross*12,0))))) -> 144000 | D9: =IF(AnnualModelTable[[#This Row],[Year]]>SaleExitYear,0,IF(AnnualModelTable[[#This Row],[Year]]=0,0,AnnualModelTable[[#This Row],[Gross Potential Rent]]*IF(AnnualModelTable[[#This Row],[Year]]=1,LeaseUpOccupancy,StabilizedOccupancy))) -> 133920 | E9: =IF(AnnualModelTable[[#This Row],[Year]]>SaleExitYear,0,AnnualModelTable[[#This Row],[Occupancy Effective Gross Income]]*OperatingExpenseRatio) -> 62825.2 | F9: =IF(AnnualModelTable[[#This Row],[Year]]>SaleExitYear,0,AnnualModelTable[[#This Row],[Occupancy Effective Gross Income]]-AnnualModelTable[[#This Row],[Operating Expenses]]) -> 71094.8 | G9: =IF(AnnualModelTable[[#This Row],[Year]]>SaleExitYear,0,IF(AND(AnnualModelTable[[#This Row],[Year]]>=1,AnnualModelTable[[#This Row],[Year]]<StabilizationRefiYear),ExistingDebtServiceAnnual,IF(AND(AnnualModelTable[[#This Row],[Year]]>=StabilizationRefiYear,AnnualModelTable[[#This Row],[Year]]<=SaleExitYear),-PMT(RefinanceLoanRate/12,RefinanceLoanAmortizationYears*12,RefinanceLoanAmount)*12,0))) -> 55541.823 | H9: =IF(AnnualModelTable[[#This Row],[Year]]>SaleExitYear,0,AnnualModelTable[[#This Row],[NOI]]-AnnualModelTable[[#This Row],[Debt Service]]) -> 15552.977 | I9: =IF(AnnualModelTable[[#This Row],[Year]]>SaleExitYear,0,IF(AnnualModelTable[[#This Row],[Year]]=0,SponsorPropertyPayment,IF(AnnualModelTable[[#This Row],[Year]]=StabilizationRefiYear,MAX(0,RefinanceLoanAmount-TotalExistingDebt),IF(AnnualModelTable[[#This Row],[Year]]=SaleExitYear,MAX(0,AnnualModelTable[[#This Row],[Property Value / Refi Value]]*(1-SellingCosts)-AnnualModelTable[[#This Row],[Loan Balance]]),0)))) -> 1025187 | J9: =IF(AnnualModelTable[[#This Row],[Year]]>SaleExitYear,0,IF(AnnualModelTable[[#This Row],[Year]]=0,0,MIN(MAX(0,RepairsMaintenanceReserveTarget-IFERROR(INDEX(AnnualModelTable[Reserve Balance],MATCH(AnnualModelTable[[#This Row],[Year]]-1,AnnualModelTable[Year],0)),0)),MAX(0,IFERROR(INDEX(AnnualModelTable[Ending Cash Balance],MATCH(AnnualModelTable[[#This Row],[Year]]-1,AnnualModelTable[Year],0)),0)+AnnualModelTable[[#This Row],[Cash Before Refi/Sale]]+AnnualModelTable[[#This Row],[Net Refi/Sale Proceeds]])))) -> 0 | K9: =IF(AnnualModelTable[[#This Row],[Year]]>SaleExitYear,0,IF(AnnualModelTable[[#This Row],[Year]]=0,0,IFERROR(INDEX(AnnualModelTable[Reserve Balance],MATCH(AnnualModelTable[[#This Row],[Year]]-1,AnnualModelTable[Year],0)),0)+AnnualModelTable[[#This Row],[Reserve Funding]])) -> 9000 | L9: =IF(AnnualModelTable[[#This Row],[Year]]>SaleExitYear,0,IF(AnnualModelTable[[#This Row],[Year]]=0,0,IFERROR(INDEX(AnnualModelTable[Ending Cash Balance],MATCH(AnnualModelTable[[#This Row],[Year]]-1,AnnualModelTable[Year],0)),0))+AnnualModelTable[[#This Row],[Cash Before Refi/Sale]]+AnnualModelTable[[#This Row],[Net Refi/Sale Proceeds]]-AnnualModelTable[[#This Row],[Reserve Funding]]) -> 1040740 | M9: =IF(AnnualModelTable[[#This Row],[Year]]>SaleExitYear,0,SUM(INDEX(WaterfallTable[Total Dist A],MATCH(AnnualModelTable[[#This Row],[Year]],WaterfallTable[Year],0)),INDEX(WaterfallTable[Total Dist B],MATCH(AnnualModelTable[[#This Row],[Year]],WaterfallTable[Year],0)),INDEX(WaterfallTable[Total Dist2],MATCH(AnnualModelTable[[#This Row],[Year]],WaterfallTable[Year],0)))) -> 1040740 | N9: =IF(AnnualModelTable[[#This Row],[Year]]>SaleExitYear,0,MAX(0,AnnualModelTable[[#This Row],[Cash Available Before Distributions]]-AnnualModelTable[[#This Row],[Waterfall Distributions]])) -> 0 | O9: =IF(AnnualModelTable[[#This Row],[Year]]>SaleExitYear,0,IF(AnnualModelTable[[#This Row],[Year]]<StabilizationRefiYear,0,IF(AnnualModelTable[[#This Row],[Year]]=SaleExitYear,0,-FV(RefinanceLoanRate/12,(AnnualModelTable[[#This Row],[Year]]-StabilizationRefiYear)*12,PMT(RefinanceLoanRate/12,RefinanceLoanAmortizationYears*12,RefinanceLoanAmount),RefinanceLoanAmount)))) -> 0 | P9: =IF(AnnualModelTable[[#This Row],[Year]]>SaleExitYear,0,IF(AnnualModelTable[[#This Row],[Year]]<StabilizationRefiYear,0,AnnualModelTable[[#This Row],[NOI]]*(1+NOIGrowth)/ExitCapRate)) -> 1046109.2
A10: 6 | B10: Operations | C10: =IF(AnnualModelTable[[#This Row],[Year]]>SaleExitYear,0,IF(AnnualModelTable[[#This Row],[Year]]=0,0,IF(AnnualModelTable[[#This Row],[Year]]>=RentScenarioHighEffectiveYear,RentScenarioHighMonthlyGross*12,IF(AnnualModelTable[[#This Row],[Year]]>=RentScenarioMediumEffectiveYear,RentScenarioMediumMonthlyGross*12,IF(AnnualModelTable[[#This Row],[Year]]>=RentScenarioLowEffectiveYear,RentScenarioLowMonthlyGross*12,0))))) -> 0 | D10: =IF(AnnualModelTable[[#This Row],[Year]]>SaleExitYear,0,IF(AnnualModelTable[[#This Row],[Year]]=0,0,AnnualModelTable[[#This Row],[Gross Potential Rent]]*IF(AnnualModelTable[[#This Row],[Year]]=1,LeaseUpOccupancy,StabilizedOccupancy))) -> 0 | E10: =IF(AnnualModelTable[[#This Row],[Year]]>SaleExitYear,0,AnnualModelTable[[#This Row],[Occupancy Effective Gross Income]]*OperatingExpenseRatio) -> 0 | F10: =IF(AnnualModelTable[[#This Row],[Year]]>SaleExitYear,0,AnnualModelTable[[#This Row],[Occupancy Effective Gross Income]]-AnnualModelTable[[#This Row],[Operating Expenses]]) -> 0 | G10: =IF(AnnualModelTable[[#This Row],[Year]]>SaleExitYear,0,IF(AND(AnnualModelTable[[#This Row],[Year]]>=1,AnnualModelTable[[#This Row],[Year]]<StabilizationRefiYear),ExistingDebtServiceAnnual,IF(AND(AnnualModelTable[[#This Row],[Year]]>=StabilizationRefiYear,AnnualModelTable[[#This Row],[Year]]<=SaleExitYear),-PMT(RefinanceLoanRate/12,RefinanceLoanAmortizationYears*12,RefinanceLoanAmount)*12,0))) -> 0 | H10: =IF(AnnualModelTable[[#This Row],[Year]]>SaleExitYear,0,AnnualModelTable[[#This Row],[NOI]]-AnnualModelTable[[#This Row],[Debt Service]]) -> 0 | I10: =IF(AnnualModelTable[[#This Row],[Year]]>SaleExitYear,0,IF(AnnualModelTable[[#This Row],[Year]]=0,SponsorPropertyPayment,IF(AnnualModelTable[[#This Row],[Year]]=StabilizationRefiYear,MAX(0,RefinanceLoanAmount-TotalExistingDebt),IF(AnnualModelTable[[#This Row],[Year]]=SaleExitYear,MAX(0,AnnualModelTable[[#This Row],[Property Value / Refi Value]]*(1-SellingCosts)-AnnualModelTable[[#This Row],[Loan Balance]]),0)))) -> 0 | J10: =IF(AnnualModelTable[[#This Row],[Year]]>SaleExitYear,0,IF(AnnualModelTable[[#This Row],[Year]]=0,0,MIN(MAX(0,RepairsMaintenanceReserveTarget-IFERROR(INDEX(AnnualModelTable[Reserve Balance],MATCH(AnnualModelTable[[#This Row],[Year]]-1,AnnualModelTable[Year],0)),0)),MAX(0,IFERROR(INDEX(AnnualModelTable[Ending Cash Balance],MATCH(AnnualModelTable[[#This Row],[Year]]-1,AnnualModelTable[Year],0)),0)+AnnualModelTable[[#This Row],[Cash Before Refi/Sale]]+AnnualModelTable[[#This Row],[Net Refi/Sale Proceeds]])))) -> 0 | K10: =IF(AnnualModelTable[[#This Row],[Year]]>SaleExitYear,0,IF(AnnualModelTable[[#This Row],[Year]]=0,0,IFERROR(INDEX(AnnualModelTable[Reserve Balance],MATCH(AnnualModelTable[[#This Row],[Year]]-1,AnnualModelTable[Year],0)),0)+AnnualModelTable[[#This Row],[Reserve Funding]])) -> 0 | L10: =IF(AnnualModelTable[[#This Row],[Year]]>SaleExitYear,0,IF(AnnualModelTable[[#This Row],[Year]]=0,0,IFERROR(INDEX(AnnualModelTable[Ending Cash Balance],MATCH(AnnualModelTable[[#This Row],[Year]]-1,AnnualModelTable[Year],0)),0))+AnnualModelTable[[#This Row],[Cash Before Refi/Sale]]+AnnualModelTable[[#This Row],[Net Refi/Sale Proceeds]]-AnnualModelTable[[#This Row],[Reserve Funding]]) -> 0 | M10: =IF(AnnualModelTable[[#This Row],[Year]]>SaleExitYear,0,SUM(INDEX(WaterfallTable[Total Dist A],MATCH(AnnualModelTable[[#This Row],[Year]],WaterfallTable[Year],0)),INDEX(WaterfallTable[Total Dist B],MATCH(AnnualModelTable[[#This Row],[Year]],WaterfallTable[Year],0)),INDEX(WaterfallTable[Total Dist2],MATCH(AnnualModelTable[[#This Row],[Year]],WaterfallTable[Year],0)))) -> 0 | N10: =IF(AnnualModelTable[[#This Row],[Year]]>SaleExitYear,0,MAX(0,AnnualModelTable[[#This Row],[Cash Available Before Distributions]]-AnnualModelTable[[#This Row],[Waterfall Distributions]])) -> 0 | O10: =IF(AnnualModelTable[[#This Row],[Year]]>SaleExitYear,0,IF(AnnualModelTable[[#This Row],[Year]]<StabilizationRefiYear,0,IF(AnnualModelTable[[#This Row],[Year]]=SaleExitYear,0,-FV(RefinanceLoanRate/12,(AnnualModelTable[[#This Row],[Year]]-StabilizationRefiYear)*12,PMT(RefinanceLoanRate/12,RefinanceLoanAmortizationYears*12,RefinanceLoanAmount),RefinanceLoanAmount)))) -> 0 | P10: =IF(AnnualModelTable[[#This Row],[Year]]>SaleExitYear,0,IF(AnnualModelTable[[#This Row],[Year]]<StabilizationRefiYear,0,AnnualModelTable[[#This Row],[NOI]]*(1+NOIGrowth)/ExitCapRate)) -> 0
A11: 7 | B11: Operations | C11: =IF(AnnualModelTable[[#This Row],[Year]]>SaleExitYear,0,IF(AnnualModelTable[[#This Row],[Year]]=0,0,IF(AnnualModelTable[[#This Row],[Year]]>=RentScenarioHighEffectiveYear,RentScenarioHighMonthlyGross*12,IF(AnnualModelTable[[#This Row],[Year]]>=RentScenarioMediumEffectiveYear,RentScenarioMediumMonthlyGross*12,IF(AnnualModelTable[[#This Row],[Year]]>=RentScenarioLowEffectiveYear,RentScenarioLowMonthlyGross*12,0))))) -> 0 | D11: =IF(AnnualModelTable[[#This Row],[Year]]>SaleExitYear,0,IF(AnnualModelTable[[#This Row],[Year]]=0,0,AnnualModelTable[[#This Row],[Gross Potential Rent]]*IF(AnnualModelTable[[#This Row],[Year]]=1,LeaseUpOccupancy,StabilizedOccupancy))) -> 0 | E11: =IF(AnnualModelTable[[#This Row],[Year]]>SaleExitYear,0,AnnualModelTable[[#This Row],[Occupancy Effective Gross Income]]*OperatingExpenseRatio) -> 0 | F11: =IF(AnnualModelTable[[#This Row],[Year]]>SaleExitYear,0,AnnualModelTable[[#This Row],[Occupancy Effective Gross Income]]-AnnualModelTable[[#This Row],[Operating Expenses]]) -> 0 | G11: =IF(AnnualModelTable[[#This Row],[Year]]>SaleExitYear,0,IF(AND(AnnualModelTable[[#This Row],[Year]]>=1,AnnualModelTable[[#This Row],[Year]]<StabilizationRefiYear),ExistingDebtServiceAnnual,IF(AND(AnnualModelTable[[#This Row],[Year]]>=StabilizationRefiYear,AnnualModelTable[[#This Row],[Year]]<=SaleExitYear),-PMT(RefinanceLoanRate/12,RefinanceLoanAmortizationYears*12,RefinanceLoanAmount)*12,0))) -> 0 | H11: =IF(AnnualModelTable[[#This Row],[Year]]>SaleExitYear,0,AnnualModelTable[[#This Row],[NOI]]-AnnualModelTable[[#This Row],[Debt Service]]) -> 0 | I11: =IF(AnnualModelTable[[#This Row],[Year]]>SaleExitYear,0,IF(AnnualModelTable[[#This Row],[Year]]=0,SponsorPropertyPayment,IF(AnnualModelTable[[#This Row],[Year]]=StabilizationRefiYear,MAX(0,RefinanceLoanAmount-TotalExistingDebt),IF(AnnualModelTable[[#This Row],[Year]]=SaleExitYear,MAX(0,AnnualModelTable[[#This Row],[Property Value / Refi Value]]*(1-SellingCosts)-AnnualModelTable[[#This Row],[Loan Balance]]),0)))) -> 0 | J11: =IF(AnnualModelTable[[#This Row],[Year]]>SaleExitYear,0,IF(AnnualModelTable[[#This Row],[Year]]=0,0,MIN(MAX(0,RepairsMaintenanceReserveTarget-IFERROR(INDEX(AnnualModelTable[Reserve Balance],MATCH(AnnualModelTable[[#This Row],[Year]]-1,AnnualModelTable[Year],0)),0)),MAX(0,IFERROR(INDEX(AnnualModelTable[Ending Cash Balance],MATCH(AnnualModelTable[[#This Row],[Year]]-1,AnnualModelTable[Year],0)),0)+AnnualModelTable[[#This Row],[Cash Before Refi/Sale]]+AnnualModelTable[[#This Row],[Net Refi/Sale Proceeds]])))) -> 0 | K11: =IF(AnnualModelTable[[#This Row],[Year]]>SaleExitYear,0,IF(AnnualModelTable[[#This Row],[Year]]=0,0,IFERROR(INDEX(AnnualModelTable[Reserve Balance],MATCH(AnnualModelTable[[#This Row],[Year]]-1,AnnualModelTable[Year],0)),0)+AnnualModelTable[[#This Row],[Reserve Funding]])) -> 0 | L11: =IF(AnnualModelTable[[#This Row],[Year]]>SaleExitYear,0,IF(AnnualModelTable[[#This Row],[Year]]=0,0,IFERROR(INDEX(AnnualModelTable[Ending Cash Balance],MATCH(AnnualModelTable[[#This Row],[Year]]-1,AnnualModelTable[Year],0)),0))+AnnualModelTable[[#This Row],[Cash Before Refi/Sale]]+AnnualModelTable[[#This Row],[Net Refi/Sale Proceeds]]-AnnualModelTable[[#This Row],[Reserve Funding]]) -> 0 | M11: =IF(AnnualModelTable[[#This Row],[Year]]>SaleExitYear,0,SUM(INDEX(WaterfallTable[Total Dist A],MATCH(AnnualModelTable[[#This Row],[Year]],WaterfallTable[Year],0)),INDEX(WaterfallTable[Total Dist B],MATCH(AnnualModelTable[[#This Row],[Year]],WaterfallTable[Year],0)),INDEX(WaterfallTable[Total Dist2],MATCH(AnnualModelTable[[#This Row],[Year]],WaterfallTable[Year],0)))) -> 0 | N11: =IF(AnnualModelTable[[#This Row],[Year]]>SaleExitYear,0,MAX(0,AnnualModelTable[[#This Row],[Cash Available Before Distributions]]-AnnualModelTable[[#This Row],[Waterfall Distributions]])) -> 0 | O11: =IF(AnnualModelTable[[#This Row],[Year]]>SaleExitYear,0,IF(AnnualModelTable[[#This Row],[Year]]<StabilizationRefiYear,0,IF(AnnualModelTable[[#This Row],[Year]]=SaleExitYear,0,-FV(RefinanceLoanRate/12,(AnnualModelTable[[#This Row],[Year]]-StabilizationRefiYear)*12,PMT(RefinanceLoanRate/12,RefinanceLoanAmortizationYears*12,RefinanceLoanAmount),RefinanceLoanAmount)))) -> 0 | P11: =IF(AnnualModelTable[[#This Row],[Year]]>SaleExitYear,0,IF(AnnualModelTable[[#This Row],[Year]]<StabilizationRefiYear,0,AnnualModelTable[[#This Row],[NOI]]*(1+NOIGrowth)/ExitCapRate)) -> 0
A12: 8 | B12: Operations | C12: =IF(AnnualModelTable[[#This Row],[Year]]>SaleExitYear,0,IF(AnnualModelTable[[#This Row],[Year]]=0,0,IF(AnnualModelTable[[#This Row],[Year]]>=RentScenarioHighEffectiveYear,RentScenarioHighMonthlyGross*12,IF(AnnualModelTable[[#This Row],[Year]]>=RentScenarioMediumEffectiveYear,RentScenarioMediumMonthlyGross*12,IF(AnnualModelTable[[#This Row],[Year]]>=RentScenarioLowEffectiveYear,RentScenarioLowMonthlyGross*12,0))))) -> 0 | D12: =IF(AnnualModelTable[[#This Row],[Year]]>SaleExitYear,0,IF(AnnualModelTable[[#This Row],[Year]]=0,0,AnnualModelTable[[#This Row],[Gross Potential Rent]]*IF(AnnualModelTable[[#This Row],[Year]]=1,LeaseUpOccupancy,StabilizedOccupancy))) -> 0 | E12: =IF(AnnualModelTable[[#This Row],[Year]]>SaleExitYear,0,AnnualModelTable[[#This Row],[Occupancy Effective Gross Income]]*OperatingExpenseRatio) -> 0 | F12: =IF(AnnualModelTable[[#This Row],[Year]]>SaleExitYear,0,AnnualModelTable[[#This Row],[Occupancy Effective Gross Income]]-AnnualModelTable[[#This Row],[Operating Expenses]]) -> 0 | G12: =IF(AnnualModelTable[[#This Row],[Year]]>SaleExitYear,0,IF(AND(AnnualModelTable[[#This Row],[Year]]>=1,AnnualModelTable[[#This Row],[Year]]<StabilizationRefiYear),ExistingDebtServiceAnnual,IF(AND(AnnualModelTable[[#This Row],[Year]]>=StabilizationRefiYear,AnnualModelTable[[#This Row],[Year]]<=SaleExitYear),-PMT(RefinanceLoanRate/12,RefinanceLoanAmortizationYears*12,RefinanceLoanAmount)*12,0))) -> 0 | H12: =IF(AnnualModelTable[[#This Row],[Year]]>SaleExitYear,0,AnnualModelTable[[#This Row],[NOI]]-AnnualModelTable[[#This Row],[Debt Service]]) -> 0 | I12: =IF(AnnualModelTable[[#This Row],[Year]]>SaleExitYear,0,IF(AnnualModelTable[[#This Row],[Year]]=0,SponsorPropertyPayment,IF(AnnualModelTable[[#This Row],[Year]]=StabilizationRefiYear,MAX(0,RefinanceLoanAmount-TotalExistingDebt),IF(AnnualModelTable[[#This Row],[Year]]=SaleExitYear,MAX(0,AnnualModelTable[[#This Row],[Property Value / Refi Value]]*(1-SellingCosts)-AnnualModelTable[[#This Row],[Loan Balance]]),0)))) -> 0 | J12: =IF(AnnualModelTable[[#This Row],[Year]]>SaleExitYear,0,IF(AnnualModelTable[[#This Row],[Year]]=0,0,MIN(MAX(0,RepairsMaintenanceReserveTarget-IFERROR(INDEX(AnnualModelTable[Reserve Balance],MATCH(AnnualModelTable[[#This Row],[Year]]-1,AnnualModelTable[Year],0)),0)),MAX(0,IFERROR(INDEX(AnnualModelTable[Ending Cash Balance],MATCH(AnnualModelTable[[#This Row],[Year]]-1,AnnualModelTable[Year],0)),0)+AnnualModelTable[[#This Row],[Cash Before Refi/Sale]]+AnnualModelTable[[#This Row],[Net Refi/Sale Proceeds]])))) -> 0 | K12: =IF(AnnualModelTable[[#This Row],[Year]]>SaleExitYear,0,IF(AnnualModelTable[[#This Row],[Year]]=0,0,IFERROR(INDEX(AnnualModelTable[Reserve Balance],MATCH(AnnualModelTable[[#This Row],[Year]]-1,AnnualModelTable[Year],0)),0)+AnnualModelTable[[#This Row],[Reserve Funding]])) -> 0 | L12: =IF(AnnualModelTable[[#This Row],[Year]]>SaleExitYear,0,IF(AnnualModelTable[[#This Row],[Year]]=0,0,IFERROR(INDEX(AnnualModelTable[Ending Cash Balance],MATCH(AnnualModelTable[[#This Row],[Year]]-1,AnnualModelTable[Year],0)),0))+AnnualModelTable[[#This Row],[Cash Before Refi/Sale]]+AnnualModelTable[[#This Row],[Net Refi/Sale Proceeds]]-AnnualModelTable[[#This Row],[Reserve Funding]]) -> 0 | M12: =IF(AnnualModelTable[[#This Row],[Year]]>SaleExitYear,0,SUM(INDEX(WaterfallTable[Total Dist A],MATCH(AnnualModelTable[[#This Row],[Year]],WaterfallTable[Year],0)),INDEX(WaterfallTable[Total Dist B],MATCH(AnnualModelTable[[#This Row],[Year]],WaterfallTable[Year],0)),INDEX(WaterfallTable[Total Dist2],MATCH(AnnualModelTable[[#This Row],[Year]],WaterfallTable[Year],0)))) -> 0 | N12: =IF(AnnualModelTable[[#This Row],[Year]]>SaleExitYear,0,MAX(0,AnnualModelTable[[#This Row],[Cash Available Before Distributions]]-AnnualModelTable[[#This Row],[Waterfall Distributions]])) -> 0 | O12: =IF(AnnualModelTable[[#This Row],[Year]]>SaleExitYear,0,IF(AnnualModelTable[[#This Row],[Year]]<StabilizationRefiYear,0,IF(AnnualModelTable[[#This Row],[Year]]=SaleExitYear,0,-FV(RefinanceLoanRate/12,(AnnualModelTable[[#This Row],[Year]]-StabilizationRefiYear)*12,PMT(RefinanceLoanRate/12,RefinanceLoanAmortizationYears*12,RefinanceLoanAmount),RefinanceLoanAmount)))) -> 0 | P12: =IF(AnnualModelTable[[#This Row],[Year]]>SaleExitYear,0,IF(AnnualModelTable[[#This Row],[Year]]<StabilizationRefiYear,0,AnnualModelTable[[#This Row],[NOI]]*(1+NOIGrowth)/ExitCapRate)) -> 0
A13: 9 | B13: Operations | C13: =IF(AnnualModelTable[[#This Row],[Year]]>SaleExitYear,0,IF(AnnualModelTable[[#This Row],[Year]]=0,0,IF(AnnualModelTable[[#This Row],[Year]]>=RentScenarioHighEffectiveYear,RentScenarioHighMonthlyGross*12,IF(AnnualModelTable[[#This Row],[Year]]>=RentScenarioMediumEffectiveYear,RentScenarioMediumMonthlyGross*12,IF(AnnualModelTable[[#This Row],[Year]]>=RentScenarioLowEffectiveYear,RentScenarioLowMonthlyGross*12,0))))) -> 0 | D13: =IF(AnnualModelTable[[#This Row],[Year]]>SaleExitYear,0,IF(AnnualModelTable[[#This Row],[Year]]=0,0,AnnualModelTable[[#This Row],[Gross Potential Rent]]*IF(AnnualModelTable[[#This Row],[Year]]=1,LeaseUpOccupancy,StabilizedOccupancy))) -> 0 | E13: =IF(AnnualModelTable[[#This Row],[Year]]>SaleExitYear,0,AnnualModelTable[[#This Row],[Occupancy Effective Gross Income]]*OperatingExpenseRatio) -> 0 | F13: =IF(AnnualModelTable[[#This Row],[Year]]>SaleExitYear,0,AnnualModelTable[[#This Row],[Occupancy Effective Gross Income]]-AnnualModelTable[[#This Row],[Operating Expenses]]) -> 0 | G13: =IF(AnnualModelTable[[#This Row],[Year]]>SaleExitYear,0,IF(AND(AnnualModelTable[[#This Row],[Year]]>=1,AnnualModelTable[[#This Row],[Year]]<StabilizationRefiYear),ExistingDebtServiceAnnual,IF(AND(AnnualModelTable[[#This Row],[Year]]>=StabilizationRefiYear,AnnualModelTable[[#This Row],[Year]]<=SaleExitYear),-PMT(RefinanceLoanRate/12,RefinanceLoanAmortizationYears*12,RefinanceLoanAmount)*12,0))) -> 0 | H13: =IF(AnnualModelTable[[#This Row],[Year]]>SaleExitYear,0,AnnualModelTable[[#This Row],[NOI]]-AnnualModelTable[[#This Row],[Debt Service]]) -> 0 | I13: =IF(AnnualModelTable[[#This Row],[Year]]>SaleExitYear,0,IF(AnnualModelTable[[#This Row],[Year]]=0,SponsorPropertyPayment,IF(AnnualModelTable[[#This Row],[Year]]=StabilizationRefiYear,MAX(0,RefinanceLoanAmount-TotalExistingDebt),IF(AnnualModelTable[[#This Row],[Year]]=SaleExitYear,MAX(0,AnnualModelTable[[#This Row],[Property Value / Refi Value]]*(1-SellingCosts)-AnnualModelTable[[#This Row],[Loan Balance]]),0)))) -> 0 | J13: =IF(AnnualModelTable[[#This Row],[Year]]>SaleExitYear,0,IF(AnnualModelTable[[#This Row],[Year]]=0,0,MIN(MAX(0,RepairsMaintenanceReserveTarget-IFERROR(INDEX(AnnualModelTable[Reserve Balance],MATCH(AnnualModelTable[[#This Row],[Year]]-1,AnnualModelTable[Year],0)),0)),MAX(0,IFERROR(INDEX(AnnualModelTable[Ending Cash Balance],MATCH(AnnualModelTable[[#This Row],[Year]]-1,AnnualModelTable[Year],0)),0)+AnnualModelTable[[#This Row],[Cash Before Refi/Sale]]+AnnualModelTable[[#This Row],[Net Refi/Sale Proceeds]])))) -> 0 | K13: =IF(AnnualModelTable[[#This Row],[Year]]>SaleExitYear,0,IF(AnnualModelTable[[#This Row],[Year]]=0,0,IFERROR(INDEX(AnnualModelTable[Reserve Balance],MATCH(AnnualModelTable[[#This Row],[Year]]-1,AnnualModelTable[Year],0)),0)+AnnualModelTable[[#This Row],[Reserve Funding]])) -> 0 | L13: =IF(AnnualModelTable[[#This Row],[Year]]>SaleExitYear,0,IF(AnnualModelTable[[#This Row],[Year]]=0,0,IFERROR(INDEX(AnnualModelTable[Ending Cash Balance],MATCH(AnnualModelTable[[#This Row],[Year]]-1,AnnualModelTable[Year],0)),0))+AnnualModelTable[[#This Row],[Cash Before Refi/Sale]]+AnnualModelTable[[#This Row],[Net Refi/Sale Proceeds]]-AnnualModelTable[[#This Row],[Reserve Funding]]) -> 0 | M13: =IF(AnnualModelTable[[#This Row],[Year]]>SaleExitYear,0,SUM(INDEX(WaterfallTable[Total Dist A],MATCH(AnnualModelTable[[#This Row],[Year]],WaterfallTable[Year],0)),INDEX(WaterfallTable[Total Dist B],MATCH(AnnualModelTable[[#This Row],[Year]],WaterfallTable[Year],0)),INDEX(WaterfallTable[Total Dist2],MATCH(AnnualModelTable[[#This Row],[Year]],WaterfallTable[Year],0)))) -> 0 | N13: =IF(AnnualModelTable[[#This Row],[Year]]>SaleExitYear,0,MAX(0,AnnualModelTable[[#This Row],[Cash Available Before Distributions]]-AnnualModelTable[[#This Row],[Waterfall Distributions]])) -> 0 | O13: =IF(AnnualModelTable[[#This Row],[Year]]>SaleExitYear,0,IF(AnnualModelTable[[#This Row],[Year]]<StabilizationRefiYear,0,IF(AnnualModelTable[[#This Row],[Year]]=SaleExitYear,0,-FV(RefinanceLoanRate/12,(AnnualModelTable[[#This Row],[Year]]-StabilizationRefiYear)*12,PMT(RefinanceLoanRate/12,RefinanceLoanAmortizationYears*12,RefinanceLoanAmount),RefinanceLoanAmount)))) -> 0 | P13: =IF(AnnualModelTable[[#This Row],[Year]]>SaleExitYear,0,IF(AnnualModelTable[[#This Row],[Year]]<StabilizationRefiYear,0,AnnualModelTable[[#This Row],[NOI]]*(1+NOIGrowth)/ExitCapRate)) -> 0
A14: 10 | B14: Exit | C14: =IF(AnnualModelTable[[#This Row],[Year]]>SaleExitYear,0,IF(AnnualModelTable[[#This Row],[Year]]=0,0,IF(AnnualModelTable[[#This Row],[Year]]>=RentScenarioHighEffectiveYear,RentScenarioHighMonthlyGross*12,IF(AnnualModelTable[[#This Row],[Year]]>=RentScenarioMediumEffectiveYear,RentScenarioMediumMonthlyGross*12,IF(AnnualModelTable[[#This Row],[Year]]>=RentScenarioLowEffectiveYear,RentScenarioLowMonthlyGross*12,0))))) -> 0 | D14: =IF(AnnualModelTable[[#This Row],[Year]]>SaleExitYear,0,IF(AnnualModelTable[[#This Row],[Year]]=0,0,AnnualModelTable[[#This Row],[Gross Potential Rent]]*IF(AnnualModelTable[[#This Row],[Year]]=1,LeaseUpOccupancy,StabilizedOccupancy))) -> 0 | E14: =IF(AnnualModelTable[[#This Row],[Year]]>SaleExitYear,0,AnnualModelTable[[#This Row],[Occupancy Effective Gross Income]]*OperatingExpenseRatio) -> 0 | F14: =IF(AnnualModelTable[[#This Row],[Year]]>SaleExitYear,0,AnnualModelTable[[#This Row],[Occupancy Effective Gross Income]]-AnnualModelTable[[#This Row],[Operating Expenses]]) -> 0 | G14: =IF(AnnualModelTable[[#This Row],[Year]]>SaleExitYear,0,IF(AND(AnnualModelTable[[#This Row],[Year]]>=1,AnnualModelTable[[#This Row],[Year]]<StabilizationRefiYear),ExistingDebtServiceAnnual,IF(AND(AnnualModelTable[[#This Row],[Year]]>=StabilizationRefiYear,AnnualModelTable[[#This Row],[Year]]<=SaleExitYear),-PMT(RefinanceLoanRate/12,RefinanceLoanAmortizationYears*12,RefinanceLoanAmount)*12,0))) -> 0 | H14: =IF(AnnualModelTable[[#This Row],[Year]]>SaleExitYear,0,AnnualModelTable[[#This Row],[NOI]]-AnnualModelTable[[#This Row],[Debt Service]]) -> 0 | I14: =IF(AnnualModelTable[[#This Row],[Year]]>SaleExitYear,0,IF(AnnualModelTable[[#This Row],[Year]]=0,SponsorPropertyPayment,IF(AnnualModelTable[[#This Row],[Year]]=StabilizationRefiYear,MAX(0,RefinanceLoanAmount-TotalExistingDebt),IF(AnnualModelTable[[#This Row],[Year]]=SaleExitYear,MAX(0,AnnualModelTable[[#This Row],[Property Value / Refi Value]]*(1-SellingCosts)-AnnualModelTable[[#This Row],[Loan Balance]]),0)))) -> 0 | J14: =IF(AnnualModelTable[[#This Row],[Year]]>SaleExitYear,0,IF(AnnualModelTable[[#This Row],[Year]]=0,0,MIN(MAX(0,RepairsMaintenanceReserveTarget-IFERROR(INDEX(AnnualModelTable[Reserve Balance],MATCH(AnnualModelTable[[#This Row],[Year]]-1,AnnualModelTable[Year],0)),0)),MAX(0,IFERROR(INDEX(AnnualModelTable[Ending Cash Balance],MATCH(AnnualModelTable[[#This Row],[Year]]-1,AnnualModelTable[Year],0)),0)+AnnualModelTable[[#This Row],[Cash Before Refi/Sale]]+AnnualModelTable[[#This Row],[Net Refi/Sale Proceeds]])))) -> 0 | K14: =IF(AnnualModelTable[[#This Row],[Year]]>SaleExitYear,0,IF(AnnualModelTable[[#This Row],[Year]]=0,0,IFERROR(INDEX(AnnualModelTable[Reserve Balance],MATCH(AnnualModelTable[[#This Row],[Year]]-1,AnnualModelTable[Year],0)),0)+AnnualModelTable[[#This Row],[Reserve Funding]])) -> 0 | L14: =IF(AnnualModelTable[[#This Row],[Year]]>SaleExitYear,0,IF(AnnualModelTable[[#This Row],[Year]]=0,0,IFERROR(INDEX(AnnualModelTable[Ending Cash Balance],MATCH(AnnualModelTable[[#This Row],[Year]]-1,AnnualModelTable[Year],0)),0))+AnnualModelTable[[#This Row],[Cash Before Refi/Sale]]+AnnualModelTable[[#This Row],[Net Refi/Sale Proceeds]]-AnnualModelTable[[#This Row],[Reserve Funding]]) -> 0 | M14: =IF(AnnualModelTable[[#This Row],[Year]]>SaleExitYear,0,SUM(INDEX(WaterfallTable[Total Dist A],MATCH(AnnualModelTable[[#This Row],[Year]],WaterfallTable[Year],0)),INDEX(WaterfallTable[Total Dist B],MATCH(AnnualModelTable[[#This Row],[Year]],WaterfallTable[Year],0)),INDEX(WaterfallTable[Total Dist2],MATCH(AnnualModelTable[[#This Row],[Year]],WaterfallTable[Year],0)))) -> 0 | N14: =IF(AnnualModelTable[[#This Row],[Year]]>SaleExitYear,0,MAX(0,AnnualModelTable[[#This Row],[Cash Available Before Distributions]]-AnnualModelTable[[#This Row],[Waterfall Distributions]])) -> 0 | O14: =IF(AnnualModelTable[[#This Row],[Year]]>SaleExitYear,0,IF(AnnualModelTable[[#This Row],[Year]]<StabilizationRefiYear,0,IF(AnnualModelTable[[#This Row],[Year]]=SaleExitYear,0,-FV(RefinanceLoanRate/12,(AnnualModelTable[[#This Row],[Year]]-StabilizationRefiYear)*12,PMT(RefinanceLoanRate/12,RefinanceLoanAmortizationYears*12,RefinanceLoanAmount),RefinanceLoanAmount)))) -> 0 | P14: =IF(AnnualModelTable[[#This Row],[Year]]>SaleExitYear,0,IF(AnnualModelTable[[#This Row],[Year]]<StabilizationRefiYear,0,AnnualModelTable[[#This Row],[NOI]]*(1+NOIGrowth)/ExitCapRate)) -> 0

Sheet Waterfall
A1: Annual Waterfall
C2: Class A | J2: Class B | N2: Sponsor | R2: Refi Year | S2: Exit Year
A3: Year | B3: Cash Available | C3: Pref Accrued | D3: Pref Paid | E3: End of Year Pref Balance | F3: Capital Balance A | G3: Capital Returned A | H3: Residual A | I3: Total Dist A | J3: Capital Balance B | K3: Capital Returned B | L3: Residual B | M3: Total Dist B | N3: Property Payment | O3: Residual | P3: Total Dist2 | R3: 3 | S3: 5
A4: 0 | B4: =IF(WaterfallTable[[#This Row],[Year]]>SaleExitYear,0,INDEX(AnnualModelTable[Cash Available Before Distributions],MATCH(WaterfallTable[[#This Row],[Year]],AnnualModelTable[Year],0))) -> 150000 | C4: =IF(WaterfallTable[[#This Row],[Year]]>SaleExitYear,0,WaterfallTable[[#This Row],[Capital Balance A]]*ClassAPreferredReturn) -> 24000 | D4: =IF(WaterfallTable[[#This Row],[Year]]>SaleExitYear,0,IF(WaterfallTable[[#This Row],[Year]]=0,0,MIN(WaterfallTable[[#This Row],[Cash Available]],0+WaterfallTable[[#This Row],[Pref Accrued]]))) -> 0 | E4: =IF(WaterfallTable[[#This Row],[Year]]>SaleExitYear,0,MAX(0,0+WaterfallTable[[#This Row],[Pref Accrued]]-WaterfallTable[[#This Row],[Pref Paid]])) -> 24000 | F4: =IF(WaterfallTable[[#This Row],[Year]]>SaleExitYear,0,ClassACapital) -> 300000 | G4: =IF(WaterfallTable[[#This Row],[Year]]>SaleExitYear,0,IF(WaterfallTable[[#This Row],[Year]]=0,0,MIN(MAX(0,WaterfallTable[[#This Row],[Cash Available]]-WaterfallTable[[#This Row],[Pref Paid]]),WaterfallTable[[#This Row],[Capital Balance A]]))) -> 0 | H4: =IF(WaterfallTable[[#This Row],[Year]]>SaleExitYear,0,IF(WaterfallTable[[#This Row],[Year]]=0,0,MAX(0,WaterfallTable[[#This Row],[Cash Available]]-WaterfallTable[[#This Row],[Pref Paid]]-WaterfallTable[[#This Row],[Capital Returned A]]-WaterfallTable[[#This Row],[Capital Returned B]])*ClassAResidualShare)) -> 0 | I4: =IF(WaterfallTable[[#This Row],[Year]]>SaleExitYear,0,WaterfallTable[[#This Row],[Pref Paid]]+WaterfallTable[[#This Row],[Capital Returned A]]+WaterfallTable[[#This Row],[Residual A]]) -> 0 | J4: =IF(WaterfallTable[[#This Row],[Year]]>SaleExitYear,0,ClassBCapital) -> 597500 | K4: =IF(WaterfallTable[[#This Row],[Year]]>SaleExitYear,0,IF(WaterfallTable[[#This Row],[Year]]=0,0,IF(ClassBReturnPriority=1,MIN(MAX(0,WaterfallTable[[#This Row],[Cash Available]]-WaterfallTable[[#This Row],[Pref Paid]]-WaterfallTable[[#This Row],[Capital Returned A]]),WaterfallTable[[#This Row],[ Capital Balance B]]),0))) -> 0 | L4: =IF(WaterfallTable[[#This Row],[Year]]>SaleExitYear,0,IF(WaterfallTable[[#This Row],[Year]]=0,0,MAX(0,WaterfallTable[[#This Row],[Cash Available]]-WaterfallTable[[#This Row],[Pref Paid]]-WaterfallTable[[#This Row],[Capital Returned A]]-WaterfallTable[[#This Row],[Capital Returned B]])*ClassBResidualShare)) -> 0 | M4: =IF(WaterfallTable[[#This Row],[Year]]>SaleExitYear,0,WaterfallTable[[#This Row],[Capital Returned B]]+WaterfallTable[[#This Row],[ Residual B]]) -> 0 | N4: =IF(WaterfallTable[[#This Row],[Year]]>SaleExitYear,0,IF(WaterfallTable[[#This Row],[Year]]=0,SponsorPropertyPayment,0)) -> 150000 | O4: =IF(WaterfallTable[[#This Row],[Year]]>SaleExitYear,0,IF(WaterfallTable[[#This Row],[Year]]=0,0,MAX(0,WaterfallTable[[#This Row],[Cash Available]]-WaterfallTable[[#This Row],[Pref Paid]]-WaterfallTable[[#This Row],[Capital Returned A]]-WaterfallTable[[#This Row],[Capital Returned B]])*SponsorResidualShare)) -> 0 | P4: =IF(WaterfallTable[[#This Row],[Year]]>SaleExitYear,0,WaterfallTable[[#This Row],[Property Payment]]+WaterfallTable[[#This Row],[Residual]]) -> 150000
A5: 1 | B5: =IF(WaterfallTable[[#This Row],[Year]]>SaleExitYear,0,INDEX(AnnualModelTable[Cash Available Before Distributions],MATCH(WaterfallTable[[#This Row],[Year]],AnnualModelTable[Year],0))) -> 5218.2079 | C5: =IF(WaterfallTable[[#This Row],[Year]]>SaleExitYear,0,WaterfallTable[[#This Row],[Capital Balance A]]*ClassAPreferredReturn) -> 24000 | D5: =IF(WaterfallTable[[#This Row],[Year]]>SaleExitYear,0,IF(WaterfallTable[[#This Row],[Year]]=0,0,MIN(WaterfallTable[[#This Row],[Cash Available]],INDEX(WaterfallTable[End of Year Pref Balance],1)+WaterfallTable[[#This Row],[Pref Accrued]]))) -> 5218.2079 | E5: =IF(WaterfallTable[[#This Row],[Year]]>SaleExitYear,0,MAX(0,INDEX(WaterfallTable[End of Year Pref Balance],1)+WaterfallTable[[#This Row],[Pref Accrued]]-WaterfallTable[[#This Row],[Pref Paid]])) -> 42781.792 | F5: =IF(WaterfallTable[[#This Row],[Year]]>SaleExitYear,0,MAX(0,INDEX(WaterfallTable[Capital Balance A],1)-INDEX(WaterfallTable[Capital Returned A],1))) -> 300000 | G5: =IF(WaterfallTable[[#This Row],[Year]]>SaleExitYear,0,IF(WaterfallTable[[#This Row],[Year]]=0,0,MIN(MAX(0,WaterfallTable[[#This Row],[Cash Available]]-WaterfallTable[[#This Row],[Pref Paid]]),WaterfallTable[[#This Row],[Capital Balance A]]))) -> 0 | H5: =IF(WaterfallTable[[#This Row],[Year]]>SaleExitYear,0,IF(WaterfallTable[[#This Row],[Year]]=0,0,MAX(0,WaterfallTable[[#This Row],[Cash Available]]-WaterfallTable[[#This Row],[Pref Paid]]-WaterfallTable[[#This Row],[Capital Returned A]]-WaterfallTable[[#This Row],[Capital Returned B]])*ClassAResidualShare)) -> 0 | I5: =IF(WaterfallTable[[#This Row],[Year]]>SaleExitYear,0,WaterfallTable[[#This Row],[Pref Paid]]+WaterfallTable[[#This Row],[Capital Returned A]]+WaterfallTable[[#This Row],[Residual A]]) -> 5218.2079 | J5: =IF(WaterfallTable[[#This Row],[Year]]>SaleExitYear,0,MAX(0,INDEX(WaterfallTable[[ Capital Balance B]],1)-INDEX(WaterfallTable[Capital Returned B],1))) -> 597500 | K5: =IF(WaterfallTable[[#This Row],[Year]]>SaleExitYear,0,IF(WaterfallTable[[#This Row],[Year]]=0,0,IF(ClassBReturnPriority=1,MIN(MAX(0,WaterfallTable[[#This Row],[Cash Available]]-WaterfallTable[[#This Row],[Pref Paid]]-WaterfallTable[[#This Row],[Capital Returned A]]),WaterfallTable[[#This Row],[ Capital Balance B]]),0))) -> 0 | L5: =IF(WaterfallTable[[#This Row],[Year]]>SaleExitYear,0,IF(WaterfallTable[[#This Row],[Year]]=0,0,MAX(0,WaterfallTable[[#This Row],[Cash Available]]-WaterfallTable[[#This Row],[Pref Paid]]-WaterfallTable[[#This Row],[Capital Returned A]]-WaterfallTable[[#This Row],[Capital Returned B]])*ClassBResidualShare)) -> 0 | M5: =IF(WaterfallTable[[#This Row],[Year]]>SaleExitYear,0,WaterfallTable[[#This Row],[Capital Returned B]]+WaterfallTable[[#This Row],[ Residual B]]) -> 0 | N5: =IF(WaterfallTable[[#This Row],[Year]]>SaleExitYear,0,IF(WaterfallTable[[#This Row],[Year]]=0,SponsorPropertyPayment,0)) -> 0 | O5: =IF(WaterfallTable[[#This Row],[Year]]>SaleExitYear,0,IF(WaterfallTable[[#This Row],[Year]]=0,0,MAX(0,WaterfallTable[[#This Row],[Cash Available]]-WaterfallTable[[#This Row],[Pref Paid]]-WaterfallTable[[#This Row],[Capital Returned A]]-WaterfallTable[[#This Row],[Capital Returned B]])*SponsorResidualShare)) -> 0 | P5: =IF(WaterfallTable[[#This Row],[Year]]>SaleExitYear,0,WaterfallTable[[#This Row],[Property Payment]]+WaterfallTable[[#This Row],[Residual]]) -> 0
A6: 2 | B6: =IF(WaterfallTable[[#This Row],[Year]]>SaleExitYear,0,INDEX(AnnualModelTable[Cash Available Before Distributions],MATCH(WaterfallTable[[#This Row],[Year]],AnnualModelTable[Year],0))) -> 50173.32 | C6: =IF(WaterfallTable[[#This Row],[Year]]>SaleExitYear,0,WaterfallTable[[#This Row],[Capital Balance A]]*ClassAPreferredReturn) -> 24000 | D6: =IF(WaterfallTable[[#This Row],[Year]]>SaleExitYear,0,IF(WaterfallTable[[#This Row],[Year]]=0,0,MIN(WaterfallTable[[#This Row],[Cash Available]],INDEX(WaterfallTable[End of Year Pref Balance],2)+WaterfallTable[[#This Row],[Pref Accrued]]))) -> 50173.32 | E6: =IF(WaterfallTable[[#This Row],[Year]]>SaleExitYear,0,MAX(0,INDEX(WaterfallTable[End of Year Pref Balance],2)+WaterfallTable[[#This Row],[Pref Accrued]]-WaterfallTable[[#This Row],[Pref Paid]])) -> 16608.472 | F6: =IF(WaterfallTable[[#This Row],[Year]]>SaleExitYear,0,MAX(0,INDEX(WaterfallTable[Capital Balance A],2)-INDEX(WaterfallTable[Capital Returned A],2))) -> 300000 | G6: =IF(WaterfallTable[[#This Row],[Year]]>SaleExitYear,0,IF(WaterfallTable[[#This Row],[Year]]=0,0,MIN(MAX(0,WaterfallTable[[#This Row],[Cash Available]]-WaterfallTable[[#This Row],[Pref Paid]]),WaterfallTable[[#This Row],[Capital Balance A]]))) -> 0 | H6: =IF(WaterfallTable[[#This Row],[Year]]>SaleExitYear,0,IF(WaterfallTable[[#This Row],[Year]]=0,0,MAX(0,WaterfallTable[[#This Row],[Cash Available]]-WaterfallTable[[#This Row],[Pref Paid]]-WaterfallTable[[#This Row],[Capital Returned A]]-WaterfallTable[[#This Row],[Capital Returned B]])*ClassAResidualShare)) -> 0 | I6: =IF(WaterfallTable[[#This Row],[Year]]>SaleExitYear,0,WaterfallTable[[#This Row],[Pref Paid]]+WaterfallTable[[#This Row],[Capital Returned A]]+WaterfallTable[[#This Row],[Residual A]]) -> 50173.32 | J6: =IF(WaterfallTable[[#This Row],[Year]]>SaleExitYear,0,MAX(0,INDEX(WaterfallTable[[ Capital Balance B]],2)-INDEX(WaterfallTable[Capital Returned B],2))) -> 597500 | K6: =IF(WaterfallTable[[#This Row],[Year]]>SaleExitYear,0,IF(WaterfallTable[[#This Row],[Year]]=0,0,IF(ClassBReturnPriority=1,MIN(MAX(0,WaterfallTable[[#This Row],[Cash Available]]-WaterfallTable[[#This Row],[Pref Paid]]-WaterfallTable[[#This Row],[Capital Returned A]]),WaterfallTable[[#This Row],[ Capital Balance B]]),0))) -> 0 | L6: =IF(WaterfallTable[[#This Row],[Year]]>SaleExitYear,0,IF(WaterfallTable[[#This Row],[Year]]=0,0,MAX(0,WaterfallTable[[#This Row],[Cash Available]]-WaterfallTable[[#This Row],[Pref Paid]]-WaterfallTable[[#This Row],[Capital Returned A]]-WaterfallTable[[#This Row],[Capital Returned B]])*ClassBResidualShare)) -> 0 | M6: =IF(WaterfallTable[[#This Row],[Year]]>SaleExitYear,0,WaterfallTable[[#This Row],[Capital Returned B]]+WaterfallTable[[#This Row],[ Residual B]]) -> 0 | N6: =IF(WaterfallTable[[#This Row],[Year]]>SaleExitYear,0,IF(WaterfallTable[[#This Row],[Year]]=0,SponsorPropertyPayment,0)) -> 0 | O6: =IF(WaterfallTable[[#This Row],[Year]]>SaleExitYear,0,IF(WaterfallTable[[#This Row],[Year]]=0,0,MAX(0,WaterfallTable[[#This Row],[Cash Available]]-WaterfallTable[[#This Row],[Pref Paid]]-WaterfallTable[[#This Row],[Capital Returned A]]-WaterfallTable[[#This Row],[Capital Returned B]])*SponsorResidualShare)) -> 0 | P6: =IF(WaterfallTable[[#This Row],[Year]]>SaleExitYear,0,WaterfallTable[[#This Row],[Property Payment]]+WaterfallTable[[#This Row],[Residual]]) -> 0
A7: 3 | B7: =IF(WaterfallTable[[#This Row],[Year]]>SaleExitYear,0,INDEX(AnnualModelTable[Cash Available Before Distributions],MATCH(WaterfallTable[[#This Row],[Year]],AnnualModelTable[Year],0))) -> 553829.42 | C7: =IF(WaterfallTable[[#This Row],[Year]]>SaleExitYear,0,WaterfallTable[[#This Row],[Capital Balance A]]*ClassAPreferredReturn) -> 24000 | D7: =IF(WaterfallTable[[#This Row],[Year]]>SaleExitYear,0,IF(WaterfallTable[[#This Row],[Year]]=0,0,MIN(WaterfallTable[[#This Row],[Cash Available]],INDEX(WaterfallTable[End of Year Pref Balance],3)+WaterfallTable[[#This Row],[Pref Accrued]]))) -> 40608.472 | E7: =IF(WaterfallTable[[#This Row],[Year]]>SaleExitYear,0,MAX(0,INDEX(WaterfallTable[End of Year Pref Balance],3)+WaterfallTable[[#This Row],[Pref Accrued]]-WaterfallTable[[#This Row],[Pref Paid]])) -> 0 | F7: =IF(WaterfallTable[[#This Row],[Year]]>SaleExitYear,0,MAX(0,INDEX(WaterfallTable[Capital Balance A],3)-INDEX(WaterfallTable[Capital Returned A],3))) -> 300000 | G7: =IF(WaterfallTable[[#This Row],[Year]]>SaleExitYear,0,IF(WaterfallTable[[#This Row],[Year]]=0,0,MIN(MAX(0,WaterfallTable[[#This Row],[Cash Available]]-WaterfallTable[[#This Row],[Pref Paid]]),WaterfallTable[[#This Row],[Capital Balance A]]))) -> 300000 | H7: =IF(WaterfallTable[[#This Row],[Year]]>SaleExitYear,0,IF(WaterfallTable[[#This Row],[Year]]=0,0,MAX(0,WaterfallTable[[#This Row],[Cash Available]]-WaterfallTable[[#This Row],[Pref Paid]]-WaterfallTable[[#This Row],[Capital Returned A]]-WaterfallTable[[#This Row],[Capital Returned B]])*ClassAResidualShare)) -> 0 | I7: =IF(WaterfallTable[[#This Row],[Year]]>SaleExitYear,0,WaterfallTable[[#This Row],[Pref Paid]]+WaterfallTable[[#This Row],[Capital Returned A]]+WaterfallTable[[#This Row],[Residual A]]) -> 340608.47 | J7: =IF(WaterfallTable[[#This Row],[Year]]>SaleExitYear,0,MAX(0,INDEX(WaterfallTable[[ Capital Balance B]],3)-INDEX(WaterfallTable[Capital Returned B],3))) -> 597500 | K7: =IF(WaterfallTable[[#This Row],[Year]]>SaleExitYear,0,IF(WaterfallTable[[#This Row],[Year]]=0,0,IF(ClassBReturnPriority=1,MIN(MAX(0,WaterfallTable[[#This Row],[Cash Available]]-WaterfallTable[[#This Row],[Pref Paid]]-WaterfallTable[[#This Row],[Capital Returned A]]),WaterfallTable[[#This Row],[ Capital Balance B]]),0))) -> 213220.95 | L7: =IF(WaterfallTable[[#This Row],[Year]]>SaleExitYear,0,IF(WaterfallTable[[#This Row],[Year]]=0,0,MAX(0,WaterfallTable[[#This Row],[Cash Available]]-WaterfallTable[[#This Row],[Pref Paid]]-WaterfallTable[[#This Row],[Capital Returned A]]-WaterfallTable[[#This Row],[Capital Returned B]])*ClassBResidualShare)) -> 0 | M7: =IF(WaterfallTable[[#This Row],[Year]]>SaleExitYear,0,WaterfallTable[[#This Row],[Capital Returned B]]+WaterfallTable[[#This Row],[ Residual B]]) -> 213220.95 | N7: =IF(WaterfallTable[[#This Row],[Year]]>SaleExitYear,0,IF(WaterfallTable[[#This Row],[Year]]=0,SponsorPropertyPayment,0)) -> 0 | O7: =IF(WaterfallTable[[#This Row],[Year]]>SaleExitYear,0,IF(WaterfallTable[[#This Row],[Year]]=0,0,MAX(0,WaterfallTable[[#This Row],[Cash Available]]-WaterfallTable[[#This Row],[Pref Paid]]-WaterfallTable[[#This Row],[Capital Returned A]]-WaterfallTable[[#This Row],[Capital Returned B]])*SponsorResidualShare)) -> 0 | P7: =IF(WaterfallTable[[#This Row],[Year]]>SaleExitYear,0,WaterfallTable[[#This Row],[Property Payment]]+WaterfallTable[[#This Row],[Residual]]) -> 0
A8: 4 | B8: =IF(WaterfallTable[[#This Row],[Year]]>SaleExitYear,0,INDEX(AnnualModelTable[Cash Available Before Distributions],MATCH(WaterfallTable[[#This Row],[Year]],AnnualModelTable[Year],0))) -> 15552.977 | C8: =IF(WaterfallTable[[#This Row],[Year]]>SaleExitYear,0,WaterfallTable[[#This Row],[Capital Balance A]]*ClassAPreferredReturn) -> 0 | D8: =IF(WaterfallTable[[#This Row],[Year]]>SaleExitYear,0,IF(WaterfallTable[[#This Row],[Year]]=0,0,MIN(WaterfallTable[[#This Row],[Cash Available]],INDEX(WaterfallTable[End of Year Pref Balance],4)+WaterfallTable[[#This Row],[Pref Accrued]]))) -> 0 | E8: =IF(WaterfallTable[[#This Row],[Year]]>SaleExitYear,0,MAX(0,INDEX(WaterfallTable[End of Year Pref Balance],4)+WaterfallTable[[#This Row],[Pref Accrued]]-WaterfallTable[[#This Row],[Pref Paid]])) -> 0 | F8: =IF(WaterfallTable[[#This Row],[Year]]>SaleExitYear,0,MAX(0,INDEX(WaterfallTable[Capital Balance A],4)-INDEX(WaterfallTable[Capital Returned A],4))) -> 0 | G8: =IF(WaterfallTable[[#This Row],[Year]]>SaleExitYear,0,IF(WaterfallTable[[#This Row],[Year]]=0,0,MIN(MAX(0,WaterfallTable[[#This Row],[Cash Available]]-WaterfallTable[[#This Row],[Pref Paid]]),WaterfallTable[[#This Row],[Capital Balance A]]))) -> 0 | H8: =IF(WaterfallTable[[#This Row],[Year]]>SaleExitYear,0,IF(WaterfallTable[[#This Row],[Year]]=0,0,MAX(0,WaterfallTable[[#This Row],[Cash Available]]-WaterfallTable[[#This Row],[Pref Paid]]-WaterfallTable[[#This Row],[Capital Returned A]]-WaterfallTable[[#This Row],[Capital Returned B]])*ClassAResidualShare)) -> 0 | I8: =IF(WaterfallTable[[#This Row],[Year]]>SaleExitYear,0,WaterfallTable[[#This Row],[Pref Paid]]+WaterfallTable[[#This Row],[Capital Returned A]]+WaterfallTable[[#This Row],[Residual A]]) -> 0 | J8: =IF(WaterfallTable[[#This Row],[Year]]>SaleExitYear,0,MAX(0,INDEX(WaterfallTable[[ Capital Balance B]],4)-INDEX(WaterfallTable[Capital Returned B],4))) -> 384279.05 | K8: =IF(WaterfallTable[[#This Row],[Year]]>SaleExitYear,0,IF(WaterfallTable[[#This Row],[Year]]=0,0,IF(ClassBReturnPriority=1,MIN(MAX(0,WaterfallTable[[#This Row],[Cash Available]]-WaterfallTable[[#This Row],[Pref Paid]]-WaterfallTable[[#This Row],[Capital Returned A]]),WaterfallTable[[#This Row],[ Capital Balance B]]),0))) -> 15552.977 | L8: =IF(WaterfallTable[[#This Row],[Year]]>SaleExitYear,0,IF(WaterfallTable[[#This Row],[Year]]=0,0,MAX(0,WaterfallTable[[#This Row],[Cash Available]]-WaterfallTable[[#This Row],[Pref Paid]]-WaterfallTable[[#This Row],[Capital Returned A]]-WaterfallTable[[#This Row],[Capital Returned B]])*ClassBResidualShare)) -> 0 | M8: =IF(WaterfallTable[[#This Row],[Year]]>SaleExitYear,0,WaterfallTable[[#This Row],[Capital Returned B]]+WaterfallTable[[#This Row],[ Residual B]]) -> 15552.977 | N8: =IF(WaterfallTable[[#This Row],[Year]]>SaleExitYear,0,IF(WaterfallTable[[#This Row],[Year]]=0,SponsorPropertyPayment,0)) -> 0 | O8: =IF(WaterfallTable[[#This Row],[Year]]>SaleExitYear,0,IF(WaterfallTable[[#This Row],[Year]]=0,0,MAX(0,WaterfallTable[[#This Row],[Cash Available]]-WaterfallTable[[#This Row],[Pref Paid]]-WaterfallTable[[#This Row],[Capital Returned A]]-WaterfallTable[[#This Row],[Capital Returned B]])*SponsorResidualShare)) -> 0 | P8: =IF(WaterfallTable[[#This Row],[Year]]>SaleExitYear,0,WaterfallTable[[#This Row],[Property Payment]]+WaterfallTable[[#This Row],[Residual]]) -> 0
A9: 5 | B9: =IF(WaterfallTable[[#This Row],[Year]]>SaleExitYear,0,INDEX(AnnualModelTable[Cash Available Before Distributions],MATCH(WaterfallTable[[#This Row],[Year]],AnnualModelTable[Year],0))) -> 1040740 | C9: =IF(WaterfallTable[[#This Row],[Year]]>SaleExitYear,0,WaterfallTable[[#This Row],[Capital Balance A]]*ClassAPreferredReturn) -> 0 | D9: =IF(WaterfallTable[[#This Row],[Year]]>SaleExitYear,0,IF(WaterfallTable[[#This Row],[Year]]=0,0,MIN(WaterfallTable[[#This Row],[Cash Available]],INDEX(WaterfallTable[End of Year Pref Balance],5)+WaterfallTable[[#This Row],[Pref Accrued]]))) -> 0 | E9: =IF(WaterfallTable[[#This Row],[Year]]>SaleExitYear,0,MAX(0,INDEX(WaterfallTable[End of Year Pref Balance],5)+WaterfallTable[[#This Row],[Pref Accrued]]-WaterfallTable[[#This Row],[Pref Paid]])) -> 0 | F9: =IF(WaterfallTable[[#This Row],[Year]]>SaleExitYear,0,MAX(0,INDEX(WaterfallTable[Capital Balance A],5)-INDEX(WaterfallTable[Capital Returned A],5))) -> 0 | G9: =IF(WaterfallTable[[#This Row],[Year]]>SaleExitYear,0,IF(WaterfallTable[[#This Row],[Year]]=0,0,MIN(MAX(0,WaterfallTable[[#This Row],[Cash Available]]-WaterfallTable[[#This Row],[Pref Paid]]),WaterfallTable[[#This Row],[Capital Balance A]]))) -> 0 | H9: =IF(WaterfallTable[[#This Row],[Year]]>SaleExitYear,0,IF(WaterfallTable[[#This Row],[Year]]=0,0,MAX(0,WaterfallTable[[#This Row],[Cash Available]]-WaterfallTable[[#This Row],[Pref Paid]]-WaterfallTable[[#This Row],[Capital Returned A]]-WaterfallTable[[#This Row],[Capital Returned B]])*ClassAResidualShare)) -> 134777.16 | I9: =IF(WaterfallTable[[#This Row],[Year]]>SaleExitYear,0,WaterfallTable[[#This Row],[Pref Paid]]+WaterfallTable[[#This Row],[Capital Returned A]]+WaterfallTable[[#This Row],[Residual A]]) -> 134777.16 | J9: =IF(WaterfallTable[[#This Row],[Year]]>SaleExitYear,0,MAX(0,INDEX(WaterfallTable[[ Capital Balance B]],5)-INDEX(WaterfallTable[Capital Returned B],5))) -> 368726.08 | K9: =IF(WaterfallTable[[#This Row],[Year]]>SaleExitYear,0,IF(WaterfallTable[[#This Row],[Year]]=0,0,IF(ClassBReturnPriority=1,MIN(MAX(0,WaterfallTable[[#This Row],[Cash Available]]-WaterfallTable[[#This Row],[Pref Paid]]-WaterfallTable[[#This Row],[Capital Returned A]]),WaterfallTable[[#This Row],[ Capital Balance B]]),0))) -> 368726.08 | L9: =IF(WaterfallTable[[#This Row],[Year]]>SaleExitYear,0,IF(WaterfallTable[[#This Row],[Year]]=0,0,MAX(0,WaterfallTable[[#This Row],[Cash Available]]-WaterfallTable[[#This Row],[Pref Paid]]-WaterfallTable[[#This Row],[Capital Returned A]]-WaterfallTable[[#This Row],[Capital Returned B]])*ClassBResidualShare)) -> 268431.19 | M9: =IF(WaterfallTable[[#This Row],[Year]]>SaleExitYear,0,WaterfallTable[[#This Row],[Capital Returned B]]+WaterfallTable[[#This Row],[ Residual B]]) -> 637157.26 | N9: =IF(WaterfallTable[[#This Row],[Year]]>SaleExitYear,0,IF(WaterfallTable[[#This Row],[Year]]=0,SponsorPropertyPayment,0)) -> 0 | O9: =IF(WaterfallTable[[#This Row],[Year]]>SaleExitYear,0,IF(WaterfallTable[[#This Row],[Year]]=0,0,MAX(0,WaterfallTable[[#This Row],[Cash Available]]-WaterfallTable[[#This Row],[Pref Paid]]-WaterfallTable[[#This Row],[Capital Returned A]]-WaterfallTable[[#This Row],[Capital Returned B]])*SponsorResidualShare)) -> 268805.57 | P9: =IF(WaterfallTable[[#This Row],[Year]]>SaleExitYear,0,WaterfallTable[[#This Row],[Property Payment]]+WaterfallTable[[#This Row],[Residual]]) -> 268805.57
A10: 6 | B10: =IF(WaterfallTable[[#This Row],[Year]]>SaleExitYear,0,INDEX(AnnualModelTable[Cash Available Before Distributions],MATCH(WaterfallTable[[#This Row],[Year]],AnnualModelTable[Year],0))) -> 0 | C10: =IF(WaterfallTable[[#This Row],[Year]]>SaleExitYear,0,WaterfallTable[[#This Row],[Capital Balance A]]*ClassAPreferredReturn) -> 0 | D10: =IF(WaterfallTable[[#This Row],[Year]]>SaleExitYear,0,IF(WaterfallTable[[#This Row],[Year]]=0,0,MIN(WaterfallTable[[#This Row],[Cash Available]],INDEX(WaterfallTable[End of Year Pref Balance],6)+WaterfallTable[[#This Row],[Pref Accrued]]))) -> 0 | E10: =IF(WaterfallTable[[#This Row],[Year]]>SaleExitYear,0,MAX(0,INDEX(WaterfallTable[End of Year Pref Balance],6)+WaterfallTable[[#This Row],[Pref Accrued]]-WaterfallTable[[#This Row],[Pref Paid]])) -> 0 | F10: =IF(WaterfallTable[[#This Row],[Year]]>SaleExitYear,0,MAX(0,INDEX(WaterfallTable[Capital Balance A],6)-INDEX(WaterfallTable[Capital Returned A],6))) -> 0 | G10: =IF(WaterfallTable[[#This Row],[Year]]>SaleExitYear,0,IF(WaterfallTable[[#This Row],[Year]]=0,0,MIN(MAX(0,WaterfallTable[[#This Row],[Cash Available]]-WaterfallTable[[#This Row],[Pref Paid]]),WaterfallTable[[#This Row],[Capital Balance A]]))) -> 0 | H10: =IF(WaterfallTable[[#This Row],[Year]]>SaleExitYear,0,IF(WaterfallTable[[#This Row],[Year]]=0,0,MAX(0,WaterfallTable[[#This Row],[Cash Available]]-WaterfallTable[[#This Row],[Pref Paid]]-WaterfallTable[[#This Row],[Capital Returned A]]-WaterfallTable[[#This Row],[Capital Returned B]])*ClassAResidualShare)) -> 0 | I10: =IF(WaterfallTable[[#This Row],[Year]]>SaleExitYear,0,WaterfallTable[[#This Row],[Pref Paid]]+WaterfallTable[[#This Row],[Capital Returned A]]+WaterfallTable[[#This Row],[Residual A]]) -> 0 | J10: =IF(WaterfallTable[[#This Row],[Year]]>SaleExitYear,0,MAX(0,INDEX(WaterfallTable[[ Capital Balance B]],6)-INDEX(WaterfallTable[Capital Returned B],6))) -> 0 | K10: =IF(WaterfallTable[[#This Row],[Year]]>SaleExitYear,0,IF(WaterfallTable[[#This Row],[Year]]=0,0,IF(ClassBReturnPriority=1,MIN(MAX(0,WaterfallTable[[#This Row],[Cash Available]]-WaterfallTable[[#This Row],[Pref Paid]]-WaterfallTable[[#This Row],[Capital Returned A]]),WaterfallTable[[#This Row],[ Capital Balance B]]),0))) -> 0 | L10: =IF(WaterfallTable[[#This Row],[Year]]>SaleExitYear,0,IF(WaterfallTable[[#This Row],[Year]]=0,0,MAX(0,WaterfallTable[[#This Row],[Cash Available]]-WaterfallTable[[#This Row],[Pref Paid]]-WaterfallTable[[#This Row],[Capital Returned A]]-WaterfallTable[[#This Row],[Capital Returned B]])*ClassBResidualShare)) -> 0 | M10: =IF(WaterfallTable[[#This Row],[Year]]>SaleExitYear,0,WaterfallTable[[#This Row],[Capital Returned B]]+WaterfallTable[[#This Row],[ Residual B]]) -> 0 | N10: =IF(WaterfallTable[[#This Row],[Year]]>SaleExitYear,0,IF(WaterfallTable[[#This Row],[Year]]=0,SponsorPropertyPayment,0)) -> 0 | O10: =IF(WaterfallTable[[#This Row],[Year]]>SaleExitYear,0,IF(WaterfallTable[[#This Row],[Year]]=0,0,MAX(0,WaterfallTable[[#This Row],[Cash Available]]-WaterfallTable[[#This Row],[Pref Paid]]-WaterfallTable[[#This Row],[Capital Returned A]]-WaterfallTable[[#This Row],[Capital Returned B]])*SponsorResidualShare)) -> 0 | P10: =IF(WaterfallTable[[#This Row],[Year]]>SaleExitYear,0,WaterfallTable[[#This Row],[Property Payment]]+WaterfallTable[[#This Row],[Residual]]) -> 0
A11: 7 | B11: =IF(WaterfallTable[[#This Row],[Year]]>SaleExitYear,0,INDEX(AnnualModelTable[Cash Available Before Distributions],MATCH(WaterfallTable[[#This Row],[Year]],AnnualModelTable[Year],0))) -> 0 | C11: =IF(WaterfallTable[[#This Row],[Year]]>SaleExitYear,0,WaterfallTable[[#This Row],[Capital Balance A]]*ClassAPreferredReturn) -> 0 | D11: =IF(WaterfallTable[[#This Row],[Year]]>SaleExitYear,0,IF(WaterfallTable[[#This Row],[Year]]=0,0,MIN(WaterfallTable[[#This Row],[Cash Available]],INDEX(WaterfallTable[End of Year Pref Balance],7)+WaterfallTable[[#This Row],[Pref Accrued]]))) -> 0 | E11: =IF(WaterfallTable[[#This Row],[Year]]>SaleExitYear,0,MAX(0,INDEX(WaterfallTable[End of Year Pref Balance],7)+WaterfallTable[[#This Row],[Pref Accrued]]-WaterfallTable[[#This Row],[Pref Paid]])) -> 0 | F11: =IF(WaterfallTable[[#This Row],[Year]]>SaleExitYear,0,MAX(0,INDEX(WaterfallTable[Capital Balance A],7)-INDEX(WaterfallTable[Capital Returned A],7))) -> 0 | G11: =IF(WaterfallTable[[#This Row],[Year]]>SaleExitYear,0,IF(WaterfallTable[[#This Row],[Year]]=0,0,MIN(MAX(0,WaterfallTable[[#This Row],[Cash Available]]-WaterfallTable[[#This Row],[Pref Paid]]),WaterfallTable[[#This Row],[Capital Balance A]]))) -> 0 | H11: =IF(WaterfallTable[[#This Row],[Year]]>SaleExitYear,0,IF(WaterfallTable[[#This Row],[Year]]=0,0,MAX(0,WaterfallTable[[#This Row],[Cash Available]]-WaterfallTable[[#This Row],[Pref Paid]]-WaterfallTable[[#This Row],[Capital Returned A]]-WaterfallTable[[#This Row],[Capital Returned B]])*ClassAResidualShare)) -> 0 | I11: =IF(WaterfallTable[[#This Row],[Year]]>SaleExitYear,0,WaterfallTable[[#This Row],[Pref Paid]]+WaterfallTable[[#This Row],[Capital Returned A]]+WaterfallTable[[#This Row],[Residual A]]) -> 0 | J11: =IF(WaterfallTable[[#This Row],[Year]]>SaleExitYear,0,MAX(0,INDEX(WaterfallTable[[ Capital Balance B]],7)-INDEX(WaterfallTable[Capital Returned B],7))) -> 0 | K11: =IF(WaterfallTable[[#This Row],[Year]]>SaleExitYear,0,IF(WaterfallTable[[#This Row],[Year]]=0,0,IF(ClassBReturnPriority=1,MIN(MAX(0,WaterfallTable[[#This Row],[Cash Available]]-WaterfallTable[[#This Row],[Pref Paid]]-WaterfallTable[[#This Row],[Capital Returned A]]),WaterfallTable[[#This Row],[ Capital Balance B]]),0))) -> 0 | L11: =IF(WaterfallTable[[#This Row],[Year]]>SaleExitYear,0,IF(WaterfallTable[[#This Row],[Year]]=0,0,MAX(0,WaterfallTable[[#This Row],[Cash Available]]-WaterfallTable[[#This Row],[Pref Paid]]-WaterfallTable[[#This Row],[Capital Returned A]]-WaterfallTable[[#This Row],[Capital Returned B]])*ClassBResidualShare)) -> 0 | M11: =IF(WaterfallTable[[#This Row],[Year]]>SaleExitYear,0,WaterfallTable[[#This Row],[Capital Returned B]]+WaterfallTable[[#This Row],[ Residual B]]) -> 0 | N11: =IF(WaterfallTable[[#This Row],[Year]]>SaleExitYear,0,IF(WaterfallTable[[#This Row],[Year]]=0,SponsorPropertyPayment,0)) -> 0 | O11: =IF(WaterfallTable[[#This Row],[Year]]>SaleExitYear,0,IF(WaterfallTable[[#This Row],[Year]]=0,0,MAX(0,WaterfallTable[[#This Row],[Cash Available]]-WaterfallTable[[#This Row],[Pref Paid]]-WaterfallTable[[#This Row],[Capital Returned A]]-WaterfallTable[[#This Row],[Capital Returned B]])*SponsorResidualShare)) -> 0 | P11: =IF(WaterfallTable[[#This Row],[Year]]>SaleExitYear,0,WaterfallTable[[#This Row],[Property Payment]]+WaterfallTable[[#This Row],[Residual]]) -> 0
A12: 8 | B12: =IF(WaterfallTable[[#This Row],[Year]]>SaleExitYear,0,INDEX(AnnualModelTable[Cash Available Before Distributions],MATCH(WaterfallTable[[#This Row],[Year]],AnnualModelTable[Year],0))) -> 0 | C12: =IF(WaterfallTable[[#This Row],[Year]]>SaleExitYear,0,WaterfallTable[[#This Row],[Capital Balance A]]*ClassAPreferredReturn) -> 0 | D12: =IF(WaterfallTable[[#This Row],[Year]]>SaleExitYear,0,IF(WaterfallTable[[#This Row],[Year]]=0,0,MIN(WaterfallTable[[#This Row],[Cash Available]],INDEX(WaterfallTable[End of Year Pref Balance],8)+WaterfallTable[[#This Row],[Pref Accrued]]))) -> 0 | E12: =IF(WaterfallTable[[#This Row],[Year]]>SaleExitYear,0,MAX(0,INDEX(WaterfallTable[End of Year Pref Balance],8)+WaterfallTable[[#This Row],[Pref Accrued]]-WaterfallTable[[#This Row],[Pref Paid]])) -> 0 | F12: =IF(WaterfallTable[[#This Row],[Year]]>SaleExitYear,0,MAX(0,INDEX(WaterfallTable[Capital Balance A],8)-INDEX(WaterfallTable[Capital Returned A],8))) -> 0 | G12: =IF(WaterfallTable[[#This Row],[Year]]>SaleExitYear,0,IF(WaterfallTable[[#This Row],[Year]]=0,0,MIN(MAX(0,WaterfallTable[[#This Row],[Cash Available]]-WaterfallTable[[#This Row],[Pref Paid]]),WaterfallTable[[#This Row],[Capital Balance A]]))) -> 0 | H12: =IF(WaterfallTable[[#This Row],[Year]]>SaleExitYear,0,IF(WaterfallTable[[#This Row],[Year]]=0,0,MAX(0,WaterfallTable[[#This Row],[Cash Available]]-WaterfallTable[[#This Row],[Pref Paid]]-WaterfallTable[[#This Row],[Capital Returned A]]-WaterfallTable[[#This Row],[Capital Returned B]])*ClassAResidualShare)) -> 0 | I12: =IF(WaterfallTable[[#This Row],[Year]]>SaleExitYear,0,WaterfallTable[[#This Row],[Pref Paid]]+WaterfallTable[[#This Row],[Capital Returned A]]+WaterfallTable[[#This Row],[Residual A]]) -> 0 | J12: =IF(WaterfallTable[[#This Row],[Year]]>SaleExitYear,0,MAX(0,INDEX(WaterfallTable[[ Capital Balance B]],8)-INDEX(WaterfallTable[Capital Returned B],8))) -> 0 | K12: =IF(WaterfallTable[[#This Row],[Year]]>SaleExitYear,0,IF(WaterfallTable[[#This Row],[Year]]=0,0,IF(ClassBReturnPriority=1,MIN(MAX(0,WaterfallTable[[#This Row],[Cash Available]]-WaterfallTable[[#This Row],[Pref Paid]]-WaterfallTable[[#This Row],[Capital Returned A]]),WaterfallTable[[#This Row],[ Capital Balance B]]),0))) -> 0 | L12: =IF(WaterfallTable[[#This Row],[Year]]>SaleExitYear,0,IF(WaterfallTable[[#This Row],[Year]]=0,0,MAX(0,WaterfallTable[[#This Row],[Cash Available]]-WaterfallTable[[#This Row],[Pref Paid]]-WaterfallTable[[#This Row],[Capital Returned A]]-WaterfallTable[[#This Row],[Capital Returned B]])*ClassBResidualShare)) -> 0 | M12: =IF(WaterfallTable[[#This Row],[Year]]>SaleExitYear,0,WaterfallTable[[#This Row],[Capital Returned B]]+WaterfallTable[[#This Row],[ Residual B]]) -> 0 | N12: =IF(WaterfallTable[[#This Row],[Year]]>SaleExitYear,0,IF(WaterfallTable[[#This Row],[Year]]=0,SponsorPropertyPayment,0)) -> 0 | O12: =IF(WaterfallTable[[#This Row],[Year]]>SaleExitYear,0,IF(WaterfallTable[[#This Row],[Year]]=0,0,MAX(0,WaterfallTable[[#This Row],[Cash Available]]-WaterfallTable[[#This Row],[Pref Paid]]-WaterfallTable[[#This Row],[Capital Returned A]]-WaterfallTable[[#This Row],[Capital Returned B]])*SponsorResidualShare)) -> 0 | P12: =IF(WaterfallTable[[#This Row],[Year]]>SaleExitYear,0,WaterfallTable[[#This Row],[Property Payment]]+WaterfallTable[[#This Row],[Residual]]) -> 0
A13: 9 | B13: =IF(WaterfallTable[[#This Row],[Year]]>SaleExitYear,0,INDEX(AnnualModelTable[Cash Available Before Distributions],MATCH(WaterfallTable[[#This Row],[Year]],AnnualModelTable[Year],0))) -> 0 | C13: =IF(WaterfallTable[[#This Row],[Year]]>SaleExitYear,0,WaterfallTable[[#This Row],[Capital Balance A]]*ClassAPreferredReturn) -> 0 | D13: =IF(WaterfallTable[[#This Row],[Year]]>SaleExitYear,0,IF(WaterfallTable[[#This Row],[Year]]=0,0,MIN(WaterfallTable[[#This Row],[Cash Available]],INDEX(WaterfallTable[End of Year Pref Balance],9)+WaterfallTable[[#This Row],[Pref Accrued]]))) -> 0 | E13: =IF(WaterfallTable[[#This Row],[Year]]>SaleExitYear,0,MAX(0,INDEX(WaterfallTable[End of Year Pref Balance],9)+WaterfallTable[[#This Row],[Pref Accrued]]-WaterfallTable[[#This Row],[Pref Paid]])) -> 0 | F13: =IF(WaterfallTable[[#This Row],[Year]]>SaleExitYear,0,MAX(0,INDEX(WaterfallTable[Capital Balance A],9)-INDEX(WaterfallTable[Capital Returned A],9))) -> 0 | G13: =IF(WaterfallTable[[#This Row],[Year]]>SaleExitYear,0,IF(WaterfallTable[[#This Row],[Year]]=0,0,MIN(MAX(0,WaterfallTable[[#This Row],[Cash Available]]-WaterfallTable[[#This Row],[Pref Paid]]),WaterfallTable[[#This Row],[Capital Balance A]]))) -> 0 | H13: =IF(WaterfallTable[[#This Row],[Year]]>SaleExitYear,0,IF(WaterfallTable[[#This Row],[Year]]=0,0,MAX(0,WaterfallTable[[#This Row],[Cash Available]]-WaterfallTable[[#This Row],[Pref Paid]]-WaterfallTable[[#This Row],[Capital Returned A]]-WaterfallTable[[#This Row],[Capital Returned B]])*ClassAResidualShare)) -> 0 | I13: =IF(WaterfallTable[[#This Row],[Year]]>SaleExitYear,0,WaterfallTable[[#This Row],[Pref Paid]]+WaterfallTable[[#This Row],[Capital Returned A]]+WaterfallTable[[#This Row],[Residual A]]) -> 0 | J13: =IF(WaterfallTable[[#This Row],[Year]]>SaleExitYear,0,MAX(0,INDEX(WaterfallTable[[ Capital Balance B]],9)-INDEX(WaterfallTable[Capital Returned B],9))) -> 0 | K13: =IF(WaterfallTable[[#This Row],[Year]]>SaleExitYear,0,IF(WaterfallTable[[#This Row],[Year]]=0,0,IF(ClassBReturnPriority=1,MIN(MAX(0,WaterfallTable[[#This Row],[Cash Available]]-WaterfallTable[[#This Row],[Pref Paid]]-WaterfallTable[[#This Row],[Capital Returned A]]),WaterfallTable[[#This Row],[ Capital Balance B]]),0))) -> 0 | L13: =IF(WaterfallTable[[#This Row],[Year]]>SaleExitYear,0,IF(WaterfallTable[[#This Row],[Year]]=0,0,MAX(0,WaterfallTable[[#This Row],[Cash Available]]-WaterfallTable[[#This Row],[Pref Paid]]-WaterfallTable[[#This Row],[Capital Returned A]]-WaterfallTable[[#This Row],[Capital Returned B]])*ClassBResidualShare)) -> 0 | M13: =IF(WaterfallTable[[#This Row],[Year]]>SaleExitYear,0,WaterfallTable[[#This Row],[Capital Returned B]]+WaterfallTable[[#This Row],[ Residual B]]) -> 0 | N13: =IF(WaterfallTable[[#This Row],[Year]]>SaleExitYear,0,IF(WaterfallTable[[#This Row],[Year]]=0,SponsorPropertyPayment,0)) -> 0 | O13: =IF(WaterfallTable[[#This Row],[Year]]>SaleExitYear,0,IF(WaterfallTable[[#This Row],[Year]]=0,0,MAX(0,WaterfallTable[[#This Row],[Cash Available]]-WaterfallTable[[#This Row],[Pref Paid]]-WaterfallTable[[#This Row],[Capital Returned A]]-WaterfallTable[[#This Row],[Capital Returned B]])*SponsorResidualShare)) -> 0 | P13: =IF(WaterfallTable[[#This Row],[Year]]>SaleExitYear,0,WaterfallTable[[#This Row],[Property Payment]]+WaterfallTable[[#This Row],[Residual]]) -> 0
A14: 10 | B14: =IF(WaterfallTable[[#This Row],[Year]]>SaleExitYear,0,INDEX(AnnualModelTable[Cash Available Before Distributions],MATCH(WaterfallTable[[#This Row],[Year]],AnnualModelTable[Year],0))) -> 0 | C14: =IF(WaterfallTable[[#This Row],[Year]]>SaleExitYear,0,WaterfallTable[[#This Row],[Capital Balance A]]*ClassAPreferredReturn) -> 0 | D14: =IF(WaterfallTable[[#This Row],[Year]]>SaleExitYear,0,IF(WaterfallTable[[#This Row],[Year]]=0,0,MIN(WaterfallTable[[#This Row],[Cash Available]],INDEX(WaterfallTable[End of Year Pref Balance],10)+WaterfallTable[[#This Row],[Pref Accrued]]))) -> 0 | E14: =IF(WaterfallTable[[#This Row],[Year]]>SaleExitYear,0,MAX(0,INDEX(WaterfallTable[End of Year Pref Balance],10)+WaterfallTable[[#This Row],[Pref Accrued]]-WaterfallTable[[#This Row],[Pref Paid]])) -> 0 | F14: =IF(WaterfallTable[[#This Row],[Year]]>SaleExitYear,0,MAX(0,INDEX(WaterfallTable[Capital Balance A],10)-INDEX(WaterfallTable[Capital Returned A],10))) -> 0 | G14: =IF(WaterfallTable[[#This Row],[Year]]>SaleExitYear,0,IF(WaterfallTable[[#This Row],[Year]]=0,0,MIN(MAX(0,WaterfallTable[[#This Row],[Cash Available]]-WaterfallTable[[#This Row],[Pref Paid]]),WaterfallTable[[#This Row],[Capital Balance A]]))) -> 0 | H14: =IF(WaterfallTable[[#This Row],[Year]]>SaleExitYear,0,IF(WaterfallTable[[#This Row],[Year]]=0,0,MAX(0,WaterfallTable[[#This Row],[Cash Available]]-WaterfallTable[[#This Row],[Pref Paid]]-WaterfallTable[[#This Row],[Capital Returned A]]-WaterfallTable[[#This Row],[Capital Returned B]])*ClassAResidualShare)) -> 0 | I14: =IF(WaterfallTable[[#This Row],[Year]]>SaleExitYear,0,WaterfallTable[[#This Row],[Pref Paid]]+WaterfallTable[[#This Row],[Capital Returned A]]+WaterfallTable[[#This Row],[Residual A]]) -> 0 | J14: =IF(WaterfallTable[[#This Row],[Year]]>SaleExitYear,0,MAX(0,INDEX(WaterfallTable[[ Capital Balance B]],10)-INDEX(WaterfallTable[Capital Returned B],10))) -> 0 | K14: =IF(WaterfallTable[[#This Row],[Year]]>SaleExitYear,0,IF(WaterfallTable[[#This Row],[Year]]=0,0,IF(ClassBReturnPriority=1,MIN(MAX(0,WaterfallTable[[#This Row],[Cash Available]]-WaterfallTable[[#This Row],[Pref Paid]]-WaterfallTable[[#This Row],[Capital Returned A]]),WaterfallTable[[#This Row],[ Capital Balance B]]),0))) -> 0 | L14: =IF(WaterfallTable[[#This Row],[Year]]>SaleExitYear,0,IF(WaterfallTable[[#This Row],[Year]]=0,0,MAX(0,WaterfallTable[[#This Row],[Cash Available]]-WaterfallTable[[#This Row],[Pref Paid]]-WaterfallTable[[#This Row],[Capital Returned A]]-WaterfallTable[[#This Row],[Capital Returned B]])*ClassBResidualShare)) -> 0 | M14: =IF(WaterfallTable[[#This Row],[Year]]>SaleExitYear,0,WaterfallTable[[#This Row],[Capital Returned B]]+WaterfallTable[[#This Row],[ Residual B]]) -> 0 | N14: =IF(WaterfallTable[[#This Row],[Year]]>SaleExitYear,0,IF(WaterfallTable[[#This Row],[Year]]=0,SponsorPropertyPayment,0)) -> 0 | O14: =IF(WaterfallTable[[#This Row],[Year]]>SaleExitYear,0,IF(WaterfallTable[[#This Row],[Year]]=0,0,MAX(0,WaterfallTable[[#This Row],[Cash Available]]-WaterfallTable[[#This Row],[Pref Paid]]-WaterfallTable[[#This Row],[Capital Returned A]]-WaterfallTable[[#This Row],[Capital Returned B]])*SponsorResidualShare)) -> 0 | P14: =IF(WaterfallTable[[#This Row],[Year]]>SaleExitYear,0,WaterfallTable[[#This Row],[Property Payment]]+WaterfallTable[[#This Row],[Residual]]) -> 0
A16: Returns Summary
A18: Participant | B18: Capital Investment | C18: Basis / Property Payment | D18: Initial Capitalization | E18: Year 1 | F18: Year 2 | G18: Year 3 | H18: Year 4 | I18: Year 5 | J18: Year 6 | K18: Year 7 | L18: Year 8 | M18: Year 9 | N18: Year 10 | O18: Total Profit | P18: Total Dist | Q18: Equity Multiple | R18: ROI % | S18: IRR
A19: Class A | B19: =ClassACapital -> 300000 | C19: =ClassACapital -> 300000 | D19: =-ReturnsTable[[#This Row],[Capital Investment]] -> -300000 | E19: =IF(1>SaleExitYear,0,INDEX(WaterfallTable[Total Dist A],MATCH(1,WaterfallTable[Year],0))) -> 5218.2079 | F19: =IF(2>SaleExitYear,0,INDEX(WaterfallTable[Total Dist A],MATCH(2,WaterfallTable[Year],0))) -> 50173.32 | G19: =IF(3>SaleExitYear,0,INDEX(WaterfallTable[Total Dist A],MATCH(3,WaterfallTable[Year],0))) -> 340608.47 | H19: =IF(4>SaleExitYear,0,INDEX(WaterfallTable[Total Dist A],MATCH(4,WaterfallTable[Year],0))) -> 0 | I19: =IF(5>SaleExitYear,0,INDEX(WaterfallTable[Total Dist A],MATCH(5,WaterfallTable[Year],0))) -> 134777.16 | J19: =IF(6>SaleExitYear,0,INDEX(WaterfallTable[Total Dist A],MATCH(6,WaterfallTable[Year],0))) -> 0 | K19: =IF(7>SaleExitYear,0,INDEX(WaterfallTable[Total Dist A],MATCH(7,WaterfallTable[Year],0))) -> 0 | L19: =IF(8>SaleExitYear,0,INDEX(WaterfallTable[Total Dist A],MATCH(8,WaterfallTable[Year],0))) -> 0 | M19: =IF(9>SaleExitYear,0,INDEX(WaterfallTable[Total Dist A],MATCH(9,WaterfallTable[Year],0))) -> 0 | N19: =IF(10>SaleExitYear,0,INDEX(WaterfallTable[Total Dist A],MATCH(10,WaterfallTable[Year],0))) -> 0 | O19: =SUM(ReturnsTable[[#This Row],[Initial Capitalization]:[Year 10]]) -> 230777.16 | P19: =ReturnsTable[[#This Row],[Total Profit]]+ReturnsTable[[#This Row],[Capital Investment]] -> 530777.16 | Q19: =IFERROR(ReturnsTable[[#This Row],[Total Dist]]/ReturnsTable[[#This Row],[Capital Investment]],0) -> 1.7692572 | R19: =IFERROR(ReturnsTable[[#This Row],[Total Profit]]/ReturnsTable[[#This Row],[Capital Investment]],0) -> 0.76925721 | S19: =IFERROR(IRR(ReturnsTable[[#This Row],[Initial Capitalization]:[Year 10]]),0) -> 0.18805238
A20: Class B | B20: =ClassBCapital -> 597500 | C20: =ClassBCapital -> 597500 | D20: =-ReturnsTable[[#This Row],[Capital Investment]] -> -597500 | E20: =IF(1>SaleExitYear,0,INDEX(WaterfallTable[Total Dist B],MATCH(1,WaterfallTable[Year],0))) -> 0 | F20: =IF(2>SaleExitYear,0,INDEX(WaterfallTable[Total Dist B],MATCH(2,WaterfallTable[Year],0))) -> 0 | G20: =IF(3>SaleExitYear,0,INDEX(WaterfallTable[Total Dist B],MATCH(3,WaterfallTable[Year],0))) -> 213220.95 | H20: =IF(4>SaleExitYear,0,INDEX(WaterfallTable[Total Dist B],MATCH(4,WaterfallTable[Year],0))) -> 15552.977 | I20: =IF(5>SaleExitYear,0,INDEX(WaterfallTable[Total Dist B],MATCH(5,WaterfallTable[Year],0))) -> 637157.26 | J20: =IF(6>SaleExitYear,0,INDEX(WaterfallTable[Total Dist B],MATCH(6,WaterfallTable[Year],0))) -> 0 | K20: =IF(7>SaleExitYear,0,INDEX(WaterfallTable[Total Dist B],MATCH(7,WaterfallTable[Year],0))) -> 0 | L20: =IF(8>SaleExitYear,0,INDEX(WaterfallTable[Total Dist B],MATCH(8,WaterfallTable[Year],0))) -> 0 | M20: =IF(9>SaleExitYear,0,INDEX(WaterfallTable[Total Dist B],MATCH(9,WaterfallTable[Year],0))) -> 0 | N20: =IF(10>SaleExitYear,0,INDEX(WaterfallTable[Total Dist B],MATCH(10,WaterfallTable[Year],0))) -> 0 | O20: =SUM(ReturnsTable[[#This Row],[Initial Capitalization]:[Year 10]]) -> 268431.19 | P20: =ReturnsTable[[#This Row],[Total Profit]]+ReturnsTable[[#This Row],[Capital Investment]] -> 865931.19 | Q20: =IFERROR(ReturnsTable[[#This Row],[Total Dist]]/ReturnsTable[[#This Row],[Capital Investment]],0) -> 1.4492572 | R20: =IFERROR(ReturnsTable[[#This Row],[Total Profit]]/ReturnsTable[[#This Row],[Capital Investment]],0) -> 0.44925721 | S20: =IFERROR(IRR(ReturnsTable[[#This Row],[Initial Capitalization]:[Year 10]]),0) -> 0.086797479
A21: Sponsor | B21: =SponsorCapitalInvestment -> 125000 | C21: =SponsorBasis -> 150000 | D21: =INDEX(WaterfallTable[Total Dist2],MATCH(0,WaterfallTable[Year],0))-ReturnsTable[[#This Row],[Capital Investment]] -> 25000 | E21: =IF(1>SaleExitYear,0,INDEX(WaterfallTable[Total Dist2],MATCH(1,WaterfallTable[Year],0))) -> 0 | F21: =IF(2>SaleExitYear,0,INDEX(WaterfallTable[Total Dist2],MATCH(2,WaterfallTable[Year],0))) -> 0 | G21: =IF(3>SaleExitYear,0,INDEX(WaterfallTable[Total Dist2],MATCH(3,WaterfallTable[Year],0))) -> 0 | H21: =IF(4>SaleExitYear,0,INDEX(WaterfallTable[Total Dist2],MATCH(4,WaterfallTable[Year],0))) -> 0 | I21: =IF(5>SaleExitYear,0,INDEX(WaterfallTable[Total Dist2],MATCH(5,WaterfallTable[Year],0))) -> 268805.57 | J21: =IF(6>SaleExitYear,0,INDEX(WaterfallTable[Total Dist2],MATCH(6,WaterfallTable[Year],0))) -> 0 | K21: =IF(7>SaleExitYear,0,INDEX(WaterfallTable[Total Dist2],MATCH(7,WaterfallTable[Year],0))) -> 0 | L21: =IF(8>SaleExitYear,0,INDEX(WaterfallTable[Total Dist2],MATCH(8,WaterfallTable[Year],0))) -> 0 | M21: =IF(9>SaleExitYear,0,INDEX(WaterfallTable[Total Dist2],MATCH(9,WaterfallTable[Year],0))) -> 0 | N21: =IF(10>SaleExitYear,0,INDEX(WaterfallTable[Total Dist2],MATCH(10,WaterfallTable[Year],0))) -> 0 | O21: =SUM(ReturnsTable[[#This Row],[Initial Capitalization]:[Year 10]]) -> 293805.57 | P21: =ReturnsTable[[#This Row],[Total Profit]]+ReturnsTable[[#This Row],[Capital Investment]] -> 418805.57 | Q21: =IFERROR(ReturnsTable[[#This Row],[Total Dist]]/ReturnsTable[[#This Row],[Capital Investment]],0) -> 3.3504445 | R21: =IFERROR(ReturnsTable[[#This Row],[Total Profit]]/ReturnsTable[[#This Row],[Capital Investment]],0) -> 2.3504445 | S21: =IFERROR(IRR(ReturnsTable[[#This Row],[Initial Capitalization]:[Year 10]]),0) -> 0
A22: Management | B22: =0 -> 0 | C22: =0 -> 0 | D22: =0 -> 0 | E22: =IF(1>SaleExitYear,0,ManagementFeeRate*INDEX(AnnualModelTable[Occupancy Effective Gross Income],MATCH(1,AnnualModelTable[Year],0))) -> 3168 | F22: =IF(2>SaleExitYear,0,ManagementFeeRate*INDEX(AnnualModelTable[Occupancy Effective Gross Income],MATCH(2,AnnualModelTable[Year],0))) -> 7231.68 | G22: =IF(3>SaleExitYear,0,ManagementFeeRate*INDEX(AnnualModelTable[Occupancy Effective Gross Income],MATCH(3,AnnualModelTable[Year],0))) -> 8035.2 | H22: =IF(4>SaleExitYear,0,ManagementFeeRate*INDEX(AnnualModelTable[Occupancy Effective Gross Income],MATCH(4,AnnualModelTable[Year],0))) -> 8035.2 | I22: =IF(5>SaleExitYear,0,ManagementFeeRate*INDEX(AnnualModelTable[Occupancy Effective Gross Income],MATCH(5,AnnualModelTable[Year],0))) -> 8035.2 | J22: =IF(6>SaleExitYear,0,ManagementFeeRate*INDEX(AnnualModelTable[Occupancy Effective Gross Income],MATCH(6,AnnualModelTable[Year],0))) -> 0 | K22: =IF(7>SaleExitYear,0,ManagementFeeRate*INDEX(AnnualModelTable[Occupancy Effective Gross Income],MATCH(7,AnnualModelTable[Year],0))) -> 0 | L22: =IF(8>SaleExitYear,0,ManagementFeeRate*INDEX(AnnualModelTable[Occupancy Effective Gross Income],MATCH(8,AnnualModelTable[Year],0))) -> 0 | M22: =IF(9>SaleExitYear,0,ManagementFeeRate*INDEX(AnnualModelTable[Occupancy Effective Gross Income],MATCH(9,AnnualModelTable[Year],0))) -> 0 | N22: =IF(10>SaleExitYear,0,ManagementFeeRate*INDEX(AnnualModelTable[Occupancy Effective Gross Income],MATCH(10,AnnualModelTable[Year],0))) -> 0 | O22: =SUM(ReturnsTable[[#This Row],[Initial Capitalization]:[Year 10]]) -> 34505.28 | P22: =ReturnsTable[[#This Row],[Total Profit]] -> 34505.28 | Q22: =0 -> 0 | R22: =0 -> 0 | S22: =0 -> 0

Sheet Returns
A1: Legacy Returns sheet retained for reference. Primary ReturnsTable is now on the Waterfall tab.
A3: Participant | B3: Capital / Basis | C3: Total Distributions | D3: Net Profit | E3: Equity Multiple | F3: ROI % | G3: IRR | H3: Year 0 | I3: Year 1 | J3: Year 2 | K3: Year 3 | L3: Year 4 | M3: Year 5 | N3: Year 6 | O3: Year 7 | P3: Year 8 | Q3: Year 9 | R3: Year 10
A4: Class A | B4: =ClassACapital -> 300000 | C4: =SUM(Waterfall!$I$4:$I$14) -> 530777.16 | D4: =C4-B4 -> 230777.16 | E4: =IFERROR(C4/B4,0) -> 1.7692572 | F4: =IFERROR(D4/B4,0) -> 0.76925721 | G4: =IRR(H4:R4) -> 0.18805238 | H4: =-B4 -> -300000 | I4: =INDEX(Waterfall!$I$4:$I$14,MATCH(1,Waterfall!$A$4:$A$14,0)) -> 5218.2079 | J4: =INDEX(Waterfall!$I$4:$I$14,MATCH(2,Waterfall!$A$4:$A$14,0)) -> 50173.32 | K4: =INDEX(Waterfall!$I$4:$I$14,MATCH(3,Waterfall!$A$4:$A$14,0)) -> 340608.47 | L4: =INDEX(Waterfall!$I$4:$I$14,MATCH(4,Waterfall!$A$4:$A$14,0)) -> 0 | M4: =INDEX(Waterfall!$I$4:$I$14,MATCH(5,Waterfall!$A$4:$A$14,0)) -> 134777.16 | N4: =INDEX(Waterfall!$I$4:$I$14,MATCH(6,Waterfall!$A$4:$A$14,0)) -> 0 | O4: =INDEX(Waterfall!$I$4:$I$14,MATCH(7,Waterfall!$A$4:$A$14,0)) -> 0 | P4: =INDEX(Waterfall!$I$4:$I$14,MATCH(8,Waterfall!$A$4:$A$14,0)) -> 0 | Q4: =INDEX(Waterfall!$I$4:$I$14,MATCH(9,Waterfall!$A$4:$A$14,0)) -> 0 | R4: =INDEX(Waterfall!$I$4:$I$14,MATCH(10,Waterfall!$A$4:$A$14,0)) -> 0
A5: Class B | B5: =ClassBCapital -> 597500 | C5: =SUM(Waterfall!$M$4:$M$14) -> 865931.19 | D5: =C5-B5 -> 268431.19 | E5: =IFERROR(C5/B5,0) -> 1.4492572 | F5: =IFERROR(D5/B5,0) -> 0.44925721 | G5: =IFERROR(IRR(H5:R5),0) -> 0.086797479 | H5: =-B5 -> -597500 | I5: =INDEX(Waterfall!$M$4:$M$14,MATCH(1,Waterfall!$A$4:$A$14,0)) -> 0 | J5: =INDEX(Waterfall!$M$4:$M$14,MATCH(2,Waterfall!$A$4:$A$14,0)) -> 0 | K5: =INDEX(Waterfall!$M$4:$M$14,MATCH(3,Waterfall!$A$4:$A$14,0)) -> 213220.95 | L5: =INDEX(Waterfall!$M$4:$M$14,MATCH(4,Waterfall!$A$4:$A$14,0)) -> 15552.977 | M5: =INDEX(Waterfall!$M$4:$M$14,MATCH(5,Waterfall!$A$4:$A$14,0)) -> 637157.26 | N5: =INDEX(Waterfall!$M$4:$M$14,MATCH(6,Waterfall!$A$4:$A$14,0)) -> 0 | O5: =INDEX(Waterfall!$M$4:$M$14,MATCH(7,Waterfall!$A$4:$A$14,0)) -> 0 | P5: =INDEX(Waterfall!$M$4:$M$14,MATCH(8,Waterfall!$A$4:$A$14,0)) -> 0 | Q5: =INDEX(Waterfall!$M$4:$M$14,MATCH(9,Waterfall!$A$4:$A$14,0)) -> 0 | R5: =INDEX(Waterfall!$M$4:$M$14,MATCH(10,Waterfall!$A$4:$A$14,0)) -> 0
A6: Sponsor | B6: =SponsorBasis -> 150000 | C6: =SUM(Waterfall!$P$4:$P$14) -> 418805.57 | D6: =C6-B6 -> 268805.57 | E6: =IFERROR(C6/B6,0) -> 2.7920371 | F6: =IFERROR(D6/B6,0) -> 1.7920371 | G6: =IFERROR(IRR(H6:R6),0) -> 0.12374921 | H6: =-B6 -> -150000 | I6: =INDEX(Waterfall!$P$4:$P$14,MATCH(1,Waterfall!$A$4:$A$14,0)) -> 0 | J6: =INDEX(Waterfall!$P$4:$P$14,MATCH(2,Waterfall!$A$4:$A$14,0)) -> 0 | K6: =INDEX(Waterfall!$P$4:$P$14,MATCH(3,Waterfall!$A$4:$A$14,0)) -> 0 | L6: =INDEX(Waterfall!$P$4:$P$14,MATCH(4,Waterfall!$A$4:$A$14,0)) -> 0 | M6: =INDEX(Waterfall!$P$4:$P$14,MATCH(5,Waterfall!$A$4:$A$14,0)) -> 268805.57 | N6: =INDEX(Waterfall!$P$4:$P$14,MATCH(6,Waterfall!$A$4:$A$14,0)) -> 0 | O6: =INDEX(Waterfall!$P$4:$P$14,MATCH(7,Waterfall!$A$4:$A$14,0)) -> 0 | P6: =INDEX(Waterfall!$P$4:$P$14,MATCH(8,Waterfall!$A$4:$A$14,0)) -> 0 | Q6: =INDEX(Waterfall!$P$4:$P$14,MATCH(9,Waterfall!$A$4:$A$14,0)) -> 0 | R6: =INDEX(Waterfall!$P$4:$P$14,MATCH(10,Waterfall!$A$4:$A$14,0)) -> 0
A9: Important | B9: Class A preferred return is modeled as cumulative simple annual accrual on unrecovered Class A capital. After Class A and Class B capital are returned, Sponsor receives the editable Sponsor residual share. Class A and Class B split the remaining residual in proportion to their capital.

Sheet Notes
A1: Model Notes
A3: Purpose | B3: Calculates project-level cash available, then allocates distributions to Class A, Class B, and Sponsor through a simplified waterfall.
A4: Key editable cells | B4: Use the Assumptions tab, column B.
A5: Class A | B5: Modeled with 8% cumulative annual preferred return by default, then return of capital, then no residual share unless you revise the waterfall.
A6: Class B | B6: Modeled as subordinate capital that can receive capital back before residual distributions, plus residual participation.
A7: Sponsor | B7: Modeled using sponsor basis / deemed investment as the return denominator and sponsor residual share as the distribution source.
A8: Caution | B8: This workbook is for planning and discussion only. It is not legal, tax, securities, appraisal, or investment advice. Have counsel and CPA review before investor use.

Sheet Cost Analysis
A1: 3325 Banks Rd - Design, Development & Build Cost Analysis
A2: Status | B2: Planning estimate added 2026-05-11
A3: Source Markdown | B3: 04_Design_Development_and_Build_Cost_Analysis.md
B6: Select Scenario: | C6: Low
A7: Project Cost Case Summary | B7: Low | C7: High | E7: Case Selection | G7: =$C$6="Low" -> TRUE | H7: =$C$6="High" -> FALSE
A8: Sponsor-Controlled Case (from controlling bridge below) | B8: =B27 -> 897500 | C8: =C27 -> 1635000 | E8: Sponsor-Controlled | H8: =$E$8="Sponsor-Controlled" -> TRUE
A9: Outside-Market Benchmark (from outside-market subtotals below) | B9: =B41+B50+B59 -> 1880000 | C9: =C41+C50+C59 -> 4160000 | H9: =$E$8="Outside-Market Benchmark" -> FALSE
A10: Selected Total Project Cost | B10: =IF($C$6="Low",IF($E$8="Sponsor-Controlled",B8,B9),"") -> 897500 | C10: =IF($C$6="High",IF($E$8="Sponsor-Controlled",C8,C9),"") | G10: =IF($C$6="Low",B10,C10) -> 897500
A12: Selected Cost Metrics | B12: Low Case | C12: High Case
A14: Cost per SF at 5,000 SF | B14: =$G$10/5000 -> 179.5
A15: Cost per SF at 6,000 SF | B15: =$G$10/6000 -> 149.58333
A17: Controlling Sponsor-Controlled Line-Item Bridge | B17: Low | C17: High
A18: Sponsor property payment | B18: =SponsorPropertyPayment -> 150000 | C18: =SponsorPropertyPayment -> 150000
A19: Design, entitlement, permits, and professional services | B19: 75000 | C19: 175000
A20: Development, financing, carrying, and administration | B20: 40000 | C20: 100000
A21: Construction-period insurance | B21: 7500 | C21: 10000
A22: Post-frame building shell and interior buildout | B22: 390000 | C22: 610000
A23: Sitework, access, grading, drainage, and parking | B23: 55000 | C23: 110000
A24: Private utilities, well, wastewater, and related infrastructure | B24: 90000 | C24: 225000
A25: Furnishings, fixtures, equipment, and turnover | B25: 30000 | C25: 100000
A26: Contingency and owner reserve | B26: 60000 | C26: 155000
A27: Sponsor-Controlled Total Package | B27: =SUM(B18:B26) -> 897500 | C27: =SUM(C18:C26) -> 1635000
A28: Funding Gap Analysis | B28: Selected
A29: Estimated total project cost | B29: =SelectedProjectCost -> 897500
A30: Class A + Class B capitalization | B30: =ClassACapital+ClassBCapital -> 897500
A31: Potential unfunded development gap | B31: =MAX(0,B29-B30) -> 0
A33: Outside Market - Design & Entitlement Detail | B33: Low | C33: High
A34: Architecture and building design | B34: 35000 | C34: 90000
A35: Civil engineering and site planning | B35: 20000 | C35: 60000
A36: Septic, soil, and wastewater engineering | B36: 20000 | C36: 90000
A37: Survey, testing, environmental, and due diligence | B37: 10000 | C37: 30000
A38: Permitting, review, and municipal/county coordination | B38: 15000 | C38: 50000
A39: Legal, accounting, and trust structuring | B39: 15000 | C39: 40000
A40: Design/entitlement contingency | B40: 15000 | C40: 45000
A41: Design & entitlement total | B41: =SUM(B34:B40) -> 130000 | C41: =SUM(C34:C40) -> 405000
A43: Outside Market - Development & Pre-Construction Detail | B43: Low | C43: High
A44: Development management / sponsor fee | B44: 50000 | C44: 150000
A45: Financing, lender, appraisal, and closing costs | B45: 40000 | C45: 120000
A46: Insurance, taxes, utilities, and carrying costs | B46: 25000 | C46: 75000
A47: Accounting, administration, and reporting | B47: 10000 | C47: 30000
A48: Leasing, operations setup, and launch costs | B48: 20000 | C48: 60000
A49: Development contingency / liquidity reserve | B49: 40000 | C49: 125000
A50: Development & pre-construction total | B50: =SUM(B44:B49) -> 185000 | C50: =SUM(C44:C49) -> 560000
A52: Outside Market - Build & Delivery Detail | B52: Low | C52: High
A53: Building construction, 5,000-6,000 SF | B53: 1125000 | C53: 1950000
A54: Sitework, grading, access, parking, and drainage | B54: 125000 | C54: 350000
A55: Private utilities and well infrastructure | B55: 35000 | C55: 125000
A56: Engineered onsite wastewater system | B56: 75000 | C56: 300000
A57: Furnishings, fixtures, equipment, and turnover | B57: 60000 | C57: 180000
A58: Construction contingency | B58: 145000 | C58: 290000
A59: Build & delivery total | B59: =SUM(B53:B58) -> 1565000 | C59: =SUM(C53:C58) -> 3195000
A61: Sponsor-Controlled Cost Justification
A62: Cost-positioning note | B62: 700,000-1,300,000 is a target range, not a guaranteed budget. It depends on post-frame construction, sponsor-owned equipment, sponsor-controlled crew capacity, disciplined finish scope, and avoiding a high-cost engineered wastewater outcome.
A65: Conditions Required To Support Target Range
A66: Post-frame approach accepted through design and permitting | B66: Yes | C66: Confirmed cost saver
A67: Sponsor can self-perform or directly manage meaningful construction scope | B67: Yes | C67: Confirmed cost saver
A68: Equipment ownership reduces sitework and construction logistics cost | B68: Yes | C68: Confirmed cost saver
A69: Major subcontracted trades are competitively bid | B69: Yes | C69: Confirmed cost saver
A70: Wastewater solution does not require a high-end engineered system | B70: No | C70: Not confirmed; risk reserve retained
A71: Suite count and bathroom/kitchenette count do not expand | B71: Yes | C71: Confirmed scope control
A72: Finish package stays durable and efficient rather than luxury | B72: Yes | C72: Confirmed finish discipline
A73: Project carries a disciplined contingency | B73: Yes | C73: Confirmed reserve discipline
A75: Risks That Could Break Target Range
A76: Advanced/high-cost wastewater system requirement | B76: Yes | C76: Confirmed risk; wastewater allowance increased
A77: Expensive fire, code, or occupancy upgrades | B77: No
A78: Higher-than-expected mechanical/electrical/plumbing scope | B78: No
A79: Extensive parking, drainage, or access improvements | B79: No
A80: Sponsor crew advantage limited by labor availability | B80: No
A81: Finish level moves closer to conventional apartment construction | B81: Yes | C81: Confirmed risk; FF&E/contingency allowance increased

Sheet Operating Expense Budget
A1: 3325 Banks Rd - Operating Expense Budget
A3: Toggle / Selection
A4: Use Calculated Budget Ratio? | C4: FALSE = use assumed ratio; TRUE = use calculated budget ratio | I4: TRUE
A5: Assumed Operating Expense Ratio | B5: 0.4 | C5: Current planning assumption reflected in Assumptions tab when toggle is FALSE
A6: Calculated Operating Expense Ratio | B6: =IFERROR(B36/B10,0) -> 0.46912485 | C6: Total annual operating expense budget / effective gross income
A7: Selected Operating Expense Ratio | B7: =IF(I4,B6,B5) -> 0.46912485 | C7: Feeds Assumptions!B15
A9: Revenue Basis
A10: Stabilized Effective Gross Income | B10: =StabilizedMonthlyGrossRent*12*StabilizedOccupancy -> 133920 | C10: Annual stabilized EGI after occupancy
A12: Expense Category | B12: Annual Amount | C12: Basis / Notes
A13: Property taxes | B13: 7000 | C13: Placeholder; replace with assessed value/tax estimate
A14: Completed property insurance | B14: 4350 | C14: Post-completion hazard/liability coverage estimate; excludes construction-period insurance
A15: Property management / administration | B15: =D15*B10 -> 8035.2 | C15: 6% of stabilized effective gross income (EGI) | D15: 0.06
A16: Utilities - electric | B16: =600*12 -> 7200 | C16: Owner-paid/common-area and vacancy exposure
A17: Utilities - water / well maintenance | B17: 500 | C17: Well testing, maintenance, treatment allowance
A18: Utilities - internet | B18: 2400 | C18: Shared/furnished rental expectation
A19: Trash / recycling | B19: 1800 | C19: Recurring service
A20: Repairs & maintenance reserve | B20: 9000 | C20: Annual reserve target funded before waterfall distributions; once funded, excess cash flows through waterfall
A21: Turnover, cleaning, and supplies | B21: =200*8 -> 1600 | C21: Co-living/furnished turnover allowance
A22: Landscaping / grounds | B22: =90*20 -> 1800 | C22: Mowing, upkeep, seasonal cleanup
A23: Pest control | B23: 600 | C23: Recurring service
A24: Septic / wastewater maintenance | B24: 1000 | C24: Inspection, pump, service contracts
A25: CapEx / replacement reserve | B25: 4000 | C25: Furniture, fixtures, equipment, building reserves
A26: Marketing / leasing | B26: 0 | C26: Listings, tenant placement, materials
A27: Bookkeeping / accounting | B27: =120*12 -> 1440 | C27: Operating accounting/reporting
A28: Legal / compliance | C28: Lease forms, notices, compliance allowance
A29: Licenses, permits, inspections | B29: 1200 | C29: Recurring local/regulatory allowance
A30: Security / access control | C30: Locks, cameras, access systems, monitoring
A31: Common area furnishings replacement | B31: 2400 | C31: Shared space replacement reserve
A32: Laundry equipment maintenance | B32: 1200 | C32: Repair/replacement allowance
A33: Snow/ice/storm cleanup reserve | B33: 800 | C33: Weather/event allowance
A34: Bad debt / collections | B34: 2500 | C34: Collection loss allowance
A35: Miscellaneous / operating contingency | B35: 4000 | C35: Catch-all reserve
A36: Total Annual Operating Expense Budget | B36: =SUM(B13:B35) -> 62825.2 | C36: Calculated from line items
