Workbook
Name AnnualManagementFee: 'Operating Expense Budget'!$B$15
Name AssumedOperatingExpenseRatio: 'Operating Expense Budget'!$B$5
Name CalculatedOperatingExpenseRatio: 'Operating Expense Budget'!$B$6
Name ClassACapital: Assumptions!$B$39
Name ClassAPreferredReturn: Assumptions!$B$40
Name ClassAResidualShare: Assumptions!$B$44
Name ClassBCapital: Assumptions!$B$41
Name ClassBResidualShare: Assumptions!$B$45
Name ClassBReturnPriority: Assumptions!$B$42
Name CoLivingSuiteRent: Assumptions!$B$11
Name CoLivingSuiteRentHigh: Assumptions!$G$10
Name CoLivingSuiteRentLow: Assumptions!$E$10
Name CoLivingSuiteRentMedium: Assumptions!$F$10
Name CoLivingSuites: Assumptions!$B$10
Name ExistingDebtServiceAnnual: Assumptions!$B$28
Name ExistingFirstMortgage: Assumptions!$B$20
Name ExistingFirstMortgageAnnualPayment: Assumptions!$B$26
Name ExistingFirstMortgageMonthlyPI: Assumptions!$B$25
Name ExistingFirstMortgagePrincipal: Assumptions!$B$20
Name ExistingFirstMortgageRate: Assumptions!$B$21
Name ExitCapRate: Assumptions!$B$35
Name LeaseUpOccupancy: Assumptions!$B$14
Name ManagementFeeRate: 'Operating Expense Budget'!$D$15
Name NOIGrowth: Assumptions!$B$16
Name OperatingExpenseRatio: Assumptions!$B$15
Name OtherMonthlyIncome: Assumptions!$B$12
Name PermanentLoanAmortizationYears: Assumptions!$B$34
Name PermanentLoanAmount: Assumptions!$B$30
Name PermanentLoanRate: Assumptions!$B$33
Name PremiumSuiteRent: Assumptions!$B$9
Name PremiumSuiteRentHigh: Assumptions!$G$9
Name PremiumSuiteRentLow: Assumptions!$E$9
Name PremiumSuiteRentMedium: Assumptions!$F$9
Name PremiumSuites: Assumptions!$B$8
Name PrivateDebtAnnualInterestPayment: Assumptions!$B$27
Name PrivateDebtInterestRate: Assumptions!$B$23
Name PrivateDebtPrincipal: Assumptions!$B$22
Name ProjectDebtPayoffAtRefi: Assumptions!$B$24
Name RefinanceLoanAmortizationYears: Assumptions!$B$34
Name RefinanceLoanAmount: Assumptions!$B$30
Name RefinanceLoanRate: Assumptions!$B$33
Name RefinanceLoanToValueCap: Assumptions!$B$29
Name RefinanceProceedsAfterDebtAndClassA: Assumptions!$B$32
Name RefinanceProceedsAfterExistingDebt: Assumptions!$B$31
Name RentScenarioAverageMonthlyGross: Assumptions!$H$11
Name RentScenarioHighEffectiveYear: Assumptions!$G$12
Name RentScenarioHighMonthlyGross: Assumptions!$G$11
Name RentScenarioLowEffectiveYear: Assumptions!$E$12
Name RentScenarioLowMonthlyGross: Assumptions!$E$11
Name RentScenarioMediumEffectiveYear: Assumptions!$F$12
Name RentScenarioMediumMonthlyGross: Assumptions!$F$11
Name RepairsMaintenanceReserveTarget: 'Operating Expense Budget'!$B$20
Name SaleExitYear: Assumptions!$B$5
Name SelectedAnnualGrossRent: 'STR Scenarios'!$L$25:$L$34
Name SelectedCostCase: 'Cost Analysis'!$E$8
Name SelectedCostCaseId: 'Cost Analysis'!$D$11
Name SelectedOperatingExpenseRatio: 'Operating Expense Budget'!$B$7
Name SelectedOperatingScenario: 'STR Scenarios'!$D$4
Name SelectedOperatingScenarioId: 'STR Scenarios'!$H$4
Name SelectedProjectCost: 'Cost Analysis'!$G$10

Sheet STR Notes
A1: STR Experimental Workbook Notes
A3: This workbook is an experimental copy of the investor ROI model. The original workbook is not modified.
A5: The STR Scenarios tab lets the Annual Model switch between Base Co-Living / Medium-Term, One Floor STR + One Floor Co-Living, and Whole Building STR.
A7: STR outputs are modeled as annual gross rent after platform/lodging cost haircut and turnover cost allowance. Operating expenses still flow through the existing Operating Expense Budget unless separately revised.
A9: Use this copy for sensitivity testing. If the STR approach is abandoned, return to the original workbook.

Sheet STR Scenarios
A1: 3325 Banks Rd - STR Operating Scenarios
B2: Annual Model revenue pulls from this selected scenario.
A3: Scenario Selector | H3: Option #
A4: Selected Operating Scenario | D4: =IF(OR($H$4<1,$H$4>3),"",INDEX($B$7:$B$9,$H$4)) -> One Floor STR + One Floor Co-Living | H4: 2
A6: Select | B6: Operating Scenario | E6: Description
B7: Base Co-Living / Medium-Term | E7: Existing co-living rent schedule remains controlling.
B8: One Floor STR + One Floor Co-Living | E8: One full floor rents weekly as STR; other floor remains co-living/medium-term.
B9: Whole Building STR | E9: Entire building rents weekly as STR.
A12: STR Input Assumptions
A13: Input | D13: Low / Year 1 | E13: Medium / Year 2 | F13: High / Year 3+ | G13: Notes
A14: One-floor STR weekly rent | D14: 2500 | E14: 3250 | F14: 4000 | G14: Weekly gross rent for one full floor
A15: One-floor STR occupancy | D15: 0.4 | E15: 0.5 | F15: 0.6 | G15: Occupied week percentage
A16: Whole-building STR weekly rent | D16: 4500 | E16: 6000 | F16: 7500 | G16: Weekly gross rent for full building
A17: Whole-building STR occupancy | D17: 0.35 | E17: 0.45 | F17: 0.55 | G17: Occupied week percentage
A18: STR platform / lodging cost ratio | D18: 0.08 | E18: 0.09 | F18: 0.1 | G18: Gross-revenue haircut for STR platform/tax/admin stress
A19: STR turnover cost per occupied week | D19: 250 | E19: 300 | F19: 350 | G19: Cleaning, supplies, turnover allowance
A23: Annual Revenue Scenario Output
A24: Year | B24: Rent Case | C24: Base Monthly Gross Rent | D24: Base Annual Gross Rent | E24: One-Floor STR Weekly Rent | F24: One-Floor STR Occupancy | G24: Other Floor Annual Rent | H24: One-Floor STR Annual Gross | I24: Whole-Building STR Weekly Rent | J24: Whole-Building STR Occupancy | K24: Whole-Building STR Annual Gross | L24: Selected Annual Gross Rent
A25: 1 | B25: =IF(STRScenarioTable[[#This Row],[Year]]>=RentScenarioHighEffectiveYear,"High",IF(STRScenarioTable[[#This Row],[Year]]>=RentScenarioMediumEffectiveYear,"Medium",IF(STRScenarioTable[[#This Row],[Year]]>=RentScenarioLowEffectiveYear,"Low","None"))) -> Low | C25: =IF(STRScenarioTable[[#This Row],[Year]]>=RentScenarioHighEffectiveYear,RentScenarioHighMonthlyGross,IF(STRScenarioTable[[#This Row],[Year]]>=RentScenarioMediumEffectiveYear,RentScenarioMediumMonthlyGross,IF(STRScenarioTable[[#This Row],[Year]]>=RentScenarioLowEffectiveYear,RentScenarioLowMonthlyGross,0))) -> 8800 | D25: =STRScenarioTable[[#This Row],[Base Monthly Gross Rent]]*12 -> 105600 | E25: =IF(STRScenarioTable[[#This Row],[Year]]>=3,$F$14,IF(STRScenarioTable[[#This Row],[Year]]>=2,$E$14,$D$14)) -> 2500 | F25: =IF(STRScenarioTable[[#This Row],[Year]]>=3,$F$15,IF(STRScenarioTable[[#This Row],[Year]]>=2,$E$15,$D$15)) -> 0.4 | G25: =STRScenarioTable[[#This Row],[Base Annual Gross Rent]]/2 -> 52800 | H25: =(STRScenarioTable[[#This Row],[One-Floor STR Weekly Rent]]*52*STRScenarioTable[[#This Row],[One-Floor STR Occupancy]]*(1-IF(STRScenarioTable[[#This Row],[Year]]>=3,$F$18,IF(STRScenarioTable[[#This Row],[Year]]>=2,$E$18,$D$18))))-(STRScenarioTable[[#This Row],[One-Floor STR Occupancy]]*52*IF(STRScenarioTable[[#This Row],[Year]]>=3,$F$19,IF(STRScenarioTable[[#This Row],[Year]]>=2,$E$19,$D$19)))+STRScenarioTable[[#This Row],[Other Floor Annual Rent]] -> 95440 | I25: =IF(STRScenarioTable[[#This Row],[Year]]>=3,$F$16,IF(STRScenarioTable[[#This Row],[Year]]>=2,$E$16,$D$16)) -> 4500 | J25: =IF(STRScenarioTable[[#This Row],[Year]]>=3,$F$17,IF(STRScenarioTable[[#This Row],[Year]]>=2,$E$17,$D$17)) -> 0.35 | K25: =(STRScenarioTable[[#This Row],[Whole-Building STR Weekly Rent]]*52*STRScenarioTable[[#This Row],[Whole-Building STR Occupancy]]*(1-IF(STRScenarioTable[[#This Row],[Year]]>=3,$F$18,IF(STRScenarioTable[[#This Row],[Year]]>=2,$E$18,$D$18))))-(STRScenarioTable[[#This Row],[Whole-Building STR Occupancy]]*52*IF(STRScenarioTable[[#This Row],[Year]]>=3,$F$19,IF(STRScenarioTable[[#This Row],[Year]]>=2,$E$19,$D$19))) -> 70798 | L25: =CHOOSE(SelectedOperatingScenarioId,STRScenarioTable[[#This Row],[Base Annual Gross Rent]],STRScenarioTable[[#This Row],[One-Floor STR Annual Gross]],STRScenarioTable[[#This Row],[Whole-Building STR Annual Gross]]) -> 95440 | O25: =SUM(SelectedAnnualGrossRent) -> 1616535
A26: 2 | B26: =IF(STRScenarioTable[[#This Row],[Year]]>=RentScenarioHighEffectiveYear,"High",IF(STRScenarioTable[[#This Row],[Year]]>=RentScenarioMediumEffectiveYear,"Medium",IF(STRScenarioTable[[#This Row],[Year]]>=RentScenarioLowEffectiveYear,"Low","None"))) -> Medium | C26: =IF(STRScenarioTable[[#This Row],[Year]]>=RentScenarioHighEffectiveYear,RentScenarioHighMonthlyGross,IF(STRScenarioTable[[#This Row],[Year]]>=RentScenarioMediumEffectiveYear,RentScenarioMediumMonthlyGross,IF(STRScenarioTable[[#This Row],[Year]]>=RentScenarioLowEffectiveYear,RentScenarioLowMonthlyGross,0))) -> 10800 | D26: =STRScenarioTable[[#This Row],[Base Monthly Gross Rent]]*12 -> 129600 | E26: =IF(STRScenarioTable[[#This Row],[Year]]>=3,$F$14,IF(STRScenarioTable[[#This Row],[Year]]>=2,$E$14,$D$14)) -> 3250 | F26: =IF(STRScenarioTable[[#This Row],[Year]]>=3,$F$15,IF(STRScenarioTable[[#This Row],[Year]]>=2,$E$15,$D$15)) -> 0.5 | G26: =STRScenarioTable[[#This Row],[Base Annual Gross Rent]]/2 -> 64800 | H26: =(STRScenarioTable[[#This Row],[One-Floor STR Weekly Rent]]*52*STRScenarioTable[[#This Row],[One-Floor STR Occupancy]]*(1-IF(STRScenarioTable[[#This Row],[Year]]>=3,$F$18,IF(STRScenarioTable[[#This Row],[Year]]>=2,$E$18,$D$18))))-(STRScenarioTable[[#This Row],[One-Floor STR Occupancy]]*52*IF(STRScenarioTable[[#This Row],[Year]]>=3,$F$19,IF(STRScenarioTable[[#This Row],[Year]]>=2,$E$19,$D$19)))+STRScenarioTable[[#This Row],[Other Floor Annual Rent]] -> 133895 | I26: =IF(STRScenarioTable[[#This Row],[Year]]>=3,$F$16,IF(STRScenarioTable[[#This Row],[Year]]>=2,$E$16,$D$16)) -> 6000 | J26: =IF(STRScenarioTable[[#This Row],[Year]]>=3,$F$17,IF(STRScenarioTable[[#This Row],[Year]]>=2,$E$17,$D$17)) -> 0.45 | K26: =(STRScenarioTable[[#This Row],[Whole-Building STR Weekly Rent]]*52*STRScenarioTable[[#This Row],[Whole-Building STR Occupancy]]*(1-IF(STRScenarioTable[[#This Row],[Year]]>=3,$F$18,IF(STRScenarioTable[[#This Row],[Year]]>=2,$E$18,$D$18))))-(STRScenarioTable[[#This Row],[Whole-Building STR Occupancy]]*52*IF(STRScenarioTable[[#This Row],[Year]]>=3,$F$19,IF(STRScenarioTable[[#This Row],[Year]]>=2,$E$19,$D$19))) -> 120744 | L26: =CHOOSE(SelectedOperatingScenarioId,STRScenarioTable[[#This Row],[Base Annual Gross Rent]],STRScenarioTable[[#This Row],[One-Floor STR Annual Gross]],STRScenarioTable[[#This Row],[Whole-Building STR Annual Gross]]) -> 133895
A27: 3 | B27: =IF(STRScenarioTable[[#This Row],[Year]]>=RentScenarioHighEffectiveYear,"High",IF(STRScenarioTable[[#This Row],[Year]]>=RentScenarioMediumEffectiveYear,"Medium",IF(STRScenarioTable[[#This Row],[Year]]>=RentScenarioLowEffectiveYear,"Low","None"))) -> High | C27: =IF(STRScenarioTable[[#This Row],[Year]]>=RentScenarioHighEffectiveYear,RentScenarioHighMonthlyGross,IF(STRScenarioTable[[#This Row],[Year]]>=RentScenarioMediumEffectiveYear,RentScenarioMediumMonthlyGross,IF(STRScenarioTable[[#This Row],[Year]]>=RentScenarioLowEffectiveYear,RentScenarioLowMonthlyGross,0))) -> 12000 | D27: =STRScenarioTable[[#This Row],[Base Monthly Gross Rent]]*12 -> 144000 | E27: =IF(STRScenarioTable[[#This Row],[Year]]>=3,$F$14,IF(STRScenarioTable[[#This Row],[Year]]>=2,$E$14,$D$14)) -> 4000 | F27: =IF(STRScenarioTable[[#This Row],[Year]]>=3,$F$15,IF(STRScenarioTable[[#This Row],[Year]]>=2,$E$15,$D$15)) -> 0.6 | G27: =STRScenarioTable[[#This Row],[Base Annual Gross Rent]]/2 -> 72000 | H27: =(STRScenarioTable[[#This Row],[One-Floor STR Weekly Rent]]*52*STRScenarioTable[[#This Row],[One-Floor STR Occupancy]]*(1-IF(STRScenarioTable[[#This Row],[Year]]>=3,$F$18,IF(STRScenarioTable[[#This Row],[Year]]>=2,$E$18,$D$18))))-(STRScenarioTable[[#This Row],[One-Floor STR Occupancy]]*52*IF(STRScenarioTable[[#This Row],[Year]]>=3,$F$19,IF(STRScenarioTable[[#This Row],[Year]]>=2,$E$19,$D$19)))+STRScenarioTable[[#This Row],[Other Floor Annual Rent]] -> 173400 | I27: =IF(STRScenarioTable[[#This Row],[Year]]>=3,$F$16,IF(STRScenarioTable[[#This Row],[Year]]>=2,$E$16,$D$16)) -> 7500 | J27: =IF(STRScenarioTable[[#This Row],[Year]]>=3,$F$17,IF(STRScenarioTable[[#This Row],[Year]]>=2,$E$17,$D$17)) -> 0.55 | K27: =(STRScenarioTable[[#This Row],[Whole-Building STR Weekly Rent]]*52*STRScenarioTable[[#This Row],[Whole-Building STR Occupancy]]*(1-IF(STRScenarioTable[[#This Row],[Year]]>=3,$F$18,IF(STRScenarioTable[[#This Row],[Year]]>=2,$E$18,$D$18))))-(STRScenarioTable[[#This Row],[Whole-Building STR Occupancy]]*52*IF(STRScenarioTable[[#This Row],[Year]]>=3,$F$19,IF(STRScenarioTable[[#This Row],[Year]]>=2,$E$19,$D$19))) -> 183040 | L27: =CHOOSE(SelectedOperatingScenarioId,STRScenarioTable[[#This Row],[Base Annual Gross Rent]],STRScenarioTable[[#This Row],[One-Floor STR Annual Gross]],STRScenarioTable[[#This Row],[Whole-Building STR Annual Gross]]) -> 173400
A28: 4 | B28: =IF(STRScenarioTable[[#This Row],[Year]]>=RentScenarioHighEffectiveYear,"High",IF(STRScenarioTable[[#This Row],[Year]]>=RentScenarioMediumEffectiveYear,"Medium",IF(STRScenarioTable[[#This Row],[Year]]>=RentScenarioLowEffectiveYear,"Low","None"))) -> High | C28: =IF(STRScenarioTable[[#This Row],[Year]]>=RentScenarioHighEffectiveYear,RentScenarioHighMonthlyGross,IF(STRScenarioTable[[#This Row],[Year]]>=RentScenarioMediumEffectiveYear,RentScenarioMediumMonthlyGross,IF(STRScenarioTable[[#This Row],[Year]]>=RentScenarioLowEffectiveYear,RentScenarioLowMonthlyGross,0))) -> 12000 | D28: =STRScenarioTable[[#This Row],[Base Monthly Gross Rent]]*12 -> 144000 | E28: =IF(STRScenarioTable[[#This Row],[Year]]>=3,$F$14,IF(STRScenarioTable[[#This Row],[Year]]>=2,$E$14,$D$14)) -> 4000 | F28: =IF(STRScenarioTable[[#This Row],[Year]]>=3,$F$15,IF(STRScenarioTable[[#This Row],[Year]]>=2,$E$15,$D$15)) -> 0.6 | G28: =STRScenarioTable[[#This Row],[Base Annual Gross Rent]]/2 -> 72000 | H28: =(STRScenarioTable[[#This Row],[One-Floor STR Weekly Rent]]*52*STRScenarioTable[[#This Row],[One-Floor STR Occupancy]]*(1-IF(STRScenarioTable[[#This Row],[Year]]>=3,$F$18,IF(STRScenarioTable[[#This Row],[Year]]>=2,$E$18,$D$18))))-(STRScenarioTable[[#This Row],[One-Floor STR Occupancy]]*52*IF(STRScenarioTable[[#This Row],[Year]]>=3,$F$19,IF(STRScenarioTable[[#This Row],[Year]]>=2,$E$19,$D$19)))+STRScenarioTable[[#This Row],[Other Floor Annual Rent]] -> 173400 | I28: =IF(STRScenarioTable[[#This Row],[Year]]>=3,$F$16,IF(STRScenarioTable[[#This Row],[Year]]>=2,$E$16,$D$16)) -> 7500 | J28: =IF(STRScenarioTable[[#This Row],[Year]]>=3,$F$17,IF(STRScenarioTable[[#This Row],[Year]]>=2,$E$17,$D$17)) -> 0.55 | K28: =(STRScenarioTable[[#This Row],[Whole-Building STR Weekly Rent]]*52*STRScenarioTable[[#This Row],[Whole-Building STR Occupancy]]*(1-IF(STRScenarioTable[[#This Row],[Year]]>=3,$F$18,IF(STRScenarioTable[[#This Row],[Year]]>=2,$E$18,$D$18))))-(STRScenarioTable[[#This Row],[Whole-Building STR Occupancy]]*52*IF(STRScenarioTable[[#This Row],[Year]]>=3,$F$19,IF(STRScenarioTable[[#This Row],[Year]]>=2,$E$19,$D$19))) -> 183040 | L28: =CHOOSE(SelectedOperatingScenarioId,STRScenarioTable[[#This Row],[Base Annual Gross Rent]],STRScenarioTable[[#This Row],[One-Floor STR Annual Gross]],STRScenarioTable[[#This Row],[Whole-Building STR Annual Gross]]) -> 173400
A29: 5 | B29: =IF(STRScenarioTable[[#This Row],[Year]]>=RentScenarioHighEffectiveYear,"High",IF(STRScenarioTable[[#This Row],[Year]]>=RentScenarioMediumEffectiveYear,"Medium",IF(STRScenarioTable[[#This Row],[Year]]>=RentScenarioLowEffectiveYear,"Low","None"))) -> High | C29: =IF(STRScenarioTable[[#This Row],[Year]]>=RentScenarioHighEffectiveYear,RentScenarioHighMonthlyGross,IF(STRScenarioTable[[#This Row],[Year]]>=RentScenarioMediumEffectiveYear,RentScenarioMediumMonthlyGross,IF(STRScenarioTable[[#This Row],[Year]]>=RentScenarioLowEffectiveYear,RentScenarioLowMonthlyGross,0))) -> 12000 | D29: =STRScenarioTable[[#This Row],[Base Monthly Gross Rent]]*12 -> 144000 | E29: =IF(STRScenarioTable[[#This Row],[Year]]>=3,$F$14,IF(STRScenarioTable[[#This Row],[Year]]>=2,$E$14,$D$14)) -> 4000 | F29: =IF(STRScenarioTable[[#This Row],[Year]]>=3,$F$15,IF(STRScenarioTable[[#This Row],[Year]]>=2,$E$15,$D$15)) -> 0.6 | G29: =STRScenarioTable[[#This Row],[Base Annual Gross Rent]]/2 -> 72000 | H29: =(STRScenarioTable[[#This Row],[One-Floor STR Weekly Rent]]*52*STRScenarioTable[[#This Row],[One-Floor STR Occupancy]]*(1-IF(STRScenarioTable[[#This Row],[Year]]>=3,$F$18,IF(STRScenarioTable[[#This Row],[Year]]>=2,$E$18,$D$18))))-(STRScenarioTable[[#This Row],[One-Floor STR Occupancy]]*52*IF(STRScenarioTable[[#This Row],[Year]]>=3,$F$19,IF(STRScenarioTable[[#This Row],[Year]]>=2,$E$19,$D$19)))+STRScenarioTable[[#This Row],[Other Floor Annual Rent]] -> 173400 | I29: =IF(STRScenarioTable[[#This Row],[Year]]>=3,$F$16,IF(STRScenarioTable[[#This Row],[Year]]>=2,$E$16,$D$16)) -> 7500 | J29: =IF(STRScenarioTable[[#This Row],[Year]]>=3,$F$17,IF(STRScenarioTable[[#This Row],[Year]]>=2,$E$17,$D$17)) -> 0.55 | K29: =(STRScenarioTable[[#This Row],[Whole-Building STR Weekly Rent]]*52*STRScenarioTable[[#This Row],[Whole-Building STR Occupancy]]*(1-IF(STRScenarioTable[[#This Row],[Year]]>=3,$F$18,IF(STRScenarioTable[[#This Row],[Year]]>=2,$E$18,$D$18))))-(STRScenarioTable[[#This Row],[Whole-Building STR Occupancy]]*52*IF(STRScenarioTable[[#This Row],[Year]]>=3,$F$19,IF(STRScenarioTable[[#This Row],[Year]]>=2,$E$19,$D$19))) -> 183040 | L29: =CHOOSE(SelectedOperatingScenarioId,STRScenarioTable[[#This Row],[Base Annual Gross Rent]],STRScenarioTable[[#This Row],[One-Floor STR Annual Gross]],STRScenarioTable[[#This Row],[Whole-Building STR Annual Gross]]) -> 173400
A30: 6 | B30: =IF(STRScenarioTable[[#This Row],[Year]]>=RentScenarioHighEffectiveYear,"High",IF(STRScenarioTable[[#This Row],[Year]]>=RentScenarioMediumEffectiveYear,"Medium",IF(STRScenarioTable[[#This Row],[Year]]>=RentScenarioLowEffectiveYear,"Low","None"))) -> High | C30: =IF(STRScenarioTable[[#This Row],[Year]]>=RentScenarioHighEffectiveYear,RentScenarioHighMonthlyGross,IF(STRScenarioTable[[#This Row],[Year]]>=RentScenarioMediumEffectiveYear,RentScenarioMediumMonthlyGross,IF(STRScenarioTable[[#This Row],[Year]]>=RentScenarioLowEffectiveYear,RentScenarioLowMonthlyGross,0))) -> 12000 | D30: =STRScenarioTable[[#This Row],[Base Monthly Gross Rent]]*12 -> 144000 | E30: =IF(STRScenarioTable[[#This Row],[Year]]>=3,$F$14,IF(STRScenarioTable[[#This Row],[Year]]>=2,$E$14,$D$14)) -> 4000 | F30: =IF(STRScenarioTable[[#This Row],[Year]]>=3,$F$15,IF(STRScenarioTable[[#This Row],[Year]]>=2,$E$15,$D$15)) -> 0.6 | G30: =STRScenarioTable[[#This Row],[Base Annual Gross Rent]]/2 -> 72000 | H30: =(STRScenarioTable[[#This Row],[One-Floor STR Weekly Rent]]*52*STRScenarioTable[[#This Row],[One-Floor STR Occupancy]]*(1-IF(STRScenarioTable[[#This Row],[Year]]>=3,$F$18,IF(STRScenarioTable[[#This Row],[Year]]>=2,$E$18,$D$18))))-(STRScenarioTable[[#This Row],[One-Floor STR Occupancy]]*52*IF(STRScenarioTable[[#This Row],[Year]]>=3,$F$19,IF(STRScenarioTable[[#This Row],[Year]]>=2,$E$19,$D$19)))+STRScenarioTable[[#This Row],[Other Floor Annual Rent]] -> 173400 | I30: =IF(STRScenarioTable[[#This Row],[Year]]>=3,$F$16,IF(STRScenarioTable[[#This Row],[Year]]>=2,$E$16,$D$16)) -> 7500 | J30: =IF(STRScenarioTable[[#This Row],[Year]]>=3,$F$17,IF(STRScenarioTable[[#This Row],[Year]]>=2,$E$17,$D$17)) -> 0.55 | K30: =(STRScenarioTable[[#This Row],[Whole-Building STR Weekly Rent]]*52*STRScenarioTable[[#This Row],[Whole-Building STR Occupancy]]*(1-IF(STRScenarioTable[[#This Row],[Year]]>=3,$F$18,IF(STRScenarioTable[[#This Row],[Year]]>=2,$E$18,$D$18))))-(STRScenarioTable[[#This Row],[Whole-Building STR Occupancy]]*52*IF(STRScenarioTable[[#This Row],[Year]]>=3,$F$19,IF(STRScenarioTable[[#This Row],[Year]]>=2,$E$19,$D$19))) -> 183040 | L30: =CHOOSE(SelectedOperatingScenarioId,STRScenarioTable[[#This Row],[Base Annual Gross Rent]],STRScenarioTable[[#This Row],[One-Floor STR Annual Gross]],STRScenarioTable[[#This Row],[Whole-Building STR Annual Gross]]) -> 173400
A31: 7 | B31: =IF(STRScenarioTable[[#This Row],[Year]]>=RentScenarioHighEffectiveYear,"High",IF(STRScenarioTable[[#This Row],[Year]]>=RentScenarioMediumEffectiveYear,"Medium",IF(STRScenarioTable[[#This Row],[Year]]>=RentScenarioLowEffectiveYear,"Low","None"))) -> High | C31: =IF(STRScenarioTable[[#This Row],[Year]]>=RentScenarioHighEffectiveYear,RentScenarioHighMonthlyGross,IF(STRScenarioTable[[#This Row],[Year]]>=RentScenarioMediumEffectiveYear,RentScenarioMediumMonthlyGross,IF(STRScenarioTable[[#This Row],[Year]]>=RentScenarioLowEffectiveYear,RentScenarioLowMonthlyGross,0))) -> 12000 | D31: =STRScenarioTable[[#This Row],[Base Monthly Gross Rent]]*12 -> 144000 | E31: =IF(STRScenarioTable[[#This Row],[Year]]>=3,$F$14,IF(STRScenarioTable[[#This Row],[Year]]>=2,$E$14,$D$14)) -> 4000 | F31: =IF(STRScenarioTable[[#This Row],[Year]]>=3,$F$15,IF(STRScenarioTable[[#This Row],[Year]]>=2,$E$15,$D$15)) -> 0.6 | G31: =STRScenarioTable[[#This Row],[Base Annual Gross Rent]]/2 -> 72000 | H31: =(STRScenarioTable[[#This Row],[One-Floor STR Weekly Rent]]*52*STRScenarioTable[[#This Row],[One-Floor STR Occupancy]]*(1-IF(STRScenarioTable[[#This Row],[Year]]>=3,$F$18,IF(STRScenarioTable[[#This Row],[Year]]>=2,$E$18,$D$18))))-(STRScenarioTable[[#This Row],[One-Floor STR Occupancy]]*52*IF(STRScenarioTable[[#This Row],[Year]]>=3,$F$19,IF(STRScenarioTable[[#This Row],[Year]]>=2,$E$19,$D$19)))+STRScenarioTable[[#This Row],[Other Floor Annual Rent]] -> 173400 | I31: =IF(STRScenarioTable[[#This Row],[Year]]>=3,$F$16,IF(STRScenarioTable[[#This Row],[Year]]>=2,$E$16,$D$16)) -> 7500 | J31: =IF(STRScenarioTable[[#This Row],[Year]]>=3,$F$17,IF(STRScenarioTable[[#This Row],[Year]]>=2,$E$17,$D$17)) -> 0.55 | K31: =(STRScenarioTable[[#This Row],[Whole-Building STR Weekly Rent]]*52*STRScenarioTable[[#This Row],[Whole-Building STR Occupancy]]*(1-IF(STRScenarioTable[[#This Row],[Year]]>=3,$F$18,IF(STRScenarioTable[[#This Row],[Year]]>=2,$E$18,$D$18))))-(STRScenarioTable[[#This Row],[Whole-Building STR Occupancy]]*52*IF(STRScenarioTable[[#This Row],[Year]]>=3,$F$19,IF(STRScenarioTable[[#This Row],[Year]]>=2,$E$19,$D$19))) -> 183040 | L31: =CHOOSE(SelectedOperatingScenarioId,STRScenarioTable[[#This Row],[Base Annual Gross Rent]],STRScenarioTable[[#This Row],[One-Floor STR Annual Gross]],STRScenarioTable[[#This Row],[Whole-Building STR Annual Gross]]) -> 173400
A32: 8 | B32: =IF(STRScenarioTable[[#This Row],[Year]]>=RentScenarioHighEffectiveYear,"High",IF(STRScenarioTable[[#This Row],[Year]]>=RentScenarioMediumEffectiveYear,"Medium",IF(STRScenarioTable[[#This Row],[Year]]>=RentScenarioLowEffectiveYear,"Low","None"))) -> High | C32: =IF(STRScenarioTable[[#This Row],[Year]]>=RentScenarioHighEffectiveYear,RentScenarioHighMonthlyGross,IF(STRScenarioTable[[#This Row],[Year]]>=RentScenarioMediumEffectiveYear,RentScenarioMediumMonthlyGross,IF(STRScenarioTable[[#This Row],[Year]]>=RentScenarioLowEffectiveYear,RentScenarioLowMonthlyGross,0))) -> 12000 | D32: =STRScenarioTable[[#This Row],[Base Monthly Gross Rent]]*12 -> 144000 | E32: =IF(STRScenarioTable[[#This Row],[Year]]>=3,$F$14,IF(STRScenarioTable[[#This Row],[Year]]>=2,$E$14,$D$14)) -> 4000 | F32: =IF(STRScenarioTable[[#This Row],[Year]]>=3,$F$15,IF(STRScenarioTable[[#This Row],[Year]]>=2,$E$15,$D$15)) -> 0.6 | G32: =STRScenarioTable[[#This Row],[Base Annual Gross Rent]]/2 -> 72000 | H32: =(STRScenarioTable[[#This Row],[One-Floor STR Weekly Rent]]*52*STRScenarioTable[[#This Row],[One-Floor STR Occupancy]]*(1-IF(STRScenarioTable[[#This Row],[Year]]>=3,$F$18,IF(STRScenarioTable[[#This Row],[Year]]>=2,$E$18,$D$18))))-(STRScenarioTable[[#This Row],[One-Floor STR Occupancy]]*52*IF(STRScenarioTable[[#This Row],[Year]]>=3,$F$19,IF(STRScenarioTable[[#This Row],[Year]]>=2,$E$19,$D$19)))+STRScenarioTable[[#This Row],[Other Floor Annual Rent]] -> 173400 | I32: =IF(STRScenarioTable[[#This Row],[Year]]>=3,$F$16,IF(STRScenarioTable[[#This Row],[Year]]>=2,$E$16,$D$16)) -> 7500 | J32: =IF(STRScenarioTable[[#This Row],[Year]]>=3,$F$17,IF(STRScenarioTable[[#This Row],[Year]]>=2,$E$17,$D$17)) -> 0.55 | K32: =(STRScenarioTable[[#This Row],[Whole-Building STR Weekly Rent]]*52*STRScenarioTable[[#This Row],[Whole-Building STR Occupancy]]*(1-IF(STRScenarioTable[[#This Row],[Year]]>=3,$F$18,IF(STRScenarioTable[[#This Row],[Year]]>=2,$E$18,$D$18))))-(STRScenarioTable[[#This Row],[Whole-Building STR Occupancy]]*52*IF(STRScenarioTable[[#This Row],[Year]]>=3,$F$19,IF(STRScenarioTable[[#This Row],[Year]]>=2,$E$19,$D$19))) -> 183040 | L32: =CHOOSE(SelectedOperatingScenarioId,STRScenarioTable[[#This Row],[Base Annual Gross Rent]],STRScenarioTable[[#This Row],[One-Floor STR Annual Gross]],STRScenarioTable[[#This Row],[Whole-Building STR Annual Gross]]) -> 173400
A33: 9 | B33: =IF(STRScenarioTable[[#This Row],[Year]]>=RentScenarioHighEffectiveYear,"High",IF(STRScenarioTable[[#This Row],[Year]]>=RentScenarioMediumEffectiveYear,"Medium",IF(STRScenarioTable[[#This Row],[Year]]>=RentScenarioLowEffectiveYear,"Low","None"))) -> High | C33: =IF(STRScenarioTable[[#This Row],[Year]]>=RentScenarioHighEffectiveYear,RentScenarioHighMonthlyGross,IF(STRScenarioTable[[#This Row],[Year]]>=RentScenarioMediumEffectiveYear,RentScenarioMediumMonthlyGross,IF(STRScenarioTable[[#This Row],[Year]]>=RentScenarioLowEffectiveYear,RentScenarioLowMonthlyGross,0))) -> 12000 | D33: =STRScenarioTable[[#This Row],[Base Monthly Gross Rent]]*12 -> 144000 | E33: =IF(STRScenarioTable[[#This Row],[Year]]>=3,$F$14,IF(STRScenarioTable[[#This Row],[Year]]>=2,$E$14,$D$14)) -> 4000 | F33: =IF(STRScenarioTable[[#This Row],[Year]]>=3,$F$15,IF(STRScenarioTable[[#This Row],[Year]]>=2,$E$15,$D$15)) -> 0.6 | G33: =STRScenarioTable[[#This Row],[Base Annual Gross Rent]]/2 -> 72000 | H33: =(STRScenarioTable[[#This Row],[One-Floor STR Weekly Rent]]*52*STRScenarioTable[[#This Row],[One-Floor STR Occupancy]]*(1-IF(STRScenarioTable[[#This Row],[Year]]>=3,$F$18,IF(STRScenarioTable[[#This Row],[Year]]>=2,$E$18,$D$18))))-(STRScenarioTable[[#This Row],[One-Floor STR Occupancy]]*52*IF(STRScenarioTable[[#This Row],[Year]]>=3,$F$19,IF(STRScenarioTable[[#This Row],[Year]]>=2,$E$19,$D$19)))+STRScenarioTable[[#This Row],[Other Floor Annual Rent]] -> 173400 | I33: =IF(STRScenarioTable[[#This Row],[Year]]>=3,$F$16,IF(STRScenarioTable[[#This Row],[Year]]>=2,$E$16,$D$16)) -> 7500 | J33: =IF(STRScenarioTable[[#This Row],[Year]]>=3,$F$17,IF(STRScenarioTable[[#This Row],[Year]]>=2,$E$17,$D$17)) -> 0.55 | K33: =(STRScenarioTable[[#This Row],[Whole-Building STR Weekly Rent]]*52*STRScenarioTable[[#This Row],[Whole-Building STR Occupancy]]*(1-IF(STRScenarioTable[[#This Row],[Year]]>=3,$F$18,IF(STRScenarioTable[[#This Row],[Year]]>=2,$E$18,$D$18))))-(STRScenarioTable[[#This Row],[Whole-Building STR Occupancy]]*52*IF(STRScenarioTable[[#This Row],[Year]]>=3,$F$19,IF(STRScenarioTable[[#This Row],[Year]]>=2,$E$19,$D$19))) -> 183040 | L33: =CHOOSE(SelectedOperatingScenarioId,STRScenarioTable[[#This Row],[Base Annual Gross Rent]],STRScenarioTable[[#This Row],[One-Floor STR Annual Gross]],STRScenarioTable[[#This Row],[Whole-Building STR Annual Gross]]) -> 173400
A34: 10 | B34: =IF(STRScenarioTable[[#This Row],[Year]]>=RentScenarioHighEffectiveYear,"High",IF(STRScenarioTable[[#This Row],[Year]]>=RentScenarioMediumEffectiveYear,"Medium",IF(STRScenarioTable[[#This Row],[Year]]>=RentScenarioLowEffectiveYear,"Low","None"))) -> High | C34: =IF(STRScenarioTable[[#This Row],[Year]]>=RentScenarioHighEffectiveYear,RentScenarioHighMonthlyGross,IF(STRScenarioTable[[#This Row],[Year]]>=RentScenarioMediumEffectiveYear,RentScenarioMediumMonthlyGross,IF(STRScenarioTable[[#This Row],[Year]]>=RentScenarioLowEffectiveYear,RentScenarioLowMonthlyGross,0))) -> 12000 | D34: =STRScenarioTable[[#This Row],[Base Monthly Gross Rent]]*12 -> 144000 | E34: =IF(STRScenarioTable[[#This Row],[Year]]>=3,$F$14,IF(STRScenarioTable[[#This Row],[Year]]>=2,$E$14,$D$14)) -> 4000 | F34: =IF(STRScenarioTable[[#This Row],[Year]]>=3,$F$15,IF(STRScenarioTable[[#This Row],[Year]]>=2,$E$15,$D$15)) -> 0.6 | G34: =STRScenarioTable[[#This Row],[Base Annual Gross Rent]]/2 -> 72000 | H34: =(STRScenarioTable[[#This Row],[One-Floor STR Weekly Rent]]*52*STRScenarioTable[[#This Row],[One-Floor STR Occupancy]]*(1-IF(STRScenarioTable[[#This Row],[Year]]>=3,$F$18,IF(STRScenarioTable[[#This Row],[Year]]>=2,$E$18,$D$18))))-(STRScenarioTable[[#This Row],[One-Floor STR Occupancy]]*52*IF(STRScenarioTable[[#This Row],[Year]]>=3,$F$19,IF(STRScenarioTable[[#This Row],[Year]]>=2,$E$19,$D$19)))+STRScenarioTable[[#This Row],[Other Floor Annual Rent]] -> 173400 | I34: =IF(STRScenarioTable[[#This Row],[Year]]>=3,$F$16,IF(STRScenarioTable[[#This Row],[Year]]>=2,$E$16,$D$16)) -> 7500 | J34: =IF(STRScenarioTable[[#This Row],[Year]]>=3,$F$17,IF(STRScenarioTable[[#This Row],[Year]]>=2,$E$17,$D$17)) -> 0.55 | K34: =(STRScenarioTable[[#This Row],[Whole-Building STR Weekly Rent]]*52*STRScenarioTable[[#This Row],[Whole-Building STR Occupancy]]*(1-IF(STRScenarioTable[[#This Row],[Year]]>=3,$F$18,IF(STRScenarioTable[[#This Row],[Year]]>=2,$E$18,$D$18))))-(STRScenarioTable[[#This Row],[Whole-Building STR Occupancy]]*52*IF(STRScenarioTable[[#This Row],[Year]]>=3,$F$19,IF(STRScenarioTable[[#This Row],[Year]]>=2,$E$19,$D$19))) -> 183040 | L34: =CHOOSE(SelectedOperatingScenarioId,STRScenarioTable[[#This Row],[Base Annual Gross Rent]],STRScenarioTable[[#This Row],[One-Floor STR Annual Gross]],STRScenarioTable[[#This Row],[Whole-Building STR Annual Gross]]) -> 173400

Sheet Assumptions
A1: 3325 Banks Rd - Investor Return Model | C1: Editable inputs are in column B. Outputs update through formulas.
A3: Project Timing | L3: Experimental STR Scenario
A4: Stabilization / Refinance Year | B4: =MAX(1,MIN(10,SelectedWaterfallRefiOption)) -> 3 | C4: Model uses selected Waterfall refinance-year option button; helper cell Waterfall!R3; buttons shown for Years 1-10 only | L4: Selected Operating Scenario | M4: =SelectedOperatingScenario -> One Floor STR + One Floor Co-Living
A5: Sale / Exit Year | B5: =MAX(1,MIN(10,SelectedWaterfallExitOption)) -> 5 | C5: Model uses selected Waterfall exit-year option button; helper cell Waterfall!S3; buttons shown for Years 1-10 only | L5: Edit selector on STR Scenarios!B4
A7: Rental Program | D7: Rent Scenario Schedule
A8: First Floor Premium Suites | B8: 4 | C8: Private bed/bath/kitchenette suites | D8: Rent Input | E8: Low | F8: Medium | G8: High | H8: Average | I8: Current Use | J8: Notes
A9: Monthly Rent per Premium Suite | B9: 1600 | C9: Mid/base reference; Annual Model uses scenario schedule at right | D9: Premium Suite Rent | E9: 1350 | F9: 1600 | G9: 1750 | H9: =AVERAGE(E9:G9) -> 1566.6667 | I9: Rent levels increase left to right
A10: Second Floor Co-Living Suites | B10: 4 | C10: Private bed/bath with shared amenities | D10: Co-Living Suite Rent | E10: 850 | F10: 1100 | G10: 1250 | H10: =AVERAGE(E10:G10) -> 1066.6667 | I10: Rent levels increase left to right
A11: Monthly Rent per Co-Living Suite | B11: 1100 | C11: Mid/base reference; Annual Model uses scenario schedule at right | D11: Monthly Gross Rent | E11: =PremiumSuites*E9+CoLivingSuites*E10+OtherMonthlyIncome -> 8800 | F11: =PremiumSuites*F9+CoLivingSuites*F10+OtherMonthlyIncome -> 10800 | G11: =PremiumSuites*G9+CoLivingSuites*G10+OtherMonthlyIncome -> 12000 | H11: =AVERAGE(E11:G11) -> 10533.333 | I11: Average is reference only; model uses scenario schedule
A12: Other Monthly Income | B12: 0 | C12: Parking, utility fees, laundry, etc. | D12: Effective Year | E12: 1 | F12: 2 | G12: 3 | I12: Annual Model timing | J12: Low ends after Year 1 under current schedule
A13: Stabilized Occupancy | B13: 0.93 | C13: Before operating expense load
A14: Year 1 Lease-Up Occupancy | B14: 0.5 | C14: First partial operating year
A15: Selected Operating Expense Ratio | B15: =SelectedOperatingExpenseRatio -> 0.46912485 | C15: From Operating Expense Budget tab; toggle between assumed ratio and calculated budget ratio
A16: NOI Growth | B16: 0.03 | C16: Annual growth after stabilization
A17: Stabilized Monthly Gross Rent | B17: =IF(StabilizationRefiYear>=RentScenarioHighEffectiveYear,RentScenarioHighMonthlyGross,IF(StabilizationRefiYear>=RentScenarioMediumEffectiveYear,RentScenarioMediumMonthlyGross,IF(StabilizationRefiYear>=RentScenarioLowEffectiveYear,RentScenarioLowMonthlyGross,0))) -> 12000 | C17: Selected by Rent Scenario Schedule for the Stabilization / Refinance Year; average is reference only
A19: Debt / Refinance / Exit
A20: Existing First Mortgage Principal | B20: 119000 | C20: Existing first mortgage principal to be paid from refinance proceeds
A21: Existing First Mortgage Rate | B21: 0.0325 | C21: Interest rate on existing first mortgage
A22: Private Debt Principal | B22: 75000 | C22: Private debt principal; interest-only before payoff
A23: Private Debt Interest Rate | B23: 0.1 | C23: Interest-only private debt rate
A24: Total Existing Debt Payoff | B24: =_xlfn.SINGLE(ExistingFirstMortgagePrincipal)+PrivateDebtPrincipal -> 194000 | C24: Existing first mortgage principal plus private debt principal
A25: First Mortgage Monthly P&I Excl. Escrow | B25: 526 | C25: Actual monthly principal and interest payment; excludes escrow, taxes, and insurance
A26: First Mortgage Annual P&I Excl. Escrow | B26: =_xlfn.SINGLE(ExistingFirstMortgageMonthlyPI)*12 -> 6312 | C26: Annual principal and interest payment; excludes escrow, taxes, and insurance
A27: Private Debt Annual Interest Payment | B27: =PrivateDebtPrincipal*PrivateDebtInterestRate -> 7500 | C27: Interest-only payment on private debt
A28: Total Existing Annual Debt Service | B28: =ExistingFirstMortgageAnnualPayment+PrivateDebtAnnualInterestPayment -> 13812 | C28: Existing debt service before refinance; taxes and insurance remain in operating expenses
A29: Refinance Loan-to-Value Cap | B29: 0.7 | C29: Maximum refinance loan as % of stabilized value
A30: Refinance Loan Amount | B30: =MIN((StabilizedMonthlyGrossRent*12*StabilizedOccupancy*(1-OperatingExpenseRatio)*(1+NOIGrowth)/ExitCapRate)*RefinanceLoanToValueCap,TotalExistingDebt+ClassACapital+ClassBCapital) -> 732276.44 | C30: Only new loan; takeout/refinance proceeds, not development or construction debt
A31: Refi Proceeds After Existing Debt | B31: =MAX(0,RefinanceLoanAmount-TotalExistingDebt) -> 538276.44 | C31: Available to Class A first through waterfall
A32: Refi Remaining After Debt + Class A | B32: =MAX(0,RefinanceLoanAmount-TotalExistingDebt-ClassACapital) -> 238276.44 | C32: Indicative amount available to Class B before waterfall details
A33: Refinance Loan Interest Rate | B33: 0.065 | C33: Annual fixed rate on stabilization refinance loan
A34: Refinance Loan Amortization Years | B34: 30 | C34: Used for annual debt service after stabilization refinance
A35: Exit Cap Rate | B35: 0.07 | C35: Sale value = following year NOI / cap rate
A36: Selling Costs | B36: 0.02 | C36: Percent deducted from gross sale value
A38: Capital Stack / Waterfall
A39: Class A Capital | B39: 300000 | C39: Preferred capital raise
A40: Class A Preferred Return | B40: 0.08 | C40: Cumulative annual preferred return
A41: Class B Capital | B41: =MAX(0,SelectedProjectCost-ClassACapital) -> 547500 | C41: Subordinate beneficiary capital; dependent upon selected project cost in Cost Analysis
A42: Class B Capital Return Priority | B42: 1 | C42: 1 = return Class B capital before residual split
A43: Sponsor Residual Share | B43: 0.5 | C43: Editable sponsor share of residual after capital return priorities
A44: Class A Residual Share | B44: =(1-SponsorResidualShare)*(ClassACapital/(ClassACapital+ClassBCapital)) -> 0.17699115 | C44: Class A share of non-sponsor residual, proportional to Class A capital
A45: Class B Residual Share | B45: =(1-SponsorResidualShare)*(ClassBCapital/(ClassACapital+ClassBCapital)) -> 0.32300885 | C45: Class B share of non-sponsor residual, proportional to Class B capital
A46: Sponsor Property Payment / Basis | B46: 100000 | C46: Payment to Sponsor for property; also used as Sponsor basis for return analysis
A47: Sponsor Capital Investment | B47: 136283 | C47: Actual sponsor cash/cost invested; separate from property payment / basis
A48: Model Note | B48: This is a planning model, not tax, legal, securities, or investment advice.

Sheet Annual Model
A1: Annual Project Model
A3: Year | B3: Phase | C3: Gross Potential Rent | D3: Occupancy Effective Gross Income | E3: Operating Expenses | F3: NOI | G3: Debt Service | H3: Cash Before Refi/Sale | I3: Net Refi/Sale Proceeds | J3: Reserve Funding | K3: Reserve Balance | L3: Cash Available Before Distributions | M3: Waterfall Distributions | N3: Ending Cash Balance | O3: Loan Balance | P3: Property Value / Refi Value
A4: 0 | B4: Capitalization / Entitlement | C4: =IF(AnnualModelTable[[#This Row],[Year]]>SaleExitYear,0,IF(AnnualModelTable[[#This Row],[Year]]=0,0,INDEX(STRScenarioTable[Selected Annual Gross Rent],MATCH(AnnualModelTable[[#This Row],[Year]],STRScenarioTable[Year],0)))) -> 0 | D4: =IF(AnnualModelTable[[#This Row],[Year]]>SaleExitYear,0,IF(AnnualModelTable[[#This Row],[Year]]=0,0,AnnualModelTable[[#This Row],[Gross Potential Rent]]*IF(AnnualModelTable[[#This Row],[Year]]=1,LeaseUpOccupancy,StabilizedOccupancy))) -> 0 | E4: =IF(AnnualModelTable[[#This Row],[Year]]>SaleExitYear,0,AnnualModelTable[[#This Row],[Occupancy Effective Gross Income]]*OperatingExpenseRatio) -> 0 | F4: =IF(AnnualModelTable[[#This Row],[Year]]>SaleExitYear,0,AnnualModelTable[[#This Row],[Occupancy Effective Gross Income]]-AnnualModelTable[[#This Row],[Operating Expenses]]) -> 0 | G4: =IF(AnnualModelTable[[#This Row],[Year]]>SaleExitYear,0,IF(AND(AnnualModelTable[[#This Row],[Year]]>=1,AnnualModelTable[[#This Row],[Year]]<StabilizationRefiYear),ExistingDebtServiceAnnual,IF(AND(AnnualModelTable[[#This Row],[Year]]>=StabilizationRefiYear,AnnualModelTable[[#This Row],[Year]]<=SaleExitYear),-PMT(RefinanceLoanRate/12,RefinanceLoanAmortizationYears*12,RefinanceLoanAmount)*12,0))) -> 0 | H4: =IF(AnnualModelTable[[#This Row],[Year]]>SaleExitYear,0,AnnualModelTable[[#This Row],[NOI]]-AnnualModelTable[[#This Row],[Debt Service]]) -> 0 | I4: =IF(AnnualModelTable[[#This Row],[Year]]>SaleExitYear,0,IF(AnnualModelTable[[#This Row],[Year]]=0,SponsorPropertyPayment,IF(AnnualModelTable[[#This Row],[Year]]=StabilizationRefiYear,MAX(0,RefinanceLoanAmount-TotalExistingDebt),IF(AnnualModelTable[[#This Row],[Year]]=SaleExitYear,MAX(0,AnnualModelTable[[#This Row],[Property Value / Refi Value]]*(1-SellingCosts)-AnnualModelTable[[#This Row],[Loan Balance]]),0)))) -> 100000 | J4: =IF(AnnualModelTable[[#This Row],[Year]]>SaleExitYear,0,IF(AnnualModelTable[[#This Row],[Year]]=0,0,MIN(MAX(0,RepairsMaintenanceReserveTarget-IFERROR(INDEX(AnnualModelTable[Reserve Balance],MATCH(AnnualModelTable[[#This Row],[Year]]-1,AnnualModelTable[Year],0)),0)),MAX(0,IFERROR(INDEX(AnnualModelTable[Ending Cash Balance],MATCH(AnnualModelTable[[#This Row],[Year]]-1,AnnualModelTable[Year],0)),0)+AnnualModelTable[[#This Row],[Cash Before Refi/Sale]]+AnnualModelTable[[#This Row],[Net Refi/Sale Proceeds]])))) -> 0 | K4: =IF(AnnualModelTable[[#This Row],[Year]]>SaleExitYear,0,IF(AnnualModelTable[[#This Row],[Year]]=0,0,IFERROR(INDEX(AnnualModelTable[Reserve Balance],MATCH(AnnualModelTable[[#This Row],[Year]]-1,AnnualModelTable[Year],0)),0)+AnnualModelTable[[#This Row],[Reserve Funding]])) -> 0 | L4: =IF(AnnualModelTable[[#This Row],[Year]]>SaleExitYear,0,IF(AnnualModelTable[[#This Row],[Year]]=0,0,IFERROR(INDEX(AnnualModelTable[Ending Cash Balance],MATCH(AnnualModelTable[[#This Row],[Year]]-1,AnnualModelTable[Year],0)),0))+AnnualModelTable[[#This Row],[Cash Before Refi/Sale]]+AnnualModelTable[[#This Row],[Net Refi/Sale Proceeds]]-AnnualModelTable[[#This Row],[Reserve Funding]]) -> 100000 | M4: =IF(AnnualModelTable[[#This Row],[Year]]>SaleExitYear,0,SUM(INDEX(WaterfallTable[Total Dist A],MATCH(AnnualModelTable[[#This Row],[Year]],WaterfallTable[Year],0)),INDEX(WaterfallTable[Total Dist B],MATCH(AnnualModelTable[[#This Row],[Year]],WaterfallTable[Year],0)),INDEX(WaterfallTable[Total Dist2],MATCH(AnnualModelTable[[#This Row],[Year]],WaterfallTable[Year],0)))) -> 100000 | N4: =IF(AnnualModelTable[[#This Row],[Year]]>SaleExitYear,0,MAX(0,AnnualModelTable[[#This Row],[Cash Available Before Distributions]]-AnnualModelTable[[#This Row],[Waterfall Distributions]])) -> 0 | O4: =IF(AnnualModelTable[[#This Row],[Year]]>SaleExitYear,0,IF(AnnualModelTable[[#This Row],[Year]]<StabilizationRefiYear,0,IF(AnnualModelTable[[#This Row],[Year]]=SaleExitYear,0,-FV(RefinanceLoanRate/12,(AnnualModelTable[[#This Row],[Year]]-StabilizationRefiYear)*12,PMT(RefinanceLoanRate/12,RefinanceLoanAmortizationYears*12,RefinanceLoanAmount),RefinanceLoanAmount)))) -> 0 | P4: =IF(AnnualModelTable[[#This Row],[Year]]>SaleExitYear,0,IF(AnnualModelTable[[#This Row],[Year]]<StabilizationRefiYear,0,AnnualModelTable[[#This Row],[NOI]]*(1+NOIGrowth)/ExitCapRate)) -> 0
A5: 1 | B5: Lease-Up | C5: =IF(AnnualModelTable[[#This Row],[Year]]>SaleExitYear,0,IF(AnnualModelTable[[#This Row],[Year]]=0,0,INDEX(STRScenarioTable[Selected Annual Gross Rent],MATCH(AnnualModelTable[[#This Row],[Year]],STRScenarioTable[Year],0)))) -> 95440 | D5: =IF(AnnualModelTable[[#This Row],[Year]]>SaleExitYear,0,IF(AnnualModelTable[[#This Row],[Year]]=0,0,AnnualModelTable[[#This Row],[Gross Potential Rent]]*IF(AnnualModelTable[[#This Row],[Year]]=1,LeaseUpOccupancy,StabilizedOccupancy))) -> 47720 | E5: =IF(AnnualModelTable[[#This Row],[Year]]>SaleExitYear,0,AnnualModelTable[[#This Row],[Occupancy Effective Gross Income]]*OperatingExpenseRatio) -> 22386.638 | F5: =IF(AnnualModelTable[[#This Row],[Year]]>SaleExitYear,0,AnnualModelTable[[#This Row],[Occupancy Effective Gross Income]]-AnnualModelTable[[#This Row],[Operating Expenses]]) -> 25333.362 | G5: =IF(AnnualModelTable[[#This Row],[Year]]>SaleExitYear,0,IF(AND(AnnualModelTable[[#This Row],[Year]]>=1,AnnualModelTable[[#This Row],[Year]]<StabilizationRefiYear),ExistingDebtServiceAnnual,IF(AND(AnnualModelTable[[#This Row],[Year]]>=StabilizationRefiYear,AnnualModelTable[[#This Row],[Year]]<=SaleExitYear),-PMT(RefinanceLoanRate/12,RefinanceLoanAmortizationYears*12,RefinanceLoanAmount)*12,0))) -> 13812 | H5: =IF(AnnualModelTable[[#This Row],[Year]]>SaleExitYear,0,AnnualModelTable[[#This Row],[NOI]]-AnnualModelTable[[#This Row],[Debt Service]]) -> 11521.362 | I5: =IF(AnnualModelTable[[#This Row],[Year]]>SaleExitYear,0,IF(AnnualModelTable[[#This Row],[Year]]=0,SponsorPropertyPayment,IF(AnnualModelTable[[#This Row],[Year]]=StabilizationRefiYear,MAX(0,RefinanceLoanAmount-TotalExistingDebt),IF(AnnualModelTable[[#This Row],[Year]]=SaleExitYear,MAX(0,AnnualModelTable[[#This Row],[Property Value / Refi Value]]*(1-SellingCosts)-AnnualModelTable[[#This Row],[Loan Balance]]),0)))) -> 0 | J5: =IF(AnnualModelTable[[#This Row],[Year]]>SaleExitYear,0,IF(AnnualModelTable[[#This Row],[Year]]=0,0,MIN(MAX(0,RepairsMaintenanceReserveTarget-IFERROR(INDEX(AnnualModelTable[Reserve Balance],MATCH(AnnualModelTable[[#This Row],[Year]]-1,AnnualModelTable[Year],0)),0)),MAX(0,IFERROR(INDEX(AnnualModelTable[Ending Cash Balance],MATCH(AnnualModelTable[[#This Row],[Year]]-1,AnnualModelTable[Year],0)),0)+AnnualModelTable[[#This Row],[Cash Before Refi/Sale]]+AnnualModelTable[[#This Row],[Net Refi/Sale Proceeds]])))) -> 9000 | K5: =IF(AnnualModelTable[[#This Row],[Year]]>SaleExitYear,0,IF(AnnualModelTable[[#This Row],[Year]]=0,0,IFERROR(INDEX(AnnualModelTable[Reserve Balance],MATCH(AnnualModelTable[[#This Row],[Year]]-1,AnnualModelTable[Year],0)),0)+AnnualModelTable[[#This Row],[Reserve Funding]])) -> 9000 | L5: =IF(AnnualModelTable[[#This Row],[Year]]>SaleExitYear,0,IF(AnnualModelTable[[#This Row],[Year]]=0,0,IFERROR(INDEX(AnnualModelTable[Ending Cash Balance],MATCH(AnnualModelTable[[#This Row],[Year]]-1,AnnualModelTable[Year],0)),0))+AnnualModelTable[[#This Row],[Cash Before Refi/Sale]]+AnnualModelTable[[#This Row],[Net Refi/Sale Proceeds]]-AnnualModelTable[[#This Row],[Reserve Funding]]) -> 2521.3621 | M5: =IF(AnnualModelTable[[#This Row],[Year]]>SaleExitYear,0,SUM(INDEX(WaterfallTable[Total Dist A],MATCH(AnnualModelTable[[#This Row],[Year]],WaterfallTable[Year],0)),INDEX(WaterfallTable[Total Dist B],MATCH(AnnualModelTable[[#This Row],[Year]],WaterfallTable[Year],0)),INDEX(WaterfallTable[Total Dist2],MATCH(AnnualModelTable[[#This Row],[Year]],WaterfallTable[Year],0)))) -> 2521.3621 | N5: =IF(AnnualModelTable[[#This Row],[Year]]>SaleExitYear,0,MAX(0,AnnualModelTable[[#This Row],[Cash Available Before Distributions]]-AnnualModelTable[[#This Row],[Waterfall Distributions]])) -> 0 | O5: =IF(AnnualModelTable[[#This Row],[Year]]>SaleExitYear,0,IF(AnnualModelTable[[#This Row],[Year]]<StabilizationRefiYear,0,IF(AnnualModelTable[[#This Row],[Year]]=SaleExitYear,0,-FV(RefinanceLoanRate/12,(AnnualModelTable[[#This Row],[Year]]-StabilizationRefiYear)*12,PMT(RefinanceLoanRate/12,RefinanceLoanAmortizationYears*12,RefinanceLoanAmount),RefinanceLoanAmount)))) -> 0 | P5: =IF(AnnualModelTable[[#This Row],[Year]]>SaleExitYear,0,IF(AnnualModelTable[[#This Row],[Year]]<StabilizationRefiYear,0,AnnualModelTable[[#This Row],[NOI]]*(1+NOIGrowth)/ExitCapRate)) -> 0
A6: 2 | B6: Stabilization / Refi | C6: =IF(AnnualModelTable[[#This Row],[Year]]>SaleExitYear,0,IF(AnnualModelTable[[#This Row],[Year]]=0,0,INDEX(STRScenarioTable[Selected Annual Gross Rent],MATCH(AnnualModelTable[[#This Row],[Year]],STRScenarioTable[Year],0)))) -> 133895 | D6: =IF(AnnualModelTable[[#This Row],[Year]]>SaleExitYear,0,IF(AnnualModelTable[[#This Row],[Year]]=0,0,AnnualModelTable[[#This Row],[Gross Potential Rent]]*IF(AnnualModelTable[[#This Row],[Year]]=1,LeaseUpOccupancy,StabilizedOccupancy))) -> 124522.35 | E6: =IF(AnnualModelTable[[#This Row],[Year]]>SaleExitYear,0,AnnualModelTable[[#This Row],[Occupancy Effective Gross Income]]*OperatingExpenseRatio) -> 58416.529 | F6: =IF(AnnualModelTable[[#This Row],[Year]]>SaleExitYear,0,AnnualModelTable[[#This Row],[Occupancy Effective Gross Income]]-AnnualModelTable[[#This Row],[Operating Expenses]]) -> 66105.821 | G6: =IF(AnnualModelTable[[#This Row],[Year]]>SaleExitYear,0,IF(AND(AnnualModelTable[[#This Row],[Year]]>=1,AnnualModelTable[[#This Row],[Year]]<StabilizationRefiYear),ExistingDebtServiceAnnual,IF(AND(AnnualModelTable[[#This Row],[Year]]>=StabilizationRefiYear,AnnualModelTable[[#This Row],[Year]]<=SaleExitYear),-PMT(RefinanceLoanRate/12,RefinanceLoanAmortizationYears*12,RefinanceLoanAmount)*12,0))) -> 13812 | H6: =IF(AnnualModelTable[[#This Row],[Year]]>SaleExitYear,0,AnnualModelTable[[#This Row],[NOI]]-AnnualModelTable[[#This Row],[Debt Service]]) -> 52293.821 | I6: =IF(AnnualModelTable[[#This Row],[Year]]>SaleExitYear,0,IF(AnnualModelTable[[#This Row],[Year]]=0,SponsorPropertyPayment,IF(AnnualModelTable[[#This Row],[Year]]=StabilizationRefiYear,MAX(0,RefinanceLoanAmount-TotalExistingDebt),IF(AnnualModelTable[[#This Row],[Year]]=SaleExitYear,MAX(0,AnnualModelTable[[#This Row],[Property Value / Refi Value]]*(1-SellingCosts)-AnnualModelTable[[#This Row],[Loan Balance]]),0)))) -> 0 | J6: =IF(AnnualModelTable[[#This Row],[Year]]>SaleExitYear,0,IF(AnnualModelTable[[#This Row],[Year]]=0,0,MIN(MAX(0,RepairsMaintenanceReserveTarget-IFERROR(INDEX(AnnualModelTable[Reserve Balance],MATCH(AnnualModelTable[[#This Row],[Year]]-1,AnnualModelTable[Year],0)),0)),MAX(0,IFERROR(INDEX(AnnualModelTable[Ending Cash Balance],MATCH(AnnualModelTable[[#This Row],[Year]]-1,AnnualModelTable[Year],0)),0)+AnnualModelTable[[#This Row],[Cash Before Refi/Sale]]+AnnualModelTable[[#This Row],[Net Refi/Sale Proceeds]])))) -> 0 | K6: =IF(AnnualModelTable[[#This Row],[Year]]>SaleExitYear,0,IF(AnnualModelTable[[#This Row],[Year]]=0,0,IFERROR(INDEX(AnnualModelTable[Reserve Balance],MATCH(AnnualModelTable[[#This Row],[Year]]-1,AnnualModelTable[Year],0)),0)+AnnualModelTable[[#This Row],[Reserve Funding]])) -> 9000 | L6: =IF(AnnualModelTable[[#This Row],[Year]]>SaleExitYear,0,IF(AnnualModelTable[[#This Row],[Year]]=0,0,IFERROR(INDEX(AnnualModelTable[Ending Cash Balance],MATCH(AnnualModelTable[[#This Row],[Year]]-1,AnnualModelTable[Year],0)),0))+AnnualModelTable[[#This Row],[Cash Before Refi/Sale]]+AnnualModelTable[[#This Row],[Net Refi/Sale Proceeds]]-AnnualModelTable[[#This Row],[Reserve Funding]]) -> 52293.821 | M6: =IF(AnnualModelTable[[#This Row],[Year]]>SaleExitYear,0,SUM(INDEX(WaterfallTable[Total Dist A],MATCH(AnnualModelTable[[#This Row],[Year]],WaterfallTable[Year],0)),INDEX(WaterfallTable[Total Dist B],MATCH(AnnualModelTable[[#This Row],[Year]],WaterfallTable[Year],0)),INDEX(WaterfallTable[Total Dist2],MATCH(AnnualModelTable[[#This Row],[Year]],WaterfallTable[Year],0)))) -> 52293.821 | N6: =IF(AnnualModelTable[[#This Row],[Year]]>SaleExitYear,0,MAX(0,AnnualModelTable[[#This Row],[Cash Available Before Distributions]]-AnnualModelTable[[#This Row],[Waterfall Distributions]])) -> 0 | O6: =IF(AnnualModelTable[[#This Row],[Year]]>SaleExitYear,0,IF(AnnualModelTable[[#This Row],[Year]]<StabilizationRefiYear,0,IF(AnnualModelTable[[#This Row],[Year]]=SaleExitYear,0,-FV(RefinanceLoanRate/12,(AnnualModelTable[[#This Row],[Year]]-StabilizationRefiYear)*12,PMT(RefinanceLoanRate/12,RefinanceLoanAmortizationYears*12,RefinanceLoanAmount),RefinanceLoanAmount)))) -> 0 | P6: =IF(AnnualModelTable[[#This Row],[Year]]>SaleExitYear,0,IF(AnnualModelTable[[#This Row],[Year]]<StabilizationRefiYear,0,AnnualModelTable[[#This Row],[NOI]]*(1+NOIGrowth)/ExitCapRate)) -> 0
A7: 3 | B7: Operations | C7: =IF(AnnualModelTable[[#This Row],[Year]]>SaleExitYear,0,IF(AnnualModelTable[[#This Row],[Year]]=0,0,INDEX(STRScenarioTable[Selected Annual Gross Rent],MATCH(AnnualModelTable[[#This Row],[Year]],STRScenarioTable[Year],0)))) -> 173400 | D7: =IF(AnnualModelTable[[#This Row],[Year]]>SaleExitYear,0,IF(AnnualModelTable[[#This Row],[Year]]=0,0,AnnualModelTable[[#This Row],[Gross Potential Rent]]*IF(AnnualModelTable[[#This Row],[Year]]=1,LeaseUpOccupancy,StabilizedOccupancy))) -> 161262 | E7: =IF(AnnualModelTable[[#This Row],[Year]]>SaleExitYear,0,AnnualModelTable[[#This Row],[Occupancy Effective Gross Income]]*OperatingExpenseRatio) -> 75652.012 | F7: =IF(AnnualModelTable[[#This Row],[Year]]>SaleExitYear,0,AnnualModelTable[[#This Row],[Occupancy Effective Gross Income]]-AnnualModelTable[[#This Row],[Operating Expenses]]) -> 85609.988 | G7: =IF(AnnualModelTable[[#This Row],[Year]]>SaleExitYear,0,IF(AND(AnnualModelTable[[#This Row],[Year]]>=1,AnnualModelTable[[#This Row],[Year]]<StabilizationRefiYear),ExistingDebtServiceAnnual,IF(AND(AnnualModelTable[[#This Row],[Year]]>=StabilizationRefiYear,AnnualModelTable[[#This Row],[Year]]<=SaleExitYear),-PMT(RefinanceLoanRate/12,RefinanceLoanAmortizationYears*12,RefinanceLoanAmount)*12,0))) -> 55541.823 | H7: =IF(AnnualModelTable[[#This Row],[Year]]>SaleExitYear,0,AnnualModelTable[[#This Row],[NOI]]-AnnualModelTable[[#This Row],[Debt Service]]) -> 30068.166 | I7: =IF(AnnualModelTable[[#This Row],[Year]]>SaleExitYear,0,IF(AnnualModelTable[[#This Row],[Year]]=0,SponsorPropertyPayment,IF(AnnualModelTable[[#This Row],[Year]]=StabilizationRefiYear,MAX(0,RefinanceLoanAmount-TotalExistingDebt),IF(AnnualModelTable[[#This Row],[Year]]=SaleExitYear,MAX(0,AnnualModelTable[[#This Row],[Property Value / Refi Value]]*(1-SellingCosts)-AnnualModelTable[[#This Row],[Loan Balance]]),0)))) -> 538276.44 | J7: =IF(AnnualModelTable[[#This Row],[Year]]>SaleExitYear,0,IF(AnnualModelTable[[#This Row],[Year]]=0,0,MIN(MAX(0,RepairsMaintenanceReserveTarget-IFERROR(INDEX(AnnualModelTable[Reserve Balance],MATCH(AnnualModelTable[[#This Row],[Year]]-1,AnnualModelTable[Year],0)),0)),MAX(0,IFERROR(INDEX(AnnualModelTable[Ending Cash Balance],MATCH(AnnualModelTable[[#This Row],[Year]]-1,AnnualModelTable[Year],0)),0)+AnnualModelTable[[#This Row],[Cash Before Refi/Sale]]+AnnualModelTable[[#This Row],[Net Refi/Sale Proceeds]])))) -> 0 | K7: =IF(AnnualModelTable[[#This Row],[Year]]>SaleExitYear,0,IF(AnnualModelTable[[#This Row],[Year]]=0,0,IFERROR(INDEX(AnnualModelTable[Reserve Balance],MATCH(AnnualModelTable[[#This Row],[Year]]-1,AnnualModelTable[Year],0)),0)+AnnualModelTable[[#This Row],[Reserve Funding]])) -> 9000 | L7: =IF(AnnualModelTable[[#This Row],[Year]]>SaleExitYear,0,IF(AnnualModelTable[[#This Row],[Year]]=0,0,IFERROR(INDEX(AnnualModelTable[Ending Cash Balance],MATCH(AnnualModelTable[[#This Row],[Year]]-1,AnnualModelTable[Year],0)),0))+AnnualModelTable[[#This Row],[Cash Before Refi/Sale]]+AnnualModelTable[[#This Row],[Net Refi/Sale Proceeds]]-AnnualModelTable[[#This Row],[Reserve Funding]]) -> 568344.61 | M7: =IF(AnnualModelTable[[#This Row],[Year]]>SaleExitYear,0,SUM(INDEX(WaterfallTable[Total Dist A],MATCH(AnnualModelTable[[#This Row],[Year]],WaterfallTable[Year],0)),INDEX(WaterfallTable[Total Dist B],MATCH(AnnualModelTable[[#This Row],[Year]],WaterfallTable[Year],0)),INDEX(WaterfallTable[Total Dist2],MATCH(AnnualModelTable[[#This Row],[Year]],WaterfallTable[Year],0)))) -> 568344.61 | N7: =IF(AnnualModelTable[[#This Row],[Year]]>SaleExitYear,0,MAX(0,AnnualModelTable[[#This Row],[Cash Available Before Distributions]]-AnnualModelTable[[#This Row],[Waterfall Distributions]])) -> 0 | O7: =IF(AnnualModelTable[[#This Row],[Year]]>SaleExitYear,0,IF(AnnualModelTable[[#This Row],[Year]]<StabilizationRefiYear,0,IF(AnnualModelTable[[#This Row],[Year]]=SaleExitYear,0,-FV(RefinanceLoanRate/12,(AnnualModelTable[[#This Row],[Year]]-StabilizationRefiYear)*12,PMT(RefinanceLoanRate/12,RefinanceLoanAmortizationYears*12,RefinanceLoanAmount),RefinanceLoanAmount)))) -> 732276.44 | P7: =IF(AnnualModelTable[[#This Row],[Year]]>SaleExitYear,0,IF(AnnualModelTable[[#This Row],[Year]]<StabilizationRefiYear,0,AnnualModelTable[[#This Row],[NOI]]*(1+NOIGrowth)/ExitCapRate)) -> 1259689.8
A8: 4 | B8: Operations | C8: =IF(AnnualModelTable[[#This Row],[Year]]>SaleExitYear,0,IF(AnnualModelTable[[#This Row],[Year]]=0,0,INDEX(STRScenarioTable[Selected Annual Gross Rent],MATCH(AnnualModelTable[[#This Row],[Year]],STRScenarioTable[Year],0)))) -> 173400 | D8: =IF(AnnualModelTable[[#This Row],[Year]]>SaleExitYear,0,IF(AnnualModelTable[[#This Row],[Year]]=0,0,AnnualModelTable[[#This Row],[Gross Potential Rent]]*IF(AnnualModelTable[[#This Row],[Year]]=1,LeaseUpOccupancy,StabilizedOccupancy))) -> 161262 | E8: =IF(AnnualModelTable[[#This Row],[Year]]>SaleExitYear,0,AnnualModelTable[[#This Row],[Occupancy Effective Gross Income]]*OperatingExpenseRatio) -> 75652.012 | F8: =IF(AnnualModelTable[[#This Row],[Year]]>SaleExitYear,0,AnnualModelTable[[#This Row],[Occupancy Effective Gross Income]]-AnnualModelTable[[#This Row],[Operating Expenses]]) -> 85609.988 | G8: =IF(AnnualModelTable[[#This Row],[Year]]>SaleExitYear,0,IF(AND(AnnualModelTable[[#This Row],[Year]]>=1,AnnualModelTable[[#This Row],[Year]]<StabilizationRefiYear),ExistingDebtServiceAnnual,IF(AND(AnnualModelTable[[#This Row],[Year]]>=StabilizationRefiYear,AnnualModelTable[[#This Row],[Year]]<=SaleExitYear),-PMT(RefinanceLoanRate/12,RefinanceLoanAmortizationYears*12,RefinanceLoanAmount)*12,0))) -> 55541.823 | H8: =IF(AnnualModelTable[[#This Row],[Year]]>SaleExitYear,0,AnnualModelTable[[#This Row],[NOI]]-AnnualModelTable[[#This Row],[Debt Service]]) -> 30068.166 | I8: =IF(AnnualModelTable[[#This Row],[Year]]>SaleExitYear,0,IF(AnnualModelTable[[#This Row],[Year]]=0,SponsorPropertyPayment,IF(AnnualModelTable[[#This Row],[Year]]=StabilizationRefiYear,MAX(0,RefinanceLoanAmount-TotalExistingDebt),IF(AnnualModelTable[[#This Row],[Year]]=SaleExitYear,MAX(0,AnnualModelTable[[#This Row],[Property Value / Refi Value]]*(1-SellingCosts)-AnnualModelTable[[#This Row],[Loan Balance]]),0)))) -> 0 | J8: =IF(AnnualModelTable[[#This Row],[Year]]>SaleExitYear,0,IF(AnnualModelTable[[#This Row],[Year]]=0,0,MIN(MAX(0,RepairsMaintenanceReserveTarget-IFERROR(INDEX(AnnualModelTable[Reserve Balance],MATCH(AnnualModelTable[[#This Row],[Year]]-1,AnnualModelTable[Year],0)),0)),MAX(0,IFERROR(INDEX(AnnualModelTable[Ending Cash Balance],MATCH(AnnualModelTable[[#This Row],[Year]]-1,AnnualModelTable[Year],0)),0)+AnnualModelTable[[#This Row],[Cash Before Refi/Sale]]+AnnualModelTable[[#This Row],[Net Refi/Sale Proceeds]])))) -> 0 | K8: =IF(AnnualModelTable[[#This Row],[Year]]>SaleExitYear,0,IF(AnnualModelTable[[#This Row],[Year]]=0,0,IFERROR(INDEX(AnnualModelTable[Reserve Balance],MATCH(AnnualModelTable[[#This Row],[Year]]-1,AnnualModelTable[Year],0)),0)+AnnualModelTable[[#This Row],[Reserve Funding]])) -> 9000 | L8: =IF(AnnualModelTable[[#This Row],[Year]]>SaleExitYear,0,IF(AnnualModelTable[[#This Row],[Year]]=0,0,IFERROR(INDEX(AnnualModelTable[Ending Cash Balance],MATCH(AnnualModelTable[[#This Row],[Year]]-1,AnnualModelTable[Year],0)),0))+AnnualModelTable[[#This Row],[Cash Before Refi/Sale]]+AnnualModelTable[[#This Row],[Net Refi/Sale Proceeds]]-AnnualModelTable[[#This Row],[Reserve Funding]]) -> 30068.166 | M8: =IF(AnnualModelTable[[#This Row],[Year]]>SaleExitYear,0,SUM(INDEX(WaterfallTable[Total Dist A],MATCH(AnnualModelTable[[#This Row],[Year]],WaterfallTable[Year],0)),INDEX(WaterfallTable[Total Dist B],MATCH(AnnualModelTable[[#This Row],[Year]],WaterfallTable[Year],0)),INDEX(WaterfallTable[Total Dist2],MATCH(AnnualModelTable[[#This Row],[Year]],WaterfallTable[Year],0)))) -> 30068.166 | N8: =IF(AnnualModelTable[[#This Row],[Year]]>SaleExitYear,0,MAX(0,AnnualModelTable[[#This Row],[Cash Available Before Distributions]]-AnnualModelTable[[#This Row],[Waterfall Distributions]])) -> 0 | O8: =IF(AnnualModelTable[[#This Row],[Year]]>SaleExitYear,0,IF(AnnualModelTable[[#This Row],[Year]]<StabilizationRefiYear,0,IF(AnnualModelTable[[#This Row],[Year]]=SaleExitYear,0,-FV(RefinanceLoanRate/12,(AnnualModelTable[[#This Row],[Year]]-StabilizationRefiYear)*12,PMT(RefinanceLoanRate/12,RefinanceLoanAmortizationYears*12,RefinanceLoanAmount),RefinanceLoanAmount)))) -> 724091.6 | P8: =IF(AnnualModelTable[[#This Row],[Year]]>SaleExitYear,0,IF(AnnualModelTable[[#This Row],[Year]]<StabilizationRefiYear,0,AnnualModelTable[[#This Row],[NOI]]*(1+NOIGrowth)/ExitCapRate)) -> 1259689.8
A9: 5 | B9: Operations | C9: =IF(AnnualModelTable[[#This Row],[Year]]>SaleExitYear,0,IF(AnnualModelTable[[#This Row],[Year]]=0,0,INDEX(STRScenarioTable[Selected Annual Gross Rent],MATCH(AnnualModelTable[[#This Row],[Year]],STRScenarioTable[Year],0)))) -> 173400 | D9: =IF(AnnualModelTable[[#This Row],[Year]]>SaleExitYear,0,IF(AnnualModelTable[[#This Row],[Year]]=0,0,AnnualModelTable[[#This Row],[Gross Potential Rent]]*IF(AnnualModelTable[[#This Row],[Year]]=1,LeaseUpOccupancy,StabilizedOccupancy))) -> 161262 | E9: =IF(AnnualModelTable[[#This Row],[Year]]>SaleExitYear,0,AnnualModelTable[[#This Row],[Occupancy Effective Gross Income]]*OperatingExpenseRatio) -> 75652.012 | F9: =IF(AnnualModelTable[[#This Row],[Year]]>SaleExitYear,0,AnnualModelTable[[#This Row],[Occupancy Effective Gross Income]]-AnnualModelTable[[#This Row],[Operating Expenses]]) -> 85609.988 | G9: =IF(AnnualModelTable[[#This Row],[Year]]>SaleExitYear,0,IF(AND(AnnualModelTable[[#This Row],[Year]]>=1,AnnualModelTable[[#This Row],[Year]]<StabilizationRefiYear),ExistingDebtServiceAnnual,IF(AND(AnnualModelTable[[#This Row],[Year]]>=StabilizationRefiYear,AnnualModelTable[[#This Row],[Year]]<=SaleExitYear),-PMT(RefinanceLoanRate/12,RefinanceLoanAmortizationYears*12,RefinanceLoanAmount)*12,0))) -> 55541.823 | H9: =IF(AnnualModelTable[[#This Row],[Year]]>SaleExitYear,0,AnnualModelTable[[#This Row],[NOI]]-AnnualModelTable[[#This Row],[Debt Service]]) -> 30068.166 | I9: =IF(AnnualModelTable[[#This Row],[Year]]>SaleExitYear,0,IF(AnnualModelTable[[#This Row],[Year]]=0,SponsorPropertyPayment,IF(AnnualModelTable[[#This Row],[Year]]=StabilizationRefiYear,MAX(0,RefinanceLoanAmount-TotalExistingDebt),IF(AnnualModelTable[[#This Row],[Year]]=SaleExitYear,MAX(0,AnnualModelTable[[#This Row],[Property Value / Refi Value]]*(1-SellingCosts)-AnnualModelTable[[#This Row],[Loan Balance]]),0)))) -> 1234496 | J9: =IF(AnnualModelTable[[#This Row],[Year]]>SaleExitYear,0,IF(AnnualModelTable[[#This Row],[Year]]=0,0,MIN(MAX(0,RepairsMaintenanceReserveTarget-IFERROR(INDEX(AnnualModelTable[Reserve Balance],MATCH(AnnualModelTable[[#This Row],[Year]]-1,AnnualModelTable[Year],0)),0)),MAX(0,IFERROR(INDEX(AnnualModelTable[Ending Cash Balance],MATCH(AnnualModelTable[[#This Row],[Year]]-1,AnnualModelTable[Year],0)),0)+AnnualModelTable[[#This Row],[Cash Before Refi/Sale]]+AnnualModelTable[[#This Row],[Net Refi/Sale Proceeds]])))) -> 0 | K9: =IF(AnnualModelTable[[#This Row],[Year]]>SaleExitYear,0,IF(AnnualModelTable[[#This Row],[Year]]=0,0,IFERROR(INDEX(AnnualModelTable[Reserve Balance],MATCH(AnnualModelTable[[#This Row],[Year]]-1,AnnualModelTable[Year],0)),0)+AnnualModelTable[[#This Row],[Reserve Funding]])) -> 9000 | L9: =IF(AnnualModelTable[[#This Row],[Year]]>SaleExitYear,0,IF(AnnualModelTable[[#This Row],[Year]]=0,0,IFERROR(INDEX(AnnualModelTable[Ending Cash Balance],MATCH(AnnualModelTable[[#This Row],[Year]]-1,AnnualModelTable[Year],0)),0))+AnnualModelTable[[#This Row],[Cash Before Refi/Sale]]+AnnualModelTable[[#This Row],[Net Refi/Sale Proceeds]]-AnnualModelTable[[#This Row],[Reserve Funding]]) -> 1264564.2 | M9: =IF(AnnualModelTable[[#This Row],[Year]]>SaleExitYear,0,SUM(INDEX(WaterfallTable[Total Dist A],MATCH(AnnualModelTable[[#This Row],[Year]],WaterfallTable[Year],0)),INDEX(WaterfallTable[Total Dist B],MATCH(AnnualModelTable[[#This Row],[Year]],WaterfallTable[Year],0)),INDEX(WaterfallTable[Total Dist2],MATCH(AnnualModelTable[[#This Row],[Year]],WaterfallTable[Year],0)))) -> 1264564.2 | N9: =IF(AnnualModelTable[[#This Row],[Year]]>SaleExitYear,0,MAX(0,AnnualModelTable[[#This Row],[Cash Available Before Distributions]]-AnnualModelTable[[#This Row],[Waterfall Distributions]])) -> 0 | O9: =IF(AnnualModelTable[[#This Row],[Year]]>SaleExitYear,0,IF(AnnualModelTable[[#This Row],[Year]]<StabilizationRefiYear,0,IF(AnnualModelTable[[#This Row],[Year]]=SaleExitYear,0,-FV(RefinanceLoanRate/12,(AnnualModelTable[[#This Row],[Year]]-StabilizationRefiYear)*12,PMT(RefinanceLoanRate/12,RefinanceLoanAmortizationYears*12,RefinanceLoanAmount),RefinanceLoanAmount)))) -> 0 | P9: =IF(AnnualModelTable[[#This Row],[Year]]>SaleExitYear,0,IF(AnnualModelTable[[#This Row],[Year]]<StabilizationRefiYear,0,AnnualModelTable[[#This Row],[NOI]]*(1+NOIGrowth)/ExitCapRate)) -> 1259689.8
A10: 6 | B10: Operations | C10: =IF(AnnualModelTable[[#This Row],[Year]]>SaleExitYear,0,IF(AnnualModelTable[[#This Row],[Year]]=0,0,INDEX(STRScenarioTable[Selected Annual Gross Rent],MATCH(AnnualModelTable[[#This Row],[Year]],STRScenarioTable[Year],0)))) -> 0 | D10: =IF(AnnualModelTable[[#This Row],[Year]]>SaleExitYear,0,IF(AnnualModelTable[[#This Row],[Year]]=0,0,AnnualModelTable[[#This Row],[Gross Potential Rent]]*IF(AnnualModelTable[[#This Row],[Year]]=1,LeaseUpOccupancy,StabilizedOccupancy))) -> 0 | E10: =IF(AnnualModelTable[[#This Row],[Year]]>SaleExitYear,0,AnnualModelTable[[#This Row],[Occupancy Effective Gross Income]]*OperatingExpenseRatio) -> 0 | F10: =IF(AnnualModelTable[[#This Row],[Year]]>SaleExitYear,0,AnnualModelTable[[#This Row],[Occupancy Effective Gross Income]]-AnnualModelTable[[#This Row],[Operating Expenses]]) -> 0 | G10: =IF(AnnualModelTable[[#This Row],[Year]]>SaleExitYear,0,IF(AND(AnnualModelTable[[#This Row],[Year]]>=1,AnnualModelTable[[#This Row],[Year]]<StabilizationRefiYear),ExistingDebtServiceAnnual,IF(AND(AnnualModelTable[[#This Row],[Year]]>=StabilizationRefiYear,AnnualModelTable[[#This Row],[Year]]<=SaleExitYear),-PMT(RefinanceLoanRate/12,RefinanceLoanAmortizationYears*12,RefinanceLoanAmount)*12,0))) -> 0 | H10: =IF(AnnualModelTable[[#This Row],[Year]]>SaleExitYear,0,AnnualModelTable[[#This Row],[NOI]]-AnnualModelTable[[#This Row],[Debt Service]]) -> 0 | I10: =IF(AnnualModelTable[[#This Row],[Year]]>SaleExitYear,0,IF(AnnualModelTable[[#This Row],[Year]]=0,SponsorPropertyPayment,IF(AnnualModelTable[[#This Row],[Year]]=StabilizationRefiYear,MAX(0,RefinanceLoanAmount-TotalExistingDebt),IF(AnnualModelTable[[#This Row],[Year]]=SaleExitYear,MAX(0,AnnualModelTable[[#This Row],[Property Value / Refi Value]]*(1-SellingCosts)-AnnualModelTable[[#This Row],[Loan Balance]]),0)))) -> 0 | J10: =IF(AnnualModelTable[[#This Row],[Year]]>SaleExitYear,0,IF(AnnualModelTable[[#This Row],[Year]]=0,0,MIN(MAX(0,RepairsMaintenanceReserveTarget-IFERROR(INDEX(AnnualModelTable[Reserve Balance],MATCH(AnnualModelTable[[#This Row],[Year]]-1,AnnualModelTable[Year],0)),0)),MAX(0,IFERROR(INDEX(AnnualModelTable[Ending Cash Balance],MATCH(AnnualModelTable[[#This Row],[Year]]-1,AnnualModelTable[Year],0)),0)+AnnualModelTable[[#This Row],[Cash Before Refi/Sale]]+AnnualModelTable[[#This Row],[Net Refi/Sale Proceeds]])))) -> 0 | K10: =IF(AnnualModelTable[[#This Row],[Year]]>SaleExitYear,0,IF(AnnualModelTable[[#This Row],[Year]]=0,0,IFERROR(INDEX(AnnualModelTable[Reserve Balance],MATCH(AnnualModelTable[[#This Row],[Year]]-1,AnnualModelTable[Year],0)),0)+AnnualModelTable[[#This Row],[Reserve Funding]])) -> 0 | L10: =IF(AnnualModelTable[[#This Row],[Year]]>SaleExitYear,0,IF(AnnualModelTable[[#This Row],[Year]]=0,0,IFERROR(INDEX(AnnualModelTable[Ending Cash Balance],MATCH(AnnualModelTable[[#This Row],[Year]]-1,AnnualModelTable[Year],0)),0))+AnnualModelTable[[#This Row],[Cash Before Refi/Sale]]+AnnualModelTable[[#This Row],[Net Refi/Sale Proceeds]]-AnnualModelTable[[#This Row],[Reserve Funding]]) -> 0 | M10: =IF(AnnualModelTable[[#This Row],[Year]]>SaleExitYear,0,SUM(INDEX(WaterfallTable[Total Dist A],MATCH(AnnualModelTable[[#This Row],[Year]],WaterfallTable[Year],0)),INDEX(WaterfallTable[Total Dist B],MATCH(AnnualModelTable[[#This Row],[Year]],WaterfallTable[Year],0)),INDEX(WaterfallTable[Total Dist2],MATCH(AnnualModelTable[[#This Row],[Year]],WaterfallTable[Year],0)))) -> 0 | N10: =IF(AnnualModelTable[[#This Row],[Year]]>SaleExitYear,0,MAX(0,AnnualModelTable[[#This Row],[Cash Available Before Distributions]]-AnnualModelTable[[#This Row],[Waterfall Distributions]])) -> 0 | O10: =IF(AnnualModelTable[[#This Row],[Year]]>SaleExitYear,0,IF(AnnualModelTable[[#This Row],[Year]]<StabilizationRefiYear,0,IF(AnnualModelTable[[#This Row],[Year]]=SaleExitYear,0,-FV(RefinanceLoanRate/12,(AnnualModelTable[[#This Row],[Year]]-StabilizationRefiYear)*12,PMT(RefinanceLoanRate/12,RefinanceLoanAmortizationYears*12,RefinanceLoanAmount),RefinanceLoanAmount)))) -> 0 | P10: =IF(AnnualModelTable[[#This Row],[Year]]>SaleExitYear,0,IF(AnnualModelTable[[#This Row],[Year]]<StabilizationRefiYear,0,AnnualModelTable[[#This Row],[NOI]]*(1+NOIGrowth)/ExitCapRate)) -> 0
A11: 7 | B11: Operations | C11: =IF(AnnualModelTable[[#This Row],[Year]]>SaleExitYear,0,IF(AnnualModelTable[[#This Row],[Year]]=0,0,INDEX(STRScenarioTable[Selected Annual Gross Rent],MATCH(AnnualModelTable[[#This Row],[Year]],STRScenarioTable[Year],0)))) -> 0 | D11: =IF(AnnualModelTable[[#This Row],[Year]]>SaleExitYear,0,IF(AnnualModelTable[[#This Row],[Year]]=0,0,AnnualModelTable[[#This Row],[Gross Potential Rent]]*IF(AnnualModelTable[[#This Row],[Year]]=1,LeaseUpOccupancy,StabilizedOccupancy))) -> 0 | E11: =IF(AnnualModelTable[[#This Row],[Year]]>SaleExitYear,0,AnnualModelTable[[#This Row],[Occupancy Effective Gross Income]]*OperatingExpenseRatio) -> 0 | F11: =IF(AnnualModelTable[[#This Row],[Year]]>SaleExitYear,0,AnnualModelTable[[#This Row],[Occupancy Effective Gross Income]]-AnnualModelTable[[#This Row],[Operating Expenses]]) -> 0 | G11: =IF(AnnualModelTable[[#This Row],[Year]]>SaleExitYear,0,IF(AND(AnnualModelTable[[#This Row],[Year]]>=1,AnnualModelTable[[#This Row],[Year]]<StabilizationRefiYear),ExistingDebtServiceAnnual,IF(AND(AnnualModelTable[[#This Row],[Year]]>=StabilizationRefiYear,AnnualModelTable[[#This Row],[Year]]<=SaleExitYear),-PMT(RefinanceLoanRate/12,RefinanceLoanAmortizationYears*12,RefinanceLoanAmount)*12,0))) -> 0 | H11: =IF(AnnualModelTable[[#This Row],[Year]]>SaleExitYear,0,AnnualModelTable[[#This Row],[NOI]]-AnnualModelTable[[#This Row],[Debt Service]]) -> 0 | I11: =IF(AnnualModelTable[[#This Row],[Year]]>SaleExitYear,0,IF(AnnualModelTable[[#This Row],[Year]]=0,SponsorPropertyPayment,IF(AnnualModelTable[[#This Row],[Year]]=StabilizationRefiYear,MAX(0,RefinanceLoanAmount-TotalExistingDebt),IF(AnnualModelTable[[#This Row],[Year]]=SaleExitYear,MAX(0,AnnualModelTable[[#This Row],[Property Value / Refi Value]]*(1-SellingCosts)-AnnualModelTable[[#This Row],[Loan Balance]]),0)))) -> 0 | J11: =IF(AnnualModelTable[[#This Row],[Year]]>SaleExitYear,0,IF(AnnualModelTable[[#This Row],[Year]]=0,0,MIN(MAX(0,RepairsMaintenanceReserveTarget-IFERROR(INDEX(AnnualModelTable[Reserve Balance],MATCH(AnnualModelTable[[#This Row],[Year]]-1,AnnualModelTable[Year],0)),0)),MAX(0,IFERROR(INDEX(AnnualModelTable[Ending Cash Balance],MATCH(AnnualModelTable[[#This Row],[Year]]-1,AnnualModelTable[Year],0)),0)+AnnualModelTable[[#This Row],[Cash Before Refi/Sale]]+AnnualModelTable[[#This Row],[Net Refi/Sale Proceeds]])))) -> 0 | K11: =IF(AnnualModelTable[[#This Row],[Year]]>SaleExitYear,0,IF(AnnualModelTable[[#This Row],[Year]]=0,0,IFERROR(INDEX(AnnualModelTable[Reserve Balance],MATCH(AnnualModelTable[[#This Row],[Year]]-1,AnnualModelTable[Year],0)),0)+AnnualModelTable[[#This Row],[Reserve Funding]])) -> 0 | L11: =IF(AnnualModelTable[[#This Row],[Year]]>SaleExitYear,0,IF(AnnualModelTable[[#This Row],[Year]]=0,0,IFERROR(INDEX(AnnualModelTable[Ending Cash Balance],MATCH(AnnualModelTable[[#This Row],[Year]]-1,AnnualModelTable[Year],0)),0))+AnnualModelTable[[#This Row],[Cash Before Refi/Sale]]+AnnualModelTable[[#This Row],[Net Refi/Sale Proceeds]]-AnnualModelTable[[#This Row],[Reserve Funding]]) -> 0 | M11: =IF(AnnualModelTable[[#This Row],[Year]]>SaleExitYear,0,SUM(INDEX(WaterfallTable[Total Dist A],MATCH(AnnualModelTable[[#This Row],[Year]],WaterfallTable[Year],0)),INDEX(WaterfallTable[Total Dist B],MATCH(AnnualModelTable[[#This Row],[Year]],WaterfallTable[Year],0)),INDEX(WaterfallTable[Total Dist2],MATCH(AnnualModelTable[[#This Row],[Year]],WaterfallTable[Year],0)))) -> 0 | N11: =IF(AnnualModelTable[[#This Row],[Year]]>SaleExitYear,0,MAX(0,AnnualModelTable[[#This Row],[Cash Available Before Distributions]]-AnnualModelTable[[#This Row],[Waterfall Distributions]])) -> 0 | O11: =IF(AnnualModelTable[[#This Row],[Year]]>SaleExitYear,0,IF(AnnualModelTable[[#This Row],[Year]]<StabilizationRefiYear,0,IF(AnnualModelTable[[#This Row],[Year]]=SaleExitYear,0,-FV(RefinanceLoanRate/12,(AnnualModelTable[[#This Row],[Year]]-StabilizationRefiYear)*12,PMT(RefinanceLoanRate/12,RefinanceLoanAmortizationYears*12,RefinanceLoanAmount),RefinanceLoanAmount)))) -> 0 | P11: =IF(AnnualModelTable[[#This Row],[Year]]>SaleExitYear,0,IF(AnnualModelTable[[#This Row],[Year]]<StabilizationRefiYear,0,AnnualModelTable[[#This Row],[NOI]]*(1+NOIGrowth)/ExitCapRate)) -> 0
A12: 8 | B12: Operations | C12: =IF(AnnualModelTable[[#This Row],[Year]]>SaleExitYear,0,IF(AnnualModelTable[[#This Row],[Year]]=0,0,INDEX(STRScenarioTable[Selected Annual Gross Rent],MATCH(AnnualModelTable[[#This Row],[Year]],STRScenarioTable[Year],0)))) -> 0 | D12: =IF(AnnualModelTable[[#This Row],[Year]]>SaleExitYear,0,IF(AnnualModelTable[[#This Row],[Year]]=0,0,AnnualModelTable[[#This Row],[Gross Potential Rent]]*IF(AnnualModelTable[[#This Row],[Year]]=1,LeaseUpOccupancy,StabilizedOccupancy))) -> 0 | E12: =IF(AnnualModelTable[[#This Row],[Year]]>SaleExitYear,0,AnnualModelTable[[#This Row],[Occupancy Effective Gross Income]]*OperatingExpenseRatio) -> 0 | F12: =IF(AnnualModelTable[[#This Row],[Year]]>SaleExitYear,0,AnnualModelTable[[#This Row],[Occupancy Effective Gross Income]]-AnnualModelTable[[#This Row],[Operating Expenses]]) -> 0 | G12: =IF(AnnualModelTable[[#This Row],[Year]]>SaleExitYear,0,IF(AND(AnnualModelTable[[#This Row],[Year]]>=1,AnnualModelTable[[#This Row],[Year]]<StabilizationRefiYear),ExistingDebtServiceAnnual,IF(AND(AnnualModelTable[[#This Row],[Year]]>=StabilizationRefiYear,AnnualModelTable[[#This Row],[Year]]<=SaleExitYear),-PMT(RefinanceLoanRate/12,RefinanceLoanAmortizationYears*12,RefinanceLoanAmount)*12,0))) -> 0 | H12: =IF(AnnualModelTable[[#This Row],[Year]]>SaleExitYear,0,AnnualModelTable[[#This Row],[NOI]]-AnnualModelTable[[#This Row],[Debt Service]]) -> 0 | I12: =IF(AnnualModelTable[[#This Row],[Year]]>SaleExitYear,0,IF(AnnualModelTable[[#This Row],[Year]]=0,SponsorPropertyPayment,IF(AnnualModelTable[[#This Row],[Year]]=StabilizationRefiYear,MAX(0,RefinanceLoanAmount-TotalExistingDebt),IF(AnnualModelTable[[#This Row],[Year]]=SaleExitYear,MAX(0,AnnualModelTable[[#This Row],[Property Value / Refi Value]]*(1-SellingCosts)-AnnualModelTable[[#This Row],[Loan Balance]]),0)))) -> 0 | J12: =IF(AnnualModelTable[[#This Row],[Year]]>SaleExitYear,0,IF(AnnualModelTable[[#This Row],[Year]]=0,0,MIN(MAX(0,RepairsMaintenanceReserveTarget-IFERROR(INDEX(AnnualModelTable[Reserve Balance],MATCH(AnnualModelTable[[#This Row],[Year]]-1,AnnualModelTable[Year],0)),0)),MAX(0,IFERROR(INDEX(AnnualModelTable[Ending Cash Balance],MATCH(AnnualModelTable[[#This Row],[Year]]-1,AnnualModelTable[Year],0)),0)+AnnualModelTable[[#This Row],[Cash Before Refi/Sale]]+AnnualModelTable[[#This Row],[Net Refi/Sale Proceeds]])))) -> 0 | K12: =IF(AnnualModelTable[[#This Row],[Year]]>SaleExitYear,0,IF(AnnualModelTable[[#This Row],[Year]]=0,0,IFERROR(INDEX(AnnualModelTable[Reserve Balance],MATCH(AnnualModelTable[[#This Row],[Year]]-1,AnnualModelTable[Year],0)),0)+AnnualModelTable[[#This Row],[Reserve Funding]])) -> 0 | L12: =IF(AnnualModelTable[[#This Row],[Year]]>SaleExitYear,0,IF(AnnualModelTable[[#This Row],[Year]]=0,0,IFERROR(INDEX(AnnualModelTable[Ending Cash Balance],MATCH(AnnualModelTable[[#This Row],[Year]]-1,AnnualModelTable[Year],0)),0))+AnnualModelTable[[#This Row],[Cash Before Refi/Sale]]+AnnualModelTable[[#This Row],[Net Refi/Sale Proceeds]]-AnnualModelTable[[#This Row],[Reserve Funding]]) -> 0 | M12: =IF(AnnualModelTable[[#This Row],[Year]]>SaleExitYear,0,SUM(INDEX(WaterfallTable[Total Dist A],MATCH(AnnualModelTable[[#This Row],[Year]],WaterfallTable[Year],0)),INDEX(WaterfallTable[Total Dist B],MATCH(AnnualModelTable[[#This Row],[Year]],WaterfallTable[Year],0)),INDEX(WaterfallTable[Total Dist2],MATCH(AnnualModelTable[[#This Row],[Year]],WaterfallTable[Year],0)))) -> 0 | N12: =IF(AnnualModelTable[[#This Row],[Year]]>SaleExitYear,0,MAX(0,AnnualModelTable[[#This Row],[Cash Available Before Distributions]]-AnnualModelTable[[#This Row],[Waterfall Distributions]])) -> 0 | O12: =IF(AnnualModelTable[[#This Row],[Year]]>SaleExitYear,0,IF(AnnualModelTable[[#This Row],[Year]]<StabilizationRefiYear,0,IF(AnnualModelTable[[#This Row],[Year]]=SaleExitYear,0,-FV(RefinanceLoanRate/12,(AnnualModelTable[[#This Row],[Year]]-StabilizationRefiYear)*12,PMT(RefinanceLoanRate/12,RefinanceLoanAmortizationYears*12,RefinanceLoanAmount),RefinanceLoanAmount)))) -> 0 | P12: =IF(AnnualModelTable[[#This Row],[Year]]>SaleExitYear,0,IF(AnnualModelTable[[#This Row],[Year]]<StabilizationRefiYear,0,AnnualModelTable[[#This Row],[NOI]]*(1+NOIGrowth)/ExitCapRate)) -> 0
A13: 9 | B13: Operations | C13: =IF(AnnualModelTable[[#This Row],[Year]]>SaleExitYear,0,IF(AnnualModelTable[[#This Row],[Year]]=0,0,INDEX(STRScenarioTable[Selected Annual Gross Rent],MATCH(AnnualModelTable[[#This Row],[Year]],STRScenarioTable[Year],0)))) -> 0 | D13: =IF(AnnualModelTable[[#This Row],[Year]]>SaleExitYear,0,IF(AnnualModelTable[[#This Row],[Year]]=0,0,AnnualModelTable[[#This Row],[Gross Potential Rent]]*IF(AnnualModelTable[[#This Row],[Year]]=1,LeaseUpOccupancy,StabilizedOccupancy))) -> 0 | E13: =IF(AnnualModelTable[[#This Row],[Year]]>SaleExitYear,0,AnnualModelTable[[#This Row],[Occupancy Effective Gross Income]]*OperatingExpenseRatio) -> 0 | F13: =IF(AnnualModelTable[[#This Row],[Year]]>SaleExitYear,0,AnnualModelTable[[#This Row],[Occupancy Effective Gross Income]]-AnnualModelTable[[#This Row],[Operating Expenses]]) -> 0 | G13: =IF(AnnualModelTable[[#This Row],[Year]]>SaleExitYear,0,IF(AND(AnnualModelTable[[#This Row],[Year]]>=1,AnnualModelTable[[#This Row],[Year]]<StabilizationRefiYear),ExistingDebtServiceAnnual,IF(AND(AnnualModelTable[[#This Row],[Year]]>=StabilizationRefiYear,AnnualModelTable[[#This Row],[Year]]<=SaleExitYear),-PMT(RefinanceLoanRate/12,RefinanceLoanAmortizationYears*12,RefinanceLoanAmount)*12,0))) -> 0 | H13: =IF(AnnualModelTable[[#This Row],[Year]]>SaleExitYear,0,AnnualModelTable[[#This Row],[NOI]]-AnnualModelTable[[#This Row],[Debt Service]]) -> 0 | I13: =IF(AnnualModelTable[[#This Row],[Year]]>SaleExitYear,0,IF(AnnualModelTable[[#This Row],[Year]]=0,SponsorPropertyPayment,IF(AnnualModelTable[[#This Row],[Year]]=StabilizationRefiYear,MAX(0,RefinanceLoanAmount-TotalExistingDebt),IF(AnnualModelTable[[#This Row],[Year]]=SaleExitYear,MAX(0,AnnualModelTable[[#This Row],[Property Value / Refi Value]]*(1-SellingCosts)-AnnualModelTable[[#This Row],[Loan Balance]]),0)))) -> 0 | J13: =IF(AnnualModelTable[[#This Row],[Year]]>SaleExitYear,0,IF(AnnualModelTable[[#This Row],[Year]]=0,0,MIN(MAX(0,RepairsMaintenanceReserveTarget-IFERROR(INDEX(AnnualModelTable[Reserve Balance],MATCH(AnnualModelTable[[#This Row],[Year]]-1,AnnualModelTable[Year],0)),0)),MAX(0,IFERROR(INDEX(AnnualModelTable[Ending Cash Balance],MATCH(AnnualModelTable[[#This Row],[Year]]-1,AnnualModelTable[Year],0)),0)+AnnualModelTable[[#This Row],[Cash Before Refi/Sale]]+AnnualModelTable[[#This Row],[Net Refi/Sale Proceeds]])))) -> 0 | K13: =IF(AnnualModelTable[[#This Row],[Year]]>SaleExitYear,0,IF(AnnualModelTable[[#This Row],[Year]]=0,0,IFERROR(INDEX(AnnualModelTable[Reserve Balance],MATCH(AnnualModelTable[[#This Row],[Year]]-1,AnnualModelTable[Year],0)),0)+AnnualModelTable[[#This Row],[Reserve Funding]])) -> 0 | L13: =IF(AnnualModelTable[[#This Row],[Year]]>SaleExitYear,0,IF(AnnualModelTable[[#This Row],[Year]]=0,0,IFERROR(INDEX(AnnualModelTable[Ending Cash Balance],MATCH(AnnualModelTable[[#This Row],[Year]]-1,AnnualModelTable[Year],0)),0))+AnnualModelTable[[#This Row],[Cash Before Refi/Sale]]+AnnualModelTable[[#This Row],[Net Refi/Sale Proceeds]]-AnnualModelTable[[#This Row],[Reserve Funding]]) -> 0 | M13: =IF(AnnualModelTable[[#This Row],[Year]]>SaleExitYear,0,SUM(INDEX(WaterfallTable[Total Dist A],MATCH(AnnualModelTable[[#This Row],[Year]],WaterfallTable[Year],0)),INDEX(WaterfallTable[Total Dist B],MATCH(AnnualModelTable[[#This Row],[Year]],WaterfallTable[Year],0)),INDEX(WaterfallTable[Total Dist2],MATCH(AnnualModelTable[[#This Row],[Year]],WaterfallTable[Year],0)))) -> 0 | N13: =IF(AnnualModelTable[[#This Row],[Year]]>SaleExitYear,0,MAX(0,AnnualModelTable[[#This Row],[Cash Available Before Distributions]]-AnnualModelTable[[#This Row],[Waterfall Distributions]])) -> 0 | O13: =IF(AnnualModelTable[[#This Row],[Year]]>SaleExitYear,0,IF(AnnualModelTable[[#This Row],[Year]]<StabilizationRefiYear,0,IF(AnnualModelTable[[#This Row],[Year]]=SaleExitYear,0,-FV(RefinanceLoanRate/12,(AnnualModelTable[[#This Row],[Year]]-StabilizationRefiYear)*12,PMT(RefinanceLoanRate/12,RefinanceLoanAmortizationYears*12,RefinanceLoanAmount),RefinanceLoanAmount)))) -> 0 | P13: =IF(AnnualModelTable[[#This Row],[Year]]>SaleExitYear,0,IF(AnnualModelTable[[#This Row],[Year]]<StabilizationRefiYear,0,AnnualModelTable[[#This Row],[NOI]]*(1+NOIGrowth)/ExitCapRate)) -> 0
A14: 10 | B14: Exit | C14: =IF(AnnualModelTable[[#This Row],[Year]]>SaleExitYear,0,IF(AnnualModelTable[[#This Row],[Year]]=0,0,INDEX(STRScenarioTable[Selected Annual Gross Rent],MATCH(AnnualModelTable[[#This Row],[Year]],STRScenarioTable[Year],0)))) -> 0 | D14: =IF(AnnualModelTable[[#This Row],[Year]]>SaleExitYear,0,IF(AnnualModelTable[[#This Row],[Year]]=0,0,AnnualModelTable[[#This Row],[Gross Potential Rent]]*IF(AnnualModelTable[[#This Row],[Year]]=1,LeaseUpOccupancy,StabilizedOccupancy))) -> 0 | E14: =IF(AnnualModelTable[[#This Row],[Year]]>SaleExitYear,0,AnnualModelTable[[#This Row],[Occupancy Effective Gross Income]]*OperatingExpenseRatio) -> 0 | F14: =IF(AnnualModelTable[[#This Row],[Year]]>SaleExitYear,0,AnnualModelTable[[#This Row],[Occupancy Effective Gross Income]]-AnnualModelTable[[#This Row],[Operating Expenses]]) -> 0 | G14: =IF(AnnualModelTable[[#This Row],[Year]]>SaleExitYear,0,IF(AND(AnnualModelTable[[#This Row],[Year]]>=1,AnnualModelTable[[#This Row],[Year]]<StabilizationRefiYear),ExistingDebtServiceAnnual,IF(AND(AnnualModelTable[[#This Row],[Year]]>=StabilizationRefiYear,AnnualModelTable[[#This Row],[Year]]<=SaleExitYear),-PMT(RefinanceLoanRate/12,RefinanceLoanAmortizationYears*12,RefinanceLoanAmount)*12,0))) -> 0 | H14: =IF(AnnualModelTable[[#This Row],[Year]]>SaleExitYear,0,AnnualModelTable[[#This Row],[NOI]]-AnnualModelTable[[#This Row],[Debt Service]]) -> 0 | I14: =IF(AnnualModelTable[[#This Row],[Year]]>SaleExitYear,0,IF(AnnualModelTable[[#This Row],[Year]]=0,SponsorPropertyPayment,IF(AnnualModelTable[[#This Row],[Year]]=StabilizationRefiYear,MAX(0,RefinanceLoanAmount-TotalExistingDebt),IF(AnnualModelTable[[#This Row],[Year]]=SaleExitYear,MAX(0,AnnualModelTable[[#This Row],[Property Value / Refi Value]]*(1-SellingCosts)-AnnualModelTable[[#This Row],[Loan Balance]]),0)))) -> 0 | J14: =IF(AnnualModelTable[[#This Row],[Year]]>SaleExitYear,0,IF(AnnualModelTable[[#This Row],[Year]]=0,0,MIN(MAX(0,RepairsMaintenanceReserveTarget-IFERROR(INDEX(AnnualModelTable[Reserve Balance],MATCH(AnnualModelTable[[#This Row],[Year]]-1,AnnualModelTable[Year],0)),0)),MAX(0,IFERROR(INDEX(AnnualModelTable[Ending Cash Balance],MATCH(AnnualModelTable[[#This Row],[Year]]-1,AnnualModelTable[Year],0)),0)+AnnualModelTable[[#This Row],[Cash Before Refi/Sale]]+AnnualModelTable[[#This Row],[Net Refi/Sale Proceeds]])))) -> 0 | K14: =IF(AnnualModelTable[[#This Row],[Year]]>SaleExitYear,0,IF(AnnualModelTable[[#This Row],[Year]]=0,0,IFERROR(INDEX(AnnualModelTable[Reserve Balance],MATCH(AnnualModelTable[[#This Row],[Year]]-1,AnnualModelTable[Year],0)),0)+AnnualModelTable[[#This Row],[Reserve Funding]])) -> 0 | L14: =IF(AnnualModelTable[[#This Row],[Year]]>SaleExitYear,0,IF(AnnualModelTable[[#This Row],[Year]]=0,0,IFERROR(INDEX(AnnualModelTable[Ending Cash Balance],MATCH(AnnualModelTable[[#This Row],[Year]]-1,AnnualModelTable[Year],0)),0))+AnnualModelTable[[#This Row],[Cash Before Refi/Sale]]+AnnualModelTable[[#This Row],[Net Refi/Sale Proceeds]]-AnnualModelTable[[#This Row],[Reserve Funding]]) -> 0 | M14: =IF(AnnualModelTable[[#This Row],[Year]]>SaleExitYear,0,SUM(INDEX(WaterfallTable[Total Dist A],MATCH(AnnualModelTable[[#This Row],[Year]],WaterfallTable[Year],0)),INDEX(WaterfallTable[Total Dist B],MATCH(AnnualModelTable[[#This Row],[Year]],WaterfallTable[Year],0)),INDEX(WaterfallTable[Total Dist2],MATCH(AnnualModelTable[[#This Row],[Year]],WaterfallTable[Year],0)))) -> 0 | N14: =IF(AnnualModelTable[[#This Row],[Year]]>SaleExitYear,0,MAX(0,AnnualModelTable[[#This Row],[Cash Available Before Distributions]]-AnnualModelTable[[#This Row],[Waterfall Distributions]])) -> 0 | O14: =IF(AnnualModelTable[[#This Row],[Year]]>SaleExitYear,0,IF(AnnualModelTable[[#This Row],[Year]]<StabilizationRefiYear,0,IF(AnnualModelTable[[#This Row],[Year]]=SaleExitYear,0,-FV(RefinanceLoanRate/12,(AnnualModelTable[[#This Row],[Year]]-StabilizationRefiYear)*12,PMT(RefinanceLoanRate/12,RefinanceLoanAmortizationYears*12,RefinanceLoanAmount),RefinanceLoanAmount)))) -> 0 | P14: =IF(AnnualModelTable[[#This Row],[Year]]>SaleExitYear,0,IF(AnnualModelTable[[#This Row],[Year]]<StabilizationRefiYear,0,AnnualModelTable[[#This Row],[NOI]]*(1+NOIGrowth)/ExitCapRate)) -> 0

Sheet Waterfall
B2: Annual Waterfall | D2: Class A | K2: Class B | O2: Sponsor | S2: Refi Year | T2: Exit Year
B3: Year | C3: Cash Available | D3: Pref Accrued | E3: Pref Paid | F3: End of Year Pref Balance | G3: Capital Balance A | H3: Capital Returned A | I3: Residual A | J3: Total Dist A | K3: Capital Balance B | L3: Capital Returned B | M3: Residual B | N3: Total Dist B | O3: Property Payment | P3: Residual | Q3: Total Dist2 | S3: 3 | T3: 5
B4: 0 | C4: =IF(WaterfallTable[[#This Row],[Year]]>SaleExitYear,0,INDEX(AnnualModelTable[Cash Available Before Distributions],MATCH(WaterfallTable[[#This Row],[Year]],AnnualModelTable[Year],0))) -> 100000 | D4: =IF(WaterfallTable[[#This Row],[Year]]>SaleExitYear,0,WaterfallTable[[#This Row],[Capital Balance A]]*ClassAPreferredReturn) -> 24000 | E4: =IF(WaterfallTable[[#This Row],[Year]]>SaleExitYear,0,IF(WaterfallTable[[#This Row],[Year]]=0,0,MIN(MAX(0,WaterfallTable[[#This Row],[Cash Available]]-WaterfallTable[[#This Row],[Capital Returned A]]-WaterfallTable[[#This Row],[Capital Returned B]]),INDEX(WaterfallTable[End of Year Pref Balance],MATCH(WaterfallTable[[#This Row],[Year]]-1,WaterfallTable[Year],0))+WaterfallTable[[#This Row],[Pref Accrued]]))) -> 0 | F4: =IF(WaterfallTable[[#This Row],[Year]]>SaleExitYear,0,MAX(0,IF(WaterfallTable[[#This Row],[Year]]=0,0,INDEX(WaterfallTable[End of Year Pref Balance],MATCH(WaterfallTable[[#This Row],[Year]]-1,WaterfallTable[Year],0)))+WaterfallTable[[#This Row],[Pref Accrued]]-WaterfallTable[[#This Row],[Pref Paid]])) -> 24000 | G4: =IF(WaterfallTable[[#This Row],[Year]]>SaleExitYear,0,IF(WaterfallTable[[#This Row],[Year]]=0,ClassACapital,MAX(0,INDEX(WaterfallTable[Capital Balance A],MATCH(WaterfallTable[[#This Row],[Year]]-1,WaterfallTable[Year],0))-INDEX(WaterfallTable[Capital Returned A],MATCH(WaterfallTable[[#This Row],[Year]]-1,WaterfallTable[Year],0))))) -> 300000 | H4: =IF(WaterfallTable[[#This Row],[Year]]>SaleExitYear,0,IF(WaterfallTable[[#This Row],[Year]]=0,0,MIN(WaterfallTable[[#This Row],[Cash Available]],WaterfallTable[[#This Row],[Capital Balance A]]))) -> 0 | I4: =IF(WaterfallTable[[#This Row],[Year]]>SaleExitYear,0,IF(WaterfallTable[[#This Row],[Year]]=0,0,MAX(0,WaterfallTable[[#This Row],[Cash Available]]-WaterfallTable[[#This Row],[Capital Returned A]]-WaterfallTable[[#This Row],[Capital Returned B]]-WaterfallTable[[#This Row],[Pref Paid]])*ClassAResidualShare)) -> 0 | J4: =IF(WaterfallTable[[#This Row],[Year]]>SaleExitYear,0,WaterfallTable[[#This Row],[Pref Paid]]+WaterfallTable[[#This Row],[Capital Returned A]]+WaterfallTable[[#This Row],[Residual A]]) -> 0 | K4: =IF(WaterfallTable[[#This Row],[Year]]>SaleExitYear,0,IF(WaterfallTable[[#This Row],[Year]]=0,ClassBCapital,MAX(0,INDEX(WaterfallTable[ [ Capital Balance B] ],MATCH(WaterfallTable[[#This Row],[Year]]-1,WaterfallTable[Year],0))-INDEX(WaterfallTable[Capital Returned B],MATCH(WaterfallTable[[#This Row],[Year]]-1,WaterfallTable[Year],0))))) -> 547500 | L4: =IF(WaterfallTable[[#This Row],[Year]]>SaleExitYear,0,IF(WaterfallTable[[#This Row],[Year]]=0,0,IF(ClassBReturnPriority=1,MIN(MAX(0,WaterfallTable[[#This Row],[Cash Available]]-WaterfallTable[[#This Row],[Capital Returned A]]),WaterfallTable[[#This Row],[ Capital Balance B]]),0))) -> 0 | M4: =IF(WaterfallTable[[#This Row],[Year]]>SaleExitYear,0,IF(WaterfallTable[[#This Row],[Year]]=0,0,MAX(0,WaterfallTable[[#This Row],[Cash Available]]-WaterfallTable[[#This Row],[Capital Returned A]]-WaterfallTable[[#This Row],[Capital Returned B]]-WaterfallTable[[#This Row],[Pref Paid]])*ClassBResidualShare)) -> 0 | N4: =IF(WaterfallTable[[#This Row],[Year]]>SaleExitYear,0,WaterfallTable[[#This Row],[Capital Returned B]]+WaterfallTable[[#This Row],[ Residual B]]) -> 0 | O4: =IF(WaterfallTable[[#This Row],[Year]]>SaleExitYear,0,IF(WaterfallTable[[#This Row],[Year]]=0,SponsorPropertyPayment,0)) -> 100000 | P4: =IF(WaterfallTable[[#This Row],[Year]]>SaleExitYear,0,IF(WaterfallTable[[#This Row],[Year]]=0,0,MAX(0,WaterfallTable[[#This Row],[Cash Available]]-WaterfallTable[[#This Row],[Capital Returned A]]-WaterfallTable[[#This Row],[Capital Returned B]]-WaterfallTable[[#This Row],[Pref Paid]])*SponsorResidualShare)) -> 0 | Q4: =IF(WaterfallTable[[#This Row],[Year]]>SaleExitYear,0,WaterfallTable[[#This Row],[Property Payment]]+WaterfallTable[[#This Row],[Residual]]) -> 100000
B5: 1 | C5: =IF(WaterfallTable[[#This Row],[Year]]>SaleExitYear,0,INDEX(AnnualModelTable[Cash Available Before Distributions],MATCH(WaterfallTable[[#This Row],[Year]],AnnualModelTable[Year],0))) -> 2521.3621 | D5: =IF(WaterfallTable[[#This Row],[Year]]>SaleExitYear,0,WaterfallTable[[#This Row],[Capital Balance A]]*ClassAPreferredReturn) -> 24000 | E5: =IF(WaterfallTable[[#This Row],[Year]]>SaleExitYear,0,IF(WaterfallTable[[#This Row],[Year]]=0,0,MIN(MAX(0,WaterfallTable[[#This Row],[Cash Available]]-WaterfallTable[[#This Row],[Capital Returned A]]-WaterfallTable[[#This Row],[Capital Returned B]]),INDEX(WaterfallTable[End of Year Pref Balance],MATCH(WaterfallTable[[#This Row],[Year]]-1,WaterfallTable[Year],0))+WaterfallTable[[#This Row],[Pref Accrued]]))) -> 0 | F5: =IF(WaterfallTable[[#This Row],[Year]]>SaleExitYear,0,MAX(0,IF(WaterfallTable[[#This Row],[Year]]=0,0,INDEX(WaterfallTable[End of Year Pref Balance],MATCH(WaterfallTable[[#This Row],[Year]]-1,WaterfallTable[Year],0)))+WaterfallTable[[#This Row],[Pref Accrued]]-WaterfallTable[[#This Row],[Pref Paid]])) -> 48000 | G5: =IF(WaterfallTable[[#This Row],[Year]]>SaleExitYear,0,IF(WaterfallTable[[#This Row],[Year]]=0,ClassACapital,MAX(0,INDEX(WaterfallTable[Capital Balance A],MATCH(WaterfallTable[[#This Row],[Year]]-1,WaterfallTable[Year],0))-INDEX(WaterfallTable[Capital Returned A],MATCH(WaterfallTable[[#This Row],[Year]]-1,WaterfallTable[Year],0))))) -> 300000 | H5: =IF(WaterfallTable[[#This Row],[Year]]>SaleExitYear,0,IF(WaterfallTable[[#This Row],[Year]]=0,0,MIN(WaterfallTable[[#This Row],[Cash Available]],WaterfallTable[[#This Row],[Capital Balance A]]))) -> 2521.3621 | I5: =IF(WaterfallTable[[#This Row],[Year]]>SaleExitYear,0,IF(WaterfallTable[[#This Row],[Year]]=0,0,MAX(0,WaterfallTable[[#This Row],[Cash Available]]-WaterfallTable[[#This Row],[Capital Returned A]]-WaterfallTable[[#This Row],[Capital Returned B]]-WaterfallTable[[#This Row],[Pref Paid]])*ClassAResidualShare)) -> 0 | J5: =IF(WaterfallTable[[#This Row],[Year]]>SaleExitYear,0,WaterfallTable[[#This Row],[Pref Paid]]+WaterfallTable[[#This Row],[Capital Returned A]]+WaterfallTable[[#This Row],[Residual A]]) -> 2521.3621 | K5: =IF(WaterfallTable[[#This Row],[Year]]>SaleExitYear,0,IF(WaterfallTable[[#This Row],[Year]]=0,ClassBCapital,MAX(0,INDEX(WaterfallTable[ [ Capital Balance B] ],MATCH(WaterfallTable[[#This Row],[Year]]-1,WaterfallTable[Year],0))-INDEX(WaterfallTable[Capital Returned B],MATCH(WaterfallTable[[#This Row],[Year]]-1,WaterfallTable[Year],0))))) -> 547500 | L5: =IF(WaterfallTable[[#This Row],[Year]]>SaleExitYear,0,IF(WaterfallTable[[#This Row],[Year]]=0,0,IF(ClassBReturnPriority=1,MIN(MAX(0,WaterfallTable[[#This Row],[Cash Available]]-WaterfallTable[[#This Row],[Capital Returned A]]),WaterfallTable[[#This Row],[ Capital Balance B]]),0))) -> 0 | M5: =IF(WaterfallTable[[#This Row],[Year]]>SaleExitYear,0,IF(WaterfallTable[[#This Row],[Year]]=0,0,MAX(0,WaterfallTable[[#This Row],[Cash Available]]-WaterfallTable[[#This Row],[Capital Returned A]]-WaterfallTable[[#This Row],[Capital Returned B]]-WaterfallTable[[#This Row],[Pref Paid]])*ClassBResidualShare)) -> 0 | N5: =IF(WaterfallTable[[#This Row],[Year]]>SaleExitYear,0,WaterfallTable[[#This Row],[Capital Returned B]]+WaterfallTable[[#This Row],[ Residual B]]) -> 0 | O5: =IF(WaterfallTable[[#This Row],[Year]]>SaleExitYear,0,IF(WaterfallTable[[#This Row],[Year]]=0,SponsorPropertyPayment,0)) -> 0 | P5: =IF(WaterfallTable[[#This Row],[Year]]>SaleExitYear,0,IF(WaterfallTable[[#This Row],[Year]]=0,0,MAX(0,WaterfallTable[[#This Row],[Cash Available]]-WaterfallTable[[#This Row],[Capital Returned A]]-WaterfallTable[[#This Row],[Capital Returned B]]-WaterfallTable[[#This Row],[Pref Paid]])*SponsorResidualShare)) -> 0 | Q5: =IF(WaterfallTable[[#This Row],[Year]]>SaleExitYear,0,WaterfallTable[[#This Row],[Property Payment]]+WaterfallTable[[#This Row],[Residual]]) -> 0
B6: 2 | C6: =IF(WaterfallTable[[#This Row],[Year]]>SaleExitYear,0,INDEX(AnnualModelTable[Cash Available Before Distributions],MATCH(WaterfallTable[[#This Row],[Year]],AnnualModelTable[Year],0))) -> 52293.821 | D6: =IF(WaterfallTable[[#This Row],[Year]]>SaleExitYear,0,WaterfallTable[[#This Row],[Capital Balance A]]*ClassAPreferredReturn) -> 23798.291 | E6: =IF(WaterfallTable[[#This Row],[Year]]>SaleExitYear,0,IF(WaterfallTable[[#This Row],[Year]]=0,0,MIN(MAX(0,WaterfallTable[[#This Row],[Cash Available]]-WaterfallTable[[#This Row],[Capital Returned A]]-WaterfallTable[[#This Row],[Capital Returned B]]),INDEX(WaterfallTable[End of Year Pref Balance],MATCH(WaterfallTable[[#This Row],[Year]]-1,WaterfallTable[Year],0))+WaterfallTable[[#This Row],[Pref Accrued]]))) -> 0 | F6: =IF(WaterfallTable[[#This Row],[Year]]>SaleExitYear,0,MAX(0,IF(WaterfallTable[[#This Row],[Year]]=0,0,INDEX(WaterfallTable[End of Year Pref Balance],MATCH(WaterfallTable[[#This Row],[Year]]-1,WaterfallTable[Year],0)))+WaterfallTable[[#This Row],[Pref Accrued]]-WaterfallTable[[#This Row],[Pref Paid]])) -> 71798.291 | G6: =IF(WaterfallTable[[#This Row],[Year]]>SaleExitYear,0,IF(WaterfallTable[[#This Row],[Year]]=0,ClassACapital,MAX(0,INDEX(WaterfallTable[Capital Balance A],MATCH(WaterfallTable[[#This Row],[Year]]-1,WaterfallTable[Year],0))-INDEX(WaterfallTable[Capital Returned A],MATCH(WaterfallTable[[#This Row],[Year]]-1,WaterfallTable[Year],0))))) -> 297478.64 | H6: =IF(WaterfallTable[[#This Row],[Year]]>SaleExitYear,0,IF(WaterfallTable[[#This Row],[Year]]=0,0,MIN(WaterfallTable[[#This Row],[Cash Available]],WaterfallTable[[#This Row],[Capital Balance A]]))) -> 52293.821 | I6: =IF(WaterfallTable[[#This Row],[Year]]>SaleExitYear,0,IF(WaterfallTable[[#This Row],[Year]]=0,0,MAX(0,WaterfallTable[[#This Row],[Cash Available]]-WaterfallTable[[#This Row],[Capital Returned A]]-WaterfallTable[[#This Row],[Capital Returned B]]-WaterfallTable[[#This Row],[Pref Paid]])*ClassAResidualShare)) -> 0 | J6: =IF(WaterfallTable[[#This Row],[Year]]>SaleExitYear,0,WaterfallTable[[#This Row],[Pref Paid]]+WaterfallTable[[#This Row],[Capital Returned A]]+WaterfallTable[[#This Row],[Residual A]]) -> 52293.821 | K6: =IF(WaterfallTable[[#This Row],[Year]]>SaleExitYear,0,IF(WaterfallTable[[#This Row],[Year]]=0,ClassBCapital,MAX(0,INDEX(WaterfallTable[ [ Capital Balance B] ],MATCH(WaterfallTable[[#This Row],[Year]]-1,WaterfallTable[Year],0))-INDEX(WaterfallTable[Capital Returned B],MATCH(WaterfallTable[[#This Row],[Year]]-1,WaterfallTable[Year],0))))) -> 547500 | L6: =IF(WaterfallTable[[#This Row],[Year]]>SaleExitYear,0,IF(WaterfallTable[[#This Row],[Year]]=0,0,IF(ClassBReturnPriority=1,MIN(MAX(0,WaterfallTable[[#This Row],[Cash Available]]-WaterfallTable[[#This Row],[Capital Returned A]]),WaterfallTable[[#This Row],[ Capital Balance B]]),0))) -> 0 | M6: =IF(WaterfallTable[[#This Row],[Year]]>SaleExitYear,0,IF(WaterfallTable[[#This Row],[Year]]=0,0,MAX(0,WaterfallTable[[#This Row],[Cash Available]]-WaterfallTable[[#This Row],[Capital Returned A]]-WaterfallTable[[#This Row],[Capital Returned B]]-WaterfallTable[[#This Row],[Pref Paid]])*ClassBResidualShare)) -> 0 | N6: =IF(WaterfallTable[[#This Row],[Year]]>SaleExitYear,0,WaterfallTable[[#This Row],[Capital Returned B]]+WaterfallTable[[#This Row],[ Residual B]]) -> 0 | O6: =IF(WaterfallTable[[#This Row],[Year]]>SaleExitYear,0,IF(WaterfallTable[[#This Row],[Year]]=0,SponsorPropertyPayment,0)) -> 0 | P6: =IF(WaterfallTable[[#This Row],[Year]]>SaleExitYear,0,IF(WaterfallTable[[#This Row],[Year]]=0,0,MAX(0,WaterfallTable[[#This Row],[Cash Available]]-WaterfallTable[[#This Row],[Capital Returned A]]-WaterfallTable[[#This Row],[Capital Returned B]]-WaterfallTable[[#This Row],[Pref Paid]])*SponsorResidualShare)) -> 0 | Q6: =IF(WaterfallTable[[#This Row],[Year]]>SaleExitYear,0,WaterfallTable[[#This Row],[Property Payment]]+WaterfallTable[[#This Row],[Residual]]) -> 0
B7: 3 | C7: =IF(WaterfallTable[[#This Row],[Year]]>SaleExitYear,0,INDEX(AnnualModelTable[Cash Available Before Distributions],MATCH(WaterfallTable[[#This Row],[Year]],AnnualModelTable[Year],0))) -> 568344.61 | D7: =IF(WaterfallTable[[#This Row],[Year]]>SaleExitYear,0,WaterfallTable[[#This Row],[Capital Balance A]]*ClassAPreferredReturn) -> 19614.785 | E7: =IF(WaterfallTable[[#This Row],[Year]]>SaleExitYear,0,IF(WaterfallTable[[#This Row],[Year]]=0,0,MIN(MAX(0,WaterfallTable[[#This Row],[Cash Available]]-WaterfallTable[[#This Row],[Capital Returned A]]-WaterfallTable[[#This Row],[Capital Returned B]]),INDEX(WaterfallTable[End of Year Pref Balance],MATCH(WaterfallTable[[#This Row],[Year]]-1,WaterfallTable[Year],0))+WaterfallTable[[#This Row],[Pref Accrued]]))) -> 0 | F7: =IF(WaterfallTable[[#This Row],[Year]]>SaleExitYear,0,MAX(0,IF(WaterfallTable[[#This Row],[Year]]=0,0,INDEX(WaterfallTable[End of Year Pref Balance],MATCH(WaterfallTable[[#This Row],[Year]]-1,WaterfallTable[Year],0)))+WaterfallTable[[#This Row],[Pref Accrued]]-WaterfallTable[[#This Row],[Pref Paid]])) -> 91413.076 | G7: =IF(WaterfallTable[[#This Row],[Year]]>SaleExitYear,0,IF(WaterfallTable[[#This Row],[Year]]=0,ClassACapital,MAX(0,INDEX(WaterfallTable[Capital Balance A],MATCH(WaterfallTable[[#This Row],[Year]]-1,WaterfallTable[Year],0))-INDEX(WaterfallTable[Capital Returned A],MATCH(WaterfallTable[[#This Row],[Year]]-1,WaterfallTable[Year],0))))) -> 245184.82 | H7: =IF(WaterfallTable[[#This Row],[Year]]>SaleExitYear,0,IF(WaterfallTable[[#This Row],[Year]]=0,0,MIN(WaterfallTable[[#This Row],[Cash Available]],WaterfallTable[[#This Row],[Capital Balance A]]))) -> 245184.82 | I7: =IF(WaterfallTable[[#This Row],[Year]]>SaleExitYear,0,IF(WaterfallTable[[#This Row],[Year]]=0,0,MAX(0,WaterfallTable[[#This Row],[Cash Available]]-WaterfallTable[[#This Row],[Capital Returned A]]-WaterfallTable[[#This Row],[Capital Returned B]]-WaterfallTable[[#This Row],[Pref Paid]])*ClassAResidualShare)) -> 0 | J7: =IF(WaterfallTable[[#This Row],[Year]]>SaleExitYear,0,WaterfallTable[[#This Row],[Pref Paid]]+WaterfallTable[[#This Row],[Capital Returned A]]+WaterfallTable[[#This Row],[Residual A]]) -> 245184.82 | K7: =IF(WaterfallTable[[#This Row],[Year]]>SaleExitYear,0,IF(WaterfallTable[[#This Row],[Year]]=0,ClassBCapital,MAX(0,INDEX(WaterfallTable[ [ Capital Balance B] ],MATCH(WaterfallTable[[#This Row],[Year]]-1,WaterfallTable[Year],0))-INDEX(WaterfallTable[Capital Returned B],MATCH(WaterfallTable[[#This Row],[Year]]-1,WaterfallTable[Year],0))))) -> 547500 | L7: =IF(WaterfallTable[[#This Row],[Year]]>SaleExitYear,0,IF(WaterfallTable[[#This Row],[Year]]=0,0,IF(ClassBReturnPriority=1,MIN(MAX(0,WaterfallTable[[#This Row],[Cash Available]]-WaterfallTable[[#This Row],[Capital Returned A]]),WaterfallTable[[#This Row],[ Capital Balance B]]),0))) -> 323159.79 | M7: =IF(WaterfallTable[[#This Row],[Year]]>SaleExitYear,0,IF(WaterfallTable[[#This Row],[Year]]=0,0,MAX(0,WaterfallTable[[#This Row],[Cash Available]]-WaterfallTable[[#This Row],[Capital Returned A]]-WaterfallTable[[#This Row],[Capital Returned B]]-WaterfallTable[[#This Row],[Pref Paid]])*ClassBResidualShare)) -> 0 | N7: =IF(WaterfallTable[[#This Row],[Year]]>SaleExitYear,0,WaterfallTable[[#This Row],[Capital Returned B]]+WaterfallTable[[#This Row],[ Residual B]]) -> 323159.79 | O7: =IF(WaterfallTable[[#This Row],[Year]]>SaleExitYear,0,IF(WaterfallTable[[#This Row],[Year]]=0,SponsorPropertyPayment,0)) -> 0 | P7: =IF(WaterfallTable[[#This Row],[Year]]>SaleExitYear,0,IF(WaterfallTable[[#This Row],[Year]]=0,0,MAX(0,WaterfallTable[[#This Row],[Cash Available]]-WaterfallTable[[#This Row],[Capital Returned A]]-WaterfallTable[[#This Row],[Capital Returned B]]-WaterfallTable[[#This Row],[Pref Paid]])*SponsorResidualShare)) -> 0 | Q7: =IF(WaterfallTable[[#This Row],[Year]]>SaleExitYear,0,WaterfallTable[[#This Row],[Property Payment]]+WaterfallTable[[#This Row],[Residual]]) -> 0
B8: 4 | C8: =IF(WaterfallTable[[#This Row],[Year]]>SaleExitYear,0,INDEX(AnnualModelTable[Cash Available Before Distributions],MATCH(WaterfallTable[[#This Row],[Year]],AnnualModelTable[Year],0))) -> 30068.166 | D8: =IF(WaterfallTable[[#This Row],[Year]]>SaleExitYear,0,WaterfallTable[[#This Row],[Capital Balance A]]*ClassAPreferredReturn) -> 0 | E8: =IF(WaterfallTable[[#This Row],[Year]]>SaleExitYear,0,IF(WaterfallTable[[#This Row],[Year]]=0,0,MIN(MAX(0,WaterfallTable[[#This Row],[Cash Available]]-WaterfallTable[[#This Row],[Capital Returned A]]-WaterfallTable[[#This Row],[Capital Returned B]]),INDEX(WaterfallTable[End of Year Pref Balance],MATCH(WaterfallTable[[#This Row],[Year]]-1,WaterfallTable[Year],0))+WaterfallTable[[#This Row],[Pref Accrued]]))) -> 0 | F8: =IF(WaterfallTable[[#This Row],[Year]]>SaleExitYear,0,MAX(0,IF(WaterfallTable[[#This Row],[Year]]=0,0,INDEX(WaterfallTable[End of Year Pref Balance],MATCH(WaterfallTable[[#This Row],[Year]]-1,WaterfallTable[Year],0)))+WaterfallTable[[#This Row],[Pref Accrued]]-WaterfallTable[[#This Row],[Pref Paid]])) -> 91413.076 | G8: =IF(WaterfallTable[[#This Row],[Year]]>SaleExitYear,0,IF(WaterfallTable[[#This Row],[Year]]=0,ClassACapital,MAX(0,INDEX(WaterfallTable[Capital Balance A],MATCH(WaterfallTable[[#This Row],[Year]]-1,WaterfallTable[Year],0))-INDEX(WaterfallTable[Capital Returned A],MATCH(WaterfallTable[[#This Row],[Year]]-1,WaterfallTable[Year],0))))) -> 0 | H8: =IF(WaterfallTable[[#This Row],[Year]]>SaleExitYear,0,IF(WaterfallTable[[#This Row],[Year]]=0,0,MIN(WaterfallTable[[#This Row],[Cash Available]],WaterfallTable[[#This Row],[Capital Balance A]]))) -> 0 | I8: =IF(WaterfallTable[[#This Row],[Year]]>SaleExitYear,0,IF(WaterfallTable[[#This Row],[Year]]=0,0,MAX(0,WaterfallTable[[#This Row],[Cash Available]]-WaterfallTable[[#This Row],[Capital Returned A]]-WaterfallTable[[#This Row],[Capital Returned B]]-WaterfallTable[[#This Row],[Pref Paid]])*ClassAResidualShare)) -> 0 | J8: =IF(WaterfallTable[[#This Row],[Year]]>SaleExitYear,0,WaterfallTable[[#This Row],[Pref Paid]]+WaterfallTable[[#This Row],[Capital Returned A]]+WaterfallTable[[#This Row],[Residual A]]) -> 0 | K8: =IF(WaterfallTable[[#This Row],[Year]]>SaleExitYear,0,IF(WaterfallTable[[#This Row],[Year]]=0,ClassBCapital,MAX(0,INDEX(WaterfallTable[ [ Capital Balance B] ],MATCH(WaterfallTable[[#This Row],[Year]]-1,WaterfallTable[Year],0))-INDEX(WaterfallTable[Capital Returned B],MATCH(WaterfallTable[[#This Row],[Year]]-1,WaterfallTable[Year],0))))) -> 224340.21 | L8: =IF(WaterfallTable[[#This Row],[Year]]>SaleExitYear,0,IF(WaterfallTable[[#This Row],[Year]]=0,0,IF(ClassBReturnPriority=1,MIN(MAX(0,WaterfallTable[[#This Row],[Cash Available]]-WaterfallTable[[#This Row],[Capital Returned A]]),WaterfallTable[[#This Row],[ Capital Balance B]]),0))) -> 30068.166 | M8: =IF(WaterfallTable[[#This Row],[Year]]>SaleExitYear,0,IF(WaterfallTable[[#This Row],[Year]]=0,0,MAX(0,WaterfallTable[[#This Row],[Cash Available]]-WaterfallTable[[#This Row],[Capital Returned A]]-WaterfallTable[[#This Row],[Capital Returned B]]-WaterfallTable[[#This Row],[Pref Paid]])*ClassBResidualShare)) -> 0 | N8: =IF(WaterfallTable[[#This Row],[Year]]>SaleExitYear,0,WaterfallTable[[#This Row],[Capital Returned B]]+WaterfallTable[[#This Row],[ Residual B]]) -> 30068.166 | O8: =IF(WaterfallTable[[#This Row],[Year]]>SaleExitYear,0,IF(WaterfallTable[[#This Row],[Year]]=0,SponsorPropertyPayment,0)) -> 0 | P8: =IF(WaterfallTable[[#This Row],[Year]]>SaleExitYear,0,IF(WaterfallTable[[#This Row],[Year]]=0,0,MAX(0,WaterfallTable[[#This Row],[Cash Available]]-WaterfallTable[[#This Row],[Capital Returned A]]-WaterfallTable[[#This Row],[Capital Returned B]]-WaterfallTable[[#This Row],[Pref Paid]])*SponsorResidualShare)) -> 0 | Q8: =IF(WaterfallTable[[#This Row],[Year]]>SaleExitYear,0,WaterfallTable[[#This Row],[Property Payment]]+WaterfallTable[[#This Row],[Residual]]) -> 0
B9: 5 | C9: =IF(WaterfallTable[[#This Row],[Year]]>SaleExitYear,0,INDEX(AnnualModelTable[Cash Available Before Distributions],MATCH(WaterfallTable[[#This Row],[Year]],AnnualModelTable[Year],0))) -> 1264564.2 | D9: =IF(WaterfallTable[[#This Row],[Year]]>SaleExitYear,0,WaterfallTable[[#This Row],[Capital Balance A]]*ClassAPreferredReturn) -> 0 | E9: =IF(WaterfallTable[[#This Row],[Year]]>SaleExitYear,0,IF(WaterfallTable[[#This Row],[Year]]=0,0,MIN(MAX(0,WaterfallTable[[#This Row],[Cash Available]]-WaterfallTable[[#This Row],[Capital Returned A]]-WaterfallTable[[#This Row],[Capital Returned B]]),INDEX(WaterfallTable[End of Year Pref Balance],MATCH(WaterfallTable[[#This Row],[Year]]-1,WaterfallTable[Year],0))+WaterfallTable[[#This Row],[Pref Accrued]]))) -> 91413.076 | F9: =IF(WaterfallTable[[#This Row],[Year]]>SaleExitYear,0,MAX(0,IF(WaterfallTable[[#This Row],[Year]]=0,0,INDEX(WaterfallTable[End of Year Pref Balance],MATCH(WaterfallTable[[#This Row],[Year]]-1,WaterfallTable[Year],0)))+WaterfallTable[[#This Row],[Pref Accrued]]-WaterfallTable[[#This Row],[Pref Paid]])) -> 0 | G9: =IF(WaterfallTable[[#This Row],[Year]]>SaleExitYear,0,IF(WaterfallTable[[#This Row],[Year]]=0,ClassACapital,MAX(0,INDEX(WaterfallTable[Capital Balance A],MATCH(WaterfallTable[[#This Row],[Year]]-1,WaterfallTable[Year],0))-INDEX(WaterfallTable[Capital Returned A],MATCH(WaterfallTable[[#This Row],[Year]]-1,WaterfallTable[Year],0))))) -> 0 | H9: =IF(WaterfallTable[[#This Row],[Year]]>SaleExitYear,0,IF(WaterfallTable[[#This Row],[Year]]=0,0,MIN(WaterfallTable[[#This Row],[Cash Available]],WaterfallTable[[#This Row],[Capital Balance A]]))) -> 0 | I9: =IF(WaterfallTable[[#This Row],[Year]]>SaleExitYear,0,IF(WaterfallTable[[#This Row],[Year]]=0,0,MAX(0,WaterfallTable[[#This Row],[Cash Available]]-WaterfallTable[[#This Row],[Capital Returned A]]-WaterfallTable[[#This Row],[Capital Returned B]]-WaterfallTable[[#This Row],[Pref Paid]])*ClassAResidualShare)) -> 173252.93 | J9: =IF(WaterfallTable[[#This Row],[Year]]>SaleExitYear,0,WaterfallTable[[#This Row],[Pref Paid]]+WaterfallTable[[#This Row],[Capital Returned A]]+WaterfallTable[[#This Row],[Residual A]]) -> 264666.01 | K9: =IF(WaterfallTable[[#This Row],[Year]]>SaleExitYear,0,IF(WaterfallTable[[#This Row],[Year]]=0,ClassBCapital,MAX(0,INDEX(WaterfallTable[ [ Capital Balance B] ],MATCH(WaterfallTable[[#This Row],[Year]]-1,WaterfallTable[Year],0))-INDEX(WaterfallTable[Capital Returned B],MATCH(WaterfallTable[[#This Row],[Year]]-1,WaterfallTable[Year],0))))) -> 194272.05 | L9: =IF(WaterfallTable[[#This Row],[Year]]>SaleExitYear,0,IF(WaterfallTable[[#This Row],[Year]]=0,0,IF(ClassBReturnPriority=1,MIN(MAX(0,WaterfallTable[[#This Row],[Cash Available]]-WaterfallTable[[#This Row],[Capital Returned A]]),WaterfallTable[[#This Row],[ Capital Balance B]]),0))) -> 194272.05 | M9: =IF(WaterfallTable[[#This Row],[Year]]>SaleExitYear,0,IF(WaterfallTable[[#This Row],[Year]]=0,0,MAX(0,WaterfallTable[[#This Row],[Cash Available]]-WaterfallTable[[#This Row],[Capital Returned A]]-WaterfallTable[[#This Row],[Capital Returned B]]-WaterfallTable[[#This Row],[Pref Paid]])*ClassBResidualShare)) -> 316186.6 | N9: =IF(WaterfallTable[[#This Row],[Year]]>SaleExitYear,0,WaterfallTable[[#This Row],[Capital Returned B]]+WaterfallTable[[#This Row],[ Residual B]]) -> 510458.65 | O9: =IF(WaterfallTable[[#This Row],[Year]]>SaleExitYear,0,IF(WaterfallTable[[#This Row],[Year]]=0,SponsorPropertyPayment,0)) -> 0 | P9: =IF(WaterfallTable[[#This Row],[Year]]>SaleExitYear,0,IF(WaterfallTable[[#This Row],[Year]]=0,0,MAX(0,WaterfallTable[[#This Row],[Cash Available]]-WaterfallTable[[#This Row],[Capital Returned A]]-WaterfallTable[[#This Row],[Capital Returned B]]-WaterfallTable[[#This Row],[Pref Paid]])*SponsorResidualShare)) -> 489439.54 | Q9: =IF(WaterfallTable[[#This Row],[Year]]>SaleExitYear,0,WaterfallTable[[#This Row],[Property Payment]]+WaterfallTable[[#This Row],[Residual]]) -> 489439.54
B10: 6 | C10: =IF(WaterfallTable[[#This Row],[Year]]>SaleExitYear,0,INDEX(AnnualModelTable[Cash Available Before Distributions],MATCH(WaterfallTable[[#This Row],[Year]],AnnualModelTable[Year],0))) -> 0 | D10: =IF(WaterfallTable[[#This Row],[Year]]>SaleExitYear,0,WaterfallTable[[#This Row],[Capital Balance A]]*ClassAPreferredReturn) -> 0 | E10: =IF(WaterfallTable[[#This Row],[Year]]>SaleExitYear,0,IF(WaterfallTable[[#This Row],[Year]]=0,0,MIN(MAX(0,WaterfallTable[[#This Row],[Cash Available]]-WaterfallTable[[#This Row],[Capital Returned A]]-WaterfallTable[[#This Row],[Capital Returned B]]),INDEX(WaterfallTable[End of Year Pref Balance],MATCH(WaterfallTable[[#This Row],[Year]]-1,WaterfallTable[Year],0))+WaterfallTable[[#This Row],[Pref Accrued]]))) -> 0 | F10: =IF(WaterfallTable[[#This Row],[Year]]>SaleExitYear,0,MAX(0,IF(WaterfallTable[[#This Row],[Year]]=0,0,INDEX(WaterfallTable[End of Year Pref Balance],MATCH(WaterfallTable[[#This Row],[Year]]-1,WaterfallTable[Year],0)))+WaterfallTable[[#This Row],[Pref Accrued]]-WaterfallTable[[#This Row],[Pref Paid]])) -> 0 | G10: =IF(WaterfallTable[[#This Row],[Year]]>SaleExitYear,0,IF(WaterfallTable[[#This Row],[Year]]=0,ClassACapital,MAX(0,INDEX(WaterfallTable[Capital Balance A],MATCH(WaterfallTable[[#This Row],[Year]]-1,WaterfallTable[Year],0))-INDEX(WaterfallTable[Capital Returned A],MATCH(WaterfallTable[[#This Row],[Year]]-1,WaterfallTable[Year],0))))) -> 0 | H10: =IF(WaterfallTable[[#This Row],[Year]]>SaleExitYear,0,IF(WaterfallTable[[#This Row],[Year]]=0,0,MIN(WaterfallTable[[#This Row],[Cash Available]],WaterfallTable[[#This Row],[Capital Balance A]]))) -> 0 | I10: =IF(WaterfallTable[[#This Row],[Year]]>SaleExitYear,0,IF(WaterfallTable[[#This Row],[Year]]=0,0,MAX(0,WaterfallTable[[#This Row],[Cash Available]]-WaterfallTable[[#This Row],[Capital Returned A]]-WaterfallTable[[#This Row],[Capital Returned B]]-WaterfallTable[[#This Row],[Pref Paid]])*ClassAResidualShare)) -> 0 | J10: =IF(WaterfallTable[[#This Row],[Year]]>SaleExitYear,0,WaterfallTable[[#This Row],[Pref Paid]]+WaterfallTable[[#This Row],[Capital Returned A]]+WaterfallTable[[#This Row],[Residual A]]) -> 0 | K10: =IF(WaterfallTable[[#This Row],[Year]]>SaleExitYear,0,IF(WaterfallTable[[#This Row],[Year]]=0,ClassBCapital,MAX(0,INDEX(WaterfallTable[ [ Capital Balance B] ],MATCH(WaterfallTable[[#This Row],[Year]]-1,WaterfallTable[Year],0))-INDEX(WaterfallTable[Capital Returned B],MATCH(WaterfallTable[[#This Row],[Year]]-1,WaterfallTable[Year],0))))) -> 0 | L10: =IF(WaterfallTable[[#This Row],[Year]]>SaleExitYear,0,IF(WaterfallTable[[#This Row],[Year]]=0,0,IF(ClassBReturnPriority=1,MIN(MAX(0,WaterfallTable[[#This Row],[Cash Available]]-WaterfallTable[[#This Row],[Capital Returned A]]),WaterfallTable[[#This Row],[ Capital Balance B]]),0))) -> 0 | M10: =IF(WaterfallTable[[#This Row],[Year]]>SaleExitYear,0,IF(WaterfallTable[[#This Row],[Year]]=0,0,MAX(0,WaterfallTable[[#This Row],[Cash Available]]-WaterfallTable[[#This Row],[Capital Returned A]]-WaterfallTable[[#This Row],[Capital Returned B]]-WaterfallTable[[#This Row],[Pref Paid]])*ClassBResidualShare)) -> 0 | N10: =IF(WaterfallTable[[#This Row],[Year]]>SaleExitYear,0,WaterfallTable[[#This Row],[Capital Returned B]]+WaterfallTable[[#This Row],[ Residual B]]) -> 0 | O10: =IF(WaterfallTable[[#This Row],[Year]]>SaleExitYear,0,IF(WaterfallTable[[#This Row],[Year]]=0,SponsorPropertyPayment,0)) -> 0 | P10: =IF(WaterfallTable[[#This Row],[Year]]>SaleExitYear,0,IF(WaterfallTable[[#This Row],[Year]]=0,0,MAX(0,WaterfallTable[[#This Row],[Cash Available]]-WaterfallTable[[#This Row],[Capital Returned A]]-WaterfallTable[[#This Row],[Capital Returned B]]-WaterfallTable[[#This Row],[Pref Paid]])*SponsorResidualShare)) -> 0 | Q10: =IF(WaterfallTable[[#This Row],[Year]]>SaleExitYear,0,WaterfallTable[[#This Row],[Property Payment]]+WaterfallTable[[#This Row],[Residual]]) -> 0
B11: 7 | C11: =IF(WaterfallTable[[#This Row],[Year]]>SaleExitYear,0,INDEX(AnnualModelTable[Cash Available Before Distributions],MATCH(WaterfallTable[[#This Row],[Year]],AnnualModelTable[Year],0))) -> 0 | D11: =IF(WaterfallTable[[#This Row],[Year]]>SaleExitYear,0,WaterfallTable[[#This Row],[Capital Balance A]]*ClassAPreferredReturn) -> 0 | E11: =IF(WaterfallTable[[#This Row],[Year]]>SaleExitYear,0,IF(WaterfallTable[[#This Row],[Year]]=0,0,MIN(MAX(0,WaterfallTable[[#This Row],[Cash Available]]-WaterfallTable[[#This Row],[Capital Returned A]]-WaterfallTable[[#This Row],[Capital Returned B]]),INDEX(WaterfallTable[End of Year Pref Balance],MATCH(WaterfallTable[[#This Row],[Year]]-1,WaterfallTable[Year],0))+WaterfallTable[[#This Row],[Pref Accrued]]))) -> 0 | F11: =IF(WaterfallTable[[#This Row],[Year]]>SaleExitYear,0,MAX(0,IF(WaterfallTable[[#This Row],[Year]]=0,0,INDEX(WaterfallTable[End of Year Pref Balance],MATCH(WaterfallTable[[#This Row],[Year]]-1,WaterfallTable[Year],0)))+WaterfallTable[[#This Row],[Pref Accrued]]-WaterfallTable[[#This Row],[Pref Paid]])) -> 0 | G11: =IF(WaterfallTable[[#This Row],[Year]]>SaleExitYear,0,IF(WaterfallTable[[#This Row],[Year]]=0,ClassACapital,MAX(0,INDEX(WaterfallTable[Capital Balance A],MATCH(WaterfallTable[[#This Row],[Year]]-1,WaterfallTable[Year],0))-INDEX(WaterfallTable[Capital Returned A],MATCH(WaterfallTable[[#This Row],[Year]]-1,WaterfallTable[Year],0))))) -> 0 | H11: =IF(WaterfallTable[[#This Row],[Year]]>SaleExitYear,0,IF(WaterfallTable[[#This Row],[Year]]=0,0,MIN(WaterfallTable[[#This Row],[Cash Available]],WaterfallTable[[#This Row],[Capital Balance A]]))) -> 0 | I11: =IF(WaterfallTable[[#This Row],[Year]]>SaleExitYear,0,IF(WaterfallTable[[#This Row],[Year]]=0,0,MAX(0,WaterfallTable[[#This Row],[Cash Available]]-WaterfallTable[[#This Row],[Capital Returned A]]-WaterfallTable[[#This Row],[Capital Returned B]]-WaterfallTable[[#This Row],[Pref Paid]])*ClassAResidualShare)) -> 0 | J11: =IF(WaterfallTable[[#This Row],[Year]]>SaleExitYear,0,WaterfallTable[[#This Row],[Pref Paid]]+WaterfallTable[[#This Row],[Capital Returned A]]+WaterfallTable[[#This Row],[Residual A]]) -> 0 | K11: =IF(WaterfallTable[[#This Row],[Year]]>SaleExitYear,0,IF(WaterfallTable[[#This Row],[Year]]=0,ClassBCapital,MAX(0,INDEX(WaterfallTable[ [ Capital Balance B] ],MATCH(WaterfallTable[[#This Row],[Year]]-1,WaterfallTable[Year],0))-INDEX(WaterfallTable[Capital Returned B],MATCH(WaterfallTable[[#This Row],[Year]]-1,WaterfallTable[Year],0))))) -> 0 | L11: =IF(WaterfallTable[[#This Row],[Year]]>SaleExitYear,0,IF(WaterfallTable[[#This Row],[Year]]=0,0,IF(ClassBReturnPriority=1,MIN(MAX(0,WaterfallTable[[#This Row],[Cash Available]]-WaterfallTable[[#This Row],[Capital Returned A]]),WaterfallTable[[#This Row],[ Capital Balance B]]),0))) -> 0 | M11: =IF(WaterfallTable[[#This Row],[Year]]>SaleExitYear,0,IF(WaterfallTable[[#This Row],[Year]]=0,0,MAX(0,WaterfallTable[[#This Row],[Cash Available]]-WaterfallTable[[#This Row],[Capital Returned A]]-WaterfallTable[[#This Row],[Capital Returned B]]-WaterfallTable[[#This Row],[Pref Paid]])*ClassBResidualShare)) -> 0 | N11: =IF(WaterfallTable[[#This Row],[Year]]>SaleExitYear,0,WaterfallTable[[#This Row],[Capital Returned B]]+WaterfallTable[[#This Row],[ Residual B]]) -> 0 | O11: =IF(WaterfallTable[[#This Row],[Year]]>SaleExitYear,0,IF(WaterfallTable[[#This Row],[Year]]=0,SponsorPropertyPayment,0)) -> 0 | P11: =IF(WaterfallTable[[#This Row],[Year]]>SaleExitYear,0,IF(WaterfallTable[[#This Row],[Year]]=0,0,MAX(0,WaterfallTable[[#This Row],[Cash Available]]-WaterfallTable[[#This Row],[Capital Returned A]]-WaterfallTable[[#This Row],[Capital Returned B]]-WaterfallTable[[#This Row],[Pref Paid]])*SponsorResidualShare)) -> 0 | Q11: =IF(WaterfallTable[[#This Row],[Year]]>SaleExitYear,0,WaterfallTable[[#This Row],[Property Payment]]+WaterfallTable[[#This Row],[Residual]]) -> 0
B12: 8 | C12: =IF(WaterfallTable[[#This Row],[Year]]>SaleExitYear,0,INDEX(AnnualModelTable[Cash Available Before Distributions],MATCH(WaterfallTable[[#This Row],[Year]],AnnualModelTable[Year],0))) -> 0 | D12: =IF(WaterfallTable[[#This Row],[Year]]>SaleExitYear,0,WaterfallTable[[#This Row],[Capital Balance A]]*ClassAPreferredReturn) -> 0 | E12: =IF(WaterfallTable[[#This Row],[Year]]>SaleExitYear,0,IF(WaterfallTable[[#This Row],[Year]]=0,0,MIN(MAX(0,WaterfallTable[[#This Row],[Cash Available]]-WaterfallTable[[#This Row],[Capital Returned A]]-WaterfallTable[[#This Row],[Capital Returned B]]),INDEX(WaterfallTable[End of Year Pref Balance],MATCH(WaterfallTable[[#This Row],[Year]]-1,WaterfallTable[Year],0))+WaterfallTable[[#This Row],[Pref Accrued]]))) -> 0 | F12: =IF(WaterfallTable[[#This Row],[Year]]>SaleExitYear,0,MAX(0,IF(WaterfallTable[[#This Row],[Year]]=0,0,INDEX(WaterfallTable[End of Year Pref Balance],MATCH(WaterfallTable[[#This Row],[Year]]-1,WaterfallTable[Year],0)))+WaterfallTable[[#This Row],[Pref Accrued]]-WaterfallTable[[#This Row],[Pref Paid]])) -> 0 | G12: =IF(WaterfallTable[[#This Row],[Year]]>SaleExitYear,0,IF(WaterfallTable[[#This Row],[Year]]=0,ClassACapital,MAX(0,INDEX(WaterfallTable[Capital Balance A],MATCH(WaterfallTable[[#This Row],[Year]]-1,WaterfallTable[Year],0))-INDEX(WaterfallTable[Capital Returned A],MATCH(WaterfallTable[[#This Row],[Year]]-1,WaterfallTable[Year],0))))) -> 0 | H12: =IF(WaterfallTable[[#This Row],[Year]]>SaleExitYear,0,IF(WaterfallTable[[#This Row],[Year]]=0,0,MIN(WaterfallTable[[#This Row],[Cash Available]],WaterfallTable[[#This Row],[Capital Balance A]]))) -> 0 | I12: =IF(WaterfallTable[[#This Row],[Year]]>SaleExitYear,0,IF(WaterfallTable[[#This Row],[Year]]=0,0,MAX(0,WaterfallTable[[#This Row],[Cash Available]]-WaterfallTable[[#This Row],[Capital Returned A]]-WaterfallTable[[#This Row],[Capital Returned B]]-WaterfallTable[[#This Row],[Pref Paid]])*ClassAResidualShare)) -> 0 | J12: =IF(WaterfallTable[[#This Row],[Year]]>SaleExitYear,0,WaterfallTable[[#This Row],[Pref Paid]]+WaterfallTable[[#This Row],[Capital Returned A]]+WaterfallTable[[#This Row],[Residual A]]) -> 0 | K12: =IF(WaterfallTable[[#This Row],[Year]]>SaleExitYear,0,IF(WaterfallTable[[#This Row],[Year]]=0,ClassBCapital,MAX(0,INDEX(WaterfallTable[ [ Capital Balance B] ],MATCH(WaterfallTable[[#This Row],[Year]]-1,WaterfallTable[Year],0))-INDEX(WaterfallTable[Capital Returned B],MATCH(WaterfallTable[[#This Row],[Year]]-1,WaterfallTable[Year],0))))) -> 0 | L12: =IF(WaterfallTable[[#This Row],[Year]]>SaleExitYear,0,IF(WaterfallTable[[#This Row],[Year]]=0,0,IF(ClassBReturnPriority=1,MIN(MAX(0,WaterfallTable[[#This Row],[Cash Available]]-WaterfallTable[[#This Row],[Capital Returned A]]),WaterfallTable[[#This Row],[ Capital Balance B]]),0))) -> 0 | M12: =IF(WaterfallTable[[#This Row],[Year]]>SaleExitYear,0,IF(WaterfallTable[[#This Row],[Year]]=0,0,MAX(0,WaterfallTable[[#This Row],[Cash Available]]-WaterfallTable[[#This Row],[Capital Returned A]]-WaterfallTable[[#This Row],[Capital Returned B]]-WaterfallTable[[#This Row],[Pref Paid]])*ClassBResidualShare)) -> 0 | N12: =IF(WaterfallTable[[#This Row],[Year]]>SaleExitYear,0,WaterfallTable[[#This Row],[Capital Returned B]]+WaterfallTable[[#This Row],[ Residual B]]) -> 0 | O12: =IF(WaterfallTable[[#This Row],[Year]]>SaleExitYear,0,IF(WaterfallTable[[#This Row],[Year]]=0,SponsorPropertyPayment,0)) -> 0 | P12: =IF(WaterfallTable[[#This Row],[Year]]>SaleExitYear,0,IF(WaterfallTable[[#This Row],[Year]]=0,0,MAX(0,WaterfallTable[[#This Row],[Cash Available]]-WaterfallTable[[#This Row],[Capital Returned A]]-WaterfallTable[[#This Row],[Capital Returned B]]-WaterfallTable[[#This Row],[Pref Paid]])*SponsorResidualShare)) -> 0 | Q12: =IF(WaterfallTable[[#This Row],[Year]]>SaleExitYear,0,WaterfallTable[[#This Row],[Property Payment]]+WaterfallTable[[#This Row],[Residual]]) -> 0
B13: 9 | C13: =IF(WaterfallTable[[#This Row],[Year]]>SaleExitYear,0,INDEX(AnnualModelTable[Cash Available Before Distributions],MATCH(WaterfallTable[[#This Row],[Year]],AnnualModelTable[Year],0))) -> 0 | D13: =IF(WaterfallTable[[#This Row],[Year]]>SaleExitYear,0,WaterfallTable[[#This Row],[Capital Balance A]]*ClassAPreferredReturn) -> 0 | E13: =IF(WaterfallTable[[#This Row],[Year]]>SaleExitYear,0,IF(WaterfallTable[[#This Row],[Year]]=0,0,MIN(MAX(0,WaterfallTable[[#This Row],[Cash Available]]-WaterfallTable[[#This Row],[Capital Returned A]]-WaterfallTable[[#This Row],[Capital Returned B]]),INDEX(WaterfallTable[End of Year Pref Balance],MATCH(WaterfallTable[[#This Row],[Year]]-1,WaterfallTable[Year],0))+WaterfallTable[[#This Row],[Pref Accrued]]))) -> 0 | F13: =IF(WaterfallTable[[#This Row],[Year]]>SaleExitYear,0,MAX(0,IF(WaterfallTable[[#This Row],[Year]]=0,0,INDEX(WaterfallTable[End of Year Pref Balance],MATCH(WaterfallTable[[#This Row],[Year]]-1,WaterfallTable[Year],0)))+WaterfallTable[[#This Row],[Pref Accrued]]-WaterfallTable[[#This Row],[Pref Paid]])) -> 0 | G13: =IF(WaterfallTable[[#This Row],[Year]]>SaleExitYear,0,IF(WaterfallTable[[#This Row],[Year]]=0,ClassACapital,MAX(0,INDEX(WaterfallTable[Capital Balance A],MATCH(WaterfallTable[[#This Row],[Year]]-1,WaterfallTable[Year],0))-INDEX(WaterfallTable[Capital Returned A],MATCH(WaterfallTable[[#This Row],[Year]]-1,WaterfallTable[Year],0))))) -> 0 | H13: =IF(WaterfallTable[[#This Row],[Year]]>SaleExitYear,0,IF(WaterfallTable[[#This Row],[Year]]=0,0,MIN(WaterfallTable[[#This Row],[Cash Available]],WaterfallTable[[#This Row],[Capital Balance A]]))) -> 0 | I13: =IF(WaterfallTable[[#This Row],[Year]]>SaleExitYear,0,IF(WaterfallTable[[#This Row],[Year]]=0,0,MAX(0,WaterfallTable[[#This Row],[Cash Available]]-WaterfallTable[[#This Row],[Capital Returned A]]-WaterfallTable[[#This Row],[Capital Returned B]]-WaterfallTable[[#This Row],[Pref Paid]])*ClassAResidualShare)) -> 0 | J13: =IF(WaterfallTable[[#This Row],[Year]]>SaleExitYear,0,WaterfallTable[[#This Row],[Pref Paid]]+WaterfallTable[[#This Row],[Capital Returned A]]+WaterfallTable[[#This Row],[Residual A]]) -> 0 | K13: =IF(WaterfallTable[[#This Row],[Year]]>SaleExitYear,0,IF(WaterfallTable[[#This Row],[Year]]=0,ClassBCapital,MAX(0,INDEX(WaterfallTable[ [ Capital Balance B] ],MATCH(WaterfallTable[[#This Row],[Year]]-1,WaterfallTable[Year],0))-INDEX(WaterfallTable[Capital Returned B],MATCH(WaterfallTable[[#This Row],[Year]]-1,WaterfallTable[Year],0))))) -> 0 | L13: =IF(WaterfallTable[[#This Row],[Year]]>SaleExitYear,0,IF(WaterfallTable[[#This Row],[Year]]=0,0,IF(ClassBReturnPriority=1,MIN(MAX(0,WaterfallTable[[#This Row],[Cash Available]]-WaterfallTable[[#This Row],[Capital Returned A]]),WaterfallTable[[#This Row],[ Capital Balance B]]),0))) -> 0 | M13: =IF(WaterfallTable[[#This Row],[Year]]>SaleExitYear,0,IF(WaterfallTable[[#This Row],[Year]]=0,0,MAX(0,WaterfallTable[[#This Row],[Cash Available]]-WaterfallTable[[#This Row],[Capital Returned A]]-WaterfallTable[[#This Row],[Capital Returned B]]-WaterfallTable[[#This Row],[Pref Paid]])*ClassBResidualShare)) -> 0 | N13: =IF(WaterfallTable[[#This Row],[Year]]>SaleExitYear,0,WaterfallTable[[#This Row],[Capital Returned B]]+WaterfallTable[[#This Row],[ Residual B]]) -> 0 | O13: =IF(WaterfallTable[[#This Row],[Year]]>SaleExitYear,0,IF(WaterfallTable[[#This Row],[Year]]=0,SponsorPropertyPayment,0)) -> 0 | P13: =IF(WaterfallTable[[#This Row],[Year]]>SaleExitYear,0,IF(WaterfallTable[[#This Row],[Year]]=0,0,MAX(0,WaterfallTable[[#This Row],[Cash Available]]-WaterfallTable[[#This Row],[Capital Returned A]]-WaterfallTable[[#This Row],[Capital Returned B]]-WaterfallTable[[#This Row],[Pref Paid]])*SponsorResidualShare)) -> 0 | Q13: =IF(WaterfallTable[[#This Row],[Year]]>SaleExitYear,0,WaterfallTable[[#This Row],[Property Payment]]+WaterfallTable[[#This Row],[Residual]]) -> 0
B14: 10 | C14: =IF(WaterfallTable[[#This Row],[Year]]>SaleExitYear,0,INDEX(AnnualModelTable[Cash Available Before Distributions],MATCH(WaterfallTable[[#This Row],[Year]],AnnualModelTable[Year],0))) -> 0 | D14: =IF(WaterfallTable[[#This Row],[Year]]>SaleExitYear,0,WaterfallTable[[#This Row],[Capital Balance A]]*ClassAPreferredReturn) -> 0 | E14: =IF(WaterfallTable[[#This Row],[Year]]>SaleExitYear,0,IF(WaterfallTable[[#This Row],[Year]]=0,0,MIN(MAX(0,WaterfallTable[[#This Row],[Cash Available]]-WaterfallTable[[#This Row],[Capital Returned A]]-WaterfallTable[[#This Row],[Capital Returned B]]),INDEX(WaterfallTable[End of Year Pref Balance],MATCH(WaterfallTable[[#This Row],[Year]]-1,WaterfallTable[Year],0))+WaterfallTable[[#This Row],[Pref Accrued]]))) -> 0 | F14: =IF(WaterfallTable[[#This Row],[Year]]>SaleExitYear,0,MAX(0,IF(WaterfallTable[[#This Row],[Year]]=0,0,INDEX(WaterfallTable[End of Year Pref Balance],MATCH(WaterfallTable[[#This Row],[Year]]-1,WaterfallTable[Year],0)))+WaterfallTable[[#This Row],[Pref Accrued]]-WaterfallTable[[#This Row],[Pref Paid]])) -> 0 | G14: =IF(WaterfallTable[[#This Row],[Year]]>SaleExitYear,0,IF(WaterfallTable[[#This Row],[Year]]=0,ClassACapital,MAX(0,INDEX(WaterfallTable[Capital Balance A],MATCH(WaterfallTable[[#This Row],[Year]]-1,WaterfallTable[Year],0))-INDEX(WaterfallTable[Capital Returned A],MATCH(WaterfallTable[[#This Row],[Year]]-1,WaterfallTable[Year],0))))) -> 0 | H14: =IF(WaterfallTable[[#This Row],[Year]]>SaleExitYear,0,IF(WaterfallTable[[#This Row],[Year]]=0,0,MIN(WaterfallTable[[#This Row],[Cash Available]],WaterfallTable[[#This Row],[Capital Balance A]]))) -> 0 | I14: =IF(WaterfallTable[[#This Row],[Year]]>SaleExitYear,0,IF(WaterfallTable[[#This Row],[Year]]=0,0,MAX(0,WaterfallTable[[#This Row],[Cash Available]]-WaterfallTable[[#This Row],[Capital Returned A]]-WaterfallTable[[#This Row],[Capital Returned B]]-WaterfallTable[[#This Row],[Pref Paid]])*ClassAResidualShare)) -> 0 | J14: =IF(WaterfallTable[[#This Row],[Year]]>SaleExitYear,0,WaterfallTable[[#This Row],[Pref Paid]]+WaterfallTable[[#This Row],[Capital Returned A]]+WaterfallTable[[#This Row],[Residual A]]) -> 0 | K14: =IF(WaterfallTable[[#This Row],[Year]]>SaleExitYear,0,IF(WaterfallTable[[#This Row],[Year]]=0,ClassBCapital,MAX(0,INDEX(WaterfallTable[ [ Capital Balance B] ],MATCH(WaterfallTable[[#This Row],[Year]]-1,WaterfallTable[Year],0))-INDEX(WaterfallTable[Capital Returned B],MATCH(WaterfallTable[[#This Row],[Year]]-1,WaterfallTable[Year],0))))) -> 0 | L14: =IF(WaterfallTable[[#This Row],[Year]]>SaleExitYear,0,IF(WaterfallTable[[#This Row],[Year]]=0,0,IF(ClassBReturnPriority=1,MIN(MAX(0,WaterfallTable[[#This Row],[Cash Available]]-WaterfallTable[[#This Row],[Capital Returned A]]),WaterfallTable[[#This Row],[ Capital Balance B]]),0))) -> 0 | M14: =IF(WaterfallTable[[#This Row],[Year]]>SaleExitYear,0,IF(WaterfallTable[[#This Row],[Year]]=0,0,MAX(0,WaterfallTable[[#This Row],[Cash Available]]-WaterfallTable[[#This Row],[Capital Returned A]]-WaterfallTable[[#This Row],[Capital Returned B]]-WaterfallTable[[#This Row],[Pref Paid]])*ClassBResidualShare)) -> 0 | N14: =IF(WaterfallTable[[#This Row],[Year]]>SaleExitYear,0,WaterfallTable[[#This Row],[Capital Returned B]]+WaterfallTable[[#This Row],[ Residual B]]) -> 0 | O14: =IF(WaterfallTable[[#This Row],[Year]]>SaleExitYear,0,IF(WaterfallTable[[#This Row],[Year]]=0,SponsorPropertyPayment,0)) -> 0 | P14: =IF(WaterfallTable[[#This Row],[Year]]>SaleExitYear,0,IF(WaterfallTable[[#This Row],[Year]]=0,0,MAX(0,WaterfallTable[[#This Row],[Cash Available]]-WaterfallTable[[#This Row],[Capital Returned A]]-WaterfallTable[[#This Row],[Capital Returned B]]-WaterfallTable[[#This Row],[Pref Paid]])*SponsorResidualShare)) -> 0 | Q14: =IF(WaterfallTable[[#This Row],[Year]]>SaleExitYear,0,WaterfallTable[[#This Row],[Property Payment]]+WaterfallTable[[#This Row],[Residual]]) -> 0
B17: Returns Summary
B18: Participant | C18: Capital Investment | D18: Basis / Property Payment | E18: Initial Capitalization | F18: Year 1 | G18: Year 2 | H18: Year 3 | I18: Year 4 | J18: Year 5 | K18: Year 6 | L18: Year 7 | M18: Year 8 | N18: Year 9 | O18: Year 10 | P18: Total Profit | Q18: Total Dist | R18: Equity Multiple | S18: ROI % | T18: IRR
B19: Class A | C19: =ClassACapital -> 300000 | D19: =ClassACapital -> 300000 | E19: =-ReturnsTable[[#This Row],[Capital Investment]] -> -300000 | F19: =IF(1>SaleExitYear,0,INDEX(WaterfallTable[Total Dist A],MATCH(1,WaterfallTable[Year],0))) -> 2521.3621 | G19: =IF(2>SaleExitYear,0,INDEX(WaterfallTable[Total Dist A],MATCH(2,WaterfallTable[Year],0))) -> 52293.821 | H19: =IF(3>SaleExitYear,0,INDEX(WaterfallTable[Total Dist A],MATCH(3,WaterfallTable[Year],0))) -> 245184.82 | I19: =IF(4>SaleExitYear,0,INDEX(WaterfallTable[Total Dist A],MATCH(4,WaterfallTable[Year],0))) -> 0 | J19: =IF(5>SaleExitYear,0,INDEX(WaterfallTable[Total Dist A],MATCH(5,WaterfallTable[Year],0))) -> 264666.01 | K19: =IF(6>SaleExitYear,0,INDEX(WaterfallTable[Total Dist A],MATCH(6,WaterfallTable[Year],0))) -> 0 | L19: =IF(7>SaleExitYear,0,INDEX(WaterfallTable[Total Dist A],MATCH(7,WaterfallTable[Year],0))) -> 0 | M19: =IF(8>SaleExitYear,0,INDEX(WaterfallTable[Total Dist A],MATCH(8,WaterfallTable[Year],0))) -> 0 | N19: =IF(9>SaleExitYear,0,INDEX(WaterfallTable[Total Dist A],MATCH(9,WaterfallTable[Year],0))) -> 0 | O19: =IF(10>SaleExitYear,0,INDEX(WaterfallTable[Total Dist A],MATCH(10,WaterfallTable[Year],0))) -> 0 | P19: =SUM(ReturnsTable[[#This Row],[Initial Capitalization]:[Year 10]]) -> 264666.01 | Q19: =ReturnsTable[[#This Row],[Total Profit]]+ReturnsTable[[#This Row],[Capital Investment]] -> 564666.01 | R19: =IFERROR(ReturnsTable[[#This Row],[Total Dist]]/ReturnsTable[[#This Row],[Capital Investment]],0) -> 1.88222 | S19: =IFERROR(ReturnsTable[[#This Row],[Total Profit]]/ReturnsTable[[#This Row],[Capital Investment]],0) -> 0.88222003 | T19: =IFERROR(IRR(ReturnsTable[[#This Row],[Initial Capitalization]:[Year 10]]),0) -> 0.18498026
B20: Class B | C20: =ClassBCapital -> 547500 | D20: =ClassBCapital -> 547500 | E20: =-ReturnsTable[[#This Row],[Capital Investment]] -> -547500 | F20: =IF(1>SaleExitYear,0,INDEX(WaterfallTable[Total Dist B],MATCH(1,WaterfallTable[Year],0))) -> 0 | G20: =IF(2>SaleExitYear,0,INDEX(WaterfallTable[Total Dist B],MATCH(2,WaterfallTable[Year],0))) -> 0 | H20: =IF(3>SaleExitYear,0,INDEX(WaterfallTable[Total Dist B],MATCH(3,WaterfallTable[Year],0))) -> 323159.79 | I20: =IF(4>SaleExitYear,0,INDEX(WaterfallTable[Total Dist B],MATCH(4,WaterfallTable[Year],0))) -> 30068.166 | J20: =IF(5>SaleExitYear,0,INDEX(WaterfallTable[Total Dist B],MATCH(5,WaterfallTable[Year],0))) -> 510458.65 | K20: =IF(6>SaleExitYear,0,INDEX(WaterfallTable[Total Dist B],MATCH(6,WaterfallTable[Year],0))) -> 0 | L20: =IF(7>SaleExitYear,0,INDEX(WaterfallTable[Total Dist B],MATCH(7,WaterfallTable[Year],0))) -> 0 | M20: =IF(8>SaleExitYear,0,INDEX(WaterfallTable[Total Dist B],MATCH(8,WaterfallTable[Year],0))) -> 0 | N20: =IF(9>SaleExitYear,0,INDEX(WaterfallTable[Total Dist B],MATCH(9,WaterfallTable[Year],0))) -> 0 | O20: =IF(10>SaleExitYear,0,INDEX(WaterfallTable[Total Dist B],MATCH(10,WaterfallTable[Year],0))) -> 0 | P20: =SUM(ReturnsTable[[#This Row],[Initial Capitalization]:[Year 10]]) -> 316186.6 | Q20: =ReturnsTable[[#This Row],[Total Profit]]+ReturnsTable[[#This Row],[Capital Investment]] -> 863686.6 | R20: =IFERROR(ReturnsTable[[#This Row],[Total Dist]]/ReturnsTable[[#This Row],[Capital Investment]],0) -> 1.5775098 | S20: =IFERROR(ReturnsTable[[#This Row],[Total Profit]]/ReturnsTable[[#This Row],[Capital Investment]],0) -> 0.57750978 | T20: =IFERROR(IRR(ReturnsTable[[#This Row],[Initial Capitalization]:[Year 10]]),0) -> 0.11563386
B21: Sponsor | C21: =SponsorCapitalInvestment -> 136283 | D21: =SponsorBasis -> 100000 | E21: =INDEX(WaterfallTable[Total Dist2],MATCH(0,WaterfallTable[Year],0))-ReturnsTable[[#This Row],[Capital Investment]] -> -36283 | F21: =IF(1>SaleExitYear,0,INDEX(WaterfallTable[Total Dist2],MATCH(1,WaterfallTable[Year],0))) -> 0 | G21: =IF(2>SaleExitYear,0,INDEX(WaterfallTable[Total Dist2],MATCH(2,WaterfallTable[Year],0))) -> 0 | H21: =IF(3>SaleExitYear,0,INDEX(WaterfallTable[Total Dist2],MATCH(3,WaterfallTable[Year],0))) -> 0 | I21: =IF(4>SaleExitYear,0,INDEX(WaterfallTable[Total Dist2],MATCH(4,WaterfallTable[Year],0))) -> 0 | J21: =IF(5>SaleExitYear,0,INDEX(WaterfallTable[Total Dist2],MATCH(5,WaterfallTable[Year],0))) -> 489439.54 | K21: =IF(6>SaleExitYear,0,INDEX(WaterfallTable[Total Dist2],MATCH(6,WaterfallTable[Year],0))) -> 0 | L21: =IF(7>SaleExitYear,0,INDEX(WaterfallTable[Total Dist2],MATCH(7,WaterfallTable[Year],0))) -> 0 | M21: =IF(8>SaleExitYear,0,INDEX(WaterfallTable[Total Dist2],MATCH(8,WaterfallTable[Year],0))) -> 0 | N21: =IF(9>SaleExitYear,0,INDEX(WaterfallTable[Total Dist2],MATCH(9,WaterfallTable[Year],0))) -> 0 | O21: =IF(10>SaleExitYear,0,INDEX(WaterfallTable[Total Dist2],MATCH(10,WaterfallTable[Year],0))) -> 0 | P21: =SUM(ReturnsTable[[#This Row],[Initial Capitalization]:[Year 10]]) -> 453156.54 | Q21: =ReturnsTable[[#This Row],[Total Profit]]+ReturnsTable[[#This Row],[Capital Investment]] -> 589439.54 | R21: =IFERROR(ReturnsTable[[#This Row],[Total Dist]]/ReturnsTable[[#This Row],[Capital Investment]],0) -> 4.3251142 | S21: =IFERROR(ReturnsTable[[#This Row],[Total Profit]]/ReturnsTable[[#This Row],[Capital Investment]],0) -> 3.3251142 | T21: =IFERROR(IRR(ReturnsTable[[#This Row],[Initial Capitalization]:[Year 10]]),0) -> 0.68267085
B22: Management | C22: =0 -> 0 | D22: =0 -> 0 | E22: =0 -> 0 | F22: =IF(1>SaleExitYear,0,ManagementFeeRate*INDEX(AnnualModelTable[Occupancy Effective Gross Income],MATCH(1,AnnualModelTable[Year],0))) -> 2863.2 | G22: =IF(2>SaleExitYear,0,ManagementFeeRate*INDEX(AnnualModelTable[Occupancy Effective Gross Income],MATCH(2,AnnualModelTable[Year],0))) -> 7471.341 | H22: =IF(3>SaleExitYear,0,ManagementFeeRate*INDEX(AnnualModelTable[Occupancy Effective Gross Income],MATCH(3,AnnualModelTable[Year],0))) -> 9675.72 | I22: =IF(4>SaleExitYear,0,ManagementFeeRate*INDEX(AnnualModelTable[Occupancy Effective Gross Income],MATCH(4,AnnualModelTable[Year],0))) -> 9675.72 | J22: =IF(5>SaleExitYear,0,ManagementFeeRate*INDEX(AnnualModelTable[Occupancy Effective Gross Income],MATCH(5,AnnualModelTable[Year],0))) -> 9675.72 | K22: =IF(6>SaleExitYear,0,ManagementFeeRate*INDEX(AnnualModelTable[Occupancy Effective Gross Income],MATCH(6,AnnualModelTable[Year],0))) -> 0 | L22: =IF(7>SaleExitYear,0,ManagementFeeRate*INDEX(AnnualModelTable[Occupancy Effective Gross Income],MATCH(7,AnnualModelTable[Year],0))) -> 0 | M22: =IF(8>SaleExitYear,0,ManagementFeeRate*INDEX(AnnualModelTable[Occupancy Effective Gross Income],MATCH(8,AnnualModelTable[Year],0))) -> 0 | N22: =IF(9>SaleExitYear,0,ManagementFeeRate*INDEX(AnnualModelTable[Occupancy Effective Gross Income],MATCH(9,AnnualModelTable[Year],0))) -> 0 | O22: =IF(10>SaleExitYear,0,ManagementFeeRate*INDEX(AnnualModelTable[Occupancy Effective Gross Income],MATCH(10,AnnualModelTable[Year],0))) -> 0 | P22: =SUM(ReturnsTable[[#This Row],[Initial Capitalization]:[Year 10]]) -> 39361.701 | Q22: =ReturnsTable[[#This Row],[Total Profit]] -> 39361.701 | R22: =0 -> 0 | S22: =0 -> 0 | T22: =0 -> 0
B25: Select | C25: Operating Scenario | F25: Description
C26: Base Co-Living / Medium-Term | F26: Existing co-living rent schedule remains controlling.
C27: One Floor STR + One Floor Co-Living | F27: One full floor rents weekly as STR; other floor remains co-living/medium-term.
C28: Whole Building STR | F28: Entire building rents weekly as STR.
B32: Participant Return Comparison by Rent Option
B33: Rent Option | E33: Participant | F33: Chart Label | K33: Total Profit | L33: ROI % | M33: IRR % | N33: Total Distributions
B34: Base Co-Living / Medium-Term | E34: Class A | F34: Base Co-Living / Medium-Term - Class A | K34: 219799.49 | L34: 0.73266495 | M34: 0.16342648 | N34: 519799.49
B35: Base Co-Living / Medium-Term | E35: Class B | F35: Base Co-Living / Medium-Term - Class B | K35: 234783.08 | L35: 0.42882755 | M35: 0.089826902 | N35: 782283.08
B36: Base Co-Living / Medium-Term | E36: Sponsor | F36: Base Co-Living / Medium-Term - Sponsor | K36: 327148.35 | L36: 2.4005074 | M36: 0.5854182 | N36: 463431.35
B37: One Floor STR + Co-Living | E37: Class A | F37: One Floor STR + Co-Living - Class A | K37: 264666.01 | L37: 0.88222003 | M37: 0.18498026 | N37: 564666.01
B38: One Floor STR + Co-Living | E38: Class B | F38: One Floor STR + Co-Living - Class B | K38: 316186.6 | L38: 0.57750978 | M38: 0.11563386 | N38: 863686.6
B39: One Floor STR + Co-Living | E39: Sponsor | F39: One Floor STR + Co-Living - Sponsor | K39: 453156.54 | L39: 3.3251142 | M39: 0.68267085 | N39: 589439.54
B40: Whole Building STR | E40: Class A | F40: Whole Building STR - Class A | K40: 278057.43 | L40: 0.92685811 | M40: 0.18919674 | N40: 578057.43
B41: Whole Building STR | E41: Class B | F41: Whole Building STR - Class B | K41: 338354.9 | L41: 0.61799983 | M41: 0.12146973 | N41: 885854.9
B42: Whole Building STR | E42: Sponsor | F42: Whole Building STR - Sponsor | K42: 487471.85 | L42: 3.5769087 | M42: 0.70563058 | N42: 623754.85

Sheet Returns
A1: Legacy Returns sheet retained for reference. Primary ReturnsTable is now on the Waterfall tab.
A3: Participant | B3: Capital / Basis | C3: Total Distributions | D3: Net Profit | E3: Equity Multiple | F3: ROI % | G3: IRR | H3: Year 0 | I3: Year 1 | J3: Year 2 | K3: Year 3 | L3: Year 4 | M3: Year 5 | N3: Year 6 | O3: Year 7 | P3: Year 8 | Q3: Year 9 | R3: Year 10
A4: Class A | B4: =ClassACapital -> 300000 | C4: =SUM(Waterfall!$J$4:$J$14) -> 564666.01 | D4: =C4-B4 -> 264666.01 | E4: =IFERROR(C4/B4,0) -> 1.88222 | F4: =IFERROR(D4/B4,0) -> 0.88222003 | G4: =IRR(H4:R4) -> 0.18498026 | H4: =-B4 -> -300000 | I4: =INDEX(Waterfall!$J$4:$J$14,MATCH(1,Waterfall!$B$4:$B$14,0)) -> 2521.3621 | J4: =INDEX(Waterfall!$J$4:$J$14,MATCH(2,Waterfall!$B$4:$B$14,0)) -> 52293.821 | K4: =INDEX(Waterfall!$J$4:$J$14,MATCH(3,Waterfall!$B$4:$B$14,0)) -> 245184.82 | L4: =INDEX(Waterfall!$J$4:$J$14,MATCH(4,Waterfall!$B$4:$B$14,0)) -> 0 | M4: =INDEX(Waterfall!$J$4:$J$14,MATCH(5,Waterfall!$B$4:$B$14,0)) -> 264666.01 | N4: =INDEX(Waterfall!$J$4:$J$14,MATCH(6,Waterfall!$B$4:$B$14,0)) -> 0 | O4: =INDEX(Waterfall!$J$4:$J$14,MATCH(7,Waterfall!$B$4:$B$14,0)) -> 0 | P4: =INDEX(Waterfall!$J$4:$J$14,MATCH(8,Waterfall!$B$4:$B$14,0)) -> 0 | Q4: =INDEX(Waterfall!$J$4:$J$14,MATCH(9,Waterfall!$B$4:$B$14,0)) -> 0 | R4: =INDEX(Waterfall!$J$4:$J$14,MATCH(10,Waterfall!$B$4:$B$14,0)) -> 0
A5: Class B | B5: =ClassBCapital -> 547500 | C5: =SUM(Waterfall!$N$4:$N$14) -> 863686.6 | D5: =C5-B5 -> 316186.6 | E5: =IFERROR(C5/B5,0) -> 1.5775098 | F5: =IFERROR(D5/B5,0) -> 0.57750978 | G5: =IFERROR(IRR(H5:R5),0) -> 0.11563386 | H5: =-B5 -> -547500 | I5: =INDEX(Waterfall!$N$4:$N$14,MATCH(1,Waterfall!$B$4:$B$14,0)) -> 0 | J5: =INDEX(Waterfall!$N$4:$N$14,MATCH(2,Waterfall!$B$4:$B$14,0)) -> 0 | K5: =INDEX(Waterfall!$N$4:$N$14,MATCH(3,Waterfall!$B$4:$B$14,0)) -> 323159.79 | L5: =INDEX(Waterfall!$N$4:$N$14,MATCH(4,Waterfall!$B$4:$B$14,0)) -> 30068.166 | M5: =INDEX(Waterfall!$N$4:$N$14,MATCH(5,Waterfall!$B$4:$B$14,0)) -> 510458.65 | N5: =INDEX(Waterfall!$N$4:$N$14,MATCH(6,Waterfall!$B$4:$B$14,0)) -> 0 | O5: =INDEX(Waterfall!$N$4:$N$14,MATCH(7,Waterfall!$B$4:$B$14,0)) -> 0 | P5: =INDEX(Waterfall!$N$4:$N$14,MATCH(8,Waterfall!$B$4:$B$14,0)) -> 0 | Q5: =INDEX(Waterfall!$N$4:$N$14,MATCH(9,Waterfall!$B$4:$B$14,0)) -> 0 | R5: =INDEX(Waterfall!$N$4:$N$14,MATCH(10,Waterfall!$B$4:$B$14,0)) -> 0
A6: Sponsor | B6: =SponsorBasis -> 100000 | C6: =SUM(Waterfall!$Q$4:$Q$14) -> 589439.54 | D6: =C6-B6 -> 489439.54 | E6: =IFERROR(C6/B6,0) -> 5.8943954 | F6: =IFERROR(D6/B6,0) -> 4.8943954 | G6: =IFERROR(IRR(H6:R6),0) -> 0.37385156 | H6: =-B6 -> -100000 | I6: =INDEX(Waterfall!$Q$4:$Q$14,MATCH(1,Waterfall!$B$4:$B$14,0)) -> 0 | J6: =INDEX(Waterfall!$Q$4:$Q$14,MATCH(2,Waterfall!$B$4:$B$14,0)) -> 0 | K6: =INDEX(Waterfall!$Q$4:$Q$14,MATCH(3,Waterfall!$B$4:$B$14,0)) -> 0 | L6: =INDEX(Waterfall!$Q$4:$Q$14,MATCH(4,Waterfall!$B$4:$B$14,0)) -> 0 | M6: =INDEX(Waterfall!$Q$4:$Q$14,MATCH(5,Waterfall!$B$4:$B$14,0)) -> 489439.54 | N6: =INDEX(Waterfall!$Q$4:$Q$14,MATCH(6,Waterfall!$B$4:$B$14,0)) -> 0 | O6: =INDEX(Waterfall!$Q$4:$Q$14,MATCH(7,Waterfall!$B$4:$B$14,0)) -> 0 | P6: =INDEX(Waterfall!$Q$4:$Q$14,MATCH(8,Waterfall!$B$4:$B$14,0)) -> 0 | Q6: =INDEX(Waterfall!$Q$4:$Q$14,MATCH(9,Waterfall!$B$4:$B$14,0)) -> 0 | R6: =INDEX(Waterfall!$Q$4:$Q$14,MATCH(10,Waterfall!$B$4:$B$14,0)) -> 0
A9: Important | B9: Class A preferred return is modeled as cumulative simple annual accrual on unrecovered Class A capital. After Class A and Class B capital are returned, Sponsor receives the editable Sponsor residual share. Class A and Class B split the remaining residual in proportion to their capital.

Sheet Notes
A1: Model Notes
A3: Purpose | B3: Calculates project-level cash available, then allocates distributions to Class A, Class B, and Sponsor through a simplified waterfall.
A4: Key editable cells | B4: Use the Assumptions tab, column B.
A5: Class A | B5: Modeled with 8% cumulative annual preferred return by default, then return of capital, then no residual share unless you revise the waterfall.
A6: Class B | B6: Modeled as subordinate capital that can receive capital back before residual distributions, plus residual participation.
A7: Sponsor | B7: Modeled using sponsor basis / deemed investment as the return denominator and sponsor residual share as the distribution source.
A8: Caution | B8: This workbook is for planning and discussion only. It is not legal, tax, securities, appraisal, or investment advice. Have counsel and CPA review before investor use.

Sheet Cost Analysis
A1: 3325 Banks Rd - Design, Development & Build Cost Analysis
A2: Status | B2: Planning estimate added 2026-05-11
A3: Source Markdown | B3: 04_Design_Development_and_Build_Cost_Analysis.md
B6: Select Scenario: | C6: Low
A7: Project Cost Case Summary | B7: Low | C7: High | E7: Case Selection | G7: =$C$6="Low" -> TRUE | H7: =$C$6="High" -> FALSE
A8: Sponsor-Controlled Case (from controlling bridge below) | B8: =B27 -> 847500 | C8: =C27 -> 1585000 | E8: Sponsor-Controlled | H8: =$E$8="Sponsor-Controlled" -> TRUE
A9: Outside-Market Benchmark (from outside-market subtotals below) | B9: =B41+B50+B59 -> 1880000 | C9: =C41+C50+C59 -> 4160000 | H9: =$E$8="Outside-Market Benchmark" -> FALSE
A10: Selected Total Project Cost | B10: =IF($C$6="Low",IF($E$8="Sponsor-Controlled",B8,B9),"") -> 847500 | C10: =IF($C$6="High",IF($E$8="Sponsor-Controlled",C8,C9),"") | G10: =IF($C$6="Low",B10,C10) -> 847500
A12: Selected Cost Metrics | B12: Low Case | C12: High Case
A14: Cost per SF at 5,000 SF | B14: =$G$10/5000 -> 169.5
A15: Cost per SF at 6,000 SF | B15: =$G$10/6000 -> 141.25
A17: Controlling Sponsor-Controlled Line-Item Bridge | B17: Low | C17: High
A18: Sponsor property payment | B18: =SponsorPropertyPayment -> 100000 | C18: =SponsorPropertyPayment -> 100000
A19: Design, entitlement, permits, and professional services | B19: 75000 | C19: 175000
A20: Development, financing, carrying, and administration | B20: 40000 | C20: 100000
A21: Construction-period insurance | B21: 7500 | C21: 10000
A22: Post-frame building shell and interior buildout | B22: 390000 | C22: 610000
A23: Sitework, access, grading, drainage, and parking | B23: 55000 | C23: 110000
A24: Private utilities, well, wastewater, and related infrastructure | B24: 90000 | C24: 225000
A25: Furnishings, fixtures, equipment, and turnover | B25: 30000 | C25: 100000
A26: Contingency and owner reserve | B26: 60000 | C26: 155000
A27: Sponsor-Controlled Total Package | B27: =SUM(B18:B26) -> 847500 | C27: =SUM(C18:C26) -> 1585000
A28: Funding Gap Analysis | B28: Selected
A29: Estimated total project cost | B29: =SelectedProjectCost -> 847500
A30: Class A + Class B capitalization | B30: =ClassACapital+ClassBCapital -> 847500
A31: Potential unfunded development gap | B31: =MAX(0,B29-B30) -> 0
A33: Outside Market - Design & Entitlement Detail | B33: Low | C33: High
A34: Architecture and building design | B34: 35000 | C34: 90000
A35: Civil engineering and site planning | B35: 20000 | C35: 60000
A36: Septic, soil, and wastewater engineering | B36: 20000 | C36: 90000
A37: Survey, testing, environmental, and due diligence | B37: 10000 | C37: 30000
A38: Permitting, review, and municipal/county coordination | B38: 15000 | C38: 50000
A39: Legal, accounting, and trust structuring | B39: 15000 | C39: 40000
A40: Design/entitlement contingency | B40: 15000 | C40: 45000
A41: Design & entitlement total | B41: =SUM(B34:B40) -> 130000 | C41: =SUM(C34:C40) -> 405000
A43: Outside Market - Development & Pre-Construction Detail | B43: Low | C43: High
A44: Development management / sponsor fee | B44: 50000 | C44: 150000
A45: Financing, lender, appraisal, and closing costs | B45: 40000 | C45: 120000
A46: Insurance, taxes, utilities, and carrying costs | B46: 25000 | C46: 75000
A47: Accounting, administration, and reporting | B47: 10000 | C47: 30000
A48: Leasing, operations setup, and launch costs | B48: 20000 | C48: 60000
A49: Development contingency / liquidity reserve | B49: 40000 | C49: 125000
A50: Development & pre-construction total | B50: =SUM(B44:B49) -> 185000 | C50: =SUM(C44:C49) -> 560000
A52: Outside Market - Build & Delivery Detail | B52: Low | C52: High
A53: Building construction, 5,000-6,000 SF | B53: 1125000 | C53: 1950000
A54: Sitework, grading, access, parking, and drainage | B54: 125000 | C54: 350000
A55: Private utilities and well infrastructure | B55: 35000 | C55: 125000
A56: Engineered onsite wastewater system | B56: 75000 | C56: 300000
A57: Furnishings, fixtures, equipment, and turnover | B57: 60000 | C57: 180000
A58: Construction contingency | B58: 145000 | C58: 290000
A59: Build & delivery total | B59: =SUM(B53:B58) -> 1565000 | C59: =SUM(C53:C58) -> 3195000
A61: Sponsor-Controlled Cost Justification
A62: Cost-positioning note | B62: 700,000-1,300,000 is a target range, not a guaranteed budget. It depends on post-frame construction, sponsor-owned equipment, sponsor-controlled crew capacity, disciplined finish scope, and avoiding a high-cost engineered wastewater outcome.
A65: Conditions Required To Support Target Range
A66: Post-frame approach accepted through design and permitting | B66: Yes | C66: Confirmed cost saver
A67: Sponsor can self-perform or directly manage meaningful construction scope | B67: Yes | C67: Confirmed cost saver
A68: Equipment ownership reduces sitework and construction logistics cost | B68: Yes | C68: Confirmed cost saver
A69: Major subcontracted trades are competitively bid | B69: Yes | C69: Confirmed cost saver
A70: Wastewater solution does not require a high-end engineered system | B70: No | C70: Not confirmed; risk reserve retained
A71: Suite count and bathroom/kitchenette count do not expand | B71: Yes | C71: Confirmed scope control
A72: Finish package stays durable and efficient rather than luxury | B72: Yes | C72: Confirmed finish discipline
A73: Project carries a disciplined contingency | B73: Yes | C73: Confirmed reserve discipline
A75: Risks That Could Break Target Range
A76: Advanced/high-cost wastewater system requirement | B76: Yes | C76: Confirmed risk; wastewater allowance increased
A77: Expensive fire, code, or occupancy upgrades | B77: No
A78: Higher-than-expected mechanical/electrical/plumbing scope | B78: No
A79: Extensive parking, drainage, or access improvements | B79: No
A80: Sponsor crew advantage limited by labor availability | B80: No
A81: Finish level moves closer to conventional apartment construction | B81: Yes | C81: Confirmed risk; FF&E/contingency allowance increased

Sheet Operating Expense Budget
A1: 3325 Banks Rd - Operating Expense Budget
A3: Toggle / Selection
A4: Use Calculated Budget Ratio? | C4: FALSE = use assumed ratio; TRUE = use calculated budget ratio | I4: TRUE
A5: Assumed Operating Expense Ratio | B5: 0.4 | C5: Current planning assumption reflected in Assumptions tab when toggle is FALSE
A6: Calculated Operating Expense Ratio | B6: =IFERROR(B36/B10,0) -> 0.46912485 | C6: Total annual operating expense budget / effective gross income
A7: Selected Operating Expense Ratio | B7: =IF(I4,B6,B5) -> 0.46912485 | C7: Feeds Assumptions!B15
A9: Revenue Basis
A10: Stabilized Effective Gross Income | B10: =StabilizedMonthlyGrossRent*12*StabilizedOccupancy -> 133920 | C10: Annual stabilized EGI after occupancy
A12: Expense Category | B12: Annual Amount | C12: Basis / Notes
A13: Property taxes | B13: 7000 | C13: Placeholder; replace with assessed value/tax estimate
A14: Completed property insurance | B14: 4350 | C14: Post-completion hazard/liability coverage estimate; excludes construction-period insurance
A15: Property management / administration | B15: =D15*B10 -> 8035.2 | C15: 6% of stabilized effective gross income (EGI) | D15: 0.06
A16: Utilities - electric | B16: =600*12 -> 7200 | C16: Owner-paid/common-area and vacancy exposure
A17: Utilities - water / well maintenance | B17: 500 | C17: Well testing, maintenance, treatment allowance
A18: Utilities - internet | B18: 2400 | C18: Shared/furnished rental expectation
A19: Trash / recycling | B19: 1800 | C19: Recurring service
A20: Repairs & maintenance reserve | B20: 9000 | C20: Annual reserve target funded before waterfall distributions; once funded, excess cash flows through waterfall
A21: Turnover, cleaning, and supplies | B21: =200*8 -> 1600 | C21: Co-living/furnished turnover allowance
A22: Landscaping / grounds | B22: =90*20 -> 1800 | C22: Mowing, upkeep, seasonal cleanup
A23: Pest control | B23: 600 | C23: Recurring service
A24: Septic / wastewater maintenance | B24: 1000 | C24: Inspection, pump, service contracts
A25: CapEx / replacement reserve | B25: 4000 | C25: Furniture, fixtures, equipment, building reserves
A26: Marketing / leasing | B26: 0 | C26: Listings, tenant placement, materials
A27: Bookkeeping / accounting | B27: =120*12 -> 1440 | C27: Operating accounting/reporting
A28: Legal / compliance | C28: Lease forms, notices, compliance allowance
A29: Licenses, permits, inspections | B29: 1200 | C29: Recurring local/regulatory allowance
A30: Security / access control | C30: Locks, cameras, access systems, monitoring
A31: Common area furnishings replacement | B31: 2400 | C31: Shared space replacement reserve
A32: Laundry equipment maintenance | B32: 1200 | C32: Repair/replacement allowance
A33: Snow/ice/storm cleanup reserve | B33: 800 | C33: Weather/event allowance
A34: Bad debt / collections | B34: 2500 | C34: Collection loss allowance
A35: Miscellaneous / operating contingency | B35: 4000 | C35: Catch-all reserve
A36: Total Annual Operating Expense Budget | B36: =SUM(B13:B35) -> 62825.2 | C36: Calculated from line items
