Workbook
Name Milestone_Marker: 'Gnatt Chart'!$G$4
Name Project_Start: 'Gnatt Chart'!$F$2
Name Scrolling_Increment: 'Gnatt Chart'!$AB$26
Name Today: TODAY()

Sheet Profit
A1: Flip, Hold or Wholetale: | B1: flip | E1: Buy | F1: Your Home LLC
B2: 3325 Banks Rd, Raleigh, NC 27603 | H2: Monthly Cash Flow | J2: Hearing Date:
A3: Income | D3: Immediate | F3: Upon Sale
A4: CMA: | B4: 439000 | J4: Finalized: | K4: No | O4: Todays' date: | P4: =NOW() -> 46167.635
A5: % Above/Below Market Sale: | B5: -0.15 | C5: 0.1 | N5: Zillow | O5: 45161 | P5: 276600
A6: Sale Price: | B6: =+B4 + IF(B1="Hold",B4*C5,0) + IF(B1="wholetale",B4*B5,0) -> 439000 | G6: =IF($B$1="hold",$B$4,$B$6) -> 439000 | J6: Anuual Growth: | K6: 0.1
A7: NonRefundable Deposit: | D7: =+B7 -> 0 | F7: =-B7 -> 0 | G7: =+IF($B$1="hold",$K$6,0)*$C$35/12*B4 -> 0 | H7: =+IF($B$1="hold","<-- Apprication -----------","")
A8: Rent: | B8: 2000 | I8: =IF(B1="Hold",+B8,"") | J8: Sq Footage | K8: 1899
C9: Net Income: | D9: Net Income: | E9: =SUM(D4:D8) -> 0 | F9: =+SUM(F4:G8) -> 439000 | H9: =SUM(H4:I8) -> 0
A11: Expenses
A12: Reinstatment Cost 1st: | B12: 12645 | D12: =-B12 -> -12645 | G12: =IF(K4="Yes",0.3*B12,"") | H12: <-- Approx Pay-Down | J12: If the Subject To Value is finalized, zero-out the Pay-Down savings
A13: Subject To 1st:Truist | B13: 0.03125 | C13: 125037.73 | F13: =-C13 -> -125037.73
A14: Reinstatment Cost 2st: | F14: =-+(120-C34)*(C14/120) -> 0 | H14: =-(C14*B14/12) -> 0
A15: Subject To 2st:Notes | B15: 0.1 | F15: =-C15 -> 0 | H15: =-C15/120-(C15*B15/12) -> 0
A16: Liens - IRS & HOA | D16: =-C16 -> 0
A17: Partners Share % | B17: 0
A18: or Seller Payout: | B18: 10000 | D18: =-B18 -> -10000 | J18: Yellow cells can be edited
A19: HOA Fees(Catch Up) | C19: 0 | D19: =-B19 -> 0
A20: Months Carried | B20: =+F57/30 -> 59.2 | J20: Do not edit Green cells. They are highlighted only to show profit
A21: Mortgage Payment: | B21: =+Carrying!H$88/$B$20 -> 1178.3024 | H21: =IF(B1="Hold",-B21,"")
A22: Mortgage Payment - 2nd: | H22: =IF(B1="Hold",-B22,"")
A23: Property Insurance | B23: =+Carrying!L$88/$B$20 -> 87.344764 | H23: =IF(B1="Hold",-B23,"")
A24: HOA Fees (monthly) | H24: =IF(B1="Hold",-B24,"")
A25: Electric | B25: =+Carrying!D$88/$B$20 -> 12.24375
A26: water | O26: 1st Mortgage | P26: =+C13 -> 125037.73
A27: Carrying Cost | B27: =+B20*SUM(B21:B26) -> 75651.14 | D27: =-B27 -> -75651.14 | J27: Purchase Cost | K27: =+SUM(B12:C16)+B18 -> 147682.86 | N27: Private Lender | O27: Neal Issacs | P27: 75000
A28: Private Lender Rate: | B28: 0.1 | C28: yes
A29: 75%ARV-Debt: | B29: =IF(C28="NO",0,+(B6*0.75)-(C13+C14+C15)) -> 204212.27 | E29: 75000 | F29: =IF(C28="No","",-E29-(B20*E29*B28/12)) -> -112000 | H29: =-IF($B$1="Hold",E29*B28/12,0) -> 0 | J29: Out of Pocket | K29: =+B12+C14+C16+B18+B30 -> 54069.184
A30: Rehab: | B30: =-D51 -> 31424.184 | D30: =-B30 -> -31424.184 | M30: =+K27+B30 -> 179107.05
A31: Marketing: | B31: 600 | D31: =-B31 -> -600 | J31: PL Balance +Interest | Q31: =SUM(P26:P30) -> 200037.73
A32: Seller Realtor's Flat Fee | B32: 1 | C32: =+B32*399 -> 399 | F32: =-C32 -> -399
A33: Seller Realtor's Fee Percent: | B33: 0 | C33: 0.026 | F33: =-B33*C33*$F$9 -> 0
A34: Buyers Realtors Fee Percent: | B34: 1 | C34: 0.024 | F34: =-B34*C34*$F$9 -> -10536
A35: Number of Rent Payments : | C35: 12
A36: Buyer Assistance | F36: =-C36 -> 0
A37: Buying Closing Cost: | B37: =+D71 -> 5998 | D37: =-B37 -> -5998
A38: Selling Closing Cost: | B38: =+D82 -> 290 | F38: =-B38 -> -290
C39: Net Expenses: | E39: =+SUM(D12:D38) -> -136318.32 | F39: =+SUM(F12:F38) -> -248262.73 | H39: =+SUM(H9:I38) -> 0
B40: Immediate Profit: | E40: =+SUM(E9:E39) -> -61318.324 | F40: =+SUM(F9:G38) -> 190737.27
E41: Long Term Profit: | G41: =+E40+F40 -> 129418.95 | J41: Partners Profit Share | K41: Our Profit Share
E42: Cash Flow Profit for Months: | H42: =IF(B1="Hold",C35,0) -> 0 | I42: =+H42*H39 -> 0
F43: Gross Profit: | I43: =+I42+G41 -> 129418.95 | J43: =$B$17*$I$43 -> 0 | K43: =+$I$43-J43 -> 129418.95
A44: Capital Gains Tax | B44: 0 | H44: Capital Gains | J44: =IF(B44="",0,-$B$44*J43) -> 0 | K44: =IF(B44="",0,-$B$44*K43) -> 0
A45: Chartiable Contribution: | B45: 0.1 | C45: 0.15 | D45: =+K45*B45 -> 12941.895 | H45: Gross Profit: | J45: =+J43+J44 -> 0 | K45: =+K43+K44 -> 129418.95
A47: Rehab Cost Detail
A48: Gnatt Chart | B48: =+'Gnatt Chart'!J5 -> 28567.44 | D48: =-B48 -> -28567.44
A49: Murphy %: | B49: 0.1 | G49: Murphy will be Zeroed-Out whe project is finalized
A50: Murphy's Cut: | B50: =IF(K4<>"Yes",+B49*SUM(B48:C48),0) -> 2856.744 | D50: =-B50 -> -2856.744
A51: Rehab Summary: | D51: =+SUM(D48:E50) -> -31424.184 | G51: This value is carried up to cell C29, Labeled Rehab
A52: Buying Closing Cost
A53: Settlement Fee to Attorney: | B53: 650
A54: Probate Attorney | B54: 5000
A55: Seller Doc Prep | B55: 250
A56: Seller Doc Prep | F56: Days Invested | H56: Start Date | J56: End Date
A57: Wire Fee | F57: =_xlfn.DAYS(J57,H57) -> 1776 | H57: 44391 | J57: =NOW() -> 46167.635
A58: Wire Fee
A59: Deed Package:
A60: Indemnety:
A61: Ttitle Search:
A62: Cancelation Fee:
A63: Overnight Express Fees:
A64: Title Insurance: | B64: 66
A65: Affadavits:
A66: Notice to Creditors Ad
A67: Recording Fee Deed: | B67: 26
A68: Transfer Taxes - Wake County | B68: 6
A69: Revenue Stamps
A70: LLC Manager Fee
D71: =+SUM(B53:C70) -> 5998 | G71: This value is carried up to cell C36, Labeled Buying Closing Cost
A73: Selling Closing Cost
A74: Settlement Fee to Attorney:
A75: Seller Doc Prep | B75: 250
A76: Seller concesson: | B76: 0
A77: Home Warrenty:
A78: Recording Fee Deed:
A79: Transfer Taxes - Wake County | B79: 40
A80: Revenue Stamps
A81: LLC Manager Fee
D82: =+SUM(B74:C81) -> 290 | G82: This value is carried up to cell C37, Labeled Selling Closing Cost

Sheet MOG
C1: Multiple Offer Generator | I1: ="Hi "&B3 & IF(B4 ="",""," and ") &B4&", Thank you for the opportunity to make an offer on your property at "&Profit!B2&". I have several options I would like for you to consider. I also want to give you several very good reasons for you to work with us here at Buy Your Home LLC. "&REPT(" ",6)&"1. If you sell your home to us, you will incur no expense from the transaction. We will pay all: "&REPT(" ",20)&"Closing Cost "&REPT(" ",20)&"Attorney's Fees "&REPT(" ",20)&"Realtor Commissions "&REPT(" ",6) &" 2. We can close fast. It will be a matter of days, probably less than two weeks, when we can "&REPT(" ",11) &"close at our attorney's office and get you your cash. "&REPT(" ",6) &"3. We cover the cost, time, and effort of paying any money due to any lender or HOA "&REPT(" ",11) &"involved." -> Hi Nikki, Thank you for the opportunity to make an offer on your property at 3325 Banks Rd, Raleigh, NC 27603. I have several options I would like for you to consider. I also want to give you several very good reasons for you to work with us here at Buy Your Home LLC. 1. If you sell your home to us, you will incur no expense from the transaction. We will pay all: Closing Cost Attorney's Fees Realtor Commissions 2. We can close fast. It will be a matter of days, probably less than two weeks, when we can close at our attorney's office and get you your cash. 3. We cover the cost, time, and effort of paying any money due to any lender or HOA involved. | J1: Buyers Copy | K1: =+I1&IF(N14="X",O14,"")&" "& IF(H15="X",I15,"") &" "& IF(H16="X",I16,"") &" "& IF(H20="X",I20,"") &" "& IF(H26="X",I26,"") &" "& IF(H33="X",I33,"") & " "& IF(H42="X",I42,"") & " "& IF(H52="X",I52,"") & " "& IF(H61="X",I61,"") & " "& IF(H74="X",I74,"") & " "& IF(H81="X",I81,"") & " "& IF(H82="X",I82,"") & " "& "" -> Hi Nikki, Thank you for the opportunity to make an offer on your property at 3325 Banks Rd, Raleigh, NC 27603. I have several options I would like for you to consider. I also want to give you several very good reasons for you to work with us here at Buy Your Home LLC. 1. If you sell your home to us, you will incur no expense from the transaction. We will pay all: Closing Cost Attorney's Fees Realtor Commissions 2. We can close fast. It will be a matter of days, probably less than two weeks, when we can close at our attorney's office and get you your cash. 3. We cover the cost, time, and effort of paying any money due to any lender or HOA involved. Here are some purchase options for your consideration. They are presented in summary form and I am sure you will have some questions that I will be happy to take time needed to answer. Each option below will have more value than the one above it. Option 1: Cash plus Assumption of Mortgage This is a cash payment, at closing. We will take responsibility for the existing mortgage, HOA fees, and any liens that may be discovered until we are able to resell the property. This offer is: Cash: $10,000.00 Total Value: $10,000.00 Option 2: Cash plus Promissory Note The explanation for the cash component is the same as for option 1. However, 20.% of the value of the offer will be cash and 80.% will be in the form of a promissory note, complete with a Deed of Trust. The note will have a 24-month term that will pay simple interest at the rate of 4% per year. Cash: $2,000.00 12 Month Note: $28,000.00 Interest Earned: $2,240.00 $93.33 per month Total Value: $32,240.00 Option 3: Cash plus Beneficial Interest in Trust The explanation for the cash component is the same as for option 2. Instead of a note as in Option 2, you will share in the profit earned when the property is resold. The property will be placed into a trust that you will share a beneficial interest in. The advantage here is you will benefit from the appreciated value of the property, over time. You will receive quarterly reports on the financial status of the property. Cash: $10,000.00 Interest in Trust: 70.% Expected Sellers Profit: $121,323.26 * Expected 10% appreciation per year Expected Value: $131,323.26 ** After 24 months. Nikki, this offer is contingent upon a normal due diligence period. The values of each option are predicated on some assumptions that may need to be altered upon further discovery. The more we can learn from you, in advance, the more reliable these options may be considered. When you decide which offer you prefer, I will email you a contract along with an earnest money payment. We are ready to be of service in any way we can. This offer is based on Zillow's Zestimate of $439,000.00. We will clean and prepare the property for a quick resale. There is also an assumption that the property will need no rehab. If that turns out to not be true, an allowance will need to be made. In any case, that will be decided in the due diligence period of the contract. Sincerely, Wes Browning (919) 899-2104
A3: Seller 1: | B3: Nikki | C3: Kulas | J3: no
A4: Seller 2:
A5: email:
A6: Phone #:
A9: Offer 1 | B9: Traditional, All Cash
B10: This is an all cash payment, at closing with no other allowances considered. Seller pays all Mortgages, liens, HOA expenses out of closings proceedings.
F12: Seller's Equity
B13: Sales Price | C13: ARV | D13: Debt | G13: BYH's Profit
B14: =+D14+F14 -> 146682.86 | C14: =+Profit!B4 -> 439000 | D14: =+Profit!K27-Profit!B18 -> 137682.86 | F14: =+B24-(B24*F16) -> 9000 | G14: =+C14-D14-F14+Profit!E39+Profit!B18 -> 165998.81
D15: BYH Out of Pocket: | E15: =+Profit!$K$29 -> 54069.184
D16: BYH Profit/Out of Pocket: | E16: =+G14/E15 -> 3.0701187 | F16: 0.1 | H16: X | I16: ="Here are some purchase options for your consideration. They are presented in summary form and I am sure you will have some questions that I will be happy to take time needed to answer. Each option below will have more value than the one above it." -> Here are some purchase options for your consideration. They are presented in summary form and I am sure you will have some questions that I will be happy to take time needed to answer. Each option below will have more value than the one above it.
D17: Buy Your Home's % of Profit: | E17: =+G14/(F14+G14) -> 0.94857108 | F17: less than Opt 2
A19: Offer 2 | B19: Cash plus Assumption of Mortgage | D19: *This is the default values from the Profit Sheet. | H19: =IF(H20="X",1,0) -> 0
B20: Cash payment in conjunction with taking the existing mortgage subject to: | I20: ="Option "&H19&": "&""&B9&" "&REPT(" ",6)&"This is a, traditional, all cash purchase, at closing with no other allowances considered. Seller "&REPT(" ",6)&"pays all mortgages, liens, HOA expenses, etc., out of closings disbursements. This option has " & REPT(" ",6) & "the smallest value for the seller. Our cash offer is: "&REPT(" ",43) &"Cash:"&REPT(" ",21)&+TEXT(B14,"$#,##0.00") & IF(J3="yes",REPT(" ",10) & "Profit = "& TEXT(G14,"$#,##0.00"),"" )& " "&REPT(" ",32) & "Total Value:"&REPT(" ",21)&TEXT(F14,"$#,##0.00") -> Option 0: Traditional, All Cash This is a, traditional, all cash purchase, at closing with no other allowances considered. Seller pays all mortgages, liens, HOA expenses, etc., out of closings disbursements. This option has the smallest value for the seller. Our cash offer is: Cash: $146,682.86 Total Value: $9,000.00
B21: After reinstating existing loans and HOA fees
F22: Seller's Total Value
B23: Cash | G23: BYH's Profit
B24: =+Profit!B18 -> 10000 | C24: <- The default value form profit sheet | F24: =+B24 -> 10000 | G24: =+Profit!K45+Profit!B18-B24 -> 129418.95
D25: BYH Out of Pocket: | E25: =+Profit!$K$29 -> 54069.184 | H25: =IF(H26="X",1+H19,H19) -> 1
D26: BYH Profit/Out of Pocket: | E26: =+G24/E25 -> 2.3935805 | H26: x | I26: ="Option " & H25 & ": "&""&B19&" "&REPT(" ",6) & "This is a cash payment, at closing. We will take responsibility for the existing mortgage, HOA "&REPT(" ",6) & "fees, and any liens that may be discovered until we are able to resell the property. This offer is: "&REPT(" ",43)&"Cash:"&REPT(" ",22) & TEXT(F24,"$#,##0.00") & IF(J3="yes",REPT(" ",10) & "Profit = "& TEXT(G24,"$#,##0.00"),"" ) & " "&REPT(" ",32)&"Total Value:"&REPT(" ",22) & TEXT(F24,"$#,##0.00") -> Option 1: Cash plus Assumption of Mortgage This is a cash payment, at closing. We will take responsibility for the existing mortgage, HOA fees, and any liens that may be discovered until we are able to resell the property. This offer is: Cash: $10,000.00 Total Value: $10,000.00
D27: Buy Your Home's % of Profit: | E27: =+G24/(F24+G24) -> 0.92827374
A30: Offer 3 | B30: Cash plus Promissory Note | D30: - this is the one to stear seller to:
B31: Cash payment in conjunction with taking the existing mortgage subject to: | I31: ="This is a cash payment, at closing, in conjunction with reinstating the existing mortgage taking responsibility for those payments, HOA fees and other liens that may be discovered. Our cash offer is:" -> This is a cash payment, at closing, in conjunction with reinstating the existing mortgage taking responsibility for those payments, HOA fees and other liens that may be discovered. Our cash offer is:
B32: After reinstating existing loans and HOA fees | H32: =IF(H33="X",H25+1,H25) -> 2
H33: x | I33: ="Option " & H32 & ": " &""&B30&" "&REPT(" ",6)&"The explanation for the cash component is the same as for option "& H25 & ". However, "&TEXT(B38,"##.#%") &" of the " & REPT(" ",6) & "value of the offer will be cash and "& TEXT(C38,"##.#%") &" will be in the form of a promissory note, complete " & REPT(" ",6) & "with a Deed of Trust. The note will have a " & D35 & "-month term that will pay simple interest at " & REPT(" ",6) & "the rate of "&E37*100&"% per year. "& REPT(" ",43) & "Cash:" & REPT(" ",23) & TEXT(B37,"$#,##0.00") & IF(J3="yes",REPT(" ",10) & "Profit = "& TEXT(G37,"$#,##0.00"),"" ) &" "& REPT(" ",24) & "12 Month Note:" & REPT(" ",24) & TEXT(C37,"$#,##0.00")&" "& REPT(" ",25) & "Interest Earned:" & REPT(" ",25) & TEXT(D37,"$#,##0.00") &REPT(" ",12)&+TEXT(D37/D35,"$#,##0.00") & " per month" & " "& REPT(" ",32) & "Total Value:" & REPT(" ",20) & TEXT(F37,"$#,##0.00") -> Option 2: Cash plus Promissory Note The explanation for the cash component is the same as for option 1. However, 20.% of the value of the offer will be cash and 80.% will be in the form of a promissory note, complete with a Deed of Trust. The note will have a 24-month term that will pay simple interest at the rate of 4% per year. Cash: $2,000.00 12 Month Note: $28,000.00 Interest Earned: $2,240.00 $93.33 per month Total Value: $32,240.00
C34: Note is a simple interest note for: | D34: Months | F34: (Based on Current Valuation)
B35: Value added to Note: | C35: 20000 | D35: 24 | F35: Seller's Total Value
B36: Cash | C36: Note | D36: Interest Earned | E36: Interest Rate | G36: BYH's Profit
B37: =+(Profit!$B$18)*B38 -> 2000 | C37: =+(Profit!$B$18)-B37+C35 -> 28000 | D37: =+C37*D35/12*E37 -> 2240 | E37: 0.04 | F37: =+SUM(B37:D37) -> 32240 | G37: =+Profit!$K$45-D37-C35 -> 107178.95
B38: 0.2 | C38: =1-B38 -> 0.8
D39: BYH Out of Pocket: | E39: =+Profit!$K$29-C37+C35 -> 46069.184
D40: BYH Profit/Out of Pocket: | E40: =+G37/E39 -> 2.3264781
D41: Buy Your Home's % of Profit: | E41: =+G37/(F37+G37) -> 0.76875453 | H41: =IF(H42="X",H32+1,H32) -> 3
A42: Offer 4 | B42: Cash plus Beneficial Interest in Trust | H42: x | I42: ="Option " & H41 & ": " & B42&" "&REPT(" ",6)&"The explanation for the cash component is the same as for option "& H32 & ". Instead of a note as in " & REPT(" ",6) & "Option "& H32 & ", you will share in the profit earned when the property is resold." &" The property will " & REPT(" ",6) & "be placed into a trust that you will share a beneficial interest in. The advantage here is you will " & REPT(" ",6) & "benefit from the appreciated value of the property, over time." &" You will receive quarterly " & REPT(" ",6) & "reports on the financial status of the property. "& REPT(" ",43) & "Cash:" & REPT(" ",23) & TEXT(B50,"$#,##0.00") & IF(J3="yes",REPT(" ",10) & "Profit = "& TEXT(G50,"$#,##0.00"),"" ) &" "& REPT(" ",24) & "Interest in Trust:" & REPT(" ",33) & TEXT(D50,"#.#%")&" "& REPT(" ",13) & "Expected Sellers Profit:" & REPT(" ",23) & TEXT(E50,"$#,##0.00") &" * Expected "&Profit!$K$6*100&"% appreciation per year" & " "& REPT(" ",26) & "Expected Value:" & REPT(" ",20) & TEXT(F50,"$#,##0.00") & " ** After " & D35 &" months." -> Option 3: Cash plus Beneficial Interest in Trust The explanation for the cash component is the same as for option 2. Instead of a note as in Option 2, you will share in the profit earned when the property is resold. The property will be placed into a trust that you will share a beneficial interest in. The advantage here is you will benefit from the appreciated value of the property, over time. You will receive quarterly reports on the financial status of the property. Cash: $10,000.00 Interest in Trust: 70.% Expected Sellers Profit: $121,323.26 * Expected 10% appreciation per year Expected Value: $131,323.26 ** After 24 months.
B43: Cash payment in conjunction with taking the existing mortgage subject to:
B44: After reinstating existing loans and HOA fees
B45: Profit split is a split of the profits upon the eventual sale of the pproperty.
B46: Profits will be calculated after deducting all expenses incurred from the sales price
F47: (Based on Future Valuation)
C48: Trust Future Profit | D48: Seller's Profit Sharing Percent | E48: Seller's Profit Share | F48: Seller's Total Value
B49: Cash | C49: Trust Future Profit | D49: Seller's Profit Sharing Percent | E49: Sellers Share Profit | G49: BYH's Profit
B50: 10000 | C50: =+Profit!$K$45+Profit!B18-B50+(Profit!K6*Profit!C35/12*Profit!B4) -> 173318.95 | D50: 0.7 | E50: =+D50*C50 -> 121323.26 | F50: =+B50+E50 -> 131323.26 | G50: =(1-D50)*C50 -> 51995.684
D51: *This precentage is not set in Profit sheet. It is for proposal only.
D52: BYH Out of Pocket: | E52: =+Profit!$K$29-B24+B50 -> 54069.184 | H52: X | I52: =B3 & ", this offer is contingent upon a normal due diligence period. The values of each option are predicated on some assumptions that may need to be altered upon further discovery. " & "The more we can learn from you, in advance, the more reliable these options may be considered. When you decide which offer you prefer, I will email you a contract along with an earnest money payment. We are ready to be of service in any way we can." -> Nikki, this offer is contingent upon a normal due diligence period. The values of each option are predicated on some assumptions that may need to be altered upon further discovery. The more we can learn from you, in advance, the more reliable these options may be considered. When you decide which offer you prefer, I will email you a contract along with an earnest money payment. We are ready to be of service in any way we can.
D53: BYH Profit/Out of Pocket: | E53: =+G50/E52 -> 0.96165098
D54: Buy Your Home's % of Profit: | E54: =+G50/(F50+G50) -> 0.28363508
B56: Personalize Note | D56: {alt}{enter] = carrage return
A57: ="This offer is based on Zillow's Zestimate of " & TEXT(Profit!B4,"$#,##0.00") & ". " & "We will clean and prepare the property for a quick resale. There is also an assumption that the property will need no rehab." & " If that turns out to not be true, an allowance will need to be made. In any case, that will be decided in the due diligence period of the contract. " & "" -> This offer is based on Zillow's Zestimate of $439,000.00. We will clean and prepare the property for a quick resale. There is also an assumption that the property will need no rehab. If that turns out to not be true, an allowance will need to be made. In any case, that will be decided in the due diligence period of the contract.
H61: X | I61: =A57 -> This offer is based on Zillow's Zestimate of $439,000.00. We will clean and prepare the property for a quick resale. There is also an assumption that the property will need no rehab. If that turns out to not be true, an allowance will need to be made. In any case, that will be decided in the due diligence period of the contract.
H74: X | I74: ="Sincerely, Wes Browning" -> Sincerely, Wes Browning
G81: Foreclosure Leads | I81: (919) 899-4954
G82: Liberty Leads | H82: X | I82: (919) 899-2104

Sheet Todo
B1: =+Profit!B2 -> 3325 Banks Rd, Raleigh, NC 27603 | D1: Notes | G1: 6004 Sandy Run | H1: Larchmont | I1: 2608 Alton | J1: 202 Avery | K1: 1900 Red Quartz | L1: 120 Keith | M1: 3007 Eric | N1: 2153 Haig Point | O1: 178 Patricia | P1: 1201 Hazelnut | Q1: 1223 Roffler | R1: 2025 Metacomet | S1: 5619 Marthonna
A2: New Seller
B3: Purchase & Sale Agreement | C3: Yes | H3: Yes
B4: Letter of Authorization | C4: Yes | H4: Yes (2)
B5: Reinstatement Quote | C5: Yes | H5: Yes (2)
B6: Bank Acknowledgement | C6: Yes | H6: yes
B7: On-Line Bank Access | C7: yes | H7: yes
B8: Change Mail | C8: yes | H8: yes
B9: Bank Attorney letter of dismisal | C9: na | H9: yes
B10: Get (orignal) Property Authorization | C10: na | H10: yes
H11: 0
A12: After Purchase | H12: 0
B13: Insurance Claim for Roof | C13: na | H13: yes
B14: Locks Changed | C14: na | H14: yes
B15: Gas Service | C15: na | H15: yes
B16: Electrical & Water Service | C16: yes | H16: yes
B17: Rehab bids | D17: In progress | H17: yes
B18: Order Dumpster | C18: yes | H18: n/a
B19: A/C service | C19: na | H19: yes
B20: Establish Mortgage payment | C20: yes | H20: yes
B21: Remove PMI | C21: na | H21: yes
B22: Claim Property on Zillow | C22: yes | H22: yes
B23: Add property to Our Website | C23: yes | H23: yes
B24: Make sure deed and agreement are done | C24: yes | H24: yes
B25: Change Insurance | C25: yes | H25: yes
B26: Get Insurance payments installed | C26: na | H26: yes
B27: Add Private Lender to Insurance | D27: In progess Add Scott Moore | H27: yes
B28: Probate letters - Notice to Creditors | C28: na | H28: yes
H29: 0
A30: Upon Sales Contract | B30: Send Clay contract | H30: 0
B31: Get Payoff Letter from Mortgage | H31: 0
B32: Respond to Closing Attorney | H32: 0
B33: Turn off utilities | H33: 0
B34: Alert Private Lenders | H34: 0
H35: 0
H36: 0
H37: 0
A38: Upon Closing | B38: Documents to send to Clay | H38: 0
B39: Alert Private Lenders | H39: 0
B40: Send Clay CD/Alta signed by all | H40: 0
B41: Drop Insurance | H41: 0
C43: Totals Across Projects | E43: =+B1 -> 3325 Banks Rd, Raleigh, NC 27603 | G43: 6004 Sandy Run | H43: Larchmont | I43: 2608 Alton | J43: 202 Avery | K43: =+K1 -> 1900 Red Quartz | L43: =+L1 -> 120 Keith | M43: =+M1 -> 3007 Eric | N43: =+N1 -> 2153 Haig Point | O43: =+O1 -> 178 Patricia | P43: =+P1 -> 1201 Hazelnut | Q43: =+Q1 -> 1223 Roffler | R43: =+R1 -> 2025 Metacomet | S43: =+S1 -> 5619 Marthonna
B44: Total CMA: | C44: =+SUM(E44:T44) -> 4285329 | E44: =+Profit!$B$4 -> 439000 | G44: 285000 | H44: 689000 | I44: 258000 | J44: 210000 | K44: 423529 | L44: 330000 | M44: 299000 | N44: 363900 | O44: 210000 | P44: 237900 | Q44: 150000 | R44: 195000 | S44: 195000
B45: Total Purchase Cost: | C45: =+SUM(E45:$T$45) -> 1182457.5 | E45: =+Profit!K27 -> 147682.86 | G45: 0 | H45: -334733.86 | I45: 102500 | J45: 127000 | K45: 174585.47 | L45: 85975.79 | M45: 167033.66 | N45: 220000 | O45: 107061.9 | P45: 74709 | Q45: 71644.86 | R45: 110309.86 | S45: 128687.99
B46: Total Rehab Expense: | C46: =+SUM(E46:T46) -> 717651.49 | E46: =+Profit!B30 -> 31424.184 | G46: 94360 | H46: 115791.71 | I46: 131036.72 | J46: 15000 | K46: 12223 | L46: 82805.727 | M46: 38679.38 | N46: 27507.698 | O46: 47760.57 | P46: 71081.807 | Q46: 6302.96 | R46: 20425.14 | S46: 23252.602
B47: Total Debt | C47: =+SUM(E47:T47) -> 200037.73 | E47: =+SUM(Profit!C13:C17)+Profit!E29 -> 200037.73
B48: Monthly Carring Cost: | C48: =+SUM(E48:T48) -> 1277.9909 | E48: =+Profit!B27/Profit!B20 -> 1277.8909 | G48: 0 | H48: 0.1
B49: Monthly Income: | C49: =+SUM(E49:N49) -> 0 | E49: =+Profit!H9 -> 0 | G49: 0 | H49: 0
B50: Total Expected Profit: | C50: =+SUM($E$50:$T$50) -> 864180.6 | E50: =+Profit!K45 -> 129418.95 | G50: 94360 | H50: 164326.05 | I50: 131036.72 | J50: 15000 | K50: 12223 | L50: 82805.727 | M50: 38679.38 | N50: 27507.698 | O50: 47760.57 | P50: 71081.807 | Q50: 6302.96 | R50: 20425.14 | S50: 23252.602
B51: Total Chartable Contribution: | C51: =+SUM($E$51:$T$51) -> 28412.698 | E51: =+E50*0.1 -> 12941.895 | K51: 15470.804
B52: Average CMA: | C52: =+AVERAGE(E44:S44) -> 306094.93
B53: Average Purchase Cost: | C53: =+AVERAGE(E45:S45) -> 84461.252 | L53: Uncompleted Project
B54: Average Rehab Expense: | C54: =+AVERAGE(E46:S46) -> 51260.821 | L54: Completed for Sell Your Home
B55: Average Profit: | C55: =+AVERAGE(D50:S50) -> 61727.186 | L55: Completed for Buy Your Home

Sheet Contact
A1: Vendor | B1: Phone Number | C1: Contact | D1: Acct/Policy | E1: Email | F1: Purpose
C2: Zola Turner | D2: SS#: 404-54-1686
C3: Karen Reilly | D3: SS#: 244-23-5473 | E3: Could be SS#: 244-23-5173
A5: Scooby Steve Power Wash | B5: 919-714-9713 | C5: Steve Simeus | F5: Power Wash | O5: Mortgagee | P5: Additional Insured | Q5: Loss Payee | R5: Lenders Loss Payee | S5: Certificate
A6: Braswell Realty | B6: 919-262-6828 | C6: Brantley Baker | E6: brantley@eldridgeandfranklin.com | F6: RE Investor - contacts | N6: Rushmore Loan Services | O6: X | P6: X | R6: X
B7: 919 579 8743 | E7: LaLogallazo@gmail.com | F7: Painter | N7: Neal Issacs | P7: X
A8: Handyman of Hedingham | B8: 919-819-6201 | C8: Tim Fleming | F8: Handyman | I8: Hedingham | N8: LoLa Turner | P8: X
A9: The Raleigh Handyman | B9: 919-210-1525 | C9: Alan C Thompson | E9: ac63yhompson@gmail.com | F9: Handyman | I9: Hedingham | N9: Scott Moore | P9: X
A10: Caliber Flooring, Inc | B10: 919-977-1153 | C10: Jennifer Lynn | F10: Flooring | I10: 1239 Wicker Drive | J10: Referral Sarah Huffman | N10: Rushmore Loan Services | O10: X | P10: X | R10: X
A11: Andy Carlson | B11: (213) 293-7539 | E11: andycarlson27@yahoo.com | N11: Neal Issacs | P11: X
N12: LoLa Turner | P12: X
A13: True Service Heating and AC | B13: 919 794 1804 | C13: Matt Truelove | E13: Matt@trueserviceinc.com | N13: Scott Moore | P13: X
A14: Walter Brothers | B14: 919 228 9107 | E14: Walter@GlasgowDB.com | N14: Rushmore Loan Services | S14: X
N15: Neal Issacs | S15: X
N16: LoLa Turner | S16: X
N17: Scott Moore | S17: X
A18: Rushmore Loan Mangement | B18: 888 504 6700
B19: 888 504 7200 | E19: User:WesWill@BuyYourHomeLLC.com | F19: PW:w3638B0@
A20: New Mortage Info: | B20: 877 888 4606 | D20: Loan #708108824 | E20: https://www.rushmoreservicing.com
E21: Rushmore Servicing
E22: Att: Payment Processing
E23: PO BOX 650783
E24: Dallas, TX 75265-0783
A26: 3rd party authorization | B26: Fax 949 341 2242 | C26: sent on 9/21/21 | E26: PW:W3638B0@
A27: Zola Turner | D27: SS# 404 54 1686
A28: Karen Reilly | D28: SS# 244 23 5473
A30: NREIG | B30: 770 734 1523 | C30: Jennifer Knight | D30: NRE8120320 | E30: https://nreig.com/contact/
A31: Insurance National Real Estate Insurance Group LLC | E31: Morgagee Clause: Truest Bank ISAOA/ATIMA, PO Box 47047,Atlanta GA, 30362
A33: juriscition | B33: Wake County
A34: Zoning | B34: R-30
A35: Acres | B35: 1.12

Sheet Carrying
A1: All Utilities | E1: Mortgage Payment paid after Reinstatement | J1: Insurance Payments | N1: Aqua America (Water)
A3: Utility | B3: Date | C3: Tax | F3: Date | G3: payment | J3: Date | K3: payment | N3: Date | O3: payment
A5: Duke | B5: 44482 | C5: 114.72 | F5: 44405 | G5: 724.38 | J5: 44565 | K5: 149.79
B6: =+B5+30 -> 44512 | C6: 30.06 | F6: 44440 | G6: 748.17 | J6: 44599 | K6: 149.79
B7: 44571 | C7: 30.21 | F7: 44461 | G7: 748.17 | J7: 44627 | K7: 149.79
B8: =+B7+30 -> 44601 | C8: 30.21 | F8: 44504 | G8: 748.17 | J8: 44656 | K8: 149.79
B9: =+B8+30 -> 44631 | C9: 30.39 | F9: 44524 | G9: 748.17 | J9: =+J8+30 -> 44686 | K9: 149.79
B10: 44648 | C10: 30.31 | F10: 44546 | G10: 748.17 | J10: 44713 | K10: 149.79
B11: 44712 | C11: 60.81 | F11: 44573 | G11: 748.17 | J11: =+J10+30 -> 44743 | K11: 149.79
B12: 44740 | C12: 30.39 | F12: 44588 | G12: 748.17 | J12: =+J11+30 -> 44773 | K12: 149.79
B13: 44776 | C13: 30.39 | F13: 44648 | G13: 748.17 | J13: 44809 | K13: 149.79
B14: 45041 | C14: 33.24 | F14: 44649 | G14: 748.17 | J14: =+J13+30 -> 44839 | K14: 149.79
B15: 45083 | C15: 30.61 | F15: =+F16-30 -> 44667 | G15: 749.94 | J15: =+J14+30 -> 44869 | K15: 149.79
B16: 45135 | C16: 7.74 | F16: 44697 | G16: 749.94 | J16: =+J15+30 -> 44899 | K16: 149.79
B17: 45166 | C17: 25.86 | F17: =+F18-30 -> 44745 | G17: 748.17 | J17: =+J16+30 -> 44929 | K17: 149.79
B18: 45195 | C18: 31.48 | F18: =+F19-30 -> 44775 | G18: 748.17 | J18: =+J17+30 -> 44959 | K18: 149.79
B19: =+B18+30 -> 45225 | C19: 32.12 | F19: 44805 | G19: 748.17 | J19: =+J18+30 -> 44989 | K19: 149.79
B20: 45329 | C20: 18.74 | F20: =+F5+30 -> 44435 | G20: 751.63 | J20: =+J19+30 -> 45019 | K20: 149.79
B21: 45364 | C21: 32.34 | F21: =+F20+30 -> 44465 | G21: =+G20 -> 751.63 | J21: =+J20+30 -> 45049 | K21: 149.79
B22: 45379 | C22: 32.34 | F22: 44896 | G22: =+G21 -> 751.63 | J22: 45078 | K22: 149.79
B23: 45400 | C23: 32.34 | F23: 44927 | G23: =+G22 -> 751.63 | J23: 45117 | K23: 222.97
B24: 45433 | C24: 32.34 | F24: =+F23+30 -> 44957 | G24: =+G23 -> 751.63 | J24: 45142 | K24: 222.97
B25: 45462 | C25: 32.34 | F25: =+F24+30 -> 44987 | G25: =+G24 -> 751.63 | J25: 45182 | K25: 222.97
B26: =+B25+30 -> 45492 | C26: 32.34 | F26: =+F25+30 -> 45017 | G26: =+G25 -> 751.63 | J26: 45202 | K26: 222.97
B27: 45524 | C27: -115.05 | F27: 45019 | G27: =+G26 -> 751.63 | J27: 45231 | K27: 222.97
B28: 45554 | C28: -115.05 | F28: =+F27+30 -> 45049 | G28: =+G27 -> 751.63 | J28: =+J27+30 -> 45261 | K28: 222.97
B29: 45586 | C29: -82.71 | F29: =+F28+30 -> 45079 | G29: =+G28 -> 751.63 | J29: 45292 | K29: 222.97
B30: 45615 | C30: -50.37 | F30: =+F29+30 -> 45109 | G30: =+G29 -> 751.63 | J30: 45323 | K30: 182.76
B31: 45644 | C31: -17.05 | F31: =+F30+30 -> 45139 | G31: =+G30 -> 751.63 | J31: =+J30+30 -> 45353 | K31: 182.76
B32: 45678 | C32: 16.39 | F32: =+F31+30 -> 45169 | G32: =+G31 -> 751.63 | J32: =+J31+30 -> 45383 | K32: 182.76
B33: 45708 | C33: -69.17 | F33: =+F32+30 -> 45199 | G33: =+G32 -> 751.63 | J33: =+J32+30 -> 45413 | K33: 182.76
B34: 45736 | C34: -36.46 | F34: =+F33+30 -> 45229 | G34: =+G33 -> 751.63 | K34: 182.76
B35: 45768 | C35: -3.75 | F35: =+F34+30 -> 45259 | G35: =+G34 -> 751.63
B36: 45797 | C36: 28.96 | F36: 45292 | G36: =+G35 -> 751.63
B37: 45827 | C37: 33.29 | F37: =+F36+30 -> 45322 | G37: =+G36 -> 751.63
B38: 45859 | C38: 32.71 | F38: =+F37+30 -> 45352 | G38: =+G37 -> 751.63
B39: 45889 | C39: 32.71 | F39: =+F38+30 -> 45382 | G39: =+G38 -> 751.63
B40: 45919 | C40: 32.71 | F40: =+F39+30 -> 45412 | G40: =+G39 -> 751.63
B41: 45951 | C41: 32.71 | F41: =+F40+30 -> 45442 | G41: =+G40 -> 751.63
B42: 45980 | C42: 32.71 | F42: =+F41+30 -> 45472 | G42: 782.96
B43: 46009 | C43: 33.75 | F43: =+F42+30 -> 45502 | G43: =+G42 -> 782.96
B44: 46043 | C44: 35.1 | F44: =+F43+30 -> 45532 | G44: =+G43 -> 782.96
B45: 46071 | C45: 35.52 | F45: =+F44+30 -> 45562 | G45: =+G44 -> 782.96
B46: 46100 | C46: 35.52 | F46: =+F45+30 -> 45592 | G46: =+G45 -> 782.96
B47: 46133 | C47: 35.52 | F47: =+F46+30 -> 45622 | G47: =+G46 -> 782.96
B48: 46161 | C48: 35.52 | F48: 45657 | G48: 966.22
F49: =+F48+30 -> 45687 | G49: =+G48 -> 966.22
F50: =+F49+30 -> 45717 | G50: =+G49 -> 966.22
F51: =+F50+30 -> 45747 | G51: =+G50 -> 966.22
F52: =+F51+30 -> 45777 | G52: =+G51 -> 966.22
F53: =+F52+30 -> 45807 | G53: =+G52 -> 966.22
F54: =+F53+30 -> 45837 | G54: =+G53 -> 966.22
F55: =+F54+30 -> 45867 | G55: =+G54 -> 966.22
F56: =+F55+30 -> 45897 | G56: =+G55 -> 966.22
F57: =+F56+30 -> 45927 | G57: =+G56 -> 966.22
F58: =+F57+30 -> 45957 | G58: =+G57 -> 966.22
F59: =+F58+30 -> 45987 | G59: =+G58 -> 966.22
F60: =+F59+30 -> 46017 | G60: =+G59 -> 966.22
... F64: =+F63+30 -> 46137 | G64: =+G63 -> 966.22
F65: 45807 | G65: 949.72
F66: =+F65+30 -> 45837 | G66: =+G65 -> 949.72
F67: =+F66+30 -> 45867 | G67: =+G66 -> 949.72
F68: =+F67+30 -> 45897 | G68: =+G67 -> 949.72
F69: =+F68+30 -> 45927 | G69: =+G68 -> 949.72
F70: =+F69+30 -> 45957 | G70: =+G69 -> 949.72
F71: =+F70+30 -> 45987 | G71: =+G70 -> 949.72
F72: =+F71+30 -> 46017 | G72: =+G71 -> 949.72
F73: =+F72+30 -> 46047 | G73: =+G72 -> 949.72
F74: =+F73+30 -> 46077 | G74: =+G73 -> 949.72
F75: =+F74+30 -> 46107 | G75: =+G74 -> 949.72
F76: =+F75+30 -> 46137 | G76: =+G75 -> 949.72
F77: =+F76+30 -> 46167 | G77: =+G76 -> 949.72
... F86: =+F85+30 -> 46437 | G86: =+G85 -> 949.72
D88: =SUM(C4:C87) -> 724.83 | H88: =SUM(G4:G87) -> 69755.5 | L88: =SUM(K4:K87) -> 5170.81 | P88: =SUM(O4:O87) -> 0

Sheet Proposal
B2: ="Preassigned Rows Indicating Payment or Scheduling by " &Profit!E1&" Your Home" -> Preassigned Rows Indicating Payment or Scheduling by Buy Your Home
B4: Preassigned Rows Cordination of Glasgow with Contrtactors
B6: Pasted rows from Builder's Trend Proposal
B8: Notes: Only add rows to the bottom of the table
A11: Cost Code | B11: Title | C11: Description | D11: Qty | E11: Unit Price
A12: Deposit | B12: Deposit | C12: Initial Deposit to Start Job | D12: 0
A13: Draw | B13: Draw 1 | C13: Draw 1 | D13: 0
A14: Draw | B14: Draw 2 | C14: Draw 2 | D14: 0
B15: Sell | C15: List with MLS | D15: 6
A16: HVAC | B16: Cordinate Sub | C16: HVAC | D16: 0 | E16: 0
A17: Floor Coverings | B17: Cordinate Sub | C17: Flooring Contractor | D17: 0 | E17: 200
A18: Supervision | B18: Cordinate Sub | C18: Termite Treatment | D18: 0 | E18: 200
A19: Cabinets & Vanities | B19: Cordinate Sub | C19: Cabinet Delivery | D19: 0 | E19: 200
A20: Countertops | B20: Cordinate Sub | C20: Manage installion of granite countertops by others in kitchen | D20: 0 | E20: 135
C21: Clean out House | D21: 1 | E21: 0
C22: Contract | D22: 0 | E22: 0
A23: Deck labor
A24: Deck labor
A25: Deck material
A26: ... Demo
A27: ... Demo
A28: ... Demo
A29: ... Demo
A30: Demo labor
A31: 20 Millwork & Trim
A32: 20 Millwork & Trim
A33: 20 Millwork & Trim
A34: 22 Specialty
... A37: Bath Accessories
A38: Building Permits | G38: 1160
A39: Cabinets & Vanities
A40: Electrical & Lighting
A41: Frame labor
A42: Frame labor
A43: Frame labor
A44: Frame labor
A45: Frame materials
A46: Frame materials
A47: Frame materials
A48: HVAC
A49: Insulation
A50: Insulation
... A70: Deck labor

Sheet ProposalUpdate
A1: These Cells are updated from the Proposal tab and are protected here. | I1: These cells are updated here and carried over to the Gnatt Chart | P1: Contracted Task | Q1: 1 | R1: Payment | S1: 4
P2: Change Order | Q2: 2 | R2: Not Used | S2: 0
P3: Manage Vendor | Q3: 3 | R3: Post Contract | S3: 5
A4: Party | B4: Item | C4: Cost Code | D4: Title | E4: Description | F4: Qty | G4: Unit Price | H4: Price | I4: Done | J4: Group Order | K4: Start Date | L4: Days | M4: Paid | N4: Notes
A5: =+IF(FromProposal[[#This Row],[Cost Code]]<>0,"Glasgow","") -> Glasgow | B5: 1 | C5: Deposit | D5: Deposit | E5: Initial Deposit to Start Job | F5: 0
A6: =+IF(FromProposal[[#This Row],[Cost Code]]<>0,"Glasgow","") -> Glasgow | B6: 2 | C6: Draw | D6: Draw 1 | E6: Draw 1 | F6: 0
A7: =+IF(FromProposal[[#This Row],[Cost Code]]<>0,"Glasgow","") -> Glasgow | B7: 3 | C7: Draw | D7: Draw 2 | E7: Draw 2 | F7: 0
A8: =+IF(FromProposal[[#This Row],[Cost Code]]<>0,"Glasgow","") | B8: 4 | D8: Sell | E8: List with MLS | F8: 6
A9: =+IF(FromProposal[[#This Row],[Cost Code]]<>0,"Glasgow","") -> Glasgow | B9: 5 | C9: HVAC | D9: Cordinate Sub | E9: HVAC | F9: 0 | G9: 0 | H9: 0
A10: =+IF(FromProposal[[#This Row],[Cost Code]]<>0,"Glasgow","") -> Glasgow | B10: 6 | C10: Floor Coverings | D10: Cordinate Sub | E10: Flooring Contractor | F10: 0 | G10: 200 | H10: 0
A11: =+IF(FromProposal[[#This Row],[Cost Code]]<>0,"Glasgow","") -> Glasgow | B11: 7 | C11: Supervision | D11: Cordinate Sub | E11: Termite Treatment | F11: 0 | G11: 200 | H11: 0
A12: =+IF(FromProposal[[#This Row],[Cost Code]]<>0,"Glasgow","") -> Glasgow | B12: 8 | C12: Cabinets & Vanities | D12: Cordinate Sub | E12: Cabinet Delivery | F12: 0 | G12: 200 | H12: 0
A13: =+IF(FromProposal[[#This Row],[Cost Code]]<>0,"Glasgow","") -> Glasgow | B13: 9 | C13: Countertops | D13: Cordinate Sub | E13: Manage installion of granite countertops by others in kitchen | F13: 0 | G13: 135 | H13: 0
A14: =+IF(FromProposal[[#This Row],[Cost Code]]<>0,"Glasgow","") | B14: 10 | E14: Clean out House | F14: 1 | G14: 0 | H14: 0
A15: =+IF(FromProposal[[#This Row],[Cost Code]]<>0,"Glasgow","") | B15: 11 | E15: Contract | F15: 0 | G15: 0 | H15: 0
A16: =+IF(FromProposal[[#This Row],[Cost Code]]<>0,"Glasgow","") -> Glasgow | B16: 12 | C16: Deck labor
A17: =+IF(FromProposal[[#This Row],[Cost Code]]<>0,"Glasgow","") -> Glasgow | B17: 13 | C17: Deck labor
A18: =+IF(FromProposal[[#This Row],[Cost Code]]<>0,"Glasgow","") -> Glasgow | B18: 14 | C18: Deck material
A19: =+IF(FromProposal[[#This Row],[Cost Code]]<>0,"Glasgow","") -> Glasgow | B19: 15 | C19: ... Demo
A20: =+IF(FromProposal[[#This Row],[Cost Code]]<>0,"Glasgow","") -> Glasgow | B20: 16 | C20: ... Demo

Sheet Gnatt Chart
J1: Expense | N1: Due:
A2: ="Glasgow Design Build for "&Profit!E1& " Your Home" -> Glasgow Design Build for Buy Your Home | E2: Project Start Date: | F2: =+MIN(ProposalToGnatt[Start Date]) -> 0 | H2: Company Paid Materials Total: | J2: =+SUM(H8:H22) -> 27817.44 | M2: =+SUM(O8:O22)-SUM(M8:M22) -> 1070
A3: Jonathan Brothers | B3: Jonathan Brothers | H3: Contractors Total: | J3: =SUM(H24:H27) -> 750 | M3: =+J3-SUM(M24:M27) -> 0
A4: =+Profit!B2 -> 3325 Banks Rd, Raleigh, NC 27603 | B4: =+Profit!B2 -> 3325 Banks Rd, Raleigh, NC 27603 | E4: Milestone Marker: | G4: 1 | H4: Glasgow Total: | J4: =SUM(ProposalToGnatt[Price]) -> 0 | M4: {=+SUM(ProposalToGnatt[Due]-ProposalToGnatt[Paid])} -> 0
B5: Cells H5 through BK5 contain the day number of the month for the Month represented in the cell block above each date cell and are auto calculated. Do not modify these cells. Dates leading up to Today are shaded. | E5: Milestone Marker 2: | G5: 2 | H5: Grand Total | J5: =+SUM(J2:K4) -> 28567.44 | M5: =+SUM(M2:N4) -> 1070
E6: =Profit!E1&" Your Home Supplied Materials" -> Buy Your Home Supplied Materials
A7: Assigned | B7: Item # | C7: Cost Code | D7: Title | E7: Description | F7: Qty | G7: Unit Price | H7: Price | I7: Done | J7: Group Order | K7: Start Date | L7: Days | M7: Paid | N7: Notes | O7: Due | AO7: =IFERROR(IF(LEN(#REF!)=0,"",IF(AND(#REF!=#REF!,#REF!=1),Milestone_Marker_Old,"")),"")
A8: =Profit!$E$1&" Your Home" -> Buy Your Home | B8: 1 | E8: Cleanup (from Demo & Trash Haul Tab) | F8: 1 | G8: =+'Demo & Trash Haul'!G21 -> 5322.49 | H8: =+F8*G8 -> 5322.49 | I8: Yes | M8: 4672.49 | O8: =IF(I8="Yes",H8,0) -> 5322.49
A9: =Profit!$E$1&" Your Home" -> Buy Your Home | B9: =+B8+1 -> 2 | E9: Taxes - outside of closing (from Taxes tab) | F9: 0 | G9: =+Taxes!E19 -> 0 | H9: =+F9*G9 -> 0 | O9: =IF(I9="Yes",H9,0) -> 0
A10: =Profit!$E$1&" Your Home" -> Buy Your Home | B10: =+B8+1 -> 2 | E10: Appliances (from Appliances Tab) | F10: 0 | G10: =+Appliances!F21 -> 1269.16 | H10: =+F10*G10 -> 0 | O10: =IF(I10="Yes",H10,0) -> 0
A11: =Profit!$E$1&" Your Home" -> Buy Your Home | B11: =+B10+1 -> 3 | E11: Plubing Fixtures | F11: 0 | G11: =+'Plumbing Fixtures'!F23 -> 433.46 | H11: =+F11*G11 -> 0 | O11: =IF(I11="Yes",H11,0) -> 0
A12: =Profit!$E$1&" Your Home" -> Buy Your Home | B12: =+B11+1 -> 4 | E12: Windows & Doors | F12: 0 | G12: =+'Windows & Doors'!F30 -> 749.65 | H12: =+F12*G12 -> 0 | O12: =IF(I12="Yes",H12,0) -> 0
A13: =Profit!$E$1&" Your Home" -> Buy Your Home | B13: =+B12+1 -> 5 | E13: Cabinets (from Cabinets Tab) | F13: 0 | G13: =+Cabinets!G44 -> 4165.4 | H13: =+F13*G13 -> 0 | O13: =IF(I13="Yes",H13,0) -> 0
A14: =Profit!$E$1&" Your Home" -> Buy Your Home | B14: =+B13+1 -> 6 | E14: Paint (from Paint Tab) | F14: 0 | G14: =+Paint!G28 -> 1332.94 | H14: =+F14*G14 -> 0 | O14: =IF(I14="Yes",H14,0) -> 0
A15: =Profit!$E$1&" Your Home" -> Buy Your Home | B15: =+B14+1 -> 7 | E15: Flooring | F15: 0 | G15: =+Flooring!G7 -> 5098.8 | H15: =+F15*G15 -> 0 | O15: =IF(I15="Yes",H15,0) -> 0 | AP15: =IFERROR(IF(LEN(#REF!)=0,"",IF(P$29=#REF!,Milestone_Marker_Old,"")),"") | AQ15: =IFERROR(IF(LEN(#REF!)=0,"",IF(Q$29=#REF!,Milestone_Marker_Old,"")),"") | AR15: =IFERROR(IF(LEN(#REF!)=0,"",IF(R$29=#REF!,Milestone_Marker_Old,"")),"") | AS15: =IFERROR(IF(LEN(#REF!)=0,"",IF(S$29=#REF!,Milestone_Marker_Old,"")),"") | AT15: =IFERROR(IF(LEN(#REF!)=0,"",IF(T$29=#REF!,Milestone_Marker_Old,"")),"") | AU15: =IFERROR(IF(LEN(#REF!)=0,"",IF(U$29=#REF!,Milestone_Marker_Old,"")),"") | AV15: =IFERROR(IF(LEN(#REF!)=0,"",IF(V$29=#REF!,Milestone_Marker_Old,"")),"") | AW15: =IFERROR(IF(LEN(#REF!)=0,"",IF(W$29=#REF!,Milestone_Marker_Old,"")),"") | ... DU15: =IFERROR(IF(LEN(#REF!)=0,"",IF(CU$29=#REF!,Milestone_Marker_Old,"")),"")
A16: =Profit!$E$1&" Your Home" -> Buy Your Home | B16: =+B15+1 -> 8 | E16: Electrical fixtures (from Misc Tab) | F16: 0 | G16: =+'Electrical Fixtures'!F23 -> 1357.2 | H16: =+F16*G16 -> 0 | O16: =IF(I16="Yes",H16,0) -> 0 | AP16: =IFERROR(IF(LEN(#REF!)=0,"",IF(P$29=#REF!,Milestone_Marker_Old,"")),"") | AQ16: =IFERROR(IF(LEN(#REF!)=0,"",IF(Q$29=#REF!,Milestone_Marker_Old,"")),"") | AR16: =IFERROR(IF(LEN(#REF!)=0,"",IF(R$29=#REF!,Milestone_Marker_Old,"")),"") | AS16: =IFERROR(IF(LEN(#REF!)=0,"",IF(S$29=#REF!,Milestone_Marker_Old,"")),"") | AT16: =IFERROR(IF(LEN(#REF!)=0,"",IF(T$29=#REF!,Milestone_Marker_Old,"")),"") | AU16: =IFERROR(IF(LEN(#REF!)=0,"",IF(U$29=#REF!,Milestone_Marker_Old,"")),"") | AV16: =IFERROR(IF(LEN(#REF!)=0,"",IF(V$29=#REF!,Milestone_Marker_Old,"")),"") | AW16: =IFERROR(IF(LEN(#REF!)=0,"",IF(W$29=#REF!,Milestone_Marker_Old,"")),"") | ... DU16: =IFERROR(IF(LEN(#REF!)=0,"",IF(CU$29=#REF!,Milestone_Marker_Old,"")),"")
A17: =Profit!$E$1&" Your Home" -> Buy Your Home | B17: =+B16+1 -> 9 | E17: Exterior Tab | F17: 1 | G17: =+Exterior!D16 -> 19189.95 | H17: =+F17*G17 -> 19189.95 | I17: Yes | M17: 19189.95 | O17: =IF(I17="Yes",H17,0) -> 19189.95
A18: =Profit!$E$1&" Your Home" -> Buy Your Home | B18: =+B17+1 -> 10 | E18: Landscaping Tab | F18: 1 | G18: =+Landscape!H17 -> 3305 | H18: =+F18*G18 -> 3305 | I18: Yes | M18: 2885 | O18: =IF(I18="Yes",H18,0) -> 3305
A19: =Profit!$E$1&" Your Home" -> Buy Your Home | B19: =+B18+1 -> 11 | E19: HVAC Contractor | F19: 0 | G19: =+'Demo & Trash Haul'!F33 -> 0 | H19: =+F19*G19 -> 0 | O19: =IF(I19="Yes",H19,0) -> 0 | AP19: =IFERROR(IF(LEN(#REF!)=0,"",IF(P$29=#REF!,Milestone_Marker_Old,"")),"") | AQ19: =IFERROR(IF(LEN(#REF!)=0,"",IF(Q$29=#REF!,Milestone_Marker_Old,"")),"") | AR19: =IFERROR(IF(LEN(#REF!)=0,"",IF(R$29=#REF!,Milestone_Marker_Old,"")),"") | AS19: =IFERROR(IF(LEN(#REF!)=0,"",IF(S$29=#REF!,Milestone_Marker_Old,"")),"") | AT19: =IFERROR(IF(LEN(#REF!)=0,"",IF(T$29=#REF!,Milestone_Marker_Old,"")),"") | AU19: =IFERROR(IF(LEN(#REF!)=0,"",IF(U$29=#REF!,Milestone_Marker_Old,"")),"") | AV19: =IFERROR(IF(LEN(#REF!)=0,"",IF(V$29=#REF!,Milestone_Marker_Old,"")),"") | AW19: =IFERROR(IF(LEN(#REF!)=0,"",IF(W$29=#REF!,Milestone_Marker_Old,"")),"") | ... DU19: =IFERROR(IF(LEN(#REF!)=0,"",IF(CU$29=#REF!,Milestone_Marker_Old,"")),"")
A20: =Profit!$E$1&" Your Home" -> Buy Your Home | B20: =+B19+1 -> 12 | E20: Landscape | F20: 0 | G20: =+'Demo & Trash Haul'!F34 -> 0 | H20: =+F20*G20 -> 0 | O20: =IF(I20="Yes",H20,0) -> 0 | AP20: =IFERROR(IF(LEN(#REF!)=0,"",IF(P$29=#REF!,Milestone_Marker_Old,"")),"") | AQ20: =IFERROR(IF(LEN(#REF!)=0,"",IF(Q$29=#REF!,Milestone_Marker_Old,"")),"") | AR20: =IFERROR(IF(LEN(#REF!)=0,"",IF(R$29=#REF!,Milestone_Marker_Old,"")),"") | AS20: =IFERROR(IF(LEN(#REF!)=0,"",IF(S$29=#REF!,Milestone_Marker_Old,"")),"") | AT20: =IFERROR(IF(LEN(#REF!)=0,"",IF(T$29=#REF!,Milestone_Marker_Old,"")),"") | AU20: =IFERROR(IF(LEN(#REF!)=0,"",IF(U$29=#REF!,Milestone_Marker_Old,"")),"") | AV20: =IFERROR(IF(LEN(#REF!)=0,"",IF(V$29=#REF!,Milestone_Marker_Old,"")),"") | AW20: =IFERROR(IF(LEN(#REF!)=0,"",IF(W$29=#REF!,Milestone_Marker_Old,"")),"") | ... DU20: =IFERROR(IF(LEN(#REF!)=0,"",IF(CU$29=#REF!,Milestone_Marker_Old,"")),"")
A21: =Profit!$E$1&" Your Home" -> Buy Your Home | B21: =+B20+1 -> 13 | E21: Exterior- Termite | F21: 0 | G21: 0 | H21: =+F21*G21 -> 0 | O21: =IF(I21="Yes",H21,0) -> 0 | AP21: =IFERROR(IF(LEN(#REF!)=0,"",IF(P$29=#REF!,Milestone_Marker_Old,"")),"") | AQ21: =IFERROR(IF(LEN(#REF!)=0,"",IF(Q$29=#REF!,Milestone_Marker_Old,"")),"") | AR21: =IFERROR(IF(LEN(#REF!)=0,"",IF(R$29=#REF!,Milestone_Marker_Old,"")),"") | AS21: =IFERROR(IF(LEN(#REF!)=0,"",IF(S$29=#REF!,Milestone_Marker_Old,"")),"") | AT21: =IFERROR(IF(LEN(#REF!)=0,"",IF(T$29=#REF!,Milestone_Marker_Old,"")),"") | AU21: =IFERROR(IF(LEN(#REF!)=0,"",IF(U$29=#REF!,Milestone_Marker_Old,"")),"") | AV21: =IFERROR(IF(LEN(#REF!)=0,"",IF(V$29=#REF!,Milestone_Marker_Old,"")),"") | AW21: =IFERROR(IF(LEN(#REF!)=0,"",IF(W$29=#REF!,Milestone_Marker_Old,"")),"") | ... DU21: =IFERROR(IF(LEN(#REF!)=0,"",IF(CU$29=#REF!,Milestone_Marker_Old,"")),"")
A22: =Profit!$E$1&" Your Home" -> Buy Your Home | B22: =+B21+1 -> 14 | E22: Drainage | F22: 0 | G22: =+'Demo & Trash Haul'!F36 -> 0 | H22: =+F22*G22 -> 0 | O22: =IF(I22="Yes",H22,0) -> 0 | AP22: =IFERROR(IF(LEN(#REF!)=0,"",IF(P$29=#REF!,Milestone_Marker_Old,"")),"") | AQ22: =IFERROR(IF(LEN(#REF!)=0,"",IF(Q$29=#REF!,Milestone_Marker_Old,"")),"") | AR22: =IFERROR(IF(LEN(#REF!)=0,"",IF(R$29=#REF!,Milestone_Marker_Old,"")),"") | AS22: =IFERROR(IF(LEN(#REF!)=0,"",IF(S$29=#REF!,Milestone_Marker_Old,"")),"") | AT22: =IFERROR(IF(LEN(#REF!)=0,"",IF(T$29=#REF!,Milestone_Marker_Old,"")),"") | AU22: =IFERROR(IF(LEN(#REF!)=0,"",IF(U$29=#REF!,Milestone_Marker_Old,"")),"") | AV22: =IFERROR(IF(LEN(#REF!)=0,"",IF(V$29=#REF!,Milestone_Marker_Old,"")),"") | AW22: =IFERROR(IF(LEN(#REF!)=0,"",IF(W$29=#REF!,Milestone_Marker_Old,"")),"") | ... DU22: =IFERROR(IF(LEN(#REF!)=0,"",IF(CU$29=#REF!,Milestone_Marker_Old,"")),"")
E23: =Profit!E1&" Your Home's Paid Contractors" -> Buy Your Home's Paid Contractors | AP23: =IFERROR(IF(LEN(#REF!)=0,"",IF(P$29=#REF!,Milestone_Marker_Old,"")),"") | AQ23: =IFERROR(IF(LEN(#REF!)=0,"",IF(Q$29=#REF!,Milestone_Marker_Old,"")),"") | AR23: =IFERROR(IF(LEN(#REF!)=0,"",IF(R$29=#REF!,Milestone_Marker_Old,"")),"") | AS23: =IFERROR(IF(LEN(#REF!)=0,"",IF(S$29=#REF!,Milestone_Marker_Old,"")),"") | AT23: =IFERROR(IF(LEN(#REF!)=0,"",IF(T$29=#REF!,Milestone_Marker_Old,"")),"") | AU23: =IFERROR(IF(LEN(#REF!)=0,"",IF(U$29=#REF!,Milestone_Marker_Old,"")),"") | AV23: =IFERROR(IF(LEN(#REF!)=0,"",IF(V$29=#REF!,Milestone_Marker_Old,"")),"") | AW23: =IFERROR(IF(LEN(#REF!)=0,"",IF(W$29=#REF!,Milestone_Marker_Old,"")),"") | ... DU23: =IFERROR(IF(LEN(#REF!)=0,"",IF(CU$29=#REF!,Milestone_Marker_Old,"")),"")
A24: Mabrey Roofing | B24: =+B22+1 -> 15 | E24: Esitimate on new build | F24: 0 | G24: 300000 | H24: =+F24*G24 -> 0 | O24: =IF(I24="Yes",H24,0) -> 0 | AA24: Scrolling Increment: | AP24: =IFERROR(IF(LEN(#REF!)=0,"",IF(P$29=#REF!,Milestone_Marker_Old,"")),"") | AQ24: =IFERROR(IF(LEN(#REF!)=0,"",IF(Q$29=#REF!,Milestone_Marker_Old,"")),"") | AR24: =IFERROR(IF(LEN(#REF!)=0,"",IF(R$29=#REF!,Milestone_Marker_Old,"")),"") | AS24: =IFERROR(IF(LEN(#REF!)=0,"",IF(S$29=#REF!,Milestone_Marker_Old,"")),"") | AT24: =IFERROR(IF(LEN(#REF!)=0,"",IF(T$29=#REF!,Milestone_Marker_Old,"")),"") | AU24: =IFERROR(IF(LEN(#REF!)=0,"",IF(U$29=#REF!,Milestone_Marker_Old,"")),"") | AV24: =IFERROR(IF(LEN(#REF!)=0,"",IF(V$29=#REF!,Milestone_Marker_Old,"")),"") | AW24: =IFERROR(IF(LEN(#REF!)=0,"",IF(W$29=#REF!,Milestone_Marker_Old,"")),"") | ... DU24: =IFERROR(IF(LEN(#REF!)=0,"",IF(CU$29=#REF!,Milestone_Marker_Old,"")),"")
A25: Remodeling Solutions | B25: =+B24+1 -> 16 | E25: Design Plans | F25: 1 | G25: 750 | H25: =+F25*G25 -> 750 | I25: Yes | M25: 750 | O25: =IF(I25="Yes",H25,0) -> 750 | AP25: =IFERROR(IF(LEN(#REF!)=0,"",IF(P$29=#REF!,Milestone_Marker_Old,"")),"") | AQ25: =IFERROR(IF(LEN(#REF!)=0,"",IF(Q$29=#REF!,Milestone_Marker_Old,"")),"") | AR25: =IFERROR(IF(LEN(#REF!)=0,"",IF(R$29=#REF!,Milestone_Marker_Old,"")),"") | AS25: =IFERROR(IF(LEN(#REF!)=0,"",IF(S$29=#REF!,Milestone_Marker_Old,"")),"") | AT25: =IFERROR(IF(LEN(#REF!)=0,"",IF(T$29=#REF!,Milestone_Marker_Old,"")),"") | AU25: =IFERROR(IF(LEN(#REF!)=0,"",IF(U$29=#REF!,Milestone_Marker_Old,"")),"") | AV25: =IFERROR(IF(LEN(#REF!)=0,"",IF(V$29=#REF!,Milestone_Marker_Old,"")),"") | AW25: =IFERROR(IF(LEN(#REF!)=0,"",IF(W$29=#REF!,Milestone_Marker_Old,"")),"") | ... DU25: =IFERROR(IF(LEN(#REF!)=0,"",IF(CU$29=#REF!,Milestone_Marker_Old,"")),"")
A26: Love Services | B26: =+B25+1 -> 17 | E26: HVAC Contractor - Package Heat Pump | F26: 0 | G26: =+HVAC!F13 -> 13062 | H26: =+F26*G26 -> 0 | O26: =IF(I26="Yes",H26,0) -> 0 | AB26: 0
A27: Love Services | B27: =+B26+1 -> 18 | E27: HVAC Contractor - Duct Work | F27: 0 | G27: 4598 | H27: =+F27*G27 -> 0 | O27: =IF(I27="Yes",H27,0) -> 0
E28: Glasgow Design Items (all items should be updated from Proposal or ProposalUpdate tab) | P28: =IF(TEXT(Project_Start,"mmmm")=TEXT(P29,"mmmm"),"",TEXT(P29,"mmmm")) | Q28: =IF(TEXT(P29,"mmmm")=TEXT(Q29,"mmmm"),"",TEXT(Q29,"mmmm")) | R28: =IF(TEXT(Q29,"mmmm")=TEXT(R29,"mmmm"),"",TEXT(R29,"mmmm")) | S28: =IF(TEXT(R29,"mmmm")=TEXT(S29,"mmmm"),"",TEXT(S29,"mmmm")) | T28: =IF(TEXT(S29,"mmmm")=TEXT(T29,"mmmm"),"",TEXT(T29,"mmmm")) | U28: =IF(TEXT(T29,"mmmm")=TEXT(U29,"mmmm"),"",TEXT(U29,"mmmm")) | V28: =IF(TEXT(U29,"mmmm")=TEXT(V29,"mmmm"),"",TEXT(V29,"mmmm")) | W28: =IF(TEXT(V29,"mmmm")=TEXT(W29,"mmmm"),"",TEXT(W29,"mmmm")) | X28: =IF(TEXT(W29,"mmmm")=TEXT(X29,"mmmm"),"",TEXT(X29,"mmmm")) | ... CU28: =IF(TEXT(CT29,"mmmm")=TEXT(CU29,"mmmm"),"",TEXT(CU29,"mmmm"))
A29: Party | B29: Item | C29: Cost Code | D29: Title | E29: Description | F29: Qty | G29: Unit Price | H29: Price | I29: Done | J29: Group Order | K29: Start Date | L29: Days | M29: Paid | N29: Notes | O29: Due | P29: =IFERROR(Project_Start+Scrolling_Increment,TODAY()) -> 0 | Q29: =+P29+1 -> 1 | R29: =+Q29+1 -> 2 | S29: =+R29+1 -> 3 | T29: =+S29+1 -> 4 | U29: =+T29+1 -> 5 | V29: =+U29+1 -> 6 | W29: =+V29+1 -> 7 | X29: =+W29+1 -> 8 | ... CU29: =+CT29+1 -> 83
A30: Glasgow | B30: 1 | C30: Deposit | D30: Deposit | E30: Initial Deposit to Start Job | F30: 0 | P30: =IFERROR(+IF(P$29=ProposalToGnatt[[#This Row],[Start Date]],Milestone_Marker,IF(AND(P$29>ProposalToGnatt[[#This Row],[Start Date]],P$29<ProposalToGnatt[[#This Row],[Start Date]]+ProposalToGnatt[[#This Row],[Days]]),$G$5,"")),"") -> 1 | Q30: =IFERROR(+IF(Q$29=ProposalToGnatt[[#This Row],[Start Date]],Milestone_Marker,IF(AND(Q$29>ProposalToGnatt[[#This Row],[Start Date]],Q$29<ProposalToGnatt[[#This Row],[Start Date]]+ProposalToGnatt[[#This Row],[Days]]),$G$5,"")),"") | R30: =IFERROR(+IF(R$29=ProposalToGnatt[[#This Row],[Start Date]],Milestone_Marker,IF(AND(R$29>ProposalToGnatt[[#This Row],[Start Date]],R$29<ProposalToGnatt[[#This Row],[Start Date]]+ProposalToGnatt[[#This Row],[Days]]),$G$5,"")),"") | S30: =IFERROR(+IF(S$29=ProposalToGnatt[[#This Row],[Start Date]],Milestone_Marker,IF(AND(S$29>ProposalToGnatt[[#This Row],[Start Date]],S$29<ProposalToGnatt[[#This Row],[Start Date]]+ProposalToGnatt[[#This Row],[Days]]),$G$5,"")),"") | T30: =IFERROR(+IF(T$29=ProposalToGnatt[[#This Row],[Start Date]],Milestone_Marker,IF(AND(T$29>ProposalToGnatt[[#This Row],[Start Date]],T$29<ProposalToGnatt[[#This Row],[Start Date]]+ProposalToGnatt[[#This Row],[Days]]),$G$5,"")),"") | U30: =IFERROR(+IF(U$29=ProposalToGnatt[[#This Row],[Start Date]],Milestone_Marker,IF(AND(U$29>ProposalToGnatt[[#This Row],[Start Date]],U$29<ProposalToGnatt[[#This Row],[Start Date]]+ProposalToGnatt[[#This Row],[Days]]),$G$5,"")),"") | V30: =IFERROR(+IF(V$29=ProposalToGnatt[[#This Row],[Start Date]],Milestone_Marker,IF(AND(V$29>ProposalToGnatt[[#This Row],[Start Date]],V$29<ProposalToGnatt[[#This Row],[Start Date]]+ProposalToGnatt[[#This Row],[Days]]),$G$5,"")),"") | W30: =IFERROR(+IF(W$29=ProposalToGnatt[[#This Row],[Start Date]],Milestone_Marker,IF(AND(W$29>ProposalToGnatt[[#This Row],[Start Date]],W$29<ProposalToGnatt[[#This Row],[Start Date]]+ProposalToGnatt[[#This Row],[Days]]),$G$5,"")),"") | ... CU30: =IFERROR(+IF(CU$29=ProposalToGnatt[[#This Row],[Start Date]],Milestone_Marker,IF(AND(CU$29>ProposalToGnatt[[#This Row],[Start Date]],CU$29<ProposalToGnatt[[#This Row],[Start Date]]+ProposalToGnatt[[#This Row],[Days]]),$G$5,"")),"")
A31: Glasgow | B31: 2 | C31: Draw | D31: Draw 1 | E31: Draw 1 | F31: 0 | P31: =IFERROR(+IF(P$29=ProposalToGnatt[[#This Row],[Start Date]],Milestone_Marker,IF(AND(P$29>ProposalToGnatt[[#This Row],[Start Date]],P$29<ProposalToGnatt[[#This Row],[Start Date]]+ProposalToGnatt[[#This Row],[Days]]),$G$5,"")),"") -> 1 | Q31: =IFERROR(+IF(Q$29=ProposalToGnatt[[#This Row],[Start Date]],Milestone_Marker,IF(AND(Q$29>ProposalToGnatt[[#This Row],[Start Date]],Q$29<ProposalToGnatt[[#This Row],[Start Date]]+ProposalToGnatt[[#This Row],[Days]]),$G$5,"")),"") | R31: =IFERROR(+IF(R$29=ProposalToGnatt[[#This Row],[Start Date]],Milestone_Marker,IF(AND(R$29>ProposalToGnatt[[#This Row],[Start Date]],R$29<ProposalToGnatt[[#This Row],[Start Date]]+ProposalToGnatt[[#This Row],[Days]]),$G$5,"")),"") | S31: =IFERROR(+IF(S$29=ProposalToGnatt[[#This Row],[Start Date]],Milestone_Marker,IF(AND(S$29>ProposalToGnatt[[#This Row],[Start Date]],S$29<ProposalToGnatt[[#This Row],[Start Date]]+ProposalToGnatt[[#This Row],[Days]]),$G$5,"")),"") | T31: =IFERROR(+IF(T$29=ProposalToGnatt[[#This Row],[Start Date]],Milestone_Marker,IF(AND(T$29>ProposalToGnatt[[#This Row],[Start Date]],T$29<ProposalToGnatt[[#This Row],[Start Date]]+ProposalToGnatt[[#This Row],[Days]]),$G$5,"")),"") | U31: =IFERROR(+IF(U$29=ProposalToGnatt[[#This Row],[Start Date]],Milestone_Marker,IF(AND(U$29>ProposalToGnatt[[#This Row],[Start Date]],U$29<ProposalToGnatt[[#This Row],[Start Date]]+ProposalToGnatt[[#This Row],[Days]]),$G$5,"")),"") | V31: =IFERROR(+IF(V$29=ProposalToGnatt[[#This Row],[Start Date]],Milestone_Marker,IF(AND(V$29>ProposalToGnatt[[#This Row],[Start Date]],V$29<ProposalToGnatt[[#This Row],[Start Date]]+ProposalToGnatt[[#This Row],[Days]]),$G$5,"")),"") | W31: =IFERROR(+IF(W$29=ProposalToGnatt[[#This Row],[Start Date]],Milestone_Marker,IF(AND(W$29>ProposalToGnatt[[#This Row],[Start Date]],W$29<ProposalToGnatt[[#This Row],[Start Date]]+ProposalToGnatt[[#This Row],[Days]]),$G$5,"")),"") | ... CU31: =IFERROR(+IF(CU$29=ProposalToGnatt[[#This Row],[Start Date]],Milestone_Marker,IF(AND(CU$29>ProposalToGnatt[[#This Row],[Start Date]],CU$29<ProposalToGnatt[[#This Row],[Start Date]]+ProposalToGnatt[[#This Row],[Days]]),$G$5,"")),"")
A32: Glasgow | B32: 3 | C32: Draw | D32: Draw 2 | E32: Draw 2 | F32: 0 | P32: =IFERROR(+IF(P$29=ProposalToGnatt[[#This Row],[Start Date]],Milestone_Marker,IF(AND(P$29>ProposalToGnatt[[#This Row],[Start Date]],P$29<ProposalToGnatt[[#This Row],[Start Date]]+ProposalToGnatt[[#This Row],[Days]]),$G$5,"")),"") -> 1 | Q32: =IFERROR(+IF(Q$29=ProposalToGnatt[[#This Row],[Start Date]],Milestone_Marker,IF(AND(Q$29>ProposalToGnatt[[#This Row],[Start Date]],Q$29<ProposalToGnatt[[#This Row],[Start Date]]+ProposalToGnatt[[#This Row],[Days]]),$G$5,"")),"") | R32: =IFERROR(+IF(R$29=ProposalToGnatt[[#This Row],[Start Date]],Milestone_Marker,IF(AND(R$29>ProposalToGnatt[[#This Row],[Start Date]],R$29<ProposalToGnatt[[#This Row],[Start Date]]+ProposalToGnatt[[#This Row],[Days]]),$G$5,"")),"") | S32: =IFERROR(+IF(S$29=ProposalToGnatt[[#This Row],[Start Date]],Milestone_Marker,IF(AND(S$29>ProposalToGnatt[[#This Row],[Start Date]],S$29<ProposalToGnatt[[#This Row],[Start Date]]+ProposalToGnatt[[#This Row],[Days]]),$G$5,"")),"") | T32: =IFERROR(+IF(T$29=ProposalToGnatt[[#This Row],[Start Date]],Milestone_Marker,IF(AND(T$29>ProposalToGnatt[[#This Row],[Start Date]],T$29<ProposalToGnatt[[#This Row],[Start Date]]+ProposalToGnatt[[#This Row],[Days]]),$G$5,"")),"") | U32: =IFERROR(+IF(U$29=ProposalToGnatt[[#This Row],[Start Date]],Milestone_Marker,IF(AND(U$29>ProposalToGnatt[[#This Row],[Start Date]],U$29<ProposalToGnatt[[#This Row],[Start Date]]+ProposalToGnatt[[#This Row],[Days]]),$G$5,"")),"") | V32: =IFERROR(+IF(V$29=ProposalToGnatt[[#This Row],[Start Date]],Milestone_Marker,IF(AND(V$29>ProposalToGnatt[[#This Row],[Start Date]],V$29<ProposalToGnatt[[#This Row],[Start Date]]+ProposalToGnatt[[#This Row],[Days]]),$G$5,"")),"") | W32: =IFERROR(+IF(W$29=ProposalToGnatt[[#This Row],[Start Date]],Milestone_Marker,IF(AND(W$29>ProposalToGnatt[[#This Row],[Start Date]],W$29<ProposalToGnatt[[#This Row],[Start Date]]+ProposalToGnatt[[#This Row],[Days]]),$G$5,"")),"") | ... CU32: =IFERROR(+IF(CU$29=ProposalToGnatt[[#This Row],[Start Date]],Milestone_Marker,IF(AND(CU$29>ProposalToGnatt[[#This Row],[Start Date]],CU$29<ProposalToGnatt[[#This Row],[Start Date]]+ProposalToGnatt[[#This Row],[Days]]),$G$5,"")),"")
B33: 4 | D33: Sell | E33: List with MLS | F33: 6 | P33: =IFERROR(+IF(P$29=ProposalToGnatt[[#This Row],[Start Date]],Milestone_Marker,IF(AND(P$29>ProposalToGnatt[[#This Row],[Start Date]],P$29<ProposalToGnatt[[#This Row],[Start Date]]+ProposalToGnatt[[#This Row],[Days]]),$G$5,"")),"") -> 1 | Q33: =IFERROR(+IF(Q$29=ProposalToGnatt[[#This Row],[Start Date]],Milestone_Marker,IF(AND(Q$29>ProposalToGnatt[[#This Row],[Start Date]],Q$29<ProposalToGnatt[[#This Row],[Start Date]]+ProposalToGnatt[[#This Row],[Days]]),$G$5,"")),"") | R33: =IFERROR(+IF(R$29=ProposalToGnatt[[#This Row],[Start Date]],Milestone_Marker,IF(AND(R$29>ProposalToGnatt[[#This Row],[Start Date]],R$29<ProposalToGnatt[[#This Row],[Start Date]]+ProposalToGnatt[[#This Row],[Days]]),$G$5,"")),"") | S33: =IFERROR(+IF(S$29=ProposalToGnatt[[#This Row],[Start Date]],Milestone_Marker,IF(AND(S$29>ProposalToGnatt[[#This Row],[Start Date]],S$29<ProposalToGnatt[[#This Row],[Start Date]]+ProposalToGnatt[[#This Row],[Days]]),$G$5,"")),"") | T33: =IFERROR(+IF(T$29=ProposalToGnatt[[#This Row],[Start Date]],Milestone_Marker,IF(AND(T$29>ProposalToGnatt[[#This Row],[Start Date]],T$29<ProposalToGnatt[[#This Row],[Start Date]]+ProposalToGnatt[[#This Row],[Days]]),$G$5,"")),"") | U33: =IFERROR(+IF(U$29=ProposalToGnatt[[#This Row],[Start Date]],Milestone_Marker,IF(AND(U$29>ProposalToGnatt[[#This Row],[Start Date]],U$29<ProposalToGnatt[[#This Row],[Start Date]]+ProposalToGnatt[[#This Row],[Days]]),$G$5,"")),"") | V33: =IFERROR(+IF(V$29=ProposalToGnatt[[#This Row],[Start Date]],Milestone_Marker,IF(AND(V$29>ProposalToGnatt[[#This Row],[Start Date]],V$29<ProposalToGnatt[[#This Row],[Start Date]]+ProposalToGnatt[[#This Row],[Days]]),$G$5,"")),"") | W33: =IFERROR(+IF(W$29=ProposalToGnatt[[#This Row],[Start Date]],Milestone_Marker,IF(AND(W$29>ProposalToGnatt[[#This Row],[Start Date]],W$29<ProposalToGnatt[[#This Row],[Start Date]]+ProposalToGnatt[[#This Row],[Days]]),$G$5,"")),"") | ... CU33: =IFERROR(+IF(CU$29=ProposalToGnatt[[#This Row],[Start Date]],Milestone_Marker,IF(AND(CU$29>ProposalToGnatt[[#This Row],[Start Date]],CU$29<ProposalToGnatt[[#This Row],[Start Date]]+ProposalToGnatt[[#This Row],[Days]]),$G$5,"")),"")
A34: Glasgow | B34: 5 | C34: HVAC | D34: Cordinate Sub | E34: HVAC | F34: 0 | G34: 0 | H34: 0 | P34: =IFERROR(+IF(P$29=ProposalToGnatt[[#This Row],[Start Date]],Milestone_Marker,IF(AND(P$29>ProposalToGnatt[[#This Row],[Start Date]],P$29<ProposalToGnatt[[#This Row],[Start Date]]+ProposalToGnatt[[#This Row],[Days]]),$G$5,"")),"") -> 1 | Q34: =IFERROR(+IF(Q$29=ProposalToGnatt[[#This Row],[Start Date]],Milestone_Marker,IF(AND(Q$29>ProposalToGnatt[[#This Row],[Start Date]],Q$29<ProposalToGnatt[[#This Row],[Start Date]]+ProposalToGnatt[[#This Row],[Days]]),$G$5,"")),"") | R34: =IFERROR(+IF(R$29=ProposalToGnatt[[#This Row],[Start Date]],Milestone_Marker,IF(AND(R$29>ProposalToGnatt[[#This Row],[Start Date]],R$29<ProposalToGnatt[[#This Row],[Start Date]]+ProposalToGnatt[[#This Row],[Days]]),$G$5,"")),"") | S34: =IFERROR(+IF(S$29=ProposalToGnatt[[#This Row],[Start Date]],Milestone_Marker,IF(AND(S$29>ProposalToGnatt[[#This Row],[Start Date]],S$29<ProposalToGnatt[[#This Row],[Start Date]]+ProposalToGnatt[[#This Row],[Days]]),$G$5,"")),"") | T34: =IFERROR(+IF(T$29=ProposalToGnatt[[#This Row],[Start Date]],Milestone_Marker,IF(AND(T$29>ProposalToGnatt[[#This Row],[Start Date]],T$29<ProposalToGnatt[[#This Row],[Start Date]]+ProposalToGnatt[[#This Row],[Days]]),$G$5,"")),"") | U34: =IFERROR(+IF(U$29=ProposalToGnatt[[#This Row],[Start Date]],Milestone_Marker,IF(AND(U$29>ProposalToGnatt[[#This Row],[Start Date]],U$29<ProposalToGnatt[[#This Row],[Start Date]]+ProposalToGnatt[[#This Row],[Days]]),$G$5,"")),"") | V34: =IFERROR(+IF(V$29=ProposalToGnatt[[#This Row],[Start Date]],Milestone_Marker,IF(AND(V$29>ProposalToGnatt[[#This Row],[Start Date]],V$29<ProposalToGnatt[[#This Row],[Start Date]]+ProposalToGnatt[[#This Row],[Days]]),$G$5,"")),"") | W34: =IFERROR(+IF(W$29=ProposalToGnatt[[#This Row],[Start Date]],Milestone_Marker,IF(AND(W$29>ProposalToGnatt[[#This Row],[Start Date]],W$29<ProposalToGnatt[[#This Row],[Start Date]]+ProposalToGnatt[[#This Row],[Days]]),$G$5,"")),"") | ... CU34: =IFERROR(+IF(CU$29=ProposalToGnatt[[#This Row],[Start Date]],Milestone_Marker,IF(AND(CU$29>ProposalToGnatt[[#This Row],[Start Date]],CU$29<ProposalToGnatt[[#This Row],[Start Date]]+ProposalToGnatt[[#This Row],[Days]]),$G$5,"")),"")
A35: Glasgow | B35: 6 | C35: Floor Coverings | D35: Cordinate Sub | E35: Flooring Contractor | F35: 0 | G35: 200 | H35: 0 | P35: =IFERROR(+IF(P$29=ProposalToGnatt[[#This Row],[Start Date]],Milestone_Marker,IF(AND(P$29>ProposalToGnatt[[#This Row],[Start Date]],P$29<ProposalToGnatt[[#This Row],[Start Date]]+ProposalToGnatt[[#This Row],[Days]]),$G$5,"")),"") -> 1 | Q35: =IFERROR(+IF(Q$29=ProposalToGnatt[[#This Row],[Start Date]],Milestone_Marker,IF(AND(Q$29>ProposalToGnatt[[#This Row],[Start Date]],Q$29<ProposalToGnatt[[#This Row],[Start Date]]+ProposalToGnatt[[#This Row],[Days]]),$G$5,"")),"") | R35: =IFERROR(+IF(R$29=ProposalToGnatt[[#This Row],[Start Date]],Milestone_Marker,IF(AND(R$29>ProposalToGnatt[[#This Row],[Start Date]],R$29<ProposalToGnatt[[#This Row],[Start Date]]+ProposalToGnatt[[#This Row],[Days]]),$G$5,"")),"") | S35: =IFERROR(+IF(S$29=ProposalToGnatt[[#This Row],[Start Date]],Milestone_Marker,IF(AND(S$29>ProposalToGnatt[[#This Row],[Start Date]],S$29<ProposalToGnatt[[#This Row],[Start Date]]+ProposalToGnatt[[#This Row],[Days]]),$G$5,"")),"") | T35: =IFERROR(+IF(T$29=ProposalToGnatt[[#This Row],[Start Date]],Milestone_Marker,IF(AND(T$29>ProposalToGnatt[[#This Row],[Start Date]],T$29<ProposalToGnatt[[#This Row],[Start Date]]+ProposalToGnatt[[#This Row],[Days]]),$G$5,"")),"") | U35: =IFERROR(+IF(U$29=ProposalToGnatt[[#This Row],[Start Date]],Milestone_Marker,IF(AND(U$29>ProposalToGnatt[[#This Row],[Start Date]],U$29<ProposalToGnatt[[#This Row],[Start Date]]+ProposalToGnatt[[#This Row],[Days]]),$G$5,"")),"") | V35: =IFERROR(+IF(V$29=ProposalToGnatt[[#This Row],[Start Date]],Milestone_Marker,IF(AND(V$29>ProposalToGnatt[[#This Row],[Start Date]],V$29<ProposalToGnatt[[#This Row],[Start Date]]+ProposalToGnatt[[#This Row],[Days]]),$G$5,"")),"") | W35: =IFERROR(+IF(W$29=ProposalToGnatt[[#This Row],[Start Date]],Milestone_Marker,IF(AND(W$29>ProposalToGnatt[[#This Row],[Start Date]],W$29<ProposalToGnatt[[#This Row],[Start Date]]+ProposalToGnatt[[#This Row],[Days]]),$G$5,"")),"") | ... CU35: =IFERROR(+IF(CU$29=ProposalToGnatt[[#This Row],[Start Date]],Milestone_Marker,IF(AND(CU$29>ProposalToGnatt[[#This Row],[Start Date]],CU$29<ProposalToGnatt[[#This Row],[Start Date]]+ProposalToGnatt[[#This Row],[Days]]),$G$5,"")),"")
A36: Glasgow | B36: 7 | C36: Supervision | D36: Cordinate Sub | E36: Termite Treatment | F36: 0 | G36: 200 | H36: 0 | P36: =IFERROR(+IF(P$29=ProposalToGnatt[[#This Row],[Start Date]],Milestone_Marker,IF(AND(P$29>ProposalToGnatt[[#This Row],[Start Date]],P$29<ProposalToGnatt[[#This Row],[Start Date]]+ProposalToGnatt[[#This Row],[Days]]),$G$5,"")),"") -> 1 | Q36: =IFERROR(+IF(Q$29=ProposalToGnatt[[#This Row],[Start Date]],Milestone_Marker,IF(AND(Q$29>ProposalToGnatt[[#This Row],[Start Date]],Q$29<ProposalToGnatt[[#This Row],[Start Date]]+ProposalToGnatt[[#This Row],[Days]]),$G$5,"")),"") | R36: =IFERROR(+IF(R$29=ProposalToGnatt[[#This Row],[Start Date]],Milestone_Marker,IF(AND(R$29>ProposalToGnatt[[#This Row],[Start Date]],R$29<ProposalToGnatt[[#This Row],[Start Date]]+ProposalToGnatt[[#This Row],[Days]]),$G$5,"")),"") | S36: =IFERROR(+IF(S$29=ProposalToGnatt[[#This Row],[Start Date]],Milestone_Marker,IF(AND(S$29>ProposalToGnatt[[#This Row],[Start Date]],S$29<ProposalToGnatt[[#This Row],[Start Date]]+ProposalToGnatt[[#This Row],[Days]]),$G$5,"")),"") | T36: =IFERROR(+IF(T$29=ProposalToGnatt[[#This Row],[Start Date]],Milestone_Marker,IF(AND(T$29>ProposalToGnatt[[#This Row],[Start Date]],T$29<ProposalToGnatt[[#This Row],[Start Date]]+ProposalToGnatt[[#This Row],[Days]]),$G$5,"")),"") | U36: =IFERROR(+IF(U$29=ProposalToGnatt[[#This Row],[Start Date]],Milestone_Marker,IF(AND(U$29>ProposalToGnatt[[#This Row],[Start Date]],U$29<ProposalToGnatt[[#This Row],[Start Date]]+ProposalToGnatt[[#This Row],[Days]]),$G$5,"")),"") | V36: =IFERROR(+IF(V$29=ProposalToGnatt[[#This Row],[Start Date]],Milestone_Marker,IF(AND(V$29>ProposalToGnatt[[#This Row],[Start Date]],V$29<ProposalToGnatt[[#This Row],[Start Date]]+ProposalToGnatt[[#This Row],[Days]]),$G$5,"")),"") | W36: =IFERROR(+IF(W$29=ProposalToGnatt[[#This Row],[Start Date]],Milestone_Marker,IF(AND(W$29>ProposalToGnatt[[#This Row],[Start Date]],W$29<ProposalToGnatt[[#This Row],[Start Date]]+ProposalToGnatt[[#This Row],[Days]]),$G$5,"")),"") | ... CU36: =IFERROR(+IF(CU$29=ProposalToGnatt[[#This Row],[Start Date]],Milestone_Marker,IF(AND(CU$29>ProposalToGnatt[[#This Row],[Start Date]],CU$29<ProposalToGnatt[[#This Row],[Start Date]]+ProposalToGnatt[[#This Row],[Days]]),$G$5,"")),"")
A37: Glasgow | B37: 8 | C37: Cabinets & Vanities | D37: Cordinate Sub | E37: Cabinet Delivery | F37: 0 | G37: 200 | H37: 0 | P37: =IFERROR(+IF(P$29=ProposalToGnatt[[#This Row],[Start Date]],Milestone_Marker,IF(AND(P$29>ProposalToGnatt[[#This Row],[Start Date]],P$29<ProposalToGnatt[[#This Row],[Start Date]]+ProposalToGnatt[[#This Row],[Days]]),$G$5,"")),"") -> 1 | Q37: =IFERROR(+IF(Q$29=ProposalToGnatt[[#This Row],[Start Date]],Milestone_Marker,IF(AND(Q$29>ProposalToGnatt[[#This Row],[Start Date]],Q$29<ProposalToGnatt[[#This Row],[Start Date]]+ProposalToGnatt[[#This Row],[Days]]),$G$5,"")),"") | R37: =IFERROR(+IF(R$29=ProposalToGnatt[[#This Row],[Start Date]],Milestone_Marker,IF(AND(R$29>ProposalToGnatt[[#This Row],[Start Date]],R$29<ProposalToGnatt[[#This Row],[Start Date]]+ProposalToGnatt[[#This Row],[Days]]),$G$5,"")),"") | S37: =IFERROR(+IF(S$29=ProposalToGnatt[[#This Row],[Start Date]],Milestone_Marker,IF(AND(S$29>ProposalToGnatt[[#This Row],[Start Date]],S$29<ProposalToGnatt[[#This Row],[Start Date]]+ProposalToGnatt[[#This Row],[Days]]),$G$5,"")),"") | T37: =IFERROR(+IF(T$29=ProposalToGnatt[[#This Row],[Start Date]],Milestone_Marker,IF(AND(T$29>ProposalToGnatt[[#This Row],[Start Date]],T$29<ProposalToGnatt[[#This Row],[Start Date]]+ProposalToGnatt[[#This Row],[Days]]),$G$5,"")),"") | U37: =IFERROR(+IF(U$29=ProposalToGnatt[[#This Row],[Start Date]],Milestone_Marker,IF(AND(U$29>ProposalToGnatt[[#This Row],[Start Date]],U$29<ProposalToGnatt[[#This Row],[Start Date]]+ProposalToGnatt[[#This Row],[Days]]),$G$5,"")),"") | V37: =IFERROR(+IF(V$29=ProposalToGnatt[[#This Row],[Start Date]],Milestone_Marker,IF(AND(V$29>ProposalToGnatt[[#This Row],[Start Date]],V$29<ProposalToGnatt[[#This Row],[Start Date]]+ProposalToGnatt[[#This Row],[Days]]),$G$5,"")),"") | W37: =IFERROR(+IF(W$29=ProposalToGnatt[[#This Row],[Start Date]],Milestone_Marker,IF(AND(W$29>ProposalToGnatt[[#This Row],[Start Date]],W$29<ProposalToGnatt[[#This Row],[Start Date]]+ProposalToGnatt[[#This Row],[Days]]),$G$5,"")),"") | ... CU37: =IFERROR(+IF(CU$29=ProposalToGnatt[[#This Row],[Start Date]],Milestone_Marker,IF(AND(CU$29>ProposalToGnatt[[#This Row],[Start Date]],CU$29<ProposalToGnatt[[#This Row],[Start Date]]+ProposalToGnatt[[#This Row],[Days]]),$G$5,"")),"")
A38: Glasgow | B38: 9 | C38: Countertops | D38: Cordinate Sub | E38: Manage installion of granite countertops by others in kitchen | F38: 0 | G38: 135 | H38: 0 | P38: =IFERROR(+IF(P$29=ProposalToGnatt[[#This Row],[Start Date]],Milestone_Marker,IF(AND(P$29>ProposalToGnatt[[#This Row],[Start Date]],P$29<ProposalToGnatt[[#This Row],[Start Date]]+ProposalToGnatt[[#This Row],[Days]]),$G$5,"")),"") -> 1 | Q38: =IFERROR(+IF(Q$29=ProposalToGnatt[[#This Row],[Start Date]],Milestone_Marker,IF(AND(Q$29>ProposalToGnatt[[#This Row],[Start Date]],Q$29<ProposalToGnatt[[#This Row],[Start Date]]+ProposalToGnatt[[#This Row],[Days]]),$G$5,"")),"") | R38: =IFERROR(+IF(R$29=ProposalToGnatt[[#This Row],[Start Date]],Milestone_Marker,IF(AND(R$29>ProposalToGnatt[[#This Row],[Start Date]],R$29<ProposalToGnatt[[#This Row],[Start Date]]+ProposalToGnatt[[#This Row],[Days]]),$G$5,"")),"") | S38: =IFERROR(+IF(S$29=ProposalToGnatt[[#This Row],[Start Date]],Milestone_Marker,IF(AND(S$29>ProposalToGnatt[[#This Row],[Start Date]],S$29<ProposalToGnatt[[#This Row],[Start Date]]+ProposalToGnatt[[#This Row],[Days]]),$G$5,"")),"") | T38: =IFERROR(+IF(T$29=ProposalToGnatt[[#This Row],[Start Date]],Milestone_Marker,IF(AND(T$29>ProposalToGnatt[[#This Row],[Start Date]],T$29<ProposalToGnatt[[#This Row],[Start Date]]+ProposalToGnatt[[#This Row],[Days]]),$G$5,"")),"") | U38: =IFERROR(+IF(U$29=ProposalToGnatt[[#This Row],[Start Date]],Milestone_Marker,IF(AND(U$29>ProposalToGnatt[[#This Row],[Start Date]],U$29<ProposalToGnatt[[#This Row],[Start Date]]+ProposalToGnatt[[#This Row],[Days]]),$G$5,"")),"") | V38: =IFERROR(+IF(V$29=ProposalToGnatt[[#This Row],[Start Date]],Milestone_Marker,IF(AND(V$29>ProposalToGnatt[[#This Row],[Start Date]],V$29<ProposalToGnatt[[#This Row],[Start Date]]+ProposalToGnatt[[#This Row],[Days]]),$G$5,"")),"") | W38: =IFERROR(+IF(W$29=ProposalToGnatt[[#This Row],[Start Date]],Milestone_Marker,IF(AND(W$29>ProposalToGnatt[[#This Row],[Start Date]],W$29<ProposalToGnatt[[#This Row],[Start Date]]+ProposalToGnatt[[#This Row],[Days]]),$G$5,"")),"") | ... CU38: =IFERROR(+IF(CU$29=ProposalToGnatt[[#This Row],[Start Date]],Milestone_Marker,IF(AND(CU$29>ProposalToGnatt[[#This Row],[Start Date]],CU$29<ProposalToGnatt[[#This Row],[Start Date]]+ProposalToGnatt[[#This Row],[Days]]),$G$5,"")),"")
B39: 10 | E39: Clean out House | F39: 1 | G39: 0 | H39: 0 | P39: =IFERROR(+IF(P$29=ProposalToGnatt[[#This Row],[Start Date]],Milestone_Marker,IF(AND(P$29>ProposalToGnatt[[#This Row],[Start Date]],P$29<ProposalToGnatt[[#This Row],[Start Date]]+ProposalToGnatt[[#This Row],[Days]]),$G$5,"")),"") -> 1 | Q39: =IFERROR(+IF(Q$29=ProposalToGnatt[[#This Row],[Start Date]],Milestone_Marker,IF(AND(Q$29>ProposalToGnatt[[#This Row],[Start Date]],Q$29<ProposalToGnatt[[#This Row],[Start Date]]+ProposalToGnatt[[#This Row],[Days]]),$G$5,"")),"") | R39: =IFERROR(+IF(R$29=ProposalToGnatt[[#This Row],[Start Date]],Milestone_Marker,IF(AND(R$29>ProposalToGnatt[[#This Row],[Start Date]],R$29<ProposalToGnatt[[#This Row],[Start Date]]+ProposalToGnatt[[#This Row],[Days]]),$G$5,"")),"") | S39: =IFERROR(+IF(S$29=ProposalToGnatt[[#This Row],[Start Date]],Milestone_Marker,IF(AND(S$29>ProposalToGnatt[[#This Row],[Start Date]],S$29<ProposalToGnatt[[#This Row],[Start Date]]+ProposalToGnatt[[#This Row],[Days]]),$G$5,"")),"") | T39: =IFERROR(+IF(T$29=ProposalToGnatt[[#This Row],[Start Date]],Milestone_Marker,IF(AND(T$29>ProposalToGnatt[[#This Row],[Start Date]],T$29<ProposalToGnatt[[#This Row],[Start Date]]+ProposalToGnatt[[#This Row],[Days]]),$G$5,"")),"") | U39: =IFERROR(+IF(U$29=ProposalToGnatt[[#This Row],[Start Date]],Milestone_Marker,IF(AND(U$29>ProposalToGnatt[[#This Row],[Start Date]],U$29<ProposalToGnatt[[#This Row],[Start Date]]+ProposalToGnatt[[#This Row],[Days]]),$G$5,"")),"") | V39: =IFERROR(+IF(V$29=ProposalToGnatt[[#This Row],[Start Date]],Milestone_Marker,IF(AND(V$29>ProposalToGnatt[[#This Row],[Start Date]],V$29<ProposalToGnatt[[#This Row],[Start Date]]+ProposalToGnatt[[#This Row],[Days]]),$G$5,"")),"") | W39: =IFERROR(+IF(W$29=ProposalToGnatt[[#This Row],[Start Date]],Milestone_Marker,IF(AND(W$29>ProposalToGnatt[[#This Row],[Start Date]],W$29<ProposalToGnatt[[#This Row],[Start Date]]+ProposalToGnatt[[#This Row],[Days]]),$G$5,"")),"") | ... CU39: =IFERROR(+IF(CU$29=ProposalToGnatt[[#This Row],[Start Date]],Milestone_Marker,IF(AND(CU$29>ProposalToGnatt[[#This Row],[Start Date]],CU$29<ProposalToGnatt[[#This Row],[Start Date]]+ProposalToGnatt[[#This Row],[Days]]),$G$5,"")),"")
B40: 11 | E40: Contract | F40: 0 | G40: 0 | H40: 0 | P40: =IFERROR(+IF(P$29=ProposalToGnatt[[#This Row],[Start Date]],Milestone_Marker,IF(AND(P$29>ProposalToGnatt[[#This Row],[Start Date]],P$29<ProposalToGnatt[[#This Row],[Start Date]]+ProposalToGnatt[[#This Row],[Days]]),$G$5,"")),"") -> 1 | Q40: =IFERROR(+IF(Q$29=ProposalToGnatt[[#This Row],[Start Date]],Milestone_Marker,IF(AND(Q$29>ProposalToGnatt[[#This Row],[Start Date]],Q$29<ProposalToGnatt[[#This Row],[Start Date]]+ProposalToGnatt[[#This Row],[Days]]),$G$5,"")),"") | R40: =IFERROR(+IF(R$29=ProposalToGnatt[[#This Row],[Start Date]],Milestone_Marker,IF(AND(R$29>ProposalToGnatt[[#This Row],[Start Date]],R$29<ProposalToGnatt[[#This Row],[Start Date]]+ProposalToGnatt[[#This Row],[Days]]),$G$5,"")),"") | S40: =IFERROR(+IF(S$29=ProposalToGnatt[[#This Row],[Start Date]],Milestone_Marker,IF(AND(S$29>ProposalToGnatt[[#This Row],[Start Date]],S$29<ProposalToGnatt[[#This Row],[Start Date]]+ProposalToGnatt[[#This Row],[Days]]),$G$5,"")),"") | T40: =IFERROR(+IF(T$29=ProposalToGnatt[[#This Row],[Start Date]],Milestone_Marker,IF(AND(T$29>ProposalToGnatt[[#This Row],[Start Date]],T$29<ProposalToGnatt[[#This Row],[Start Date]]+ProposalToGnatt[[#This Row],[Days]]),$G$5,"")),"") | U40: =IFERROR(+IF(U$29=ProposalToGnatt[[#This Row],[Start Date]],Milestone_Marker,IF(AND(U$29>ProposalToGnatt[[#This Row],[Start Date]],U$29<ProposalToGnatt[[#This Row],[Start Date]]+ProposalToGnatt[[#This Row],[Days]]),$G$5,"")),"") | V40: =IFERROR(+IF(V$29=ProposalToGnatt[[#This Row],[Start Date]],Milestone_Marker,IF(AND(V$29>ProposalToGnatt[[#This Row],[Start Date]],V$29<ProposalToGnatt[[#This Row],[Start Date]]+ProposalToGnatt[[#This Row],[Days]]),$G$5,"")),"") | W40: =IFERROR(+IF(W$29=ProposalToGnatt[[#This Row],[Start Date]],Milestone_Marker,IF(AND(W$29>ProposalToGnatt[[#This Row],[Start Date]],W$29<ProposalToGnatt[[#This Row],[Start Date]]+ProposalToGnatt[[#This Row],[Days]]),$G$5,"")),"") | ... CU40: =IFERROR(+IF(CU$29=ProposalToGnatt[[#This Row],[Start Date]],Milestone_Marker,IF(AND(CU$29>ProposalToGnatt[[#This Row],[Start Date]],CU$29<ProposalToGnatt[[#This Row],[Start Date]]+ProposalToGnatt[[#This Row],[Days]]),$G$5,"")),"")
A41: Glasgow | B41: 12 | C41: Deck labor | P41: =IFERROR(+IF(P$29=ProposalToGnatt[[#This Row],[Start Date]],Milestone_Marker,IF(AND(P$29>ProposalToGnatt[[#This Row],[Start Date]],P$29<ProposalToGnatt[[#This Row],[Start Date]]+ProposalToGnatt[[#This Row],[Days]]),$G$5,"")),"") -> 1 | Q41: =IFERROR(+IF(Q$29=ProposalToGnatt[[#This Row],[Start Date]],Milestone_Marker,IF(AND(Q$29>ProposalToGnatt[[#This Row],[Start Date]],Q$29<ProposalToGnatt[[#This Row],[Start Date]]+ProposalToGnatt[[#This Row],[Days]]),$G$5,"")),"") | R41: =IFERROR(+IF(R$29=ProposalToGnatt[[#This Row],[Start Date]],Milestone_Marker,IF(AND(R$29>ProposalToGnatt[[#This Row],[Start Date]],R$29<ProposalToGnatt[[#This Row],[Start Date]]+ProposalToGnatt[[#This Row],[Days]]),$G$5,"")),"") | S41: =IFERROR(+IF(S$29=ProposalToGnatt[[#This Row],[Start Date]],Milestone_Marker,IF(AND(S$29>ProposalToGnatt[[#This Row],[Start Date]],S$29<ProposalToGnatt[[#This Row],[Start Date]]+ProposalToGnatt[[#This Row],[Days]]),$G$5,"")),"") | T41: =IFERROR(+IF(T$29=ProposalToGnatt[[#This Row],[Start Date]],Milestone_Marker,IF(AND(T$29>ProposalToGnatt[[#This Row],[Start Date]],T$29<ProposalToGnatt[[#This Row],[Start Date]]+ProposalToGnatt[[#This Row],[Days]]),$G$5,"")),"") | U41: =IFERROR(+IF(U$29=ProposalToGnatt[[#This Row],[Start Date]],Milestone_Marker,IF(AND(U$29>ProposalToGnatt[[#This Row],[Start Date]],U$29<ProposalToGnatt[[#This Row],[Start Date]]+ProposalToGnatt[[#This Row],[Days]]),$G$5,"")),"") | V41: =IFERROR(+IF(V$29=ProposalToGnatt[[#This Row],[Start Date]],Milestone_Marker,IF(AND(V$29>ProposalToGnatt[[#This Row],[Start Date]],V$29<ProposalToGnatt[[#This Row],[Start Date]]+ProposalToGnatt[[#This Row],[Days]]),$G$5,"")),"") | W41: =IFERROR(+IF(W$29=ProposalToGnatt[[#This Row],[Start Date]],Milestone_Marker,IF(AND(W$29>ProposalToGnatt[[#This Row],[Start Date]],W$29<ProposalToGnatt[[#This Row],[Start Date]]+ProposalToGnatt[[#This Row],[Days]]),$G$5,"")),"") | ... CU41: =IFERROR(+IF(CU$29=ProposalToGnatt[[#This Row],[Start Date]],Milestone_Marker,IF(AND(CU$29>ProposalToGnatt[[#This Row],[Start Date]],CU$29<ProposalToGnatt[[#This Row],[Start Date]]+ProposalToGnatt[[#This Row],[Days]]),$G$5,"")),"")
A42: Glasgow | B42: 13 | C42: Deck labor | P42: =IFERROR(+IF(P$29=ProposalToGnatt[[#This Row],[Start Date]],Milestone_Marker,IF(AND(P$29>ProposalToGnatt[[#This Row],[Start Date]],P$29<ProposalToGnatt[[#This Row],[Start Date]]+ProposalToGnatt[[#This Row],[Days]]),$G$5,"")),"") -> 1 | Q42: =IFERROR(+IF(Q$29=ProposalToGnatt[[#This Row],[Start Date]],Milestone_Marker,IF(AND(Q$29>ProposalToGnatt[[#This Row],[Start Date]],Q$29<ProposalToGnatt[[#This Row],[Start Date]]+ProposalToGnatt[[#This Row],[Days]]),$G$5,"")),"") | R42: =IFERROR(+IF(R$29=ProposalToGnatt[[#This Row],[Start Date]],Milestone_Marker,IF(AND(R$29>ProposalToGnatt[[#This Row],[Start Date]],R$29<ProposalToGnatt[[#This Row],[Start Date]]+ProposalToGnatt[[#This Row],[Days]]),$G$5,"")),"") | S42: =IFERROR(+IF(S$29=ProposalToGnatt[[#This Row],[Start Date]],Milestone_Marker,IF(AND(S$29>ProposalToGnatt[[#This Row],[Start Date]],S$29<ProposalToGnatt[[#This Row],[Start Date]]+ProposalToGnatt[[#This Row],[Days]]),$G$5,"")),"") | T42: =IFERROR(+IF(T$29=ProposalToGnatt[[#This Row],[Start Date]],Milestone_Marker,IF(AND(T$29>ProposalToGnatt[[#This Row],[Start Date]],T$29<ProposalToGnatt[[#This Row],[Start Date]]+ProposalToGnatt[[#This Row],[Days]]),$G$5,"")),"") | U42: =IFERROR(+IF(U$29=ProposalToGnatt[[#This Row],[Start Date]],Milestone_Marker,IF(AND(U$29>ProposalToGnatt[[#This Row],[Start Date]],U$29<ProposalToGnatt[[#This Row],[Start Date]]+ProposalToGnatt[[#This Row],[Days]]),$G$5,"")),"") | V42: =IFERROR(+IF(V$29=ProposalToGnatt[[#This Row],[Start Date]],Milestone_Marker,IF(AND(V$29>ProposalToGnatt[[#This Row],[Start Date]],V$29<ProposalToGnatt[[#This Row],[Start Date]]+ProposalToGnatt[[#This Row],[Days]]),$G$5,"")),"") | W42: =IFERROR(+IF(W$29=ProposalToGnatt[[#This Row],[Start Date]],Milestone_Marker,IF(AND(W$29>ProposalToGnatt[[#This Row],[Start Date]],W$29<ProposalToGnatt[[#This Row],[Start Date]]+ProposalToGnatt[[#This Row],[Days]]),$G$5,"")),"") | ... CU42: =IFERROR(+IF(CU$29=ProposalToGnatt[[#This Row],[Start Date]],Milestone_Marker,IF(AND(CU$29>ProposalToGnatt[[#This Row],[Start Date]],CU$29<ProposalToGnatt[[#This Row],[Start Date]]+ProposalToGnatt[[#This Row],[Days]]),$G$5,"")),"")
A43: Glasgow | B43: 14 | C43: Deck material | P43: =IFERROR(+IF(P$29=ProposalToGnatt[[#This Row],[Start Date]],Milestone_Marker,IF(AND(P$29>ProposalToGnatt[[#This Row],[Start Date]],P$29<ProposalToGnatt[[#This Row],[Start Date]]+ProposalToGnatt[[#This Row],[Days]]),$G$5,"")),"") -> 1 | Q43: =IFERROR(+IF(Q$29=ProposalToGnatt[[#This Row],[Start Date]],Milestone_Marker,IF(AND(Q$29>ProposalToGnatt[[#This Row],[Start Date]],Q$29<ProposalToGnatt[[#This Row],[Start Date]]+ProposalToGnatt[[#This Row],[Days]]),$G$5,"")),"") | R43: =IFERROR(+IF(R$29=ProposalToGnatt[[#This Row],[Start Date]],Milestone_Marker,IF(AND(R$29>ProposalToGnatt[[#This Row],[Start Date]],R$29<ProposalToGnatt[[#This Row],[Start Date]]+ProposalToGnatt[[#This Row],[Days]]),$G$5,"")),"") | S43: =IFERROR(+IF(S$29=ProposalToGnatt[[#This Row],[Start Date]],Milestone_Marker,IF(AND(S$29>ProposalToGnatt[[#This Row],[Start Date]],S$29<ProposalToGnatt[[#This Row],[Start Date]]+ProposalToGnatt[[#This Row],[Days]]),$G$5,"")),"") | T43: =IFERROR(+IF(T$29=ProposalToGnatt[[#This Row],[Start Date]],Milestone_Marker,IF(AND(T$29>ProposalToGnatt[[#This Row],[Start Date]],T$29<ProposalToGnatt[[#This Row],[Start Date]]+ProposalToGnatt[[#This Row],[Days]]),$G$5,"")),"") | U43: =IFERROR(+IF(U$29=ProposalToGnatt[[#This Row],[Start Date]],Milestone_Marker,IF(AND(U$29>ProposalToGnatt[[#This Row],[Start Date]],U$29<ProposalToGnatt[[#This Row],[Start Date]]+ProposalToGnatt[[#This Row],[Days]]),$G$5,"")),"") | V43: =IFERROR(+IF(V$29=ProposalToGnatt[[#This Row],[Start Date]],Milestone_Marker,IF(AND(V$29>ProposalToGnatt[[#This Row],[Start Date]],V$29<ProposalToGnatt[[#This Row],[Start Date]]+ProposalToGnatt[[#This Row],[Days]]),$G$5,"")),"") | W43: =IFERROR(+IF(W$29=ProposalToGnatt[[#This Row],[Start Date]],Milestone_Marker,IF(AND(W$29>ProposalToGnatt[[#This Row],[Start Date]],W$29<ProposalToGnatt[[#This Row],[Start Date]]+ProposalToGnatt[[#This Row],[Days]]),$G$5,"")),"") | ... CU43: =IFERROR(+IF(CU$29=ProposalToGnatt[[#This Row],[Start Date]],Milestone_Marker,IF(AND(CU$29>ProposalToGnatt[[#This Row],[Start Date]],CU$29<ProposalToGnatt[[#This Row],[Start Date]]+ProposalToGnatt[[#This Row],[Days]]),$G$5,"")),"")
A44: Glasgow | B44: 15 | C44: ... Demo | P44: =IFERROR(+IF(P$29=ProposalToGnatt[[#This Row],[Start Date]],Milestone_Marker,IF(AND(P$29>ProposalToGnatt[[#This Row],[Start Date]],P$29<ProposalToGnatt[[#This Row],[Start Date]]+ProposalToGnatt[[#This Row],[Days]]),$G$5,"")),"") -> 1 | Q44: =IFERROR(+IF(Q$29=ProposalToGnatt[[#This Row],[Start Date]],Milestone_Marker,IF(AND(Q$29>ProposalToGnatt[[#This Row],[Start Date]],Q$29<ProposalToGnatt[[#This Row],[Start Date]]+ProposalToGnatt[[#This Row],[Days]]),$G$5,"")),"") | R44: =IFERROR(+IF(R$29=ProposalToGnatt[[#This Row],[Start Date]],Milestone_Marker,IF(AND(R$29>ProposalToGnatt[[#This Row],[Start Date]],R$29<ProposalToGnatt[[#This Row],[Start Date]]+ProposalToGnatt[[#This Row],[Days]]),$G$5,"")),"") | S44: =IFERROR(+IF(S$29=ProposalToGnatt[[#This Row],[Start Date]],Milestone_Marker,IF(AND(S$29>ProposalToGnatt[[#This Row],[Start Date]],S$29<ProposalToGnatt[[#This Row],[Start Date]]+ProposalToGnatt[[#This Row],[Days]]),$G$5,"")),"") | T44: =IFERROR(+IF(T$29=ProposalToGnatt[[#This Row],[Start Date]],Milestone_Marker,IF(AND(T$29>ProposalToGnatt[[#This Row],[Start Date]],T$29<ProposalToGnatt[[#This Row],[Start Date]]+ProposalToGnatt[[#This Row],[Days]]),$G$5,"")),"") | U44: =IFERROR(+IF(U$29=ProposalToGnatt[[#This Row],[Start Date]],Milestone_Marker,IF(AND(U$29>ProposalToGnatt[[#This Row],[Start Date]],U$29<ProposalToGnatt[[#This Row],[Start Date]]+ProposalToGnatt[[#This Row],[Days]]),$G$5,"")),"") | V44: =IFERROR(+IF(V$29=ProposalToGnatt[[#This Row],[Start Date]],Milestone_Marker,IF(AND(V$29>ProposalToGnatt[[#This Row],[Start Date]],V$29<ProposalToGnatt[[#This Row],[Start Date]]+ProposalToGnatt[[#This Row],[Days]]),$G$5,"")),"") | W44: =IFERROR(+IF(W$29=ProposalToGnatt[[#This Row],[Start Date]],Milestone_Marker,IF(AND(W$29>ProposalToGnatt[[#This Row],[Start Date]],W$29<ProposalToGnatt[[#This Row],[Start Date]]+ProposalToGnatt[[#This Row],[Days]]),$G$5,"")),"") | ... CU44: =IFERROR(+IF(CU$29=ProposalToGnatt[[#This Row],[Start Date]],Milestone_Marker,IF(AND(CU$29>ProposalToGnatt[[#This Row],[Start Date]],CU$29<ProposalToGnatt[[#This Row],[Start Date]]+ProposalToGnatt[[#This Row],[Days]]),$G$5,"")),"")
A45: Glasgow | B45: 16 | C45: ... Demo | P45: =IFERROR(+IF(P$29=ProposalToGnatt[[#This Row],[Start Date]],Milestone_Marker,IF(AND(P$29>ProposalToGnatt[[#This Row],[Start Date]],P$29<ProposalToGnatt[[#This Row],[Start Date]]+ProposalToGnatt[[#This Row],[Days]]),$G$5,"")),"") -> 1 | Q45: =IFERROR(+IF(Q$29=ProposalToGnatt[[#This Row],[Start Date]],Milestone_Marker,IF(AND(Q$29>ProposalToGnatt[[#This Row],[Start Date]],Q$29<ProposalToGnatt[[#This Row],[Start Date]]+ProposalToGnatt[[#This Row],[Days]]),$G$5,"")),"") | R45: =IFERROR(+IF(R$29=ProposalToGnatt[[#This Row],[Start Date]],Milestone_Marker,IF(AND(R$29>ProposalToGnatt[[#This Row],[Start Date]],R$29<ProposalToGnatt[[#This Row],[Start Date]]+ProposalToGnatt[[#This Row],[Days]]),$G$5,"")),"") | S45: =IFERROR(+IF(S$29=ProposalToGnatt[[#This Row],[Start Date]],Milestone_Marker,IF(AND(S$29>ProposalToGnatt[[#This Row],[Start Date]],S$29<ProposalToGnatt[[#This Row],[Start Date]]+ProposalToGnatt[[#This Row],[Days]]),$G$5,"")),"") | T45: =IFERROR(+IF(T$29=ProposalToGnatt[[#This Row],[Start Date]],Milestone_Marker,IF(AND(T$29>ProposalToGnatt[[#This Row],[Start Date]],T$29<ProposalToGnatt[[#This Row],[Start Date]]+ProposalToGnatt[[#This Row],[Days]]),$G$5,"")),"") | U45: =IFERROR(+IF(U$29=ProposalToGnatt[[#This Row],[Start Date]],Milestone_Marker,IF(AND(U$29>ProposalToGnatt[[#This Row],[Start Date]],U$29<ProposalToGnatt[[#This Row],[Start Date]]+ProposalToGnatt[[#This Row],[Days]]),$G$5,"")),"") | V45: =IFERROR(+IF(V$29=ProposalToGnatt[[#This Row],[Start Date]],Milestone_Marker,IF(AND(V$29>ProposalToGnatt[[#This Row],[Start Date]],V$29<ProposalToGnatt[[#This Row],[Start Date]]+ProposalToGnatt[[#This Row],[Days]]),$G$5,"")),"") | W45: =IFERROR(+IF(W$29=ProposalToGnatt[[#This Row],[Start Date]],Milestone_Marker,IF(AND(W$29>ProposalToGnatt[[#This Row],[Start Date]],W$29<ProposalToGnatt[[#This Row],[Start Date]]+ProposalToGnatt[[#This Row],[Days]]),$G$5,"")),"") | ... CU45: =IFERROR(+IF(CU$29=ProposalToGnatt[[#This Row],[Start Date]],Milestone_Marker,IF(AND(CU$29>ProposalToGnatt[[#This Row],[Start Date]],CU$29<ProposalToGnatt[[#This Row],[Start Date]]+ProposalToGnatt[[#This Row],[Days]]),$G$5,"")),"")
P46: =IFERROR(+IF(P$29=ProposalToGnatt[[#This Row],[Start Date]],Milestone_Marker,IF(AND(P$29>ProposalToGnatt[[#This Row],[Start Date]],P$29<ProposalToGnatt[[#This Row],[Start Date]]+ProposalToGnatt[[#This Row],[Days]]),$G$5,"")),"") | Q46: =IFERROR(+IF(Q$29=ProposalToGnatt[[#This Row],[Start Date]],Milestone_Marker,IF(AND(Q$29>ProposalToGnatt[[#This Row],[Start Date]],Q$29<ProposalToGnatt[[#This Row],[Start Date]]+ProposalToGnatt[[#This Row],[Days]]),$G$5,"")),"") | R46: =IFERROR(+IF(R$29=ProposalToGnatt[[#This Row],[Start Date]],Milestone_Marker,IF(AND(R$29>ProposalToGnatt[[#This Row],[Start Date]],R$29<ProposalToGnatt[[#This Row],[Start Date]]+ProposalToGnatt[[#This Row],[Days]]),$G$5,"")),"") | S46: =IFERROR(+IF(S$29=ProposalToGnatt[[#This Row],[Start Date]],Milestone_Marker,IF(AND(S$29>ProposalToGnatt[[#This Row],[Start Date]],S$29<ProposalToGnatt[[#This Row],[Start Date]]+ProposalToGnatt[[#This Row],[Days]]),$G$5,"")),"") | T46: =IFERROR(+IF(T$29=ProposalToGnatt[[#This Row],[Start Date]],Milestone_Marker,IF(AND(T$29>ProposalToGnatt[[#This Row],[Start Date]],T$29<ProposalToGnatt[[#This Row],[Start Date]]+ProposalToGnatt[[#This Row],[Days]]),$G$5,"")),"") | U46: =IFERROR(+IF(U$29=ProposalToGnatt[[#This Row],[Start Date]],Milestone_Marker,IF(AND(U$29>ProposalToGnatt[[#This Row],[Start Date]],U$29<ProposalToGnatt[[#This Row],[Start Date]]+ProposalToGnatt[[#This Row],[Days]]),$G$5,"")),"") | V46: =IFERROR(+IF(V$29=ProposalToGnatt[[#This Row],[Start Date]],Milestone_Marker,IF(AND(V$29>ProposalToGnatt[[#This Row],[Start Date]],V$29<ProposalToGnatt[[#This Row],[Start Date]]+ProposalToGnatt[[#This Row],[Days]]),$G$5,"")),"") | W46: =IFERROR(+IF(W$29=ProposalToGnatt[[#This Row],[Start Date]],Milestone_Marker,IF(AND(W$29>ProposalToGnatt[[#This Row],[Start Date]],W$29<ProposalToGnatt[[#This Row],[Start Date]]+ProposalToGnatt[[#This Row],[Days]]),$G$5,"")),"") | ... CU46: =IFERROR(+IF(CU$29=ProposalToGnatt[[#This Row],[Start Date]],Milestone_Marker,IF(AND(CU$29>ProposalToGnatt[[#This Row],[Start Date]],CU$29<ProposalToGnatt[[#This Row],[Start Date]]+ProposalToGnatt[[#This Row],[Days]]),$G$5,"")),"")
P47: =IFERROR(+IF(P$29=ProposalToGnatt[[#This Row],[Start Date]],Milestone_Marker,IF(AND(P$29>ProposalToGnatt[[#This Row],[Start Date]],P$29<ProposalToGnatt[[#This Row],[Start Date]]+ProposalToGnatt[[#This Row],[Days]]),$G$5,"")),"") | Q47: =IFERROR(+IF(Q$29=ProposalToGnatt[[#This Row],[Start Date]],Milestone_Marker,IF(AND(Q$29>ProposalToGnatt[[#This Row],[Start Date]],Q$29<ProposalToGnatt[[#This Row],[Start Date]]+ProposalToGnatt[[#This Row],[Days]]),$G$5,"")),"") | R47: =IFERROR(+IF(R$29=ProposalToGnatt[[#This Row],[Start Date]],Milestone_Marker,IF(AND(R$29>ProposalToGnatt[[#This Row],[Start Date]],R$29<ProposalToGnatt[[#This Row],[Start Date]]+ProposalToGnatt[[#This Row],[Days]]),$G$5,"")),"") | S47: =IFERROR(+IF(S$29=ProposalToGnatt[[#This Row],[Start Date]],Milestone_Marker,IF(AND(S$29>ProposalToGnatt[[#This Row],[Start Date]],S$29<ProposalToGnatt[[#This Row],[Start Date]]+ProposalToGnatt[[#This Row],[Days]]),$G$5,"")),"") | T47: =IFERROR(+IF(T$29=ProposalToGnatt[[#This Row],[Start Date]],Milestone_Marker,IF(AND(T$29>ProposalToGnatt[[#This Row],[Start Date]],T$29<ProposalToGnatt[[#This Row],[Start Date]]+ProposalToGnatt[[#This Row],[Days]]),$G$5,"")),"") | U47: =IFERROR(+IF(U$29=ProposalToGnatt[[#This Row],[Start Date]],Milestone_Marker,IF(AND(U$29>ProposalToGnatt[[#This Row],[Start Date]],U$29<ProposalToGnatt[[#This Row],[Start Date]]+ProposalToGnatt[[#This Row],[Days]]),$G$5,"")),"") | V47: =IFERROR(+IF(V$29=ProposalToGnatt[[#This Row],[Start Date]],Milestone_Marker,IF(AND(V$29>ProposalToGnatt[[#This Row],[Start Date]],V$29<ProposalToGnatt[[#This Row],[Start Date]]+ProposalToGnatt[[#This Row],[Days]]),$G$5,"")),"") | W47: =IFERROR(+IF(W$29=ProposalToGnatt[[#This Row],[Start Date]],Milestone_Marker,IF(AND(W$29>ProposalToGnatt[[#This Row],[Start Date]],W$29<ProposalToGnatt[[#This Row],[Start Date]]+ProposalToGnatt[[#This Row],[Days]]),$G$5,"")),"") | ... CU47: =IFERROR(+IF(CU$29=ProposalToGnatt[[#This Row],[Start Date]],Milestone_Marker,IF(AND(CU$29>ProposalToGnatt[[#This Row],[Start Date]],CU$29<ProposalToGnatt[[#This Row],[Start Date]]+ProposalToGnatt[[#This Row],[Days]]),$G$5,"")),"")
P48: =IFERROR(+IF(P$29=ProposalToGnatt[[#This Row],[Start Date]],Milestone_Marker,IF(AND(P$29>ProposalToGnatt[[#This Row],[Start Date]],P$29<ProposalToGnatt[[#This Row],[Start Date]]+ProposalToGnatt[[#This Row],[Days]]),$G$5,"")),"") | Q48: =IFERROR(+IF(Q$29=ProposalToGnatt[[#This Row],[Start Date]],Milestone_Marker,IF(AND(Q$29>ProposalToGnatt[[#This Row],[Start Date]],Q$29<ProposalToGnatt[[#This Row],[Start Date]]+ProposalToGnatt[[#This Row],[Days]]),$G$5,"")),"") | R48: =IFERROR(+IF(R$29=ProposalToGnatt[[#This Row],[Start Date]],Milestone_Marker,IF(AND(R$29>ProposalToGnatt[[#This Row],[Start Date]],R$29<ProposalToGnatt[[#This Row],[Start Date]]+ProposalToGnatt[[#This Row],[Days]]),$G$5,"")),"") | S48: =IFERROR(+IF(S$29=ProposalToGnatt[[#This Row],[Start Date]],Milestone_Marker,IF(AND(S$29>ProposalToGnatt[[#This Row],[Start Date]],S$29<ProposalToGnatt[[#This Row],[Start Date]]+ProposalToGnatt[[#This Row],[Days]]),$G$5,"")),"") | T48: =IFERROR(+IF(T$29=ProposalToGnatt[[#This Row],[Start Date]],Milestone_Marker,IF(AND(T$29>ProposalToGnatt[[#This Row],[Start Date]],T$29<ProposalToGnatt[[#This Row],[Start Date]]+ProposalToGnatt[[#This Row],[Days]]),$G$5,"")),"") | U48: =IFERROR(+IF(U$29=ProposalToGnatt[[#This Row],[Start Date]],Milestone_Marker,IF(AND(U$29>ProposalToGnatt[[#This Row],[Start Date]],U$29<ProposalToGnatt[[#This Row],[Start Date]]+ProposalToGnatt[[#This Row],[Days]]),$G$5,"")),"") | V48: =IFERROR(+IF(V$29=ProposalToGnatt[[#This Row],[Start Date]],Milestone_Marker,IF(AND(V$29>ProposalToGnatt[[#This Row],[Start Date]],V$29<ProposalToGnatt[[#This Row],[Start Date]]+ProposalToGnatt[[#This Row],[Days]]),$G$5,"")),"") | W48: =IFERROR(+IF(W$29=ProposalToGnatt[[#This Row],[Start Date]],Milestone_Marker,IF(AND(W$29>ProposalToGnatt[[#This Row],[Start Date]],W$29<ProposalToGnatt[[#This Row],[Start Date]]+ProposalToGnatt[[#This Row],[Days]]),$G$5,"")),"") | ... CU48: =IFERROR(+IF(CU$29=ProposalToGnatt[[#This Row],[Start Date]],Milestone_Marker,IF(AND(CU$29>ProposalToGnatt[[#This Row],[Start Date]],CU$29<ProposalToGnatt[[#This Row],[Start Date]]+ProposalToGnatt[[#This Row],[Days]]),$G$5,"")),"")
P49: =IFERROR(+IF(P$29=ProposalToGnatt[[#This Row],[Start Date]],Milestone_Marker,IF(AND(P$29>ProposalToGnatt[[#This Row],[Start Date]],P$29<ProposalToGnatt[[#This Row],[Start Date]]+ProposalToGnatt[[#This Row],[Days]]),$G$5,"")),"") | Q49: =IFERROR(+IF(Q$29=ProposalToGnatt[[#This Row],[Start Date]],Milestone_Marker,IF(AND(Q$29>ProposalToGnatt[[#This Row],[Start Date]],Q$29<ProposalToGnatt[[#This Row],[Start Date]]+ProposalToGnatt[[#This Row],[Days]]),$G$5,"")),"") | R49: =IFERROR(+IF(R$29=ProposalToGnatt[[#This Row],[Start Date]],Milestone_Marker,IF(AND(R$29>ProposalToGnatt[[#This Row],[Start Date]],R$29<ProposalToGnatt[[#This Row],[Start Date]]+ProposalToGnatt[[#This Row],[Days]]),$G$5,"")),"") | S49: =IFERROR(+IF(S$29=ProposalToGnatt[[#This Row],[Start Date]],Milestone_Marker,IF(AND(S$29>ProposalToGnatt[[#This Row],[Start Date]],S$29<ProposalToGnatt[[#This Row],[Start Date]]+ProposalToGnatt[[#This Row],[Days]]),$G$5,"")),"") | T49: =IFERROR(+IF(T$29=ProposalToGnatt[[#This Row],[Start Date]],Milestone_Marker,IF(AND(T$29>ProposalToGnatt[[#This Row],[Start Date]],T$29<ProposalToGnatt[[#This Row],[Start Date]]+ProposalToGnatt[[#This Row],[Days]]),$G$5,"")),"") | U49: =IFERROR(+IF(U$29=ProposalToGnatt[[#This Row],[Start Date]],Milestone_Marker,IF(AND(U$29>ProposalToGnatt[[#This Row],[Start Date]],U$29<ProposalToGnatt[[#This Row],[Start Date]]+ProposalToGnatt[[#This Row],[Days]]),$G$5,"")),"") | V49: =IFERROR(+IF(V$29=ProposalToGnatt[[#This Row],[Start Date]],Milestone_Marker,IF(AND(V$29>ProposalToGnatt[[#This Row],[Start Date]],V$29<ProposalToGnatt[[#This Row],[Start Date]]+ProposalToGnatt[[#This Row],[Days]]),$G$5,"")),"") | W49: =IFERROR(+IF(W$29=ProposalToGnatt[[#This Row],[Start Date]],Milestone_Marker,IF(AND(W$29>ProposalToGnatt[[#This Row],[Start Date]],W$29<ProposalToGnatt[[#This Row],[Start Date]]+ProposalToGnatt[[#This Row],[Days]]),$G$5,"")),"") | ... CU49: =IFERROR(+IF(CU$29=ProposalToGnatt[[#This Row],[Start Date]],Milestone_Marker,IF(AND(CU$29>ProposalToGnatt[[#This Row],[Start Date]],CU$29<ProposalToGnatt[[#This Row],[Start Date]]+ProposalToGnatt[[#This Row],[Days]]),$G$5,"")),"")
P50: =IFERROR(+IF(P$29=ProposalToGnatt[[#This Row],[Start Date]],Milestone_Marker,IF(AND(P$29>ProposalToGnatt[[#This Row],[Start Date]],P$29<ProposalToGnatt[[#This Row],[Start Date]]+ProposalToGnatt[[#This Row],[Days]]),$G$5,"")),"") | Q50: =IFERROR(+IF(Q$29=ProposalToGnatt[[#This Row],[Start Date]],Milestone_Marker,IF(AND(Q$29>ProposalToGnatt[[#This Row],[Start Date]],Q$29<ProposalToGnatt[[#This Row],[Start Date]]+ProposalToGnatt[[#This Row],[Days]]),$G$5,"")),"") | R50: =IFERROR(+IF(R$29=ProposalToGnatt[[#This Row],[Start Date]],Milestone_Marker,IF(AND(R$29>ProposalToGnatt[[#This Row],[Start Date]],R$29<ProposalToGnatt[[#This Row],[Start Date]]+ProposalToGnatt[[#This Row],[Days]]),$G$5,"")),"") | S50: =IFERROR(+IF(S$29=ProposalToGnatt[[#This Row],[Start Date]],Milestone_Marker,IF(AND(S$29>ProposalToGnatt[[#This Row],[Start Date]],S$29<ProposalToGnatt[[#This Row],[Start Date]]+ProposalToGnatt[[#This Row],[Days]]),$G$5,"")),"") | T50: =IFERROR(+IF(T$29=ProposalToGnatt[[#This Row],[Start Date]],Milestone_Marker,IF(AND(T$29>ProposalToGnatt[[#This Row],[Start Date]],T$29<ProposalToGnatt[[#This Row],[Start Date]]+ProposalToGnatt[[#This Row],[Days]]),$G$5,"")),"") | U50: =IFERROR(+IF(U$29=ProposalToGnatt[[#This Row],[Start Date]],Milestone_Marker,IF(AND(U$29>ProposalToGnatt[[#This Row],[Start Date]],U$29<ProposalToGnatt[[#This Row],[Start Date]]+ProposalToGnatt[[#This Row],[Days]]),$G$5,"")),"") | V50: =IFERROR(+IF(V$29=ProposalToGnatt[[#This Row],[Start Date]],Milestone_Marker,IF(AND(V$29>ProposalToGnatt[[#This Row],[Start Date]],V$29<ProposalToGnatt[[#This Row],[Start Date]]+ProposalToGnatt[[#This Row],[Days]]),$G$5,"")),"") | W50: =IFERROR(+IF(W$29=ProposalToGnatt[[#This Row],[Start Date]],Milestone_Marker,IF(AND(W$29>ProposalToGnatt[[#This Row],[Start Date]],W$29<ProposalToGnatt[[#This Row],[Start Date]]+ProposalToGnatt[[#This Row],[Days]]),$G$5,"")),"") | ... CU50: =IFERROR(+IF(CU$29=ProposalToGnatt[[#This Row],[Start Date]],Milestone_Marker,IF(AND(CU$29>ProposalToGnatt[[#This Row],[Start Date]],CU$29<ProposalToGnatt[[#This Row],[Start Date]]+ProposalToGnatt[[#This Row],[Days]]),$G$5,"")),"")
P51: =IFERROR(+IF(P$29=ProposalToGnatt[[#This Row],[Start Date]],Milestone_Marker,IF(AND(P$29>ProposalToGnatt[[#This Row],[Start Date]],P$29<ProposalToGnatt[[#This Row],[Start Date]]+ProposalToGnatt[[#This Row],[Days]]),$G$5,"")),"") | Q51: =IFERROR(+IF(Q$29=ProposalToGnatt[[#This Row],[Start Date]],Milestone_Marker,IF(AND(Q$29>ProposalToGnatt[[#This Row],[Start Date]],Q$29<ProposalToGnatt[[#This Row],[Start Date]]+ProposalToGnatt[[#This Row],[Days]]),$G$5,"")),"") | R51: =IFERROR(+IF(R$29=ProposalToGnatt[[#This Row],[Start Date]],Milestone_Marker,IF(AND(R$29>ProposalToGnatt[[#This Row],[Start Date]],R$29<ProposalToGnatt[[#This Row],[Start Date]]+ProposalToGnatt[[#This Row],[Days]]),$G$5,"")),"") | S51: =IFERROR(+IF(S$29=ProposalToGnatt[[#This Row],[Start Date]],Milestone_Marker,IF(AND(S$29>ProposalToGnatt[[#This Row],[Start Date]],S$29<ProposalToGnatt[[#This Row],[Start Date]]+ProposalToGnatt[[#This Row],[Days]]),$G$5,"")),"") | T51: =IFERROR(+IF(T$29=ProposalToGnatt[[#This Row],[Start Date]],Milestone_Marker,IF(AND(T$29>ProposalToGnatt[[#This Row],[Start Date]],T$29<ProposalToGnatt[[#This Row],[Start Date]]+ProposalToGnatt[[#This Row],[Days]]),$G$5,"")),"") | U51: =IFERROR(+IF(U$29=ProposalToGnatt[[#This Row],[Start Date]],Milestone_Marker,IF(AND(U$29>ProposalToGnatt[[#This Row],[Start Date]],U$29<ProposalToGnatt[[#This Row],[Start Date]]+ProposalToGnatt[[#This Row],[Days]]),$G$5,"")),"") | V51: =IFERROR(+IF(V$29=ProposalToGnatt[[#This Row],[Start Date]],Milestone_Marker,IF(AND(V$29>ProposalToGnatt[[#This Row],[Start Date]],V$29<ProposalToGnatt[[#This Row],[Start Date]]+ProposalToGnatt[[#This Row],[Days]]),$G$5,"")),"") | W51: =IFERROR(+IF(W$29=ProposalToGnatt[[#This Row],[Start Date]],Milestone_Marker,IF(AND(W$29>ProposalToGnatt[[#This Row],[Start Date]],W$29<ProposalToGnatt[[#This Row],[Start Date]]+ProposalToGnatt[[#This Row],[Days]]),$G$5,"")),"") | ... CU51: =IFERROR(+IF(CU$29=ProposalToGnatt[[#This Row],[Start Date]],Milestone_Marker,IF(AND(CU$29>ProposalToGnatt[[#This Row],[Start Date]],CU$29<ProposalToGnatt[[#This Row],[Start Date]]+ProposalToGnatt[[#This Row],[Days]]),$G$5,"")),"")
P52: =IFERROR(+IF(P$29=ProposalToGnatt[[#This Row],[Start Date]],Milestone_Marker,IF(AND(P$29>ProposalToGnatt[[#This Row],[Start Date]],P$29<ProposalToGnatt[[#This Row],[Start Date]]+ProposalToGnatt[[#This Row],[Days]]),$G$5,"")),"") | Q52: =IFERROR(+IF(Q$29=ProposalToGnatt[[#This Row],[Start Date]],Milestone_Marker,IF(AND(Q$29>ProposalToGnatt[[#This Row],[Start Date]],Q$29<ProposalToGnatt[[#This Row],[Start Date]]+ProposalToGnatt[[#This Row],[Days]]),$G$5,"")),"") | R52: =IFERROR(+IF(R$29=ProposalToGnatt[[#This Row],[Start Date]],Milestone_Marker,IF(AND(R$29>ProposalToGnatt[[#This Row],[Start Date]],R$29<ProposalToGnatt[[#This Row],[Start Date]]+ProposalToGnatt[[#This Row],[Days]]),$G$5,"")),"") | S52: =IFERROR(+IF(S$29=ProposalToGnatt[[#This Row],[Start Date]],Milestone_Marker,IF(AND(S$29>ProposalToGnatt[[#This Row],[Start Date]],S$29<ProposalToGnatt[[#This Row],[Start Date]]+ProposalToGnatt[[#This Row],[Days]]),$G$5,"")),"") | T52: =IFERROR(+IF(T$29=ProposalToGnatt[[#This Row],[Start Date]],Milestone_Marker,IF(AND(T$29>ProposalToGnatt[[#This Row],[Start Date]],T$29<ProposalToGnatt[[#This Row],[Start Date]]+ProposalToGnatt[[#This Row],[Days]]),$G$5,"")),"") | U52: =IFERROR(+IF(U$29=ProposalToGnatt[[#This Row],[Start Date]],Milestone_Marker,IF(AND(U$29>ProposalToGnatt[[#This Row],[Start Date]],U$29<ProposalToGnatt[[#This Row],[Start Date]]+ProposalToGnatt[[#This Row],[Days]]),$G$5,"")),"") | V52: =IFERROR(+IF(V$29=ProposalToGnatt[[#This Row],[Start Date]],Milestone_Marker,IF(AND(V$29>ProposalToGnatt[[#This Row],[Start Date]],V$29<ProposalToGnatt[[#This Row],[Start Date]]+ProposalToGnatt[[#This Row],[Days]]),$G$5,"")),"") | W52: =IFERROR(+IF(W$29=ProposalToGnatt[[#This Row],[Start Date]],Milestone_Marker,IF(AND(W$29>ProposalToGnatt[[#This Row],[Start Date]],W$29<ProposalToGnatt[[#This Row],[Start Date]]+ProposalToGnatt[[#This Row],[Days]]),$G$5,"")),"") | ... CU52: =IFERROR(+IF(CU$29=ProposalToGnatt[[#This Row],[Start Date]],Milestone_Marker,IF(AND(CU$29>ProposalToGnatt[[#This Row],[Start Date]],CU$29<ProposalToGnatt[[#This Row],[Start Date]]+ProposalToGnatt[[#This Row],[Days]]),$G$5,"")),"")
P53: =IFERROR(+IF(P$29=ProposalToGnatt[[#This Row],[Start Date]],Milestone_Marker,IF(AND(P$29>ProposalToGnatt[[#This Row],[Start Date]],P$29<ProposalToGnatt[[#This Row],[Start Date]]+ProposalToGnatt[[#This Row],[Days]]),$G$5,"")),"") | Q53: =IFERROR(+IF(Q$29=ProposalToGnatt[[#This Row],[Start Date]],Milestone_Marker,IF(AND(Q$29>ProposalToGnatt[[#This Row],[Start Date]],Q$29<ProposalToGnatt[[#This Row],[Start Date]]+ProposalToGnatt[[#This Row],[Days]]),$G$5,"")),"") | R53: =IFERROR(+IF(R$29=ProposalToGnatt[[#This Row],[Start Date]],Milestone_Marker,IF(AND(R$29>ProposalToGnatt[[#This Row],[Start Date]],R$29<ProposalToGnatt[[#This Row],[Start Date]]+ProposalToGnatt[[#This Row],[Days]]),$G$5,"")),"") | S53: =IFERROR(+IF(S$29=ProposalToGnatt[[#This Row],[Start Date]],Milestone_Marker,IF(AND(S$29>ProposalToGnatt[[#This Row],[Start Date]],S$29<ProposalToGnatt[[#This Row],[Start Date]]+ProposalToGnatt[[#This Row],[Days]]),$G$5,"")),"") | T53: =IFERROR(+IF(T$29=ProposalToGnatt[[#This Row],[Start Date]],Milestone_Marker,IF(AND(T$29>ProposalToGnatt[[#This Row],[Start Date]],T$29<ProposalToGnatt[[#This Row],[Start Date]]+ProposalToGnatt[[#This Row],[Days]]),$G$5,"")),"") | U53: =IFERROR(+IF(U$29=ProposalToGnatt[[#This Row],[Start Date]],Milestone_Marker,IF(AND(U$29>ProposalToGnatt[[#This Row],[Start Date]],U$29<ProposalToGnatt[[#This Row],[Start Date]]+ProposalToGnatt[[#This Row],[Days]]),$G$5,"")),"") | V53: =IFERROR(+IF(V$29=ProposalToGnatt[[#This Row],[Start Date]],Milestone_Marker,IF(AND(V$29>ProposalToGnatt[[#This Row],[Start Date]],V$29<ProposalToGnatt[[#This Row],[Start Date]]+ProposalToGnatt[[#This Row],[Days]]),$G$5,"")),"") | W53: =IFERROR(+IF(W$29=ProposalToGnatt[[#This Row],[Start Date]],Milestone_Marker,IF(AND(W$29>ProposalToGnatt[[#This Row],[Start Date]],W$29<ProposalToGnatt[[#This Row],[Start Date]]+ProposalToGnatt[[#This Row],[Days]]),$G$5,"")),"") | ... CU53: =IFERROR(+IF(CU$29=ProposalToGnatt[[#This Row],[Start Date]],Milestone_Marker,IF(AND(CU$29>ProposalToGnatt[[#This Row],[Start Date]],CU$29<ProposalToGnatt[[#This Row],[Start Date]]+ProposalToGnatt[[#This Row],[Days]]),$G$5,"")),"")
P54: =IFERROR(+IF(P$29=ProposalToGnatt[[#This Row],[Start Date]],Milestone_Marker,IF(AND(P$29>ProposalToGnatt[[#This Row],[Start Date]],P$29<ProposalToGnatt[[#This Row],[Start Date]]+ProposalToGnatt[[#This Row],[Days]]),$G$5,"")),"") | Q54: =IFERROR(+IF(Q$29=ProposalToGnatt[[#This Row],[Start Date]],Milestone_Marker,IF(AND(Q$29>ProposalToGnatt[[#This Row],[Start Date]],Q$29<ProposalToGnatt[[#This Row],[Start Date]]+ProposalToGnatt[[#This Row],[Days]]),$G$5,"")),"") | R54: =IFERROR(+IF(R$29=ProposalToGnatt[[#This Row],[Start Date]],Milestone_Marker,IF(AND(R$29>ProposalToGnatt[[#This Row],[Start Date]],R$29<ProposalToGnatt[[#This Row],[Start Date]]+ProposalToGnatt[[#This Row],[Days]]),$G$5,"")),"") | S54: =IFERROR(+IF(S$29=ProposalToGnatt[[#This Row],[Start Date]],Milestone_Marker,IF(AND(S$29>ProposalToGnatt[[#This Row],[Start Date]],S$29<ProposalToGnatt[[#This Row],[Start Date]]+ProposalToGnatt[[#This Row],[Days]]),$G$5,"")),"") | T54: =IFERROR(+IF(T$29=ProposalToGnatt[[#This Row],[Start Date]],Milestone_Marker,IF(AND(T$29>ProposalToGnatt[[#This Row],[Start Date]],T$29<ProposalToGnatt[[#This Row],[Start Date]]+ProposalToGnatt[[#This Row],[Days]]),$G$5,"")),"") | U54: =IFERROR(+IF(U$29=ProposalToGnatt[[#This Row],[Start Date]],Milestone_Marker,IF(AND(U$29>ProposalToGnatt[[#This Row],[Start Date]],U$29<ProposalToGnatt[[#This Row],[Start Date]]+ProposalToGnatt[[#This Row],[Days]]),$G$5,"")),"") | V54: =IFERROR(+IF(V$29=ProposalToGnatt[[#This Row],[Start Date]],Milestone_Marker,IF(AND(V$29>ProposalToGnatt[[#This Row],[Start Date]],V$29<ProposalToGnatt[[#This Row],[Start Date]]+ProposalToGnatt[[#This Row],[Days]]),$G$5,"")),"") | W54: =IFERROR(+IF(W$29=ProposalToGnatt[[#This Row],[Start Date]],Milestone_Marker,IF(AND(W$29>ProposalToGnatt[[#This Row],[Start Date]],W$29<ProposalToGnatt[[#This Row],[Start Date]]+ProposalToGnatt[[#This Row],[Days]]),$G$5,"")),"") | ... CU54: =IFERROR(+IF(CU$29=ProposalToGnatt[[#This Row],[Start Date]],Milestone_Marker,IF(AND(CU$29>ProposalToGnatt[[#This Row],[Start Date]],CU$29<ProposalToGnatt[[#This Row],[Start Date]]+ProposalToGnatt[[#This Row],[Days]]),$G$5,"")),"")
P55: =IFERROR(+IF(P$29=ProposalToGnatt[[#This Row],[Start Date]],Milestone_Marker,IF(AND(P$29>ProposalToGnatt[[#This Row],[Start Date]],P$29<ProposalToGnatt[[#This Row],[Start Date]]+ProposalToGnatt[[#This Row],[Days]]),$G$5,"")),"") | Q55: =IFERROR(+IF(Q$29=ProposalToGnatt[[#This Row],[Start Date]],Milestone_Marker,IF(AND(Q$29>ProposalToGnatt[[#This Row],[Start Date]],Q$29<ProposalToGnatt[[#This Row],[Start Date]]+ProposalToGnatt[[#This Row],[Days]]),$G$5,"")),"") | R55: =IFERROR(+IF(R$29=ProposalToGnatt[[#This Row],[Start Date]],Milestone_Marker,IF(AND(R$29>ProposalToGnatt[[#This Row],[Start Date]],R$29<ProposalToGnatt[[#This Row],[Start Date]]+ProposalToGnatt[[#This Row],[Days]]),$G$5,"")),"") | S55: =IFERROR(+IF(S$29=ProposalToGnatt[[#This Row],[Start Date]],Milestone_Marker,IF(AND(S$29>ProposalToGnatt[[#This Row],[Start Date]],S$29<ProposalToGnatt[[#This Row],[Start Date]]+ProposalToGnatt[[#This Row],[Days]]),$G$5,"")),"") | T55: =IFERROR(+IF(T$29=ProposalToGnatt[[#This Row],[Start Date]],Milestone_Marker,IF(AND(T$29>ProposalToGnatt[[#This Row],[Start Date]],T$29<ProposalToGnatt[[#This Row],[Start Date]]+ProposalToGnatt[[#This Row],[Days]]),$G$5,"")),"") | U55: =IFERROR(+IF(U$29=ProposalToGnatt[[#This Row],[Start Date]],Milestone_Marker,IF(AND(U$29>ProposalToGnatt[[#This Row],[Start Date]],U$29<ProposalToGnatt[[#This Row],[Start Date]]+ProposalToGnatt[[#This Row],[Days]]),$G$5,"")),"") | V55: =IFERROR(+IF(V$29=ProposalToGnatt[[#This Row],[Start Date]],Milestone_Marker,IF(AND(V$29>ProposalToGnatt[[#This Row],[Start Date]],V$29<ProposalToGnatt[[#This Row],[Start Date]]+ProposalToGnatt[[#This Row],[Days]]),$G$5,"")),"") | W55: =IFERROR(+IF(W$29=ProposalToGnatt[[#This Row],[Start Date]],Milestone_Marker,IF(AND(W$29>ProposalToGnatt[[#This Row],[Start Date]],W$29<ProposalToGnatt[[#This Row],[Start Date]]+ProposalToGnatt[[#This Row],[Days]]),$G$5,"")),"") | ... CU55: =IFERROR(+IF(CU$29=ProposalToGnatt[[#This Row],[Start Date]],Milestone_Marker,IF(AND(CU$29>ProposalToGnatt[[#This Row],[Start Date]],CU$29<ProposalToGnatt[[#This Row],[Start Date]]+ProposalToGnatt[[#This Row],[Days]]),$G$5,"")),"")
P56: =IFERROR(+IF(P$29=ProposalToGnatt[[#This Row],[Start Date]],Milestone_Marker,IF(AND(P$29>ProposalToGnatt[[#This Row],[Start Date]],P$29<ProposalToGnatt[[#This Row],[Start Date]]+ProposalToGnatt[[#This Row],[Days]]),$G$5,"")),"") | Q56: =IFERROR(+IF(Q$29=ProposalToGnatt[[#This Row],[Start Date]],Milestone_Marker,IF(AND(Q$29>ProposalToGnatt[[#This Row],[Start Date]],Q$29<ProposalToGnatt[[#This Row],[Start Date]]+ProposalToGnatt[[#This Row],[Days]]),$G$5,"")),"") | R56: =IFERROR(+IF(R$29=ProposalToGnatt[[#This Row],[Start Date]],Milestone_Marker,IF(AND(R$29>ProposalToGnatt[[#This Row],[Start Date]],R$29<ProposalToGnatt[[#This Row],[Start Date]]+ProposalToGnatt[[#This Row],[Days]]),$G$5,"")),"") | S56: =IFERROR(+IF(S$29=ProposalToGnatt[[#This Row],[Start Date]],Milestone_Marker,IF(AND(S$29>ProposalToGnatt[[#This Row],[Start Date]],S$29<ProposalToGnatt[[#This Row],[Start Date]]+ProposalToGnatt[[#This Row],[Days]]),$G$5,"")),"") | T56: =IFERROR(+IF(T$29=ProposalToGnatt[[#This Row],[Start Date]],Milestone_Marker,IF(AND(T$29>ProposalToGnatt[[#This Row],[Start Date]],T$29<ProposalToGnatt[[#This Row],[Start Date]]+ProposalToGnatt[[#This Row],[Days]]),$G$5,"")),"") | U56: =IFERROR(+IF(U$29=ProposalToGnatt[[#This Row],[Start Date]],Milestone_Marker,IF(AND(U$29>ProposalToGnatt[[#This Row],[Start Date]],U$29<ProposalToGnatt[[#This Row],[Start Date]]+ProposalToGnatt[[#This Row],[Days]]),$G$5,"")),"") | V56: =IFERROR(+IF(V$29=ProposalToGnatt[[#This Row],[Start Date]],Milestone_Marker,IF(AND(V$29>ProposalToGnatt[[#This Row],[Start Date]],V$29<ProposalToGnatt[[#This Row],[Start Date]]+ProposalToGnatt[[#This Row],[Days]]),$G$5,"")),"") | W56: =IFERROR(+IF(W$29=ProposalToGnatt[[#This Row],[Start Date]],Milestone_Marker,IF(AND(W$29>ProposalToGnatt[[#This Row],[Start Date]],W$29<ProposalToGnatt[[#This Row],[Start Date]]+ProposalToGnatt[[#This Row],[Days]]),$G$5,"")),"") | ... CU56: =IFERROR(+IF(CU$29=ProposalToGnatt[[#This Row],[Start Date]],Milestone_Marker,IF(AND(CU$29>ProposalToGnatt[[#This Row],[Start Date]],CU$29<ProposalToGnatt[[#This Row],[Start Date]]+ProposalToGnatt[[#This Row],[Days]]),$G$5,"")),"")
P57: =IFERROR(+IF(P$29=ProposalToGnatt[[#This Row],[Start Date]],Milestone_Marker,IF(AND(P$29>ProposalToGnatt[[#This Row],[Start Date]],P$29<ProposalToGnatt[[#This Row],[Start Date]]+ProposalToGnatt[[#This Row],[Days]]),$G$5,"")),"") | Q57: =IFERROR(+IF(Q$29=ProposalToGnatt[[#This Row],[Start Date]],Milestone_Marker,IF(AND(Q$29>ProposalToGnatt[[#This Row],[Start Date]],Q$29<ProposalToGnatt[[#This Row],[Start Date]]+ProposalToGnatt[[#This Row],[Days]]),$G$5,"")),"") | R57: =IFERROR(+IF(R$29=ProposalToGnatt[[#This Row],[Start Date]],Milestone_Marker,IF(AND(R$29>ProposalToGnatt[[#This Row],[Start Date]],R$29<ProposalToGnatt[[#This Row],[Start Date]]+ProposalToGnatt[[#This Row],[Days]]),$G$5,"")),"") | S57: =IFERROR(+IF(S$29=ProposalToGnatt[[#This Row],[Start Date]],Milestone_Marker,IF(AND(S$29>ProposalToGnatt[[#This Row],[Start Date]],S$29<ProposalToGnatt[[#This Row],[Start Date]]+ProposalToGnatt[[#This Row],[Days]]),$G$5,"")),"") | T57: =IFERROR(+IF(T$29=ProposalToGnatt[[#This Row],[Start Date]],Milestone_Marker,IF(AND(T$29>ProposalToGnatt[[#This Row],[Start Date]],T$29<ProposalToGnatt[[#This Row],[Start Date]]+ProposalToGnatt[[#This Row],[Days]]),$G$5,"")),"") | U57: =IFERROR(+IF(U$29=ProposalToGnatt[[#This Row],[Start Date]],Milestone_Marker,IF(AND(U$29>ProposalToGnatt[[#This Row],[Start Date]],U$29<ProposalToGnatt[[#This Row],[Start Date]]+ProposalToGnatt[[#This Row],[Days]]),$G$5,"")),"") | V57: =IFERROR(+IF(V$29=ProposalToGnatt[[#This Row],[Start Date]],Milestone_Marker,IF(AND(V$29>ProposalToGnatt[[#This Row],[Start Date]],V$29<ProposalToGnatt[[#This Row],[Start Date]]+ProposalToGnatt[[#This Row],[Days]]),$G$5,"")),"") | W57: =IFERROR(+IF(W$29=ProposalToGnatt[[#This Row],[Start Date]],Milestone_Marker,IF(AND(W$29>ProposalToGnatt[[#This Row],[Start Date]],W$29<ProposalToGnatt[[#This Row],[Start Date]]+ProposalToGnatt[[#This Row],[Days]]),$G$5,"")),"") | ... CU57: =IFERROR(+IF(CU$29=ProposalToGnatt[[#This Row],[Start Date]],Milestone_Marker,IF(AND(CU$29>ProposalToGnatt[[#This Row],[Start Date]],CU$29<ProposalToGnatt[[#This Row],[Start Date]]+ProposalToGnatt[[#This Row],[Days]]),$G$5,"")),"")
... P79: =IFERROR(+IF(P$29=ProposalToGnatt[[#This Row],[Start Date]],Milestone_Marker,IF(AND(P$29>ProposalToGnatt[[#This Row],[Start Date]],P$29<ProposalToGnatt[[#This Row],[Start Date]]+ProposalToGnatt[[#This Row],[Days]]),$G$5,"")),"") | Q79: =IFERROR(+IF(Q$29=ProposalToGnatt[[#This Row],[Start Date]],Milestone_Marker,IF(AND(Q$29>ProposalToGnatt[[#This Row],[Start Date]],Q$29<ProposalToGnatt[[#This Row],[Start Date]]+ProposalToGnatt[[#This Row],[Days]]),$G$5,"")),"") | R79: =IFERROR(+IF(R$29=ProposalToGnatt[[#This Row],[Start Date]],Milestone_Marker,IF(AND(R$29>ProposalToGnatt[[#This Row],[Start Date]],R$29<ProposalToGnatt[[#This Row],[Start Date]]+ProposalToGnatt[[#This Row],[Days]]),$G$5,"")),"") | S79: =IFERROR(+IF(S$29=ProposalToGnatt[[#This Row],[Start Date]],Milestone_Marker,IF(AND(S$29>ProposalToGnatt[[#This Row],[Start Date]],S$29<ProposalToGnatt[[#This Row],[Start Date]]+ProposalToGnatt[[#This Row],[Days]]),$G$5,"")),"") | T79: =IFERROR(+IF(T$29=ProposalToGnatt[[#This Row],[Start Date]],Milestone_Marker,IF(AND(T$29>ProposalToGnatt[[#This Row],[Start Date]],T$29<ProposalToGnatt[[#This Row],[Start Date]]+ProposalToGnatt[[#This Row],[Days]]),$G$5,"")),"") | U79: =IFERROR(+IF(U$29=ProposalToGnatt[[#This Row],[Start Date]],Milestone_Marker,IF(AND(U$29>ProposalToGnatt[[#This Row],[Start Date]],U$29<ProposalToGnatt[[#This Row],[Start Date]]+ProposalToGnatt[[#This Row],[Days]]),$G$5,"")),"") | V79: =IFERROR(+IF(V$29=ProposalToGnatt[[#This Row],[Start Date]],Milestone_Marker,IF(AND(V$29>ProposalToGnatt[[#This Row],[Start Date]],V$29<ProposalToGnatt[[#This Row],[Start Date]]+ProposalToGnatt[[#This Row],[Days]]),$G$5,"")),"") | W79: =IFERROR(+IF(W$29=ProposalToGnatt[[#This Row],[Start Date]],Milestone_Marker,IF(AND(W$29>ProposalToGnatt[[#This Row],[Start Date]],W$29<ProposalToGnatt[[#This Row],[Start Date]]+ProposalToGnatt[[#This Row],[Days]]),$G$5,"")),"") | ... CU79: =IFERROR(+IF(CU$29=ProposalToGnatt[[#This Row],[Start Date]],Milestone_Marker,IF(AND(CU$29>ProposalToGnatt[[#This Row],[Start Date]],CU$29<ProposalToGnatt[[#This Row],[Start Date]]+ProposalToGnatt[[#This Row],[Days]]),$G$5,"")),"")
P80: =IFERROR(+IF(P$29=ProposalToGnatt[[#This Row],[Start Date]],Milestone_Marker,IF(AND(P$29>ProposalToGnatt[[#This Row],[Start Date]],P$29<ProposalToGnatt[[#This Row],[Start Date]]+ProposalToGnatt[[#This Row],[Days]]),$G$5,"")),"") | Q80: =IFERROR(+IF(Q$29=ProposalToGnatt[[#This Row],[Start Date]],Milestone_Marker,IF(AND(Q$29>ProposalToGnatt[[#This Row],[Start Date]],Q$29<ProposalToGnatt[[#This Row],[Start Date]]+ProposalToGnatt[[#This Row],[Days]]),$G$5,"")),"") | R80: =IFERROR(+IF(R$29=ProposalToGnatt[[#This Row],[Start Date]],Milestone_Marker,IF(AND(R$29>ProposalToGnatt[[#This Row],[Start Date]],R$29<ProposalToGnatt[[#This Row],[Start Date]]+ProposalToGnatt[[#This Row],[Days]]),$G$5,"")),"") | S80: =IFERROR(+IF(S$29=ProposalToGnatt[[#This Row],[Start Date]],Milestone_Marker,IF(AND(S$29>ProposalToGnatt[[#This Row],[Start Date]],S$29<ProposalToGnatt[[#This Row],[Start Date]]+ProposalToGnatt[[#This Row],[Days]]),$G$5,"")),"") | T80: =IFERROR(+IF(T$29=ProposalToGnatt[[#This Row],[Start Date]],Milestone_Marker,IF(AND(T$29>ProposalToGnatt[[#This Row],[Start Date]],T$29<ProposalToGnatt[[#This Row],[Start Date]]+ProposalToGnatt[[#This Row],[Days]]),$G$5,"")),"") | U80: =IFERROR(+IF(U$29=ProposalToGnatt[[#This Row],[Start Date]],Milestone_Marker,IF(AND(U$29>ProposalToGnatt[[#This Row],[Start Date]],U$29<ProposalToGnatt[[#This Row],[Start Date]]+ProposalToGnatt[[#This Row],[Days]]),$G$5,"")),"") | V80: =IFERROR(+IF(V$29=ProposalToGnatt[[#This Row],[Start Date]],Milestone_Marker,IF(AND(V$29>ProposalToGnatt[[#This Row],[Start Date]],V$29<ProposalToGnatt[[#This Row],[Start Date]]+ProposalToGnatt[[#This Row],[Days]]),$G$5,"")),"") | W80: =IFERROR(+IF(W$29=ProposalToGnatt[[#This Row],[Start Date]],Milestone_Marker,IF(AND(W$29>ProposalToGnatt[[#This Row],[Start Date]],W$29<ProposalToGnatt[[#This Row],[Start Date]]+ProposalToGnatt[[#This Row],[Days]]),$G$5,"")),"") | ... CU80: =IFERROR(+IF(CU$29=ProposalToGnatt[[#This Row],[Start Date]],Milestone_Marker,IF(AND(CU$29>ProposalToGnatt[[#This Row],[Start Date]],CU$29<ProposalToGnatt[[#This Row],[Start Date]]+ProposalToGnatt[[#This Row],[Days]]),$G$5,"")),"") | CV80: =IFERROR(+IF(CT$29=#REF!,Milestone_Marker,IF(AND(CT$29>#REF!,CT$29<=#REF!+#REF!),$G$5,"")),"") | CW80: =IFERROR(+IF(CU$29=#REF!,Milestone_Marker,IF(AND(CU$29>#REF!,CU$29<=#REF!+#REF!),$G$5,"")),"")
P81: =IFERROR(+IF(P$29=ProposalToGnatt[[#This Row],[Start Date]],Milestone_Marker,IF(AND(P$29>ProposalToGnatt[[#This Row],[Start Date]],P$29<ProposalToGnatt[[#This Row],[Start Date]]+ProposalToGnatt[[#This Row],[Days]]),$G$5,"")),"") | Q81: =IFERROR(+IF(Q$29=ProposalToGnatt[[#This Row],[Start Date]],Milestone_Marker,IF(AND(Q$29>ProposalToGnatt[[#This Row],[Start Date]],Q$29<ProposalToGnatt[[#This Row],[Start Date]]+ProposalToGnatt[[#This Row],[Days]]),$G$5,"")),"") | R81: =IFERROR(+IF(R$29=ProposalToGnatt[[#This Row],[Start Date]],Milestone_Marker,IF(AND(R$29>ProposalToGnatt[[#This Row],[Start Date]],R$29<ProposalToGnatt[[#This Row],[Start Date]]+ProposalToGnatt[[#This Row],[Days]]),$G$5,"")),"") | S81: =IFERROR(+IF(S$29=ProposalToGnatt[[#This Row],[Start Date]],Milestone_Marker,IF(AND(S$29>ProposalToGnatt[[#This Row],[Start Date]],S$29<ProposalToGnatt[[#This Row],[Start Date]]+ProposalToGnatt[[#This Row],[Days]]),$G$5,"")),"") | T81: =IFERROR(+IF(T$29=ProposalToGnatt[[#This Row],[Start Date]],Milestone_Marker,IF(AND(T$29>ProposalToGnatt[[#This Row],[Start Date]],T$29<ProposalToGnatt[[#This Row],[Start Date]]+ProposalToGnatt[[#This Row],[Days]]),$G$5,"")),"") | U81: =IFERROR(+IF(U$29=ProposalToGnatt[[#This Row],[Start Date]],Milestone_Marker,IF(AND(U$29>ProposalToGnatt[[#This Row],[Start Date]],U$29<ProposalToGnatt[[#This Row],[Start Date]]+ProposalToGnatt[[#This Row],[Days]]),$G$5,"")),"") | V81: =IFERROR(+IF(V$29=ProposalToGnatt[[#This Row],[Start Date]],Milestone_Marker,IF(AND(V$29>ProposalToGnatt[[#This Row],[Start Date]],V$29<ProposalToGnatt[[#This Row],[Start Date]]+ProposalToGnatt[[#This Row],[Days]]),$G$5,"")),"") | W81: =IFERROR(+IF(W$29=ProposalToGnatt[[#This Row],[Start Date]],Milestone_Marker,IF(AND(W$29>ProposalToGnatt[[#This Row],[Start Date]],W$29<ProposalToGnatt[[#This Row],[Start Date]]+ProposalToGnatt[[#This Row],[Days]]),$G$5,"")),"") | ... CU81: =IFERROR(+IF(CU$29=ProposalToGnatt[[#This Row],[Start Date]],Milestone_Marker,IF(AND(CU$29>ProposalToGnatt[[#This Row],[Start Date]],CU$29<ProposalToGnatt[[#This Row],[Start Date]]+ProposalToGnatt[[#This Row],[Days]]),$G$5,"")),"") | CV81: =IFERROR(+IF(CT$29=#REF!,Milestone_Marker,IF(AND(CT$29>#REF!,CT$29<=#REF!+#REF!),$G$5,"")),"") | CW81: =IFERROR(+IF(CU$29=#REF!,Milestone_Marker,IF(AND(CU$29>#REF!,CU$29<=#REF!+#REF!),$G$5,"")),"")
P82: =IFERROR(+IF(P$29=ProposalToGnatt[[#This Row],[Start Date]],Milestone_Marker,IF(AND(P$29>ProposalToGnatt[[#This Row],[Start Date]],P$29<ProposalToGnatt[[#This Row],[Start Date]]+ProposalToGnatt[[#This Row],[Days]]),$G$5,"")),"") | Q82: =IFERROR(+IF(Q$29=ProposalToGnatt[[#This Row],[Start Date]],Milestone_Marker,IF(AND(Q$29>ProposalToGnatt[[#This Row],[Start Date]],Q$29<ProposalToGnatt[[#This Row],[Start Date]]+ProposalToGnatt[[#This Row],[Days]]),$G$5,"")),"") | R82: =IFERROR(+IF(R$29=ProposalToGnatt[[#This Row],[Start Date]],Milestone_Marker,IF(AND(R$29>ProposalToGnatt[[#This Row],[Start Date]],R$29<ProposalToGnatt[[#This Row],[Start Date]]+ProposalToGnatt[[#This Row],[Days]]),$G$5,"")),"") | S82: =IFERROR(+IF(S$29=ProposalToGnatt[[#This Row],[Start Date]],Milestone_Marker,IF(AND(S$29>ProposalToGnatt[[#This Row],[Start Date]],S$29<ProposalToGnatt[[#This Row],[Start Date]]+ProposalToGnatt[[#This Row],[Days]]),$G$5,"")),"") | T82: =IFERROR(+IF(T$29=ProposalToGnatt[[#This Row],[Start Date]],Milestone_Marker,IF(AND(T$29>ProposalToGnatt[[#This Row],[Start Date]],T$29<ProposalToGnatt[[#This Row],[Start Date]]+ProposalToGnatt[[#This Row],[Days]]),$G$5,"")),"") | U82: =IFERROR(+IF(U$29=ProposalToGnatt[[#This Row],[Start Date]],Milestone_Marker,IF(AND(U$29>ProposalToGnatt[[#This Row],[Start Date]],U$29<ProposalToGnatt[[#This Row],[Start Date]]+ProposalToGnatt[[#This Row],[Days]]),$G$5,"")),"") | V82: =IFERROR(+IF(V$29=ProposalToGnatt[[#This Row],[Start Date]],Milestone_Marker,IF(AND(V$29>ProposalToGnatt[[#This Row],[Start Date]],V$29<ProposalToGnatt[[#This Row],[Start Date]]+ProposalToGnatt[[#This Row],[Days]]),$G$5,"")),"") | W82: =IFERROR(+IF(W$29=ProposalToGnatt[[#This Row],[Start Date]],Milestone_Marker,IF(AND(W$29>ProposalToGnatt[[#This Row],[Start Date]],W$29<ProposalToGnatt[[#This Row],[Start Date]]+ProposalToGnatt[[#This Row],[Days]]),$G$5,"")),"") | ... CU82: =IFERROR(+IF(CU$29=ProposalToGnatt[[#This Row],[Start Date]],Milestone_Marker,IF(AND(CU$29>ProposalToGnatt[[#This Row],[Start Date]],CU$29<ProposalToGnatt[[#This Row],[Start Date]]+ProposalToGnatt[[#This Row],[Days]]),$G$5,"")),"") | CV82: =IFERROR(+IF(CT$29=#REF!,Milestone_Marker,IF(AND(CT$29>#REF!,CT$29<=#REF!+#REF!),$G$5,"")),"") | CW82: =IFERROR(+IF(CU$29=#REF!,Milestone_Marker,IF(AND(CU$29>#REF!,CU$29<=#REF!+#REF!),$G$5,"")),"")
P83: =IFERROR(+IF(P$29=ProposalToGnatt[[#This Row],[Start Date]],Milestone_Marker,IF(AND(P$29>ProposalToGnatt[[#This Row],[Start Date]],P$29<ProposalToGnatt[[#This Row],[Start Date]]+ProposalToGnatt[[#This Row],[Days]]),$G$5,"")),"") | Q83: =IFERROR(+IF(Q$29=ProposalToGnatt[[#This Row],[Start Date]],Milestone_Marker,IF(AND(Q$29>ProposalToGnatt[[#This Row],[Start Date]],Q$29<ProposalToGnatt[[#This Row],[Start Date]]+ProposalToGnatt[[#This Row],[Days]]),$G$5,"")),"") | R83: =IFERROR(+IF(R$29=ProposalToGnatt[[#This Row],[Start Date]],Milestone_Marker,IF(AND(R$29>ProposalToGnatt[[#This Row],[Start Date]],R$29<ProposalToGnatt[[#This Row],[Start Date]]+ProposalToGnatt[[#This Row],[Days]]),$G$5,"")),"") | S83: =IFERROR(+IF(S$29=ProposalToGnatt[[#This Row],[Start Date]],Milestone_Marker,IF(AND(S$29>ProposalToGnatt[[#This Row],[Start Date]],S$29<ProposalToGnatt[[#This Row],[Start Date]]+ProposalToGnatt[[#This Row],[Days]]),$G$5,"")),"") | T83: =IFERROR(+IF(T$29=ProposalToGnatt[[#This Row],[Start Date]],Milestone_Marker,IF(AND(T$29>ProposalToGnatt[[#This Row],[Start Date]],T$29<ProposalToGnatt[[#This Row],[Start Date]]+ProposalToGnatt[[#This Row],[Days]]),$G$5,"")),"") | U83: =IFERROR(+IF(U$29=ProposalToGnatt[[#This Row],[Start Date]],Milestone_Marker,IF(AND(U$29>ProposalToGnatt[[#This Row],[Start Date]],U$29<ProposalToGnatt[[#This Row],[Start Date]]+ProposalToGnatt[[#This Row],[Days]]),$G$5,"")),"") | V83: =IFERROR(+IF(V$29=ProposalToGnatt[[#This Row],[Start Date]],Milestone_Marker,IF(AND(V$29>ProposalToGnatt[[#This Row],[Start Date]],V$29<ProposalToGnatt[[#This Row],[Start Date]]+ProposalToGnatt[[#This Row],[Days]]),$G$5,"")),"") | W83: =IFERROR(+IF(W$29=ProposalToGnatt[[#This Row],[Start Date]],Milestone_Marker,IF(AND(W$29>ProposalToGnatt[[#This Row],[Start Date]],W$29<ProposalToGnatt[[#This Row],[Start Date]]+ProposalToGnatt[[#This Row],[Days]]),$G$5,"")),"") | ... CU83: =IFERROR(+IF(CU$29=ProposalToGnatt[[#This Row],[Start Date]],Milestone_Marker,IF(AND(CU$29>ProposalToGnatt[[#This Row],[Start Date]],CU$29<ProposalToGnatt[[#This Row],[Start Date]]+ProposalToGnatt[[#This Row],[Days]]),$G$5,"")),"") | CV83: =IFERROR(+IF(CT$29=#REF!,Milestone_Marker,IF(AND(CT$29>#REF!,CT$29<=#REF!+#REF!),$G$5,"")),"") | CW83: =IFERROR(+IF(CU$29=#REF!,Milestone_Marker,IF(AND(CU$29>#REF!,CU$29<=#REF!+#REF!),$G$5,"")),"")
P84: =IFERROR(+IF(P$29=ProposalToGnatt[[#This Row],[Start Date]],Milestone_Marker,IF(AND(P$29>ProposalToGnatt[[#This Row],[Start Date]],P$29<ProposalToGnatt[[#This Row],[Start Date]]+ProposalToGnatt[[#This Row],[Days]]),$G$5,"")),"") | Q84: =IFERROR(+IF(Q$29=ProposalToGnatt[[#This Row],[Start Date]],Milestone_Marker,IF(AND(Q$29>ProposalToGnatt[[#This Row],[Start Date]],Q$29<ProposalToGnatt[[#This Row],[Start Date]]+ProposalToGnatt[[#This Row],[Days]]),$G$5,"")),"") | R84: =IFERROR(+IF(R$29=ProposalToGnatt[[#This Row],[Start Date]],Milestone_Marker,IF(AND(R$29>ProposalToGnatt[[#This Row],[Start Date]],R$29<ProposalToGnatt[[#This Row],[Start Date]]+ProposalToGnatt[[#This Row],[Days]]),$G$5,"")),"") | S84: =IFERROR(+IF(S$29=ProposalToGnatt[[#This Row],[Start Date]],Milestone_Marker,IF(AND(S$29>ProposalToGnatt[[#This Row],[Start Date]],S$29<ProposalToGnatt[[#This Row],[Start Date]]+ProposalToGnatt[[#This Row],[Days]]),$G$5,"")),"") | T84: =IFERROR(+IF(T$29=ProposalToGnatt[[#This Row],[Start Date]],Milestone_Marker,IF(AND(T$29>ProposalToGnatt[[#This Row],[Start Date]],T$29<ProposalToGnatt[[#This Row],[Start Date]]+ProposalToGnatt[[#This Row],[Days]]),$G$5,"")),"") | U84: =IFERROR(+IF(U$29=ProposalToGnatt[[#This Row],[Start Date]],Milestone_Marker,IF(AND(U$29>ProposalToGnatt[[#This Row],[Start Date]],U$29<ProposalToGnatt[[#This Row],[Start Date]]+ProposalToGnatt[[#This Row],[Days]]),$G$5,"")),"") | V84: =IFERROR(+IF(V$29=ProposalToGnatt[[#This Row],[Start Date]],Milestone_Marker,IF(AND(V$29>ProposalToGnatt[[#This Row],[Start Date]],V$29<ProposalToGnatt[[#This Row],[Start Date]]+ProposalToGnatt[[#This Row],[Days]]),$G$5,"")),"") | W84: =IFERROR(+IF(W$29=ProposalToGnatt[[#This Row],[Start Date]],Milestone_Marker,IF(AND(W$29>ProposalToGnatt[[#This Row],[Start Date]],W$29<ProposalToGnatt[[#This Row],[Start Date]]+ProposalToGnatt[[#This Row],[Days]]),$G$5,"")),"") | ... CU84: =IFERROR(+IF(CU$29=ProposalToGnatt[[#This Row],[Start Date]],Milestone_Marker,IF(AND(CU$29>ProposalToGnatt[[#This Row],[Start Date]],CU$29<ProposalToGnatt[[#This Row],[Start Date]]+ProposalToGnatt[[#This Row],[Days]]),$G$5,"")),"") | CV84: =IFERROR(+IF(CT$29=#REF!,Milestone_Marker,IF(AND(CT$29>#REF!,CT$29<=#REF!+#REF!),$G$5,"")),"") | CW84: =IFERROR(+IF(CU$29=#REF!,Milestone_Marker,IF(AND(CU$29>#REF!,CU$29<=#REF!+#REF!),$G$5,"")),"")
P85: =IFERROR(+IF(Q$29=#REF!,Milestone_Marker,IF(AND(Q$29>#REF!,Q$29<=#REF!+#REF!),$G$5,"")),"") | Q85: =IFERROR(+IF(R$29=#REF!,Milestone_Marker,IF(AND(R$29>#REF!,R$29<=#REF!+#REF!),$G$5,"")),"") | R85: =IFERROR(+IF(S$29=#REF!,Milestone_Marker,IF(AND(S$29>#REF!,S$29<=#REF!+#REF!),$G$5,"")),"") | S85: =IFERROR(+IF(T$29=#REF!,Milestone_Marker,IF(AND(T$29>#REF!,T$29<=#REF!+#REF!),$G$5,"")),"") | T85: =IFERROR(+IF(U$29=#REF!,Milestone_Marker,IF(AND(U$29>#REF!,U$29<=#REF!+#REF!),$G$5,"")),"") | U85: =IFERROR(+IF(V$29=#REF!,Milestone_Marker,IF(AND(V$29>#REF!,V$29<=#REF!+#REF!),$G$5,"")),"") | V85: =IFERROR(+IF(W$29=#REF!,Milestone_Marker,IF(AND(W$29>#REF!,W$29<=#REF!+#REF!),$G$5,"")),"") | W85: =IFERROR(+IF(X$29=#REF!,Milestone_Marker,IF(AND(X$29>#REF!,X$29<=#REF!+#REF!),$G$5,"")),"") | ... CT85: =IFERROR(+IF(CU$29=#REF!,Milestone_Marker,IF(AND(CU$29>#REF!,CU$29<=#REF!+#REF!),$G$5,"")),"")
P86: =IFERROR(+IF(Q$29=#REF!,Milestone_Marker,IF(AND(Q$29>#REF!,Q$29<=#REF!+#REF!),$G$5,"")),"") | Q86: =IFERROR(+IF(R$29=#REF!,Milestone_Marker,IF(AND(R$29>#REF!,R$29<=#REF!+#REF!),$G$5,"")),"") | R86: =IFERROR(+IF(S$29=#REF!,Milestone_Marker,IF(AND(S$29>#REF!,S$29<=#REF!+#REF!),$G$5,"")),"") | S86: =IFERROR(+IF(T$29=#REF!,Milestone_Marker,IF(AND(T$29>#REF!,T$29<=#REF!+#REF!),$G$5,"")),"") | T86: =IFERROR(+IF(U$29=#REF!,Milestone_Marker,IF(AND(U$29>#REF!,U$29<=#REF!+#REF!),$G$5,"")),"") | U86: =IFERROR(+IF(V$29=#REF!,Milestone_Marker,IF(AND(V$29>#REF!,V$29<=#REF!+#REF!),$G$5,"")),"") | V86: =IFERROR(+IF(W$29=#REF!,Milestone_Marker,IF(AND(W$29>#REF!,W$29<=#REF!+#REF!),$G$5,"")),"") | W86: =IFERROR(+IF(X$29=#REF!,Milestone_Marker,IF(AND(X$29>#REF!,X$29<=#REF!+#REF!),$G$5,"")),"") | ... CT86: =IFERROR(+IF(CU$29=#REF!,Milestone_Marker,IF(AND(CU$29>#REF!,CU$29<=#REF!+#REF!),$G$5,"")),"")
P87: =IFERROR(+IF(Q$29=#REF!,Milestone_Marker,IF(AND(Q$29>#REF!,Q$29<=#REF!+#REF!),$G$5,"")),"") | Q87: =IFERROR(+IF(R$29=#REF!,Milestone_Marker,IF(AND(R$29>#REF!,R$29<=#REF!+#REF!),$G$5,"")),"") | R87: =IFERROR(+IF(S$29=#REF!,Milestone_Marker,IF(AND(S$29>#REF!,S$29<=#REF!+#REF!),$G$5,"")),"") | S87: =IFERROR(+IF(T$29=#REF!,Milestone_Marker,IF(AND(T$29>#REF!,T$29<=#REF!+#REF!),$G$5,"")),"") | T87: =IFERROR(+IF(U$29=#REF!,Milestone_Marker,IF(AND(U$29>#REF!,U$29<=#REF!+#REF!),$G$5,"")),"") | U87: =IFERROR(+IF(V$29=#REF!,Milestone_Marker,IF(AND(V$29>#REF!,V$29<=#REF!+#REF!),$G$5,"")),"") | V87: =IFERROR(+IF(W$29=#REF!,Milestone_Marker,IF(AND(W$29>#REF!,W$29<=#REF!+#REF!),$G$5,"")),"") | W87: =IFERROR(+IF(X$29=#REF!,Milestone_Marker,IF(AND(X$29>#REF!,X$29<=#REF!+#REF!),$G$5,"")),"") | ... CT87: =IFERROR(+IF(CU$29=#REF!,Milestone_Marker,IF(AND(CU$29>#REF!,CU$29<=#REF!+#REF!),$G$5,"")),"")
P88: =IFERROR(+IF(Q$29=#REF!,Milestone_Marker,IF(AND(Q$29>#REF!,Q$29<=#REF!+#REF!),$G$5,"")),"") | Q88: =IFERROR(+IF(R$29=#REF!,Milestone_Marker,IF(AND(R$29>#REF!,R$29<=#REF!+#REF!),$G$5,"")),"") | R88: =IFERROR(+IF(S$29=#REF!,Milestone_Marker,IF(AND(S$29>#REF!,S$29<=#REF!+#REF!),$G$5,"")),"") | S88: =IFERROR(+IF(T$29=#REF!,Milestone_Marker,IF(AND(T$29>#REF!,T$29<=#REF!+#REF!),$G$5,"")),"") | T88: =IFERROR(+IF(U$29=#REF!,Milestone_Marker,IF(AND(U$29>#REF!,U$29<=#REF!+#REF!),$G$5,"")),"") | U88: =IFERROR(+IF(V$29=#REF!,Milestone_Marker,IF(AND(V$29>#REF!,V$29<=#REF!+#REF!),$G$5,"")),"") | V88: =IFERROR(+IF(W$29=#REF!,Milestone_Marker,IF(AND(W$29>#REF!,W$29<=#REF!+#REF!),$G$5,"")),"") | W88: =IFERROR(+IF(X$29=#REF!,Milestone_Marker,IF(AND(X$29>#REF!,X$29<=#REF!+#REF!),$G$5,"")),"") | ... CT88: =IFERROR(+IF(CU$29=#REF!,Milestone_Marker,IF(AND(CU$29>#REF!,CU$29<=#REF!+#REF!),$G$5,"")),"")
P89: =IFERROR(+IF(Q$29=#REF!,Milestone_Marker,IF(AND(Q$29>#REF!,Q$29<=#REF!+#REF!),$G$5,"")),"") | Q89: =IFERROR(+IF(R$29=#REF!,Milestone_Marker,IF(AND(R$29>#REF!,R$29<=#REF!+#REF!),$G$5,"")),"") | R89: =IFERROR(+IF(S$29=#REF!,Milestone_Marker,IF(AND(S$29>#REF!,S$29<=#REF!+#REF!),$G$5,"")),"") | S89: =IFERROR(+IF(T$29=#REF!,Milestone_Marker,IF(AND(T$29>#REF!,T$29<=#REF!+#REF!),$G$5,"")),"") | T89: =IFERROR(+IF(U$29=#REF!,Milestone_Marker,IF(AND(U$29>#REF!,U$29<=#REF!+#REF!),$G$5,"")),"") | U89: =IFERROR(+IF(V$29=#REF!,Milestone_Marker,IF(AND(V$29>#REF!,V$29<=#REF!+#REF!),$G$5,"")),"") | V89: =IFERROR(+IF(W$29=#REF!,Milestone_Marker,IF(AND(W$29>#REF!,W$29<=#REF!+#REF!),$G$5,"")),"") | W89: =IFERROR(+IF(X$29=#REF!,Milestone_Marker,IF(AND(X$29>#REF!,X$29<=#REF!+#REF!),$G$5,"")),"") | ... CT89: =IFERROR(+IF(CU$29=#REF!,Milestone_Marker,IF(AND(CU$29>#REF!,CU$29<=#REF!+#REF!),$G$5,"")),"")
P90: =IFERROR(+IF(Q$29=#REF!,Milestone_Marker,IF(AND(Q$29>#REF!,Q$29<=#REF!+#REF!),$G$5,"")),"") | Q90: =IFERROR(+IF(R$29=#REF!,Milestone_Marker,IF(AND(R$29>#REF!,R$29<=#REF!+#REF!),$G$5,"")),"") | R90: =IFERROR(+IF(S$29=#REF!,Milestone_Marker,IF(AND(S$29>#REF!,S$29<=#REF!+#REF!),$G$5,"")),"") | S90: =IFERROR(+IF(T$29=#REF!,Milestone_Marker,IF(AND(T$29>#REF!,T$29<=#REF!+#REF!),$G$5,"")),"") | T90: =IFERROR(+IF(U$29=#REF!,Milestone_Marker,IF(AND(U$29>#REF!,U$29<=#REF!+#REF!),$G$5,"")),"") | U90: =IFERROR(+IF(V$29=#REF!,Milestone_Marker,IF(AND(V$29>#REF!,V$29<=#REF!+#REF!),$G$5,"")),"") | V90: =IFERROR(+IF(W$29=#REF!,Milestone_Marker,IF(AND(W$29>#REF!,W$29<=#REF!+#REF!),$G$5,"")),"") | W90: =IFERROR(+IF(X$29=#REF!,Milestone_Marker,IF(AND(X$29>#REF!,X$29<=#REF!+#REF!),$G$5,"")),"") | ... CT90: =IFERROR(+IF(CU$29=#REF!,Milestone_Marker,IF(AND(CU$29>#REF!,CU$29<=#REF!+#REF!),$G$5,"")),"")
P91: =IFERROR(+IF(Q$29=#REF!,Milestone_Marker,IF(AND(Q$29>#REF!,Q$29<=#REF!+#REF!),$G$5,"")),"") | Q91: =IFERROR(+IF(R$29=#REF!,Milestone_Marker,IF(AND(R$29>#REF!,R$29<=#REF!+#REF!),$G$5,"")),"") | R91: =IFERROR(+IF(S$29=#REF!,Milestone_Marker,IF(AND(S$29>#REF!,S$29<=#REF!+#REF!),$G$5,"")),"") | S91: =IFERROR(+IF(T$29=#REF!,Milestone_Marker,IF(AND(T$29>#REF!,T$29<=#REF!+#REF!),$G$5,"")),"") | T91: =IFERROR(+IF(U$29=#REF!,Milestone_Marker,IF(AND(U$29>#REF!,U$29<=#REF!+#REF!),$G$5,"")),"") | U91: =IFERROR(+IF(V$29=#REF!,Milestone_Marker,IF(AND(V$29>#REF!,V$29<=#REF!+#REF!),$G$5,"")),"") | V91: =IFERROR(+IF(W$29=#REF!,Milestone_Marker,IF(AND(W$29>#REF!,W$29<=#REF!+#REF!),$G$5,"")),"") | W91: =IFERROR(+IF(X$29=#REF!,Milestone_Marker,IF(AND(X$29>#REF!,X$29<=#REF!+#REF!),$G$5,"")),"") | ... CT91: =IFERROR(+IF(CU$29=#REF!,Milestone_Marker,IF(AND(CU$29>#REF!,CU$29<=#REF!+#REF!),$G$5,"")),"")
P92: =IFERROR(+IF(Q$29=#REF!,Milestone_Marker,IF(AND(Q$29>#REF!,Q$29<=#REF!+#REF!),$G$5,"")),"") | Q92: =IFERROR(+IF(R$29=#REF!,Milestone_Marker,IF(AND(R$29>#REF!,R$29<=#REF!+#REF!),$G$5,"")),"") | R92: =IFERROR(+IF(S$29=#REF!,Milestone_Marker,IF(AND(S$29>#REF!,S$29<=#REF!+#REF!),$G$5,"")),"") | S92: =IFERROR(+IF(T$29=#REF!,Milestone_Marker,IF(AND(T$29>#REF!,T$29<=#REF!+#REF!),$G$5,"")),"") | T92: =IFERROR(+IF(U$29=#REF!,Milestone_Marker,IF(AND(U$29>#REF!,U$29<=#REF!+#REF!),$G$5,"")),"") | U92: =IFERROR(+IF(V$29=#REF!,Milestone_Marker,IF(AND(V$29>#REF!,V$29<=#REF!+#REF!),$G$5,"")),"") | V92: =IFERROR(+IF(W$29=#REF!,Milestone_Marker,IF(AND(W$29>#REF!,W$29<=#REF!+#REF!),$G$5,"")),"") | W92: =IFERROR(+IF(X$29=#REF!,Milestone_Marker,IF(AND(X$29>#REF!,X$29<=#REF!+#REF!),$G$5,"")),"") | ... CT92: =IFERROR(+IF(CU$29=#REF!,Milestone_Marker,IF(AND(CU$29>#REF!,CU$29<=#REF!+#REF!),$G$5,"")),"")
P93: =IFERROR(+IF(Q$29=#REF!,Milestone_Marker,IF(AND(Q$29>#REF!,Q$29<=#REF!+#REF!),$G$5,"")),"") | Q93: =IFERROR(+IF(R$29=#REF!,Milestone_Marker,IF(AND(R$29>#REF!,R$29<=#REF!+#REF!),$G$5,"")),"") | R93: =IFERROR(+IF(S$29=#REF!,Milestone_Marker,IF(AND(S$29>#REF!,S$29<=#REF!+#REF!),$G$5,"")),"") | S93: =IFERROR(+IF(T$29=#REF!,Milestone_Marker,IF(AND(T$29>#REF!,T$29<=#REF!+#REF!),$G$5,"")),"") | T93: =IFERROR(+IF(U$29=#REF!,Milestone_Marker,IF(AND(U$29>#REF!,U$29<=#REF!+#REF!),$G$5,"")),"") | U93: =IFERROR(+IF(V$29=#REF!,Milestone_Marker,IF(AND(V$29>#REF!,V$29<=#REF!+#REF!),$G$5,"")),"") | V93: =IFERROR(+IF(W$29=#REF!,Milestone_Marker,IF(AND(W$29>#REF!,W$29<=#REF!+#REF!),$G$5,"")),"") | W93: =IFERROR(+IF(X$29=#REF!,Milestone_Marker,IF(AND(X$29>#REF!,X$29<=#REF!+#REF!),$G$5,"")),"") | ... CT93: =IFERROR(+IF(CU$29=#REF!,Milestone_Marker,IF(AND(CU$29>#REF!,CU$29<=#REF!+#REF!),$G$5,"")),"")
P94: =IFERROR(+IF(Q$29=#REF!,Milestone_Marker,IF(AND(Q$29>#REF!,Q$29<=#REF!+#REF!),$G$5,"")),"") | Q94: =IFERROR(+IF(R$29=#REF!,Milestone_Marker,IF(AND(R$29>#REF!,R$29<=#REF!+#REF!),$G$5,"")),"") | R94: =IFERROR(+IF(S$29=#REF!,Milestone_Marker,IF(AND(S$29>#REF!,S$29<=#REF!+#REF!),$G$5,"")),"") | S94: =IFERROR(+IF(T$29=#REF!,Milestone_Marker,IF(AND(T$29>#REF!,T$29<=#REF!+#REF!),$G$5,"")),"") | T94: =IFERROR(+IF(U$29=#REF!,Milestone_Marker,IF(AND(U$29>#REF!,U$29<=#REF!+#REF!),$G$5,"")),"") | U94: =IFERROR(+IF(V$29=#REF!,Milestone_Marker,IF(AND(V$29>#REF!,V$29<=#REF!+#REF!),$G$5,"")),"") | V94: =IFERROR(+IF(W$29=#REF!,Milestone_Marker,IF(AND(W$29>#REF!,W$29<=#REF!+#REF!),$G$5,"")),"") | W94: =IFERROR(+IF(X$29=#REF!,Milestone_Marker,IF(AND(X$29>#REF!,X$29<=#REF!+#REF!),$G$5,"")),"") | ... CT94: =IFERROR(+IF(CU$29=#REF!,Milestone_Marker,IF(AND(CU$29>#REF!,CU$29<=#REF!+#REF!),$G$5,"")),"")
P95: =IFERROR(+IF(Q$29=#REF!,Milestone_Marker,IF(AND(Q$29>#REF!,Q$29<=#REF!+#REF!),$G$5,"")),"") | Q95: =IFERROR(+IF(R$29=#REF!,Milestone_Marker,IF(AND(R$29>#REF!,R$29<=#REF!+#REF!),$G$5,"")),"") | R95: =IFERROR(+IF(S$29=#REF!,Milestone_Marker,IF(AND(S$29>#REF!,S$29<=#REF!+#REF!),$G$5,"")),"") | S95: =IFERROR(+IF(T$29=#REF!,Milestone_Marker,IF(AND(T$29>#REF!,T$29<=#REF!+#REF!),$G$5,"")),"") | T95: =IFERROR(+IF(U$29=#REF!,Milestone_Marker,IF(AND(U$29>#REF!,U$29<=#REF!+#REF!),$G$5,"")),"") | U95: =IFERROR(+IF(V$29=#REF!,Milestone_Marker,IF(AND(V$29>#REF!,V$29<=#REF!+#REF!),$G$5,"")),"") | V95: =IFERROR(+IF(W$29=#REF!,Milestone_Marker,IF(AND(W$29>#REF!,W$29<=#REF!+#REF!),$G$5,"")),"") | W95: =IFERROR(+IF(X$29=#REF!,Milestone_Marker,IF(AND(X$29>#REF!,X$29<=#REF!+#REF!),$G$5,"")),"") | ... CT95: =IFERROR(+IF(CU$29=#REF!,Milestone_Marker,IF(AND(CU$29>#REF!,CU$29<=#REF!+#REF!),$G$5,"")),"")
P96: =IFERROR(+IF(Q$29=#REF!,Milestone_Marker,IF(AND(Q$29>#REF!,Q$29<=#REF!+#REF!),$G$5,"")),"") | Q96: =IFERROR(+IF(R$29=#REF!,Milestone_Marker,IF(AND(R$29>#REF!,R$29<=#REF!+#REF!),$G$5,"")),"") | R96: =IFERROR(+IF(S$29=#REF!,Milestone_Marker,IF(AND(S$29>#REF!,S$29<=#REF!+#REF!),$G$5,"")),"") | S96: =IFERROR(+IF(T$29=#REF!,Milestone_Marker,IF(AND(T$29>#REF!,T$29<=#REF!+#REF!),$G$5,"")),"") | T96: =IFERROR(+IF(U$29=#REF!,Milestone_Marker,IF(AND(U$29>#REF!,U$29<=#REF!+#REF!),$G$5,"")),"") | U96: =IFERROR(+IF(V$29=#REF!,Milestone_Marker,IF(AND(V$29>#REF!,V$29<=#REF!+#REF!),$G$5,"")),"") | V96: =IFERROR(+IF(W$29=#REF!,Milestone_Marker,IF(AND(W$29>#REF!,W$29<=#REF!+#REF!),$G$5,"")),"") | W96: =IFERROR(+IF(X$29=#REF!,Milestone_Marker,IF(AND(X$29>#REF!,X$29<=#REF!+#REF!),$G$5,"")),"") | ... CT96: =IFERROR(+IF(CU$29=#REF!,Milestone_Marker,IF(AND(CU$29>#REF!,CU$29<=#REF!+#REF!),$G$5,"")),"")

Sheet Taxes
A1: This is for taxes paid, outside of closing process
A3: Gov't Entity | B3: Date | C3: Tax Event | D3: Tax
A5: Wake County | B5: 19-22 | C5: Property Transfer Tax | D5: 0
E19: =SUM(D4:D18) -> 0

Sheet Financing
A1: QUANTA FINANCE
A3: CLIENT: | B3: TBD
A4: DATE: | B4: TBD
A5: PROJECT: | B5: TBD
B6: DESCRIPTION OF WORK | D6: REHAB BUDGET | E6: PRE-FUNDING COSTS | F6: SCHEDULED VALUES
A7: 100 | B7: Soft Costs (Plans/Permits/Fees) | D7: 0 | E7: 0 | F7: =SUM(D7-E7) -> 0
A8: 1000 | B8: Demo & Trash Haul | D8: 0 | E8: 0 | F8: =SUM(D8-E8) -> 0
A9: 2000 | B9: Sitework/ Shoring | D9: 0 | E9: 0 | F9: =SUM(D9-E9) -> 0
A10: 3000 | B10: Foundation | D10: 0 | E10: 0 | F10: =SUM(D10-E10) -> 0
A11: 4000 | B11: Framing | D11: 0 | E11: 0 | F11: =SUM(D11-E11) -> 0
A12: 5000 | B12: Plumbing Finish Materials | D12: 0 | E12: 0 | F12: =SUM(D12-E12) -> 0
A13: 6000 | B13: Plumbing install/ Rough | D13: 0 | E13: 0 | F13: =SUM(D13-E13) -> 0
A14: 7000 | B14: Electrical Finish Materials | D14: 0 | E14: 0 | F14: =SUM(D14-E14) -> 0
A15: 8000 | B15: Electrical Install/ rough | D15: 0 | E15: 0 | F15: =SUM(D15-E15) -> 0
A16: 9000 | B16: Metal Works (iron, etc.) | D16: 0 | E16: 0 | F16: =SUM(D16-E16) -> 0
A17: 10000 | B17: HVAC | D17: 0 | E17: 0 | F17: =SUM(D17-E17) -> 0
A18: 11000 | B18: Roof | D18: 0 | E18: 0 | F18: =SUM(D18-E18) -> 0
... A48: 41000 | B48: Owner's Contribution | D48: 0 | E48: 0 | F48: =SUM(D48-E48) -> 0
B50: TOTAL | D50: =SUM(D7:D48) -> 0 | E50: =SUM(E7:E48) -> 0 | F50: =SUM(F7:F48) -> 0

Sheet Seller Advance
A1: Misc Cost | B1: AdvancesReduce Seller Pauout
A2: Sellers Payout
A4: Sellers Payoff | B4: 0 | C4: 0
A5: Seller Incentive/Day: | B5: 33
A6: Seller Vacate Days Early: | B6: 0 | C6: =B5*B6 -> 0
C7: Total Cost | D7: =SUM(C4:C6) -> 0
D11: Total Owed: | E11: =+SUM(C4:C10) -> 0

Sheet MISC 2
A1: Misc
B2: Item Name | C2: Quanity | D2: Cost/Unit | E2: Sub-Total | F2: Total
A3: Living Room Ceiling Fan | C3: 0 | D3: 0 | E3: =+C3*D3 -> 0
A4: Bedroom Ceiling Fan | C4: 0 | D4: 0 | E4: =+C4*D4 -> 0
A5: Ceiling Fan Pole | C5: 0 | D5: 0 | E5: =+C5*D5 -> 0
A6: Kitchen Light Fixture | C6: 0 | D6: 0 | E6: =+C6*D6 -> 0
A7: Dining Room Light Fixture | C7: 0 | D7: 0 | E7: =+C7*D7 -> 0
A8: Over Kitchen Sink Light Fixture | C8: 0 | D8: 0 | E8: =+C8*D8 -> 0
A9: Hall Light Fixture | C9: 0 | D9: 0 | E9: =+C9*D9 -> 0
C10: 0 | D10: 0 | E10: =+C10*D10 -> 0
C11: 0 | D11: 0 | E11: =+C11*D11 -> 0
A12: Hall Bath Light Fixture | C12: 0 | D12: 0 | E12: =+C12*D12 -> 0
A13: Master Bath Light Fixture | C13: 0 | D13: 0 | E13: =+C13*D13 -> 0
A14: 1/2 Bath Light Fixture | C14: 0 | D14: 0 | E14: =+C14*D14 -> 0
A15: Bedroom Light Fixture | C15: 0 | D15: 0 | E15: =+C15*D15 -> 0
C16: 0 | D16: 0 | E16: =+C16*D16 -> 0
A17: Laundry Light Fixture | C17: 0 | D17: 0 | E17: =+C17*D17 -> 0
A18: Closet Light Fixture | C18: 0 | D18: 0 | E18: =+C18*D18 -> 0
C19: 0 | D19: 0 | E19: =+C19*D19 -> 0
A20: Exterior Light Fixture | C20: 0 | D20: 0 | E20: =+C20*D20 -> 0
A21: Exterior Motion Light Fixture | C21: 0 | D21: 0 | E21: =+C21*D21 -> 0
C22: 0 | D22: 0 | E22: =+C22*D22 -> 0
A23: Bulbs | C23: 0 | D23: 0 | E23: =+C23*D23 -> 0
C24: 0 | D24: 0 | E24: =+C24*D24 -> 0
C25: 0 | D25: 0 | E25: =+C25*D25 -> 0
A26: Kitchen Sink Faucet | C26: 0 | D26: 0 | E26: =+C26*D26 -> 0
A27: Bathroom Sink Faucet | C27: 0 | D27: 0 | E27: =+C27*D27 -> 0
A28: Toilet | C28: 0 | D28: 0 | E28: =+C28*D28 -> 0
A29: Shower Head | C29: 0 | D29: 0 | E29: =+C29*D29 -> 0
A30: Shower Handle | C30: 0 | D30: 0 | E30: =+C30*D30 -> 0
A31: Tub Faucet | C31: 0 | D31: 0 | E31: =+C31*D31 -> 0
A32: Shower Kit | C32: 0 | D32: 0 | E32: =+C32*D32 -> 0
A33: Tub | C33: 0 | D33: 0 | E33: =+C33*D33 -> 0
A34: Washing Machine Outlet | C34: 0 | D34: 0 | E34: =+C34*D34 -> 0
A35: Dryer Vent | C35: 0 | D35: 0 | E35: =+C35*D35 -> 0
A36: Kitchen Disposal | C36: 0 | D36: 0 | E36: =+C36*D36 -> 0
C37: 0 | D37: 0 | E37: =+C37*D37 -> 0
A38: Hall Bath Vanity | C38: 0 | D38: 0 | E38: =+C38*D38 -> 0
A39: 1/2 Bath Vanity | C39: 0 | D39: 0 | E39: =+C39*D39 -> 0
A40: Master Bath Vanity | C40: 0 | D40: 0 | E40: =+C40*D40 -> 0
A41: Bath Sink Top | C41: 0 | D41: 0 | E41: =+C41*D41 -> 0
C42: 0 | D42: 0 | E42: =+C42*D42 -> 0
C43: 0 | D43: 0 | E43: =+C43*D43 -> 0
C44: 0 | D44: 0 | E44: =+C44*D44 -> 0
C45: 0 | D45: 0 | E45: =+C45*D45 -> 0
C46: 0 | D46: 0 | E46: =+C46*D46 -> 0
C47: 0 | D47: 0 | E47: =+C47*D47 -> 0
C48: 0 | D48: 0 | E48: =+C48*D48 -> 0
C49: 0 | D49: 0 | E49: =+C49*D49 -> 0
C50: 0 | D50: 0 | E50: =+C50*D50 -> 0
C51: 0 | D51: 0 | E51: =+C51*D51 -> 0
C52: 0 | D52: 0 | E52: =+C52*D52 -> 0
C53: 0 | D53: 0 | E53: =+C53*D53 -> 0
... C58: 0 | D58: 0 | E58: =+C58*D58 -> 0
A59: Hall Bath Mirror | C59: 0 | D59: 0 | E59: =+C59*D59 -> 0
C60: 0 | D60: 0 | E60: =+C60*D60 -> 0
C61: 0 | D61: 0 | E61: =+C61*D61 -> 0
F62: =+SUM(E3:E61) -> 0

Sheet Demo & Trash Haul
A1: Vender | B1: Date | C1: Per Event | D1: Iterations | E1: Carge | F1: Sub Total
F2: 0
A3: Meridian | C3: 15 Yrd Delivery | D3: 0 | E3: 50 | F3: =+D3*E3 -> 0
A4: Meridian | C4: 15 yard Haul swap | D4: 0 | E4: 150 | F4: =+D4*E4 -> 0
A5: Meridian | C5: C&D Disp | D5: 0 | E5: 104 | F5: =+D5*E5 -> 0
A6: Meridian | C6: Fuel Surcharge | D6: 0 | E6: =+(12.13+31.46+41.63)/3 -> 28.406667 | F6: =+D6*E6 -> 0
A7: Meridian | C7: Dest Fee | D7: 0 | E7: 6.35 | F7: =+D7*E7 -> 0
A8: Meridian | C8: Admin Fee | D8: 0 | E8: 2.5 | F8: =+D8*E8 -> 0
A9: Meridian | C9: Environmental Fee | D9: 0 | E9: =(8.5+10+17.34)/3 -> 11.946667 | F9: =+D9*E9 -> 0
A10: Meridian | C10: Inv 1 | D10: 0 | E10: 0 | F10: =+D10*E10 -> 0
A11: Meridian | C11: inv 2 | D11: 0 | E11: 0 | F11: =+D11*E11 -> 0
A12: Meridian | B12: 44666 | D12: 0 | E12: 599.75 | F12: =+D12*E12 -> 0
A13: Meridian | B13: 44638 | D13: 1 | E13: 1311.18 | F13: =+D13*E13 -> 1311.18
A14: Meridian | B14: 44638 | D14: 1 | E14: 661.31 | F14: =+D14*E14 -> 661.31
A15: Glasgow | B15: 44634 | D15: 1 | E15: 2700 | F15: =+D15*E15 -> 2700
A16: Glasgow | D16: 0 | F16: =+D16*E16 -> 0
A17: Glasgow | F17: =+D17*E17 -> 0
A18: Meridian | B18: 45516 | C18: Inv 4816485 | D18: 1 | E18: 650 | F18: =+D18*E18 -> 650
D19: 1 | F19: =+D19*E19 -> 0
G21: =SUM(F2:F20) -> 5322.49

Sheet Appliances
A1: Appliances
A3: Description | B3: ITEM | C3: Quanity | D3: Cost/Unit | E3: Sub-Total | F3: Total
A4: HD Microwave White | B4: 977057 | C4: 0 | D4: 149 | E4: =+C4*D4 -> 0
A5: FB Marketplace Ref | C5: 0 | D5: 400 | E5: =+C5*D5 -> 0
A6: HD Dishwasher | B6: 1002425336 | C6: 0 | D6: 348 | E6: =+C6*D6 -> 0
D8: Sub-total for Lowes | F8: =+SUM(E4:E7) -> 0
A9: Dishwasher Hose | C9: 0 | D9: 31.98 | E9: 0 | F9: 0
A11: Dishwasher Hose | B11: 1630551 | C11: 1 | D11: 32.98 | E11: =+C11*D11 -> 32.98
A12: Lowes Range | B12: 3648606 | C12: 1 | D12: 560.31 | E12: =+C12*D12 -> 560.31
A13: Lowes Dishwasher | B13: 1654366 | C13: 1 | D13: 374.29 | E13: 374.29
A14: Lowes Range cord | B14: 118694 | C14: 1 | D14: 39.28 | E14: 39.28
A15: Kitchen Sink | C15: 0 | D15: 189 | E15: =+C15*D15 -> 0
A17: Kitchen faucet | C17: 0 | D17: 169 | E17: =+C17*D17 -> 0
A18: Lowes Microwave | B18: 1692925 | C18: 1 | D18: 170.39 | E18: =+C18*D18 -> 170.39
A19: Accumulating tax | C19: 1 | D19: 90.91 | E19: 91.91
A20: FB Ref | C20: 0 | D20: 400 | E20: =+C20*D20 -> 0
C21: Total for Appliances: | F21: =SUM(E9:E20) -> 1269.16

Sheet Plumbing Fixtures
A1: Plumbing
A3: Description | B3: ITEM | C3: Quanity | D3: Cost/Unit | E3: Sub-Total | F3: Total
E4: =+C4*D4 -> 0
A5: Lowes Kitchen Faucet | B5: 1255143 | C5: 1 | D5: 107.1 | E5: =+C5*D5 -> 107.1
A6: Lowes Bath Accessory Kit | B6: 2131173 | C6: 2 | D6: 53.98 | E6: =+C6*D6 -> 107.96
A7: Lowes Shower Head | B7: 1227792 | C7: 2 | D7: 15.47 | E7: =+C7*D7 -> 30.94
A8: Lowes Bath Faucets | B8: 1233228 | C8: 2 | D8: 39.98 | E8: =+C8*D8 -> 79.96
C9: 0 | D9: 0 | E9: =+C9*D9 -> 0
C10: 0 | E10: 0
A11: toilets | C11: 0 | D11: 0 | E11: =+C11*D11 -> 0
C12: 0 | D12: 0 | E12: =+C12*D12 -> 0
E13: =+C13*D13 -> 0
A14: Resurface tubs | C14: 0 | E14: =+C14*D14 -> 0
E15: =+C15*D15 -> 0
E16: =+C16*D16 -> 0
E17: =+C17*D17 -> 0
E18: =+C18*D18 -> 0
E19: =+C19*D19 -> 0
E20: =+C20*D20 -> 0
A21: Accumulating tax | E21: 107.5
E22: =+C22*D22 -> 0
F23: =+SUM(E4:E22) -> 433.46

Sheet Windows & Doors
A1: Doors & Windows
A3: Description | B3: ITEM | C3: Quanity | D3: Cost/Unit | E3: Sub-Total | F3: Total
A4: 36" Exterior (R) Out Swing | B4: 935605 | C4: 0 | D4: 209 | E4: =+C4*D4 -> 0
A5: 36" Exterior (L) Out Swing | B5: 935604 | C5: 0 | D5: 209 | E5: =+C5*D5 -> 0
A6: 36" Exterior (L) In Swing | B6: 935599 | C6: 0 | D6: 198.56 | E6: =+C6*D6 -> 0
A7: 32" Exterior (R) Out Swing | B7: 14005 | C7: 0 | D7: 179 | E7: =+C7*D7 -> 0
A8: 32" Exterior (L) Out Swing | B8: 14006 | C8: 0 | D8: 179 | E8: =+C8*D8 -> 0
A9: 32" Exterior (L) In Swing | B9: 935587 | C9: 0 | D9: 198.55 | E9: =+C9*D9 -> 0
A10: 30" Interior (R) | B10: 49504 | C10: 0 | D10: 103 | E10: =+C10*D10 -> 0
A11: 30" Interior (L) | B11: 49706 | C11: 0 | D11: 103 | E11: =+C11*D11 -> 0
A12: 28" Interior (R) | B12: 47025 | C12: 0 | D12: 99 | E12: =+C12*D12 -> 0
A13: 28" Interior (L) | B13: 47422 | C13: 0 | D13: 99 | E13: =+C13*D13 -> 0
A14: 24" Interior (R) | B14: 43359 | C14: 0 | D14: 95 | E14: =+C14*D14 -> 0
A15: 24" Interior (L) | B15: 44035 | C15: 0 | D15: 95 | E15: =+C15*D15 -> 0
... A17: Prehung French 60" | B17: 338797 | C17: 0 | D17: 196 | E17: =+C17*D17 -> 0
A18: Windows 32"x62" Project 640493559 | C18: 0 | D18: 284.56 | E18: =+C18*D18 -> 0
A19: Windows 59"x4446.562" Project | B19: 72904 | C19: 0 | D19: 429.62 | E19: =+C19*D19 -> 0
A20: Int Dummy knobs | B20: HD | C20: 4 | D20: 8.97 | E20: =+C20*D20 -> 35.88
A21: Int Dummy knobs | B21: L399125 | C21: 3 | D21: 9.48 | E21: =+C21*D21 -> 28.44
A22: Int Dummy knobs | B22: L399125 | C22: 1 | D22: 9.48 | E22: =+C22*D22 -> 9.48
A23: Bed/bath knob | B23: HD883624 | C23: 5 | D23: 13.47 | E23: =+C23*D23 -> 67.35
A24: Lowes Front door kw powerbolt | B24: 100619 | C24: 1 | D24: 79.98 | E24: =+C24*D24 -> 79.98
A25: Lowes Front door kw door handle | B25: 287027 | C25: 1 | D25: 50.48 | E25: =+C25*D25 -> 50.48
A26: HD Ext Deadbolt combo | C26: 1 | D26: 69.47 | E26: 69.47
A27: Laundry room Fr Doors | B27: HD154372 | C27: 1 | D27: 289 | E27: =+C27*D27 -> 289
A28: Closet door knob | B28: HD883767 | C28: 4 | D28: 12.97 | E28: =+C28*D28 -> 51.88
A29: Accumulating tax | E29: 67.69
F30: =SUM(E4:E29) -> 749.65
F44: =+SUM(E39:E43) -> 0
G49: =+SUM(F30:F48) -> 749.65

Sheet Cabinets
A1: Cabinets
A3: Description | B3: ITEM | C3: Quanity | D3: Cost/Unit | E3: Sub-Total | F3: Total
B4: B21R | C4: 0 | D4: 154 | E4: =+C4*D4 -> 0
A5: 24" Arcadia Cab Master | B5: 795984 | C5: 0 | D5: 144 | E5: =+C5*D5 -> 0
A6: SCR36 | B6: SCR36 | C6: 0 | D6: 224 | E6: =+C6*D6 -> 0
A7: 36 sink base | B7: B24R | C7: 0 | D7: 152 | E7: =+C7*D7 -> 0
A8: Panel | B8: PePR335 | C8: 0 | D8: 50 | E8: =+C8*D8 -> 0
A9: Sink Base | B9: SB36B | C9: 0 | D9: 166 | E9: =+C9*D9 -> 0
A10: Base Cab | B10: B12R | C10: 0 | D10: 104 | E10: =+C10*D10 -> 0
A11: Wall Cab | B11: W1230R | C11: 0 | D11: 81.98 | E11: =+C11*D11 -> 0
A12: Wall Cab | B12: W2730B | C12: 0 | D12: 143 | E12: =+C12*D12 -> 0
A13: Wall Cab | B13: W2430B | C13: 0 | D13: 98.98 | E13: =+C13*D13 -> 0
A14: Diag Corner | B14: DC2430R | C14: 0 | D14: 165 | E14: =+C14*D14 -> 0
A15: Lowes Vanity Master | B15: 795984 | C15: 0 | D15: 144 | E15: =+C15*D15 -> 0
B16: W2130R | C16: 0 | D16: 107 | E16: =+C16*D16 -> 0
A17: Wall Cab | B17: W3014B | C17: 0 | D17: 112 | E17: =+C17*D17 -> 0
A18: Toe Kicks | B18: Toe Kicks | C18: 0 | D18: 40.96 | E18: =+C18*D18 -> 0
B19: Filler F331 | C19: 0 | D19: 18.28 | E19: =+C19*D19 -> 0
C20: 0 | D20: 0 | E20: =+C20*D20 -> 0
A21: Installation | C21: 0 | D21: 0 | E21: =+C21*D21 -> 0
A22: Buy from Lowes | C22: 1 | D22: 935.09 | E22: =+C22*D22 -> 935.09
F23: =+SUM(E4:E22) -> 935.09
A24: Cabinet Tops
A25: Description | B25: ITEM | C25: Quanity | D25: Cost/Unit | E25: Sub-Total | F25: Total
B26: surface 1 | C26: 0 | D26: 0 | E26: =+C26*D26 -> 0
B27: surface 2 | C27: 0 | D27: 0 | E27: =+C27*D27 -> 0
B28: surface 3 | C28: 0 | D28: 0 | E28: =+C28*D28 -> 0
A29: Estimate for Pilier | C29: 1 | D29: 3142.43 | E29: 3142.43
C30: 0 | D30: 0 | E30: =+C30*D30 -> 0
F32: 3142.43
A34: Cabinet Hardware
A35: Description | B35: ITEM | C35: Quanity | D35: Cost/Unit | E35: Sub-Total | F35: Total
A36: Vanities - Sun HS Warehouse | C36: 0 | D36: 1100 | E36: =+C36*D36 -> 0
A37: Satin Nick cabinet knob | B37: 400390 | C37: 4 | D37: 2.05 | E37: =+C37*D37 -> 8.2
A38: Arched 3" Drawer pull | B38: 376787 | C38: 16 | D38: 4.98 | E38: =+C38*D38 -> 79.68
C39: 0 | D39: 0 | E39: =+C39*D39 -> 0
A40: Lowes 10 pk Matte Black Knob | B40: 2280072 | C40: 0 | D40: 18.97 | E40: =+C40*D40 -> 0
A41: HD Satin Nickel Knobs | B41: 1000707539 | C41: 0 | D41: 1.98 | E41: =+C41*D41 -> 0
F42: =+SUM(E36:E41) -> 87.88
G44: =+SUM(F23:F43) -> 4165.4

Sheet Paint
A1: Paint
A2: Description | B2: Sq Ft | C2: Item # | D2: Qty | E2: Cost/Unit | F2: Sub-Total | G2: Total
A3: Interior Wall Paint | B3: =+Profit!K8 -> 1899
A4: SW | C4: 6509-48698 | D4: 1 | E4: 68.54 | F4: =+D4*E4 -> 68.54 | J4: =SUM(F4:F11)/28 -> 17.547857
A5: SW | C5: 6510-78628 | D5: 1 | E5: 85.89 | F5: =+D5*E5 -> 85.89
A6: 5 gal Lowes Kilz | C6: 185342 | D6: 1 | E6: 147 | F6: =+D6*E6 -> 147
A7: SW | C7: 6508-68102 | D7: 5 | E7: 21.99 | F7: =+D7*E7 -> 109.95
A8: HD Behr Int/ext black paint | C8: 389832 | D8: 1 | E8: 39.98 | F8: =+D8*E8 -> 39.98
A9: HD White Int/ext white paint | C9: 985007 | D9: 1 | E9: 39.98 | F9: =+D9*E9 -> 39.98
A10: HD 5 gal Wh Flat Int ceiling | C10: 814917 | D10: 0 | E10: 60.98 | F10: =+D10*E10 -> 0
A11: Valspar | C11: L1028086 | D11: 0 | E11: 40 | F11: =+D11*E11 -> 0
A12: SW 5galover White | B12: 10 | C12: 6504-06788 | D12: 10 | E12: 50.24 | F12: =+D12*E12 -> 502.4
A13: Kitchen Cabinets | B13: 0
A14: SW 5galover White
A15: Exterior Wall Paint | B15: 0
A16: 5 Gal -Valspar Signature Signature flat | C16: Stone Eagle HGSW1456 | D16: 0 | E16: 93 | F16: =+D16*E16 -> 0
A17: Deck Stain | B17: 500 | F17: =+D17*E17 -> 0
A18: L Valspar Semi trans deck stain | C18: Lowes 1028086 | D18: 2 | E18: 47.98 | F18: =+D18*E18 -> 95.96
A19: L Valspar solid porch stain | C19: Lowes 1028091 | D19: 1 | E19: 48.98 | F19: =+D19*E19 -> 48.98
A20: Ongoing tax | D20: 1 | E20: 97.13 | F20: =+D20*E20 -> 97.13
F21: =+D20*E20 -> 97.13
D23: Lowes Sub Total for Paint | G23: =SUM(F4:F21) -> 1332.94
A24: Painter | F24: 0 | G24: 0
A25: Painter | B25: =+$B$3 -> 1899 | C25: Inside | D25: Yes | E25: 2.04 | F25: 0
A26: Painter | B26: =+$B$3 -> 1899 | C26: Front Porch | D26: No | E26: 1 | F26: =IF(D26="yes",E26*B26,0) -> 0
A27: Painter | B27: =+$B$3 -> 1899 | C27: Back Porch | D27: No | E27: 1 | F27: =IF(D27="yes",E27*B27,0) -> 0
G28: =+SUM(F25:F27)+G23 -> 1332.94

Sheet Flooring
A1: Floor
A2: Description | B2: Sq Ft | C2: Item # | D2: Qty | E2: Cost/Unit | F2: Sub-Total | G2: Total
B3: =+Profit!K8 -> 1899
A4: LVP Floor Installation | B4: =+B3 -> 1899 | C4: Inside | D4: no | E4: 6.5 | F4: =IF(D4="yes",E4*B4,0) -> 0
A5: LVP Floor Repair RediCarpet #2 | B5: =+B3 -> 1899 | D5: No | E5: 1 | F5: 571.8
A6: LVP Floor RediCarpet #1 | B6: =+B3 -> 1899 | D6: No | E6: 1 | F6: 4527 | G6: 3191.7
G7: =SUM(F4:F6) -> 5098.8

Sheet HVAC
A2: HVAC
A3: Description | B3: Item | C3: Quanity | D3: Cost/Unit | E3: Sub Total | F3: Total
A4: New unit | B4: True Service HVAC | C4: 1 | D4: 13062 | E4: =+C4*D4 -> 13062
A5: A/C registers | B5: Lowes 66848 | C5: 0 | D5: 8.98 | E5: =+C5*D5 -> 0
A6: A/C registers | B6: HD 4x10 803492136468 | C6: 0 | D6: 7.98 | E6: =+C6*D6 -> 0
A7: A/C Return Vent | B7: Lowes 20x25 753897 | C7: 0 | D7: 44.93 | E7: =+C7*D7 -> 0
A8: AC Filter | B8: HD 20x25 31949488390 | C8: 0 | D8: 4.47 | E8: =+C8*D8 -> 0
A9: AC Filter | B9: Lowes 20x20 259930 | C9: 0 | D9: 4.97 | E9: =+C9*D9 -> 0
A10: Grill | B10: L65185 | C10: 0 | D10: 23 | E10: =+C10*D10 -> 0
E11: =+C11*D11 -> 0
A12: HVAC Service | C12: 0 | D12: 11504 | E12: =+C12*D12 -> 0
F13: =+SUM(E4:E12) -> 13062

Sheet Electrical Fixtures
A1: Electrical
A3: Description | B3: ITEM | C3: Quanity | D3: Cost/Unit | E3: Sub-Total | F3: Total
E4: =+C4*D4 -> 0
A5: Lowes Bedroom Ceiling Fans | B5: 2599776 | C5: 3 | D5: 124.98 | E5: =+C5*D5 -> 374.94
A6: Lowes Liv Rm Ceiling Fan | B6: 807421 | C6: 1 | D6: 112.48 | E6: =+C6*D6 -> 112.48
A7: Lowes 4light bath vanity | B7: 321702 | C7: 2 | D7: 89.98 | E7: =+C7*D7 -> 179.96
A8: Lowes Flush Kitchen Light | B8: 649829 | C8: 1 | D8: 129.98 | E8: =+C8*D8 -> 129.98
A9: Lowes Pendant Dining Light | B9: 2296055 | C9: 1 | D9: 179.98 | E9: =+C9*D9 -> 179.98
A10: Lowes Ext Motion Lights | B10: 482287 | C10: 2 | D10: 62.98 | E10: =+C10*D10 -> 125.96
A11: Lowes 2' Strip Light Mast Closet | B11: 2535475 | C11: 1 | D11: 24.98 | E11: =+C11*D11 -> 24.98
A12: Floor registers | B12: HD1002265221 | C12: 10 | D12: 10.9 | E12: =+C12*D12 -> 109
A13: LED Bulbs | B13: HD1006211602 | C13: 1 | D13: 14.97 | E13: =+C13*D13 -> 14.97
A14: Outdoor flood light fixture | B14: HD233840 | C14: 2 | D14: 19.97 | E14: =+C14*D14 -> 39.94
A15: Hall Light | B15: HD385544 | C15: 1 | D15: 17.97 | E15: =+C15*D15 -> 17.97
A16: Flood Light Bulbs | B16: HD1006248217 | C16: 2 | D16: 16.98 | E16: =+C16*D16 -> 33.96
A17: Wall protectors | B17: HD316307 | C17: 4 | D17: 3.27 | E17: =+C17*D17 -> 13.08
E18: =+C18*D18 -> 0
E19: =+C19*D19 -> 0
B20: Misc | C20: 0 | D20: 700 | E20: =+C20*D20 -> 0
E21: =+C21*D21 -> 0
E22: =+C22*D22 -> 0
F23: =SUM(E4:E22) -> 1357.2

Sheet Landscape
B1: Landscape
A2: Date | B2: Item | C2: Cost/sf | D2: Square Feet | E2: Quanity | F2: cost/unit | G2: SubTotal | H2: Total
A4: 44355 | B4: Andrew | C4: 0.79 | D4: 500 | E4: 1 | F4: 110 | G4: =+E4*F4 -> 110
A5: 44407 | B5: Andrew | C5: 1 | D5: =24*10 -> 240 | E5: 1 | F5: 890 | G5: =+E5*F5 -> 890
A6: 44435 | B6: Andrew | E6: 1 | F6: 200 | G6: =+E6*F6 -> 200
A7: 44454 | B7: Andrew | E7: 1 | F7: 200 | G7: =+E7*F7 -> 200
A8: 6/23/22-11/15/23 | B8: Grenview Works | E8: 1 | F8: 1485 | G8: =+E8*F8 -> 1485
B9: Mow Grass 8/5/23 | E9: 1 | F9: 140 | G9: =+E9*F9 -> 140
B10: Mow Grass 10/2/23 | E10: 1 | F10: 70 | G10: =+E10*F10 -> 70
B11: Mow Grass 11/2/23 | E11: 1 | F11: 70 | G11: =+E11*F11 -> 70
B12: Mow Grass 4/24/24 | E12: 1 | F12: 70 | G12: =+E12*F12 -> 70
B13: Mow Grass 5/25/24 | E13: 1 | F13: 70 | G13: =+E13*F13 -> 70
E14: 0 | F14: 0 | G14: =+E14*F14 -> 0
E15: 0 | F15: 0 | G15: =+E15*F15 -> 0
D17: =+SUM(D4:D16) -> 740 | G17: Total | H17: =+SUM(G4:G16) -> 3305

Sheet Exterior
A1: Roof
A2: Item | B2: Qty | C2: Cost/item | D2: Total | E2: Hourly Rate: | G2: 20
A4: Termite Treatment | B4: 0 | C4: 800 | D4: =+B4*C4 -> 0
A5: Lowes Mailbox | B5: 0 | C5: 28.46 | D5: =+B5*C5 -> 0
A6: Mailbox post | B6: HD106052 | C6: 1 | D6: 32.98
A7: Crawl Plumbing | D7: =+B7*C7 -> 0
A8: Crawl Plumbing | D8: =+B8*C8 -> 0
A9: Siding Repair | C9: 1000 | D9: =+B9*C9 -> 0
A10: Drainage repair | D10: =+B10*C10 -> 0
A11: Oil Tank remidation | B11: 1 | C11: 19156.97 | D11: =+B11*C11 -> 19156.97
A12: Deck rebuild | B12: 0 | C12: 5500 | D12: =+B12*C12 -> 0
A13: Masking tape | C13: 1604326 | D13: =+B13*C13 -> 0
A14: Drop cloths | C14: 228556 | D14: =+B14*C14 -> 0
A15: Power wash | B15: 0 | C15: 400 | D15: 0
D16: =SUM(D4:D15) -> 19189.95
