Workbook
Name Milestone_Marker: 'Gnatt Chart'!$G$4
Name Project_Start: 'Gnatt Chart'!$F$2
Name Scrolling_Increment: 'Gnatt Chart'!$AB$26
Name Today: TODAY()

Sheet Profit
A1: Flip, Hold or Wholetale: | B1: hold | E1: Buy | F1: Your Home LLC
B2: 3413 Pinetree Ln, Greenville, NC 27858 | H2: Monthly Cash Flow | J2: Hearing Date:
A3: Income | D3: Immediate | F3: Upon Sale
A4: CMA: | B4: 287000 | J4: Finalized: | K4: No
A5: % Above/Below Market Sale: | B5: -0.15 | C5: 0.1 | N5: Zillow | O5: 45161 | P5: 276600
A6: Sale Price: | B6: =+B4 + IF(B1="Hold",B4*C5,0) + IF(B1="wholetale",B4*B5,0) -> 315700 | G6: =IF($B$1="hold",$B$4,$B$6) -> 287000 | J6: Anuual Growth: | K6: 0.1 | O6: 45754 | P6: 303900
A7: NonRefundable Deposit: | D7: =+B7 -> 0 | F7: =-B7 -> 0 | G7: =+IF($B$1="hold",$K$6,0)*$C$35/12*B4 -> 28700 | H7: =+IF($B$1="hold","<-- Apprication -----------","") -> <-- Apprication -----------
A8: Rent: | B8: 890.3 | I8: =IF(B1="Hold",+B8,"") -> 890.3 | J8: Sq Footage | K8: 1899
C9: Net Income: | D9: Net Income: | E9: =SUM(D4:D8) -> 0 | F9: =+SUM(F4:G8) -> 315700 | H9: =SUM(H4:I8) -> 890.3
A11: Expenses
A12: Reinstatment Cost 1st: | B12: =12028-11056+12028 -> 13000 | D12: =-B12 -> -13000 | G12: =IF(K4="Yes",0.3*B12,"") | H12: <-- Approx Pay-Down | J12: If the Subject To Value is finalized, zero-out the Pay-Down savings
A13: Subject To 1st:Truist | B13: 0.03125 | C13: 142424 | F13: =-C13 -> -142424
A14: Reinstatment Cost 2st: | F14: =-+(120-C34)*(C14/120) -> 0 | H14: =-(C14*B14/12) -> 0
A15: Subject To 2st:Notes | B15: 0.1 | F15: =-C15 -> 0 | H15: =-C15/120-(C15*B15/12) -> 0
A16: Liens - IRS & HOA | D16: =-C16 -> 0
A17: Partners Share % | B17: 0
A18: or Seller Payout: | B18: 30000 | D18: =-B18 -> -30000 | J18: Yellow cells can be edited
A19: HOA Fees(Catch Up) | C19: 0 | D19: =-B19 -> 0 | N19: =SUM(B12:C18) -> 185424.13
A20: Months Carried | B20: 6 | J20: Do not edit Green cells. They are highlighted only to show profit
A21: Mortgage Payment: | B21: =262.98+392.24+235.06 -> 890.28 | H21: =IF(B1="Hold",-B21,"") -> -890.28
A22: Mortgage Payment - 2nd: | H22: =IF(B1="Hold",-B22,"") -> 0 | N22: =+N19+B30 -> 191100.4
A23: Property Insurance | B23: 0 | H23: =IF(B1="Hold",-B23,"") -> 0
A24: HOA Fees (monthly) | B24: 0 | H24: =IF(B1="Hold",-B24,"") -> 0
A25: Electric | B25: 0
A26: water | B26: 0
A27: Carrying Cost | B27: =+B20*SUM(B21:B26) -> 5341.68 | D27: =-B27 -> -5341.68 | J27: Purchase Cost | K27: =+SUM(B12:C16)+B18 -> 185424.13
A28: Private Lender Rate: | B28: 0.1 | C28: no
A29: 75%ARV-Debt: | B29: =IF(C28="NO",0,+(B6*0.75)-(C13+C14+C15)) -> 0 | E29: =IF(B29<0,0,B29) -> 0 | F29: =IF(C28="No","",-E29-(B20*E29*B28/12)) | H29: =-IF($B$1="Hold",E29*B28/12,0) -> 0 | J29: Out of Pocket | K29: =+B12+C14+C16+B18+B30 -> 48676.264
A30: Rehab: | B30: =-D51 -> 5676.264 | D30: =-B30 -> -5676.264
A31: Marketing: | B31: 600 | D31: =-B31 -> -600 | J31: PL Balance +Interest
A32: Seller Realtor's Flat Fee | B32: 1 | C32: =+B32*399 -> 399 | F32: =-C32 -> -399
A33: Seller Realtor's Fee Percent: | B33: 0 | C33: 0.026 | F33: =-B33*C33*$F$9 -> 0
A34: Buyers Realtors Fee Percent: | B34: 1 | C34: 0.024 | F34: =-B34*C34*$F$9 -> -7576.8
A35: Number of Rent Payments : | C35: 12
A36: Buyer Assistance | F36: =-C36 -> 0
A37: Buying Closing Cost: | B37: =+D71 -> 5998 | D37: =-B37 -> -5998
A38: Selling Closing Cost: | B38: =+D82 -> 290 | F38: =-B38 -> -290
C39: Net Expenses: | E39: =+SUM(D12:D38) -> -60615.944 | F39: =+SUM(F12:F38) -> -150689.8 | H39: =+SUM(H9:I38) -> 0.02
B40: Immediate Profit: | E40: =+SUM(E9:E39) -> -60615.944 | F40: =+SUM(F9:G38) -> 165010.2
E41: Long Term Profit: | G41: =+E40+F40 -> 104394.26 | J41: Partners Profit Share | K41: Our Profit Share
E42: Cash Flow Profit for Months: | H42: =IF(B1="Hold",C35,0) -> 12 | I42: =+H42*H39 -> 0.24
F43: Gross Profit: | I43: =+I42+G41 -> 104394.5 | J43: =$B$17*$I$43 -> 0 | K43: =+$I$43-J43 -> 104394.5
A44: Capital Gains Tax | B44: 0 | H44: Capital Gains | J44: =IF(B44="",0,-$B$44*J43) -> 0 | K44: =IF(B44="",0,-$B$44*K43) -> 0
A45: Chartiable Contribution: | B45: 0.1 | C45: 0.15 | D45: =+K45*B45 -> 10439.45 | H45: Gross Profit: | J45: =+J43+J44 -> 0 | K45: =+K43+K44 -> 104394.5
A47: Rehab Cost Detail
A48: Gnatt Chart | B48: =+'Gnatt Chart'!J5 -> 5160.24 | D48: =-B48 -> -5160.24
A49: Murphy %: | B49: 0.1 | G49: Murphy will be Zeroed-Out whe project is finalized
A50: Murphy's Cut: | B50: =IF(K4<>"Yes",+B49*SUM(B48:C48),0) -> 516.024 | D50: =-B50 -> -516.024
A51: Rehab Summary: | D51: =+SUM(D48:E50) -> -5676.264 | G51: This value is carried up to cell C29, Labeled Rehab
A52: Buying Closing Cost
A53: Settlement Fee to Attorney: | B53: 650
A54: Probate Attorney | B54: 5000
A55: Seller Doc Prep | B55: 250
A56: Seller Doc Prep
A57: Wire Fee
A58: Wire Fee
A59: Deed Package:
A60: Indemnety:
A61: Ttitle Search:
A62: Cancelation Fee:
A63: Overnight Express Fees:
A64: Title Insurance: | B64: 66
A65: Affadavits:
A66: Notice to Creditors Ad
A67: Recording Fee Deed: | B67: 26
A68: Transfer Taxes - Wake County | B68: 6
A69: Revenue Stamps
A70: LLC Manager Fee
D71: =+SUM(B53:C70) -> 5998 | G71: This value is carried up to cell C36, Labeled Buying Closing Cost
A73: Selling Closing Cost
A74: Settlement Fee to Attorney:
A75: Seller Doc Prep | B75: 250
A76: Seller concesson: | B76: 0
A77: Home Warrenty:
A78: Recording Fee Deed:
A79: Transfer Taxes - Wake County | B79: 40
A80: Revenue Stamps
A81: LLC Manager Fee
D82: =+SUM(B74:C81) -> 290 | G82: This value is carried up to cell C37, Labeled Selling Closing Cost

Sheet MOG
C1: Multiple Offer Generator | I1: ="Hi "&B3 & IF(B4 ="",""," and ") &B4&", Thank you for the opportunity to make an offer on your property at "&Profit!B2&". I have several options I would like for you to consider. I also want to give you several very good reasons for you to work with us here at Buy Your Home LLC. "&REPT(" ",6)&"1. If you sell your home to us, you will incur no expense from the transaction. We will pay all: "&REPT(" ",20)&"Closing Cost "&REPT(" ",20)&"Attorney's Fees "&REPT(" ",20)&"Realtor Commissions "&REPT(" ",6) &" 2. We can close fast. It will be a matter of days, probably less than two weeks, when we can "&REPT(" ",11) &"close at our attorney's office and get you your cash. "&REPT(" ",6) &"3. We cover the cost, time, and effort of paying any money due to any lender or HOA "&REPT(" ",11) &"involved." -> Hi Nikki, Thank you for the opportunity to make an offer on your property at 3413 Pinetree Ln, Greenville, NC 27858. I have several options I would like for you to consider. I also want to give you several very good reasons for you to work with us here at Buy Your Home LLC. 1. If you sell your home to us, you will incur no expense from the transaction. We will pay all: Closing Cost Attorney's Fees Realtor Commissions 2. We can close fast. It will be a matter of days, probably less than two weeks, when we can close at our attorney's office and get you your cash. 3. We cover the cost, time, and effort of paying any money due to any lender or HOA involved. | J1: Buyers Copy | K1: =+I1&IF(N14="X",O14,"")&" "& IF(H15="X",I15,"") &" "& IF(H16="X",I16,"") &" "& IF(H20="X",I20,"") &" "& IF(H26="X",I26,"") &" "& IF(H33="X",I33,"") & " "& IF(H42="X",I42,"") & " "& IF(H52="X",I52,"") & " "& IF(H61="X",I61,"") & " "& IF(H74="X",I74,"") & " "& IF(H81="X",I81,"") & " "& IF(H82="X",I82,"") & " "& "" -> Hi Nikki, Thank you for the opportunity to make an offer on your property at 3413 Pinetree Ln, Greenville, NC 27858. I have several options I would like for you to consider. I also want to give you several very good reasons for you to work with us here at Buy Your Home LLC. 1. If you sell your home to us, you will incur no expense from the transaction. We will pay all: Closing Cost Attorney's Fees Realtor Commissions 2. We can close fast. It will be a matter of days, probably less than two weeks, when we can close at our attorney's office and get you your cash. 3. We cover the cost, time, and effort of paying any money due to any lender or HOA involved. Here are some purchase options for your consideration. They are presented in summary form and I am sure you will have some questions that I will be happy to take time needed to answer. Each option below will have more value than the one above it. Option 1: Cash plus Assumption of Mortgage This is a cash payment, at closing. We will take responsibility for the existing mortgage, HOA fees, and any liens that may be discovered until we are able to resell the property. This offer is: Cash: $30,000.00 Total Value: $30,000.00 Option 2: Cash plus Promissory Note The explanation for the cash component is the same as for option 1. However, 20.% of the value of the offer will be cash and 80.% will be in the form of a promissory note, complete with a Deed of Trust. The note will have a 24-month term that will pay simple interest at the rate of 4% per year. Cash: $6,000.00 12 Month Note: $44,000.00 Interest Earned: $3,520.00 $146.67 per month Total Value: $53,520.00 Option 3: Cash plus Beneficial Interest in Trust The explanation for the cash component is the same as for option 2. Instead of a note as in Option 2, you will share in the profit earned when the property is resold. The property will be placed into a trust that you will share a beneficial interest in. The advantage here is you will benefit from the appreciated value of the property, over time. You will receive quarterly reports on the financial status of the property. Cash: $10,000.00 Interest in Trust: 70.% Expected Sellers Profit: $107,166.15 * Expected 10% appreciation per year Expected Value: $117,166.15 ** After 24 months. Nikki, this offer is contingent upon a normal due diligence period. The values of each option are predicated on some assumptions that may need to be altered upon further discovery. The more we can learn from you, in advance, the more reliable these options may be considered. When you decide which offer you prefer, I will email you a contract along with an earnest money payment. We are ready to be of service in any way we can. This offer is based on Zillow's Zestimate of $287,000.00. We will clean and prepare the property for a quick resale. There is also an assumption that the property will need no rehab. If that turns out to not be true, an allowance will need to be made. In any case, that will be decided in the due diligence period of the contract. Sincerely, Wes Browning (919) 899-2104
A3: Seller 1: | B3: Nikki | C3: Kulas | J3: no
A4: Seller 2:
A5: email:
A6: Phone #:
A9: Offer 1 | B9: Traditional, All Cash
B10: This is an all cash payment, at closing with no other allowances considered. Seller pays all Mortgages, liens, HOA expenses out of closings proceedings.
F12: Seller's Equity
B13: Sales Price | C13: ARV | D13: Debt | G13: BYH's Profit
B14: =+D14+F14 -> 182424.13 | C14: =+Profit!B4 -> 287000 | D14: =+Profit!K27-Profit!B18 -> 155424.13 | F14: =+B24-(B24*F16) -> 27000 | G14: =+C14-D14-F14+Profit!E39+Profit!B18 -> 73959.925
D15: BYH Out of Pocket: | E15: =+Profit!$K$29 -> 48676.264
D16: BYH Profit/Out of Pocket: | E16: =+G14/E15 -> 1.5194248 | F16: 0.1 | H16: X | I16: ="Here are some purchase options for your consideration. They are presented in summary form and I am sure you will have some questions that I will be happy to take time needed to answer. Each option below will have more value than the one above it." -> Here are some purchase options for your consideration. They are presented in summary form and I am sure you will have some questions that I will be happy to take time needed to answer. Each option below will have more value than the one above it.
D17: Buy Your Home's % of Profit: | E17: =+G14/(F14+G14) -> 0.73256715 | F17: less than Opt 2
A19: Offer 2 | B19: Cash plus Assumption of Mortgage | D19: *This is the default values from the Profit Sheet. | H19: =IF(H20="X",1,0) -> 0
B20: Cash payment in conjunction with taking the existing mortgage subject to: | I20: ="Option "&H19&": "&""&B9&" "&REPT(" ",6)&"This is a, traditional, all cash purchase, at closing with no other allowances considered. Seller "&REPT(" ",6)&"pays all mortgages, liens, HOA expenses, etc., out of closings disbursements. This option has " & REPT(" ",6) & "the smallest value for the seller. Our cash offer is: "&REPT(" ",43) &"Cash:"&REPT(" ",21)&+TEXT(B14,"$#,##0.00") & IF(J3="yes",REPT(" ",10) & "Profit = "& TEXT(G14,"$#,##0.00"),"" )& " "&REPT(" ",32) & "Total Value:"&REPT(" ",21)&TEXT(F14,"$#,##0.00") -> Option 0: Traditional, All Cash This is a, traditional, all cash purchase, at closing with no other allowances considered. Seller pays all mortgages, liens, HOA expenses, etc., out of closings disbursements. This option has the smallest value for the seller. Our cash offer is: Cash: $182,424.13 Total Value: $27,000.00
B21: After reinstating existing loans and HOA fees
F22: Seller's Total Value
B23: Cash | G23: BYH's Profit
B24: =+Profit!B18 -> 30000 | C24: <- The default value form profit sheet | F24: =+B24 -> 30000 | G24: =+Profit!K45+Profit!B18-B24 -> 104394.5
D25: BYH Out of Pocket: | E25: =+Profit!$K$29 -> 48676.264 | H25: =IF(H26="X",1+H19,H19) -> 1
D26: BYH Profit/Out of Pocket: | E26: =+G24/E25 -> 2.1446694 | H26: x | I26: ="Option " & H25 & ": "&""&B19&" "&REPT(" ",6) & "This is a cash payment, at closing. We will take responsibility for the existing mortgage, HOA "&REPT(" ",6) & "fees, and any liens that may be discovered until we are able to resell the property. This offer is: "&REPT(" ",43)&"Cash:"&REPT(" ",22) & TEXT(F24,"$#,##0.00") & IF(J3="yes",REPT(" ",10) & "Profit = "& TEXT(G24,"$#,##0.00"),"" ) & " "&REPT(" ",32)&"Total Value:"&REPT(" ",22) & TEXT(F24,"$#,##0.00") -> Option 1: Cash plus Assumption of Mortgage This is a cash payment, at closing. We will take responsibility for the existing mortgage, HOA fees, and any liens that may be discovered until we are able to resell the property. This offer is: Cash: $30,000.00 Total Value: $30,000.00
D27: Buy Your Home's % of Profit: | E27: =+G24/(F24+G24) -> 0.77677657
A30: Offer 3 | B30: Cash plus Promissory Note | D30: - this is the one to stear seller to:
B31: Cash payment in conjunction with taking the existing mortgage subject to: | I31: ="This is a cash payment, at closing, in conjunction with reinstating the existing mortgage taking responsibility for those payments, HOA fees and other liens that may be discovered. Our cash offer is:" -> This is a cash payment, at closing, in conjunction with reinstating the existing mortgage taking responsibility for those payments, HOA fees and other liens that may be discovered. Our cash offer is:
B32: After reinstating existing loans and HOA fees | H32: =IF(H33="X",H25+1,H25) -> 2
H33: x | I33: ="Option " & H32 & ": " &""&B30&" "&REPT(" ",6)&"The explanation for the cash component is the same as for option "& H25 & ". However, "&TEXT(B38,"##.#%") &" of the " & REPT(" ",6) & "value of the offer will be cash and "& TEXT(C38,"##.#%") &" will be in the form of a promissory note, complete " & REPT(" ",6) & "with a Deed of Trust. The note will have a " & D35 & "-month term that will pay simple interest at " & REPT(" ",6) & "the rate of "&E37*100&"% per year. "& REPT(" ",43) & "Cash:" & REPT(" ",23) & TEXT(B37,"$#,##0.00") & IF(J3="yes",REPT(" ",10) & "Profit = "& TEXT(G37,"$#,##0.00"),"" ) &" "& REPT(" ",24) & "12 Month Note:" & REPT(" ",24) & TEXT(C37,"$#,##0.00")&" "& REPT(" ",25) & "Interest Earned:" & REPT(" ",25) & TEXT(D37,"$#,##0.00") &REPT(" ",12)&+TEXT(D37/D35,"$#,##0.00") & " per month" & " "& REPT(" ",32) & "Total Value:" & REPT(" ",20) & TEXT(F37,"$#,##0.00") -> Option 2: Cash plus Promissory Note The explanation for the cash component is the same as for option 1. However, 20.% of the value of the offer will be cash and 80.% will be in the form of a promissory note, complete with a Deed of Trust. The note will have a 24-month term that will pay simple interest at the rate of 4% per year. Cash: $6,000.00 12 Month Note: $44,000.00 Interest Earned: $3,520.00 $146.67 per month Total Value: $53,520.00
C34: Note is a simple interest note for: | D34: Months | F34: (Based on Current Valuation)
B35: Value added to Note: | C35: 20000 | D35: 24 | F35: Seller's Total Value
B36: Cash | C36: Note | D36: Interest Earned | E36: Interest Rate | G36: BYH's Profit
B37: =+(Profit!$B$18)*B38 -> 6000 | C37: =+(Profit!$B$18)-B37+C35 -> 44000 | D37: =+C37*D35/12*E37 -> 3520 | E37: 0.04 | F37: =+SUM(B37:D37) -> 53520 | G37: =+Profit!$K$45-D37-C35 -> 80874.496
B38: 0.2 | C38: =1-B38 -> 0.8
D39: BYH Out of Pocket: | E39: =+Profit!$K$29-C37+C35 -> 24676.264
D40: BYH Profit/Out of Pocket: | E40: =+G37/E39 -> 3.2774206
D41: Buy Your Home's % of Profit: | E41: =+G37/(F37+G37) -> 0.60176941 | H41: =IF(H42="X",H32+1,H32) -> 3
A42: Offer 4 | B42: Cash plus Beneficial Interest in Trust | H42: x | I42: ="Option " & H41 & ": " & B42&" "&REPT(" ",6)&"The explanation for the cash component is the same as for option "& H32 & ". Instead of a note as in " & REPT(" ",6) & "Option "& H32 & ", you will share in the profit earned when the property is resold." &" The property will " & REPT(" ",6) & "be placed into a trust that you will share a beneficial interest in. The advantage here is you will " & REPT(" ",6) & "benefit from the appreciated value of the property, over time." &" You will receive quarterly " & REPT(" ",6) & "reports on the financial status of the property. "& REPT(" ",43) & "Cash:" & REPT(" ",23) & TEXT(B50,"$#,##0.00") & IF(J3="yes",REPT(" ",10) & "Profit = "& TEXT(G50,"$#,##0.00"),"" ) &" "& REPT(" ",24) & "Interest in Trust:" & REPT(" ",33) & TEXT(D50,"#.#%")&" "& REPT(" ",13) & "Expected Sellers Profit:" & REPT(" ",23) & TEXT(E50,"$#,##0.00") &" * Expected "&Profit!$K$6*100&"% appreciation per year" & " "& REPT(" ",26) & "Expected Value:" & REPT(" ",20) & TEXT(F50,"$#,##0.00") & " ** After " & D35 &" months." -> Option 3: Cash plus Beneficial Interest in Trust The explanation for the cash component is the same as for option 2. Instead of a note as in Option 2, you will share in the profit earned when the property is resold. The property will be placed into a trust that you will share a beneficial interest in. The advantage here is you will benefit from the appreciated value of the property, over time. You will receive quarterly reports on the financial status of the property. Cash: $10,000.00 Interest in Trust: 70.% Expected Sellers Profit: $107,166.15 * Expected 10% appreciation per year Expected Value: $117,166.15 ** After 24 months.
B43: Cash payment in conjunction with taking the existing mortgage subject to:
B44: After reinstating existing loans and HOA fees
B45: Profit split is a split of the profits upon the eventual sale of the pproperty.
B46: Profits will be calculated after deducting all expenses incurred from the sales price
F47: (Based on Future Valuation)
C48: Trust Future Profit | D48: Seller's Profit Sharing Percent | E48: Seller's Profit Share | F48: Seller's Total Value
B49: Cash | C49: Trust Future Profit | D49: Seller's Profit Sharing Percent | E49: Sellers Share Profit | G49: BYH's Profit
B50: 10000 | C50: =+Profit!$K$45+Profit!B18-B50+(Profit!K6*Profit!C35/12*Profit!B4) -> 153094.5 | D50: 0.7 | E50: =+D50*C50 -> 107166.15 | F50: =+B50+E50 -> 117166.15 | G50: =(1-D50)*C50 -> 45928.349
D51: *This precentage is not set in Profit sheet. It is for proposal only.
D52: BYH Out of Pocket: | E52: =+Profit!$K$29-B24+B50 -> 28676.264 | H52: X | I52: =B3 & ", this offer is contingent upon a normal due diligence period. The values of each option are predicated on some assumptions that may need to be altered upon further discovery. " & "The more we can learn from you, in advance, the more reliable these options may be considered. When you decide which offer you prefer, I will email you a contract along with an earnest money payment. We are ready to be of service in any way we can." -> Nikki, this offer is contingent upon a normal due diligence period. The values of each option are predicated on some assumptions that may need to be altered upon further discovery. The more we can learn from you, in advance, the more reliable these options may be considered. When you decide which offer you prefer, I will email you a contract along with an earnest money payment. We are ready to be of service in any way we can.
D53: BYH Profit/Out of Pocket: | E53: =+G50/E52 -> 1.6016155
D54: Buy Your Home's % of Profit: | E54: =+G50/(F50+G50) -> 0.28160576
B56: Personalize Note | D56: {alt}{enter] = carrage return
A57: ="This offer is based on Zillow's Zestimate of " & TEXT(Profit!B4,"$#,##0.00") & ". " & "We will clean and prepare the property for a quick resale. There is also an assumption that the property will need no rehab." & " If that turns out to not be true, an allowance will need to be made. In any case, that will be decided in the due diligence period of the contract. " & "" -> This offer is based on Zillow's Zestimate of $287,000.00. We will clean and prepare the property for a quick resale. There is also an assumption that the property will need no rehab. If that turns out to not be true, an allowance will need to be made. In any case, that will be decided in the due diligence period of the contract.
H61: X | I61: =A57 -> This offer is based on Zillow's Zestimate of $287,000.00. We will clean and prepare the property for a quick resale. There is also an assumption that the property will need no rehab. If that turns out to not be true, an allowance will need to be made. In any case, that will be decided in the due diligence period of the contract.
H74: X | I74: ="Sincerely, Wes Browning" -> Sincerely, Wes Browning
G81: Foreclosure Leads | I81: (919) 899-4954
G82: Liberty Leads | H82: X | I82: (919) 899-2104

Sheet Todo
B1: =+Profit!B2 -> 3413 Pinetree Ln, Greenville, NC 27858 | D1: Notes | F1: 3021 Pearces Rd | G1: 6004 Sandy Run | H1: Larchmont | I1: 3325 Banks | J1: 2608 Alton | K1: 202 Avery | L1: 1900 Red Quartz | M1: 120 Keith | N1: 3007 Eric | O1: 2153 Haig Point | P1: 178 Patricia | Q1: 1201 Hazelnut | R1: 1223 Roffler | S1: 2025 Metacomet | T1: 5619 Marthonna
A2: New Seller
B3: Purchase & Sale Agreement | C3: Yes | F3: 0 | H3: Yes | I3: =+[1]Todo!$C3 -> Yes
B4: Letter of Authorization | C4: Yes | F4: 0 | H4: Yes (2) | I4: =+[1]Todo!$C4 -> Yes
B5: Reinstatement Quote | C5: Yes | F5: 0 | H5: Yes (2) | I5: =+[1]Todo!$C5 -> Yes
B6: Bank Acknowledgement | C6: Yes | F6: 0 | H6: yes | I6: =+[1]Todo!$C6 -> Yes
B7: On-Line Bank Access | C7: yes | F7: 0 | H7: yes | I7: =+[1]Todo!$C7 -> yes
B8: Change Mail | C8: yes | F8: 0 | H8: yes | I8: =+[1]Todo!$C8 -> yes
B9: Bank Attorney letter of dismisal | C9: na | F9: 0 | H9: yes | I9: =+[1]Todo!$C9 -> na
B10: Get (orignal) Property Authorization | C10: na | F10: 0 | H10: yes | I10: =+[1]Todo!$C10 -> na
F11: 0 | H11: 0 | I11: =+[1]Todo!$C11 -> 0
A12: After Purchase | F12: After Purchase | H12: 0 | I12: =+[1]Todo!$C12 -> 0
B13: Insurance Claim for Roof | F13: 0 | H13: yes | I13: =+[1]Todo!$C13 -> na
B14: Locks Changed | D14: na till vacant | F14: 0 | H14: yes | I14: =+[1]Todo!$C14 -> na
B15: Gas Service | D15: na till vacant | F15: 0 | H15: yes | I15: =+[1]Todo!$C15 -> na
B16: Electrical & Water Service | D16: na till vacant | F16: 0 | H16: yes | I16: =+[1]Todo!$C16 -> yes
B17: Rehab bids | D17: na till vacant | F17: 0 | H17: yes | I17: =+[1]Todo!$C17 -> 0
B18: Order Dumpster | D18: na till vacant | F18: 0 | H18: n/a | I18: =+[1]Todo!$C18 -> yes
B19: A/C service | D19: na till vacant | F19: 0 | H19: yes | I19: =+[1]Todo!$C19 -> na
B20: Establish Mortgage payment | C20: yes | F20: 0 | H20: yes | I20: =+[1]Todo!$C20 -> yes
B21: Remove PMI | F21: 0 | H21: yes | I21: =+[1]Todo!$C21 -> na
B22: Claim Property on Zillow | F22: 0 | H22: yes | I22: =+[1]Todo!$C22 -> yes
B23: Add property to Our Website | F23: 0 | H23: yes | I23: =+[1]Todo!$C23 -> yes
B24: Make sure deed and agreement are done | C24: yes | D24: waiting on recorded deed | F24: 0 | H24: yes | I24: =+[1]Todo!$C24 -> yes
B25: Change Insurance | F25: 0 | H25: yes | I25: =+[1]Todo!$C25 -> yes
B26: Get Insurance payments installed | F26: 0 | H26: yes | I26: =+[1]Todo!$C26 -> na
B27: Add Private Lender to Insurance | F27: 0 | H27: yes | I27: =+[1]Todo!$C27 -> 0
B28: Probate letters - Notice to Creditors | C28: na | F28: 0 | H28: yes | I28: =+[1]Todo!$C28 -> na
F29: 0 | H29: 0 | I29: =+[1]Todo!$C29 -> 0
A30: Upon Sales Contract | B30: Send list realtor contract | F30: Upon Sales Contract | H30: 0 | I30: =+[1]Todo!$C30 -> 0
B31: Get Payoff Letter from Mortgage | F31: 0 | H31: 0 | I31: =+[1]Todo!$C31 -> 0
B32: Respond to Closing Attorney | F32: 0 | H32: 0 | I32: =+[1]Todo!$C32 -> 0
B33: Turn off utilities | F33: 0 | H33: 0 | I33: =+[1]Todo!$C33 -> 0
B34: Alert Private Lenders | F34: 0 | H34: 0 | I34: =+[1]Todo!$C34 -> 0
F35: 0 | H35: 0
F36: 0 | H36: 0
F37: 0 | H37: 0
A38: Upon Closing | B38: Documents to send to list realtor | F38: Upon Closing | H38: 0 | I38: =+[1]Todo!$C38 -> 0
B39: Alert Private Lenders | F39: 0 | H39: 0 | I39: =+[1]Todo!$C39 -> 0
B40: Send list realtor CD/Alta signed by all | F40: 0 | H40: 0 | I40: =+[1]Todo!$C40 -> 0
B41: Drop Insurance | F41: 0 | H41: 0 | I41: =+[1]Todo!$C41 -> 0
C43: Totals Across Projects | E43: =+B1 -> 3413 Pinetree Ln, Greenville, NC 27858 | G43: 6004 Sandy Run | H43: Larchmont | I43: =+I1 -> 3325 Banks | J43: 2608 Alton | K43: 202 Avery | L43: 1900 Red Quartz | M43: 120 Keith | N43: 3007 Eric | O43: 2153 Haig Point | P43: 178 Patricia | Q43: 1201 Hazelnut | R43: 1223 Roffler | S43: 2025 Metacomet | T43: 5619 Marthonna
B44: Total CMA: | C44: =+SUM(E44:U44) -> 4690329 | E44: =+Profit!$B$4 -> 287000 | F44: 50000 | G44: 285000 | H44: 700000 | I44: =+[1]Todo!$E44 -> 439000 | J44: 315000 | K44: 210000 | L44: 423529 | M44: 330000 | N44: 299000 | O44: 363900 | P44: 210000 | Q44: 237900 | R44: 150000 | S44: 195000 | T44: 195000
B45: Total Purchase Cost: | C45: =+SUM(E45:$U$45) -> 1791714.8 | E45: =+Profit!K27 -> 185424.13 | F45: 10000.139 | G45: 79099.139 | H45: 0 | I45: =+[1]Todo!$E45 -> 147682.86 | J45: 102500 | K45: 127000 | L45: 174585.47 | M45: 85975.79 | N45: 167033.66 | O45: 220000 | P45: 107061.9 | Q45: 74709 | R45: 71644.86 | S45: 110309.86 | T45: 128687.99
B46: Total Rehab Expense: | C46: =+SUM(E46:U46) -> 634691.06 | E46: =+Profit!B30 -> 5676.264 | F46: 0 | G46: 94360 | H46: 39067.44 | I46: =+[1]Todo!$E46 -> 31424.184 | J46: 119124.29 | K46: 15000 | L46: 12223 | M46: 82805.727 | N46: 38679.38 | O46: 27507.698 | P46: 47760.57 | Q46: 71081.807 | R46: 6302.96 | S46: 20425.14 | T46: 23252.602
B47: Total Debt | C47: =+SUM(E47:U47) -> 342461.73 | E47: =SUM(Profit!C13:C19)+Profit!B39 -> 142424 | I47: =+[1]Todo!$E47 -> 200037.73 | J47: 0 | K47: 0 | L47: 0 | M47: 0 | N47: 0 | O47: 0 | P47: 0 | Q47: 0 | R47: 0 | S47: 0 | T47: 0
B48: Monthly Carring Cost: | C48: =+SUM(E48:U48) -> 1603.9537 | E48: =+Profit!B27/Profit!B20 -> 890.28 | F48: 0 | G48: 0 | H48: 0.1 | I48: =+[1]Todo!$E48 -> 713.57367 | J48: 0 | K48: 0 | L48: 0 | M48: 0 | N48: 0 | O48: 0 | P48: 0 | Q48: 0 | R48: 0 | S48: 0 | T48: 0
B49: Monthly Income: | C49: =+SUM(E49:O49) -> 890.3 | E49: =+Profit!H9 -> 890.3 | F49: 0 | G49: 0 | H49: 0 | I49: =+[1]Todo!$E49 -> 0 | J49: 0 | K49: 0 | L49: 0 | M49: 0 | N49: 0 | O49: 0 | P49: 0 | Q49: 0 | R49: 0 | S49: 0 | T49: 0
B50: Total Expected Profit: | C50: =+SUM($E$50:$U$50) -> 1307709.5 | E50: =+Profit!K45 -> 104394.5 | F50: 0 | G50: 0 | H50: 111547.89 | I50: =+[1]Todo!$E50 -> 179023.27 | J50: 68424.71 | K50: 67485.868 | L50: 154708.04 | M50: 154490.2 | N50: 94527.968 | O50: 92658.782 | P50: 64240.53 | Q50: 100167.79 | R50: 37694.072 | S50: 52771.49 | T50: 25574.364
B51: Total Chartable Contribution: | C51: =+SUM($E$51:$U$51) -> 43812.58 | E51: =+E50*0.1 -> 10439.45 | I51: =+[1]Todo!$E51 -> 17902.327 | L51: 15470.804
B52: Average CMA: | C52: =+AVERAGE(E44:T44) -> 293145.56
B53: Average Purchase Cost: | C53: =+AVERAGE(E45:T45) -> 111982.18 | M53: Uncompleted Project
B54: Average Rehab Expense: | C54: =+AVERAGE(E46:T46) -> 39668.191 | M54: Completed for Sell Your Home
B55: Average Profit: | C55: =+AVERAGE(D50:T50) -> 81731.842 | M55: Completed for Buy Your Home

Sheet Contact
A1: Vendor | B1: Phone Number | C1: Contact | D1: Acct/Policy | E1: Email | F1: Purpose
A2: Sellers
A4: Lola Williams | B4: 252 814 4221 | D4: SS 237 72 4905 | E4: username: Wes@BYHLLC.com PW:w3638B0# | G4: https://account.mrcooper.com/ed04d0f3-eba1-467f-91e7-52505132554c/oauth2/v2.0/authorize?p=B2C_1A_SignUpOrSignIn&client_id=2a694b91-5631-4fe1-9039-775a23b420c8&nonce=defaultNonce&redirect_uri=https://www.mrcooper.com/sessions/login&scope=openid&response_type=id_token&response_mode=form_post&pageName=&guid=&ga_client_id=&session_id=395071fa82d98b338e7ef9cf7a7320d9&&getCustomer=no&state={%22redirect%22:null}&x-client-SKU=apollo-accounts-mrcooper
A6: Mortgage | E6: Wiring Instructions: Acct: 46290000967540 Rt#: 021000021 Address: JP Morgan Chase Bank, 270 Park ave, New York, NY 10017
A7: Rocket Mortgage | B7: 866 316 2432 | D7: 0623844180 | E7: https://rocket.com/mortgage/servicing/onboarding?loanNumber=623844180 | F7: sent on 8/23/2023
D8: login: | E8: Wes@BYHLLC.com
D9: Pasword: | E9: w3638B0@
A14: NREIG | B14: 770 734 1523
U16: To | V16: Subject | W16: Sent | X16: Size | Y16: Categories
U17: DefaultCFC@Truist.com | V17: 5008 Larchmont Dr - Loan 9015 2144 11-5998 | W17: 0.44583333 | X17: 478 KB
A20: Insurance National Real Estate Insurance Group LLC
A21: Rani Walker | B21: 678 329 0123 | C21: RWalker@insurancehub.com
A22: Customer Care Specialist
A23: InsuranceHub Leavitt Agency
A24: Phone/SMS/Fax: 678.329.0123 | insurancehub.com
A25: Becki Miron | B25: 678.685.3277 | C25: BMiron@insurancehub.com
A26: Account Manager
A27: InsuranceHub Leavitt Agency
A28: Phone/SMS/Fax: 678.685.3277 | insurancehub.com

Sheet Example Proposal
A1: Building Permits | B1: Permits | C1: File for building, electrical, plumbing ad mechanical permits | D1: 1 | E1: 675
A2: Demo labor | B2: Demolition | C2: Remove two (2) bathroom vanities and toilets | D2: 4 | E2: 33.75
A3: Deck material | B3: Deck material | C3: Supply treated material to build new deck | D3: 144 | E3: 14.85
A4: Supevision | B4: Roof Install | C4: Supervise roof replacement | D4: 0 | E4: 100
A5: Deck labor | B5: Deck | C5: Remove existing deck and build new 12x12 deck and stain. Stain supplied by HO. | D5: 144 | E5: 13.5
A6: Frame | B6: Floor repair | C6: Demo and replace water damaged floor in living room, hallway, first bedroom and both bathrooms | D6: 1 | E6: 7020
A7: Frame | B7: Change Order No. 1 | C7: Repair termte damaged subfloor and joists | D7: 1 | E7: 7500
A8: Supevision | B8: HVAC Install | C8: Supervise HVAC replacement | D8: 3 | E8: 100
A9: Home Repairs | B9: Repair fiberglass tubs | C9: Repair two (2) fiberglass tubs | D9: 2 | E9: 270
A10: Home Repairs | B10: Sliding glass door | C10: Clean track and repair sliding glass door.. No door cost included. | D10: 1 | E10: 202.5
A11: Siding labor | B11: Shed | C11: Repair and paint 12x12 shed. HO to supply paint. | D11: 100 | E11: 6.75
A12: Siding material | B12: Shed repair material | C12: Supply material to replace doors, siding, and some floor on shed | D12: 1 | E12: 472.5
A13: Window labor | B13: Replace broken window glass | C13: Replace glass in laundry room window and master bath | D13: 2 | E13: 303.75
A14: Interest | B14: Draw 1 Interest Charge | C14: Credit Card interest fee
A15: Cleaning | B15: Shed and crawl | C15: Clean shed and crawl | D15: 1375 | E15: 1.0125
A16: Floor Coverings | B16: LVP Flooring | C16: Install 1375 sq. ft. of Presto Plus Weathered Barnboard LVP throughout the home with11/16 Primed Quarter Round shoe molding. GDB to supply the flooring and shoe molding. | D16: 1375 | E16: 6.453
A17: Paint | B17: Powerwash | C17: Powerwash exterior of home and shed. | D17: 1 | E17: 405
A18: Paint | B18: Laundry cabinets | C18: Sand, prime and paint laundry room cabinets HO supplied paint | D18: 1 | E18: 405
A19: Paint | B19: Exterior paint | C19: Paint rails, stain porches, paint shutters, and doors | D19: 500 | E19: 1.35
A20: Paint | B20: Interior paint | C20: Prime with KIlz and paint all interior walls, ceiling and trim/doors. Remove borders, repair drywall. HO to supply paint | D20: 1375 | E20: 4.725
A21: Paint | B21: Paint floors | C21: Paint all floors with Kilz HO to supply paint | D21: 1
A22: Paint | B22: Paint kitchen cabinets | C22: Sand, prime and paint 16 kitchen cabinets. HO supplies paint | D22: 16 | E22: 135
A23: Cabinets & Vanities | B23: Bath vanities | C23: Install two (2) HO supplied bath vanities. Atlantic to install countertops with integrated sinks.. | D23: 2 | E23: 202.5
A24: Cabinets & Vanities | B24: Cabinet hardware | C24: Install knobs bath cabinets HO to supply hardware | D24: 5 | E24: 6.75
A25: Cabinets & Vanities | B25: Kitchen cabinet hardware | C25: Install HO supplied hardware on 16 kitchen cabinets | D25: 16 | E25: 6.75
A26: Supervision | B26: Kitchen Countertops | C26: Supervise installation of kitchen countertops | D26: 3 | E26: 100
A27: Plumbing | B27: Ice Maker Walter Line | C27: Install water line for the refrigerator ice maker. | D27: 1 | E27: 255.15
A28: Plumbing | B28: Kitchen plumbing | C28: Install kitchen sink, faucet and dishwasher. HO to supply sink, dishwasher and faucets. | D28: 3 | E28: 214.65
A29: Plumbing | B29: Install toilets | C29: Install two (2) HO supplied toilets | D29: 2 | E29: 222.75
A30: Plumbing | B30: Bathroom plumbing | C30: Install three (3) HO supplied bathroom faucets. | D30: 3 | E30: 255.15
A31: Electrical & Lighting | B31: Ceiling fans bedrooms | C31: Install ceiling fans with lights in three (3) bedrooms. HO to supply fans and lights. | D31: 3 | E31: 101.25
A32: Electrical & Lighting | B32: Ceiling fan living room | C32: Install ceiling fans with lights in living room.. HO to supply fans and lights. | D32: 1 | E32: 101.25
A33: Electrical & Lighting | B33: Bath lighting | C33: Replace light fixtures in two (2) bathrooms. HO to supply fixtures. | D33: 3 | E33: 67.5
... A47: Home Repairs | B47: Change Order No. 8 | C47: install HO supplied maibox | D47: 1 | E47: 135

Sheet Proposal
B2: ="Preassigned Rows Indicating Payment or Scheduling by " &Profit!E1&" Your Home" -> Preassigned Rows Indicating Payment or Scheduling by Buy Your Home
B4: Preassigned Rows Cordination of Glasgow with Contrtactors
B6: Pasted rows from Builder's Trend Proposal
B8: Notes: Only add rows to the bottom of the table
A11: Cost Code | B11: Title | C11: Description | D11: Qty | E11: Unit Price
A12: Deposit | B12: Deposit | C12: Initial Deposit to Start Job | D12: 0
A13: Draw | B13: Draw 1 | C13: Draw 1 | D13: 0
A14: Draw | B14: Draw 2 | C14: Draw 2 | D14: 0
B15: Sell | C15: List with MLS | D15: 6
A16: HVAC | B16: Cordinate Sub | C16: HVAC | D16: 0 | E16: 0
A17: Floor Coverings | B17: Cordinate Sub | C17: Flooring Contractor | D17: 0 | E17: 200
A18: Supervision | B18: Cordinate Sub | C18: Termite Treatment | D18: 0 | E18: 200
A19: Cabinets & Vanities | B19: Cordinate Sub | C19: Cabinet Delivery | D19: 0 | E19: 200
A20: Countertops | B20: Cordinate Sub | C20: Manage installion of granite countertops by others in kitchen | D20: 0 | E20: 135
C21: Clean out House | D21: 1 | E21: 0
C22: Contract | D22: 0 | E22: 0
A23: Deck labor
A24: Deck labor
A25: Deck material
A26: ... Demo
A27: ... Demo
A28: ... Demo
A29: ... Demo
A30: Demo labor
A31: 20 Millwork & Trim
A32: 20 Millwork & Trim
A33: 20 Millwork & Trim
A34: 22 Specialty
... A37: Bath Accessories
A38: Building Permits | G38: 1160
A39: Cabinets & Vanities
A40: Electrical & Lighting
A41: Frame labor
A42: Frame labor
A43: Frame labor
A44: Frame labor
A45: Frame materials
A46: Frame materials
A47: Frame materials
A48: HVAC
A49: Insulation
A50: Insulation
... A70: Deck labor

Sheet ProposalUpdate
A1: These Cells are updated from the Proposal tab and are protected here. | I1: These cells are updated here and carried over to the Gnatt Chart | P1: Contracted Task | Q1: 1 | R1: Payment | S1: 4
P2: Change Order | Q2: 2 | R2: Not Used | S2: 0
P3: Manage Vendor | Q3: 3 | R3: Post Contract | S3: 5
A4: Party | B4: Item | C4: Cost Code | D4: Title | E4: Description | F4: Qty | G4: Unit Price | H4: Price | I4: Done | J4: Group Order | K4: Start Date | L4: Days | M4: Paid | N4: Notes
A5: =+IF(FromProposal[[#This Row],[Cost Code]]<>0,"Glasgow","") -> Glasgow | B5: 1 | C5: Deposit | D5: Deposit | E5: Initial Deposit to Start Job | F5: 0
A6: =+IF(FromProposal[[#This Row],[Cost Code]]<>0,"Glasgow","") -> Glasgow | B6: 2 | C6: Draw | D6: Draw 1 | E6: Draw 1 | F6: 0
A7: =+IF(FromProposal[[#This Row],[Cost Code]]<>0,"Glasgow","") -> Glasgow | B7: 3 | C7: Draw | D7: Draw 2 | E7: Draw 2 | F7: 0
A8: =+IF(FromProposal[[#This Row],[Cost Code]]<>0,"Glasgow","") | B8: 4 | D8: Sell | E8: List with MLS | F8: 6
A9: =+IF(FromProposal[[#This Row],[Cost Code]]<>0,"Glasgow","") -> Glasgow | B9: 5 | C9: HVAC | D9: Cordinate Sub | E9: HVAC | F9: 0 | G9: 0 | H9: 0
A10: =+IF(FromProposal[[#This Row],[Cost Code]]<>0,"Glasgow","") -> Glasgow | B10: 6 | C10: Floor Coverings | D10: Cordinate Sub | E10: Flooring Contractor | F10: 0 | G10: 200 | H10: 0
A11: =+IF(FromProposal[[#This Row],[Cost Code]]<>0,"Glasgow","") -> Glasgow | B11: 7 | C11: Supervision | D11: Cordinate Sub | E11: Termite Treatment | F11: 0 | G11: 200 | H11: 0
A12: =+IF(FromProposal[[#This Row],[Cost Code]]<>0,"Glasgow","") -> Glasgow | B12: 8 | C12: Cabinets & Vanities | D12: Cordinate Sub | E12: Cabinet Delivery | F12: 0 | G12: 200 | H12: 0
A13: =+IF(FromProposal[[#This Row],[Cost Code]]<>0,"Glasgow","") -> Glasgow | B13: 9 | C13: Countertops | D13: Cordinate Sub | E13: Manage installion of granite countertops by others in kitchen | F13: 0 | G13: 135 | H13: 0
A14: =+IF(FromProposal[[#This Row],[Cost Code]]<>0,"Glasgow","") | B14: 10 | E14: Clean out House | F14: 1 | G14: 0 | H14: 0
A15: =+IF(FromProposal[[#This Row],[Cost Code]]<>0,"Glasgow","") | B15: 11 | E15: Contract | F15: 0 | G15: 0 | H15: 0
A16: =+IF(FromProposal[[#This Row],[Cost Code]]<>0,"Glasgow","") -> Glasgow | B16: 12 | C16: Deck labor
A17: =+IF(FromProposal[[#This Row],[Cost Code]]<>0,"Glasgow","") -> Glasgow | B17: 13 | C17: Deck labor
A18: =+IF(FromProposal[[#This Row],[Cost Code]]<>0,"Glasgow","") -> Glasgow | B18: 14 | C18: Deck material
A19: =+IF(FromProposal[[#This Row],[Cost Code]]<>0,"Glasgow","") -> Glasgow | B19: 15 | C19: ... Demo
A20: =+IF(FromProposal[[#This Row],[Cost Code]]<>0,"Glasgow","") -> Glasgow | B20: 16 | C20: ... Demo

Sheet Gnatt Chart
J1: Expense | N1: Due:
A2: ="Glasgow Design Build for "&Profit!E1& " Your Home" -> Glasgow Design Build for Buy Your Home | E2: Project Start Date: | F2: =+MIN(ProposalToGnatt[Start Date]) -> 0 | H2: Company Paid Materials Total: | J2: =+SUM(H8:H22) -> 5160.24 | M2: =+SUM(O8:O22)-SUM(M8:M22) -> 0
A3: Jonathan Brothers | B3: Jonathan Brothers | H3: Contractors Total: | J3: =SUM(H24:H27) -> 0 | M3: =+J3-SUM(M24:M27) -> 0
A4: =+Profit!B2 -> 3413 Pinetree Ln, Greenville, NC 27858 | B4: =+Profit!B2 -> 3413 Pinetree Ln, Greenville, NC 27858 | E4: Milestone Marker: | G4: 1 | H4: Glasgow Total: | J4: =SUM(ProposalToGnatt[Price]) -> 0 | M4: {=+SUM(ProposalToGnatt[Due]-ProposalToGnatt[Paid])} -> 0
B5: Cells H5 through BK5 contain the day number of the month for the Month represented in the cell block above each date cell and are auto calculated. Do not modify these cells. Dates leading up to Today are shaded. | E5: Milestone Marker 2: | G5: 2 | H5: Grand Total | J5: =+SUM(J2:K4) -> 5160.24 | M5: =+SUM(M2:N4) -> 0
E6: =Profit!E1&" Your Home Supplied Materials" -> Buy Your Home Supplied Materials
A7: Assigned | B7: Item # | C7: Cost Code | D7: Title | E7: Description | F7: Qty | G7: Unit Price | H7: Price | I7: Done | J7: Group Order | K7: Start Date | L7: Days | M7: Paid | N7: Notes | O7: Due | AO7: =IFERROR(IF(LEN(#REF!)=0,"",IF(AND(#REF!=#REF!,#REF!=1),Milestone_Marker_Old,"")),"")
A8: =Profit!$E$1&" Your Home" -> Buy Your Home | B8: 1 | E8: Cleanup (from Demo & Trash Haul Tab) | F8: 1 | G8: =+'Demo & Trash Haul'!G17 -> 0 | H8: =+F8*G8 -> 0 | O8: =IF(I8="Yes",H8,0) -> 0
A9: =Profit!$E$1&" Your Home" -> Buy Your Home | B9: =+B8+1 -> 2 | E9: Taxes - outside of closing (from Taxes tab) | F9: 0 | G9: =+Taxes!E19 -> 2138.17 | H9: =+F9*G9 -> 0 | O9: =IF(I9="Yes",H9,0) -> 0
A10: =Profit!$E$1&" Your Home" -> Buy Your Home | B10: =+B8+1 -> 2 | E10: Appliances (from Appliances Tab) | F10: 1 | G10: =+Appliances!F21 -> 0 | H10: =+F10*G10 -> 0 | O10: =IF(I10="Yes",H10,0) -> 0
A11: =Profit!$E$1&" Your Home" -> Buy Your Home | B11: =+B10+1 -> 3 | E11: Plubing Fixtures | F11: 1 | G11: =+'Plumbing Fixtures'!F23 -> 0 | H11: =+F11*G11 -> 0 | O11: =IF(I11="Yes",H11,0) -> 0
A12: =Profit!$E$1&" Your Home" -> Buy Your Home | B12: =+B11+1 -> 4 | E12: Windows & Doors | F12: 0 | G12: =+'Windows & Doors'!F30 -> 235.81 | H12: =+F12*G12 -> 0 | O12: =IF(I12="Yes",H12,0) -> 0
A13: =Profit!$E$1&" Your Home" -> Buy Your Home | B13: =+B12+1 -> 5 | E13: Cabinets (from Cabinets Tab) | F13: 0 | G13: =+Cabinets!G44 -> 0 | H13: =+F13*G13 -> 0 | O13: =IF(I13="Yes",H13,0) -> 0
A14: =Profit!$E$1&" Your Home" -> Buy Your Home | B14: =+B13+1 -> 6 | E14: Paint (from Paint Tab) | F14: 1 | G14: =+Paint!G28 -> 0 | H14: =+F14*G14 -> 0 | O14: =IF(I14="Yes",H14,0) -> 0
A15: =Profit!$E$1&" Your Home" -> Buy Your Home | B15: =+B14+1 -> 7 | E15: Flooring | F15: 1 | G15: =+Flooring!G7 -> 5098.8 | H15: =+F15*G15 -> 5098.8 | O15: =IF(I15="Yes",H15,0) -> 0 | AP15: =IFERROR(IF(LEN(#REF!)=0,"",IF(P$29=#REF!,Milestone_Marker_Old,"")),"") | AQ15: =IFERROR(IF(LEN(#REF!)=0,"",IF(Q$29=#REF!,Milestone_Marker_Old,"")),"") | AR15: =IFERROR(IF(LEN(#REF!)=0,"",IF(R$29=#REF!,Milestone_Marker_Old,"")),"") | AS15: =IFERROR(IF(LEN(#REF!)=0,"",IF(S$29=#REF!,Milestone_Marker_Old,"")),"") | AT15: =IFERROR(IF(LEN(#REF!)=0,"",IF(T$29=#REF!,Milestone_Marker_Old,"")),"") | AU15: =IFERROR(IF(LEN(#REF!)=0,"",IF(U$29=#REF!,Milestone_Marker_Old,"")),"") | AV15: =IFERROR(IF(LEN(#REF!)=0,"",IF(V$29=#REF!,Milestone_Marker_Old,"")),"") | AW15: =IFERROR(IF(LEN(#REF!)=0,"",IF(W$29=#REF!,Milestone_Marker_Old,"")),"") | ... DU15: =IFERROR(IF(LEN(#REF!)=0,"",IF(CU$29=#REF!,Milestone_Marker_Old,"")),"")
A16: =Profit!$E$1&" Your Home" -> Buy Your Home | B16: =+B15+1 -> 8 | E16: Electrical fixtures (from Misc Tab) | F16: 0 | G16: =+'Electrical Fixtures'!F23 -> 0 | H16: =+F16*G16 -> 0 | O16: =IF(I16="Yes",H16,0) -> 0 | AP16: =IFERROR(IF(LEN(#REF!)=0,"",IF(P$29=#REF!,Milestone_Marker_Old,"")),"") | AQ16: =IFERROR(IF(LEN(#REF!)=0,"",IF(Q$29=#REF!,Milestone_Marker_Old,"")),"") | AR16: =IFERROR(IF(LEN(#REF!)=0,"",IF(R$29=#REF!,Milestone_Marker_Old,"")),"") | AS16: =IFERROR(IF(LEN(#REF!)=0,"",IF(S$29=#REF!,Milestone_Marker_Old,"")),"") | AT16: =IFERROR(IF(LEN(#REF!)=0,"",IF(T$29=#REF!,Milestone_Marker_Old,"")),"") | AU16: =IFERROR(IF(LEN(#REF!)=0,"",IF(U$29=#REF!,Milestone_Marker_Old,"")),"") | AV16: =IFERROR(IF(LEN(#REF!)=0,"",IF(V$29=#REF!,Milestone_Marker_Old,"")),"") | AW16: =IFERROR(IF(LEN(#REF!)=0,"",IF(W$29=#REF!,Milestone_Marker_Old,"")),"") | ... DU16: =IFERROR(IF(LEN(#REF!)=0,"",IF(CU$29=#REF!,Milestone_Marker_Old,"")),"")
A17: =Profit!$E$1&" Your Home" -> Buy Your Home | B17: =+B16+1 -> 9 | E17: Exterior Tab | F17: 1 | G17: =+Exterior!D16 -> 61.44 | H17: =+F17*G17 -> 61.44 | O17: =IF(I17="Yes",H17,0) -> 0
A18: =Profit!$E$1&" Your Home" -> Buy Your Home | B18: =+B17+1 -> 10 | E18: Landscaping Tab | F18: 0 | G18: =+Landscape!G17 -> 0 | H18: =+F18*G18 -> 0 | O18: =IF(I18="Yes",H18,0) -> 0
A19: =Profit!$E$1&" Your Home" -> Buy Your Home | B19: =+B18+1 -> 11 | E19: HVAC Contractor | F19: 0 | G19: =+'Demo & Trash Haul'!F29 -> 0 | H19: =+F19*G19 -> 0 | O19: =IF(I19="Yes",H19,0) -> 0 | AP19: =IFERROR(IF(LEN(#REF!)=0,"",IF(P$29=#REF!,Milestone_Marker_Old,"")),"") | AQ19: =IFERROR(IF(LEN(#REF!)=0,"",IF(Q$29=#REF!,Milestone_Marker_Old,"")),"") | AR19: =IFERROR(IF(LEN(#REF!)=0,"",IF(R$29=#REF!,Milestone_Marker_Old,"")),"") | AS19: =IFERROR(IF(LEN(#REF!)=0,"",IF(S$29=#REF!,Milestone_Marker_Old,"")),"") | AT19: =IFERROR(IF(LEN(#REF!)=0,"",IF(T$29=#REF!,Milestone_Marker_Old,"")),"") | AU19: =IFERROR(IF(LEN(#REF!)=0,"",IF(U$29=#REF!,Milestone_Marker_Old,"")),"") | AV19: =IFERROR(IF(LEN(#REF!)=0,"",IF(V$29=#REF!,Milestone_Marker_Old,"")),"") | AW19: =IFERROR(IF(LEN(#REF!)=0,"",IF(W$29=#REF!,Milestone_Marker_Old,"")),"") | ... DU19: =IFERROR(IF(LEN(#REF!)=0,"",IF(CU$29=#REF!,Milestone_Marker_Old,"")),"")
A20: =Profit!$E$1&" Your Home" -> Buy Your Home | B20: =+B19+1 -> 12 | E20: Landscape | F20: 0 | G20: =+'Demo & Trash Haul'!F30 -> 0 | H20: =+F20*G20 -> 0 | O20: =IF(I20="Yes",H20,0) -> 0 | AP20: =IFERROR(IF(LEN(#REF!)=0,"",IF(P$29=#REF!,Milestone_Marker_Old,"")),"") | AQ20: =IFERROR(IF(LEN(#REF!)=0,"",IF(Q$29=#REF!,Milestone_Marker_Old,"")),"") | AR20: =IFERROR(IF(LEN(#REF!)=0,"",IF(R$29=#REF!,Milestone_Marker_Old,"")),"") | AS20: =IFERROR(IF(LEN(#REF!)=0,"",IF(S$29=#REF!,Milestone_Marker_Old,"")),"") | AT20: =IFERROR(IF(LEN(#REF!)=0,"",IF(T$29=#REF!,Milestone_Marker_Old,"")),"") | AU20: =IFERROR(IF(LEN(#REF!)=0,"",IF(U$29=#REF!,Milestone_Marker_Old,"")),"") | AV20: =IFERROR(IF(LEN(#REF!)=0,"",IF(V$29=#REF!,Milestone_Marker_Old,"")),"") | AW20: =IFERROR(IF(LEN(#REF!)=0,"",IF(W$29=#REF!,Milestone_Marker_Old,"")),"") | ... DU20: =IFERROR(IF(LEN(#REF!)=0,"",IF(CU$29=#REF!,Milestone_Marker_Old,"")),"")
A21: =Profit!$E$1&" Your Home" -> Buy Your Home | B21: =+B20+1 -> 13 | E21: Exterior- Termite | F21: 0 | G21: 0 | H21: =+F21*G21 -> 0 | O21: =IF(I21="Yes",H21,0) -> 0 | AP21: =IFERROR(IF(LEN(#REF!)=0,"",IF(P$29=#REF!,Milestone_Marker_Old,"")),"") | AQ21: =IFERROR(IF(LEN(#REF!)=0,"",IF(Q$29=#REF!,Milestone_Marker_Old,"")),"") | AR21: =IFERROR(IF(LEN(#REF!)=0,"",IF(R$29=#REF!,Milestone_Marker_Old,"")),"") | AS21: =IFERROR(IF(LEN(#REF!)=0,"",IF(S$29=#REF!,Milestone_Marker_Old,"")),"") | AT21: =IFERROR(IF(LEN(#REF!)=0,"",IF(T$29=#REF!,Milestone_Marker_Old,"")),"") | AU21: =IFERROR(IF(LEN(#REF!)=0,"",IF(U$29=#REF!,Milestone_Marker_Old,"")),"") | AV21: =IFERROR(IF(LEN(#REF!)=0,"",IF(V$29=#REF!,Milestone_Marker_Old,"")),"") | AW21: =IFERROR(IF(LEN(#REF!)=0,"",IF(W$29=#REF!,Milestone_Marker_Old,"")),"") | ... DU21: =IFERROR(IF(LEN(#REF!)=0,"",IF(CU$29=#REF!,Milestone_Marker_Old,"")),"")
A22: =Profit!$E$1&" Your Home" -> Buy Your Home | B22: =+B21+1 -> 14 | E22: Drainage | F22: 0 | G22: =+'Demo & Trash Haul'!F32 -> 0 | H22: =+F22*G22 -> 0 | O22: =IF(I22="Yes",H22,0) -> 0 | AP22: =IFERROR(IF(LEN(#REF!)=0,"",IF(P$29=#REF!,Milestone_Marker_Old,"")),"") | AQ22: =IFERROR(IF(LEN(#REF!)=0,"",IF(Q$29=#REF!,Milestone_Marker_Old,"")),"") | AR22: =IFERROR(IF(LEN(#REF!)=0,"",IF(R$29=#REF!,Milestone_Marker_Old,"")),"") | AS22: =IFERROR(IF(LEN(#REF!)=0,"",IF(S$29=#REF!,Milestone_Marker_Old,"")),"") | AT22: =IFERROR(IF(LEN(#REF!)=0,"",IF(T$29=#REF!,Milestone_Marker_Old,"")),"") | AU22: =IFERROR(IF(LEN(#REF!)=0,"",IF(U$29=#REF!,Milestone_Marker_Old,"")),"") | AV22: =IFERROR(IF(LEN(#REF!)=0,"",IF(V$29=#REF!,Milestone_Marker_Old,"")),"") | AW22: =IFERROR(IF(LEN(#REF!)=0,"",IF(W$29=#REF!,Milestone_Marker_Old,"")),"") | ... DU22: =IFERROR(IF(LEN(#REF!)=0,"",IF(CU$29=#REF!,Milestone_Marker_Old,"")),"")
E23: =Profit!E1&" Your Home's Paid Contractors" -> Buy Your Home's Paid Contractors | AP23: =IFERROR(IF(LEN(#REF!)=0,"",IF(P$29=#REF!,Milestone_Marker_Old,"")),"") | AQ23: =IFERROR(IF(LEN(#REF!)=0,"",IF(Q$29=#REF!,Milestone_Marker_Old,"")),"") | AR23: =IFERROR(IF(LEN(#REF!)=0,"",IF(R$29=#REF!,Milestone_Marker_Old,"")),"") | AS23: =IFERROR(IF(LEN(#REF!)=0,"",IF(S$29=#REF!,Milestone_Marker_Old,"")),"") | AT23: =IFERROR(IF(LEN(#REF!)=0,"",IF(T$29=#REF!,Milestone_Marker_Old,"")),"") | AU23: =IFERROR(IF(LEN(#REF!)=0,"",IF(U$29=#REF!,Milestone_Marker_Old,"")),"") | AV23: =IFERROR(IF(LEN(#REF!)=0,"",IF(V$29=#REF!,Milestone_Marker_Old,"")),"") | AW23: =IFERROR(IF(LEN(#REF!)=0,"",IF(W$29=#REF!,Milestone_Marker_Old,"")),"") | ... DU23: =IFERROR(IF(LEN(#REF!)=0,"",IF(CU$29=#REF!,Milestone_Marker_Old,"")),"")
A24: Mabrey Roofing | B24: =+B22+1 -> 15 | E24: Roof Contractor | F24: 0 | G24: =3743.62*2 -> 7487.24 | H24: =+F24*G24 -> 0 | O24: =IF(I24="Yes",H24,0) -> 0 | AA24: Scrolling Increment: | AP24: =IFERROR(IF(LEN(#REF!)=0,"",IF(P$29=#REF!,Milestone_Marker_Old,"")),"") | AQ24: =IFERROR(IF(LEN(#REF!)=0,"",IF(Q$29=#REF!,Milestone_Marker_Old,"")),"") | AR24: =IFERROR(IF(LEN(#REF!)=0,"",IF(R$29=#REF!,Milestone_Marker_Old,"")),"") | AS24: =IFERROR(IF(LEN(#REF!)=0,"",IF(S$29=#REF!,Milestone_Marker_Old,"")),"") | AT24: =IFERROR(IF(LEN(#REF!)=0,"",IF(T$29=#REF!,Milestone_Marker_Old,"")),"") | AU24: =IFERROR(IF(LEN(#REF!)=0,"",IF(U$29=#REF!,Milestone_Marker_Old,"")),"") | AV24: =IFERROR(IF(LEN(#REF!)=0,"",IF(V$29=#REF!,Milestone_Marker_Old,"")),"") | AW24: =IFERROR(IF(LEN(#REF!)=0,"",IF(W$29=#REF!,Milestone_Marker_Old,"")),"") | ... DU24: =IFERROR(IF(LEN(#REF!)=0,"",IF(CU$29=#REF!,Milestone_Marker_Old,"")),"")
A25: Mabrey Roofing | B25: =+B24+1 -> 16 | E25: Roof Contractor | F25: 0 | G25: 400 | H25: =+F25*G25 -> 0 | O25: =IF(I25="Yes",H25,0) -> 0 | AP25: =IFERROR(IF(LEN(#REF!)=0,"",IF(P$29=#REF!,Milestone_Marker_Old,"")),"") | AQ25: =IFERROR(IF(LEN(#REF!)=0,"",IF(Q$29=#REF!,Milestone_Marker_Old,"")),"") | AR25: =IFERROR(IF(LEN(#REF!)=0,"",IF(R$29=#REF!,Milestone_Marker_Old,"")),"") | AS25: =IFERROR(IF(LEN(#REF!)=0,"",IF(S$29=#REF!,Milestone_Marker_Old,"")),"") | AT25: =IFERROR(IF(LEN(#REF!)=0,"",IF(T$29=#REF!,Milestone_Marker_Old,"")),"") | AU25: =IFERROR(IF(LEN(#REF!)=0,"",IF(U$29=#REF!,Milestone_Marker_Old,"")),"") | AV25: =IFERROR(IF(LEN(#REF!)=0,"",IF(V$29=#REF!,Milestone_Marker_Old,"")),"") | AW25: =IFERROR(IF(LEN(#REF!)=0,"",IF(W$29=#REF!,Milestone_Marker_Old,"")),"") | ... DU25: =IFERROR(IF(LEN(#REF!)=0,"",IF(CU$29=#REF!,Milestone_Marker_Old,"")),"")
A26: Love Services | B26: =+B25+1 -> 17 | E26: HVAC Contractor - Package Heat Pump | F26: 1 | G26: =+HVAC!F13 -> 0 | H26: =+F26*G26 -> 0 | O26: =IF(I26="Yes",H26,0) -> 0 | AB26: 0
A27: Love Services | B27: =+B26+1 -> 18 | E27: HVAC Contractor - Duct Work | F27: 0 | G27: 4598 | H27: =+F27*G27 -> 0 | O27: =IF(I27="Yes",H27,0) -> 0
E28: Glasgow Design Items (all items should be updated from Proposal or ProposalUpdate tab) | P28: =IF(TEXT(Project_Start,"mmmm")=TEXT(P29,"mmmm"),"",TEXT(P29,"mmmm")) | Q28: =IF(TEXT(P29,"mmmm")=TEXT(Q29,"mmmm"),"",TEXT(Q29,"mmmm")) | R28: =IF(TEXT(Q29,"mmmm")=TEXT(R29,"mmmm"),"",TEXT(R29,"mmmm")) | S28: =IF(TEXT(R29,"mmmm")=TEXT(S29,"mmmm"),"",TEXT(S29,"mmmm")) | T28: =IF(TEXT(S29,"mmmm")=TEXT(T29,"mmmm"),"",TEXT(T29,"mmmm")) | U28: =IF(TEXT(T29,"mmmm")=TEXT(U29,"mmmm"),"",TEXT(U29,"mmmm")) | V28: =IF(TEXT(U29,"mmmm")=TEXT(V29,"mmmm"),"",TEXT(V29,"mmmm")) | W28: =IF(TEXT(V29,"mmmm")=TEXT(W29,"mmmm"),"",TEXT(W29,"mmmm")) | X28: =IF(TEXT(W29,"mmmm")=TEXT(X29,"mmmm"),"",TEXT(X29,"mmmm")) | ... CU28: =IF(TEXT(CT29,"mmmm")=TEXT(CU29,"mmmm"),"",TEXT(CU29,"mmmm"))
A29: Party | B29: Item | C29: Cost Code | D29: Title | E29: Description | F29: Qty | G29: Unit Price | H29: Price | I29: Done | J29: Group Order | K29: Start Date | L29: Days | M29: Paid | N29: Notes | O29: Due | P29: =IFERROR(Project_Start+Scrolling_Increment,TODAY()) -> 0 | Q29: =+P29+1 -> 1 | R29: =+Q29+1 -> 2 | S29: =+R29+1 -> 3 | T29: =+S29+1 -> 4 | U29: =+T29+1 -> 5 | V29: =+U29+1 -> 6 | W29: =+V29+1 -> 7 | X29: =+W29+1 -> 8 | ... CU29: =+CT29+1 -> 83
A30: Glasgow | B30: 1 | C30: Deposit | D30: Deposit | E30: Initial Deposit to Start Job | F30: 0 | P30: =IFERROR(+IF(P$29=ProposalToGnatt[[#This Row],[Start Date]],Milestone_Marker,IF(AND(P$29>ProposalToGnatt[[#This Row],[Start Date]],P$29<ProposalToGnatt[[#This Row],[Start Date]]+ProposalToGnatt[[#This Row],[Days]]),$G$5,"")),"") -> 1 | Q30: =IFERROR(+IF(Q$29=ProposalToGnatt[[#This Row],[Start Date]],Milestone_Marker,IF(AND(Q$29>ProposalToGnatt[[#This Row],[Start Date]],Q$29<ProposalToGnatt[[#This Row],[Start Date]]+ProposalToGnatt[[#This Row],[Days]]),$G$5,"")),"") | R30: =IFERROR(+IF(R$29=ProposalToGnatt[[#This Row],[Start Date]],Milestone_Marker,IF(AND(R$29>ProposalToGnatt[[#This Row],[Start Date]],R$29<ProposalToGnatt[[#This Row],[Start Date]]+ProposalToGnatt[[#This Row],[Days]]),$G$5,"")),"") | S30: =IFERROR(+IF(S$29=ProposalToGnatt[[#This Row],[Start Date]],Milestone_Marker,IF(AND(S$29>ProposalToGnatt[[#This Row],[Start Date]],S$29<ProposalToGnatt[[#This Row],[Start Date]]+ProposalToGnatt[[#This Row],[Days]]),$G$5,"")),"") | T30: =IFERROR(+IF(T$29=ProposalToGnatt[[#This Row],[Start Date]],Milestone_Marker,IF(AND(T$29>ProposalToGnatt[[#This Row],[Start Date]],T$29<ProposalToGnatt[[#This Row],[Start Date]]+ProposalToGnatt[[#This Row],[Days]]),$G$5,"")),"") | U30: =IFERROR(+IF(U$29=ProposalToGnatt[[#This Row],[Start Date]],Milestone_Marker,IF(AND(U$29>ProposalToGnatt[[#This Row],[Start Date]],U$29<ProposalToGnatt[[#This Row],[Start Date]]+ProposalToGnatt[[#This Row],[Days]]),$G$5,"")),"") | V30: =IFERROR(+IF(V$29=ProposalToGnatt[[#This Row],[Start Date]],Milestone_Marker,IF(AND(V$29>ProposalToGnatt[[#This Row],[Start Date]],V$29<ProposalToGnatt[[#This Row],[Start Date]]+ProposalToGnatt[[#This Row],[Days]]),$G$5,"")),"") | W30: =IFERROR(+IF(W$29=ProposalToGnatt[[#This Row],[Start Date]],Milestone_Marker,IF(AND(W$29>ProposalToGnatt[[#This Row],[Start Date]],W$29<ProposalToGnatt[[#This Row],[Start Date]]+ProposalToGnatt[[#This Row],[Days]]),$G$5,"")),"") | ... CU30: =IFERROR(+IF(CU$29=ProposalToGnatt[[#This Row],[Start Date]],Milestone_Marker,IF(AND(CU$29>ProposalToGnatt[[#This Row],[Start Date]],CU$29<ProposalToGnatt[[#This Row],[Start Date]]+ProposalToGnatt[[#This Row],[Days]]),$G$5,"")),"")
A31: Glasgow | B31: 2 | C31: Draw | D31: Draw 1 | E31: Draw 1 | F31: 0 | P31: =IFERROR(+IF(P$29=ProposalToGnatt[[#This Row],[Start Date]],Milestone_Marker,IF(AND(P$29>ProposalToGnatt[[#This Row],[Start Date]],P$29<ProposalToGnatt[[#This Row],[Start Date]]+ProposalToGnatt[[#This Row],[Days]]),$G$5,"")),"") -> 1 | Q31: =IFERROR(+IF(Q$29=ProposalToGnatt[[#This Row],[Start Date]],Milestone_Marker,IF(AND(Q$29>ProposalToGnatt[[#This Row],[Start Date]],Q$29<ProposalToGnatt[[#This Row],[Start Date]]+ProposalToGnatt[[#This Row],[Days]]),$G$5,"")),"") | R31: =IFERROR(+IF(R$29=ProposalToGnatt[[#This Row],[Start Date]],Milestone_Marker,IF(AND(R$29>ProposalToGnatt[[#This Row],[Start Date]],R$29<ProposalToGnatt[[#This Row],[Start Date]]+ProposalToGnatt[[#This Row],[Days]]),$G$5,"")),"") | S31: =IFERROR(+IF(S$29=ProposalToGnatt[[#This Row],[Start Date]],Milestone_Marker,IF(AND(S$29>ProposalToGnatt[[#This Row],[Start Date]],S$29<ProposalToGnatt[[#This Row],[Start Date]]+ProposalToGnatt[[#This Row],[Days]]),$G$5,"")),"") | T31: =IFERROR(+IF(T$29=ProposalToGnatt[[#This Row],[Start Date]],Milestone_Marker,IF(AND(T$29>ProposalToGnatt[[#This Row],[Start Date]],T$29<ProposalToGnatt[[#This Row],[Start Date]]+ProposalToGnatt[[#This Row],[Days]]),$G$5,"")),"") | U31: =IFERROR(+IF(U$29=ProposalToGnatt[[#This Row],[Start Date]],Milestone_Marker,IF(AND(U$29>ProposalToGnatt[[#This Row],[Start Date]],U$29<ProposalToGnatt[[#This Row],[Start Date]]+ProposalToGnatt[[#This Row],[Days]]),$G$5,"")),"") | V31: =IFERROR(+IF(V$29=ProposalToGnatt[[#This Row],[Start Date]],Milestone_Marker,IF(AND(V$29>ProposalToGnatt[[#This Row],[Start Date]],V$29<ProposalToGnatt[[#This Row],[Start Date]]+ProposalToGnatt[[#This Row],[Days]]),$G$5,"")),"") | W31: =IFERROR(+IF(W$29=ProposalToGnatt[[#This Row],[Start Date]],Milestone_Marker,IF(AND(W$29>ProposalToGnatt[[#This Row],[Start Date]],W$29<ProposalToGnatt[[#This Row],[Start Date]]+ProposalToGnatt[[#This Row],[Days]]),$G$5,"")),"") | ... CU31: =IFERROR(+IF(CU$29=ProposalToGnatt[[#This Row],[Start Date]],Milestone_Marker,IF(AND(CU$29>ProposalToGnatt[[#This Row],[Start Date]],CU$29<ProposalToGnatt[[#This Row],[Start Date]]+ProposalToGnatt[[#This Row],[Days]]),$G$5,"")),"")
A32: Glasgow | B32: 3 | C32: Draw | D32: Draw 2 | E32: Draw 2 | F32: 0 | P32: =IFERROR(+IF(P$29=ProposalToGnatt[[#This Row],[Start Date]],Milestone_Marker,IF(AND(P$29>ProposalToGnatt[[#This Row],[Start Date]],P$29<ProposalToGnatt[[#This Row],[Start Date]]+ProposalToGnatt[[#This Row],[Days]]),$G$5,"")),"") -> 1 | Q32: =IFERROR(+IF(Q$29=ProposalToGnatt[[#This Row],[Start Date]],Milestone_Marker,IF(AND(Q$29>ProposalToGnatt[[#This Row],[Start Date]],Q$29<ProposalToGnatt[[#This Row],[Start Date]]+ProposalToGnatt[[#This Row],[Days]]),$G$5,"")),"") | R32: =IFERROR(+IF(R$29=ProposalToGnatt[[#This Row],[Start Date]],Milestone_Marker,IF(AND(R$29>ProposalToGnatt[[#This Row],[Start Date]],R$29<ProposalToGnatt[[#This Row],[Start Date]]+ProposalToGnatt[[#This Row],[Days]]),$G$5,"")),"") | S32: =IFERROR(+IF(S$29=ProposalToGnatt[[#This Row],[Start Date]],Milestone_Marker,IF(AND(S$29>ProposalToGnatt[[#This Row],[Start Date]],S$29<ProposalToGnatt[[#This Row],[Start Date]]+ProposalToGnatt[[#This Row],[Days]]),$G$5,"")),"") | T32: =IFERROR(+IF(T$29=ProposalToGnatt[[#This Row],[Start Date]],Milestone_Marker,IF(AND(T$29>ProposalToGnatt[[#This Row],[Start Date]],T$29<ProposalToGnatt[[#This Row],[Start Date]]+ProposalToGnatt[[#This Row],[Days]]),$G$5,"")),"") | U32: =IFERROR(+IF(U$29=ProposalToGnatt[[#This Row],[Start Date]],Milestone_Marker,IF(AND(U$29>ProposalToGnatt[[#This Row],[Start Date]],U$29<ProposalToGnatt[[#This Row],[Start Date]]+ProposalToGnatt[[#This Row],[Days]]),$G$5,"")),"") | V32: =IFERROR(+IF(V$29=ProposalToGnatt[[#This Row],[Start Date]],Milestone_Marker,IF(AND(V$29>ProposalToGnatt[[#This Row],[Start Date]],V$29<ProposalToGnatt[[#This Row],[Start Date]]+ProposalToGnatt[[#This Row],[Days]]),$G$5,"")),"") | W32: =IFERROR(+IF(W$29=ProposalToGnatt[[#This Row],[Start Date]],Milestone_Marker,IF(AND(W$29>ProposalToGnatt[[#This Row],[Start Date]],W$29<ProposalToGnatt[[#This Row],[Start Date]]+ProposalToGnatt[[#This Row],[Days]]),$G$5,"")),"") | ... CU32: =IFERROR(+IF(CU$29=ProposalToGnatt[[#This Row],[Start Date]],Milestone_Marker,IF(AND(CU$29>ProposalToGnatt[[#This Row],[Start Date]],CU$29<ProposalToGnatt[[#This Row],[Start Date]]+ProposalToGnatt[[#This Row],[Days]]),$G$5,"")),"")
B33: 4 | D33: Sell | E33: List with MLS | F33: 6 | P33: =IFERROR(+IF(P$29=ProposalToGnatt[[#This Row],[Start Date]],Milestone_Marker,IF(AND(P$29>ProposalToGnatt[[#This Row],[Start Date]],P$29<ProposalToGnatt[[#This Row],[Start Date]]+ProposalToGnatt[[#This Row],[Days]]),$G$5,"")),"") -> 1 | Q33: =IFERROR(+IF(Q$29=ProposalToGnatt[[#This Row],[Start Date]],Milestone_Marker,IF(AND(Q$29>ProposalToGnatt[[#This Row],[Start Date]],Q$29<ProposalToGnatt[[#This Row],[Start Date]]+ProposalToGnatt[[#This Row],[Days]]),$G$5,"")),"") | R33: =IFERROR(+IF(R$29=ProposalToGnatt[[#This Row],[Start Date]],Milestone_Marker,IF(AND(R$29>ProposalToGnatt[[#This Row],[Start Date]],R$29<ProposalToGnatt[[#This Row],[Start Date]]+ProposalToGnatt[[#This Row],[Days]]),$G$5,"")),"") | S33: =IFERROR(+IF(S$29=ProposalToGnatt[[#This Row],[Start Date]],Milestone_Marker,IF(AND(S$29>ProposalToGnatt[[#This Row],[Start Date]],S$29<ProposalToGnatt[[#This Row],[Start Date]]+ProposalToGnatt[[#This Row],[Days]]),$G$5,"")),"") | T33: =IFERROR(+IF(T$29=ProposalToGnatt[[#This Row],[Start Date]],Milestone_Marker,IF(AND(T$29>ProposalToGnatt[[#This Row],[Start Date]],T$29<ProposalToGnatt[[#This Row],[Start Date]]+ProposalToGnatt[[#This Row],[Days]]),$G$5,"")),"") | U33: =IFERROR(+IF(U$29=ProposalToGnatt[[#This Row],[Start Date]],Milestone_Marker,IF(AND(U$29>ProposalToGnatt[[#This Row],[Start Date]],U$29<ProposalToGnatt[[#This Row],[Start Date]]+ProposalToGnatt[[#This Row],[Days]]),$G$5,"")),"") | V33: =IFERROR(+IF(V$29=ProposalToGnatt[[#This Row],[Start Date]],Milestone_Marker,IF(AND(V$29>ProposalToGnatt[[#This Row],[Start Date]],V$29<ProposalToGnatt[[#This Row],[Start Date]]+ProposalToGnatt[[#This Row],[Days]]),$G$5,"")),"") | W33: =IFERROR(+IF(W$29=ProposalToGnatt[[#This Row],[Start Date]],Milestone_Marker,IF(AND(W$29>ProposalToGnatt[[#This Row],[Start Date]],W$29<ProposalToGnatt[[#This Row],[Start Date]]+ProposalToGnatt[[#This Row],[Days]]),$G$5,"")),"") | ... CU33: =IFERROR(+IF(CU$29=ProposalToGnatt[[#This Row],[Start Date]],Milestone_Marker,IF(AND(CU$29>ProposalToGnatt[[#This Row],[Start Date]],CU$29<ProposalToGnatt[[#This Row],[Start Date]]+ProposalToGnatt[[#This Row],[Days]]),$G$5,"")),"")
A34: Glasgow | B34: 5 | C34: HVAC | D34: Cordinate Sub | E34: HVAC | F34: 0 | G34: 0 | H34: 0 | P34: =IFERROR(+IF(P$29=ProposalToGnatt[[#This Row],[Start Date]],Milestone_Marker,IF(AND(P$29>ProposalToGnatt[[#This Row],[Start Date]],P$29<ProposalToGnatt[[#This Row],[Start Date]]+ProposalToGnatt[[#This Row],[Days]]),$G$5,"")),"") -> 1 | Q34: =IFERROR(+IF(Q$29=ProposalToGnatt[[#This Row],[Start Date]],Milestone_Marker,IF(AND(Q$29>ProposalToGnatt[[#This Row],[Start Date]],Q$29<ProposalToGnatt[[#This Row],[Start Date]]+ProposalToGnatt[[#This Row],[Days]]),$G$5,"")),"") | R34: =IFERROR(+IF(R$29=ProposalToGnatt[[#This Row],[Start Date]],Milestone_Marker,IF(AND(R$29>ProposalToGnatt[[#This Row],[Start Date]],R$29<ProposalToGnatt[[#This Row],[Start Date]]+ProposalToGnatt[[#This Row],[Days]]),$G$5,"")),"") | S34: =IFERROR(+IF(S$29=ProposalToGnatt[[#This Row],[Start Date]],Milestone_Marker,IF(AND(S$29>ProposalToGnatt[[#This Row],[Start Date]],S$29<ProposalToGnatt[[#This Row],[Start Date]]+ProposalToGnatt[[#This Row],[Days]]),$G$5,"")),"") | T34: =IFERROR(+IF(T$29=ProposalToGnatt[[#This Row],[Start Date]],Milestone_Marker,IF(AND(T$29>ProposalToGnatt[[#This Row],[Start Date]],T$29<ProposalToGnatt[[#This Row],[Start Date]]+ProposalToGnatt[[#This Row],[Days]]),$G$5,"")),"") | U34: =IFERROR(+IF(U$29=ProposalToGnatt[[#This Row],[Start Date]],Milestone_Marker,IF(AND(U$29>ProposalToGnatt[[#This Row],[Start Date]],U$29<ProposalToGnatt[[#This Row],[Start Date]]+ProposalToGnatt[[#This Row],[Days]]),$G$5,"")),"") | V34: =IFERROR(+IF(V$29=ProposalToGnatt[[#This Row],[Start Date]],Milestone_Marker,IF(AND(V$29>ProposalToGnatt[[#This Row],[Start Date]],V$29<ProposalToGnatt[[#This Row],[Start Date]]+ProposalToGnatt[[#This Row],[Days]]),$G$5,"")),"") | W34: =IFERROR(+IF(W$29=ProposalToGnatt[[#This Row],[Start Date]],Milestone_Marker,IF(AND(W$29>ProposalToGnatt[[#This Row],[Start Date]],W$29<ProposalToGnatt[[#This Row],[Start Date]]+ProposalToGnatt[[#This Row],[Days]]),$G$5,"")),"") | ... CU34: =IFERROR(+IF(CU$29=ProposalToGnatt[[#This Row],[Start Date]],Milestone_Marker,IF(AND(CU$29>ProposalToGnatt[[#This Row],[Start Date]],CU$29<ProposalToGnatt[[#This Row],[Start Date]]+ProposalToGnatt[[#This Row],[Days]]),$G$5,"")),"")
A35: Glasgow | B35: 6 | C35: Floor Coverings | D35: Cordinate Sub | E35: Flooring Contractor | F35: 0 | G35: 200 | H35: 0 | P35: =IFERROR(+IF(P$29=ProposalToGnatt[[#This Row],[Start Date]],Milestone_Marker,IF(AND(P$29>ProposalToGnatt[[#This Row],[Start Date]],P$29<ProposalToGnatt[[#This Row],[Start Date]]+ProposalToGnatt[[#This Row],[Days]]),$G$5,"")),"") -> 1 | Q35: =IFERROR(+IF(Q$29=ProposalToGnatt[[#This Row],[Start Date]],Milestone_Marker,IF(AND(Q$29>ProposalToGnatt[[#This Row],[Start Date]],Q$29<ProposalToGnatt[[#This Row],[Start Date]]+ProposalToGnatt[[#This Row],[Days]]),$G$5,"")),"") | R35: =IFERROR(+IF(R$29=ProposalToGnatt[[#This Row],[Start Date]],Milestone_Marker,IF(AND(R$29>ProposalToGnatt[[#This Row],[Start Date]],R$29<ProposalToGnatt[[#This Row],[Start Date]]+ProposalToGnatt[[#This Row],[Days]]),$G$5,"")),"") | S35: =IFERROR(+IF(S$29=ProposalToGnatt[[#This Row],[Start Date]],Milestone_Marker,IF(AND(S$29>ProposalToGnatt[[#This Row],[Start Date]],S$29<ProposalToGnatt[[#This Row],[Start Date]]+ProposalToGnatt[[#This Row],[Days]]),$G$5,"")),"") | T35: =IFERROR(+IF(T$29=ProposalToGnatt[[#This Row],[Start Date]],Milestone_Marker,IF(AND(T$29>ProposalToGnatt[[#This Row],[Start Date]],T$29<ProposalToGnatt[[#This Row],[Start Date]]+ProposalToGnatt[[#This Row],[Days]]),$G$5,"")),"") | U35: =IFERROR(+IF(U$29=ProposalToGnatt[[#This Row],[Start Date]],Milestone_Marker,IF(AND(U$29>ProposalToGnatt[[#This Row],[Start Date]],U$29<ProposalToGnatt[[#This Row],[Start Date]]+ProposalToGnatt[[#This Row],[Days]]),$G$5,"")),"") | V35: =IFERROR(+IF(V$29=ProposalToGnatt[[#This Row],[Start Date]],Milestone_Marker,IF(AND(V$29>ProposalToGnatt[[#This Row],[Start Date]],V$29<ProposalToGnatt[[#This Row],[Start Date]]+ProposalToGnatt[[#This Row],[Days]]),$G$5,"")),"") | W35: =IFERROR(+IF(W$29=ProposalToGnatt[[#This Row],[Start Date]],Milestone_Marker,IF(AND(W$29>ProposalToGnatt[[#This Row],[Start Date]],W$29<ProposalToGnatt[[#This Row],[Start Date]]+ProposalToGnatt[[#This Row],[Days]]),$G$5,"")),"") | ... CU35: =IFERROR(+IF(CU$29=ProposalToGnatt[[#This Row],[Start Date]],Milestone_Marker,IF(AND(CU$29>ProposalToGnatt[[#This Row],[Start Date]],CU$29<ProposalToGnatt[[#This Row],[Start Date]]+ProposalToGnatt[[#This Row],[Days]]),$G$5,"")),"")
A36: Glasgow | B36: 7 | C36: Supervision | D36: Cordinate Sub | E36: Termite Treatment | F36: 0 | G36: 200 | H36: 0 | P36: =IFERROR(+IF(P$29=ProposalToGnatt[[#This Row],[Start Date]],Milestone_Marker,IF(AND(P$29>ProposalToGnatt[[#This Row],[Start Date]],P$29<ProposalToGnatt[[#This Row],[Start Date]]+ProposalToGnatt[[#This Row],[Days]]),$G$5,"")),"") -> 1 | Q36: =IFERROR(+IF(Q$29=ProposalToGnatt[[#This Row],[Start Date]],Milestone_Marker,IF(AND(Q$29>ProposalToGnatt[[#This Row],[Start Date]],Q$29<ProposalToGnatt[[#This Row],[Start Date]]+ProposalToGnatt[[#This Row],[Days]]),$G$5,"")),"") | R36: =IFERROR(+IF(R$29=ProposalToGnatt[[#This Row],[Start Date]],Milestone_Marker,IF(AND(R$29>ProposalToGnatt[[#This Row],[Start Date]],R$29<ProposalToGnatt[[#This Row],[Start Date]]+ProposalToGnatt[[#This Row],[Days]]),$G$5,"")),"") | S36: =IFERROR(+IF(S$29=ProposalToGnatt[[#This Row],[Start Date]],Milestone_Marker,IF(AND(S$29>ProposalToGnatt[[#This Row],[Start Date]],S$29<ProposalToGnatt[[#This Row],[Start Date]]+ProposalToGnatt[[#This Row],[Days]]),$G$5,"")),"") | T36: =IFERROR(+IF(T$29=ProposalToGnatt[[#This Row],[Start Date]],Milestone_Marker,IF(AND(T$29>ProposalToGnatt[[#This Row],[Start Date]],T$29<ProposalToGnatt[[#This Row],[Start Date]]+ProposalToGnatt[[#This Row],[Days]]),$G$5,"")),"") | U36: =IFERROR(+IF(U$29=ProposalToGnatt[[#This Row],[Start Date]],Milestone_Marker,IF(AND(U$29>ProposalToGnatt[[#This Row],[Start Date]],U$29<ProposalToGnatt[[#This Row],[Start Date]]+ProposalToGnatt[[#This Row],[Days]]),$G$5,"")),"") | V36: =IFERROR(+IF(V$29=ProposalToGnatt[[#This Row],[Start Date]],Milestone_Marker,IF(AND(V$29>ProposalToGnatt[[#This Row],[Start Date]],V$29<ProposalToGnatt[[#This Row],[Start Date]]+ProposalToGnatt[[#This Row],[Days]]),$G$5,"")),"") | W36: =IFERROR(+IF(W$29=ProposalToGnatt[[#This Row],[Start Date]],Milestone_Marker,IF(AND(W$29>ProposalToGnatt[[#This Row],[Start Date]],W$29<ProposalToGnatt[[#This Row],[Start Date]]+ProposalToGnatt[[#This Row],[Days]]),$G$5,"")),"") | ... CU36: =IFERROR(+IF(CU$29=ProposalToGnatt[[#This Row],[Start Date]],Milestone_Marker,IF(AND(CU$29>ProposalToGnatt[[#This Row],[Start Date]],CU$29<ProposalToGnatt[[#This Row],[Start Date]]+ProposalToGnatt[[#This Row],[Days]]),$G$5,"")),"")
A37: Glasgow | B37: 8 | C37: Cabinets & Vanities | D37: Cordinate Sub | E37: Cabinet Delivery | F37: 0 | G37: 200 | H37: 0 | P37: =IFERROR(+IF(P$29=ProposalToGnatt[[#This Row],[Start Date]],Milestone_Marker,IF(AND(P$29>ProposalToGnatt[[#This Row],[Start Date]],P$29<ProposalToGnatt[[#This Row],[Start Date]]+ProposalToGnatt[[#This Row],[Days]]),$G$5,"")),"") -> 1 | Q37: =IFERROR(+IF(Q$29=ProposalToGnatt[[#This Row],[Start Date]],Milestone_Marker,IF(AND(Q$29>ProposalToGnatt[[#This Row],[Start Date]],Q$29<ProposalToGnatt[[#This Row],[Start Date]]+ProposalToGnatt[[#This Row],[Days]]),$G$5,"")),"") | R37: =IFERROR(+IF(R$29=ProposalToGnatt[[#This Row],[Start Date]],Milestone_Marker,IF(AND(R$29>ProposalToGnatt[[#This Row],[Start Date]],R$29<ProposalToGnatt[[#This Row],[Start Date]]+ProposalToGnatt[[#This Row],[Days]]),$G$5,"")),"") | S37: =IFERROR(+IF(S$29=ProposalToGnatt[[#This Row],[Start Date]],Milestone_Marker,IF(AND(S$29>ProposalToGnatt[[#This Row],[Start Date]],S$29<ProposalToGnatt[[#This Row],[Start Date]]+ProposalToGnatt[[#This Row],[Days]]),$G$5,"")),"") | T37: =IFERROR(+IF(T$29=ProposalToGnatt[[#This Row],[Start Date]],Milestone_Marker,IF(AND(T$29>ProposalToGnatt[[#This Row],[Start Date]],T$29<ProposalToGnatt[[#This Row],[Start Date]]+ProposalToGnatt[[#This Row],[Days]]),$G$5,"")),"") | U37: =IFERROR(+IF(U$29=ProposalToGnatt[[#This Row],[Start Date]],Milestone_Marker,IF(AND(U$29>ProposalToGnatt[[#This Row],[Start Date]],U$29<ProposalToGnatt[[#This Row],[Start Date]]+ProposalToGnatt[[#This Row],[Days]]),$G$5,"")),"") | V37: =IFERROR(+IF(V$29=ProposalToGnatt[[#This Row],[Start Date]],Milestone_Marker,IF(AND(V$29>ProposalToGnatt[[#This Row],[Start Date]],V$29<ProposalToGnatt[[#This Row],[Start Date]]+ProposalToGnatt[[#This Row],[Days]]),$G$5,"")),"") | W37: =IFERROR(+IF(W$29=ProposalToGnatt[[#This Row],[Start Date]],Milestone_Marker,IF(AND(W$29>ProposalToGnatt[[#This Row],[Start Date]],W$29<ProposalToGnatt[[#This Row],[Start Date]]+ProposalToGnatt[[#This Row],[Days]]),$G$5,"")),"") | ... CU37: =IFERROR(+IF(CU$29=ProposalToGnatt[[#This Row],[Start Date]],Milestone_Marker,IF(AND(CU$29>ProposalToGnatt[[#This Row],[Start Date]],CU$29<ProposalToGnatt[[#This Row],[Start Date]]+ProposalToGnatt[[#This Row],[Days]]),$G$5,"")),"")
A38: Glasgow | B38: 9 | C38: Countertops | D38: Cordinate Sub | E38: Manage installion of granite countertops by others in kitchen | F38: 0 | G38: 135 | H38: 0 | P38: =IFERROR(+IF(P$29=ProposalToGnatt[[#This Row],[Start Date]],Milestone_Marker,IF(AND(P$29>ProposalToGnatt[[#This Row],[Start Date]],P$29<ProposalToGnatt[[#This Row],[Start Date]]+ProposalToGnatt[[#This Row],[Days]]),$G$5,"")),"") -> 1 | Q38: =IFERROR(+IF(Q$29=ProposalToGnatt[[#This Row],[Start Date]],Milestone_Marker,IF(AND(Q$29>ProposalToGnatt[[#This Row],[Start Date]],Q$29<ProposalToGnatt[[#This Row],[Start Date]]+ProposalToGnatt[[#This Row],[Days]]),$G$5,"")),"") | R38: =IFERROR(+IF(R$29=ProposalToGnatt[[#This Row],[Start Date]],Milestone_Marker,IF(AND(R$29>ProposalToGnatt[[#This Row],[Start Date]],R$29<ProposalToGnatt[[#This Row],[Start Date]]+ProposalToGnatt[[#This Row],[Days]]),$G$5,"")),"") | S38: =IFERROR(+IF(S$29=ProposalToGnatt[[#This Row],[Start Date]],Milestone_Marker,IF(AND(S$29>ProposalToGnatt[[#This Row],[Start Date]],S$29<ProposalToGnatt[[#This Row],[Start Date]]+ProposalToGnatt[[#This Row],[Days]]),$G$5,"")),"") | T38: =IFERROR(+IF(T$29=ProposalToGnatt[[#This Row],[Start Date]],Milestone_Marker,IF(AND(T$29>ProposalToGnatt[[#This Row],[Start Date]],T$29<ProposalToGnatt[[#This Row],[Start Date]]+ProposalToGnatt[[#This Row],[Days]]),$G$5,"")),"") | U38: =IFERROR(+IF(U$29=ProposalToGnatt[[#This Row],[Start Date]],Milestone_Marker,IF(AND(U$29>ProposalToGnatt[[#This Row],[Start Date]],U$29<ProposalToGnatt[[#This Row],[Start Date]]+ProposalToGnatt[[#This Row],[Days]]),$G$5,"")),"") | V38: =IFERROR(+IF(V$29=ProposalToGnatt[[#This Row],[Start Date]],Milestone_Marker,IF(AND(V$29>ProposalToGnatt[[#This Row],[Start Date]],V$29<ProposalToGnatt[[#This Row],[Start Date]]+ProposalToGnatt[[#This Row],[Days]]),$G$5,"")),"") | W38: =IFERROR(+IF(W$29=ProposalToGnatt[[#This Row],[Start Date]],Milestone_Marker,IF(AND(W$29>ProposalToGnatt[[#This Row],[Start Date]],W$29<ProposalToGnatt[[#This Row],[Start Date]]+ProposalToGnatt[[#This Row],[Days]]),$G$5,"")),"") | ... CU38: =IFERROR(+IF(CU$29=ProposalToGnatt[[#This Row],[Start Date]],Milestone_Marker,IF(AND(CU$29>ProposalToGnatt[[#This Row],[Start Date]],CU$29<ProposalToGnatt[[#This Row],[Start Date]]+ProposalToGnatt[[#This Row],[Days]]),$G$5,"")),"")
B39: 10 | E39: Clean out House | F39: 1 | G39: 0 | H39: 0 | P39: =IFERROR(+IF(P$29=ProposalToGnatt[[#This Row],[Start Date]],Milestone_Marker,IF(AND(P$29>ProposalToGnatt[[#This Row],[Start Date]],P$29<ProposalToGnatt[[#This Row],[Start Date]]+ProposalToGnatt[[#This Row],[Days]]),$G$5,"")),"") -> 1 | Q39: =IFERROR(+IF(Q$29=ProposalToGnatt[[#This Row],[Start Date]],Milestone_Marker,IF(AND(Q$29>ProposalToGnatt[[#This Row],[Start Date]],Q$29<ProposalToGnatt[[#This Row],[Start Date]]+ProposalToGnatt[[#This Row],[Days]]),$G$5,"")),"") | R39: =IFERROR(+IF(R$29=ProposalToGnatt[[#This Row],[Start Date]],Milestone_Marker,IF(AND(R$29>ProposalToGnatt[[#This Row],[Start Date]],R$29<ProposalToGnatt[[#This Row],[Start Date]]+ProposalToGnatt[[#This Row],[Days]]),$G$5,"")),"") | S39: =IFERROR(+IF(S$29=ProposalToGnatt[[#This Row],[Start Date]],Milestone_Marker,IF(AND(S$29>ProposalToGnatt[[#This Row],[Start Date]],S$29<ProposalToGnatt[[#This Row],[Start Date]]+ProposalToGnatt[[#This Row],[Days]]),$G$5,"")),"") | T39: =IFERROR(+IF(T$29=ProposalToGnatt[[#This Row],[Start Date]],Milestone_Marker,IF(AND(T$29>ProposalToGnatt[[#This Row],[Start Date]],T$29<ProposalToGnatt[[#This Row],[Start Date]]+ProposalToGnatt[[#This Row],[Days]]),$G$5,"")),"") | U39: =IFERROR(+IF(U$29=ProposalToGnatt[[#This Row],[Start Date]],Milestone_Marker,IF(AND(U$29>ProposalToGnatt[[#This Row],[Start Date]],U$29<ProposalToGnatt[[#This Row],[Start Date]]+ProposalToGnatt[[#This Row],[Days]]),$G$5,"")),"") | V39: =IFERROR(+IF(V$29=ProposalToGnatt[[#This Row],[Start Date]],Milestone_Marker,IF(AND(V$29>ProposalToGnatt[[#This Row],[Start Date]],V$29<ProposalToGnatt[[#This Row],[Start Date]]+ProposalToGnatt[[#This Row],[Days]]),$G$5,"")),"") | W39: =IFERROR(+IF(W$29=ProposalToGnatt[[#This Row],[Start Date]],Milestone_Marker,IF(AND(W$29>ProposalToGnatt[[#This Row],[Start Date]],W$29<ProposalToGnatt[[#This Row],[Start Date]]+ProposalToGnatt[[#This Row],[Days]]),$G$5,"")),"") | ... CU39: =IFERROR(+IF(CU$29=ProposalToGnatt[[#This Row],[Start Date]],Milestone_Marker,IF(AND(CU$29>ProposalToGnatt[[#This Row],[Start Date]],CU$29<ProposalToGnatt[[#This Row],[Start Date]]+ProposalToGnatt[[#This Row],[Days]]),$G$5,"")),"")
B40: 11 | E40: Contract | F40: 0 | G40: 0 | H40: 0 | P40: =IFERROR(+IF(P$29=ProposalToGnatt[[#This Row],[Start Date]],Milestone_Marker,IF(AND(P$29>ProposalToGnatt[[#This Row],[Start Date]],P$29<ProposalToGnatt[[#This Row],[Start Date]]+ProposalToGnatt[[#This Row],[Days]]),$G$5,"")),"") -> 1 | Q40: =IFERROR(+IF(Q$29=ProposalToGnatt[[#This Row],[Start Date]],Milestone_Marker,IF(AND(Q$29>ProposalToGnatt[[#This Row],[Start Date]],Q$29<ProposalToGnatt[[#This Row],[Start Date]]+ProposalToGnatt[[#This Row],[Days]]),$G$5,"")),"") | R40: =IFERROR(+IF(R$29=ProposalToGnatt[[#This Row],[Start Date]],Milestone_Marker,IF(AND(R$29>ProposalToGnatt[[#This Row],[Start Date]],R$29<ProposalToGnatt[[#This Row],[Start Date]]+ProposalToGnatt[[#This Row],[Days]]),$G$5,"")),"") | S40: =IFERROR(+IF(S$29=ProposalToGnatt[[#This Row],[Start Date]],Milestone_Marker,IF(AND(S$29>ProposalToGnatt[[#This Row],[Start Date]],S$29<ProposalToGnatt[[#This Row],[Start Date]]+ProposalToGnatt[[#This Row],[Days]]),$G$5,"")),"") | T40: =IFERROR(+IF(T$29=ProposalToGnatt[[#This Row],[Start Date]],Milestone_Marker,IF(AND(T$29>ProposalToGnatt[[#This Row],[Start Date]],T$29<ProposalToGnatt[[#This Row],[Start Date]]+ProposalToGnatt[[#This Row],[Days]]),$G$5,"")),"") | U40: =IFERROR(+IF(U$29=ProposalToGnatt[[#This Row],[Start Date]],Milestone_Marker,IF(AND(U$29>ProposalToGnatt[[#This Row],[Start Date]],U$29<ProposalToGnatt[[#This Row],[Start Date]]+ProposalToGnatt[[#This Row],[Days]]),$G$5,"")),"") | V40: =IFERROR(+IF(V$29=ProposalToGnatt[[#This Row],[Start Date]],Milestone_Marker,IF(AND(V$29>ProposalToGnatt[[#This Row],[Start Date]],V$29<ProposalToGnatt[[#This Row],[Start Date]]+ProposalToGnatt[[#This Row],[Days]]),$G$5,"")),"") | W40: =IFERROR(+IF(W$29=ProposalToGnatt[[#This Row],[Start Date]],Milestone_Marker,IF(AND(W$29>ProposalToGnatt[[#This Row],[Start Date]],W$29<ProposalToGnatt[[#This Row],[Start Date]]+ProposalToGnatt[[#This Row],[Days]]),$G$5,"")),"") | ... CU40: =IFERROR(+IF(CU$29=ProposalToGnatt[[#This Row],[Start Date]],Milestone_Marker,IF(AND(CU$29>ProposalToGnatt[[#This Row],[Start Date]],CU$29<ProposalToGnatt[[#This Row],[Start Date]]+ProposalToGnatt[[#This Row],[Days]]),$G$5,"")),"")
A41: Glasgow | B41: 12 | C41: Deck labor | P41: =IFERROR(+IF(P$29=ProposalToGnatt[[#This Row],[Start Date]],Milestone_Marker,IF(AND(P$29>ProposalToGnatt[[#This Row],[Start Date]],P$29<ProposalToGnatt[[#This Row],[Start Date]]+ProposalToGnatt[[#This Row],[Days]]),$G$5,"")),"") -> 1 | Q41: =IFERROR(+IF(Q$29=ProposalToGnatt[[#This Row],[Start Date]],Milestone_Marker,IF(AND(Q$29>ProposalToGnatt[[#This Row],[Start Date]],Q$29<ProposalToGnatt[[#This Row],[Start Date]]+ProposalToGnatt[[#This Row],[Days]]),$G$5,"")),"") | R41: =IFERROR(+IF(R$29=ProposalToGnatt[[#This Row],[Start Date]],Milestone_Marker,IF(AND(R$29>ProposalToGnatt[[#This Row],[Start Date]],R$29<ProposalToGnatt[[#This Row],[Start Date]]+ProposalToGnatt[[#This Row],[Days]]),$G$5,"")),"") | S41: =IFERROR(+IF(S$29=ProposalToGnatt[[#This Row],[Start Date]],Milestone_Marker,IF(AND(S$29>ProposalToGnatt[[#This Row],[Start Date]],S$29<ProposalToGnatt[[#This Row],[Start Date]]+ProposalToGnatt[[#This Row],[Days]]),$G$5,"")),"") | T41: =IFERROR(+IF(T$29=ProposalToGnatt[[#This Row],[Start Date]],Milestone_Marker,IF(AND(T$29>ProposalToGnatt[[#This Row],[Start Date]],T$29<ProposalToGnatt[[#This Row],[Start Date]]+ProposalToGnatt[[#This Row],[Days]]),$G$5,"")),"") | U41: =IFERROR(+IF(U$29=ProposalToGnatt[[#This Row],[Start Date]],Milestone_Marker,IF(AND(U$29>ProposalToGnatt[[#This Row],[Start Date]],U$29<ProposalToGnatt[[#This Row],[Start Date]]+ProposalToGnatt[[#This Row],[Days]]),$G$5,"")),"") | V41: =IFERROR(+IF(V$29=ProposalToGnatt[[#This Row],[Start Date]],Milestone_Marker,IF(AND(V$29>ProposalToGnatt[[#This Row],[Start Date]],V$29<ProposalToGnatt[[#This Row],[Start Date]]+ProposalToGnatt[[#This Row],[Days]]),$G$5,"")),"") | W41: =IFERROR(+IF(W$29=ProposalToGnatt[[#This Row],[Start Date]],Milestone_Marker,IF(AND(W$29>ProposalToGnatt[[#This Row],[Start Date]],W$29<ProposalToGnatt[[#This Row],[Start Date]]+ProposalToGnatt[[#This Row],[Days]]),$G$5,"")),"") | ... CU41: =IFERROR(+IF(CU$29=ProposalToGnatt[[#This Row],[Start Date]],Milestone_Marker,IF(AND(CU$29>ProposalToGnatt[[#This Row],[Start Date]],CU$29<ProposalToGnatt[[#This Row],[Start Date]]+ProposalToGnatt[[#This Row],[Days]]),$G$5,"")),"")
A42: Glasgow | B42: 13 | C42: Deck labor | P42: =IFERROR(+IF(P$29=ProposalToGnatt[[#This Row],[Start Date]],Milestone_Marker,IF(AND(P$29>ProposalToGnatt[[#This Row],[Start Date]],P$29<ProposalToGnatt[[#This Row],[Start Date]]+ProposalToGnatt[[#This Row],[Days]]),$G$5,"")),"") -> 1 | Q42: =IFERROR(+IF(Q$29=ProposalToGnatt[[#This Row],[Start Date]],Milestone_Marker,IF(AND(Q$29>ProposalToGnatt[[#This Row],[Start Date]],Q$29<ProposalToGnatt[[#This Row],[Start Date]]+ProposalToGnatt[[#This Row],[Days]]),$G$5,"")),"") | R42: =IFERROR(+IF(R$29=ProposalToGnatt[[#This Row],[Start Date]],Milestone_Marker,IF(AND(R$29>ProposalToGnatt[[#This Row],[Start Date]],R$29<ProposalToGnatt[[#This Row],[Start Date]]+ProposalToGnatt[[#This Row],[Days]]),$G$5,"")),"") | S42: =IFERROR(+IF(S$29=ProposalToGnatt[[#This Row],[Start Date]],Milestone_Marker,IF(AND(S$29>ProposalToGnatt[[#This Row],[Start Date]],S$29<ProposalToGnatt[[#This Row],[Start Date]]+ProposalToGnatt[[#This Row],[Days]]),$G$5,"")),"") | T42: =IFERROR(+IF(T$29=ProposalToGnatt[[#This Row],[Start Date]],Milestone_Marker,IF(AND(T$29>ProposalToGnatt[[#This Row],[Start Date]],T$29<ProposalToGnatt[[#This Row],[Start Date]]+ProposalToGnatt[[#This Row],[Days]]),$G$5,"")),"") | U42: =IFERROR(+IF(U$29=ProposalToGnatt[[#This Row],[Start Date]],Milestone_Marker,IF(AND(U$29>ProposalToGnatt[[#This Row],[Start Date]],U$29<ProposalToGnatt[[#This Row],[Start Date]]+ProposalToGnatt[[#This Row],[Days]]),$G$5,"")),"") | V42: =IFERROR(+IF(V$29=ProposalToGnatt[[#This Row],[Start Date]],Milestone_Marker,IF(AND(V$29>ProposalToGnatt[[#This Row],[Start Date]],V$29<ProposalToGnatt[[#This Row],[Start Date]]+ProposalToGnatt[[#This Row],[Days]]),$G$5,"")),"") | W42: =IFERROR(+IF(W$29=ProposalToGnatt[[#This Row],[Start Date]],Milestone_Marker,IF(AND(W$29>ProposalToGnatt[[#This Row],[Start Date]],W$29<ProposalToGnatt[[#This Row],[Start Date]]+ProposalToGnatt[[#This Row],[Days]]),$G$5,"")),"") | ... CU42: =IFERROR(+IF(CU$29=ProposalToGnatt[[#This Row],[Start Date]],Milestone_Marker,IF(AND(CU$29>ProposalToGnatt[[#This Row],[Start Date]],CU$29<ProposalToGnatt[[#This Row],[Start Date]]+ProposalToGnatt[[#This Row],[Days]]),$G$5,"")),"")
A43: Glasgow | B43: 14 | C43: Deck material | P43: =IFERROR(+IF(P$29=ProposalToGnatt[[#This Row],[Start Date]],Milestone_Marker,IF(AND(P$29>ProposalToGnatt[[#This Row],[Start Date]],P$29<ProposalToGnatt[[#This Row],[Start Date]]+ProposalToGnatt[[#This Row],[Days]]),$G$5,"")),"") -> 1 | Q43: =IFERROR(+IF(Q$29=ProposalToGnatt[[#This Row],[Start Date]],Milestone_Marker,IF(AND(Q$29>ProposalToGnatt[[#This Row],[Start Date]],Q$29<ProposalToGnatt[[#This Row],[Start Date]]+ProposalToGnatt[[#This Row],[Days]]),$G$5,"")),"") | R43: =IFERROR(+IF(R$29=ProposalToGnatt[[#This Row],[Start Date]],Milestone_Marker,IF(AND(R$29>ProposalToGnatt[[#This Row],[Start Date]],R$29<ProposalToGnatt[[#This Row],[Start Date]]+ProposalToGnatt[[#This Row],[Days]]),$G$5,"")),"") | S43: =IFERROR(+IF(S$29=ProposalToGnatt[[#This Row],[Start Date]],Milestone_Marker,IF(AND(S$29>ProposalToGnatt[[#This Row],[Start Date]],S$29<ProposalToGnatt[[#This Row],[Start Date]]+ProposalToGnatt[[#This Row],[Days]]),$G$5,"")),"") | T43: =IFERROR(+IF(T$29=ProposalToGnatt[[#This Row],[Start Date]],Milestone_Marker,IF(AND(T$29>ProposalToGnatt[[#This Row],[Start Date]],T$29<ProposalToGnatt[[#This Row],[Start Date]]+ProposalToGnatt[[#This Row],[Days]]),$G$5,"")),"") | U43: =IFERROR(+IF(U$29=ProposalToGnatt[[#This Row],[Start Date]],Milestone_Marker,IF(AND(U$29>ProposalToGnatt[[#This Row],[Start Date]],U$29<ProposalToGnatt[[#This Row],[Start Date]]+ProposalToGnatt[[#This Row],[Days]]),$G$5,"")),"") | V43: =IFERROR(+IF(V$29=ProposalToGnatt[[#This Row],[Start Date]],Milestone_Marker,IF(AND(V$29>ProposalToGnatt[[#This Row],[Start Date]],V$29<ProposalToGnatt[[#This Row],[Start Date]]+ProposalToGnatt[[#This Row],[Days]]),$G$5,"")),"") | W43: =IFERROR(+IF(W$29=ProposalToGnatt[[#This Row],[Start Date]],Milestone_Marker,IF(AND(W$29>ProposalToGnatt[[#This Row],[Start Date]],W$29<ProposalToGnatt[[#This Row],[Start Date]]+ProposalToGnatt[[#This Row],[Days]]),$G$5,"")),"") | ... CU43: =IFERROR(+IF(CU$29=ProposalToGnatt[[#This Row],[Start Date]],Milestone_Marker,IF(AND(CU$29>ProposalToGnatt[[#This Row],[Start Date]],CU$29<ProposalToGnatt[[#This Row],[Start Date]]+ProposalToGnatt[[#This Row],[Days]]),$G$5,"")),"")
A44: Glasgow | B44: 15 | C44: ... Demo | P44: =IFERROR(+IF(P$29=ProposalToGnatt[[#This Row],[Start Date]],Milestone_Marker,IF(AND(P$29>ProposalToGnatt[[#This Row],[Start Date]],P$29<ProposalToGnatt[[#This Row],[Start Date]]+ProposalToGnatt[[#This Row],[Days]]),$G$5,"")),"") -> 1 | Q44: =IFERROR(+IF(Q$29=ProposalToGnatt[[#This Row],[Start Date]],Milestone_Marker,IF(AND(Q$29>ProposalToGnatt[[#This Row],[Start Date]],Q$29<ProposalToGnatt[[#This Row],[Start Date]]+ProposalToGnatt[[#This Row],[Days]]),$G$5,"")),"") | R44: =IFERROR(+IF(R$29=ProposalToGnatt[[#This Row],[Start Date]],Milestone_Marker,IF(AND(R$29>ProposalToGnatt[[#This Row],[Start Date]],R$29<ProposalToGnatt[[#This Row],[Start Date]]+ProposalToGnatt[[#This Row],[Days]]),$G$5,"")),"") | S44: =IFERROR(+IF(S$29=ProposalToGnatt[[#This Row],[Start Date]],Milestone_Marker,IF(AND(S$29>ProposalToGnatt[[#This Row],[Start Date]],S$29<ProposalToGnatt[[#This Row],[Start Date]]+ProposalToGnatt[[#This Row],[Days]]),$G$5,"")),"") | T44: =IFERROR(+IF(T$29=ProposalToGnatt[[#This Row],[Start Date]],Milestone_Marker,IF(AND(T$29>ProposalToGnatt[[#This Row],[Start Date]],T$29<ProposalToGnatt[[#This Row],[Start Date]]+ProposalToGnatt[[#This Row],[Days]]),$G$5,"")),"") | U44: =IFERROR(+IF(U$29=ProposalToGnatt[[#This Row],[Start Date]],Milestone_Marker,IF(AND(U$29>ProposalToGnatt[[#This Row],[Start Date]],U$29<ProposalToGnatt[[#This Row],[Start Date]]+ProposalToGnatt[[#This Row],[Days]]),$G$5,"")),"") | V44: =IFERROR(+IF(V$29=ProposalToGnatt[[#This Row],[Start Date]],Milestone_Marker,IF(AND(V$29>ProposalToGnatt[[#This Row],[Start Date]],V$29<ProposalToGnatt[[#This Row],[Start Date]]+ProposalToGnatt[[#This Row],[Days]]),$G$5,"")),"") | W44: =IFERROR(+IF(W$29=ProposalToGnatt[[#This Row],[Start Date]],Milestone_Marker,IF(AND(W$29>ProposalToGnatt[[#This Row],[Start Date]],W$29<ProposalToGnatt[[#This Row],[Start Date]]+ProposalToGnatt[[#This Row],[Days]]),$G$5,"")),"") | ... CU44: =IFERROR(+IF(CU$29=ProposalToGnatt[[#This Row],[Start Date]],Milestone_Marker,IF(AND(CU$29>ProposalToGnatt[[#This Row],[Start Date]],CU$29<ProposalToGnatt[[#This Row],[Start Date]]+ProposalToGnatt[[#This Row],[Days]]),$G$5,"")),"")
A45: Glasgow | B45: 16 | C45: ... Demo | P45: =IFERROR(+IF(P$29=ProposalToGnatt[[#This Row],[Start Date]],Milestone_Marker,IF(AND(P$29>ProposalToGnatt[[#This Row],[Start Date]],P$29<ProposalToGnatt[[#This Row],[Start Date]]+ProposalToGnatt[[#This Row],[Days]]),$G$5,"")),"") -> 1 | Q45: =IFERROR(+IF(Q$29=ProposalToGnatt[[#This Row],[Start Date]],Milestone_Marker,IF(AND(Q$29>ProposalToGnatt[[#This Row],[Start Date]],Q$29<ProposalToGnatt[[#This Row],[Start Date]]+ProposalToGnatt[[#This Row],[Days]]),$G$5,"")),"") | R45: =IFERROR(+IF(R$29=ProposalToGnatt[[#This Row],[Start Date]],Milestone_Marker,IF(AND(R$29>ProposalToGnatt[[#This Row],[Start Date]],R$29<ProposalToGnatt[[#This Row],[Start Date]]+ProposalToGnatt[[#This Row],[Days]]),$G$5,"")),"") | S45: =IFERROR(+IF(S$29=ProposalToGnatt[[#This Row],[Start Date]],Milestone_Marker,IF(AND(S$29>ProposalToGnatt[[#This Row],[Start Date]],S$29<ProposalToGnatt[[#This Row],[Start Date]]+ProposalToGnatt[[#This Row],[Days]]),$G$5,"")),"") | T45: =IFERROR(+IF(T$29=ProposalToGnatt[[#This Row],[Start Date]],Milestone_Marker,IF(AND(T$29>ProposalToGnatt[[#This Row],[Start Date]],T$29<ProposalToGnatt[[#This Row],[Start Date]]+ProposalToGnatt[[#This Row],[Days]]),$G$5,"")),"") | U45: =IFERROR(+IF(U$29=ProposalToGnatt[[#This Row],[Start Date]],Milestone_Marker,IF(AND(U$29>ProposalToGnatt[[#This Row],[Start Date]],U$29<ProposalToGnatt[[#This Row],[Start Date]]+ProposalToGnatt[[#This Row],[Days]]),$G$5,"")),"") | V45: =IFERROR(+IF(V$29=ProposalToGnatt[[#This Row],[Start Date]],Milestone_Marker,IF(AND(V$29>ProposalToGnatt[[#This Row],[Start Date]],V$29<ProposalToGnatt[[#This Row],[Start Date]]+ProposalToGnatt[[#This Row],[Days]]),$G$5,"")),"") | W45: =IFERROR(+IF(W$29=ProposalToGnatt[[#This Row],[Start Date]],Milestone_Marker,IF(AND(W$29>ProposalToGnatt[[#This Row],[Start Date]],W$29<ProposalToGnatt[[#This Row],[Start Date]]+ProposalToGnatt[[#This Row],[Days]]),$G$5,"")),"") | ... CU45: =IFERROR(+IF(CU$29=ProposalToGnatt[[#This Row],[Start Date]],Milestone_Marker,IF(AND(CU$29>ProposalToGnatt[[#This Row],[Start Date]],CU$29<ProposalToGnatt[[#This Row],[Start Date]]+ProposalToGnatt[[#This Row],[Days]]),$G$5,"")),"")
P46: =IFERROR(+IF(P$29=ProposalToGnatt[[#This Row],[Start Date]],Milestone_Marker,IF(AND(P$29>ProposalToGnatt[[#This Row],[Start Date]],P$29<ProposalToGnatt[[#This Row],[Start Date]]+ProposalToGnatt[[#This Row],[Days]]),$G$5,"")),"") | Q46: =IFERROR(+IF(Q$29=ProposalToGnatt[[#This Row],[Start Date]],Milestone_Marker,IF(AND(Q$29>ProposalToGnatt[[#This Row],[Start Date]],Q$29<ProposalToGnatt[[#This Row],[Start Date]]+ProposalToGnatt[[#This Row],[Days]]),$G$5,"")),"") | R46: =IFERROR(+IF(R$29=ProposalToGnatt[[#This Row],[Start Date]],Milestone_Marker,IF(AND(R$29>ProposalToGnatt[[#This Row],[Start Date]],R$29<ProposalToGnatt[[#This Row],[Start Date]]+ProposalToGnatt[[#This Row],[Days]]),$G$5,"")),"") | S46: =IFERROR(+IF(S$29=ProposalToGnatt[[#This Row],[Start Date]],Milestone_Marker,IF(AND(S$29>ProposalToGnatt[[#This Row],[Start Date]],S$29<ProposalToGnatt[[#This Row],[Start Date]]+ProposalToGnatt[[#This Row],[Days]]),$G$5,"")),"") | T46: =IFERROR(+IF(T$29=ProposalToGnatt[[#This Row],[Start Date]],Milestone_Marker,IF(AND(T$29>ProposalToGnatt[[#This Row],[Start Date]],T$29<ProposalToGnatt[[#This Row],[Start Date]]+ProposalToGnatt[[#This Row],[Days]]),$G$5,"")),"") | U46: =IFERROR(+IF(U$29=ProposalToGnatt[[#This Row],[Start Date]],Milestone_Marker,IF(AND(U$29>ProposalToGnatt[[#This Row],[Start Date]],U$29<ProposalToGnatt[[#This Row],[Start Date]]+ProposalToGnatt[[#This Row],[Days]]),$G$5,"")),"") | V46: =IFERROR(+IF(V$29=ProposalToGnatt[[#This Row],[Start Date]],Milestone_Marker,IF(AND(V$29>ProposalToGnatt[[#This Row],[Start Date]],V$29<ProposalToGnatt[[#This Row],[Start Date]]+ProposalToGnatt[[#This Row],[Days]]),$G$5,"")),"") | W46: =IFERROR(+IF(W$29=ProposalToGnatt[[#This Row],[Start Date]],Milestone_Marker,IF(AND(W$29>ProposalToGnatt[[#This Row],[Start Date]],W$29<ProposalToGnatt[[#This Row],[Start Date]]+ProposalToGnatt[[#This Row],[Days]]),$G$5,"")),"") | ... CU46: =IFERROR(+IF(CU$29=ProposalToGnatt[[#This Row],[Start Date]],Milestone_Marker,IF(AND(CU$29>ProposalToGnatt[[#This Row],[Start Date]],CU$29<ProposalToGnatt[[#This Row],[Start Date]]+ProposalToGnatt[[#This Row],[Days]]),$G$5,"")),"")
P47: =IFERROR(+IF(P$29=ProposalToGnatt[[#This Row],[Start Date]],Milestone_Marker,IF(AND(P$29>ProposalToGnatt[[#This Row],[Start Date]],P$29<ProposalToGnatt[[#This Row],[Start Date]]+ProposalToGnatt[[#This Row],[Days]]),$G$5,"")),"") | Q47: =IFERROR(+IF(Q$29=ProposalToGnatt[[#This Row],[Start Date]],Milestone_Marker,IF(AND(Q$29>ProposalToGnatt[[#This Row],[Start Date]],Q$29<ProposalToGnatt[[#This Row],[Start Date]]+ProposalToGnatt[[#This Row],[Days]]),$G$5,"")),"") | R47: =IFERROR(+IF(R$29=ProposalToGnatt[[#This Row],[Start Date]],Milestone_Marker,IF(AND(R$29>ProposalToGnatt[[#This Row],[Start Date]],R$29<ProposalToGnatt[[#This Row],[Start Date]]+ProposalToGnatt[[#This Row],[Days]]),$G$5,"")),"") | S47: =IFERROR(+IF(S$29=ProposalToGnatt[[#This Row],[Start Date]],Milestone_Marker,IF(AND(S$29>ProposalToGnatt[[#This Row],[Start Date]],S$29<ProposalToGnatt[[#This Row],[Start Date]]+ProposalToGnatt[[#This Row],[Days]]),$G$5,"")),"") | T47: =IFERROR(+IF(T$29=ProposalToGnatt[[#This Row],[Start Date]],Milestone_Marker,IF(AND(T$29>ProposalToGnatt[[#This Row],[Start Date]],T$29<ProposalToGnatt[[#This Row],[Start Date]]+ProposalToGnatt[[#This Row],[Days]]),$G$5,"")),"") | U47: =IFERROR(+IF(U$29=ProposalToGnatt[[#This Row],[Start Date]],Milestone_Marker,IF(AND(U$29>ProposalToGnatt[[#This Row],[Start Date]],U$29<ProposalToGnatt[[#This Row],[Start Date]]+ProposalToGnatt[[#This Row],[Days]]),$G$5,"")),"") | V47: =IFERROR(+IF(V$29=ProposalToGnatt[[#This Row],[Start Date]],Milestone_Marker,IF(AND(V$29>ProposalToGnatt[[#This Row],[Start Date]],V$29<ProposalToGnatt[[#This Row],[Start Date]]+ProposalToGnatt[[#This Row],[Days]]),$G$5,"")),"") | W47: =IFERROR(+IF(W$29=ProposalToGnatt[[#This Row],[Start Date]],Milestone_Marker,IF(AND(W$29>ProposalToGnatt[[#This Row],[Start Date]],W$29<ProposalToGnatt[[#This Row],[Start Date]]+ProposalToGnatt[[#This Row],[Days]]),$G$5,"")),"") | ... CU47: =IFERROR(+IF(CU$29=ProposalToGnatt[[#This Row],[Start Date]],Milestone_Marker,IF(AND(CU$29>ProposalToGnatt[[#This Row],[Start Date]],CU$29<ProposalToGnatt[[#This Row],[Start Date]]+ProposalToGnatt[[#This Row],[Days]]),$G$5,"")),"")
P48: =IFERROR(+IF(P$29=ProposalToGnatt[[#This Row],[Start Date]],Milestone_Marker,IF(AND(P$29>ProposalToGnatt[[#This Row],[Start Date]],P$29<ProposalToGnatt[[#This Row],[Start Date]]+ProposalToGnatt[[#This Row],[Days]]),$G$5,"")),"") | Q48: =IFERROR(+IF(Q$29=ProposalToGnatt[[#This Row],[Start Date]],Milestone_Marker,IF(AND(Q$29>ProposalToGnatt[[#This Row],[Start Date]],Q$29<ProposalToGnatt[[#This Row],[Start Date]]+ProposalToGnatt[[#This Row],[Days]]),$G$5,"")),"") | R48: =IFERROR(+IF(R$29=ProposalToGnatt[[#This Row],[Start Date]],Milestone_Marker,IF(AND(R$29>ProposalToGnatt[[#This Row],[Start Date]],R$29<ProposalToGnatt[[#This Row],[Start Date]]+ProposalToGnatt[[#This Row],[Days]]),$G$5,"")),"") | S48: =IFERROR(+IF(S$29=ProposalToGnatt[[#This Row],[Start Date]],Milestone_Marker,IF(AND(S$29>ProposalToGnatt[[#This Row],[Start Date]],S$29<ProposalToGnatt[[#This Row],[Start Date]]+ProposalToGnatt[[#This Row],[Days]]),$G$5,"")),"") | T48: =IFERROR(+IF(T$29=ProposalToGnatt[[#This Row],[Start Date]],Milestone_Marker,IF(AND(T$29>ProposalToGnatt[[#This Row],[Start Date]],T$29<ProposalToGnatt[[#This Row],[Start Date]]+ProposalToGnatt[[#This Row],[Days]]),$G$5,"")),"") | U48: =IFERROR(+IF(U$29=ProposalToGnatt[[#This Row],[Start Date]],Milestone_Marker,IF(AND(U$29>ProposalToGnatt[[#This Row],[Start Date]],U$29<ProposalToGnatt[[#This Row],[Start Date]]+ProposalToGnatt[[#This Row],[Days]]),$G$5,"")),"") | V48: =IFERROR(+IF(V$29=ProposalToGnatt[[#This Row],[Start Date]],Milestone_Marker,IF(AND(V$29>ProposalToGnatt[[#This Row],[Start Date]],V$29<ProposalToGnatt[[#This Row],[Start Date]]+ProposalToGnatt[[#This Row],[Days]]),$G$5,"")),"") | W48: =IFERROR(+IF(W$29=ProposalToGnatt[[#This Row],[Start Date]],Milestone_Marker,IF(AND(W$29>ProposalToGnatt[[#This Row],[Start Date]],W$29<ProposalToGnatt[[#This Row],[Start Date]]+ProposalToGnatt[[#This Row],[Days]]),$G$5,"")),"") | ... CU48: =IFERROR(+IF(CU$29=ProposalToGnatt[[#This Row],[Start Date]],Milestone_Marker,IF(AND(CU$29>ProposalToGnatt[[#This Row],[Start Date]],CU$29<ProposalToGnatt[[#This Row],[Start Date]]+ProposalToGnatt[[#This Row],[Days]]),$G$5,"")),"")
P49: =IFERROR(+IF(P$29=ProposalToGnatt[[#This Row],[Start Date]],Milestone_Marker,IF(AND(P$29>ProposalToGnatt[[#This Row],[Start Date]],P$29<ProposalToGnatt[[#This Row],[Start Date]]+ProposalToGnatt[[#This Row],[Days]]),$G$5,"")),"") | Q49: =IFERROR(+IF(Q$29=ProposalToGnatt[[#This Row],[Start Date]],Milestone_Marker,IF(AND(Q$29>ProposalToGnatt[[#This Row],[Start Date]],Q$29<ProposalToGnatt[[#This Row],[Start Date]]+ProposalToGnatt[[#This Row],[Days]]),$G$5,"")),"") | R49: =IFERROR(+IF(R$29=ProposalToGnatt[[#This Row],[Start Date]],Milestone_Marker,IF(AND(R$29>ProposalToGnatt[[#This Row],[Start Date]],R$29<ProposalToGnatt[[#This Row],[Start Date]]+ProposalToGnatt[[#This Row],[Days]]),$G$5,"")),"") | S49: =IFERROR(+IF(S$29=ProposalToGnatt[[#This Row],[Start Date]],Milestone_Marker,IF(AND(S$29>ProposalToGnatt[[#This Row],[Start Date]],S$29<ProposalToGnatt[[#This Row],[Start Date]]+ProposalToGnatt[[#This Row],[Days]]),$G$5,"")),"") | T49: =IFERROR(+IF(T$29=ProposalToGnatt[[#This Row],[Start Date]],Milestone_Marker,IF(AND(T$29>ProposalToGnatt[[#This Row],[Start Date]],T$29<ProposalToGnatt[[#This Row],[Start Date]]+ProposalToGnatt[[#This Row],[Days]]),$G$5,"")),"") | U49: =IFERROR(+IF(U$29=ProposalToGnatt[[#This Row],[Start Date]],Milestone_Marker,IF(AND(U$29>ProposalToGnatt[[#This Row],[Start Date]],U$29<ProposalToGnatt[[#This Row],[Start Date]]+ProposalToGnatt[[#This Row],[Days]]),$G$5,"")),"") | V49: =IFERROR(+IF(V$29=ProposalToGnatt[[#This Row],[Start Date]],Milestone_Marker,IF(AND(V$29>ProposalToGnatt[[#This Row],[Start Date]],V$29<ProposalToGnatt[[#This Row],[Start Date]]+ProposalToGnatt[[#This Row],[Days]]),$G$5,"")),"") | W49: =IFERROR(+IF(W$29=ProposalToGnatt[[#This Row],[Start Date]],Milestone_Marker,IF(AND(W$29>ProposalToGnatt[[#This Row],[Start Date]],W$29<ProposalToGnatt[[#This Row],[Start Date]]+ProposalToGnatt[[#This Row],[Days]]),$G$5,"")),"") | ... CU49: =IFERROR(+IF(CU$29=ProposalToGnatt[[#This Row],[Start Date]],Milestone_Marker,IF(AND(CU$29>ProposalToGnatt[[#This Row],[Start Date]],CU$29<ProposalToGnatt[[#This Row],[Start Date]]+ProposalToGnatt[[#This Row],[Days]]),$G$5,"")),"")
P50: =IFERROR(+IF(P$29=ProposalToGnatt[[#This Row],[Start Date]],Milestone_Marker,IF(AND(P$29>ProposalToGnatt[[#This Row],[Start Date]],P$29<ProposalToGnatt[[#This Row],[Start Date]]+ProposalToGnatt[[#This Row],[Days]]),$G$5,"")),"") | Q50: =IFERROR(+IF(Q$29=ProposalToGnatt[[#This Row],[Start Date]],Milestone_Marker,IF(AND(Q$29>ProposalToGnatt[[#This Row],[Start Date]],Q$29<ProposalToGnatt[[#This Row],[Start Date]]+ProposalToGnatt[[#This Row],[Days]]),$G$5,"")),"") | R50: =IFERROR(+IF(R$29=ProposalToGnatt[[#This Row],[Start Date]],Milestone_Marker,IF(AND(R$29>ProposalToGnatt[[#This Row],[Start Date]],R$29<ProposalToGnatt[[#This Row],[Start Date]]+ProposalToGnatt[[#This Row],[Days]]),$G$5,"")),"") | S50: =IFERROR(+IF(S$29=ProposalToGnatt[[#This Row],[Start Date]],Milestone_Marker,IF(AND(S$29>ProposalToGnatt[[#This Row],[Start Date]],S$29<ProposalToGnatt[[#This Row],[Start Date]]+ProposalToGnatt[[#This Row],[Days]]),$G$5,"")),"") | T50: =IFERROR(+IF(T$29=ProposalToGnatt[[#This Row],[Start Date]],Milestone_Marker,IF(AND(T$29>ProposalToGnatt[[#This Row],[Start Date]],T$29<ProposalToGnatt[[#This Row],[Start Date]]+ProposalToGnatt[[#This Row],[Days]]),$G$5,"")),"") | U50: =IFERROR(+IF(U$29=ProposalToGnatt[[#This Row],[Start Date]],Milestone_Marker,IF(AND(U$29>ProposalToGnatt[[#This Row],[Start Date]],U$29<ProposalToGnatt[[#This Row],[Start Date]]+ProposalToGnatt[[#This Row],[Days]]),$G$5,"")),"") | V50: =IFERROR(+IF(V$29=ProposalToGnatt[[#This Row],[Start Date]],Milestone_Marker,IF(AND(V$29>ProposalToGnatt[[#This Row],[Start Date]],V$29<ProposalToGnatt[[#This Row],[Start Date]]+ProposalToGnatt[[#This Row],[Days]]),$G$5,"")),"") | W50: =IFERROR(+IF(W$29=ProposalToGnatt[[#This Row],[Start Date]],Milestone_Marker,IF(AND(W$29>ProposalToGnatt[[#This Row],[Start Date]],W$29<ProposalToGnatt[[#This Row],[Start Date]]+ProposalToGnatt[[#This Row],[Days]]),$G$5,"")),"") | ... CU50: =IFERROR(+IF(CU$29=ProposalToGnatt[[#This Row],[Start Date]],Milestone_Marker,IF(AND(CU$29>ProposalToGnatt[[#This Row],[Start Date]],CU$29<ProposalToGnatt[[#This Row],[Start Date]]+ProposalToGnatt[[#This Row],[Days]]),$G$5,"")),"")
P51: =IFERROR(+IF(P$29=ProposalToGnatt[[#This Row],[Start Date]],Milestone_Marker,IF(AND(P$29>ProposalToGnatt[[#This Row],[Start Date]],P$29<ProposalToGnatt[[#This Row],[Start Date]]+ProposalToGnatt[[#This Row],[Days]]),$G$5,"")),"") | Q51: =IFERROR(+IF(Q$29=ProposalToGnatt[[#This Row],[Start Date]],Milestone_Marker,IF(AND(Q$29>ProposalToGnatt[[#This Row],[Start Date]],Q$29<ProposalToGnatt[[#This Row],[Start Date]]+ProposalToGnatt[[#This Row],[Days]]),$G$5,"")),"") | R51: =IFERROR(+IF(R$29=ProposalToGnatt[[#This Row],[Start Date]],Milestone_Marker,IF(AND(R$29>ProposalToGnatt[[#This Row],[Start Date]],R$29<ProposalToGnatt[[#This Row],[Start Date]]+ProposalToGnatt[[#This Row],[Days]]),$G$5,"")),"") | S51: =IFERROR(+IF(S$29=ProposalToGnatt[[#This Row],[Start Date]],Milestone_Marker,IF(AND(S$29>ProposalToGnatt[[#This Row],[Start Date]],S$29<ProposalToGnatt[[#This Row],[Start Date]]+ProposalToGnatt[[#This Row],[Days]]),$G$5,"")),"") | T51: =IFERROR(+IF(T$29=ProposalToGnatt[[#This Row],[Start Date]],Milestone_Marker,IF(AND(T$29>ProposalToGnatt[[#This Row],[Start Date]],T$29<ProposalToGnatt[[#This Row],[Start Date]]+ProposalToGnatt[[#This Row],[Days]]),$G$5,"")),"") | U51: =IFERROR(+IF(U$29=ProposalToGnatt[[#This Row],[Start Date]],Milestone_Marker,IF(AND(U$29>ProposalToGnatt[[#This Row],[Start Date]],U$29<ProposalToGnatt[[#This Row],[Start Date]]+ProposalToGnatt[[#This Row],[Days]]),$G$5,"")),"") | V51: =IFERROR(+IF(V$29=ProposalToGnatt[[#This Row],[Start Date]],Milestone_Marker,IF(AND(V$29>ProposalToGnatt[[#This Row],[Start Date]],V$29<ProposalToGnatt[[#This Row],[Start Date]]+ProposalToGnatt[[#This Row],[Days]]),$G$5,"")),"") | W51: =IFERROR(+IF(W$29=ProposalToGnatt[[#This Row],[Start Date]],Milestone_Marker,IF(AND(W$29>ProposalToGnatt[[#This Row],[Start Date]],W$29<ProposalToGnatt[[#This Row],[Start Date]]+ProposalToGnatt[[#This Row],[Days]]),$G$5,"")),"") | ... CU51: =IFERROR(+IF(CU$29=ProposalToGnatt[[#This Row],[Start Date]],Milestone_Marker,IF(AND(CU$29>ProposalToGnatt[[#This Row],[Start Date]],CU$29<ProposalToGnatt[[#This Row],[Start Date]]+ProposalToGnatt[[#This Row],[Days]]),$G$5,"")),"")
P52: =IFERROR(+IF(P$29=ProposalToGnatt[[#This Row],[Start Date]],Milestone_Marker,IF(AND(P$29>ProposalToGnatt[[#This Row],[Start Date]],P$29<ProposalToGnatt[[#This Row],[Start Date]]+ProposalToGnatt[[#This Row],[Days]]),$G$5,"")),"") | Q52: =IFERROR(+IF(Q$29=ProposalToGnatt[[#This Row],[Start Date]],Milestone_Marker,IF(AND(Q$29>ProposalToGnatt[[#This Row],[Start Date]],Q$29<ProposalToGnatt[[#This Row],[Start Date]]+ProposalToGnatt[[#This Row],[Days]]),$G$5,"")),"") | R52: =IFERROR(+IF(R$29=ProposalToGnatt[[#This Row],[Start Date]],Milestone_Marker,IF(AND(R$29>ProposalToGnatt[[#This Row],[Start Date]],R$29<ProposalToGnatt[[#This Row],[Start Date]]+ProposalToGnatt[[#This Row],[Days]]),$G$5,"")),"") | S52: =IFERROR(+IF(S$29=ProposalToGnatt[[#This Row],[Start Date]],Milestone_Marker,IF(AND(S$29>ProposalToGnatt[[#This Row],[Start Date]],S$29<ProposalToGnatt[[#This Row],[Start Date]]+ProposalToGnatt[[#This Row],[Days]]),$G$5,"")),"") | T52: =IFERROR(+IF(T$29=ProposalToGnatt[[#This Row],[Start Date]],Milestone_Marker,IF(AND(T$29>ProposalToGnatt[[#This Row],[Start Date]],T$29<ProposalToGnatt[[#This Row],[Start Date]]+ProposalToGnatt[[#This Row],[Days]]),$G$5,"")),"") | U52: =IFERROR(+IF(U$29=ProposalToGnatt[[#This Row],[Start Date]],Milestone_Marker,IF(AND(U$29>ProposalToGnatt[[#This Row],[Start Date]],U$29<ProposalToGnatt[[#This Row],[Start Date]]+ProposalToGnatt[[#This Row],[Days]]),$G$5,"")),"") | V52: =IFERROR(+IF(V$29=ProposalToGnatt[[#This Row],[Start Date]],Milestone_Marker,IF(AND(V$29>ProposalToGnatt[[#This Row],[Start Date]],V$29<ProposalToGnatt[[#This Row],[Start Date]]+ProposalToGnatt[[#This Row],[Days]]),$G$5,"")),"") | W52: =IFERROR(+IF(W$29=ProposalToGnatt[[#This Row],[Start Date]],Milestone_Marker,IF(AND(W$29>ProposalToGnatt[[#This Row],[Start Date]],W$29<ProposalToGnatt[[#This Row],[Start Date]]+ProposalToGnatt[[#This Row],[Days]]),$G$5,"")),"") | ... CU52: =IFERROR(+IF(CU$29=ProposalToGnatt[[#This Row],[Start Date]],Milestone_Marker,IF(AND(CU$29>ProposalToGnatt[[#This Row],[Start Date]],CU$29<ProposalToGnatt[[#This Row],[Start Date]]+ProposalToGnatt[[#This Row],[Days]]),$G$5,"")),"")
P53: =IFERROR(+IF(P$29=ProposalToGnatt[[#This Row],[Start Date]],Milestone_Marker,IF(AND(P$29>ProposalToGnatt[[#This Row],[Start Date]],P$29<ProposalToGnatt[[#This Row],[Start Date]]+ProposalToGnatt[[#This Row],[Days]]),$G$5,"")),"") | Q53: =IFERROR(+IF(Q$29=ProposalToGnatt[[#This Row],[Start Date]],Milestone_Marker,IF(AND(Q$29>ProposalToGnatt[[#This Row],[Start Date]],Q$29<ProposalToGnatt[[#This Row],[Start Date]]+ProposalToGnatt[[#This Row],[Days]]),$G$5,"")),"") | R53: =IFERROR(+IF(R$29=ProposalToGnatt[[#This Row],[Start Date]],Milestone_Marker,IF(AND(R$29>ProposalToGnatt[[#This Row],[Start Date]],R$29<ProposalToGnatt[[#This Row],[Start Date]]+ProposalToGnatt[[#This Row],[Days]]),$G$5,"")),"") | S53: =IFERROR(+IF(S$29=ProposalToGnatt[[#This Row],[Start Date]],Milestone_Marker,IF(AND(S$29>ProposalToGnatt[[#This Row],[Start Date]],S$29<ProposalToGnatt[[#This Row],[Start Date]]+ProposalToGnatt[[#This Row],[Days]]),$G$5,"")),"") | T53: =IFERROR(+IF(T$29=ProposalToGnatt[[#This Row],[Start Date]],Milestone_Marker,IF(AND(T$29>ProposalToGnatt[[#This Row],[Start Date]],T$29<ProposalToGnatt[[#This Row],[Start Date]]+ProposalToGnatt[[#This Row],[Days]]),$G$5,"")),"") | U53: =IFERROR(+IF(U$29=ProposalToGnatt[[#This Row],[Start Date]],Milestone_Marker,IF(AND(U$29>ProposalToGnatt[[#This Row],[Start Date]],U$29<ProposalToGnatt[[#This Row],[Start Date]]+ProposalToGnatt[[#This Row],[Days]]),$G$5,"")),"") | V53: =IFERROR(+IF(V$29=ProposalToGnatt[[#This Row],[Start Date]],Milestone_Marker,IF(AND(V$29>ProposalToGnatt[[#This Row],[Start Date]],V$29<ProposalToGnatt[[#This Row],[Start Date]]+ProposalToGnatt[[#This Row],[Days]]),$G$5,"")),"") | W53: =IFERROR(+IF(W$29=ProposalToGnatt[[#This Row],[Start Date]],Milestone_Marker,IF(AND(W$29>ProposalToGnatt[[#This Row],[Start Date]],W$29<ProposalToGnatt[[#This Row],[Start Date]]+ProposalToGnatt[[#This Row],[Days]]),$G$5,"")),"") | ... CU53: =IFERROR(+IF(CU$29=ProposalToGnatt[[#This Row],[Start Date]],Milestone_Marker,IF(AND(CU$29>ProposalToGnatt[[#This Row],[Start Date]],CU$29<ProposalToGnatt[[#This Row],[Start Date]]+ProposalToGnatt[[#This Row],[Days]]),$G$5,"")),"")
P54: =IFERROR(+IF(P$29=ProposalToGnatt[[#This Row],[Start Date]],Milestone_Marker,IF(AND(P$29>ProposalToGnatt[[#This Row],[Start Date]],P$29<ProposalToGnatt[[#This Row],[Start Date]]+ProposalToGnatt[[#This Row],[Days]]),$G$5,"")),"") | Q54: =IFERROR(+IF(Q$29=ProposalToGnatt[[#This Row],[Start Date]],Milestone_Marker,IF(AND(Q$29>ProposalToGnatt[[#This Row],[Start Date]],Q$29<ProposalToGnatt[[#This Row],[Start Date]]+ProposalToGnatt[[#This Row],[Days]]),$G$5,"")),"") | R54: =IFERROR(+IF(R$29=ProposalToGnatt[[#This Row],[Start Date]],Milestone_Marker,IF(AND(R$29>ProposalToGnatt[[#This Row],[Start Date]],R$29<ProposalToGnatt[[#This Row],[Start Date]]+ProposalToGnatt[[#This Row],[Days]]),$G$5,"")),"") | S54: =IFERROR(+IF(S$29=ProposalToGnatt[[#This Row],[Start Date]],Milestone_Marker,IF(AND(S$29>ProposalToGnatt[[#This Row],[Start Date]],S$29<ProposalToGnatt[[#This Row],[Start Date]]+ProposalToGnatt[[#This Row],[Days]]),$G$5,"")),"") | T54: =IFERROR(+IF(T$29=ProposalToGnatt[[#This Row],[Start Date]],Milestone_Marker,IF(AND(T$29>ProposalToGnatt[[#This Row],[Start Date]],T$29<ProposalToGnatt[[#This Row],[Start Date]]+ProposalToGnatt[[#This Row],[Days]]),$G$5,"")),"") | U54: =IFERROR(+IF(U$29=ProposalToGnatt[[#This Row],[Start Date]],Milestone_Marker,IF(AND(U$29>ProposalToGnatt[[#This Row],[Start Date]],U$29<ProposalToGnatt[[#This Row],[Start Date]]+ProposalToGnatt[[#This Row],[Days]]),$G$5,"")),"") | V54: =IFERROR(+IF(V$29=ProposalToGnatt[[#This Row],[Start Date]],Milestone_Marker,IF(AND(V$29>ProposalToGnatt[[#This Row],[Start Date]],V$29<ProposalToGnatt[[#This Row],[Start Date]]+ProposalToGnatt[[#This Row],[Days]]),$G$5,"")),"") | W54: =IFERROR(+IF(W$29=ProposalToGnatt[[#This Row],[Start Date]],Milestone_Marker,IF(AND(W$29>ProposalToGnatt[[#This Row],[Start Date]],W$29<ProposalToGnatt[[#This Row],[Start Date]]+ProposalToGnatt[[#This Row],[Days]]),$G$5,"")),"") | ... CU54: =IFERROR(+IF(CU$29=ProposalToGnatt[[#This Row],[Start Date]],Milestone_Marker,IF(AND(CU$29>ProposalToGnatt[[#This Row],[Start Date]],CU$29<ProposalToGnatt[[#This Row],[Start Date]]+ProposalToGnatt[[#This Row],[Days]]),$G$5,"")),"")
P55: =IFERROR(+IF(P$29=ProposalToGnatt[[#This Row],[Start Date]],Milestone_Marker,IF(AND(P$29>ProposalToGnatt[[#This Row],[Start Date]],P$29<ProposalToGnatt[[#This Row],[Start Date]]+ProposalToGnatt[[#This Row],[Days]]),$G$5,"")),"") | Q55: =IFERROR(+IF(Q$29=ProposalToGnatt[[#This Row],[Start Date]],Milestone_Marker,IF(AND(Q$29>ProposalToGnatt[[#This Row],[Start Date]],Q$29<ProposalToGnatt[[#This Row],[Start Date]]+ProposalToGnatt[[#This Row],[Days]]),$G$5,"")),"") | R55: =IFERROR(+IF(R$29=ProposalToGnatt[[#This Row],[Start Date]],Milestone_Marker,IF(AND(R$29>ProposalToGnatt[[#This Row],[Start Date]],R$29<ProposalToGnatt[[#This Row],[Start Date]]+ProposalToGnatt[[#This Row],[Days]]),$G$5,"")),"") | S55: =IFERROR(+IF(S$29=ProposalToGnatt[[#This Row],[Start Date]],Milestone_Marker,IF(AND(S$29>ProposalToGnatt[[#This Row],[Start Date]],S$29<ProposalToGnatt[[#This Row],[Start Date]]+ProposalToGnatt[[#This Row],[Days]]),$G$5,"")),"") | T55: =IFERROR(+IF(T$29=ProposalToGnatt[[#This Row],[Start Date]],Milestone_Marker,IF(AND(T$29>ProposalToGnatt[[#This Row],[Start Date]],T$29<ProposalToGnatt[[#This Row],[Start Date]]+ProposalToGnatt[[#This Row],[Days]]),$G$5,"")),"") | U55: =IFERROR(+IF(U$29=ProposalToGnatt[[#This Row],[Start Date]],Milestone_Marker,IF(AND(U$29>ProposalToGnatt[[#This Row],[Start Date]],U$29<ProposalToGnatt[[#This Row],[Start Date]]+ProposalToGnatt[[#This Row],[Days]]),$G$5,"")),"") | V55: =IFERROR(+IF(V$29=ProposalToGnatt[[#This Row],[Start Date]],Milestone_Marker,IF(AND(V$29>ProposalToGnatt[[#This Row],[Start Date]],V$29<ProposalToGnatt[[#This Row],[Start Date]]+ProposalToGnatt[[#This Row],[Days]]),$G$5,"")),"") | W55: =IFERROR(+IF(W$29=ProposalToGnatt[[#This Row],[Start Date]],Milestone_Marker,IF(AND(W$29>ProposalToGnatt[[#This Row],[Start Date]],W$29<ProposalToGnatt[[#This Row],[Start Date]]+ProposalToGnatt[[#This Row],[Days]]),$G$5,"")),"") | ... CU55: =IFERROR(+IF(CU$29=ProposalToGnatt[[#This Row],[Start Date]],Milestone_Marker,IF(AND(CU$29>ProposalToGnatt[[#This Row],[Start Date]],CU$29<ProposalToGnatt[[#This Row],[Start Date]]+ProposalToGnatt[[#This Row],[Days]]),$G$5,"")),"")
P56: =IFERROR(+IF(P$29=ProposalToGnatt[[#This Row],[Start Date]],Milestone_Marker,IF(AND(P$29>ProposalToGnatt[[#This Row],[Start Date]],P$29<ProposalToGnatt[[#This Row],[Start Date]]+ProposalToGnatt[[#This Row],[Days]]),$G$5,"")),"") | Q56: =IFERROR(+IF(Q$29=ProposalToGnatt[[#This Row],[Start Date]],Milestone_Marker,IF(AND(Q$29>ProposalToGnatt[[#This Row],[Start Date]],Q$29<ProposalToGnatt[[#This Row],[Start Date]]+ProposalToGnatt[[#This Row],[Days]]),$G$5,"")),"") | R56: =IFERROR(+IF(R$29=ProposalToGnatt[[#This Row],[Start Date]],Milestone_Marker,IF(AND(R$29>ProposalToGnatt[[#This Row],[Start Date]],R$29<ProposalToGnatt[[#This Row],[Start Date]]+ProposalToGnatt[[#This Row],[Days]]),$G$5,"")),"") | S56: =IFERROR(+IF(S$29=ProposalToGnatt[[#This Row],[Start Date]],Milestone_Marker,IF(AND(S$29>ProposalToGnatt[[#This Row],[Start Date]],S$29<ProposalToGnatt[[#This Row],[Start Date]]+ProposalToGnatt[[#This Row],[Days]]),$G$5,"")),"") | T56: =IFERROR(+IF(T$29=ProposalToGnatt[[#This Row],[Start Date]],Milestone_Marker,IF(AND(T$29>ProposalToGnatt[[#This Row],[Start Date]],T$29<ProposalToGnatt[[#This Row],[Start Date]]+ProposalToGnatt[[#This Row],[Days]]),$G$5,"")),"") | U56: =IFERROR(+IF(U$29=ProposalToGnatt[[#This Row],[Start Date]],Milestone_Marker,IF(AND(U$29>ProposalToGnatt[[#This Row],[Start Date]],U$29<ProposalToGnatt[[#This Row],[Start Date]]+ProposalToGnatt[[#This Row],[Days]]),$G$5,"")),"") | V56: =IFERROR(+IF(V$29=ProposalToGnatt[[#This Row],[Start Date]],Milestone_Marker,IF(AND(V$29>ProposalToGnatt[[#This Row],[Start Date]],V$29<ProposalToGnatt[[#This Row],[Start Date]]+ProposalToGnatt[[#This Row],[Days]]),$G$5,"")),"") | W56: =IFERROR(+IF(W$29=ProposalToGnatt[[#This Row],[Start Date]],Milestone_Marker,IF(AND(W$29>ProposalToGnatt[[#This Row],[Start Date]],W$29<ProposalToGnatt[[#This Row],[Start Date]]+ProposalToGnatt[[#This Row],[Days]]),$G$5,"")),"") | ... CU56: =IFERROR(+IF(CU$29=ProposalToGnatt[[#This Row],[Start Date]],Milestone_Marker,IF(AND(CU$29>ProposalToGnatt[[#This Row],[Start Date]],CU$29<ProposalToGnatt[[#This Row],[Start Date]]+ProposalToGnatt[[#This Row],[Days]]),$G$5,"")),"")
P57: =IFERROR(+IF(P$29=ProposalToGnatt[[#This Row],[Start Date]],Milestone_Marker,IF(AND(P$29>ProposalToGnatt[[#This Row],[Start Date]],P$29<ProposalToGnatt[[#This Row],[Start Date]]+ProposalToGnatt[[#This Row],[Days]]),$G$5,"")),"") | Q57: =IFERROR(+IF(Q$29=ProposalToGnatt[[#This Row],[Start Date]],Milestone_Marker,IF(AND(Q$29>ProposalToGnatt[[#This Row],[Start Date]],Q$29<ProposalToGnatt[[#This Row],[Start Date]]+ProposalToGnatt[[#This Row],[Days]]),$G$5,"")),"") | R57: =IFERROR(+IF(R$29=ProposalToGnatt[[#This Row],[Start Date]],Milestone_Marker,IF(AND(R$29>ProposalToGnatt[[#This Row],[Start Date]],R$29<ProposalToGnatt[[#This Row],[Start Date]]+ProposalToGnatt[[#This Row],[Days]]),$G$5,"")),"") | S57: =IFERROR(+IF(S$29=ProposalToGnatt[[#This Row],[Start Date]],Milestone_Marker,IF(AND(S$29>ProposalToGnatt[[#This Row],[Start Date]],S$29<ProposalToGnatt[[#This Row],[Start Date]]+ProposalToGnatt[[#This Row],[Days]]),$G$5,"")),"") | T57: =IFERROR(+IF(T$29=ProposalToGnatt[[#This Row],[Start Date]],Milestone_Marker,IF(AND(T$29>ProposalToGnatt[[#This Row],[Start Date]],T$29<ProposalToGnatt[[#This Row],[Start Date]]+ProposalToGnatt[[#This Row],[Days]]),$G$5,"")),"") | U57: =IFERROR(+IF(U$29=ProposalToGnatt[[#This Row],[Start Date]],Milestone_Marker,IF(AND(U$29>ProposalToGnatt[[#This Row],[Start Date]],U$29<ProposalToGnatt[[#This Row],[Start Date]]+ProposalToGnatt[[#This Row],[Days]]),$G$5,"")),"") | V57: =IFERROR(+IF(V$29=ProposalToGnatt[[#This Row],[Start Date]],Milestone_Marker,IF(AND(V$29>ProposalToGnatt[[#This Row],[Start Date]],V$29<ProposalToGnatt[[#This Row],[Start Date]]+ProposalToGnatt[[#This Row],[Days]]),$G$5,"")),"") | W57: =IFERROR(+IF(W$29=ProposalToGnatt[[#This Row],[Start Date]],Milestone_Marker,IF(AND(W$29>ProposalToGnatt[[#This Row],[Start Date]],W$29<ProposalToGnatt[[#This Row],[Start Date]]+ProposalToGnatt[[#This Row],[Days]]),$G$5,"")),"") | ... CU57: =IFERROR(+IF(CU$29=ProposalToGnatt[[#This Row],[Start Date]],Milestone_Marker,IF(AND(CU$29>ProposalToGnatt[[#This Row],[Start Date]],CU$29<ProposalToGnatt[[#This Row],[Start Date]]+ProposalToGnatt[[#This Row],[Days]]),$G$5,"")),"")
... P79: =IFERROR(+IF(P$29=ProposalToGnatt[[#This Row],[Start Date]],Milestone_Marker,IF(AND(P$29>ProposalToGnatt[[#This Row],[Start Date]],P$29<ProposalToGnatt[[#This Row],[Start Date]]+ProposalToGnatt[[#This Row],[Days]]),$G$5,"")),"") | Q79: =IFERROR(+IF(Q$29=ProposalToGnatt[[#This Row],[Start Date]],Milestone_Marker,IF(AND(Q$29>ProposalToGnatt[[#This Row],[Start Date]],Q$29<ProposalToGnatt[[#This Row],[Start Date]]+ProposalToGnatt[[#This Row],[Days]]),$G$5,"")),"") | R79: =IFERROR(+IF(R$29=ProposalToGnatt[[#This Row],[Start Date]],Milestone_Marker,IF(AND(R$29>ProposalToGnatt[[#This Row],[Start Date]],R$29<ProposalToGnatt[[#This Row],[Start Date]]+ProposalToGnatt[[#This Row],[Days]]),$G$5,"")),"") | S79: =IFERROR(+IF(S$29=ProposalToGnatt[[#This Row],[Start Date]],Milestone_Marker,IF(AND(S$29>ProposalToGnatt[[#This Row],[Start Date]],S$29<ProposalToGnatt[[#This Row],[Start Date]]+ProposalToGnatt[[#This Row],[Days]]),$G$5,"")),"") | T79: =IFERROR(+IF(T$29=ProposalToGnatt[[#This Row],[Start Date]],Milestone_Marker,IF(AND(T$29>ProposalToGnatt[[#This Row],[Start Date]],T$29<ProposalToGnatt[[#This Row],[Start Date]]+ProposalToGnatt[[#This Row],[Days]]),$G$5,"")),"") | U79: =IFERROR(+IF(U$29=ProposalToGnatt[[#This Row],[Start Date]],Milestone_Marker,IF(AND(U$29>ProposalToGnatt[[#This Row],[Start Date]],U$29<ProposalToGnatt[[#This Row],[Start Date]]+ProposalToGnatt[[#This Row],[Days]]),$G$5,"")),"") | V79: =IFERROR(+IF(V$29=ProposalToGnatt[[#This Row],[Start Date]],Milestone_Marker,IF(AND(V$29>ProposalToGnatt[[#This Row],[Start Date]],V$29<ProposalToGnatt[[#This Row],[Start Date]]+ProposalToGnatt[[#This Row],[Days]]),$G$5,"")),"") | W79: =IFERROR(+IF(W$29=ProposalToGnatt[[#This Row],[Start Date]],Milestone_Marker,IF(AND(W$29>ProposalToGnatt[[#This Row],[Start Date]],W$29<ProposalToGnatt[[#This Row],[Start Date]]+ProposalToGnatt[[#This Row],[Days]]),$G$5,"")),"") | ... CU79: =IFERROR(+IF(CU$29=ProposalToGnatt[[#This Row],[Start Date]],Milestone_Marker,IF(AND(CU$29>ProposalToGnatt[[#This Row],[Start Date]],CU$29<ProposalToGnatt[[#This Row],[Start Date]]+ProposalToGnatt[[#This Row],[Days]]),$G$5,"")),"")
P80: =IFERROR(+IF(P$29=ProposalToGnatt[[#This Row],[Start Date]],Milestone_Marker,IF(AND(P$29>ProposalToGnatt[[#This Row],[Start Date]],P$29<ProposalToGnatt[[#This Row],[Start Date]]+ProposalToGnatt[[#This Row],[Days]]),$G$5,"")),"") | Q80: =IFERROR(+IF(Q$29=ProposalToGnatt[[#This Row],[Start Date]],Milestone_Marker,IF(AND(Q$29>ProposalToGnatt[[#This Row],[Start Date]],Q$29<ProposalToGnatt[[#This Row],[Start Date]]+ProposalToGnatt[[#This Row],[Days]]),$G$5,"")),"") | R80: =IFERROR(+IF(R$29=ProposalToGnatt[[#This Row],[Start Date]],Milestone_Marker,IF(AND(R$29>ProposalToGnatt[[#This Row],[Start Date]],R$29<ProposalToGnatt[[#This Row],[Start Date]]+ProposalToGnatt[[#This Row],[Days]]),$G$5,"")),"") | S80: =IFERROR(+IF(S$29=ProposalToGnatt[[#This Row],[Start Date]],Milestone_Marker,IF(AND(S$29>ProposalToGnatt[[#This Row],[Start Date]],S$29<ProposalToGnatt[[#This Row],[Start Date]]+ProposalToGnatt[[#This Row],[Days]]),$G$5,"")),"") | T80: =IFERROR(+IF(T$29=ProposalToGnatt[[#This Row],[Start Date]],Milestone_Marker,IF(AND(T$29>ProposalToGnatt[[#This Row],[Start Date]],T$29<ProposalToGnatt[[#This Row],[Start Date]]+ProposalToGnatt[[#This Row],[Days]]),$G$5,"")),"") | U80: =IFERROR(+IF(U$29=ProposalToGnatt[[#This Row],[Start Date]],Milestone_Marker,IF(AND(U$29>ProposalToGnatt[[#This Row],[Start Date]],U$29<ProposalToGnatt[[#This Row],[Start Date]]+ProposalToGnatt[[#This Row],[Days]]),$G$5,"")),"") | V80: =IFERROR(+IF(V$29=ProposalToGnatt[[#This Row],[Start Date]],Milestone_Marker,IF(AND(V$29>ProposalToGnatt[[#This Row],[Start Date]],V$29<ProposalToGnatt[[#This Row],[Start Date]]+ProposalToGnatt[[#This Row],[Days]]),$G$5,"")),"") | W80: =IFERROR(+IF(W$29=ProposalToGnatt[[#This Row],[Start Date]],Milestone_Marker,IF(AND(W$29>ProposalToGnatt[[#This Row],[Start Date]],W$29<ProposalToGnatt[[#This Row],[Start Date]]+ProposalToGnatt[[#This Row],[Days]]),$G$5,"")),"") | ... CU80: =IFERROR(+IF(CU$29=ProposalToGnatt[[#This Row],[Start Date]],Milestone_Marker,IF(AND(CU$29>ProposalToGnatt[[#This Row],[Start Date]],CU$29<ProposalToGnatt[[#This Row],[Start Date]]+ProposalToGnatt[[#This Row],[Days]]),$G$5,"")),"") | CV80: =IFERROR(+IF(CT$29=#REF!,Milestone_Marker,IF(AND(CT$29>#REF!,CT$29<=#REF!+#REF!),$G$5,"")),"") | CW80: =IFERROR(+IF(CU$29=#REF!,Milestone_Marker,IF(AND(CU$29>#REF!,CU$29<=#REF!+#REF!),$G$5,"")),"")
P81: =IFERROR(+IF(P$29=ProposalToGnatt[[#This Row],[Start Date]],Milestone_Marker,IF(AND(P$29>ProposalToGnatt[[#This Row],[Start Date]],P$29<ProposalToGnatt[[#This Row],[Start Date]]+ProposalToGnatt[[#This Row],[Days]]),$G$5,"")),"") | Q81: =IFERROR(+IF(Q$29=ProposalToGnatt[[#This Row],[Start Date]],Milestone_Marker,IF(AND(Q$29>ProposalToGnatt[[#This Row],[Start Date]],Q$29<ProposalToGnatt[[#This Row],[Start Date]]+ProposalToGnatt[[#This Row],[Days]]),$G$5,"")),"") | R81: =IFERROR(+IF(R$29=ProposalToGnatt[[#This Row],[Start Date]],Milestone_Marker,IF(AND(R$29>ProposalToGnatt[[#This Row],[Start Date]],R$29<ProposalToGnatt[[#This Row],[Start Date]]+ProposalToGnatt[[#This Row],[Days]]),$G$5,"")),"") | S81: =IFERROR(+IF(S$29=ProposalToGnatt[[#This Row],[Start Date]],Milestone_Marker,IF(AND(S$29>ProposalToGnatt[[#This Row],[Start Date]],S$29<ProposalToGnatt[[#This Row],[Start Date]]+ProposalToGnatt[[#This Row],[Days]]),$G$5,"")),"") | T81: =IFERROR(+IF(T$29=ProposalToGnatt[[#This Row],[Start Date]],Milestone_Marker,IF(AND(T$29>ProposalToGnatt[[#This Row],[Start Date]],T$29<ProposalToGnatt[[#This Row],[Start Date]]+ProposalToGnatt[[#This Row],[Days]]),$G$5,"")),"") | U81: =IFERROR(+IF(U$29=ProposalToGnatt[[#This Row],[Start Date]],Milestone_Marker,IF(AND(U$29>ProposalToGnatt[[#This Row],[Start Date]],U$29<ProposalToGnatt[[#This Row],[Start Date]]+ProposalToGnatt[[#This Row],[Days]]),$G$5,"")),"") | V81: =IFERROR(+IF(V$29=ProposalToGnatt[[#This Row],[Start Date]],Milestone_Marker,IF(AND(V$29>ProposalToGnatt[[#This Row],[Start Date]],V$29<ProposalToGnatt[[#This Row],[Start Date]]+ProposalToGnatt[[#This Row],[Days]]),$G$5,"")),"") | W81: =IFERROR(+IF(W$29=ProposalToGnatt[[#This Row],[Start Date]],Milestone_Marker,IF(AND(W$29>ProposalToGnatt[[#This Row],[Start Date]],W$29<ProposalToGnatt[[#This Row],[Start Date]]+ProposalToGnatt[[#This Row],[Days]]),$G$5,"")),"") | ... CU81: =IFERROR(+IF(CU$29=ProposalToGnatt[[#This Row],[Start Date]],Milestone_Marker,IF(AND(CU$29>ProposalToGnatt[[#This Row],[Start Date]],CU$29<ProposalToGnatt[[#This Row],[Start Date]]+ProposalToGnatt[[#This Row],[Days]]),$G$5,"")),"") | CV81: =IFERROR(+IF(CT$29=#REF!,Milestone_Marker,IF(AND(CT$29>#REF!,CT$29<=#REF!+#REF!),$G$5,"")),"") | CW81: =IFERROR(+IF(CU$29=#REF!,Milestone_Marker,IF(AND(CU$29>#REF!,CU$29<=#REF!+#REF!),$G$5,"")),"")
P82: =IFERROR(+IF(P$29=ProposalToGnatt[[#This Row],[Start Date]],Milestone_Marker,IF(AND(P$29>ProposalToGnatt[[#This Row],[Start Date]],P$29<ProposalToGnatt[[#This Row],[Start Date]]+ProposalToGnatt[[#This Row],[Days]]),$G$5,"")),"") | Q82: =IFERROR(+IF(Q$29=ProposalToGnatt[[#This Row],[Start Date]],Milestone_Marker,IF(AND(Q$29>ProposalToGnatt[[#This Row],[Start Date]],Q$29<ProposalToGnatt[[#This Row],[Start Date]]+ProposalToGnatt[[#This Row],[Days]]),$G$5,"")),"") | R82: =IFERROR(+IF(R$29=ProposalToGnatt[[#This Row],[Start Date]],Milestone_Marker,IF(AND(R$29>ProposalToGnatt[[#This Row],[Start Date]],R$29<ProposalToGnatt[[#This Row],[Start Date]]+ProposalToGnatt[[#This Row],[Days]]),$G$5,"")),"") | S82: =IFERROR(+IF(S$29=ProposalToGnatt[[#This Row],[Start Date]],Milestone_Marker,IF(AND(S$29>ProposalToGnatt[[#This Row],[Start Date]],S$29<ProposalToGnatt[[#This Row],[Start Date]]+ProposalToGnatt[[#This Row],[Days]]),$G$5,"")),"") | T82: =IFERROR(+IF(T$29=ProposalToGnatt[[#This Row],[Start Date]],Milestone_Marker,IF(AND(T$29>ProposalToGnatt[[#This Row],[Start Date]],T$29<ProposalToGnatt[[#This Row],[Start Date]]+ProposalToGnatt[[#This Row],[Days]]),$G$5,"")),"") | U82: =IFERROR(+IF(U$29=ProposalToGnatt[[#This Row],[Start Date]],Milestone_Marker,IF(AND(U$29>ProposalToGnatt[[#This Row],[Start Date]],U$29<ProposalToGnatt[[#This Row],[Start Date]]+ProposalToGnatt[[#This Row],[Days]]),$G$5,"")),"") | V82: =IFERROR(+IF(V$29=ProposalToGnatt[[#This Row],[Start Date]],Milestone_Marker,IF(AND(V$29>ProposalToGnatt[[#This Row],[Start Date]],V$29<ProposalToGnatt[[#This Row],[Start Date]]+ProposalToGnatt[[#This Row],[Days]]),$G$5,"")),"") | W82: =IFERROR(+IF(W$29=ProposalToGnatt[[#This Row],[Start Date]],Milestone_Marker,IF(AND(W$29>ProposalToGnatt[[#This Row],[Start Date]],W$29<ProposalToGnatt[[#This Row],[Start Date]]+ProposalToGnatt[[#This Row],[Days]]),$G$5,"")),"") | ... CU82: =IFERROR(+IF(CU$29=ProposalToGnatt[[#This Row],[Start Date]],Milestone_Marker,IF(AND(CU$29>ProposalToGnatt[[#This Row],[Start Date]],CU$29<ProposalToGnatt[[#This Row],[Start Date]]+ProposalToGnatt[[#This Row],[Days]]),$G$5,"")),"") | CV82: =IFERROR(+IF(CT$29=#REF!,Milestone_Marker,IF(AND(CT$29>#REF!,CT$29<=#REF!+#REF!),$G$5,"")),"") | CW82: =IFERROR(+IF(CU$29=#REF!,Milestone_Marker,IF(AND(CU$29>#REF!,CU$29<=#REF!+#REF!),$G$5,"")),"")
P83: =IFERROR(+IF(P$29=ProposalToGnatt[[#This Row],[Start Date]],Milestone_Marker,IF(AND(P$29>ProposalToGnatt[[#This Row],[Start Date]],P$29<ProposalToGnatt[[#This Row],[Start Date]]+ProposalToGnatt[[#This Row],[Days]]),$G$5,"")),"") | Q83: =IFERROR(+IF(Q$29=ProposalToGnatt[[#This Row],[Start Date]],Milestone_Marker,IF(AND(Q$29>ProposalToGnatt[[#This Row],[Start Date]],Q$29<ProposalToGnatt[[#This Row],[Start Date]]+ProposalToGnatt[[#This Row],[Days]]),$G$5,"")),"") | R83: =IFERROR(+IF(R$29=ProposalToGnatt[[#This Row],[Start Date]],Milestone_Marker,IF(AND(R$29>ProposalToGnatt[[#This Row],[Start Date]],R$29<ProposalToGnatt[[#This Row],[Start Date]]+ProposalToGnatt[[#This Row],[Days]]),$G$5,"")),"") | S83: =IFERROR(+IF(S$29=ProposalToGnatt[[#This Row],[Start Date]],Milestone_Marker,IF(AND(S$29>ProposalToGnatt[[#This Row],[Start Date]],S$29<ProposalToGnatt[[#This Row],[Start Date]]+ProposalToGnatt[[#This Row],[Days]]),$G$5,"")),"") | T83: =IFERROR(+IF(T$29=ProposalToGnatt[[#This Row],[Start Date]],Milestone_Marker,IF(AND(T$29>ProposalToGnatt[[#This Row],[Start Date]],T$29<ProposalToGnatt[[#This Row],[Start Date]]+ProposalToGnatt[[#This Row],[Days]]),$G$5,"")),"") | U83: =IFERROR(+IF(U$29=ProposalToGnatt[[#This Row],[Start Date]],Milestone_Marker,IF(AND(U$29>ProposalToGnatt[[#This Row],[Start Date]],U$29<ProposalToGnatt[[#This Row],[Start Date]]+ProposalToGnatt[[#This Row],[Days]]),$G$5,"")),"") | V83: =IFERROR(+IF(V$29=ProposalToGnatt[[#This Row],[Start Date]],Milestone_Marker,IF(AND(V$29>ProposalToGnatt[[#This Row],[Start Date]],V$29<ProposalToGnatt[[#This Row],[Start Date]]+ProposalToGnatt[[#This Row],[Days]]),$G$5,"")),"") | W83: =IFERROR(+IF(W$29=ProposalToGnatt[[#This Row],[Start Date]],Milestone_Marker,IF(AND(W$29>ProposalToGnatt[[#This Row],[Start Date]],W$29<ProposalToGnatt[[#This Row],[Start Date]]+ProposalToGnatt[[#This Row],[Days]]),$G$5,"")),"") | ... CU83: =IFERROR(+IF(CU$29=ProposalToGnatt[[#This Row],[Start Date]],Milestone_Marker,IF(AND(CU$29>ProposalToGnatt[[#This Row],[Start Date]],CU$29<ProposalToGnatt[[#This Row],[Start Date]]+ProposalToGnatt[[#This Row],[Days]]),$G$5,"")),"") | CV83: =IFERROR(+IF(CT$29=#REF!,Milestone_Marker,IF(AND(CT$29>#REF!,CT$29<=#REF!+#REF!),$G$5,"")),"") | CW83: =IFERROR(+IF(CU$29=#REF!,Milestone_Marker,IF(AND(CU$29>#REF!,CU$29<=#REF!+#REF!),$G$5,"")),"")
P84: =IFERROR(+IF(P$29=ProposalToGnatt[[#This Row],[Start Date]],Milestone_Marker,IF(AND(P$29>ProposalToGnatt[[#This Row],[Start Date]],P$29<ProposalToGnatt[[#This Row],[Start Date]]+ProposalToGnatt[[#This Row],[Days]]),$G$5,"")),"") | Q84: =IFERROR(+IF(Q$29=ProposalToGnatt[[#This Row],[Start Date]],Milestone_Marker,IF(AND(Q$29>ProposalToGnatt[[#This Row],[Start Date]],Q$29<ProposalToGnatt[[#This Row],[Start Date]]+ProposalToGnatt[[#This Row],[Days]]),$G$5,"")),"") | R84: =IFERROR(+IF(R$29=ProposalToGnatt[[#This Row],[Start Date]],Milestone_Marker,IF(AND(R$29>ProposalToGnatt[[#This Row],[Start Date]],R$29<ProposalToGnatt[[#This Row],[Start Date]]+ProposalToGnatt[[#This Row],[Days]]),$G$5,"")),"") | S84: =IFERROR(+IF(S$29=ProposalToGnatt[[#This Row],[Start Date]],Milestone_Marker,IF(AND(S$29>ProposalToGnatt[[#This Row],[Start Date]],S$29<ProposalToGnatt[[#This Row],[Start Date]]+ProposalToGnatt[[#This Row],[Days]]),$G$5,"")),"") | T84: =IFERROR(+IF(T$29=ProposalToGnatt[[#This Row],[Start Date]],Milestone_Marker,IF(AND(T$29>ProposalToGnatt[[#This Row],[Start Date]],T$29<ProposalToGnatt[[#This Row],[Start Date]]+ProposalToGnatt[[#This Row],[Days]]),$G$5,"")),"") | U84: =IFERROR(+IF(U$29=ProposalToGnatt[[#This Row],[Start Date]],Milestone_Marker,IF(AND(U$29>ProposalToGnatt[[#This Row],[Start Date]],U$29<ProposalToGnatt[[#This Row],[Start Date]]+ProposalToGnatt[[#This Row],[Days]]),$G$5,"")),"") | V84: =IFERROR(+IF(V$29=ProposalToGnatt[[#This Row],[Start Date]],Milestone_Marker,IF(AND(V$29>ProposalToGnatt[[#This Row],[Start Date]],V$29<ProposalToGnatt[[#This Row],[Start Date]]+ProposalToGnatt[[#This Row],[Days]]),$G$5,"")),"") | W84: =IFERROR(+IF(W$29=ProposalToGnatt[[#This Row],[Start Date]],Milestone_Marker,IF(AND(W$29>ProposalToGnatt[[#This Row],[Start Date]],W$29<ProposalToGnatt[[#This Row],[Start Date]]+ProposalToGnatt[[#This Row],[Days]]),$G$5,"")),"") | ... CU84: =IFERROR(+IF(CU$29=ProposalToGnatt[[#This Row],[Start Date]],Milestone_Marker,IF(AND(CU$29>ProposalToGnatt[[#This Row],[Start Date]],CU$29<ProposalToGnatt[[#This Row],[Start Date]]+ProposalToGnatt[[#This Row],[Days]]),$G$5,"")),"") | CV84: =IFERROR(+IF(CT$29=#REF!,Milestone_Marker,IF(AND(CT$29>#REF!,CT$29<=#REF!+#REF!),$G$5,"")),"") | CW84: =IFERROR(+IF(CU$29=#REF!,Milestone_Marker,IF(AND(CU$29>#REF!,CU$29<=#REF!+#REF!),$G$5,"")),"")
P85: =IFERROR(+IF(Q$29=#REF!,Milestone_Marker,IF(AND(Q$29>#REF!,Q$29<=#REF!+#REF!),$G$5,"")),"") | Q85: =IFERROR(+IF(R$29=#REF!,Milestone_Marker,IF(AND(R$29>#REF!,R$29<=#REF!+#REF!),$G$5,"")),"") | R85: =IFERROR(+IF(S$29=#REF!,Milestone_Marker,IF(AND(S$29>#REF!,S$29<=#REF!+#REF!),$G$5,"")),"") | S85: =IFERROR(+IF(T$29=#REF!,Milestone_Marker,IF(AND(T$29>#REF!,T$29<=#REF!+#REF!),$G$5,"")),"") | T85: =IFERROR(+IF(U$29=#REF!,Milestone_Marker,IF(AND(U$29>#REF!,U$29<=#REF!+#REF!),$G$5,"")),"") | U85: =IFERROR(+IF(V$29=#REF!,Milestone_Marker,IF(AND(V$29>#REF!,V$29<=#REF!+#REF!),$G$5,"")),"") | V85: =IFERROR(+IF(W$29=#REF!,Milestone_Marker,IF(AND(W$29>#REF!,W$29<=#REF!+#REF!),$G$5,"")),"") | W85: =IFERROR(+IF(X$29=#REF!,Milestone_Marker,IF(AND(X$29>#REF!,X$29<=#REF!+#REF!),$G$5,"")),"") | ... CT85: =IFERROR(+IF(CU$29=#REF!,Milestone_Marker,IF(AND(CU$29>#REF!,CU$29<=#REF!+#REF!),$G$5,"")),"")
P86: =IFERROR(+IF(Q$29=#REF!,Milestone_Marker,IF(AND(Q$29>#REF!,Q$29<=#REF!+#REF!),$G$5,"")),"") | Q86: =IFERROR(+IF(R$29=#REF!,Milestone_Marker,IF(AND(R$29>#REF!,R$29<=#REF!+#REF!),$G$5,"")),"") | R86: =IFERROR(+IF(S$29=#REF!,Milestone_Marker,IF(AND(S$29>#REF!,S$29<=#REF!+#REF!),$G$5,"")),"") | S86: =IFERROR(+IF(T$29=#REF!,Milestone_Marker,IF(AND(T$29>#REF!,T$29<=#REF!+#REF!),$G$5,"")),"") | T86: =IFERROR(+IF(U$29=#REF!,Milestone_Marker,IF(AND(U$29>#REF!,U$29<=#REF!+#REF!),$G$5,"")),"") | U86: =IFERROR(+IF(V$29=#REF!,Milestone_Marker,IF(AND(V$29>#REF!,V$29<=#REF!+#REF!),$G$5,"")),"") | V86: =IFERROR(+IF(W$29=#REF!,Milestone_Marker,IF(AND(W$29>#REF!,W$29<=#REF!+#REF!),$G$5,"")),"") | W86: =IFERROR(+IF(X$29=#REF!,Milestone_Marker,IF(AND(X$29>#REF!,X$29<=#REF!+#REF!),$G$5,"")),"") | ... CT86: =IFERROR(+IF(CU$29=#REF!,Milestone_Marker,IF(AND(CU$29>#REF!,CU$29<=#REF!+#REF!),$G$5,"")),"")
P87: =IFERROR(+IF(Q$29=#REF!,Milestone_Marker,IF(AND(Q$29>#REF!,Q$29<=#REF!+#REF!),$G$5,"")),"") | Q87: =IFERROR(+IF(R$29=#REF!,Milestone_Marker,IF(AND(R$29>#REF!,R$29<=#REF!+#REF!),$G$5,"")),"") | R87: =IFERROR(+IF(S$29=#REF!,Milestone_Marker,IF(AND(S$29>#REF!,S$29<=#REF!+#REF!),$G$5,"")),"") | S87: =IFERROR(+IF(T$29=#REF!,Milestone_Marker,IF(AND(T$29>#REF!,T$29<=#REF!+#REF!),$G$5,"")),"") | T87: =IFERROR(+IF(U$29=#REF!,Milestone_Marker,IF(AND(U$29>#REF!,U$29<=#REF!+#REF!),$G$5,"")),"") | U87: =IFERROR(+IF(V$29=#REF!,Milestone_Marker,IF(AND(V$29>#REF!,V$29<=#REF!+#REF!),$G$5,"")),"") | V87: =IFERROR(+IF(W$29=#REF!,Milestone_Marker,IF(AND(W$29>#REF!,W$29<=#REF!+#REF!),$G$5,"")),"") | W87: =IFERROR(+IF(X$29=#REF!,Milestone_Marker,IF(AND(X$29>#REF!,X$29<=#REF!+#REF!),$G$5,"")),"") | ... CT87: =IFERROR(+IF(CU$29=#REF!,Milestone_Marker,IF(AND(CU$29>#REF!,CU$29<=#REF!+#REF!),$G$5,"")),"")
P88: =IFERROR(+IF(Q$29=#REF!,Milestone_Marker,IF(AND(Q$29>#REF!,Q$29<=#REF!+#REF!),$G$5,"")),"") | Q88: =IFERROR(+IF(R$29=#REF!,Milestone_Marker,IF(AND(R$29>#REF!,R$29<=#REF!+#REF!),$G$5,"")),"") | R88: =IFERROR(+IF(S$29=#REF!,Milestone_Marker,IF(AND(S$29>#REF!,S$29<=#REF!+#REF!),$G$5,"")),"") | S88: =IFERROR(+IF(T$29=#REF!,Milestone_Marker,IF(AND(T$29>#REF!,T$29<=#REF!+#REF!),$G$5,"")),"") | T88: =IFERROR(+IF(U$29=#REF!,Milestone_Marker,IF(AND(U$29>#REF!,U$29<=#REF!+#REF!),$G$5,"")),"") | U88: =IFERROR(+IF(V$29=#REF!,Milestone_Marker,IF(AND(V$29>#REF!,V$29<=#REF!+#REF!),$G$5,"")),"") | V88: =IFERROR(+IF(W$29=#REF!,Milestone_Marker,IF(AND(W$29>#REF!,W$29<=#REF!+#REF!),$G$5,"")),"") | W88: =IFERROR(+IF(X$29=#REF!,Milestone_Marker,IF(AND(X$29>#REF!,X$29<=#REF!+#REF!),$G$5,"")),"") | ... CT88: =IFERROR(+IF(CU$29=#REF!,Milestone_Marker,IF(AND(CU$29>#REF!,CU$29<=#REF!+#REF!),$G$5,"")),"")
P89: =IFERROR(+IF(Q$29=#REF!,Milestone_Marker,IF(AND(Q$29>#REF!,Q$29<=#REF!+#REF!),$G$5,"")),"") | Q89: =IFERROR(+IF(R$29=#REF!,Milestone_Marker,IF(AND(R$29>#REF!,R$29<=#REF!+#REF!),$G$5,"")),"") | R89: =IFERROR(+IF(S$29=#REF!,Milestone_Marker,IF(AND(S$29>#REF!,S$29<=#REF!+#REF!),$G$5,"")),"") | S89: =IFERROR(+IF(T$29=#REF!,Milestone_Marker,IF(AND(T$29>#REF!,T$29<=#REF!+#REF!),$G$5,"")),"") | T89: =IFERROR(+IF(U$29=#REF!,Milestone_Marker,IF(AND(U$29>#REF!,U$29<=#REF!+#REF!),$G$5,"")),"") | U89: =IFERROR(+IF(V$29=#REF!,Milestone_Marker,IF(AND(V$29>#REF!,V$29<=#REF!+#REF!),$G$5,"")),"") | V89: =IFERROR(+IF(W$29=#REF!,Milestone_Marker,IF(AND(W$29>#REF!,W$29<=#REF!+#REF!),$G$5,"")),"") | W89: =IFERROR(+IF(X$29=#REF!,Milestone_Marker,IF(AND(X$29>#REF!,X$29<=#REF!+#REF!),$G$5,"")),"") | ... CT89: =IFERROR(+IF(CU$29=#REF!,Milestone_Marker,IF(AND(CU$29>#REF!,CU$29<=#REF!+#REF!),$G$5,"")),"")
P90: =IFERROR(+IF(Q$29=#REF!,Milestone_Marker,IF(AND(Q$29>#REF!,Q$29<=#REF!+#REF!),$G$5,"")),"") | Q90: =IFERROR(+IF(R$29=#REF!,Milestone_Marker,IF(AND(R$29>#REF!,R$29<=#REF!+#REF!),$G$5,"")),"") | R90: =IFERROR(+IF(S$29=#REF!,Milestone_Marker,IF(AND(S$29>#REF!,S$29<=#REF!+#REF!),$G$5,"")),"") | S90: =IFERROR(+IF(T$29=#REF!,Milestone_Marker,IF(AND(T$29>#REF!,T$29<=#REF!+#REF!),$G$5,"")),"") | T90: =IFERROR(+IF(U$29=#REF!,Milestone_Marker,IF(AND(U$29>#REF!,U$29<=#REF!+#REF!),$G$5,"")),"") | U90: =IFERROR(+IF(V$29=#REF!,Milestone_Marker,IF(AND(V$29>#REF!,V$29<=#REF!+#REF!),$G$5,"")),"") | V90: =IFERROR(+IF(W$29=#REF!,Milestone_Marker,IF(AND(W$29>#REF!,W$29<=#REF!+#REF!),$G$5,"")),"") | W90: =IFERROR(+IF(X$29=#REF!,Milestone_Marker,IF(AND(X$29>#REF!,X$29<=#REF!+#REF!),$G$5,"")),"") | ... CT90: =IFERROR(+IF(CU$29=#REF!,Milestone_Marker,IF(AND(CU$29>#REF!,CU$29<=#REF!+#REF!),$G$5,"")),"")
P91: =IFERROR(+IF(Q$29=#REF!,Milestone_Marker,IF(AND(Q$29>#REF!,Q$29<=#REF!+#REF!),$G$5,"")),"") | Q91: =IFERROR(+IF(R$29=#REF!,Milestone_Marker,IF(AND(R$29>#REF!,R$29<=#REF!+#REF!),$G$5,"")),"") | R91: =IFERROR(+IF(S$29=#REF!,Milestone_Marker,IF(AND(S$29>#REF!,S$29<=#REF!+#REF!),$G$5,"")),"") | S91: =IFERROR(+IF(T$29=#REF!,Milestone_Marker,IF(AND(T$29>#REF!,T$29<=#REF!+#REF!),$G$5,"")),"") | T91: =IFERROR(+IF(U$29=#REF!,Milestone_Marker,IF(AND(U$29>#REF!,U$29<=#REF!+#REF!),$G$5,"")),"") | U91: =IFERROR(+IF(V$29=#REF!,Milestone_Marker,IF(AND(V$29>#REF!,V$29<=#REF!+#REF!),$G$5,"")),"") | V91: =IFERROR(+IF(W$29=#REF!,Milestone_Marker,IF(AND(W$29>#REF!,W$29<=#REF!+#REF!),$G$5,"")),"") | W91: =IFERROR(+IF(X$29=#REF!,Milestone_Marker,IF(AND(X$29>#REF!,X$29<=#REF!+#REF!),$G$5,"")),"") | ... CT91: =IFERROR(+IF(CU$29=#REF!,Milestone_Marker,IF(AND(CU$29>#REF!,CU$29<=#REF!+#REF!),$G$5,"")),"")
P92: =IFERROR(+IF(Q$29=#REF!,Milestone_Marker,IF(AND(Q$29>#REF!,Q$29<=#REF!+#REF!),$G$5,"")),"") | Q92: =IFERROR(+IF(R$29=#REF!,Milestone_Marker,IF(AND(R$29>#REF!,R$29<=#REF!+#REF!),$G$5,"")),"") | R92: =IFERROR(+IF(S$29=#REF!,Milestone_Marker,IF(AND(S$29>#REF!,S$29<=#REF!+#REF!),$G$5,"")),"") | S92: =IFERROR(+IF(T$29=#REF!,Milestone_Marker,IF(AND(T$29>#REF!,T$29<=#REF!+#REF!),$G$5,"")),"") | T92: =IFERROR(+IF(U$29=#REF!,Milestone_Marker,IF(AND(U$29>#REF!,U$29<=#REF!+#REF!),$G$5,"")),"") | U92: =IFERROR(+IF(V$29=#REF!,Milestone_Marker,IF(AND(V$29>#REF!,V$29<=#REF!+#REF!),$G$5,"")),"") | V92: =IFERROR(+IF(W$29=#REF!,Milestone_Marker,IF(AND(W$29>#REF!,W$29<=#REF!+#REF!),$G$5,"")),"") | W92: =IFERROR(+IF(X$29=#REF!,Milestone_Marker,IF(AND(X$29>#REF!,X$29<=#REF!+#REF!),$G$5,"")),"") | ... CT92: =IFERROR(+IF(CU$29=#REF!,Milestone_Marker,IF(AND(CU$29>#REF!,CU$29<=#REF!+#REF!),$G$5,"")),"")
P93: =IFERROR(+IF(Q$29=#REF!,Milestone_Marker,IF(AND(Q$29>#REF!,Q$29<=#REF!+#REF!),$G$5,"")),"") | Q93: =IFERROR(+IF(R$29=#REF!,Milestone_Marker,IF(AND(R$29>#REF!,R$29<=#REF!+#REF!),$G$5,"")),"") | R93: =IFERROR(+IF(S$29=#REF!,Milestone_Marker,IF(AND(S$29>#REF!,S$29<=#REF!+#REF!),$G$5,"")),"") | S93: =IFERROR(+IF(T$29=#REF!,Milestone_Marker,IF(AND(T$29>#REF!,T$29<=#REF!+#REF!),$G$5,"")),"") | T93: =IFERROR(+IF(U$29=#REF!,Milestone_Marker,IF(AND(U$29>#REF!,U$29<=#REF!+#REF!),$G$5,"")),"") | U93: =IFERROR(+IF(V$29=#REF!,Milestone_Marker,IF(AND(V$29>#REF!,V$29<=#REF!+#REF!),$G$5,"")),"") | V93: =IFERROR(+IF(W$29=#REF!,Milestone_Marker,IF(AND(W$29>#REF!,W$29<=#REF!+#REF!),$G$5,"")),"") | W93: =IFERROR(+IF(X$29=#REF!,Milestone_Marker,IF(AND(X$29>#REF!,X$29<=#REF!+#REF!),$G$5,"")),"") | ... CT93: =IFERROR(+IF(CU$29=#REF!,Milestone_Marker,IF(AND(CU$29>#REF!,CU$29<=#REF!+#REF!),$G$5,"")),"")
P94: =IFERROR(+IF(Q$29=#REF!,Milestone_Marker,IF(AND(Q$29>#REF!,Q$29<=#REF!+#REF!),$G$5,"")),"") | Q94: =IFERROR(+IF(R$29=#REF!,Milestone_Marker,IF(AND(R$29>#REF!,R$29<=#REF!+#REF!),$G$5,"")),"") | R94: =IFERROR(+IF(S$29=#REF!,Milestone_Marker,IF(AND(S$29>#REF!,S$29<=#REF!+#REF!),$G$5,"")),"") | S94: =IFERROR(+IF(T$29=#REF!,Milestone_Marker,IF(AND(T$29>#REF!,T$29<=#REF!+#REF!),$G$5,"")),"") | T94: =IFERROR(+IF(U$29=#REF!,Milestone_Marker,IF(AND(U$29>#REF!,U$29<=#REF!+#REF!),$G$5,"")),"") | U94: =IFERROR(+IF(V$29=#REF!,Milestone_Marker,IF(AND(V$29>#REF!,V$29<=#REF!+#REF!),$G$5,"")),"") | V94: =IFERROR(+IF(W$29=#REF!,Milestone_Marker,IF(AND(W$29>#REF!,W$29<=#REF!+#REF!),$G$5,"")),"") | W94: =IFERROR(+IF(X$29=#REF!,Milestone_Marker,IF(AND(X$29>#REF!,X$29<=#REF!+#REF!),$G$5,"")),"") | ... CT94: =IFERROR(+IF(CU$29=#REF!,Milestone_Marker,IF(AND(CU$29>#REF!,CU$29<=#REF!+#REF!),$G$5,"")),"")
P95: =IFERROR(+IF(Q$29=#REF!,Milestone_Marker,IF(AND(Q$29>#REF!,Q$29<=#REF!+#REF!),$G$5,"")),"") | Q95: =IFERROR(+IF(R$29=#REF!,Milestone_Marker,IF(AND(R$29>#REF!,R$29<=#REF!+#REF!),$G$5,"")),"") | R95: =IFERROR(+IF(S$29=#REF!,Milestone_Marker,IF(AND(S$29>#REF!,S$29<=#REF!+#REF!),$G$5,"")),"") | S95: =IFERROR(+IF(T$29=#REF!,Milestone_Marker,IF(AND(T$29>#REF!,T$29<=#REF!+#REF!),$G$5,"")),"") | T95: =IFERROR(+IF(U$29=#REF!,Milestone_Marker,IF(AND(U$29>#REF!,U$29<=#REF!+#REF!),$G$5,"")),"") | U95: =IFERROR(+IF(V$29=#REF!,Milestone_Marker,IF(AND(V$29>#REF!,V$29<=#REF!+#REF!),$G$5,"")),"") | V95: =IFERROR(+IF(W$29=#REF!,Milestone_Marker,IF(AND(W$29>#REF!,W$29<=#REF!+#REF!),$G$5,"")),"") | W95: =IFERROR(+IF(X$29=#REF!,Milestone_Marker,IF(AND(X$29>#REF!,X$29<=#REF!+#REF!),$G$5,"")),"") | ... CT95: =IFERROR(+IF(CU$29=#REF!,Milestone_Marker,IF(AND(CU$29>#REF!,CU$29<=#REF!+#REF!),$G$5,"")),"")
P96: =IFERROR(+IF(Q$29=#REF!,Milestone_Marker,IF(AND(Q$29>#REF!,Q$29<=#REF!+#REF!),$G$5,"")),"") | Q96: =IFERROR(+IF(R$29=#REF!,Milestone_Marker,IF(AND(R$29>#REF!,R$29<=#REF!+#REF!),$G$5,"")),"") | R96: =IFERROR(+IF(S$29=#REF!,Milestone_Marker,IF(AND(S$29>#REF!,S$29<=#REF!+#REF!),$G$5,"")),"") | S96: =IFERROR(+IF(T$29=#REF!,Milestone_Marker,IF(AND(T$29>#REF!,T$29<=#REF!+#REF!),$G$5,"")),"") | T96: =IFERROR(+IF(U$29=#REF!,Milestone_Marker,IF(AND(U$29>#REF!,U$29<=#REF!+#REF!),$G$5,"")),"") | U96: =IFERROR(+IF(V$29=#REF!,Milestone_Marker,IF(AND(V$29>#REF!,V$29<=#REF!+#REF!),$G$5,"")),"") | V96: =IFERROR(+IF(W$29=#REF!,Milestone_Marker,IF(AND(W$29>#REF!,W$29<=#REF!+#REF!),$G$5,"")),"") | W96: =IFERROR(+IF(X$29=#REF!,Milestone_Marker,IF(AND(X$29>#REF!,X$29<=#REF!+#REF!),$G$5,"")),"") | ... CT96: =IFERROR(+IF(CU$29=#REF!,Milestone_Marker,IF(AND(CU$29>#REF!,CU$29<=#REF!+#REF!),$G$5,"")),"")

Sheet Taxes
A1: This is for taxes paid, outside of closing process
A3: Gov't Entity | B3: Date | C3: Tax Event | D3: Tax
A5: Pitt Co | B5: 2024 | C5: Property Transfer Tax | D5: 2138.17
E19: =SUM(D4:D18) -> 2138.17

Sheet Financing
A1: QUANTA FINANCE
A3: CLIENT: | B3: TBD
A4: DATE: | B4: TBD
A5: PROJECT: | B5: TBD
B6: DESCRIPTION OF WORK | D6: REHAB BUDGET | E6: PRE-FUNDING COSTS | F6: SCHEDULED VALUES
A7: 100 | B7: Soft Costs (Plans/Permits/Fees) | D7: 0 | E7: 0 | F7: =SUM(D7-E7) -> 0
A8: 1000 | B8: Demo & Trash Haul | D8: 0 | E8: 0 | F8: =SUM(D8-E8) -> 0
A9: 2000 | B9: Sitework/ Shoring | D9: 0 | E9: 0 | F9: =SUM(D9-E9) -> 0
A10: 3000 | B10: Foundation | D10: 0 | E10: 0 | F10: =SUM(D10-E10) -> 0
A11: 4000 | B11: Framing | D11: 0 | E11: 0 | F11: =SUM(D11-E11) -> 0
A12: 5000 | B12: Plumbing Finish Materials | D12: 0 | E12: 0 | F12: =SUM(D12-E12) -> 0
A13: 6000 | B13: Plumbing install/ Rough | D13: 0 | E13: 0 | F13: =SUM(D13-E13) -> 0
A14: 7000 | B14: Electrical Finish Materials | D14: 0 | E14: 0 | F14: =SUM(D14-E14) -> 0
A15: 8000 | B15: Electrical Install/ rough | D15: 0 | E15: 0 | F15: =SUM(D15-E15) -> 0
A16: 9000 | B16: Metal Works (iron, etc.) | D16: 0 | E16: 0 | F16: =SUM(D16-E16) -> 0
A17: 10000 | B17: HVAC | D17: 0 | E17: 0 | F17: =SUM(D17-E17) -> 0
A18: 11000 | B18: Roof | D18: 0 | E18: 0 | F18: =SUM(D18-E18) -> 0
... A48: 41000 | B48: Owner's Contribution | D48: 0 | E48: 0 | F48: =SUM(D48-E48) -> 0
B50: TOTAL | D50: =SUM(D7:D48) -> 0 | E50: =SUM(E7:E48) -> 0 | F50: =SUM(F7:F48) -> 0

Sheet Seller Advance
A1: Misc Cost | B1: AdvancesReduce Seller Pauout
A2: Sellers Payout
A4: Sellers Payoff | B4: 0 | C4: 0
A5: Seller Incentive/Day: | B5: 33
A6: Seller Vacate Days Early: | B6: 0 | C6: =B5*B6 -> 0
C7: Total Cost | D7: =SUM(C4:C6) -> 0
D11: Total Owed: | E11: =+SUM(C4:C10) -> 0

Sheet MISC 2
A1: Misc
B2: Item Name | C2: Quanity | D2: Cost/Unit | E2: Sub-Total | F2: Total
A3: Living Room Ceiling Fan | C3: 0 | D3: 0 | E3: =+C3*D3 -> 0
A4: Bedroom Ceiling Fan | C4: 0 | D4: 0 | E4: =+C4*D4 -> 0
A5: Ceiling Fan Pole | C5: 0 | D5: 0 | E5: =+C5*D5 -> 0
A6: Kitchen Light Fixture | C6: 0 | D6: 0 | E6: =+C6*D6 -> 0
A7: Dining Room Light Fixture | C7: 0 | D7: 0 | E7: =+C7*D7 -> 0
A8: Over Kitchen Sink Light Fixture | C8: 0 | D8: 0 | E8: =+C8*D8 -> 0
A9: Hall Light Fixture | C9: 0 | D9: 0 | E9: =+C9*D9 -> 0
C10: 0 | D10: 0 | E10: =+C10*D10 -> 0
C11: 0 | D11: 0 | E11: =+C11*D11 -> 0
A12: Hall Bath Light Fixture | C12: 0 | D12: 0 | E12: =+C12*D12 -> 0
A13: Master Bath Light Fixture | C13: 0 | D13: 0 | E13: =+C13*D13 -> 0
A14: 1/2 Bath Light Fixture | C14: 0 | D14: 0 | E14: =+C14*D14 -> 0
A15: Bedroom Light Fixture | C15: 0 | D15: 0 | E15: =+C15*D15 -> 0
C16: 0 | D16: 0 | E16: =+C16*D16 -> 0
A17: Laundry Light Fixture | C17: 0 | D17: 0 | E17: =+C17*D17 -> 0
A18: Closet Light Fixture | C18: 0 | D18: 0 | E18: =+C18*D18 -> 0
C19: 0 | D19: 0 | E19: =+C19*D19 -> 0
A20: Exterior Light Fixture | C20: 0 | D20: 0 | E20: =+C20*D20 -> 0
A21: Exterior Motion Light Fixture | C21: 0 | D21: 0 | E21: =+C21*D21 -> 0
C22: 0 | D22: 0 | E22: =+C22*D22 -> 0
A23: Bulbs | C23: 0 | D23: 0 | E23: =+C23*D23 -> 0
C24: 0 | D24: 0 | E24: =+C24*D24 -> 0
C25: 0 | D25: 0 | E25: =+C25*D25 -> 0
A26: Kitchen Sink Faucet | C26: 0 | D26: 0 | E26: =+C26*D26 -> 0
A27: Bathroom Sink Faucet | C27: 0 | D27: 0 | E27: =+C27*D27 -> 0
A28: Toilet | C28: 0 | D28: 0 | E28: =+C28*D28 -> 0
A29: Shower Head | C29: 0 | D29: 0 | E29: =+C29*D29 -> 0
A30: Shower Handle | C30: 0 | D30: 0 | E30: =+C30*D30 -> 0
A31: Tub Faucet | C31: 0 | D31: 0 | E31: =+C31*D31 -> 0
A32: Shower Kit | C32: 0 | D32: 0 | E32: =+C32*D32 -> 0
A33: Tub | C33: 0 | D33: 0 | E33: =+C33*D33 -> 0
A34: Washing Machine Outlet | C34: 0 | D34: 0 | E34: =+C34*D34 -> 0
A35: Dryer Vent | C35: 0 | D35: 0 | E35: =+C35*D35 -> 0
A36: Kitchen Disposal | C36: 0 | D36: 0 | E36: =+C36*D36 -> 0
C37: 0 | D37: 0 | E37: =+C37*D37 -> 0
A38: Hall Bath Vanity | C38: 0 | D38: 0 | E38: =+C38*D38 -> 0
A39: 1/2 Bath Vanity | C39: 0 | D39: 0 | E39: =+C39*D39 -> 0
A40: Master Bath Vanity | C40: 0 | D40: 0 | E40: =+C40*D40 -> 0
A41: Bath Sink Top | C41: 0 | D41: 0 | E41: =+C41*D41 -> 0
C42: 0 | D42: 0 | E42: =+C42*D42 -> 0
C43: 0 | D43: 0 | E43: =+C43*D43 -> 0
C44: 0 | D44: 0 | E44: =+C44*D44 -> 0
C45: 0 | D45: 0 | E45: =+C45*D45 -> 0
C46: 0 | D46: 0 | E46: =+C46*D46 -> 0
C47: 0 | D47: 0 | E47: =+C47*D47 -> 0
C48: 0 | D48: 0 | E48: =+C48*D48 -> 0
C49: 0 | D49: 0 | E49: =+C49*D49 -> 0
C50: 0 | D50: 0 | E50: =+C50*D50 -> 0
C51: 0 | D51: 0 | E51: =+C51*D51 -> 0
C52: 0 | D52: 0 | E52: =+C52*D52 -> 0
C53: 0 | D53: 0 | E53: =+C53*D53 -> 0
... C58: 0 | D58: 0 | E58: =+C58*D58 -> 0
A59: Hall Bath Mirror | C59: 0 | D59: 0 | E59: =+C59*D59 -> 0
C60: 0 | D60: 0 | E60: =+C60*D60 -> 0
C61: 0 | D61: 0 | E61: =+C61*D61 -> 0
F62: =+SUM(E3:E61) -> 0

Sheet Demo & Trash Haul
A1: Vender | B1: Date | C1: Per Event | D1: Iterations | E1: Charge | F1: Sub Total
F2: 0
A3: Meridian | C3: 15 Yrd Delivery | D3: 0 | E3: 50 | F3: =+D3*E3 -> 0
A4: Meridian | C4: 15 yard Haul swap | D4: 0 | E4: 150 | F4: =+D4*E4 -> 0
A5: Meridian | C5: C&D Disp | D5: 0 | E5: 104 | F5: =+D5*E5 -> 0
A6: Meridian | C6: Fuel Surcharge | D6: 0 | E6: =+(12.13+31.46+41.63)/3 -> 28.406667 | F6: =+D6*E6 -> 0
A7: Meridian | C7: Dest Fee | D7: 0 | E7: 6.35 | F7: =+D7*E7 -> 0
A8: Meridian | C8: Admin Fee | D8: 0 | E8: 2.5 | F8: =+D8*E8 -> 0
A9: Meridian | C9: Environmental Fee | D9: 0 | E9: =(8.5+10+17.34)/3 -> 11.946667 | F9: =+D9*E9 -> 0
A10: Meridian | B10: 44620 | C10: Inv 1 | D10: 0 | E10: 73.13 | F10: =+D10*E10 -> 0
A11: Meridian | B11: 44651 | C11: inv 2 | D11: 0 | E11: 346.78 | F11: =+D11*E11 -> 0
A12: Meridian | B12: 44666 | D12: 0 | E12: 599.75 | F12: =+D12*E12 -> 0
A13: Meridian | D13: 0 | E13: 1716 | F13: =+D13*E13 -> 0
A14: Clean Out Faison | D14: 0 | E14: 0 | F14: 0
G17: =SUM(F2:F16) -> 0

Sheet Appliances
A1: Appliances
A3: Description | B3: ITEM | C3: Quanity | D3: Cost/Unit | E3: Sub-Total | F3: Total
A4: HD Microwave White | B4: 977057 | C4: 0 | D4: 149 | E4: =+C4*D4 -> 0
A5: FB Marketplace Ref | C5: 0 | D5: 400 | E5: =+C5*D5 -> 0
A6: HD Dishwasher | B6: 1002425336 | C6: 0 | D6: 348 | E6: =+C6*D6 -> 0
D8: Sub-total for Lowes | F8: =+SUM(E4:E7) -> 0
A9: Dishwasher Hose | C9: 0 | D9: 31.98 | E9: 0 | F9: 0
A11: Dishwasher Hose | B11: 1630551 | C11: 0 | D11: 32.98 | E11: =+C11*D11 -> 0
A12: Lowes Range | B12: 3648606 | C12: 0 | D12: 560.31 | E12: =+C12*D12 -> 0
A13: Lowes Dishwasher | B13: 1654366 | C13: 0 | D13: 374.29 | E13: 0
A14: Lowes Range cord | B14: 118694 | C14: 0 | D14: 39.28 | E14: 0
A15: Kitchen Sink | C15: 0 | D15: 189 | E15: =+C15*D15 -> 0
A17: Kitchen faucet | C17: 0 | D17: 169 | E17: =+C17*D17 -> 0
A18: Lowes Microwave | B18: 1692925 | C18: 0 | D18: 170.39 | E18: =+C18*D18 -> 0
A19: Accumulating tax | C19: 0 | D19: 90.91 | E19: 0
A20: FB Ref | C20: 0 | D20: 400 | E20: =+C20*D20 -> 0
C21: Total for Appliances: | F21: 0

Sheet Plumbing Fixtures
A1: Plumbing
A3: Description | B3: ITEM | C3: Quanity | D3: Cost/Unit | E3: Sub-Total | F3: Total
E4: =+C4*D4 -> 0
A5: Lowes Kitchen Faucet | B5: 1255143 | C5: 0 | D5: 0 | E5: =+C5*D5 -> 0
A6: Lowes Bath Accessory Kit | B6: 2131173 | C6: 0 | D6: 0 | E6: =+C6*D6 -> 0
A7: Lowes Shower Head | B7: 1227792 | C7: 0 | D7: 0 | E7: =+C7*D7 -> 0
A8: Lowes Bath Faucets | B8: 1233228 | C8: 0 | D8: 0 | E8: =+C8*D8 -> 0
C9: 0 | D9: 0 | E9: =+C9*D9 -> 0
C10: 0 | E10: 0
A11: toilets | C11: 0 | D11: 0 | E11: =+C11*D11 -> 0
C12: 0 | D12: 0 | E12: =+C12*D12 -> 0
E13: =+C13*D13 -> 0
A14: Resurface tubs | C14: 0 | E14: =+C14*D14 -> 0
E15: =+C15*D15 -> 0
E16: =+C16*D16 -> 0
E17: =+C17*D17 -> 0
E18: =+C18*D18 -> 0
E19: =+C19*D19 -> 0
E20: =+C20*D20 -> 0
A21: Accumulating tax | E21: 0
E22: =+C22*D22 -> 0
F23: 0

Sheet Sheet1

Sheet Sheet2

Sheet Windows & Doors
A1: Doors & Windows
A3: Description | B3: ITEM | C3: Quanity | D3: Cost/Unit | E3: Sub-Total | F3: Total
A4: 36" Exterior (R) Out Swing | B4: 935605 | C4: 0 | D4: 209 | E4: =+C4*D4 -> 0
A5: 36" Exterior (L) Out Swing | B5: 935604 | C5: 0 | D5: 209 | E5: =+C5*D5 -> 0
A6: 36" Exterior (L) In Swing | B6: 935599 | C6: 0 | D6: 198.56 | E6: =+C6*D6 -> 0
A7: 32" Exterior (R) Out Swing | B7: 14005 | C7: 0 | D7: 179 | E7: =+C7*D7 -> 0
A8: 32" Exterior (L) Out Swing | B8: 14006 | C8: 0 | D8: 179 | E8: =+C8*D8 -> 0
A9: 32" Exterior (L) In Swing | B9: 935587 | C9: 0 | D9: 198.55 | E9: =+C9*D9 -> 0
A10: 30" Interior (R) | B10: 49504 | C10: 0 | D10: 103 | E10: =+C10*D10 -> 0
A11: 30" Interior (L) | B11: 49706 | C11: 0 | D11: 103 | E11: =+C11*D11 -> 0
A12: 28" Interior (R) | B12: 47025 | C12: 0 | D12: 99 | E12: =+C12*D12 -> 0
A13: 28" Interior (L) | B13: 47422 | C13: 0 | D13: 99 | E13: =+C13*D13 -> 0
A14: 24" Interior (R) | B14: 43359 | C14: 0 | D14: 95 | E14: =+C14*D14 -> 0
A15: 24" Interior (L) | B15: 44035 | C15: 0 | D15: 95 | E15: =+C15*D15 -> 0
... A17: Prehung French 60" | B17: 338797 | C17: 0 | D17: 196 | E17: =+C17*D17 -> 0
A18: Windows 32"x62" Project 640493559 | C18: 0 | D18: 284.56 | E18: =+C18*D18 -> 0
A19: Windows 59"x4446.562" Project | B19: 72904 | C19: 0 | D19: 429.62 | E19: =+C19*D19 -> 0
A20: Int Dummy knobs | B20: HD | C20: 0 | D20: 8.97 | E20: =+C20*D20 -> 0
A21: Int Dummy knobs | B21: L399125 | C21: 0 | D21: 9.48 | E21: =+C21*D21 -> 0
A22: Int Dummy knobs | B22: L399125 | C22: 0 | D22: 9.48 | E22: =+C22*D22 -> 0
A23: Bed/bath knob | B23: HD883624 | C23: 0 | D23: 13.47 | E23: =+C23*D23 -> 0
A24: Lowes Front door kw powerbolt | B24: 5386043 | C24: 1 | D24: 31.33 | E24: =+C24*D24 -> 31.33
A25: Lowes Front door kw door handle | B25: 1456509 | C25: 1 | D25: 189.05 | E25: =+C25*D25 -> 189.05
A26: HD Ext Deadbolt combo | C26: 0 | D26: 69.47 | E26: 69.47
A27: Laundry room Fr Doors | B27: HD154372 | C27: 0 | D27: 0 | E27: =+C27*D27 -> 0
A28: Closet door knob | B28: HD883767 | C28: 0 | D28: 12.97 | E28: =+C28*D28 -> 0
A29: Accumulating tax | E29: 0
F30: 235.81
F44: =+SUM(E39:E43) -> 0
G49: =+SUM(F30:F48) -> 235.81

Sheet Cabinets
A1: Cabinets
A3: Description | B3: ITEM | C3: Quanity | D3: Cost/Unit | E3: Sub-Total | F3: Total
B4: B21R | C4: 0 | D4: 154 | E4: =+C4*D4 -> 0
A5: 24" Arcadia Cab Master | B5: 795984 | C5: 0 | D5: 144 | E5: =+C5*D5 -> 0
A6: SCR36 | B6: SCR36 | C6: 0 | D6: 224 | E6: =+C6*D6 -> 0
A7: 36 sink base | B7: B24R | C7: 0 | D7: 152 | E7: =+C7*D7 -> 0
A8: Panel | B8: PePR335 | C8: 0 | D8: 50 | E8: =+C8*D8 -> 0
A9: Sink Base | B9: SB36B | C9: 0 | D9: 166 | E9: =+C9*D9 -> 0
A10: Base Cab | B10: B12R | C10: 0 | D10: 104 | E10: =+C10*D10 -> 0
A11: Wall Cab | B11: W1230R | C11: 0 | D11: 81.98 | E11: =+C11*D11 -> 0
A12: Wall Cab | B12: W2730B | C12: 0 | D12: 143 | E12: =+C12*D12 -> 0
A13: Wall Cab | B13: W2430B | C13: 0 | D13: 98.98 | E13: =+C13*D13 -> 0
A14: Diag Corner | B14: DC2430R | C14: 0 | D14: 165 | E14: =+C14*D14 -> 0
A15: Lowes Vanity Master | B15: 795984 | C15: 0 | D15: 144 | E15: =+C15*D15 -> 0
B16: W2130R | C16: 0 | D16: 107 | E16: =+C16*D16 -> 0
A17: Wall Cab | B17: W3014B | C17: 0 | D17: 112 | E17: =+C17*D17 -> 0
A18: Toe Kicks | B18: Toe Kicks | C18: 0 | D18: 40.96 | E18: =+C18*D18 -> 0
B19: Filler F331 | C19: 0 | D19: 18.28 | E19: =+C19*D19 -> 0
C20: 0 | D20: 0 | E20: =+C20*D20 -> 0
A21: Installation | C21: 0 | D21: 0 | E21: =+C21*D21 -> 0
A22: Buy from Lowes | C22: 0 | D22: 935.09 | E22: =+C22*D22 -> 0
F23: =+SUM(E4:E22) -> 0
A24: Cabinet Tops
A25: Description | B25: ITEM | C25: Quanity | D25: Cost/Unit | E25: Sub-Total | F25: Total
B26: surface 1 | C26: 0 | D26: 0 | E26: =+C26*D26 -> 0
B27: surface 2 | C27: 0 | D27: 0 | E27: =+C27*D27 -> 0
B28: surface 3 | C28: 0 | D28: 0 | E28: =+C28*D28 -> 0
A29: Estimate for Pilier | C29: 0 | D29: 0 | E29: 0
C30: 0 | D30: 0 | E30: =+C30*D30 -> 0
F32: 0
A34: Cabinet Hardware
A35: Description | B35: ITEM | C35: Quanity | D35: Cost/Unit | E35: Sub-Total | F35: Total
A36: Vanities - Sun HS Warehouse | C36: 0 | D36: 1100 | E36: =+C36*D36 -> 0
A37: Satin Nick cabinet knob | B37: 400390 | C37: 0 | D37: 2.05 | E37: =+C37*D37 -> 0
A38: Arched 3" Drawer pull | B38: 376787 | C38: 0 | D38: 4.98 | E38: =+C38*D38 -> 0
C39: 0 | D39: 0 | E39: =+C39*D39 -> 0
A40: Lowes 10 pk Matte Black Knob | B40: 2280072 | C40: 0 | D40: 18.97 | E40: =+C40*D40 -> 0
A41: HD Satin Nickel Knobs | B41: 1000707539 | C41: 0 | D41: 1.98 | E41: =+C41*D41 -> 0
F42: 0
G44: =+SUM(F23:F43) -> 0

Sheet Paint
A1: Paint
A2: Description | B2: Sq Ft | C2: Item # | D2: Qty | E2: Cost/Unit | F2: Sub-Total | G2: Total
A3: Interior Wall Paint | B3: =+Profit!K8 -> 1899
A4: SW | C4: 6509-48698 | D4: 0 | E4: 68.54 | F4: =+D4*E4 -> 0 | J4: =SUM(F4:F11)/28 -> 0
A5: SW | C5: 6510-78628 | D5: 0 | E5: 85.89 | F5: =+D5*E5 -> 0
A6: 5 gal Lowes Kilz | C6: 185342 | D6: 0 | E6: 147 | F6: =+D6*E6 -> 0
A7: SW | C7: 6508-68102 | D7: 0 | E7: 21.99 | F7: =+D7*E7 -> 0
A8: HD Behr Int/ext black paint | C8: 389832 | D8: 0 | E8: 39.98 | F8: =+D8*E8 -> 0
A9: HD White Int/ext white paint | C9: 985007 | D9: 0 | E9: 39.98 | F9: =+D9*E9 -> 0
A10: HD 5 gal Wh Flat Int ceiling | C10: 814917 | D10: 0 | E10: 60.98 | F10: =+D10*E10 -> 0
A11: Valspar | C11: L1028086 | D11: 0 | E11: 40 | F11: =+D11*E11 -> 0
A12: SW 5galover White | B12: 10 | C12: 6504-06788 | D12: 0 | E12: 50.24 | F12: =+D12*E12 -> 0
A13: Kitchen Cabinets | B13: 0
A14: SW 5galover White
A15: Exterior Wall Paint | B15: 0
A16: 5 Gal -Valspar Signature Signature flat | C16: Stone Eagle HGSW1456 | D16: 0 | E16: 93 | F16: =+D16*E16 -> 0
A17: Deck Stain | B17: 500 | F17: =+D17*E17 -> 0
A18: L Valspar Semi trans deck stain | C18: Lowes 1028086 | D18: 0 | E18: 47.98 | F18: =+D18*E18 -> 0
A19: L Valspar solid porch stain | C19: Lowes 1028091 | D19: 0 | E19: 48.98 | F19: =+D19*E19 -> 0
A20: Ongoing tax | D20: 0 | E20: 97.13 | F20: =+D20*E20 -> 0
F21: =+D20*E20 -> 0
D23: Lowes Sub Total for Paint | G23: =SUM(F4:F21) -> 0
A24: Painter | F24: 0 | G24: 0
A25: Painter | B25: =+$B$3 -> 1899 | C25: Inside | D25: Yes | E25: 2.04 | F25: 0
A26: Painter | B26: =+$B$3 -> 1899 | C26: Front Porch | D26: No | E26: 1 | F26: =IF(D26="yes",E26*B26,0) -> 0
A27: Painter | B27: =+$B$3 -> 1899 | C27: Back Porch | D27: No | E27: 1 | F27: =IF(D27="yes",E27*B27,0) -> 0
G28: =+SUM(F25:F27)+G23 -> 0

Sheet Flooring
A1: Floor
A2: Description | B2: Sq Ft | C2: Item # | D2: Qty | E2: Cost/Unit | F2: Sub-Total | G2: Total
B3: =+Profit!K8 -> 1899
A4: LVP Floor Installation | B4: =+B3 -> 1899 | C4: Inside | D4: no | E4: 6.5 | F4: =IF(D4="yes",E4*B4,0) -> 0
A5: LVP Floor Repair RediCarpet #2 | B5: =+B3 -> 1899 | D5: No | E5: 1 | F5: 571.8
A6: LVP Floor RediCarpet #1 | B6: =+B3 -> 1899 | D6: No | E6: 1 | F6: 4527
G7: =SUM(F4:F6) -> 5098.8

Sheet HVAC
A2: HVAC
A3: Description | B3: Item | C3: Quanity | D3: Cost/Unit | E3: Sub Total | F3: Total
A4: New unit | B4: True Service HVAC | C4: 0 | D4: 13062 | E4: =+C4*D4 -> 0
A5: A/C registers | B5: Lowes 66848 | C5: 0 | D5: 8.98 | E5: =+C5*D5 -> 0
A6: A/C registers | B6: HD 4x10 803492136468 | C6: 0 | D6: 7.98 | E6: =+C6*D6 -> 0
A7: A/C Return Vent | B7: Lowes 20x25 753897 | C7: 0 | D7: 44.93 | E7: =+C7*D7 -> 0
A8: AC Filter | B8: HD 20x25 31949488390 | C8: 0 | D8: 4.47 | E8: =+C8*D8 -> 0
A9: AC Filter | B9: Lowes 20x20 259930 | C9: 0 | D9: 4.97 | E9: =+C9*D9 -> 0
A10: Grill | B10: L65185 | C10: 0 | D10: 23 | E10: =+C10*D10 -> 0
E11: =+C11*D11 -> 0
A12: HVAC Service | C12: 0 | D12: 11504 | E12: =+C12*D12 -> 0
F13: =+SUM(E4:E12) -> 0

Sheet Electrical Fixtures
A1: Electrical
A3: Description | B3: ITEM | C3: Quanity | D3: Cost/Unit | E3: Sub-Total | F3: Total
E4: =+C4*D4 -> 0
A5: Lowes Bedroom Ceiling Fans | B5: 2599776 | C5: 0 | D5: 124.98 | E5: =+C5*D5 -> 0
A6: Lowes Liv Rm Ceiling Fan | B6: 807421 | C6: 0 | D6: 112.48 | E6: =+C6*D6 -> 0
A7: Lowes 4light bath vanity | B7: 321702 | C7: 0 | D7: 89.98 | E7: =+C7*D7 -> 0
A8: Lowes Flush Kitchen Light | B8: 649829 | C8: 0 | D8: 129.98 | E8: =+C8*D8 -> 0
A9: Lowes Pendant Dining Light | B9: 2296055 | C9: 0 | D9: 179.98 | E9: =+C9*D9 -> 0
A10: Lowes Ext Motion Lights | B10: 482287 | C10: 0 | D10: 62.98 | E10: =+C10*D10 -> 0
A11: Lowes 2' Strip Light Mast Closet | B11: 2535475 | C11: 0 | D11: 24.98 | E11: =+C11*D11 -> 0
A12: Floor registers | B12: HD1002265221 | C12: 0 | D12: 10.9 | E12: =+C12*D12 -> 0
A13: LED Bulbs | B13: HD1006211602 | C13: 0 | D13: 14.97 | E13: =+C13*D13 -> 0
A14: Outdoor flood light fixture | B14: HD233840 | C14: 0 | D14: 19.97 | E14: =+C14*D14 -> 0
A15: Hall Light | B15: HD385544 | C15: 0 | D15: 17.97 | E15: =+C15*D15 -> 0
A16: Flood Light Bulbs | B16: HD1006248217 | C16: 0 | D16: 16.98 | E16: =+C16*D16 -> 0
A17: Wall protectors | B17: HD316307 | C17: 0 | D17: 3.27 | E17: =+C17*D17 -> 0
E18: =+C18*D18 -> 0
E19: =+C19*D19 -> 0
B20: Misc | C20: 0 | D20: 700 | E20: =+C20*D20 -> 0
E21: =+C21*D21 -> 0
E22: =+C22*D22 -> 0
F23: =SUM(E4:E22) -> 0

Sheet Landscape
A1: Landscape
A2: Item | B2: Cost/sf | C2: Square Feet | D2: Quanity | E2: cost/unit | F2: SubTotal | G2: Total
A4: Liesure Time Zoysia-pallet | B4: 0.79 | C4: 500 | D4: 0 | E4: 60 | F4: =+C4*B4*D4 -> 0
A5: Liesure Time Zoysia-roll | B5: 1 | C5: =24*10 -> 240 | D5: 0 | E5: 60 | F5: =+C5*B5*D5 -> 0
A6: Delivery Fee | D6: 0 | E6: 150 | F6: =+D6*E6 -> 0
A7: Fence | D7: 0 | E7: 3000 | F7: =+D7*E7 -> 0
A8: organic humis | D8: 0 | E8: 165 | F8: =+D8*E8 -> 0
A9: mulch | D9: 0 | E9: 29 | F9: =+D9*E9 -> 0
A10: Mulch Labor: | D10: 0 | E10: 15 | F10: =+D10*E10 -> 0
A11: Straighten landscape stones | D11: 0 | E11: 1100 | F11: =+D11*E11 -> 0
A12: lay sod | E12: 0 | F12: =+D12*E12 -> 0
A13: Tree pruning | E13: 1000 | F13: =+D13*E13 -> 0
A14: Mow Grass | D14: 0 | E14: 60 | F14: =+D14*E14 -> 0
A15: remove debries | D15: 0 | E15: 800 | F15: =+D15*E15 -> 0
C17: =+SUM(C4:C16) -> 740 | F17: Total | G17: =+SUM(F4:F16) -> 0

Sheet Sheet5

Sheet Exterior
A1: Roof
A2: Item | B2: Qty | C2: Cost/item | D2: Total | E2: Hourly Rate: | G2: 20
A4: Termite Treatment | B4: 0 | C4: 800 | D4: =+B4*C4 -> 0
A5: Lowes Mailbox | B5: 1 | C5: 28.46 | D5: =+B5*C5 -> 28.46
A6: Mailbox post | B6: HD106052 | C6: 1 | D6: 32.98
A7: Crawl Plumbing | D7: =+B7*C7 -> 0
A8: Crawl Plumbing | D8: =+B8*C8 -> 0
A9: Siding Repair | C9: 1000 | D9: =+B9*C9 -> 0
A10: Drainage repair | D10: =+B10*C10 -> 0
A11: Drainage repair | D11: =+B11*C11 -> 0
A12: Deck rebuild | B12: 0 | C12: 5500 | D12: =+B12*C12 -> 0
A13: Masking tape | C13: 1604326 | D13: =+B13*C13 -> 0
A14: Drop cloths | C14: 228556 | D14: =+B14*C14 -> 0
A15: Power wash | B15: 0 | C15: 400 | D15: 0
D16: =SUM(D4:D15) -> 61.44

Sheet Sheet3

Sheet Sheet4
